{"type":"FeatureCollection","features":[{"type":"Feature","properties":{"codesPostaux":["01330"],"population":1635,"nom":"Amb\u00e9rieux-en-Dombes","code":"01005"},"geometry":{"type":"Point","coordinates":[4.9106016993464,46.00012039215686]}}]}