{"type":"FeatureCollection","features":[{"type":"Feature","properties":{"codesPostaux":["01500"],"population":2503,"nom":"Ambronay","code":"01007"},"geometry":{"type":"Point","coordinates":[5.366542283950616,46.00144716049382]}}]}