{"type":"FeatureCollection","features":[{"type":"Feature","properties":{"codesPostaux":["01380"],"population":4036,"nom":"B\u00e2g\u00e9-Dommartin","code":"01025"},"geometry":{"type":"Point","coordinates":[4.957910974999996,46.32233749999998]}}]}