{"type":"FeatureCollection","features":[{"type":"Feature","properties":{"codesPostaux":["01360"],"population":3304,"nom":"B\u00e9ligneux","code":"01032"},"geometry":{"type":"Point","coordinates":[5.132760642201835,45.86536266055046]}}]}