{"type":"FeatureCollection","features":[{"type":"Feature","properties":{"codesPostaux":["01290"],"population":260,"nom":"Bey","code":"01042"},"geometry":{"type":"Point","coordinates":[4.845371071428572,46.217906547619044]}}]}