{"type":"FeatureCollection","features":[{"type":"Feature","properties":{"codesPostaux":["01470"],"population":946,"nom":"Briord","code":"01064"},"geometry":{"type":"Point","coordinates":[5.490781666666665,45.778150092592604]}}]}