{"type":"FeatureCollection","features":[{"type":"Feature","properties":{"codesPostaux":["01110"],"population":550,"nom":"Br\u00e9nod","code":"01060"},"geometry":{"type":"Point","coordinates":[5.624564113924053,46.079860253164554]}}]}