{"type":"FeatureCollection","features":[{"type":"Feature","properties":{"codesPostaux":["01460"],"population":514,"nom":"Brion","code":"01063"},"geometry":{"type":"Point","coordinates":[5.545958870967742,46.16456741935483]}}]}