{"type":"FeatureCollection","features":[{"type":"Feature","properties":{"codesPostaux":["01450"],"population":181,"nom":"Challes-la-Montagne","code":"01077"},"geometry":{"type":"Point","coordinates":[5.460150392156865,46.12321990196078]}}]}