{"type":"FeatureCollection","features":[{"type":"Feature","properties":{"codesPostaux":["01480"],"population":1199,"nom":"Chaleins","code":"01075"},"geometry":{"type":"Point","coordinates":[4.799686198347108,46.034425041322315]}}]}