{"type":"FeatureCollection","features":[{"type":"Feature","properties":{"codesPostaux":["01250"],"population":3039,"nom":"Ceyz\u00e9riat","code":"01072"},"geometry":{"type":"Point","coordinates":[5.315112159999995,46.183578639999986]}}]}