{"type":"FeatureCollection","features":[{"type":"Feature","properties":{"codesPostaux":["01990"],"population":847,"nom":"Chaneins","code":"01083"},"geometry":{"type":"Point","coordinates":[4.855217821782178,46.08880326732671]}}]}