{"type":"FeatureCollection","features":[{"type":"Feature","properties":{"codesPostaux":["01800"],"population":915,"nom":"Charnoz-sur-Ain","code":"01088"},"geometry":{"type":"Point","coordinates":[5.219998169014084,45.87312380281691]}}]}