{"type":"FeatureCollection","features":[{"type":"Feature","properties":{"codesPostaux":["01320"],"population":1573,"nom":"Ch\u00e2tillon-la-Palud","code":"01092"},"geometry":{"type":"Point","coordinates":[5.238553819444444,45.97394805555553]}}]}