{"type":"FeatureCollection","features":[{"type":"Feature","properties":{"codesPostaux":["01190"],"population":944,"nom":"Chevroux","code":"01102"},"geometry":{"type":"Point","coordinates":[4.9651795857988175,46.38222313609466]}}]}