{"type":"FeatureCollection","features":[{"type":"Feature","properties":{"codesPostaux":["01560"],"population":454,"nom":"Curciat-Dongalon","code":"01139"},"geometry":{"type":"Point","coordinates":[5.166127457044675,46.48822357388314]}}]}