{"type":"FeatureCollection","features":[{"type":"Feature","properties":{"codesPostaux":["01350"],"population":380,"nom":"Cressin-Rochefort","code":"01133"},"geometry":{"type":"Point","coordinates":[5.758893552631578,45.78432592105263]}}]}