{"type":"FeatureCollection","features":[{"type":"Feature","properties":{"codesPostaux":["01270"],"population":477,"nom":"Domsure","code":"01147"},"geometry":{"type":"Point","coordinates":[5.293113216560508,46.42420143312104]}}]}