{"type":"FeatureCollection","features":[{"type":"Feature","properties":{"codesPostaux":["01120"],"population":4308,"nom":"Dagneux","code":"01142"},"geometry":{"type":"Point","coordinates":[5.0744668539325835,45.85737752808989]}}]}