{"type":"FeatureCollection","features":[{"type":"Feature","properties":{"codesPostaux":["01170"],"population":1904,"nom":"\u00c9chenevex","code":"01153"},"geometry":{"type":"Point","coordinates":[6.02268624161074,46.315665100671126]}}]}