{"type":"FeatureCollection","features":[{"type":"Feature","properties":{"codesPostaux":["01090"],"population":591,"nom":"Genouilleux","code":"01169"},"geometry":{"type":"Point","coordinates":[4.801254117647058,46.12253882352941]}}]}