{"type":"FeatureCollection","features":[{"type":"Feature","properties":{"codesPostaux":["01480"],"population":2087,"nom":"Frans","code":"01166"},"geometry":{"type":"Point","coordinates":[4.776539795918367,45.99210775510205]}}]}