{"type":"FeatureCollection","features":[{"type":"Feature","properties":{"codesPostaux":["01100"],"population":1176,"nom":"Groissiat","code":"01181"},"geometry":{"type":"Point","coordinates":[5.618226964285713,46.22358571428572]}}]}