{"type":"FeatureCollection","features":[{"type":"Feature","properties":{"codesPostaux":["01110"],"population":3919,"nom":"Hauteville-Lompnes","code":"01185"},"geometry":{"type":"Point","coordinates":[5.572192010869564,45.964660108695654]}}]}