{"type":"FeatureCollection","features":[{"type":"Feature","properties":{"codesPostaux":["01640"],"population":2172,"nom":"Jujurieux","code":"01199"},"geometry":{"type":"Point","coordinates":[5.41887612334802,46.04619127753303]}}]}