{"type":"FeatureCollection","features":[{"type":"Feature","properties":{"codesPostaux":["01300"],"population":221,"nom":"Izieu","code":"01193"},"geometry":{"type":"Point","coordinates":[5.639218240740738,45.653658888888884]}}]}