{"type":"FeatureCollection","features":[{"type":"Feature","properties":{"codesPostaux":["01290"],"population":1187,"nom":"Laiz","code":"01203"},"geometry":{"type":"Point","coordinates":[4.89947013245033,46.247156026490075]}}]}