{"type":"FeatureCollection","features":[{"type":"Feature","properties":{"codesPostaux":["01340"],"population":1134,"nom":"Malafretaz","code":"01229"},"geometry":{"type":"Point","coordinates":[5.140565294117648,46.326033823529414]}}]}