{"type":"FeatureCollection","features":[{"type":"Feature","properties":{"codesPostaux":["01300"],"population":646,"nom":"Massignieu-de-Rives","code":"01239"},"geometry":{"type":"Point","coordinates":[5.755664795918368,45.75421040816327]}}]}