{"type":"FeatureCollection","features":[{"type":"Feature","properties":{"codesPostaux":["01100"],"population":1584,"nom":"Martignat","code":"01237"},"geometry":{"type":"Point","coordinates":[5.614612808988764,46.20620078651687]}}]}