{"type":"FeatureCollection","features":[{"type":"Feature","properties":{"codesPostaux":["01170","01410"],"population":360,"nom":"Mijoux","code":"01247"},"geometry":{"type":"Point","coordinates":[6.001461911357345,46.3587768698061]}}]}