{"type":"FeatureCollection","features":[{"type":"Feature","properties":{"codesPostaux":["01300"],"population":250,"nom":"Murs-et-G\u00e9lignieux","code":"01268"},"geometry":{"type":"Point","coordinates":[5.654064216867471,45.64198289156627]}}]}