{"type":"FeatureCollection","features":[{"type":"Feature","properties":{"codesPostaux":["01390"],"population":669,"nom":"Monthieux","code":"01261"},"geometry":{"type":"Point","coordinates":[4.942311647058823,45.963843882352926]}}]}