{"type":"FeatureCollection","features":[{"type":"Feature","properties":{"codesPostaux":["01190"],"population":649,"nom":"Ozan","code":"01284"},"geometry":{"type":"Point","coordinates":[4.914415116279069,46.38681127906978]}}]}