{"type":"FeatureCollection","features":[{"type":"Feature","properties":{"codesPostaux":["01510"],"population":154,"nom":"Ordonnaz","code":"01280"},"geometry":{"type":"Point","coordinates":[5.540286400000001,45.83268056000002]}}]}