{"type":"FeatureCollection","features":[{"type":"Feature","properties":{"codesPostaux":["01430"],"population":256,"nom":"Outriaz","code":"01282"},"geometry":{"type":"Point","coordinates":[5.552251868131866,46.06756769230772]}}]}