{"type":"FeatureCollection","features":[{"type":"Feature","properties":{"codesPostaux":["01990"],"population":471,"nom":"Relevant","code":"01319"},"geometry":{"type":"Point","coordinates":[4.941509710144929,46.08011028985504]}}]}