{"type":"FeatureCollection","features":[{"type":"Feature","properties":{"codesPostaux":["01250"],"population":912,"nom":"Revonnas","code":"01321"},"geometry":{"type":"Point","coordinates":[5.335669696969698,46.163379090909096]}}]}