{"type":"FeatureCollection","features":[{"type":"Feature","properties":{"codesPostaux":["01390"],"population":2926,"nom":"Saint-Andr\u00e9-de-Corcy","code":"01333"},"geometry":{"type":"Point","coordinates":[4.951116917293234,45.922975488721804]}}]}