{"type":"FeatureCollection","features":[{"type":"Feature","properties":{"codesPostaux":["01140"],"population":1501,"nom":"Saint-\u00c9tienne-sur-Chalaronne","code":"01351"},"geometry":{"type":"Point","coordinates":[4.873138909952606,46.14400454976301]}}]}