{"type":"FeatureCollection","features":[{"type":"Feature","properties":{"codesPostaux":["01640"],"population":1645,"nom":"Saint-Jean-le-Vieux","code":"01363"},"geometry":{"type":"Point","coordinates":[5.3838333333333335,46.031344444444436]}}]}