{"type":"FeatureCollection","features":[{"type":"Feature","properties":{"codesPostaux":["01290"],"population":1076,"nom":"Saint-Jean-sur-Veyle","code":"01365"},"geometry":{"type":"Point","coordinates":[4.926397625000003,46.265496750000004]}}]}