{"type":"FeatureCollection","features":[{"type":"Feature","properties":{"codesPostaux":["01240"],"population":1475,"nom":"Saint-Paul-de-Varax","code":"01383"},"geometry":{"type":"Point","coordinates":[5.132343148936166,46.094532553191456]}}]}