{"type":"FeatureCollection","features":[{"type":"Feature","properties":{"codesPostaux":["01270"],"population":290,"nom":"Salavre","code":"01391"},"geometry":{"type":"Point","coordinates":[5.344440955414015,46.36444401273886]}}]}