{"type":"FeatureCollection","features":[{"type":"Feature","properties":{"codesPostaux":["01420"],"population":965,"nom":"Seyssel","code":"01407"},"geometry":{"type":"Point","coordinates":[5.828030909090909,45.95024666666666]}}]}