{"type":"FeatureCollection","features":[{"type":"Feature","properties":{"codesPostaux":["01190"],"population":675,"nom":"Sermoyer","code":"01402"},"geometry":{"type":"Point","coordinates":[4.973560492610836,46.498769901477836]}}]}