{"type":"FeatureCollection","features":[{"type":"Feature","properties":{"codesPostaux":["01600"],"population":6708,"nom":"Tr\u00e9voux","code":"01427"},"geometry":{"type":"Point","coordinates":[4.764860757575759,45.94415424242423]}}]}