{"type":"FeatureCollection","features":[{"type":"Feature","properties":{"codesPostaux":["01250"],"population":1353,"nom":"Tossiat","code":"01422"},"geometry":{"type":"Point","coordinates":[5.301319146341464,46.137566707317056]}}]}