{"type":"FeatureCollection","features":[{"type":"Feature","properties":{"codesPostaux":["01170"],"population":527,"nom":"Vesancy","code":"01436"},"geometry":{"type":"Point","coordinates":[6.0793977647058846,46.365838588235306]}}]}