{"type":"FeatureCollection","features":[{"type":"Feature","properties":{"codesPostaux":["01150"],"population":1160,"nom":"Villebois","code":"01444"},"geometry":{"type":"Point","coordinates":[5.446613355704698,45.85457302013421]}}]}