{"type":"FeatureCollection","features":[{"type":"Feature","properties":{"codesPostaux":["01510"],"population":1108,"nom":"Virieu-le-Grand","code":"01452"},"geometry":{"type":"Point","coordinates":[5.6524917187499994,45.84868500000001]}}]}