{"type":"FeatureCollection","features":[{"type":"Feature","properties":{"codesPostaux":["02370"],"population":304,"nom":"Aizy-Jouy","code":"02008"},"geometry":{"type":"Point","coordinates":[3.506421020408163,49.43920061224492]}}]}