{"type":"FeatureCollection","features":[{"type":"Feature","properties":{"codesPostaux":["02240"],"population":529,"nom":"Alaincourt","code":"02009"},"geometry":{"type":"Point","coordinates":[3.372965416666667,49.76562591666667]}}]}