{"type":"FeatureCollection","features":[{"type":"Feature","properties":{"codesPostaux":["02800"],"population":208,"nom":"Andelain","code":"02016"},"geometry":{"type":"Point","coordinates":[3.3680562711864397,49.64126796610169]}}]}