{"type":"FeatureCollection","features":[{"type":"Feature","properties":{"codesPostaux":["02190"],"population":414,"nom":"Amifontaine","code":"02013"},"geometry":{"type":"Point","coordinates":[3.9228883582089558,49.49602552238805]}}]}