{"type":"FeatureCollection","features":[{"type":"Feature","properties":{"codesPostaux":["02420"],"population":296,"nom":"Aubencheul-aux-Bois","code":"02030"},"geometry":{"type":"Point","coordinates":[3.2620054761904758,50.02423071428573]}}]}