{"type":"FeatureCollection","features":[{"type":"Feature","properties":{"codesPostaux":["02250"],"population":177,"nom":"Autremencourt","code":"02039"},"geometry":{"type":"Point","coordinates":[3.7865328865979384,49.70323288659794]}}]}