{"type":"FeatureCollection","features":[{"type":"Feature","properties":{"codesPostaux":["02140"],"population":29,"nom":"Bancigny","code":"02044"},"geometry":{"type":"Point","coordinates":[4.035947857142857,49.79854214285714]}}]}