{"type":"FeatureCollection","features":[{"type":"Feature","properties":{"codesPostaux":["02700"],"population":739,"nom":"Barisis-aux-Bois","code":"02049"},"geometry":{"type":"Point","coordinates":[3.3370458100558658,49.58161558659219]}}]}