{"type":"FeatureCollection","features":[{"type":"Feature","properties":{"codesPostaux":["02270"],"population":117,"nom":"Barenton-sur-Serre","code":"02048"},"geometry":{"type":"Point","coordinates":[3.6873561386138602,49.67057089108911]}}]}