{"type":"FeatureCollection","features":[{"type":"Feature","properties":{"codesPostaux":["02110"],"population":1469,"nom":"Beaurevoir","code":"02057"},"geometry":{"type":"Point","coordinates":[3.3237245522388053,49.991178358208934]}}]}