{"type":"FeatureCollection","features":[{"type":"Feature","properties":{"codesPostaux":["02440"],"population":212,"nom":"Benay","code":"02066"},"geometry":{"type":"Point","coordinates":[3.3115779268292687,49.75333756097561]}}]}