{"type":"FeatureCollection","features":[{"type":"Feature","properties":{"codesPostaux":["02400"],"population":141,"nom":"Belleau","code":"02062"},"geometry":{"type":"Point","coordinates":[3.297616000000001,49.08286385714285]}}]}