{"type":"FeatureCollection","features":[{"type":"Feature","properties":{"codesPostaux":["02420"],"population":382,"nom":"Bellenglise","code":"02063"},"geometry":{"type":"Point","coordinates":[3.243523623188405,49.92569565217391]}}]}