{"type":"FeatureCollection","features":[{"type":"Feature","properties":{"codesPostaux":["02200"],"population":401,"nom":"Berzy-le-Sec","code":"02077"},"geometry":{"type":"Point","coordinates":[3.305938910891088,49.32232673267326]}}]}