{"type":"FeatureCollection","features":[{"type":"Feature","properties":{"codesPostaux":["02400"],"population":1012,"nom":"B\u00e9zu-Saint-Germain","code":"02085"},"geometry":{"type":"Point","coordinates":[3.407351294117648,49.106202941176484]}}]}