{"type":"FeatureCollection","features":[{"type":"Feature","properties":{"codesPostaux":["02400"],"population":383,"nom":"Bonneil","code":"02098"},"geometry":{"type":"Point","coordinates":[3.3460331034482764,49.00941862068966]}}]}