{"type":"FeatureCollection","features":[{"type":"Feature","properties":{"codesPostaux":["02350"],"population":259,"nom":"Boncourt","code":"02097"},"geometry":{"type":"Point","coordinates":[3.9543927272727264,49.620752272727266]}}]}