{"type":"FeatureCollection","features":[{"type":"Feature","properties":{"codesPostaux":["02220"],"population":2250,"nom":"Braine","code":"02110"},"geometry":{"type":"Point","coordinates":[3.5334331159420276,49.34614311594201]}}]}