{"type":"FeatureCollection","features":[{"type":"Feature","properties":{"codesPostaux":["02870"],"population":57,"nom":"Brie","code":"02122"},"geometry":{"type":"Point","coordinates":[3.4744362903225787,49.598835161290324]}}]}