{"type":"FeatureCollection","features":[{"type":"Feature","properties":{"codesPostaux":["02810"],"population":125,"nom":"Bussiares","code":"02137"},"geometry":{"type":"Point","coordinates":[3.2509442105263164,49.08462565789473]}}]}