{"type":"FeatureCollection","features":[{"type":"Feature","properties":{"codesPostaux":["02420"],"population":197,"nom":"Le Catelet","code":"02143"},"geometry":{"type":"Point","coordinates":[3.243098749999999,50.000943125000006]}}]}