{"type":"FeatureCollection","features":[{"type":"Feature","properties":{"codesPostaux":["02000"],"population":179,"nom":"Chaillevois","code":"02155"},"geometry":{"type":"Point","coordinates":[3.5243339583333335,49.50798520833334]}}]}