{"type":"FeatureCollection","features":[{"type":"Feature","properties":{"codesPostaux":["02000"],"population":768,"nom":"Chambry","code":"02157"},"geometry":{"type":"Point","coordinates":[3.665420985915493,49.59768000000002]}}]}