{"type":"FeatureCollection","features":[{"type":"Feature","properties":{"codesPostaux":["02670"],"population":286,"nom":"Champs","code":"02159"},"geometry":{"type":"Point","coordinates":[3.2595117910447766,49.53978111940301]}}]}