{"type":"FeatureCollection","features":[{"type":"Feature","properties":{"codesPostaux":["02370"],"population":200,"nom":"Chavonne","code":"02176"},"geometry":{"type":"Point","coordinates":[3.562726346153845,49.40843057692307]}}]}