{"type":"FeatureCollection","features":[{"type":"Feature","properties":{"codesPostaux":["02240"],"population":125,"nom":"Ch\u00e2tillon-sur-Oise","code":"02170"},"geometry":{"type":"Point","coordinates":[3.4189377049180325,49.79259508196723]}}]}