{"type":"FeatureCollection","features":[{"type":"Feature","properties":{"codesPostaux":["02000"],"population":196,"nom":"Chevregny","code":"02183"},"geometry":{"type":"Point","coordinates":[3.5953067346938767,49.46714755102042]}}]}