{"type":"FeatureCollection","features":[{"type":"Feature","properties":{"codesPostaux":["02350"],"population":381,"nom":"Chivres-en-Laonnois","code":"02189"},"geometry":{"type":"Point","coordinates":[3.8525981481481475,49.62427851851852]}}]}