{"type":"FeatureCollection","features":[{"type":"Feature","properties":{"codesPostaux":["02260"],"population":558,"nom":"Clairfontaine","code":"02197"},"geometry":{"type":"Point","coordinates":[3.979876470588235,49.96407226890757]}}]}