{"type":"FeatureCollection","features":[{"type":"Feature","properties":{"codesPostaux":["02300"],"population":208,"nom":"Commenchon","code":"02207"},"geometry":{"type":"Point","coordinates":[3.151871607142858,49.64142142857143]}}]}