{"type":"FeatureCollection","features":[{"type":"Feature","properties":{"codesPostaux":["02210"],"population":1316,"nom":"Coincy","code":"02203"},"geometry":{"type":"Point","coordinates":[3.4461209782608715,49.155148695652166]}}]}