{"type":"FeatureCollection","features":[{"type":"Feature","properties":{"codesPostaux":["02680"],"population":64,"nom":"Contescourt","code":"02214"},"geometry":{"type":"Point","coordinates":[3.233424691358024,49.79024851851854]}}]}