{"type":"FeatureCollection","features":[{"type":"Feature","properties":{"codesPostaux":["02160"],"population":77,"nom":"Craonne","code":"02234"},"geometry":{"type":"Point","coordinates":[3.7922677966101705,49.44514796610167]}}]}