{"type":"FeatureCollection","features":[{"type":"Feature","properties":{"codesPostaux":["02270"],"population":1485,"nom":"Cr\u00e9cy-sur-Serre","code":"02237"},"geometry":{"type":"Point","coordinates":[3.614880992907801,49.69579992907805]}}]}