{"type":"FeatureCollection","features":[{"type":"Feature","properties":{"codesPostaux":["02880"],"population":2829,"nom":"Crouy","code":"02243"},"geometry":{"type":"Point","coordinates":[3.3650149999999996,49.40767722222223]}}]}