{"type":"FeatureCollection","features":[{"type":"Feature","properties":{"codesPostaux":["02600"],"population":125,"nom":"Cutry","code":"02254"},"geometry":{"type":"Point","coordinates":[3.1835792682926827,49.34602146341464]}}]}