{"type":"FeatureCollection","features":[{"type":"Feature","properties":{"codesPostaux":["02310"],"population":665,"nom":"Domptin","code":"02268"},"geometry":{"type":"Point","coordinates":[3.2703782978723406,49.014309361702125]}}]}