{"type":"FeatureCollection","features":[{"type":"Feature","properties":{"codesPostaux":["02500"],"population":41,"nom":"\u00c9parcy","code":"02278"},"geometry":{"type":"Point","coordinates":[4.069431874999999,49.88109276785716]}}]}