{"type":"FeatureCollection","features":[{"type":"Feature","properties":{"codesPostaux":["02100"],"population":680,"nom":"Fayet","code":"02303"},"geometry":{"type":"Point","coordinates":[3.254059506172839,49.871716913580244]}}]}