{"type":"FeatureCollection","features":[{"type":"Feature","properties":{"codesPostaux":["02110"],"population":127,"nom":"Fontaine-Uterte","code":"02323"},"geometry":{"type":"Point","coordinates":[3.3673485542168677,49.92730012048192]}}]}