{"type":"FeatureCollection","features":[{"type":"Feature","properties":{"codesPostaux":["02110"],"population":405,"nom":"Fontaine-Notre-Dame","code":"02322"},"geometry":{"type":"Point","coordinates":[3.4236256521739143,49.881520579710134]}}]}