{"type":"FeatureCollection","features":[{"type":"Feature","properties":{"codesPostaux":["02130"],"population":264,"nom":"Fresnes-en-Tardenois","code":"02332"},"geometry":{"type":"Point","coordinates":[3.552036438356164,49.14622547945204]}}]}