{"type":"FeatureCollection","features":[{"type":"Feature","properties":{"codesPostaux":["02700"],"population":1006,"nom":"Fri\u00e8res-Faillou\u00ebl","code":"02336"},"geometry":{"type":"Point","coordinates":[3.2385185416666675,49.682386770833325]}}]}