{"type":"FeatureCollection","features":[{"type":"Feature","properties":{"codesPostaux":["02400"],"population":463,"nom":"Gland","code":"02347"},"geometry":{"type":"Point","coordinates":[3.4618912500000003,49.057125000000006]}}]}