{"type":"FeatureCollection","features":[{"type":"Feature","properties":{"codesPostaux":["02820"],"population":52,"nom":"Goudelancourt-l\u00e8s-Berrieux","code":"02349"},"geometry":{"type":"Point","coordinates":[3.8499885507246367,49.49740855072463]}}]}