{"type":"FeatureCollection","features":[{"type":"Feature","properties":{"codesPostaux":["02440"],"population":45,"nom":"Gibercourt","code":"02345"},"geometry":{"type":"Point","coordinates":[3.2877046153846154,49.73570205128205]}}]}