{"type":"FeatureCollection","features":[{"type":"Feature","properties":{"codesPostaux":["02120"],"population":166,"nom":"Hauteville","code":"02376"},"geometry":{"type":"Point","coordinates":[3.5265734375,49.88648734374999]}}]}