{"type":"FeatureCollection","features":[{"type":"Feature","properties":{"codesPostaux":["02120"],"population":239,"nom":"Le H\u00e9rie-la-Vi\u00e9ville","code":"02379"},"geometry":{"type":"Point","coordinates":[3.654063737373737,49.82329202020201]}}]}