{"type":"FeatureCollection","features":[{"type":"Feature","properties":{"codesPostaux":["02810"],"population":166,"nom":"Hautevesnes","code":"02375"},"geometry":{"type":"Point","coordinates":[3.234529864864865,49.10442891891891]}}]}