{"type":"FeatureCollection","features":[{"type":"Feature","properties":{"codesPostaux":["02500"],"population":152,"nom":"La H\u00e9rie","code":"02378"},"geometry":{"type":"Point","coordinates":[4.0429971568627465,49.881679411764715]}}]}