{"type":"FeatureCollection","features":[{"type":"Feature","properties":{"codesPostaux":["02140"],"population":151,"nom":"Haution","code":"02377"},"geometry":{"type":"Point","coordinates":[3.829168333333334,49.874375740740746]}}]}