{"type":"FeatureCollection","features":[{"type":"Feature","properties":{"codesPostaux":["02760"],"population":1404,"nom":"Holnon","code":"02382"},"geometry":{"type":"Point","coordinates":[3.1962018181818186,49.86224303030304]}}]}