{"type":"FeatureCollection","features":[{"type":"Feature","properties":{"codesPostaux":["02140"],"population":50,"nom":"Houry","code":"02384"},"geometry":{"type":"Point","coordinates":[3.8525325454545447,49.783657818181815]}}]}