{"type":"FeatureCollection","features":[{"type":"Feature","properties":{"codesPostaux":["02190"],"population":570,"nom":"Juvincourt-et-Damary","code":"02399"},"geometry":{"type":"Point","coordinates":[3.8958263636363615,49.43746318181818]}}]}