{"type":"FeatureCollection","features":[{"type":"Feature","properties":{"codesPostaux":["02000"],"population":25219,"nom":"Laon","code":"02408"},"geometry":{"type":"Point","coordinates":[3.618104414893616,49.57501319148936]}}]}