{"type":"FeatureCollection","features":[{"type":"Feature","properties":{"codesPostaux":["02700"],"population":422,"nom":"Liez","code":"02431"},"geometry":{"type":"Point","coordinates":[3.2965531034482756,49.69364879310345]}}]}