{"type":"FeatureCollection","features":[{"type":"Feature","properties":{"codesPostaux":["02320"],"population":268,"nom":"Lizy","code":"02434"},"geometry":{"type":"Point","coordinates":[3.476514571428571,49.511011047619036]}}]}