{"type":"FeatureCollection","features":[{"type":"Feature","properties":{"codesPostaux":["02220"],"population":186,"nom":"Lim\u00e9","code":"02432"},"geometry":{"type":"Point","coordinates":[3.55849940740741,49.32603777777779]}}]}