{"type":"FeatureCollection","features":[{"type":"Feature","properties":{"codesPostaux":["02500"],"population":78,"nom":"Logny-l\u00e8s-Aubenton","code":"02435"},"geometry":{"type":"Point","coordinates":[4.2222849090909085,49.831616000000004]}}]}