{"type":"FeatureCollection","features":[{"type":"Feature","properties":{"codesPostaux":["02130"],"population":89,"nom":"Loupeigne","code":"02442"},"geometry":{"type":"Point","coordinates":[3.5291049999999986,49.24628600000001]}}]}