{"type":"FeatureCollection","features":[{"type":"Feature","properties":{"codesPostaux":["02200"],"population":964,"nom":"Mercin-et-Vaux","code":"02477"},"geometry":{"type":"Point","coordinates":[3.2725926470588225,49.367353235294125]}}]}