{"type":"FeatureCollection","features":[{"type":"Feature","properties":{"codesPostaux":["02820"],"population":443,"nom":"Mauregny-en-Haye","code":"02472"},"geometry":{"type":"Point","coordinates":[3.797819181818183,49.53767263636363]}}]}