{"type":"FeatureCollection","features":[{"type":"Feature","properties":{"codesPostaux":["02630"],"population":634,"nom":"Mennevret","code":"02476"},"geometry":{"type":"Point","coordinates":[3.5608696428571442,49.99108196428574]}}]}