{"type":"FeatureCollection","features":[{"type":"Feature","properties":{"codesPostaux":["02160"],"population":86,"nom":"Moulins","code":"02530"},"geometry":{"type":"Point","coordinates":[3.681233220338983,49.419940847457646]}}]}