{"type":"FeatureCollection","features":[{"type":"Feature","properties":{"codesPostaux":["02470"],"population":2152,"nom":"Neuilly-Saint-Front","code":"02543"},"geometry":{"type":"Point","coordinates":[3.257638657718119,49.16726879194632]}}]}