{"type":"FeatureCollection","features":[{"type":"Feature","properties":{"codesPostaux":["02390"],"population":188,"nom":"Neuvillette","code":"02552"},"geometry":{"type":"Point","coordinates":[3.475252717391306,49.85263380434782]}}]}