{"type":"FeatureCollection","features":[{"type":"Feature","properties":{"codesPostaux":["02400"],"population":1011,"nom":"Nogentel","code":"02554"},"geometry":{"type":"Point","coordinates":[3.4066392000000003,49.01025320000001]}}]}