{"type":"FeatureCollection","features":[{"type":"Feature","properties":{"codesPostaux":["02120"],"population":171,"nom":"Noyales","code":"02563"},"geometry":{"type":"Point","coordinates":[3.5406055172413793,49.90400525862069]}}]}