{"type":"FeatureCollection","features":[{"type":"Feature","properties":{"codesPostaux":["02290"],"population":308,"nom":"Osly-Courtil","code":"02576"},"geometry":{"type":"Point","coordinates":[3.2286749999999995,49.40367851351352]}}]}