{"type":"FeatureCollection","features":[{"type":"Feature","properties":{"codesPostaux":["02220"],"population":297,"nom":"Paars","code":"02581"},"geometry":{"type":"Point","coordinates":[3.602899787234043,49.331854893617034]}}]}