{"type":"FeatureCollection","features":[{"type":"Feature","properties":{"codesPostaux":["02160"],"population":71,"nom":"Pargnan","code":"02588"},"geometry":{"type":"Point","coordinates":[3.7053754545454556,49.39168480519479]}}]}