{"type":"FeatureCollection","features":[{"type":"Feature","properties":{"codesPostaux":["02860"],"population":22,"nom":"Ployart-et-Vaurseine","code":"02609"},"geometry":{"type":"Point","coordinates":[3.739095,49.494560689655174]}}]}