{"type":"FeatureCollection","features":[{"type":"Feature","properties":{"codesPostaux":["02110"],"population":735,"nom":"Pr\u00e9mont","code":"02618"},"geometry":{"type":"Point","coordinates":[3.3955263461538463,50.01244711538462]}}]}