{"type":"FeatureCollection","features":[{"type":"Feature","properties":{"codesPostaux":["02100"],"population":312,"nom":"Remaucourt","code":"02637"},"geometry":{"type":"Point","coordinates":[3.3502459047619033,49.89701257142856]}}]}