{"type":"FeatureCollection","features":[{"type":"Feature","properties":{"codesPostaux":["02850"],"population":226,"nom":"Reuilly-Sauvigny","code":"02645"},"geometry":{"type":"Point","coordinates":[3.5616779629629622,49.0527675925926]}}]}