{"type":"FeatureCollection","features":[{"type":"Feature","properties":{"codesPostaux":["02410"],"population":114,"nom":"Saint-Nicolas-aux-Bois","code":"02685"},"geometry":{"type":"Point","coordinates":[3.4344300000000003,49.60209514705879]}}]}