{"type":"FeatureCollection","features":[{"type":"Feature","properties":{"codesPostaux":["02600"],"population":97,"nom":"Soucy","code":"02729"},"geometry":{"type":"Point","coordinates":[3.1256081538461546,49.32406046153845]}}]}