{"type":"FeatureCollection","features":[{"type":"Feature","properties":{"codesPostaux":["02480"],"population":166,"nom":"Sommette-Eaucourt","code":"02726"},"geometry":{"type":"Point","coordinates":[3.115328452380953,49.72985345238095]}}]}