{"type":"FeatureCollection","features":[{"type":"Feature","properties":{"codesPostaux":["02600"],"population":259,"nom":"Taillefontaine","code":"02734"},"geometry":{"type":"Point","coordinates":[3.051363069306932,49.31407663366335]}}]}