{"type":"FeatureCollection","features":[{"type":"Feature","properties":{"codesPostaux":["02490"],"population":90,"nom":"Trefcon","code":"02747"},"geometry":{"type":"Point","coordinates":[3.089534778761063,49.861474955752236]}}]}