{"type":"FeatureCollection","features":[{"type":"Feature","properties":{"codesPostaux":["02370"],"population":2036,"nom":"Vailly-sur-Aisne","code":"02758"},"geometry":{"type":"Point","coordinates":[3.5212243750000005,49.408848749999976]}}]}