{"type":"FeatureCollection","features":[{"type":"Feature","properties":{"codesPostaux":["02640"],"population":284,"nom":"Tugny-et-Pont","code":"02752"},"geometry":{"type":"Point","coordinates":[3.1633606976744177,49.76682209302324]}}]}