{"type":"FeatureCollection","features":[{"type":"Feature","properties":{"codesPostaux":["02110"],"population":962,"nom":"Vaux-Andigny","code":"02769"},"geometry":{"type":"Point","coordinates":[3.520439082568806,50.0135196330275]}}]}