{"type":"FeatureCollection","features":[{"type":"Feature","properties":{"codesPostaux":["02420"],"population":541,"nom":"Vendhuile","code":"02776"},"geometry":{"type":"Point","coordinates":[3.208690614035086,50.01375394736839]}}]}