{"type":"FeatureCollection","features":[{"type":"Feature","properties":{"codesPostaux":["02200"],"population":779,"nom":"Vauxbuin","code":"02770"},"geometry":{"type":"Point","coordinates":[3.298608333333333,49.35947907407409]}}]}