{"type":"FeatureCollection","features":[{"type":"Feature","properties":{"codesPostaux":["02340"],"population":275,"nom":"Vigneux-Hocquet","code":"02801"},"geometry":{"type":"Point","coordinates":[3.9950954347826078,49.74006586956521]}}]}