{"type":"FeatureCollection","features":[{"type":"Feature","properties":{"codesPostaux":["02880"],"population":42,"nom":"Vuillery","code":"02829"},"geometry":{"type":"Point","coordinates":[3.385157931034483,49.428738620689664]}}]}