{"type":"FeatureCollection","features":[{"type":"Feature","properties":{"codesPostaux":["02300"],"population":1762,"nom":"Viry-Noureuil","code":"02820"},"geometry":{"type":"Point","coordinates":[3.2488389473684185,49.63435368421053]}}]}