{"type":"FeatureCollection","features":[{"type":"Feature","properties":{"codesPostaux":["03360"],"population":1021,"nom":"Ainay-le-Ch\u00e2teau","code":"03003"},"geometry":{"type":"Point","coordinates":[2.715751666666667,46.715618518518525]}}]}