{"type":"FeatureCollection","features":[{"type":"Feature","properties":{"codesPostaux":["03250"],"population":372,"nom":"Arronnes","code":"03008"},"geometry":{"type":"Point","coordinates":[3.571779392712549,46.05431959514171]}}]}