{"type":"FeatureCollection","features":[{"type":"Feature","properties":{"codesPostaux":["03230"],"population":1661,"nom":"Beaulon","code":"03019"},"geometry":{"type":"Point","coordinates":[3.669699528985506,46.58306887681157]}}]}