{"type":"FeatureCollection","features":[{"type":"Feature","properties":{"codesPostaux":["03130"],"population":256,"nom":"Bert","code":"03024"},"geometry":{"type":"Point","coordinates":[3.702158820960697,46.32880637554587]}}]}