{"type":"FeatureCollection","features":[{"type":"Feature","properties":{"codesPostaux":["03160"],"population":2559,"nom":"Bourbon-l'Archambault","code":"03036"},"geometry":{"type":"Point","coordinates":[3.0547965016501655,46.58075026402639]}}]}