{"type":"FeatureCollection","features":[{"type":"Feature","properties":{"codesPostaux":["03700"],"population":1426,"nom":"Brugheas","code":"03044"},"geometry":{"type":"Point","coordinates":[3.378142392156864,46.07661105882356]}}]}