{"type":"FeatureCollection","features":[{"type":"Feature","properties":{"codesPostaux":["03340"],"population":228,"nom":"Chapeau","code":"03054"},"geometry":{"type":"Point","coordinates":[3.513031972477061,46.49135082568808]}}]}