{"type":"FeatureCollection","features":[{"type":"Feature","properties":{"codesPostaux":["03140"],"population":1064,"nom":"Chantelle","code":"03053"},"geometry":{"type":"Point","coordinates":[3.1596003472222223,46.23986527777779]}}]}