{"type":"FeatureCollection","features":[{"type":"Feature","properties":{"codesPostaux":["03380"],"population":984,"nom":"La Chapelaude","code":"03055"},"geometry":{"type":"Point","coordinates":[2.4996024705882354,46.4301117647059]}}]}