{"type":"FeatureCollection","features":[{"type":"Feature","properties":{"codesPostaux":["03000"],"population":673,"nom":"Coulandon","code":"03085"},"geometry":{"type":"Point","coordinates":[3.2456910119047615,46.556799166666664]}}]}