{"type":"FeatureCollection","features":[{"type":"Feature","properties":{"codesPostaux":["03430"],"population":2146,"nom":"Cosne-d'Allier","code":"03084"},"geometry":{"type":"Point","coordinates":[2.822108097826087,46.486209184782595]}}]}