{"type":"FeatureCollection","features":[{"type":"Feature","properties":{"codesPostaux":["03300"],"population":13545,"nom":"Cusset","code":"03095"},"geometry":{"type":"Point","coordinates":[3.485866292517005,46.13369948979589]}}]}