{"type":"FeatureCollection","features":[{"type":"Feature","properties":{"codesPostaux":["03120"],"population":344,"nom":"Droiturier","code":"03105"},"geometry":{"type":"Point","coordinates":[3.7071690909090913,46.23130424242426]}}]}