{"type":"FeatureCollection","features":[{"type":"Feature","properties":{"codesPostaux":["03110"],"population":754,"nom":"Escurolles","code":"03109"},"geometry":{"type":"Point","coordinates":[3.2644886086956504,46.14782139130434]}}]}