{"type":"FeatureCollection","features":[{"type":"Feature","properties":{"codesPostaux":["03290"],"population":1464,"nom":"Diou","code":"03100"},"geometry":{"type":"Point","coordinates":[3.734012639593907,46.52263319796956]}}]}