{"type":"FeatureCollection","features":[{"type":"Feature","properties":{"codesPostaux":["03160"],"population":461,"nom":"Franchesse","code":"03117"},"geometry":{"type":"Point","coordinates":[3.026047054794518,46.64388770547944]}}]}