{"type":"FeatureCollection","features":[{"type":"Feature","properties":{"codesPostaux":["03100"],"population":1126,"nom":"Lavault-Sainte-Anne","code":"03140"},"geometry":{"type":"Point","coordinates":[2.597891747572816,46.30958417475726]}}]}