{"type":"FeatureCollection","features":[{"type":"Feature","properties":{"codesPostaux":["03130"],"population":162,"nom":"Loddes","code":"03147"},"geometry":{"type":"Point","coordinates":[3.759377451923079,46.29891168269232]}}]}