{"type":"FeatureCollection","features":[{"type":"Feature","properties":{"codesPostaux":["03350"],"population":248,"nom":"Louroux-Bourbonnais","code":"03150"},"geometry":{"type":"Point","coordinates":[2.8357892213114755,46.53286782786883]}}]}