{"type":"FeatureCollection","features":[{"type":"Feature","properties":{"codesPostaux":["03210"],"population":194,"nom":"Marigny","code":"03162"},"geometry":{"type":"Point","coordinates":[3.2143605056179756,46.58128533707865]}}]}