{"type":"FeatureCollection","features":[{"type":"Feature","properties":{"codesPostaux":["03150"],"population":314,"nom":"Montaigu-le-Blin","code":"03179"},"geometry":{"type":"Point","coordinates":[3.5147553398058236,46.28967165048543]}}]}