{"type":"FeatureCollection","features":[{"type":"Feature","properties":{"codesPostaux":["03120"],"population":468,"nom":"P\u00e9rigny","code":"03205"},"geometry":{"type":"Point","coordinates":[3.558365000000001,46.24414592857142]}}]}