{"type":"FeatureCollection","features":[{"type":"Feature","properties":{"codesPostaux":["03800"],"population":136,"nom":"Po\u00ebzat","code":"03209"},"geometry":{"type":"Point","coordinates":[3.2257646153846156,46.0746741025641]}}]}