{"type":"FeatureCollection","features":[{"type":"Feature","properties":{"codesPostaux":["03210"],"population":703,"nom":"Noyant-d'Allier","code":"03202"},"geometry":{"type":"Point","coordinates":[3.1246886702127687,46.48147047872343]}}]}