{"type":"FeatureCollection","features":[{"type":"Feature","properties":{"codesPostaux":["03150"],"population":587,"nom":"Rong\u00e8res","code":"03215"},"geometry":{"type":"Point","coordinates":[3.447418602150539,46.302573440860215]}}]}