{"type":"FeatureCollection","features":[{"type":"Feature","properties":{"codesPostaux":["03160"],"population":275,"nom":"Saint-Aubin-le-Monial","code":"03218"},"geometry":{"type":"Point","coordinates":[2.9960406691449832,46.5350575464684]}}]}