{"type":"FeatureCollection","features":[{"type":"Feature","properties":{"codesPostaux":["03800"],"population":663,"nom":"Saint-Bonnet-de-Rochefort","code":"03220"},"geometry":{"type":"Point","coordinates":[3.138864369747898,46.148613529411776]}}]}