{"type":"FeatureCollection","features":[{"type":"Feature","properties":{"codesPostaux":["03300"],"population":530,"nom":"Saint-\u00c9tienne-de-Vicq","code":"03230"},"geometry":{"type":"Point","coordinates":[3.533072780269059,46.17246995515697]}}]}