{"type":"FeatureCollection","features":[{"type":"Feature","properties":{"codesPostaux":["03260"],"population":3691,"nom":"Saint-Germain-des-Foss\u00e9s","code":"03236"},"geometry":{"type":"Point","coordinates":[3.430603928571429,46.19612214285714]}}]}