{"type":"FeatureCollection","features":[{"type":"Feature","properties":{"codesPostaux":["03150"],"population":542,"nom":"Saint-Loup","code":"03242"},"geometry":{"type":"Point","coordinates":[3.3867761428571437,46.354839714285724]}}]}