{"type":"FeatureCollection","features":[{"type":"Feature","properties":{"codesPostaux":["03220"],"population":622,"nom":"Saint-L\u00e9on","code":"03240"},"geometry":{"type":"Point","coordinates":[3.6872743076923045,46.409920799999966]}}]}