{"type":"FeatureCollection","features":[{"type":"Feature","properties":{"codesPostaux":["03390"],"population":140,"nom":"Saint-Marcel-en-Murat","code":"03243"},"geometry":{"type":"Point","coordinates":[3.0092813186813188,46.32385181318681]}}]}