{"type":"FeatureCollection","features":[{"type":"Feature","properties":{"codesPostaux":["03800"],"population":149,"nom":"Saint-Priest-d'Andelot","code":"03255"},"geometry":{"type":"Point","coordinates":[3.1541224691358014,46.079218271604944]}}]}