{"type":"FeatureCollection","features":[{"type":"Feature","properties":{"codesPostaux":["03220"],"population":193,"nom":"Saint-Voir","code":"03263"},"geometry":{"type":"Point","coordinates":[3.5049181290322577,46.40531909677421]}}]}