{"type":"FeatureCollection","features":[{"type":"Feature","properties":{"codesPostaux":["03500"],"population":678,"nom":"Saulcet","code":"03267"},"geometry":{"type":"Point","coordinates":[3.2633650000000003,46.331250641025655]}}]}