{"type":"FeatureCollection","features":[{"type":"Feature","properties":{"codesPostaux":["03220"],"population":301,"nom":"Sorbier","code":"03274"},"geometry":{"type":"Point","coordinates":[3.6654514432989687,46.36548994845361]}}]}