{"type":"FeatureCollection","features":[{"type":"Feature","properties":{"codesPostaux":["03450"],"population":104,"nom":"Sussat","code":"03276"},"geometry":{"type":"Point","coordinates":[3.059283304347826,46.15456278260869]}}]}