{"type":"FeatureCollection","features":[{"type":"Feature","properties":{"codesPostaux":["03380"],"population":452,"nom":"Treignat","code":"03288"},"geometry":{"type":"Point","coordinates":[2.350600178571428,46.346277178571434]}}]}