{"type":"FeatureCollection","features":[{"type":"Feature","properties":{"codesPostaux":["03220"],"population":566,"nom":"Treteau","code":"03289"},"geometry":{"type":"Point","coordinates":[3.5202487999999987,46.37111279999999]}}]}