{"type":"FeatureCollection","features":[{"type":"Feature","properties":{"codesPostaux":["03240"],"population":401,"nom":"Treban","code":"03287"},"geometry":{"type":"Point","coordinates":[3.1636723404255327,46.39599531914892]}}]}