{"type":"FeatureCollection","features":[{"type":"Feature","properties":{"codesPostaux":["03400"],"population":1138,"nom":"Toulon-sur-Allier","code":"03286"},"geometry":{"type":"Point","coordinates":[3.3844469662921353,46.51098005617978]}}]}