{"type":"FeatureCollection","features":[{"type":"Feature","properties":{"codesPostaux":["03350"],"population":377,"nom":"Theneuille","code":"03282"},"geometry":{"type":"Point","coordinates":[2.885628737864076,46.59018325242717]}}]}