{"type":"FeatureCollection","features":[{"type":"Feature","properties":{"codesPostaux":["03390"],"population":165,"nom":"Vernusse","code":"03308"},"geometry":{"type":"Point","coordinates":[2.9765234763948474,46.262274978540766]}}]}