{"type":"FeatureCollection","features":[{"type":"Feature","properties":{"codesPostaux":["03200"],"population":25325,"nom":"Vichy","code":"03310"},"geometry":{"type":"Point","coordinates":[3.428419729729729,46.12989243243244]}}]}