{"type":"FeatureCollection","features":[{"type":"Feature","properties":{"codesPostaux":["03400"],"population":12905,"nom":"Yzeure","code":"03321"},"geometry":{"type":"Point","coordinates":[3.379446979865771,46.5721224161074]}}]}