{"type":"FeatureCollection","features":[{"type":"Feature","properties":{"codesPostaux":["04250"],"population":209,"nom":"Bayons","code":"04023"},"geometry":{"type":"Point","coordinates":[6.1737417994100285,44.335321061946914]}}]}