{"type":"FeatureCollection","features":[{"type":"Feature","properties":{"codesPostaux":["04270"],"population":121,"nom":"Beynes","code":"04028"},"geometry":{"type":"Point","coordinates":[6.249201058823532,43.97724958823529]}}]}