{"type":"FeatureCollection","features":[{"type":"Feature","properties":{"codesPostaux":["04340"],"population":693,"nom":"Ubaye-Serre-Pon\u00e7on","code":"04033"},"geometry":{"type":"Point","coordinates":[6.304068383838384,44.443047474747466]}}]}