{"type":"FeatureCollection","features":[{"type":"Feature","properties":{"codesPostaux":["04250"],"population":179,"nom":"Clamensane","code":"04057"},"geometry":{"type":"Point","coordinates":[6.080005412844037,44.328768073394485]}}]}