{"type":"FeatureCollection","features":[{"type":"Feature","properties":{"codesPostaux":["04300"],"population":812,"nom":"Dauphin","code":"04068"},"geometry":{"type":"Point","coordinates":[5.775906101694913,43.89147144067796]}}]}