{"type":"FeatureCollection","features":[{"type":"Feature","properties":{"codesPostaux":["04220"],"population":1068,"nom":"Corbi\u00e8res","code":"04063"},"geometry":{"type":"Point","coordinates":[5.740326826923073,43.763206634615365]}}]}