{"type":"FeatureCollection","features":[{"type":"Feature","properties":{"codesPostaux":["04420"],"population":98,"nom":"Draix","code":"04072"},"geometry":{"type":"Point","coordinates":[6.371323008130084,44.131828455284534]}}]}