{"type":"FeatureCollection","features":[{"type":"Feature","properties":{"codesPostaux":["04230"],"population":131,"nom":"Fontienne","code":"04087"},"geometry":{"type":"Point","coordinates":[5.798131818181817,44.00386818181818]}}]}