{"type":"FeatureCollection","features":[{"type":"Feature","properties":{"codesPostaux":["04270"],"population":478,"nom":"Estoublon","code":"04084"},"geometry":{"type":"Point","coordinates":[6.193065637254905,43.94076980392157]}}]}