{"type":"FeatureCollection","features":[{"type":"Feature","properties":{"codesPostaux":["04340"],"population":224,"nom":"Le Lauzet-Ubaye","code":"04102"},"geometry":{"type":"Point","coordinates":[6.42004022304833,44.43742375464682]}}]}