{"type":"FeatureCollection","features":[{"type":"Feature","properties":{"codesPostaux":["04110"],"population":55,"nom":"Montjustin","code":"04129"},"geometry":{"type":"Point","coordinates":[5.651898783783784,43.84711804054054]}}]}