{"type":"FeatureCollection","features":[{"type":"Feature","properties":{"codesPostaux":["04510"],"population":501,"nom":"Mirabeau","code":"04122"},"geometry":{"type":"Point","coordinates":[6.082228559322036,44.06385906779663]}}]}