{"type":"FeatureCollection","features":[{"type":"Feature","properties":{"codesPostaux":["04300"],"population":276,"nom":"Niozelles","code":"04138"},"geometry":{"type":"Point","coordinates":[5.849585096153846,43.93188567307693]}}]}