{"type":"FeatureCollection","features":[{"type":"Feature","properties":{"codesPostaux":["04110"],"population":60,"nom":"Oppedette","code":"04142"},"geometry":{"type":"Point","coordinates":[5.594071265822784,43.93460835443039]}}]}