{"type":"FeatureCollection","features":[{"type":"Feature","properties":{"codesPostaux":["04120"],"population":335,"nom":"La Palud-sur-Verdon","code":"04144"},"geometry":{"type":"Point","coordinates":[6.329719973045824,43.79683698113205]}}]}