{"type":"FeatureCollection","features":[{"type":"Feature","properties":{"codesPostaux":["05160"],"population":80,"nom":"Pontis","code":"04154"},"geometry":{"type":"Point","coordinates":[6.371423770491803,44.499507868852454]}}]}