{"type":"FeatureCollection","features":[{"type":"Feature","properties":{"codesPostaux":["04150"],"population":93,"nom":"La Rochegiron","code":"04169"},"geometry":{"type":"Point","coordinates":[5.668026937500003,44.10443868750002]}}]}