{"type":"FeatureCollection","features":[{"type":"Feature","properties":{"codesPostaux":["04000"],"population":306,"nom":"La Robine-sur-Galabre","code":"04167"},"geometry":{"type":"Point","coordinates":[6.229159539170503,44.19226322580642]}}]}