{"type":"FeatureCollection","features":[{"type":"Feature","properties":{"codesPostaux":["06260"],"population":64,"nom":"La Rochette","code":"04170"},"geometry":{"type":"Point","coordinates":[6.871364810126583,43.909008481012656]}}]}