{"type":"FeatureCollection","features":[{"type":"Feature","properties":{"codesPostaux":["04500"],"population":122,"nom":"Sainte-Croix-du-Verdon","code":"04176"},"geometry":{"type":"Point","coordinates":[6.141386197183098,43.76872070422534]}}]}