{"type":"FeatureCollection","features":[{"type":"Feature","properties":{"codesPostaux":["04330"],"population":54,"nom":"Saint-Jacques","code":"04180"},"geometry":{"type":"Point","coordinates":[6.370617647058823,43.97949588235295]}}]}