{"type":"FeatureCollection","features":[{"type":"Feature","properties":{"codesPostaux":["04270"],"population":61,"nom":"Saint-Jeannet","code":"04181"},"geometry":{"type":"Point","coordinates":[6.113298866995076,43.98172453201968]}}]}