{"type":"FeatureCollection","features":[{"type":"Feature","properties":{"codesPostaux":["04400"],"population":689,"nom":"Saint-Pons","code":"04195"},"geometry":{"type":"Point","coordinates":[6.61256144067796,44.4198583898305]}}]}