{"type":"FeatureCollection","features":[{"type":"Feature","properties":{"codesPostaux":["04140"],"population":438,"nom":"Selonnet","code":"04203"},"geometry":{"type":"Point","coordinates":[6.287185106382976,44.36835425531913]}}]}