{"type":"FeatureCollection","features":[{"type":"Feature","properties":{"codesPostaux":["04200"],"population":245,"nom":"Valbelle","code":"04229"},"geometry":{"type":"Point","coordinates":[5.881408571428569,44.138091785714295]}}]}