{"type":"FeatureCollection","features":[{"type":"Feature","properties":{"codesPostaux":["04180"],"population":3881,"nom":"Villeneuve","code":"04242"},"geometry":{"type":"Point","coordinates":[5.847650416666665,43.897076428571395]}}]}