{"type":"FeatureCollection","features":[{"type":"Feature","properties":{"codesPostaux":["05200"],"population":520,"nom":"Baratier","code":"05012"},"geometry":{"type":"Point","coordinates":[6.509811582278483,44.500546898734164]}}]}