{"type":"FeatureCollection","features":[{"type":"Feature","properties":{"codesPostaux":["05500"],"population":190,"nom":"Buissard","code":"05025"},"geometry":{"type":"Point","coordinates":[6.146954814814814,44.659692098765454]}}]}