{"type":"FeatureCollection","features":[{"type":"Feature","properties":{"codesPostaux":["05230"],"population":2774,"nom":"Chorges","code":"05040"},"geometry":{"type":"Point","coordinates":[6.288784000000004,44.54841506976743]}}]}