{"type":"FeatureCollection","features":[{"type":"Feature","properties":{"codesPostaux":["05200"],"population":1010,"nom":"Crots","code":"05045"},"geometry":{"type":"Point","coordinates":[6.452899052132701,44.486789004739364]}}]}