{"type":"FeatureCollection","features":[{"type":"Feature","properties":{"codesPostaux":["05110"],"population":40,"nom":"Esparron","code":"05049"},"geometry":{"type":"Point","coordinates":[5.886759696969692,44.456609444444446]}}]}