{"type":"FeatureCollection","features":[{"type":"Feature","properties":{"codesPostaux":["05310"],"population":205,"nom":"Freissini\u00e8res","code":"05058"},"geometry":{"type":"Point","coordinates":[6.468106556776559,44.73174076923077]}}]}