{"type":"FeatureCollection","features":[{"type":"Feature","properties":{"codesPostaux":["05140"],"population":10,"nom":"La Haute-Beaume","code":"05066"},"geometry":{"type":"Point","coordinates":[5.6317123076923075,44.57040373626375]}}]}