{"type":"FeatureCollection","features":[{"type":"Feature","properties":{"codesPostaux":["05800"],"population":106,"nom":"La Chapelle-en-Valgaud\u00e9mar","code":"05064"},"geometry":{"type":"Point","coordinates":[6.237906540084387,44.808354472573846]}}]}