{"type":"FeatureCollection","features":[{"type":"Feature","properties":{"codesPostaux":["05130"],"population":172,"nom":"Lettret","code":"05074"},"geometry":{"type":"Point","coordinates":[6.07462111111111,44.48477666666666]}}]}