{"type":"FeatureCollection","features":[{"type":"Feature","properties":{"codesPostaux":["05000"],"population":749,"nom":"Neffes","code":"05092"},"geometry":{"type":"Point","coordinates":[6.0271805042016835,44.50057504201682]}}]}