{"type":"FeatureCollection","features":[{"type":"Feature","properties":{"codesPostaux":["05700"],"population":12,"nom":"Nossage-et-B\u00e9n\u00e9vent","code":"05094"},"geometry":{"type":"Point","coordinates":[5.750848783783786,44.313500810810815]}}]}