{"type":"FeatureCollection","features":[{"type":"Feature","properties":{"codesPostaux":["05700"],"population":88,"nom":"La Piarre","code":"05102"},"geometry":{"type":"Point","coordinates":[5.645747619047615,44.47813936507937]}}]}