{"type":"FeatureCollection","features":[{"type":"Feature","properties":{"codesPostaux":["05100"],"population":519,"nom":"Puy-Saint-Pierre","code":"05109"},"geometry":{"type":"Point","coordinates":[6.6097339130434785,44.897828115942026]}}]}