{"type":"FeatureCollection","features":[{"type":"Feature","properties":{"codesPostaux":["05150"],"population":100,"nom":"Ribeyret","code":"05117"},"geometry":{"type":"Point","coordinates":[5.556554950495048,44.41243336633663]}}]}