{"type":"FeatureCollection","features":[{"type":"Feature","properties":{"codesPostaux":["05600"],"population":676,"nom":"Risoul","code":"05119"},"geometry":{"type":"Point","coordinates":[6.629923888888889,44.62363138888892]}}]}