{"type":"FeatureCollection","features":[{"type":"Feature","properties":{"codesPostaux":["05400"],"population":1466,"nom":"La Roche-des-Arnauds","code":"05123"},"geometry":{"type":"Point","coordinates":[5.972643227513226,44.58068798941795]}}]}