{"type":"FeatureCollection","features":[{"type":"Feature","properties":{"codesPostaux":["05500"],"population":499,"nom":"Saint-Laurent-du-Cros","code":"05148"},"geometry":{"type":"Point","coordinates":[6.109347826086956,44.63652876811594]}}]}