{"type":"FeatureCollection","features":[{"type":"Feature","properties":{"codesPostaux":["05350"],"population":262,"nom":"Saint-V\u00e9ran","code":"05157"},"geometry":{"type":"Point","coordinates":[6.892897724137929,44.682199586206885]}}]}