{"type":"FeatureCollection","features":[{"type":"Feature","properties":{"codesPostaux":["05110"],"population":1392,"nom":"La Saulce","code":"05162"},"geometry":{"type":"Point","coordinates":[6.010445632183907,44.43385264367816]}}]}