{"type":"FeatureCollection","features":[{"type":"Feature","properties":{"codesPostaux":["05240"],"population":960,"nom":"La Salle-les-Alpes","code":"05161"},"geometry":{"type":"Point","coordinates":[6.575416062992125,44.959961496062995]}}]}