{"type":"FeatureCollection","features":[{"type":"Feature","properties":{"codesPostaux":["06240"],"population":13279,"nom":"Beausoleil","code":"06012"},"geometry":{"type":"Point","coordinates":[7.419756060606067,43.747320202020184]}}]}