{"type":"FeatureCollection","features":[{"type":"Feature","properties":{"codesPostaux":["06450"],"population":636,"nom":"Belv\u00e9d\u00e8re","code":"06013"},"geometry":{"type":"Point","coordinates":[7.36505166666667,44.05688960784315]}}]}