{"type":"FeatureCollection","features":[{"type":"Feature","properties":{"codesPostaux":["06410"],"population":10015,"nom":"Biot","code":"06018"},"geometry":{"type":"Point","coordinates":[7.081946936936937,43.624555315315305]}}]}