{"type":"FeatureCollection","features":[{"type":"Feature","properties":{"codesPostaux":["06670"],"population":1537,"nom":"Castagniers","code":"06034"},"geometry":{"type":"Point","coordinates":[7.233734873949578,43.79564302521007]}}]}