{"type":"FeatureCollection","features":[{"type":"Feature","properties":{"codesPostaux":["06620"],"population":115,"nom":"Courmes","code":"06049"},"geometry":{"type":"Point","coordinates":[7.013129078014183,43.75641808510637]}}]}