{"type":"FeatureCollection","features":[{"type":"Feature","properties":{"codesPostaux":["06440"],"population":1216,"nom":"Luc\u00e9ram","code":"06077"},"geometry":{"type":"Point","coordinates":[7.351530614525137,43.89585888268158]}}]}