{"type":"FeatureCollection","features":[{"type":"Feature","properties":{"codesPostaux":["06210"],"population":22864,"nom":"Mandelieu-la-Napoule","code":"06079"},"geometry":{"type":"Point","coordinates":[6.929138823529414,43.53042321981429]}}]}