{"type":"FeatureCollection","features":[{"type":"Feature","properties":{"codesPostaux":["06440"],"population":1492,"nom":"Peillon","code":"06092"},"geometry":{"type":"Point","coordinates":[7.366989032258066,43.77123012903227]}}]}