{"type":"FeatureCollection","features":[{"type":"Feature","properties":{"codesPostaux":["06440"],"population":2339,"nom":"Peille","code":"06091"},"geometry":{"type":"Point","coordinates":[7.406519192982456,43.80716915789476]}}]}