{"type":"FeatureCollection","features":[{"type":"Feature","properties":{"codesPostaux":["06450"],"population":1767,"nom":"Roquebilli\u00e8re","code":"06103"},"geometry":{"type":"Point","coordinates":[7.293709492753624,44.02499057971015]}}]}