{"type":"FeatureCollection","features":[{"type":"Feature","properties":{"codesPostaux":["06550"],"population":5381,"nom":"La Roquette-sur-Siagne","code":"06108"},"geometry":{"type":"Point","coordinates":[6.953273287671232,43.58383643835617]}}]}