{"type":"FeatureCollection","features":[{"type":"Feature","properties":{"codesPostaux":["06910"],"population":567,"nom":"Roquest\u00e9ron","code":"06106"},"geometry":{"type":"Point","coordinates":[7.020243295454548,43.87005181818182]}}]}