{"type":"FeatureCollection","features":[{"type":"Feature","properties":{"codesPostaux":["06530"],"population":3851,"nom":"Saint-C\u00e9zaire-sur-Siagne","code":"06118"},"geometry":{"type":"Point","coordinates":[6.800312842639592,43.6590421827411]}}]}