{"type":"FeatureCollection","features":[{"type":"Feature","properties":{"codesPostaux":["06850"],"population":232,"nom":"Saint-Auban","code":"06116"},"geometry":{"type":"Point","coordinates":[6.74600178260869,43.831807086956545]}}]}