{"type":"FeatureCollection","features":[{"type":"Feature","properties":{"codesPostaux":["06660"],"population":1291,"nom":"Saint-\u00c9tienne-de-Tin\u00e9e","code":"06120"},"geometry":{"type":"Point","coordinates":[6.928010992366417,44.25928893129768]}}]}