{"type":"FeatureCollection","features":[{"type":"Feature","properties":{"codesPostaux":["06230"],"population":1767,"nom":"Saint-Jean-Cap-Ferrat","code":"06121"},"geometry":{"type":"Point","coordinates":[7.332596724890824,43.688141004366805]}}]}