{"type":"FeatureCollection","features":[{"type":"Feature","properties":{"codesPostaux":["06470"],"population":82,"nom":"Sauze","code":"06133"},"geometry":{"type":"Point","coordinates":[6.806864405594408,44.08134657342656]}}]}