{"type":"FeatureCollection","features":[{"type":"Feature","properties":{"codesPostaux":["06910"],"population":206,"nom":"Sigale","code":"06135"},"geometry":{"type":"Point","coordinates":[6.964565204081635,43.87468265306121]}}]}