{"type":"FeatureCollection","features":[{"type":"Feature","properties":{"codesPostaux":["06420"],"population":147,"nom":"Tournefort","code":"06146"},"geometry":{"type":"Point","coordinates":[7.158096291390731,43.94126986754964]}}]}