{"type":"FeatureCollection","features":[{"type":"Feature","properties":{"codesPostaux":["06710"],"population":698,"nom":"Tou\u00ebt-sur-Var","code":"06143"},"geometry":{"type":"Point","coordinates":[7.013743092105268,43.945255592105276]}}]}