{"type":"FeatureCollection","features":[{"type":"Feature","properties":{"codesPostaux":["06450"],"population":150,"nom":"Venanson","code":"06156"},"geometry":{"type":"Point","coordinates":[7.2405385567010265,44.04006484536082]}}]}