{"type":"FeatureCollection","features":[{"type":"Feature","properties":{"codesPostaux":["06430"],"population":719,"nom":"La Brigue","code":"06162"},"geometry":{"type":"Point","coordinates":[7.643770857142858,44.06948599999998]}}]}