{"type":"FeatureCollection","features":[{"type":"Feature","properties":{"codesPostaux":["07410"],"population":331,"nom":"Arlebosc","code":"07014"},"geometry":{"type":"Point","coordinates":[4.630794976303317,45.039407535544996]}}]}