{"type":"FeatureCollection","features":[{"type":"Feature","properties":{"codesPostaux":["07190"],"population":230,"nom":"Beauv\u00e8ne","code":"07030"},"geometry":{"type":"Point","coordinates":[4.510244196428573,44.867459464285716]}}]}