{"type":"FeatureCollection","features":[{"type":"Feature","properties":{"codesPostaux":["07310"],"population":264,"nom":"Chan\u00e9ac","code":"07054"},"geometry":{"type":"Point","coordinates":[4.310899626168225,44.93130046728971]}}]}