{"type":"FeatureCollection","features":[{"type":"Feature","properties":{"codesPostaux":["07340"],"population":621,"nom":"Champagne","code":"07051"},"geometry":{"type":"Point","coordinates":[4.796000810810811,45.27819891891893]}}]}