{"type":"FeatureCollection","features":[{"type":"Feature","properties":{"codesPostaux":["07380"],"population":263,"nom":"Chirols","code":"07065"},"geometry":{"type":"Point","coordinates":[4.293310186915886,44.68793971962616]}}]}