{"type":"FeatureCollection","features":[{"type":"Feature","properties":{"codesPostaux":["07210"],"population":2990,"nom":"Chom\u00e9rac","code":"07066"},"geometry":{"type":"Point","coordinates":[4.668540128205128,44.7068773076923]}}]}