{"type":"FeatureCollection","features":[{"type":"Feature","properties":{"codesPostaux":["07000"],"population":1669,"nom":"Coux","code":"07072"},"geometry":{"type":"Point","coordinates":[4.620565494505495,44.7432401098901]}}]}