{"type":"FeatureCollection","features":[{"type":"Feature","properties":{"codesPostaux":["07130"],"population":2234,"nom":"Cornas","code":"07070"},"geometry":{"type":"Point","coordinates":[4.834929500000001,44.9639726]}}]}