{"type":"FeatureCollection","features":[{"type":"Feature","properties":{"codesPostaux":["07320"],"population":287,"nom":"Devesset","code":"07080"},"geometry":{"type":"Point","coordinates":[4.397043873517785,45.06878790513838]}}]}