{"type":"FeatureCollection","features":[{"type":"Feature","properties":{"codesPostaux":["07270"],"population":554,"nom":"Empurany","code":"07085"},"geometry":{"type":"Point","coordinates":[4.59714078787879,45.027305818181844]}}]}