{"type":"FeatureCollection","features":[{"type":"Feature","properties":{"codesPostaux":["07200"],"population":316,"nom":"Fons","code":"07091"},"geometry":{"type":"Point","coordinates":[4.354609726027398,44.581386986301375]}}]}