{"type":"FeatureCollection","features":[{"type":"Feature","properties":{"codesPostaux":["07510","07660"],"population":110,"nom":"Issanlas","code":"07105"},"geometry":{"type":"Point","coordinates":[4.01445077464789,44.77582693661969]}}]}