{"type":"FeatureCollection","features":[{"type":"Feature","properties":{"codesPostaux":["07140"],"population":444,"nom":"Gravi\u00e8res","code":"07100"},"geometry":{"type":"Point","coordinates":[4.073371999999998,44.42190652941178]}}]}