{"type":"FeatureCollection","features":[{"type":"Feature","properties":{"codesPostaux":["07200"],"population":1385,"nom":"Lab\u00e9gude","code":"07116"},"geometry":{"type":"Point","coordinates":[4.360307083333332,44.63996770833333]}}]}