{"type":"FeatureCollection","features":[{"type":"Feature","properties":{"codesPostaux":["07600"],"population":172,"nom":"Juvinas","code":"07111"},"geometry":{"type":"Point","coordinates":[4.3068657480314965,44.703316850393705]}}]}