{"type":"FeatureCollection","features":[{"type":"Feature","properties":{"codesPostaux":["07660"],"population":82,"nom":"Lavillatte","code":"07137"},"geometry":{"type":"Point","coordinates":[3.955293756906079,44.74349187845304]}}]}