{"type":"FeatureCollection","features":[{"type":"Feature","properties":{"codesPostaux":["07340"],"population":726,"nom":"Limony","code":"07143"},"geometry":{"type":"Point","coordinates":[4.746826292134831,45.35139112359553]}}]}