{"type":"FeatureCollection","features":[{"type":"Feature","properties":{"codesPostaux":["07320"],"population":271,"nom":"Mars","code":"07151"},"geometry":{"type":"Point","coordinates":[4.334082032520328,45.00759898373979]}}]}