{"type":"FeatureCollection","features":[{"type":"Feature","properties":{"codesPostaux":["07330"],"population":261,"nom":"Mayres","code":"07153"},"geometry":{"type":"Point","coordinates":[4.1002685443038,44.663682468354416]}}]}