{"type":"FeatureCollection","features":[{"type":"Feature","properties":{"codesPostaux":["07510"],"population":138,"nom":"Mazan-l'Abbaye","code":"07154"},"geometry":{"type":"Point","coordinates":[4.090264170212765,44.73177378723405]}}]}