{"type":"FeatureCollection","features":[{"type":"Feature","properties":{"codesPostaux":["07590"],"population":52,"nom":"Le Plagnal","code":"07175"},"geometry":{"type":"Point","coordinates":[3.945137421874999,44.694167500000006]}}]}