{"type":"FeatureCollection","features":[{"type":"Feature","properties":{"codesPostaux":["07290"],"population":669,"nom":"Pr\u00e9aux","code":"07185"},"geometry":{"type":"Point","coordinates":[4.654496171875001,45.13982374999999]}}]}