{"type":"FeatureCollection","features":[{"type":"Feature","properties":{"codesPostaux":["07320"],"population":2528,"nom":"Saint-Agr\u00e8ve","code":"07204"},"geometry":{"type":"Point","coordinates":[4.410521763085395,44.99939283746557]}}]}