{"type":"FeatureCollection","features":[{"type":"Feature","properties":{"codesPostaux":["07460"],"population":474,"nom":"Saint-Andr\u00e9-de-Cruzi\u00e8res","code":"07211"},"geometry":{"type":"Point","coordinates":[4.207258818897638,44.32268173228347]}}]}