{"type":"FeatureCollection","features":[{"type":"Feature","properties":{"codesPostaux":["07430"],"population":1068,"nom":"Saint-Clair","code":"07225"},"geometry":{"type":"Point","coordinates":[4.683278732394368,45.27805507042254]}}]}