{"type":"FeatureCollection","features":[{"type":"Feature","properties":{"codesPostaux":["07530"],"population":194,"nom":"Saint-Joseph-des-Bancs","code":"07251"},"geometry":{"type":"Point","coordinates":[4.409844304635761,44.749265231788094]}}]}