{"type":"FeatureCollection","features":[{"type":"Feature","properties":{"codesPostaux":["07460"],"population":975,"nom":"Saint-Paul-le-Jeune","code":"07280"},"geometry":{"type":"Point","coordinates":[4.157967635135132,44.33336209459462]}}]}