{"type":"FeatureCollection","features":[{"type":"Feature","properties":{"codesPostaux":["07400"],"population":53,"nom":"Saint-Pierre-la-Roche","code":"07283"},"geometry":{"type":"Point","coordinates":[4.6211989523809525,44.65225723809523]}}]}