{"type":"FeatureCollection","features":[{"type":"Feature","properties":{"codesPostaux":["07460"],"population":524,"nom":"Saint-Sauveur-de-Cruzi\u00e8res","code":"07294"},"geometry":{"type":"Point","coordinates":[4.257815192307689,44.29655326923075]}}]}