{"type":"FeatureCollection","features":[{"type":"Feature","properties":{"codesPostaux":["07130"],"population":805,"nom":"Saint-Romain-de-Lerps","code":"07293"},"geometry":{"type":"Point","coordinates":[4.797766790123456,44.97732506172842]}}]}