{"type":"FeatureCollection","features":[{"type":"Feature","properties":{"codesPostaux":["07400"],"population":8292,"nom":"Le Teil","code":"07319"},"geometry":{"type":"Point","coordinates":[4.660686011904764,44.54713333333333]}}]}