{"type":"FeatureCollection","features":[{"type":"Feature","properties":{"codesPostaux":["07340"],"population":233,"nom":"Thorrenc","code":"07321"},"geometry":{"type":"Point","coordinates":[4.7606287499999995,45.233728125000006]}}]}