{"type":"FeatureCollection","features":[{"type":"Feature","properties":{"codesPostaux":["07150"],"population":554,"nom":"Vagnas","code":"07328"},"geometry":{"type":"Point","coordinates":[4.343967357142856,44.35771342857142]}}]}