{"type":"FeatureCollection","features":[{"type":"Feature","properties":{"codesPostaux":["07690"],"population":930,"nom":"Vanosc","code":"07333"},"geometry":{"type":"Point","coordinates":[4.537459388888886,45.22649605555555]}}]}