{"type":"FeatureCollection","features":[{"type":"Feature","properties":{"codesPostaux":["07340"],"population":434,"nom":"Vinzieux","code":"07344"},"geometry":{"type":"Point","coordinates":[4.702945142857142,45.33034961904762]}}]}