{"type":"FeatureCollection","features":[{"type":"Feature","properties":{"codesPostaux":["07610"],"population":944,"nom":"Vion","code":"07345"},"geometry":{"type":"Point","coordinates":[4.793863578947367,45.112315263157896]}}]}