{"type":"FeatureCollection","features":[{"type":"Feature","properties":{"codesPostaux":["08370"],"population":84,"nom":"Auflance","code":"08029"},"geometry":{"type":"Point","coordinates":[5.295806153846154,49.612507606837596]}}]}