{"type":"FeatureCollection","features":[{"type":"Feature","properties":{"codesPostaux":["08270"],"population":100,"nom":"Auboncourt-Vauzelles","code":"08027"},"geometry":{"type":"Point","coordinates":[4.485348686868689,49.557240808080806]}}]}