{"type":"FeatureCollection","features":[{"type":"Feature","properties":{"codesPostaux":["08200"],"population":1589,"nom":"Balan","code":"08043"},"geometry":{"type":"Point","coordinates":[4.962749322033899,49.68834627118643]}}]}