{"type":"FeatureCollection","features":[{"type":"Feature","properties":{"codesPostaux":["08430"],"population":239,"nom":"Ba\u00e2lons","code":"08041"},"geometry":{"type":"Point","coordinates":[4.663742176470589,49.599822823529394]}}]}