{"type":"FeatureCollection","features":[{"type":"Feature","properties":{"codesPostaux":["08240"],"population":279,"nom":"Belleville-et-Ch\u00e2tillon-sur-Bar","code":"08057"},"geometry":{"type":"Point","coordinates":[4.812133190476192,49.4677478095238]}}]}