{"type":"FeatureCollection","features":[{"type":"Feature","properties":{"codesPostaux":["08290"],"population":101,"nom":"Bossus-l\u00e8s-Rumigny","code":"08073"},"geometry":{"type":"Point","coordinates":[4.25192215909091,49.83826624999997]}}]}