{"type":"FeatureCollection","features":[{"type":"Feature","properties":{"codesPostaux":["08110"],"population":2967,"nom":"Carignan","code":"08090"},"geometry":{"type":"Point","coordinates":[5.17146754189944,49.6378536312849]}}]}