{"type":"FeatureCollection","features":[{"type":"Feature","properties":{"codesPostaux":["08400"],"population":41,"nom":"Chardeny","code":"08104"},"geometry":{"type":"Point","coordinates":[4.595614,49.420019764705884]}}]}