{"type":"FeatureCollection","features":[{"type":"Feature","properties":{"codesPostaux":["08220"],"population":96,"nom":"Chappes","code":"08102"},"geometry":{"type":"Point","coordinates":[4.281691160714285,49.609587410714276]}}]}