{"type":"FeatureCollection","features":[{"type":"Feature","properties":{"codesPostaux":["08090"],"population":309,"nom":"Cliron","code":"08125"},"geometry":{"type":"Point","coordinates":[4.6147034517766485,49.81028101522843]}}]}