{"type":"FeatureCollection","features":[{"type":"Feature","properties":{"codesPostaux":["08460"],"population":357,"nom":"Clavy-Warby","code":"08124"},"geometry":{"type":"Point","coordinates":[4.549184470588235,49.74543647058826]}}]}