{"type":"FeatureCollection","features":[{"type":"Feature","properties":{"codesPostaux":["08140"],"population":355,"nom":"Daigny","code":"08136"},"geometry":{"type":"Point","coordinates":[5.0026753658536585,49.70408487804878]}}]}