{"type":"FeatureCollection","features":[{"type":"Feature","properties":{"codesPostaux":["08110"],"population":272,"nom":"Les Deux-Villes","code":"08138"},"geometry":{"type":"Point","coordinates":[5.233232321428572,49.654022857142884]}}]}