{"type":"FeatureCollection","features":[{"type":"Feature","properties":{"codesPostaux":["08140"],"population":2134,"nom":"Douzy","code":"08145"},"geometry":{"type":"Point","coordinates":[5.043344927536232,49.66287835748789]}}]}