{"type":"FeatureCollection","features":[{"type":"Feature","properties":{"codesPostaux":["08350"],"population":2245,"nom":"Donchery","code":"08142"},"geometry":{"type":"Point","coordinates":[4.885948631578948,49.73147821052635]}}]}