{"type":"FeatureCollection","features":[{"type":"Feature","properties":{"codesPostaux":["08400"],"population":325,"nom":"Falaise","code":"08164"},"geometry":{"type":"Point","coordinates":[4.734173184357544,49.38297212290502]}}]}