{"type":"FeatureCollection","features":[{"type":"Feature","properties":{"codesPostaux":["08250"],"population":102,"nom":"Fl\u00e9ville","code":"08171"},"geometry":{"type":"Point","coordinates":[4.98219559440559,49.30658013986014]}}]}