{"type":"FeatureCollection","features":[{"type":"Feature","properties":{"codesPostaux":["08240"],"population":46,"nom":"Germont","code":"08186"},"geometry":{"type":"Point","coordinates":[4.879426710526316,49.43008907894737]}}]}