{"type":"FeatureCollection","features":[{"type":"Feature","properties":{"codesPostaux":["08600"],"population":6618,"nom":"Givet","code":"08190"},"geometry":{"type":"Point","coordinates":[4.841884197530864,50.142144135802475]}}]}