{"type":"FeatureCollection","features":[{"type":"Feature","properties":{"codesPostaux":["08190"],"population":353,"nom":"Gomont","code":"08195"},"geometry":{"type":"Point","coordinates":[4.173516923076922,49.50506653846155]}}]}