{"type":"FeatureCollection","features":[{"type":"Feature","properties":{"codesPostaux":["08250"],"population":51,"nom":"Grandham","code":"08197"},"geometry":{"type":"Point","coordinates":[4.853047162162161,49.29413635135134]}}]}