{"type":"FeatureCollection","features":[{"type":"Feature","properties":{"codesPostaux":["08090"],"population":388,"nom":"Ham-les-Moines","code":"08206"},"geometry":{"type":"Point","coordinates":[4.590452427184467,49.79568864077671]}}]}