{"type":"FeatureCollection","features":[{"type":"Feature","properties":{"codesPostaux":["08160"],"population":457,"nom":"Hannogne-Saint-Martin","code":"08209"},"geometry":{"type":"Point","coordinates":[4.834920425531916,49.67364226950353]}}]}