{"type":"FeatureCollection","features":[{"type":"Feature","properties":{"codesPostaux":["08240"],"population":37,"nom":"Harricourt","code":"08215"},"geometry":{"type":"Point","coordinates":[4.922646914893616,49.440874042553176]}}]}