{"type":"FeatureCollection","features":[{"type":"Feature","properties":{"codesPostaux":["08370"],"population":106,"nom":"Herbeuval","code":"08223"},"geometry":{"type":"Point","coordinates":[5.3533299242424235,49.60219371212122]}}]}