{"type":"FeatureCollection","features":[{"type":"Feature","properties":{"codesPostaux":["08300"],"population":88,"nom":"Inaumont","code":"08234"},"geometry":{"type":"Point","coordinates":[4.316951406249998,49.56285710937499]}}]}