{"type":"FeatureCollection","features":[{"type":"Feature","properties":{"codesPostaux":["08240"],"population":54,"nom":"Im\u00e9court","code":"08233"},"geometry":{"type":"Point","coordinates":[4.972041226415095,49.370851509433976]}}]}