{"type":"FeatureCollection","features":[{"type":"Feature","properties":{"codesPostaux":["08150"],"population":99,"nom":"L\u00e9pron-les-Vall\u00e9es","code":"08251"},"geometry":{"type":"Point","coordinates":[4.458032209302325,49.74827976744185]}}]}