{"type":"FeatureCollection","features":[{"type":"Feature","properties":{"codesPostaux":["08400"],"population":102,"nom":"Liry","code":"08256"},"geometry":{"type":"Point","coordinates":[4.646683396226415,49.30483849056603]}}]}