{"type":"FeatureCollection","features":[{"type":"Feature","properties":{"codesPostaux":["08310"],"population":142,"nom":"M\u00e9nil-L\u00e9pinois","code":"08287"},"geometry":{"type":"Point","coordinates":[4.283222222222225,49.37606777777777]}}]}