{"type":"FeatureCollection","features":[{"type":"Feature","properties":{"codesPostaux":["08800"],"population":2413,"nom":"Montherm\u00e9","code":"08302"},"geometry":{"type":"Point","coordinates":[4.745452559241707,49.89642180094786]}}]}