{"type":"FeatureCollection","features":[{"type":"Feature","properties":{"codesPostaux":["08170"],"population":87,"nom":"Montigny-sur-Meuse","code":"08304"},"geometry":{"type":"Point","coordinates":[4.7103192307692305,50.048681923076934]}}]}