{"type":"FeatureCollection","features":[{"type":"Feature","properties":{"codesPostaux":["08400"],"population":376,"nom":"Monthois","code":"08303"},"geometry":{"type":"Point","coordinates":[4.710529673202615,49.305611372549016]}}]}