{"type":"FeatureCollection","features":[{"type":"Feature","properties":{"codesPostaux":["08390"],"population":66,"nom":"Montgon","code":"08301"},"geometry":{"type":"Point","coordinates":[4.720605119047619,49.5135244047619]}}]}