{"type":"FeatureCollection","features":[{"type":"Feature","properties":{"codesPostaux":["08250"],"population":82,"nom":"Mouron","code":"08310"},"geometry":{"type":"Point","coordinates":[4.781080491803279,49.316671311475424]}}]}