{"type":"FeatureCollection","features":[{"type":"Feature","properties":{"codesPostaux":["08240"],"population":147,"nom":"Nouart","code":"08326"},"geometry":{"type":"Point","coordinates":[5.050610676691729,49.4449769924812]}}]}