{"type":"FeatureCollection","features":[{"type":"Feature","properties":{"codesPostaux":["08310"],"population":569,"nom":"La Neuville-en-Tourne-\u00e0-Fuy","code":"08320"},"geometry":{"type":"Point","coordinates":[4.394912727272726,49.34458530303031]}}]}