{"type":"FeatureCollection","features":[{"type":"Feature","properties":{"codesPostaux":["08000"],"population":1372,"nom":"Prix-l\u00e8s-M\u00e9zi\u00e8res","code":"08346"},"geometry":{"type":"Point","coordinates":[4.685446351351349,49.748683648648644]}}]}