{"type":"FeatureCollection","features":[{"type":"Feature","properties":{"codesPostaux":["08430"],"population":822,"nom":"Poix-Terron","code":"08341"},"geometry":{"type":"Point","coordinates":[4.654510873786408,49.64504320388347]}}]}