{"type":"FeatureCollection","features":[{"type":"Feature","properties":{"codesPostaux":["08230"],"population":398,"nom":"Regniowez","code":"08355"},"geometry":{"type":"Point","coordinates":[4.412034514563105,49.92542970873787]}}]}