{"type":"FeatureCollection","features":[{"type":"Feature","properties":{"codesPostaux":["08450"],"population":869,"nom":"Raucourt-et-Flaba","code":"08354"},"geometry":{"type":"Point","coordinates":[4.958994596774194,49.59613137096774]}}]}