{"type":"FeatureCollection","features":[{"type":"Feature","properties":{"codesPostaux":["08300"],"population":54,"nom":"Saint-Remy-le-Petit","code":"08397"},"geometry":{"type":"Point","coordinates":[4.236088421052631,49.405068771929834]}}]}