{"type":"FeatureCollection","features":[{"type":"Feature","properties":{"codesPostaux":["08310"],"population":65,"nom":"Saint-Pierre-\u00e0-Arnes","code":"08393"},"geometry":{"type":"Point","coordinates":[4.45936,49.300185526315786]}}]}