{"type":"FeatureCollection","features":[{"type":"Feature","properties":{"codesPostaux":["08400"],"population":376,"nom":"Savigny-sur-Aisne","code":"08406"},"geometry":{"type":"Point","coordinates":[4.725191999999998,49.36195488888889]}}]}