{"type":"FeatureCollection","features":[{"type":"Feature","properties":{"codesPostaux":["08380"],"population":1277,"nom":"Signy-le-Petit","code":"08420"},"geometry":{"type":"Point","coordinates":[4.284482418879061,49.94201091445426]}}]}