{"type":"FeatureCollection","features":[{"type":"Feature","properties":{"codesPostaux":["08130"],"population":66,"nom":"Suzanne","code":"08433"},"geometry":{"type":"Point","coordinates":[4.63928112903226,49.5195805645161]}}]}