{"type":"FeatureCollection","features":[{"type":"Feature","properties":{"codesPostaux":["08390"],"population":159,"nom":"Tannay","code":"08439"},"geometry":{"type":"Point","coordinates":[4.821210869565218,49.52740124999998]}}]}