{"type":"FeatureCollection","features":[{"type":"Feature","properties":{"codesPostaux":["08430"],"population":85,"nom":"Touligny","code":"08454"},"geometry":{"type":"Point","coordinates":[4.61531376068376,49.67552051282052]}}]}