{"type":"FeatureCollection","features":[{"type":"Feature","properties":{"codesPostaux":["08130"],"population":177,"nom":"Tourteron","code":"08458"},"geometry":{"type":"Point","coordinates":[4.637747358490564,49.54099424528302]}}]}