{"type":"FeatureCollection","features":[{"type":"Feature","properties":{"codesPostaux":["08270"],"population":290,"nom":"Viel-Saint-Remy","code":"08472"},"geometry":{"type":"Point","coordinates":[4.4743729292929295,49.635029494949514]}}]}