{"type":"FeatureCollection","features":[{"type":"Feature","properties":{"codesPostaux":["09400"],"population":209,"nom":"Arnave","code":"09016"},"geometry":{"type":"Point","coordinates":[1.6467781188118817,42.851789801980175]}}]}