{"type":"FeatureCollection","features":[{"type":"Feature","properties":{"codesPostaux":["09800"],"population":78,"nom":"Arrout","code":"09018"},"geometry":{"type":"Point","coordinates":[1.0190861538461538,42.9491135897436]}}]}