{"type":"FeatureCollection","features":[{"type":"Feature","properties":{"codesPostaux":["09800"],"population":108,"nom":"Arrien-en-Bethmale","code":"09017"},"geometry":{"type":"Point","coordinates":[1.049538839779005,42.88492983425412]}}]}