{"type":"FeatureCollection","features":[{"type":"Feature","properties":{"codesPostaux":["09460"],"population":50,"nom":"Artigues","code":"09020"},"geometry":{"type":"Point","coordinates":[2.03707023255814,42.68540232558138]}}]}