{"type":"FeatureCollection","features":[{"type":"Feature","properties":{"codesPostaux":["09800"],"population":124,"nom":"Audressein","code":"09026"},"geometry":{"type":"Point","coordinates":[1.0199087301587306,42.92627888888889]}}]}