{"type":"FeatureCollection","features":[{"type":"Feature","properties":{"codesPostaux":["09800"],"population":64,"nom":"Aucazein","code":"09025"},"geometry":{"type":"Point","coordinates":[0.9696996153846152,42.928028589743576]}}]}