{"type":"FeatureCollection","features":[{"type":"Feature","properties":{"codesPostaux":["09300"],"population":1086,"nom":"B\u00e9lesta","code":"09047"},"geometry":{"type":"Point","coordinates":[1.9462507999999996,42.89165775999998]}}]}