{"type":"FeatureCollection","features":[{"type":"Feature","properties":{"codesPostaux":["09800"],"population":98,"nom":"Bethmale","code":"09055"},"geometry":{"type":"Point","coordinates":[1.0725979255319154,42.85986324468085]}}]}