{"type":"FeatureCollection","features":[{"type":"Feature","properties":{"codesPostaux":["09100"],"population":722,"nom":"Bonnac","code":"09060"},"geometry":{"type":"Point","coordinates":[1.5886509459459455,43.17321310810811]}}]}