{"type":"FeatureCollection","features":[{"type":"Feature","properties":{"codesPostaux":["09000"],"population":105,"nom":"Le Bosc","code":"09063"},"geometry":{"type":"Point","coordinates":[1.4553037500000001,42.931595625]}}]}