{"type":"FeatureCollection","features":[{"type":"Feature","properties":{"codesPostaux":["09420"],"population":105,"nom":"Clermont","code":"09097"},"geometry":{"type":"Point","coordinates":[1.2959444680851067,43.0365955319149]}}]}