{"type":"FeatureCollection","features":[{"type":"Feature","properties":{"codesPostaux":["09800"],"population":140,"nom":"Cescau","code":"09095"},"geometry":{"type":"Point","coordinates":[1.0567175000000002,42.92580927083335]}}]}