{"type":"FeatureCollection","features":[{"type":"Feature","properties":{"codesPostaux":["09100"],"population":420,"nom":"Escosse","code":"09116"},"geometry":{"type":"Point","coordinates":[1.5519828436018959,43.12570383886255]}}]}