{"type":"FeatureCollection","features":[{"type":"Feature","properties":{"codesPostaux":["09140"],"population":543,"nom":"Erc\u00e9","code":"09113"},"geometry":{"type":"Point","coordinates":[1.2962035416666666,42.841945624999994]}}]}