{"type":"FeatureCollection","features":[{"type":"Feature","properties":{"codesPostaux":["09200"],"population":132,"nom":"Erp","code":"09114"},"geometry":{"type":"Point","coordinates":[1.1979860606060604,42.93071424242425]}}]}