{"type":"FeatureCollection","features":[{"type":"Feature","properties":{"codesPostaux":["09400"],"population":21,"nom":"G\u00e9nat","code":"09133"},"geometry":{"type":"Point","coordinates":[1.5650584269662922,42.82658707865167]}}]}