{"type":"FeatureCollection","features":[{"type":"Feature","properties":{"codesPostaux":["09800"],"population":78,"nom":"Illartein","code":"09141"},"geometry":{"type":"Point","coordinates":[0.956463333333333,42.927207142857135]}}]}