{"type":"FeatureCollection","features":[{"type":"Feature","properties":{"codesPostaux":["09240"],"population":45,"nom":"Larbont","code":"09154"},"geometry":{"type":"Point","coordinates":[1.4008936363636364,42.99268441558442]}}]}