{"type":"FeatureCollection","features":[{"type":"Feature","properties":{"codesPostaux":["09310"],"population":59,"nom":"Lassur","code":"09159"},"geometry":{"type":"Point","coordinates":[1.722173763440861,42.7480817204301]}}]}