{"type":"FeatureCollection","features":[{"type":"Feature","properties":{"codesPostaux":["09300"],"population":6312,"nom":"Lavelanet","code":"09160"},"geometry":{"type":"Point","coordinates":[1.8471811111111114,42.93123273504274]}}]}