{"type":"FeatureCollection","features":[{"type":"Feature","properties":{"codesPostaux":["09700"],"population":211,"nom":"Lissac","code":"09170"},"geometry":{"type":"Point","coordinates":[1.5086468750000002,43.270060156250004]}}]}