{"type":"FeatureCollection","features":[{"type":"Feature","properties":{"codesPostaux":["09250"],"population":537,"nom":"Luzenac","code":"09176"},"geometry":{"type":"Point","coordinates":[1.7422510563380291,42.71693211267605]}}]}