{"type":"FeatureCollection","features":[{"type":"Feature","properties":{"codesPostaux":["09100"],"population":203,"nom":"Madi\u00e8re","code":"09177"},"geometry":{"type":"Point","coordinates":[1.5212514102564099,43.10747371794873]}}]}