{"type":"FeatureCollection","features":[{"type":"Feature","properties":{"codesPostaux":["09230"],"population":39,"nom":"Mauvezin-de-Sainte-Croix","code":"09184"},"geometry":{"type":"Point","coordinates":[1.2291667999999998,43.076235400000016]}}]}