{"type":"FeatureCollection","features":[{"type":"Feature","properties":{"codesPostaux":["09500"],"population":3136,"nom":"Mirepoix","code":"09194"},"geometry":{"type":"Point","coordinates":[1.8656436317135536,43.11303092071613]}}]}