{"type":"FeatureCollection","features":[{"type":"Feature","properties":{"codesPostaux":["09240"],"population":161,"nom":"Montels","code":"09203"},"geometry":{"type":"Point","coordinates":[1.4689733333333335,43.006408444444446]}}]}