{"type":"FeatureCollection","features":[{"type":"Feature","properties":{"codesPostaux":["09200"],"population":1063,"nom":"Montjoie-en-Couserans","code":"09209"},"geometry":{"type":"Point","coordinates":[1.1790003238866398,43.01264064777325]}}]}