{"type":"FeatureCollection","features":[{"type":"Feature","properties":{"codesPostaux":["09600"],"population":118,"nom":"Montbel","code":"09200"},"geometry":{"type":"Point","coordinates":[1.969462375000002,42.979175749999996]}}]}