{"type":"FeatureCollection","features":[{"type":"Feature","properties":{"codesPostaux":["09240"],"population":81,"nom":"Montseron","code":"09212"},"geometry":{"type":"Point","coordinates":[1.312288761904762,43.01973838095238]}}]}