{"type":"FeatureCollection","features":[{"type":"Feature","properties":{"codesPostaux":["09460"],"population":38,"nom":"Le Puch","code":"09237"},"geometry":{"type":"Point","coordinates":[2.1008517948717946,42.72309256410256]}}]}