{"type":"FeatureCollection","features":[{"type":"Feature","properties":{"codesPostaux":["09110"],"population":43,"nom":"Prades","code":"09232"},"geometry":{"type":"Point","coordinates":[1.8626869841269833,42.79300714285714]}}]}