{"type":"FeatureCollection","features":[{"type":"Feature","properties":{"codesPostaux":["09400"],"population":293,"nom":"Qui\u00e9","code":"09240"},"geometry":{"type":"Point","coordinates":[1.5931048936170207,42.841521063829795]}}]}