{"type":"FeatureCollection","features":[{"type":"Feature","properties":{"codesPostaux":["09500"],"population":139,"nom":"Saint-F\u00e9lix-de-Tournegat","code":"09259"},"geometry":{"type":"Point","coordinates":[1.7614355263157895,43.12186438596491]}}]}