{"type":"FeatureCollection","features":[{"type":"Feature","properties":{"codesPostaux":["09100"],"population":222,"nom":"Saint-Victor-Rouzaud","code":"09276"},"geometry":{"type":"Point","coordinates":[1.546545238095238,43.09037496598639]}}]}