{"type":"FeatureCollection","features":[{"type":"Feature","properties":{"codesPostaux":["09100"],"population":74,"nom":"Saint-Michel","code":"09271"},"geometry":{"type":"Point","coordinates":[1.4990948863636369,43.1345485227273]}}]}