{"type":"FeatureCollection","features":[{"type":"Feature","properties":{"codesPostaux":["09300"],"population":114,"nom":"Sautel","code":"09281"},"geometry":{"type":"Point","coordinates":[1.822248571428572,42.96816214285715]}}]}