{"type":"FeatureCollection","features":[{"type":"Feature","properties":{"codesPostaux":["09140"],"population":751,"nom":"Seix","code":"09285"},"geometry":{"type":"Point","coordinates":[1.1545528571428565,42.82329939849624]}}]}