{"type":"FeatureCollection","features":[{"type":"Feature","properties":{"codesPostaux":["09400"],"population":663,"nom":"Saurat","code":"09280"},"geometry":{"type":"Point","coordinates":[1.5048706711409388,42.87710637583892]}}]}