{"type":"FeatureCollection","features":[{"type":"Feature","properties":{"codesPostaux":["09000"],"population":665,"nom":"Vernajoul","code":"09329"},"geometry":{"type":"Point","coordinates":[1.5916725,42.99614035714286]}}]}