{"type":"FeatureCollection","features":[{"type":"Feature","properties":{"codesPostaux":["09310"],"population":35,"nom":"Urs","code":"09320"},"geometry":{"type":"Point","coordinates":[1.7369560869565215,42.777556521739136]}}]}