{"type":"FeatureCollection","features":[{"type":"Feature","properties":{"codesPostaux":["09100"],"population":761,"nom":"Villeneuve-du-Par\u00e9age","code":"09339"},"geometry":{"type":"Point","coordinates":[1.6406120312499999,43.15726343749999]}}]}