{"type":"FeatureCollection","features":[{"type":"Feature","properties":{"codesPostaux":["09250"],"population":32,"nom":"Vernaux","code":"09330"},"geometry":{"type":"Point","coordinates":[1.7803432000000001,42.784999733333315]}}]}