{"type":"FeatureCollection","features":[{"type":"Feature","properties":{"codesPostaux":["10700"],"population":2918,"nom":"Arcis-sur-Aube","code":"10006"},"geometry":{"type":"Point","coordinates":[4.144158965517242,48.53904706896553]}}]}