{"type":"FeatureCollection","features":[{"type":"Feature","properties":{"codesPostaux":["10200"],"population":269,"nom":"Ailleville","code":"10002"},"geometry":{"type":"Point","coordinates":[4.689687777777778,48.25215066666667]}}]}