{"type":"FeatureCollection","features":[{"type":"Feature","properties":{"codesPostaux":["10150"],"population":313,"nom":"Aubeterre","code":"10015"},"geometry":{"type":"Point","coordinates":[4.120590491803279,48.425874098360644]}}]}