{"type":"FeatureCollection","features":[{"type":"Feature","properties":{"codesPostaux":["10200"],"population":231,"nom":"Arrenti\u00e8res","code":"10011"},"geometry":{"type":"Point","coordinates":[4.741874027777779,48.26620083333331]}}]}