{"type":"FeatureCollection","features":[{"type":"Feature","properties":{"codesPostaux":["10110"],"population":159,"nom":"Balnot-sur-Laignes","code":"10029"},"geometry":{"type":"Point","coordinates":[4.354675434782609,48.03846282608695]}}]}