{"type":"FeatureCollection","features":[{"type":"Feature","properties":{"codesPostaux":["10400"],"population":418,"nom":"Barbuise","code":"10031"},"geometry":{"type":"Point","coordinates":[3.571042280701754,48.54875885964911]}}]}