{"type":"FeatureCollection","features":[{"type":"Feature","properties":{"codesPostaux":["10110"],"population":66,"nom":"Bertignolles","code":"10041"},"geometry":{"type":"Point","coordinates":[4.512138750000001,48.13157375000001]}}]}