{"type":"FeatureCollection","features":[{"type":"Feature","properties":{"codesPostaux":["10400"],"population":59,"nom":"Bouy-sur-Orvin","code":"10057"},"geometry":{"type":"Point","coordinates":[3.4936633333333336,48.41738371794871]}}]}