{"type":"FeatureCollection","features":[{"type":"Feature","properties":{"codesPostaux":["10500"],"population":2950,"nom":"Brienne-le-Ch\u00e2teau","code":"10064"},"geometry":{"type":"Point","coordinates":[4.52568024390244,48.39433813008131]}}]}