{"type":"FeatureCollection","features":[{"type":"Feature","properties":{"codesPostaux":["10110"],"population":143,"nom":"Buxeuil","code":"10068"},"geometry":{"type":"Point","coordinates":[4.4051665168539325,48.05400056179774]}}]}