{"type":"FeatureCollection","features":[{"type":"Feature","properties":{"codesPostaux":["10600"],"population":12634,"nom":"La Chapelle-Saint-Luc","code":"10081"},"geometry":{"type":"Point","coordinates":[4.047702444444443,48.32313766666666]}}]}