{"type":"FeatureCollection","features":[{"type":"Feature","properties":{"codesPostaux":["10110"],"population":120,"nom":"Chauffour-l\u00e8s-Bailly","code":"10092"},"geometry":{"type":"Point","coordinates":[4.319042970711293,48.187613472803335]}}]}