{"type":"FeatureCollection","features":[{"type":"Feature","properties":{"codesPostaux":["10330"],"population":597,"nom":"Chavanges","code":"10094"},"geometry":{"type":"Point","coordinates":[4.574141148325355,48.5184623444976]}}]}