{"type":"FeatureCollection","features":[{"type":"Feature","properties":{"codesPostaux":["10200"],"population":204,"nom":"Colomb\u00e9-la-Fosse","code":"10102"},"geometry":{"type":"Point","coordinates":[4.787411120689657,48.26929663793104]}}]}