{"type":"FeatureCollection","features":[{"type":"Feature","properties":{"codesPostaux":["10360"],"population":191,"nom":"Cunfin","code":"10119"},"geometry":{"type":"Point","coordinates":[4.667753802816902,48.041048380281694]}}]}