{"type":"FeatureCollection","features":[{"type":"Feature","properties":{"codesPostaux":["10130"],"population":262,"nom":"Davrey","code":"10122"},"geometry":{"type":"Point","coordinates":[3.9561800000000016,48.050081496063]}}]}