{"type":"FeatureCollection","features":[{"type":"Feature","properties":{"codesPostaux":["10130"],"population":233,"nom":"Eaux-Puiseaux","code":"10133"},"geometry":{"type":"Point","coordinates":[3.8827545263157877,48.12027305263158]}}]}