{"type":"FeatureCollection","features":[{"type":"Feature","properties":{"codesPostaux":["10110"],"population":131,"nom":"\u00c9guilly-sous-Bois","code":"10136"},"geometry":{"type":"Point","coordinates":[4.543308873239436,48.132134507042245]}}]}