{"type":"FeatureCollection","features":[{"type":"Feature","properties":{"codesPostaux":["10400"],"population":647,"nom":"Fontaine-M\u00e2con","code":"10153"},"geometry":{"type":"Point","coordinates":[3.5064631249999993,48.45627708333333]}}]}