{"type":"FeatureCollection","features":[{"type":"Feature","properties":{"codesPostaux":["10100"],"population":208,"nom":"La Fosse-Corduan","code":"10157"},"geometry":{"type":"Point","coordinates":[3.657299210526315,48.44022315789475]}}]}