{"type":"FeatureCollection","features":[{"type":"Feature","properties":{"codesPostaux":["10280"],"population":885,"nom":"Fontaine-les-Gr\u00e8s","code":"10151"},"geometry":{"type":"Point","coordinates":[3.8982140384615387,48.418051153846164]}}]}