{"type":"FeatureCollection","features":[{"type":"Feature","properties":{"codesPostaux":["10190"],"population":676,"nom":"Fontvannes","code":"10156"},"geometry":{"type":"Point","coordinates":[3.875114933333333,48.27999053333333]}}]}