{"type":"FeatureCollection","features":[{"type":"Feature","properties":{"codesPostaux":["10110"],"population":88,"nom":"Fralignes","code":"10159"},"geometry":{"type":"Point","coordinates":[4.378464090909091,48.16361333333335]}}]}