{"type":"FeatureCollection","features":[{"type":"Feature","properties":{"codesPostaux":["10210"],"population":80,"nom":"Les Granges","code":"10168"},"geometry":{"type":"Point","coordinates":[4.062946842105263,48.05771631578947]}}]}