{"type":"FeatureCollection","features":[{"type":"Feature","properties":{"codesPostaux":["10270"],"population":257,"nom":"Fresnoy-le-Ch\u00e2teau","code":"10162"},"geometry":{"type":"Point","coordinates":[4.2389068711656455,48.22737374233128]}}]}