{"type":"FeatureCollection","features":[{"type":"Feature","properties":{"codesPostaux":["10700"],"population":174,"nom":"Herbisse","code":"10172"},"geometry":{"type":"Point","coordinates":[4.123003015873017,48.61337857142857]}}]}