{"type":"FeatureCollection","features":[{"type":"Feature","properties":{"codesPostaux":["10240"],"population":174,"nom":"Isle-Aubigny","code":"10174"},"geometry":{"type":"Point","coordinates":[4.264553550000001,48.52995004999998]}}]}