{"type":"FeatureCollection","features":[{"type":"Feature","properties":{"codesPostaux":["10210"],"population":254,"nom":"Lantages","code":"10188"},"geometry":{"type":"Point","coordinates":[4.212729945945944,48.07949232432432]}}]}