{"type":"FeatureCollection","features":[{"type":"Feature","properties":{"codesPostaux":["10270"],"population":516,"nom":"Laubressel","code":"10190"},"geometry":{"type":"Point","coordinates":[4.231671666666666,48.299114880952374]}}]}