{"type":"FeatureCollection","features":[{"type":"Feature","properties":{"codesPostaux":["10230"],"population":1712,"nom":"Mailly-le-Camp","code":"10216"},"geometry":{"type":"Point","coordinates":[4.194725474452553,48.674763065693426]}}]}