{"type":"FeatureCollection","features":[{"type":"Feature","properties":{"codesPostaux":["10240"],"population":59,"nom":"Mesnil-Lettre","code":"10236"},"geometry":{"type":"Point","coordinates":[4.265303214285714,48.46675964285713]}}]}