{"type":"FeatureCollection","features":[{"type":"Feature","properties":{"codesPostaux":["10130"],"population":138,"nom":"Montfey","code":"10247"},"geometry":{"type":"Point","coordinates":[3.869604041095889,48.064796506849326]}}]}