{"type":"FeatureCollection","features":[{"type":"Feature","properties":{"codesPostaux":["10200"],"population":178,"nom":"Meurville","code":"10242"},"geometry":{"type":"Point","coordinates":[4.616876484848482,48.20367193939395]}}]}