{"type":"FeatureCollection","features":[{"type":"Feature","properties":{"codesPostaux":["10250"],"population":284,"nom":"Plaines-Saint-Lange","code":"10288"},"geometry":{"type":"Point","coordinates":[4.4809138613861395,47.995866435643556]}}]}