{"type":"FeatureCollection","features":[{"type":"Feature","properties":{"codesPostaux":["10400"],"population":168,"nom":"Plessis-Barbuise","code":"10291"},"geometry":{"type":"Point","coordinates":[3.580170945945947,48.56904689189188]}}]}