{"type":"FeatureCollection","features":[{"type":"Feature","properties":{"codesPostaux":["10500"],"population":226,"nom":"Rosnay-l'H\u00f4pital","code":"10326"},"geometry":{"type":"Point","coordinates":[4.503415200000001,48.4580347]}}]}