{"type":"FeatureCollection","features":[{"type":"Feature","properties":{"codesPostaux":["10180"],"population":410,"nom":"Saint-Beno\u00eet-sur-Seine","code":"10336"},"geometry":{"type":"Point","coordinates":[4.03551738095238,48.371087142857135]}}]}