{"type":"FeatureCollection","features":[{"type":"Feature","properties":{"codesPostaux":["10260"],"population":505,"nom":"Rumilly-l\u00e8s-Vaudes","code":"10331"},"geometry":{"type":"Point","coordinates":[4.199634888888888,48.12603822222223]}}]}