{"type":"FeatureCollection","features":[{"type":"Feature","properties":{"codesPostaux":["10800"],"population":783,"nom":"Saint-L\u00e9ger-pr\u00e8s-Troyes","code":"10344"},"geometry":{"type":"Point","coordinates":[4.072421711711713,48.23934117117117]}}]}