{"type":"FeatureCollection","features":[{"type":"Feature","properties":{"codesPostaux":["10800"],"population":6904,"nom":"Saint-Julien-les-Villas","code":"10343"},"geometry":{"type":"Point","coordinates":[4.106879855072463,48.27438536231883]}}]}