{"type":"FeatureCollection","features":[{"type":"Feature","properties":{"codesPostaux":["10100"],"population":218,"nom":"Saint-Loup-de-Buffigny","code":"10347"},"geometry":{"type":"Point","coordinates":[3.6270796470588245,48.442194470588234]}}]}