{"type":"FeatureCollection","features":[{"type":"Feature","properties":{"codesPostaux":["10100"],"population":363,"nom":"Saint-Martin-de-Bossenay","code":"10351"},"geometry":{"type":"Point","coordinates":[3.679894900000002,48.44299780000002]}}]}