{"type":"FeatureCollection","features":[{"type":"Feature","properties":{"codesPostaux":["10410"],"population":3068,"nom":"Saint-Parres-aux-Tertres","code":"10357"},"geometry":{"type":"Point","coordinates":[4.125298549618321,48.290549007633594]}}]}