{"type":"FeatureCollection","features":[{"type":"Feature","properties":{"codesPostaux":["10400"],"population":64,"nom":"Saint-Nicolas-la-Chapelle","code":"10355"},"geometry":{"type":"Point","coordinates":[3.480444086956522,48.51937052173915]}}]}