{"type":"FeatureCollection","features":[{"type":"Feature","properties":{"codesPostaux":["10400"],"population":693,"nom":"La Saulsotte","code":"10367"},"geometry":{"type":"Point","coordinates":[3.510688534482758,48.53774267241377]}}]}