{"type":"FeatureCollection","features":[{"type":"Feature","properties":{"codesPostaux":["10200"],"population":144,"nom":"Thil","code":"10377"},"geometry":{"type":"Point","coordinates":[4.7921271710526305,48.342514342105275]}}]}