{"type":"FeatureCollection","features":[{"type":"Feature","properties":{"codesPostaux":["10700"],"population":447,"nom":"Torcy-le-Grand","code":"10379"},"geometry":{"type":"Point","coordinates":[4.168346973684211,48.52898421052631]}}]}