{"type":"FeatureCollection","features":[{"type":"Feature","properties":{"codesPostaux":["10200"],"population":348,"nom":"Soulaines-Dhuys","code":"10372"},"geometry":{"type":"Point","coordinates":[4.707291776649745,48.38047969543146]}}]}