{"type":"FeatureCollection","features":[{"type":"Feature","properties":{"codesPostaux":["10000"],"population":59671,"nom":"Troyes","code":"10387"},"geometry":{"type":"Point","coordinates":[4.080480509554141,48.297910254777086]}}]}