{"type":"FeatureCollection","features":[{"type":"Feature","properties":{"codesPostaux":["10240"],"population":75,"nom":"Vaucogne","code":"10398"},"geometry":{"type":"Point","coordinates":[4.342179518072289,48.532034337349415]}}]}