{"type":"FeatureCollection","features":[{"type":"Feature","properties":{"codesPostaux":["10210"],"population":321,"nom":"Vanlay","code":"10395"},"geometry":{"type":"Point","coordinates":[4.021002429906544,48.02282551401873]}}]}