{"type":"FeatureCollection","features":[{"type":"Feature","properties":{"codesPostaux":["10170"],"population":381,"nom":"Vallant-Saint-Georges","code":"10392"},"geometry":{"type":"Point","coordinates":[3.9024226206896557,48.46362144827588]}}]}