{"type":"FeatureCollection","features":[{"type":"Feature","properties":{"codesPostaux":["10380"],"population":115,"nom":"Vi\u00e2pres-le-Petit","code":"10408"},"geometry":{"type":"Point","coordinates":[4.0480120253164555,48.57268721518987]}}]}