{"type":"FeatureCollection","features":[{"type":"Feature","properties":{"codesPostaux":["10140"],"population":2384,"nom":"Vendeuvre-sur-Barse","code":"10401"},"geometry":{"type":"Point","coordinates":[4.459669333333335,48.24420964705881]}}]}