{"type":"FeatureCollection","features":[{"type":"Feature","properties":{"codesPostaux":["10370"],"population":2755,"nom":"Villenauxe-la-Grande","code":"10420"},"geometry":{"type":"Point","coordinates":[3.5550915730337076,48.600875842696624]}}]}