{"type":"FeatureCollection","features":[{"type":"Feature","properties":{"codesPostaux":["10110"],"population":234,"nom":"Ville-sur-Arce","code":"10427"},"geometry":{"type":"Point","coordinates":[4.448600353982301,48.1089885840708]}}]}