{"type":"FeatureCollection","features":[{"type":"Feature","properties":{"codesPostaux":["10260"],"population":629,"nom":"Virey-sous-Bar","code":"10437"},"geometry":{"type":"Point","coordinates":[4.311450204081631,48.13373224489796]}}]}