{"type":"FeatureCollection","features":[{"type":"Feature","properties":{"codesPostaux":["10800"],"population":178,"nom":"Villy-le-Mar\u00e9chal","code":"10435"},"geometry":{"type":"Point","coordinates":[4.075123749999999,48.190156071428575]}}]}