{"type":"FeatureCollection","features":[{"type":"Feature","properties":{"codesPostaux":["11200"],"population":365,"nom":"Argens-Minervois","code":"11013"},"geometry":{"type":"Point","coordinates":[2.770328837209302,43.24474511627907]}}]}