{"type":"FeatureCollection","features":[{"type":"Feature","properties":{"codesPostaux":["11120"],"population":2028,"nom":"Argeliers","code":"11012"},"geometry":{"type":"Point","coordinates":[2.9149966101694913,43.313394576271186]}}]}