{"type":"FeatureCollection","features":[{"type":"Feature","properties":{"codesPostaux":["11580"],"population":68,"nom":"Belcastel-et-Buc","code":"11029"},"geometry":{"type":"Point","coordinates":[2.35178359223301,43.03031980582524]}}]}