{"type":"FeatureCollection","features":[{"type":"Feature","properties":{"codesPostaux":["11410"],"population":172,"nom":"Baraigne","code":"11026"},"geometry":{"type":"Point","coordinates":[1.8210922727272725,43.332072272727274]}}]}