{"type":"FeatureCollection","features":[{"type":"Feature","properties":{"codesPostaux":["11500"],"population":289,"nom":"Belvianes-et-Cavirac","code":"11035"},"geometry":{"type":"Point","coordinates":[2.20965690140845,42.84956112676058]}}]}