{"type":"FeatureCollection","features":[{"type":"Feature","properties":{"codesPostaux":["11000"],"population":878,"nom":"Berriac","code":"11037"},"geometry":{"type":"Point","coordinates":[2.4061338181818184,43.21314636363636]}}]}