{"type":"FeatureCollection","features":[{"type":"Feature","properties":{"codesPostaux":["11200"],"population":1514,"nom":"Bizanet","code":"11040"},"geometry":{"type":"Point","coordinates":[2.8604486263736266,43.14184197802198]}}]}