{"type":"FeatureCollection","features":[{"type":"Feature","properties":{"codesPostaux":["11400"],"population":264,"nom":"Les Brunels","code":"11054"},"geometry":{"type":"Point","coordinates":[2.0472839593908643,43.410507208121835]}}]}