{"type":"FeatureCollection","features":[{"type":"Feature","properties":{"codesPostaux":["11240"],"population":265,"nom":"Cailhau","code":"11058"},"geometry":{"type":"Point","coordinates":[2.1315335483870967,43.145557580645146]}}]}