{"type":"FeatureCollection","features":[{"type":"Feature","properties":{"codesPostaux":["11200"],"population":1631,"nom":"Canet","code":"11067"},"geometry":{"type":"Point","coordinates":[2.8259269491525427,43.23207644067797]}}]}