{"type":"FeatureCollection","features":[{"type":"Feature","properties":{"codesPostaux":["11270"],"population":210,"nom":"La Cassaigne","code":"11072"},"geometry":{"type":"Point","coordinates":[1.9885621238938052,43.194619115044226]}}]}