{"type":"FeatureCollection","features":[{"type":"Feature","properties":{"codesPostaux":["11160"],"population":1672,"nom":"Caunes-Minervois","code":"11081"},"geometry":{"type":"Point","coordinates":[2.520707801418439,43.33564432624116]}}]}