{"type":"FeatureCollection","features":[{"type":"Feature","properties":{"codesPostaux":["11170"],"population":395,"nom":"Cenne-Monesti\u00e9s","code":"11089"},"geometry":{"type":"Point","coordinates":[2.129849714285714,43.320426190476184]}}]}