{"type":"FeatureCollection","features":[{"type":"Feature","properties":{"codesPostaux":["11190"],"population":1145,"nom":"Couiza","code":"11103"},"geometry":{"type":"Point","coordinates":[2.2697628057553945,42.93459223021583]}}]}