{"type":"FeatureCollection","features":[{"type":"Feature","properties":{"codesPostaux":["11410"],"population":35,"nom":"Cumi\u00e8s","code":"11114"},"geometry":{"type":"Point","coordinates":[1.8313811594202904,43.29976000000001]}}]}