{"type":"FeatureCollection","features":[{"type":"Feature","properties":{"codesPostaux":["11140"],"population":83,"nom":"Escouloubre","code":"11127"},"geometry":{"type":"Point","coordinates":[2.1223414465408807,42.73157767295599]}}]}