{"type":"FeatureCollection","features":[{"type":"Feature","properties":{"codesPostaux":["11270"],"population":209,"nom":"La Force","code":"11153"},"geometry":{"type":"Point","coordinates":[2.084316708860759,43.197286075949364]}}]}