{"type":"FeatureCollection","features":[{"type":"Feature","properties":{"codesPostaux":["11360"],"population":153,"nom":"Fontjoncouse","code":"11152"},"geometry":{"type":"Point","coordinates":[2.77128,43.03788930232558]}}]}