{"type":"FeatureCollection","features":[{"type":"Feature","properties":{"codesPostaux":["11190"],"population":66,"nom":"Fourtou","code":"11155"},"geometry":{"type":"Point","coordinates":[2.4401015999999993,42.91270529999999]}}]}