{"type":"FeatureCollection","features":[{"type":"Feature","properties":{"codesPostaux":["11360"],"population":234,"nom":"Fraiss\u00e9-des-Corbi\u00e8res","code":"11157"},"geometry":{"type":"Point","coordinates":[2.857772820512821,42.96518102564102]}}]}