{"type":"FeatureCollection","features":[{"type":"Feature","properties":{"codesPostaux":["11220"],"population":59,"nom":"Jonqui\u00e8res","code":"11176"},"geometry":{"type":"Point","coordinates":[2.7297259210526317,43.032216842105264]}}]}