{"type":"FeatureCollection","features":[{"type":"Feature","properties":{"codesPostaux":["11220"],"population":558,"nom":"Lagrasse","code":"11185"},"geometry":{"type":"Point","coordinates":[2.606273217821779,43.1035887128713]}}]}