{"type":"FeatureCollection","features":[{"type":"Feature","properties":{"codesPostaux":["11420"],"population":91,"nom":"Lafage","code":"11184"},"geometry":{"type":"Point","coordinates":[1.866507933884297,43.16667785123966]}}]}