{"type":"FeatureCollection","features":[{"type":"Feature","properties":{"codesPostaux":["11700"],"population":1118,"nom":"La Redorte","code":"11190"},"geometry":{"type":"Point","coordinates":[2.651144642857144,43.24645404761905]}}]}