{"type":"FeatureCollection","features":[{"type":"Feature","properties":{"codesPostaux":["11270"],"population":176,"nom":"Laurac","code":"11196"},"geometry":{"type":"Point","coordinates":[1.969238461538462,43.23209247863245]}}]}