{"type":"FeatureCollection","features":[{"type":"Feature","properties":{"codesPostaux":["11190"],"population":222,"nom":"Luc-sur-Aude","code":"11209"},"geometry":{"type":"Point","coordinates":[2.2752125,42.96398361111111]}}]}