{"type":"FeatureCollection","features":[{"type":"Feature","properties":{"codesPostaux":["11380"],"population":191,"nom":"Mas-Cabard\u00e8s","code":"11222"},"geometry":{"type":"Point","coordinates":[2.3532349514563102,43.40033271844662]}}]}