{"type":"FeatureCollection","features":[{"type":"Feature","properties":{"codesPostaux":["11390"],"population":269,"nom":"Les Martys","code":"11221"},"geometry":{"type":"Point","coordinates":[2.311288523489934,43.41686664429531]}}]}