{"type":"FeatureCollection","features":[{"type":"Feature","properties":{"codesPostaux":["11580"],"population":67,"nom":"Miss\u00e8gre","code":"11235"},"geometry":{"type":"Point","coordinates":[2.3745862500000006,43.00004357142859]}}]}