{"type":"FeatureCollection","features":[{"type":"Feature","properties":{"codesPostaux":["11250"],"population":166,"nom":"Montclar","code":"11242"},"geometry":{"type":"Point","coordinates":[2.240840652173912,43.13874173913044]}}]}