{"type":"FeatureCollection","features":[{"type":"Feature","properties":{"codesPostaux":["11700"],"population":317,"nom":"Montbrun-des-Corbi\u00e8res","code":"11241"},"geometry":{"type":"Point","coordinates":[2.677269,43.20252283333333]}}]}