{"type":"FeatureCollection","features":[{"type":"Feature","properties":{"codesPostaux":["11120"],"population":1823,"nom":"Moussan","code":"11258"},"geometry":{"type":"Point","coordinates":[2.958211495327102,43.23182607476634]}}]}