{"type":"FeatureCollection","features":[{"type":"Feature","properties":{"codesPostaux":["11170"],"population":854,"nom":"Montolieu","code":"11253"},"geometry":{"type":"Point","coordinates":[2.2086477241379305,43.31925220689656]}}]}