{"type":"FeatureCollection","features":[{"type":"Feature","properties":{"codesPostaux":["11140"],"population":19,"nom":"Niort-de-Sault","code":"11265"},"geometry":{"type":"Point","coordinates":[1.998272785714287,42.787897499999985]}}]}