{"type":"FeatureCollection","features":[{"type":"Feature","properties":{"codesPostaux":["11300"],"population":336,"nom":"Pauligne","code":"11274"},"geometry":{"type":"Point","coordinates":[2.148686896551723,43.07477551724137]}}]}