{"type":"FeatureCollection","features":[{"type":"Feature","properties":{"codesPostaux":["11400"],"population":487,"nom":"Peyrens","code":"11284"},"geometry":{"type":"Point","coordinates":[1.9610927499999988,43.361801750000005]}}]}