{"type":"FeatureCollection","features":[{"type":"Feature","properties":{"codesPostaux":["11300"],"population":1012,"nom":"Pieusse","code":"11289"},"geometry":{"type":"Point","coordinates":[2.2578085849056597,43.08013150943395]}}]}