{"type":"FeatureCollection","features":[{"type":"Feature","properties":{"codesPostaux":["11420"],"population":76,"nom":"Peyrefitte-sur-l'Hers","code":"11283"},"geometry":{"type":"Point","coordinates":[1.8136618518518515,43.249832222222224]}}]}