{"type":"FeatureCollection","features":[{"type":"Feature","properties":{"codesPostaux":["11190"],"population":58,"nom":"Rennes-le-Ch\u00e2teau","code":"11309"},"geometry":{"type":"Point","coordinates":[2.2777860465116277,42.91489383720929]}}]}