{"type":"FeatureCollection","features":[{"type":"Feature","properties":{"codesPostaux":["11230"],"population":521,"nom":"Puivert","code":"11303"},"geometry":{"type":"Point","coordinates":[2.066509962825279,42.91346631970259]}}]}