{"type":"FeatureCollection","features":[{"type":"Feature","properties":{"codesPostaux":["11160"],"population":2029,"nom":"Rieux-Minervois","code":"11315"},"geometry":{"type":"Point","coordinates":[2.591525599999999,43.280276640000004]}}]}