{"type":"FeatureCollection","features":[{"type":"Feature","properties":{"codesPostaux":["11270"],"population":108,"nom":"Ribouisse","code":"11312"},"geometry":{"type":"Point","coordinates":[1.904453124999999,43.169480703125004]}}]}