{"type":"FeatureCollection","features":[{"type":"Feature","properties":{"codesPostaux":["11380"],"population":68,"nom":"Roquef\u00e8re","code":"11319"},"geometry":{"type":"Point","coordinates":[2.378403698630136,43.39299849315067]}}]}