{"type":"FeatureCollection","features":[{"type":"Feature","properties":{"codesPostaux":["11220"],"population":88,"nom":"Rieux-en-Val","code":"11314"},"geometry":{"type":"Point","coordinates":[2.5449139473684212,43.08341815789474]}}]}