{"type":"FeatureCollection","features":[{"type":"Feature","properties":{"codesPostaux":["11400"],"population":306,"nom":"Ricaud","code":"11313"},"geometry":{"type":"Point","coordinates":[1.8995178787878793,43.35019984848484]}}]}