{"type":"FeatureCollection","features":[{"type":"Feature","properties":{"codesPostaux":["11250"],"population":430,"nom":"Rouffiac-d'Aude","code":"11325"},"geometry":{"type":"Point","coordinates":[2.278524878048781,43.12738914634147]}}]}