{"type":"FeatureCollection","features":[{"type":"Feature","properties":{"codesPostaux":["11800"],"population":502,"nom":"Rustiques","code":"11330"},"geometry":{"type":"Point","coordinates":[2.4781789062499997,43.215226875000006]}}]}