{"type":"FeatureCollection","features":[{"type":"Feature","properties":{"codesPostaux":["11310"],"population":521,"nom":"Saint-Denis","code":"11339"},"geometry":{"type":"Point","coordinates":[2.217978830409357,43.356494853801166]}}]}