{"type":"FeatureCollection","features":[{"type":"Feature","properties":{"codesPostaux":["11260"],"population":111,"nom":"Saint-Jean-de-Paracol","code":"11346"},"geometry":{"type":"Point","coordinates":[2.1070304964538997,42.93598617021276]}}]}