{"type":"FeatureCollection","features":[{"type":"Feature","properties":{"codesPostaux":["11410"],"population":410,"nom":"Saint-Michel-de-Lan\u00e8s","code":"11359"},"geometry":{"type":"Point","coordinates":[1.7517291735537193,43.326121404958684]}}]}