{"type":"FeatureCollection","features":[{"type":"Feature","properties":{"codesPostaux":["11500"],"population":51,"nom":"Saint-Just-et-le-B\u00e9zu","code":"11350"},"geometry":{"type":"Point","coordinates":[2.2862318867924527,42.87270433962264]}}]}