{"type":"FeatureCollection","features":[{"type":"Feature","properties":{"codesPostaux":["11300"],"population":371,"nom":"Saint-Martin-de-Villereglan","code":"11355"},"geometry":{"type":"Point","coordinates":[2.207835339805826,43.10392514563107]}}]}