{"type":"FeatureCollection","features":[{"type":"Feature","properties":{"codesPostaux":["11220"],"population":177,"nom":"Saint-Pierre-des-Champs","code":"11363"},"geometry":{"type":"Point","coordinates":[2.61308625,43.05441642857142]}}]}