{"type":"FeatureCollection","features":[{"type":"Feature","properties":{"codesPostaux":["11310"],"population":922,"nom":"Saissac","code":"11367"},"geometry":{"type":"Point","coordinates":[2.1601509422492406,43.36564796352584]}}]}