{"type":"FeatureCollection","features":[{"type":"Feature","properties":{"codesPostaux":["11220"],"population":92,"nom":"Taurize","code":"11387"},"geometry":{"type":"Point","coordinates":[2.5075338596491226,43.06576385964913]}}]}