{"type":"FeatureCollection","features":[{"type":"Feature","properties":{"codesPostaux":["11190"],"population":81,"nom":"Sougraigne","code":"11381"},"geometry":{"type":"Point","coordinates":[2.3661830555555547,42.90784972222224]}}]}