{"type":"FeatureCollection","features":[{"type":"Feature","properties":{"codesPostaux":["11160"],"population":503,"nom":"Trausse","code":"11396"},"geometry":{"type":"Point","coordinates":[2.5665782022471904,43.31643235955053]}}]}