{"type":"FeatureCollection","features":[{"type":"Feature","properties":{"codesPostaux":["11300"],"population":126,"nom":"Tourreilles","code":"11394"},"geometry":{"type":"Point","coordinates":[2.1669129629629627,43.02158024691357]}}]}