{"type":"FeatureCollection","features":[{"type":"Feature","properties":{"codesPostaux":["11610"],"population":882,"nom":"Ventenac-Cabard\u00e8s","code":"11404"},"geometry":{"type":"Point","coordinates":[2.2811960162601617,43.26845626016259]}}]}