{"type":"FeatureCollection","features":[{"type":"Feature","properties":{"codesPostaux":["11600"],"population":1018,"nom":"Villalier","code":"11410"},"geometry":{"type":"Point","coordinates":[2.4193284999999998,43.252155900000005]}}]}