{"type":"FeatureCollection","features":[{"type":"Feature","properties":{"codesPostaux":["11300"],"population":107,"nom":"Villarzel-du-Raz\u00e8s","code":"11417"},"geometry":{"type":"Point","coordinates":[2.2051439999999993,43.14246151515152]}}]}