{"type":"FeatureCollection","features":[{"type":"Feature","properties":{"codesPostaux":["11310"],"population":280,"nom":"Villemagne","code":"11428"},"geometry":{"type":"Point","coordinates":[2.1099548502994026,43.36689209580835]}}]}