{"type":"FeatureCollection","features":[{"type":"Feature","properties":{"codesPostaux":["11570"],"population":162,"nom":"Villefloure","code":"11423"},"geometry":{"type":"Point","coordinates":[2.3930553459119492,43.13010528301887]}}]}