{"type":"FeatureCollection","features":[{"type":"Feature","properties":{"codesPostaux":["11250"],"population":125,"nom":"Villebazy","code":"11420"},"geometry":{"type":"Point","coordinates":[2.335497050359713,43.05671021582736]}}]}