{"type":"FeatureCollection","features":[{"type":"Feature","properties":{"codesPostaux":["11400"],"population":1241,"nom":"Villeneuve-la-Comptal","code":"11430"},"geometry":{"type":"Point","coordinates":[1.9210087662337658,43.28430311688311]}}]}