{"type":"FeatureCollection","features":[{"type":"Feature","properties":{"codesPostaux":["11330"],"population":140,"nom":"Villerouge-Termen\u00e8s","code":"11435"},"geometry":{"type":"Point","coordinates":[2.6233765517241383,43.00223344827587]}}]}