{"type":"FeatureCollection","features":[{"type":"Feature","properties":{"codesPostaux":["11290"],"population":263,"nom":"Villeneuve-l\u00e8s-Montr\u00e9al","code":"11432"},"geometry":{"type":"Point","coordinates":[2.1114994736842103,43.179285964912275]}}]}