{"type":"FeatureCollection","features":[{"type":"Feature","properties":{"codesPostaux":["11150"],"population":369,"nom":"Villesiscle","code":"11438"},"geometry":{"type":"Point","coordinates":[2.0906106153846156,43.22898307692308]}}]}