{"type":"FeatureCollection","features":[{"type":"Feature","properties":{"codesPostaux":["12260"],"population":180,"nom":"Ambeyrac","code":"12007"},"geometry":{"type":"Point","coordinates":[1.9349198630136988,44.493827534246556]}}]}