{"type":"FeatureCollection","features":[{"type":"Feature","properties":{"codesPostaux":["12300"],"population":533,"nom":"Boisse-Penchot","code":"12028"},"geometry":{"type":"Point","coordinates":[2.211329090909091,44.57808469696969]}}]}