{"type":"FeatureCollection","features":[{"type":"Feature","properties":{"codesPostaux":["12200","12240"],"population":1638,"nom":"Le Bas S\u00e9gala","code":"12021"},"geometry":{"type":"Point","coordinates":[2.1345837896494153,44.30473377295495]}}]}