{"type":"FeatureCollection","features":[{"type":"Feature","properties":{"codesPostaux":["12700"],"population":4516,"nom":"Capdenac-Gare","code":"12052"},"geometry":{"type":"Point","coordinates":[2.0695429411764703,44.5568158235294]}}]}