{"type":"FeatureCollection","features":[{"type":"Feature","properties":{"codesPostaux":["12800"],"population":127,"nom":"Castelmary","code":"12060"},"geometry":{"type":"Point","coordinates":[2.242230343137254,44.17469808823529]}}]}