{"type":"FeatureCollection","features":[{"type":"Feature","properties":{"codesPostaux":["12120"],"population":526,"nom":"Centr\u00e8s","code":"12065"},"geometry":{"type":"Point","coordinates":[2.4380769665809776,44.16233825192804]}}]}