{"type":"FeatureCollection","features":[{"type":"Feature","properties":{"codesPostaux":["12470"],"population":307,"nom":"Condom-d'Aubrac","code":"12074"},"geometry":{"type":"Point","coordinates":[2.876559263157892,44.60334597894734]}}]}