{"type":"FeatureCollection","features":[{"type":"Feature","properties":{"codesPostaux":["12520"],"population":523,"nom":"Compeyre","code":"12070"},"geometry":{"type":"Point","coordinates":[3.101901120689655,44.17836689655173]}}]}