{"type":"FeatureCollection","features":[{"type":"Feature","properties":{"codesPostaux":["12190"],"population":504,"nom":"Coubisou","code":"12079"},"geometry":{"type":"Point","coordinates":[2.7377268209876564,44.58402512345677]}}]}