{"type":"FeatureCollection","features":[{"type":"Feature","properties":{"codesPostaux":["12640"],"population":324,"nom":"La Cresse","code":"12086"},"geometry":{"type":"Point","coordinates":[3.1639185606060614,44.169260833333354]}}]}