{"type":"FeatureCollection","features":[{"type":"Feature","properties":{"codesPostaux":["12300"],"population":1058,"nom":"Flagnac","code":"12101"},"geometry":{"type":"Point","coordinates":[2.2699635436893213,44.58972344660196]}}]}