{"type":"FeatureCollection","features":[{"type":"Feature","properties":{"codesPostaux":["12220"],"population":357,"nom":"Galgan","code":"12108"},"geometry":{"type":"Point","coordinates":[2.1819288799999996,44.505135080000045]}}]}