{"type":"FeatureCollection","features":[{"type":"Feature","properties":{"codesPostaux":["12600"],"population":464,"nom":"Lacroix-Barrez","code":"12118"},"geometry":{"type":"Point","coordinates":[2.639125015384617,44.778081200000024]}}]}