{"type":"FeatureCollection","features":[{"type":"Feature","properties":{"codesPostaux":["12350"],"population":730,"nom":"Lanu\u00e9jouls","code":"12121"},"geometry":{"type":"Point","coordinates":[2.1583860563380273,44.42264373239437]}}]}