{"type":"FeatureCollection","features":[{"type":"Feature","properties":{"codesPostaux":["12740"],"population":1476,"nom":"La Loubi\u00e8re","code":"12131"},"geometry":{"type":"Point","coordinates":[2.6551541960784313,44.38388772549021]}}]}