{"type":"FeatureCollection","features":[{"type":"Feature","properties":{"codesPostaux":["12160"],"population":763,"nom":"Manhac","code":"12137"},"geometry":{"type":"Point","coordinates":[2.4816177000000015,44.25614570000004]}}]}