{"type":"FeatureCollection","features":[{"type":"Feature","properties":{"codesPostaux":["12000"],"population":2126,"nom":"Le Monast\u00e8re","code":"12146"},"geometry":{"type":"Point","coordinates":[2.586777042253522,44.33027992957747]}}]}