{"type":"FeatureCollection","features":[{"type":"Feature","properties":{"codesPostaux":["12200"],"population":1002,"nom":"Martiel","code":"12140"},"geometry":{"type":"Point","coordinates":[1.916199011406844,44.37541832699617]}}]}