{"type":"FeatureCollection","features":[{"type":"Feature","properties":{"codesPostaux":["12550"],"population":169,"nom":"Montclar","code":"12149"},"geometry":{"type":"Point","coordinates":[2.6276511111111107,43.98242457777778]}}]}