{"type":"FeatureCollection","features":[{"type":"Feature","properties":{"codesPostaux":["12380"],"population":124,"nom":"Montfranc","code":"12152"},"geometry":{"type":"Point","coordinates":[2.5830431967213117,43.84034352459015]}}]}