{"type":"FeatureCollection","features":[{"type":"Feature","properties":{"codesPostaux":["12800"],"population":1961,"nom":"Naucelle","code":"12169"},"geometry":{"type":"Point","coordinates":[2.3437102521008413,44.19148710084032]}}]}