{"type":"FeatureCollection","features":[{"type":"Feature","properties":{"codesPostaux":["12800"],"population":826,"nom":"Quins","code":"12194"},"geometry":{"type":"Point","coordinates":[2.370339745042493,44.23264385269123]}}]}