{"type":"FeatureCollection","features":[{"type":"Feature","properties":{"codesPostaux":["12500"],"population":1329,"nom":"Saint-C\u00f4me-d'Olt","code":"12216"},"geometry":{"type":"Point","coordinates":[2.824949444444444,44.52574118055557]}}]}