{"type":"FeatureCollection","features":[{"type":"Feature","properties":{"codesPostaux":["12400"],"population":226,"nom":"Saint-F\u00e9lix-de-Sorgues","code":"12222"},"geometry":{"type":"Point","coordinates":[2.98392588607595,43.87443981012658]}}]}