{"type":"FeatureCollection","features":[{"type":"Feature","properties":{"codesPostaux":["12230"],"population":653,"nom":"Saint-Jean-du-Bruel","code":"12231"},"geometry":{"type":"Point","coordinates":[3.3781692391304357,44.025201630434786]}}]}