{"type":"FeatureCollection","features":[{"type":"Feature","properties":{"codesPostaux":["12620"],"population":157,"nom":"Saint-Laurent-de-L\u00e9v\u00e9zou","code":"12236"},"geometry":{"type":"Point","coordinates":[2.947013246753247,44.20600385281389]}}]}