{"type":"FeatureCollection","features":[{"type":"Feature","properties":{"codesPostaux":["12370"],"population":234,"nom":"Saint-Sever-du-Moustier","code":"12249"},"geometry":{"type":"Point","coordinates":[2.698131379310345,43.77032109195401]}}]}