{"type":"FeatureCollection","features":[{"type":"Feature","properties":{"codesPostaux":["12850"],"population":1731,"nom":"Sainte-Radegonde","code":"12241"},"geometry":{"type":"Point","coordinates":[2.6337483060109284,44.32551213114754]}}]}