{"type":"FeatureCollection","features":[{"type":"Feature","properties":{"codesPostaux":["12490"],"population":816,"nom":"Saint-Rome-de-Cernon","code":"12243"},"geometry":{"type":"Point","coordinates":[2.979324409448819,44.00989326771654]}}]}