{"type":"FeatureCollection","features":[{"type":"Feature","properties":{"codesPostaux":["12380"],"population":637,"nom":"Saint-Sernin-sur-Rance","code":"12248"},"geometry":{"type":"Point","coordinates":[2.6231813989637303,43.87953119170982]}}]}