{"type":"FeatureCollection","features":[{"type":"Feature","properties":{"codesPostaux":["12400"],"population":1168,"nom":"Vabres-l'Abbaye","code":"12286"},"geometry":{"type":"Point","coordinates":[2.8076410040160655,43.91887682730925]}}]}