{"type":"FeatureCollection","features":[{"type":"Feature","properties":{"codesPostaux":["12600"],"population":418,"nom":"Th\u00e9rondels","code":"12280"},"geometry":{"type":"Point","coordinates":[2.7366795907928383,44.89197869565219]}}]}