{"type":"FeatureCollection","features":[{"type":"Feature","properties":{"codesPostaux":["12520"],"population":433,"nom":"Verri\u00e8res","code":"12291"},"geometry":{"type":"Point","coordinates":[3.048163761467891,44.219541376146815]}}]}