{"type":"FeatureCollection","features":[{"type":"Feature","properties":{"codesPostaux":["12720"],"population":137,"nom":"Veyreau","code":"12293"},"geometry":{"type":"Point","coordinates":[3.292585776397514,44.182761397515534]}}]}