{"type":"FeatureCollection","features":[{"type":"Feature","properties":{"codesPostaux":["12310"],"population":253,"nom":"Vimenet","code":"12303"},"geometry":{"type":"Point","coordinates":[2.9199907373271907,44.39979276497699]}}]}