{"type":"FeatureCollection","features":[{"type":"Feature","properties":{"codesPostaux":["12110"],"population":1320,"nom":"Viviez","code":"12305"},"geometry":{"type":"Point","coordinates":[2.2184626086956536,44.555227652173926]}}]}