{"type":"FeatureCollection","features":[{"type":"Feature","properties":{"codesPostaux":["13600"],"population":4282,"nom":"Ceyreste","code":"13023"},"geometry":{"type":"Point","coordinates":[5.637821570247934,43.21682223140495]}}]}