{"type":"FeatureCollection","features":[{"type":"Feature","properties":{"codesPostaux":["13220"],"population":13792,"nom":"Ch\u00e2teauneuf-les-Martigues","code":"13026"},"geometry":{"type":"Point","coordinates":[5.136474866666668,43.384010466666645]}}]}