{"type":"FeatureCollection","features":[{"type":"Feature","properties":{"codesPostaux":["13430"],"population":6724,"nom":"Eygui\u00e8res","code":"13035"},"geometry":{"type":"Point","coordinates":[5.0150726050420165,43.71855672268907]}}]}