{"type":"FeatureCollection","features":[{"type":"Feature","properties":{"codesPostaux":["13118","13800"],"population":42937,"nom":"Istres","code":"13047"},"geometry":{"type":"Point","coordinates":[4.983850436893204,43.52000111650485]}}]}