{"type":"FeatureCollection","features":[{"type":"Feature","properties":{"codesPostaux":["13650"],"population":3743,"nom":"Meyrargues","code":"13059"},"geometry":{"type":"Point","coordinates":[5.5366206249999985,43.610927013888904]}}]}