{"type":"FeatureCollection","features":[{"type":"Feature","properties":{"codesPostaux":["13520"],"population":1750,"nom":"Paradou","code":"13068"},"geometry":{"type":"Point","coordinates":[4.78140767123288,43.70735315068493]}}]}