{"type":"FeatureCollection","features":[{"type":"Feature","properties":{"codesPostaux":["13105"],"population":4563,"nom":"Mimet","code":"13062"},"geometry":{"type":"Point","coordinates":[5.501492170542638,43.4187642635659]}}]}