{"type":"FeatureCollection","features":[{"type":"Feature","properties":{"codesPostaux":["13660"],"population":3114,"nom":"Orgon","code":"13067"},"geometry":{"type":"Point","coordinates":[5.02218182795699,43.77948064516131]}}]}