{"type":"FeatureCollection","features":[{"type":"Feature","properties":{"codesPostaux":["13124"],"population":5431,"nom":"Peypin","code":"13073"},"geometry":{"type":"Point","coordinates":[5.573121074380168,43.38738371900826]}}]}