{"type":"FeatureCollection","features":[{"type":"Feature","properties":{"codesPostaux":["13170"],"population":20018,"nom":"Les Pennes-Mirabeau","code":"13071"},"geometry":{"type":"Point","coordinates":[5.319901038961042,43.40135688311687]}}]}