{"type":"FeatureCollection","features":[{"type":"Feature","properties":{"codesPostaux":["13870"],"population":4030,"nom":"Rognonas","code":"13083"},"geometry":{"type":"Point","coordinates":[4.79666596491228,43.89677877192982]}}]}