{"type":"FeatureCollection","features":[{"type":"Feature","properties":{"codesPostaux":["13760"],"population":5388,"nom":"Saint-Cannat","code":"13091"},"geometry":{"type":"Point","coordinates":[5.300404683544303,43.616997721518985]}}]}