{"type":"FeatureCollection","features":[{"type":"Feature","properties":{"codesPostaux":["14960"],"population":587,"nom":"Asnelles","code":"14022"},"geometry":{"type":"Point","coordinates":[-0.5845663999999998,49.332335199999996]}}]}