{"type":"FeatureCollection","features":[{"type":"Feature","properties":{"codesPostaux":["14260","14770"],"population":4761,"nom":"Les Monts d'Aunay","code":"14027"},"geometry":{"type":"Point","coordinates":[-0.644896725490196,48.985478372549025]}}]}