{"type":"FeatureCollection","features":[{"type":"Feature","properties":{"codesPostaux":["14340"],"population":235,"nom":"Auvillars","code":"14033"},"geometry":{"type":"Point","coordinates":[0.07238503401360548,49.19913081632654]}}]}