{"type":"FeatureCollection","features":[{"type":"Feature","properties":{"codesPostaux":["14610"],"population":1159,"nom":"Basly","code":"14044"},"geometry":{"type":"Point","coordinates":[-0.4285750793650794,49.27639349206346]}}]}