{"type":"FeatureCollection","features":[{"type":"Feature","properties":{"codesPostaux":["14990"],"population":2358,"nom":"Berni\u00e8res-sur-Mer","code":"14066"},"geometry":{"type":"Point","coordinates":[-0.4207155813953488,49.32037162790697]}}]}