{"type":"FeatureCollection","features":[{"type":"Feature","properties":{"codesPostaux":["14130"],"population":692,"nom":"Blangy-le-Ch\u00e2teau","code":"14077"},"geometry":{"type":"Point","coordinates":[0.28414396226415095,49.246849182389944]}}]}