{"type":"FeatureCollection","features":[{"type":"Feature","properties":{"codesPostaux":["14220"],"population":638,"nom":"Boulon","code":"14090"},"geometry":{"type":"Point","coordinates":[-0.3760056571428571,49.051604685714274]}}]}