{"type":"FeatureCollection","features":[{"type":"Feature","properties":{"codesPostaux":["14760"],"population":3894,"nom":"Bretteville-sur-Odon","code":"14101"},"geometry":{"type":"Point","coordinates":[-0.4182276136363637,49.168720795454554]}}]}