{"type":"FeatureCollection","features":[{"type":"Feature","properties":{"codesPostaux":["14130"],"population":169,"nom":"Le Br\u00e9vedent","code":"14104"},"geometry":{"type":"Point","coordinates":[0.295822602739726,49.228485753424664]}}]}