{"type":"FeatureCollection","features":[{"type":"Feature","properties":{"codesPostaux":["14610"],"population":1467,"nom":"Cambes-en-Plaine","code":"14125"},"geometry":{"type":"Point","coordinates":[-0.3787352941176471,49.230373529411764]}}]}