{"type":"FeatureCollection","features":[{"type":"Feature","properties":{"codesPostaux":["14210"],"population":130,"nom":"La Caine","code":"14122"},"geometry":{"type":"Point","coordinates":[-0.5154472340425532,49.035578297872334]}}]}