{"type":"FeatureCollection","features":[{"type":"Feature","properties":{"codesPostaux":["14230"],"population":92,"nom":"Cardonville","code":"14136"},"geometry":{"type":"Point","coordinates":[-1.0519006818181817,49.34813772727273]}}]}