{"type":"FeatureCollection","features":[{"type":"Feature","properties":{"codesPostaux":["14740"],"population":308,"nom":"Carcagny","code":"14135"},"geometry":{"type":"Point","coordinates":[-0.6239153424657535,49.239066849315066]}}]}