{"type":"FeatureCollection","features":[{"type":"Feature","properties":{"codesPostaux":["14240"],"population":2434,"nom":"Caumont-sur-Aure","code":"14143"},"geometry":{"type":"Point","coordinates":[-0.8163781989247311,49.10262591397849]}}]}