{"type":"FeatureCollection","features":[{"type":"Feature","properties":{"codesPostaux":["14710"],"population":195,"nom":"Colleville-sur-Mer","code":"14165"},"geometry":{"type":"Point","coordinates":[-0.8507624324324327,49.34904675675676]}}]}