{"type":"FeatureCollection","features":[{"type":"Feature","properties":{"codesPostaux":["14880"],"population":2320,"nom":"Colleville-Montgomery","code":"14166"},"geometry":{"type":"Point","coordinates":[-0.3038469512195123,49.27405121951219]}}]}