{"type":"FeatureCollection","features":[{"type":"Feature","properties":{"codesPostaux":["14430"],"population":264,"nom":"Cresseveuille","code":"14198"},"geometry":{"type":"Point","coordinates":[0.008332605633802823,49.24172239436617]}}]}