{"type":"FeatureCollection","features":[{"type":"Feature","properties":{"codesPostaux":["14170"],"population":141,"nom":"Courcy","code":"14190"},"geometry":{"type":"Point","coordinates":[-0.037699436619718314,48.97087901408451]}}]}