{"type":"FeatureCollection","features":[{"type":"Feature","properties":{"codesPostaux":["14220"],"population":612,"nom":"Croisilles","code":"14207"},"geometry":{"type":"Point","coordinates":[-0.4526565289256199,49.001881487603306]}}]}