{"type":"FeatureCollection","features":[{"type":"Feature","properties":{"codesPostaux":["14620"],"population":305,"nom":"Crocy","code":"14206"},"geometry":{"type":"Point","coordinates":[-0.052678433734939765,48.87888012048193]}}]}