{"type":"FeatureCollection","features":[{"type":"Feature","properties":{"codesPostaux":["14250"],"population":209,"nom":"Cristot","code":"14205"},"geometry":{"type":"Point","coordinates":[-0.5716122641509435,49.1935530188679]}}]}