{"type":"FeatureCollection","features":[{"type":"Feature","properties":{"codesPostaux":["14840"],"population":3281,"nom":"D\u00e9mouville","code":"14221"},"geometry":{"type":"Point","coordinates":[-0.2630131249999999,49.17744145833333]}}]}