{"type":"FeatureCollection","features":[{"type":"Feature","properties":{"codesPostaux":["14630"],"population":583,"nom":"\u00c9mi\u00e9ville","code":"14237"},"geometry":{"type":"Point","coordinates":[-0.22725650000000003,49.153466500000015]}}]}