{"type":"FeatureCollection","features":[{"type":"Feature","properties":{"codesPostaux":["14700"],"population":334,"nom":"Eraines","code":"14244"},"geometry":{"type":"Point","coordinates":[-0.15384696969696968,48.907584242424235]}}]}