{"type":"FeatureCollection","features":[{"type":"Feature","properties":{"codesPostaux":["14320"],"population":1410,"nom":"Feuguerolles-Bully","code":"14266"},"geometry":{"type":"Point","coordinates":[-0.4131046874999999,49.11120578125]}}]}