{"type":"FeatureCollection","features":[{"type":"Feature","properties":{"codesPostaux":["14480"],"population":784,"nom":"Le Fresne-Camilly","code":"14288"},"geometry":{"type":"Point","coordinates":[-0.48789605263157876,49.25340236842106]}}]}