{"type":"FeatureCollection","features":[{"type":"Feature","properties":{"codesPostaux":["14510"],"population":704,"nom":"Gonneville-sur-Mer","code":"14305"},"geometry":{"type":"Point","coordinates":[-0.037841088435374155,49.293574353741505]}}]}