{"type":"FeatureCollection","features":[{"type":"Feature","properties":{"codesPostaux":["14730"],"population":4990,"nom":"Giberville","code":"14301"},"geometry":{"type":"Point","coordinates":[-0.2854630188679245,49.178174528301874]}}]}