{"type":"FeatureCollection","features":[{"type":"Feature","properties":{"codesPostaux":["14540"],"population":872,"nom":"Grentheville","code":"14319"},"geometry":{"type":"Point","coordinates":[-0.2969395,49.146172500000006]}}]}