{"type":"FeatureCollection","features":[{"type":"Feature","properties":{"codesPostaux":["14220"],"population":291,"nom":"Grimbosq","code":"14320"},"geometry":{"type":"Point","coordinates":[-0.44307344444444446,49.0458036666667]}}]}