{"type":"FeatureCollection","features":[{"type":"Feature","properties":{"codesPostaux":["14100"],"population":849,"nom":"Hermival-les-Vaux","code":"14326"},"geometry":{"type":"Point","coordinates":[0.29459611510791367,49.16695510791367]}}]}