{"type":"FeatureCollection","features":[{"type":"Feature","properties":{"codesPostaux":["14250"],"population":671,"nom":"Juaye-Mondaye","code":"14346"},"geometry":{"type":"Point","coordinates":[-0.6939073170731708,49.202232829268304]}}]}