{"type":"FeatureCollection","features":[{"type":"Feature","properties":{"codesPostaux":["14170"],"population":313,"nom":"Jort","code":"14345"},"geometry":{"type":"Point","coordinates":[-0.07884904347826084,48.97223860869565]}}]}