{"type":"FeatureCollection","features":[{"type":"Feature","properties":{"codesPostaux":["14310"],"population":406,"nom":"Landes-sur-Ajon","code":"14353"},"geometry":{"type":"Point","coordinates":[-0.5706615151515151,49.07604060606061]}}]}