{"type":"FeatureCollection","features":[{"type":"Feature","properties":{"codesPostaux":["14140"],"population":154,"nom":"Lessard-et-le-Ch\u00eane","code":"14362"},"geometry":{"type":"Point","coordinates":[0.11832750000000002,49.06772769230767]}}]}