{"type":"FeatureCollection","features":[{"type":"Feature","properties":{"codesPostaux":["14250"],"population":483,"nom":"Ling\u00e8vres","code":"14364"},"geometry":{"type":"Point","coordinates":[-0.6746953773584906,49.176255283018854]}}]}