{"type":"FeatureCollection","features":[{"type":"Feature","properties":{"codesPostaux":["14330"],"population":3093,"nom":"Le Molay-Littry","code":"14370"},"geometry":{"type":"Point","coordinates":[-0.8836391044776122,49.23433802238806]}}]}