{"type":"FeatureCollection","features":[{"type":"Feature","properties":{"codesPostaux":["14400"],"population":159,"nom":"Magny-en-Bessin","code":"14385"},"geometry":{"type":"Point","coordinates":[-0.6634677272727272,49.311533787878794]}}]}