{"type":"FeatureCollection","features":[{"type":"Feature","properties":{"codesPostaux":["14930"],"population":992,"nom":"Maltot","code":"14396"},"geometry":{"type":"Point","coordinates":[-0.4194635714285714,49.13234095238096]}}]}