{"type":"FeatureCollection","features":[{"type":"Feature","properties":{"codesPostaux":["14620"],"population":109,"nom":"Le Marais-la-Chapelle","code":"14402"},"geometry":{"type":"Point","coordinates":[-0.023152093023255816,48.881137209302324]}}]}