{"type":"FeatureCollection","features":[{"type":"Feature","properties":{"codesPostaux":["14810"],"population":2191,"nom":"Merville-Franceville-Plage","code":"14409"},"geometry":{"type":"Point","coordinates":[-0.19883919117647056,49.27112764705881]}}]}