{"type":"FeatureCollection","features":[{"type":"Feature","properties":{"codesPostaux":["14960"],"population":147,"nom":"Meuvaines","code":"14430"},"geometry":{"type":"Point","coordinates":[-0.5740552631578947,49.32476078947368]}}]}