{"type":"FeatureCollection","features":[{"type":"Feature","properties":{"codesPostaux":["14210"],"population":96,"nom":"Montigny","code":"14446"},"geometry":{"type":"Point","coordinates":[-0.5340833333333332,49.04120035087718]}}]}