{"type":"FeatureCollection","features":[{"type":"Feature","properties":{"codesPostaux":["14220"],"population":416,"nom":"Les Moutiers-en-Cinglais","code":"14458"},"geometry":{"type":"Point","coordinates":[-0.43954988372093007,49.023762441860455]}}]}