{"type":"FeatureCollection","features":[{"type":"Feature","properties":{"codesPostaux":["14620"],"population":113,"nom":"Les Moutiers-en-Auge","code":"14457"},"geometry":{"type":"Point","coordinates":[0.017905238095238116,48.89998793650794]}}]}