{"type":"FeatureCollection","features":[{"type":"Feature","properties":{"codesPostaux":["14400"],"population":481,"nom":"Nonant","code":"14465"},"geometry":{"type":"Point","coordinates":[-0.6430943119266055,49.237925504587146]}}]}