{"type":"FeatureCollection","features":[{"type":"Feature","properties":{"codesPostaux":["14100"],"population":863,"nom":"Ouilly-le-Vicomte","code":"14487"},"geometry":{"type":"Point","coordinates":[0.2172837301587301,49.17876253968252]}}]}