{"type":"FeatureCollection","features":[{"type":"Feature","properties":{"codesPostaux":["14210"],"population":112,"nom":"Pr\u00e9aux-Bocage","code":"14519"},"geometry":{"type":"Point","coordinates":[-0.5092133333333333,49.052406428571416]}}]}