{"type":"FeatureCollection","features":[{"type":"Feature","properties":{"codesPostaux":["14130"],"population":4534,"nom":"Pont-l'\u00c9v\u00eaque","code":"14514"},"geometry":{"type":"Point","coordinates":[0.1888370940170941,49.27931333333331]}}]}