{"type":"FeatureCollection","features":[{"type":"Feature","properties":{"codesPostaux":["14110"],"population":88,"nom":"Pont\u00e9coulant","code":"14512"},"geometry":{"type":"Point","coordinates":[-0.5875850588235293,48.88938635294117]}}]}