{"type":"FeatureCollection","features":[{"type":"Feature","properties":{"codesPostaux":["14430"],"population":299,"nom":"Putot-en-Auge","code":"14524"},"geometry":{"type":"Point","coordinates":[-0.06270593750000002,49.210016093750006]}}]}