{"type":"FeatureCollection","features":[{"type":"Feature","properties":{"codesPostaux":["14270","14340"],"population":509,"nom":"Belle Vie en Auge","code":"14527"},"geometry":{"type":"Point","coordinates":[-0.029679506172839498,49.11711481481482]}}]}