{"type":"FeatureCollection","features":[{"type":"Feature","properties":{"codesPostaux":["14400"],"population":227,"nom":"Ranchy","code":"14529"},"geometry":{"type":"Point","coordinates":[-0.7578782954545453,49.255477500000005]}}]}