{"type":"FeatureCollection","features":[{"type":"Feature","properties":{"codesPostaux":["14690"],"population":47,"nom":"Rapilly","code":"14531"},"geometry":{"type":"Point","coordinates":[-0.3447159433962264,48.85570301886793]}}]}