{"type":"FeatureCollection","features":[{"type":"Feature","properties":{"codesPostaux":["14740","14980"],"population":2387,"nom":"Rots","code":"14543"},"geometry":{"type":"Point","coordinates":[-0.4871862857142856,49.22122537142856]}}]}