{"type":"FeatureCollection","features":[{"type":"Feature","properties":{"codesPostaux":["14400"],"population":502,"nom":"Ryes","code":"14552"},"geometry":{"type":"Point","coordinates":[-0.6304607920792081,49.31315564356439]}}]}