{"type":"FeatureCollection","features":[{"type":"Feature","properties":{"codesPostaux":["14140"],"population":541,"nom":"Val-de-Vie","code":"14576"},"geometry":{"type":"Point","coordinates":[0.16354689361702138,48.96098310638297]}}]}