{"type":"FeatureCollection","features":[{"type":"Feature","properties":{"codesPostaux":["14130"],"population":1288,"nom":"Saint-Gatien-des-Bois","code":"14578"},"geometry":{"type":"Point","coordinates":[0.1864458239277652,49.35612986455984]}}]}