{"type":"FeatureCollection","features":[{"type":"Feature","properties":{"codesPostaux":["14260","14310"],"population":1307,"nom":"Seulline","code":"14579"},"geometry":{"type":"Point","coordinates":[-0.7033682233502535,49.02734989847714]}}]}