{"type":"FeatureCollection","features":[{"type":"Feature","properties":{"codesPostaux":["14190"],"population":964,"nom":"Saint-Germain-le-Vasson","code":"14589"},"geometry":{"type":"Point","coordinates":[-0.30867301886792464,49.00031056603773]}}]}