{"type":"FeatureCollection","features":[{"type":"Feature","properties":{"codesPostaux":["14240"],"population":131,"nom":"Sainte-Honorine-de-Ducy","code":"14590"},"geometry":{"type":"Point","coordinates":[-0.7852957142857143,49.13923263736262]}}]}