{"type":"FeatureCollection","features":[{"type":"Feature","properties":{"codesPostaux":["14400"],"population":400,"nom":"Saint-Loup-Hors","code":"14609"},"geometry":{"type":"Point","coordinates":[-0.7351952727272728,49.263875272727255]}}]}