{"type":"FeatureCollection","features":[{"type":"Feature","properties":{"codesPostaux":["14740"],"population":1843,"nom":"Saint-Manvieu-Norrey","code":"14610"},"geometry":{"type":"Point","coordinates":[-0.4984168181818182,49.18536787878788]}}]}