{"type":"FeatureCollection","features":[{"type":"Feature","properties":{"codesPostaux":["14330"],"population":762,"nom":"Sainte-Marguerite-d'Elle","code":"14614"},"geometry":{"type":"Point","coordinates":[-0.9898913919413926,49.21834069597071]}}]}