{"type":"FeatureCollection","features":[{"type":"Feature","properties":{"codesPostaux":["14400"],"population":2212,"nom":"Saint-Vigor-le-Grand","code":"14663"},"geometry":{"type":"Point","coordinates":[-0.6795359663865544,49.28934394957983]}}]}