{"type":"FeatureCollection","features":[{"type":"Feature","properties":{"codesPostaux":["14240","14350"],"population":820,"nom":"Val de Dr\u00f4me","code":"14672"},"geometry":{"type":"Point","coordinates":[-0.8293240431266847,49.05503423180595]}}]}