{"type":"FeatureCollection","features":[{"type":"Feature","properties":{"codesPostaux":["14610"],"population":1435,"nom":"Thaon","code":"14685"},"geometry":{"type":"Point","coordinates":[-0.4532274444444445,49.25526455555556]}}]}