{"type":"FeatureCollection","features":[{"type":"Feature","properties":{"codesPostaux":["14250"],"population":1570,"nom":"Tilly-sur-Seulles","code":"14692"},"geometry":{"type":"Point","coordinates":[-0.6240650657894736,49.168391315789506]}}]}