{"type":"FeatureCollection","features":[{"type":"Feature","properties":{"codesPostaux":["14210"],"population":412,"nom":"Trois-Monts","code":"14713"},"geometry":{"type":"Point","coordinates":[-0.4809435616438356,49.04793904109589]}}]}