{"type":"FeatureCollection","features":[{"type":"Feature","properties":{"codesPostaux":["15380"],"population":802,"nom":"Anglards-de-Salers","code":"15006"},"geometry":{"type":"Point","coordinates":[2.462808197879858,45.20102505300355]}}]}