{"type":"FeatureCollection","features":[{"type":"Feature","properties":{"codesPostaux":["15800"],"population":126,"nom":"Badailhac","code":"15017"},"geometry":{"type":"Point","coordinates":[2.6299962184873946,44.91368431372548]}}]}