{"type":"FeatureCollection","features":[{"type":"Feature","properties":{"codesPostaux":["15230"],"population":226,"nom":"C\u00e9zens","code":"15033"},"geometry":{"type":"Point","coordinates":[2.86683847107438,44.984379876033046]}}]}