{"type":"FeatureCollection","features":[{"type":"Feature","properties":{"codesPostaux":["15300"],"population":243,"nom":"La Chapelle-d'Alagnon","code":"15041"},"geometry":{"type":"Point","coordinates":[2.9097009844559585,45.10536002590676]}}]}