{"type":"FeatureCollection","features":[{"type":"Feature","properties":{"codesPostaux":["15400"],"population":196,"nom":"Le Claux","code":"15050"},"geometry":{"type":"Point","coordinates":[2.6995098657718115,45.15866416107381]}}]}