{"type":"FeatureCollection","features":[{"type":"Feature","properties":{"codesPostaux":["15130"],"population":138,"nom":"Cros-de-Ronesque","code":"15058"},"geometry":{"type":"Point","coordinates":[2.604990915750915,44.86242813186814]}}]}