{"type":"FeatureCollection","features":[{"type":"Feature","properties":{"codesPostaux":["15130"],"population":753,"nom":"Giou-de-Mamou","code":"15074"},"geometry":{"type":"Point","coordinates":[2.5078519638242875,44.93520919896645]}}]}