{"type":"FeatureCollection","features":[{"type":"Feature","properties":{"codesPostaux":["15150"],"population":185,"nom":"Gl\u00e9nat","code":"15076"},"geometry":{"type":"Point","coordinates":[2.1731679389312974,44.89573435114504]}}]}