{"type":"FeatureCollection","features":[{"type":"Feature","properties":{"codesPostaux":["15230"],"population":60,"nom":"Lacapelle-Barr\u00e8s","code":"15086"},"geometry":{"type":"Point","coordinates":[2.7255349593495937,44.950077154471565]}}]}