{"type":"FeatureCollection","features":[{"type":"Feature","properties":{"codesPostaux":["15120"],"population":516,"nom":"Ladinhac","code":"15089"},"geometry":{"type":"Point","coordinates":[2.5139272641509414,44.76558034591194]}}]}