{"type":"FeatureCollection","features":[{"type":"Feature","properties":{"codesPostaux":["15160"],"population":98,"nom":"Landeyrat","code":"15091"},"geometry":{"type":"Point","coordinates":[2.8686156140350882,45.26843304093568]}}]}