{"type":"FeatureCollection","features":[{"type":"Feature","properties":{"codesPostaux":["15300"],"population":103,"nom":"Lavigerie","code":"15102"},"geometry":{"type":"Point","coordinates":[2.7443703305785134,45.133850247933864]}}]}