{"type":"FeatureCollection","features":[{"type":"Feature","properties":{"codesPostaux":["15300"],"population":106,"nom":"Laveissenet","code":"15100"},"geometry":{"type":"Point","coordinates":[2.889080833333334,45.079391233333325]}}]}