{"type":"FeatureCollection","features":[{"type":"Feature","properties":{"codesPostaux":["15250"],"population":703,"nom":"Marmanhac","code":"15118"},"geometry":{"type":"Point","coordinates":[2.476505228310501,45.00639125570774]}}]}