{"type":"FeatureCollection","features":[{"type":"Feature","properties":{"codesPostaux":["15500"],"population":1764,"nom":"Massiac","code":"15119"},"geometry":{"type":"Point","coordinates":[3.194165632911391,45.24120185654008]}}]}