{"type":"FeatureCollection","features":[{"type":"Feature","properties":{"codesPostaux":["15240"],"population":105,"nom":"La Monselie","code":"15128"},"geometry":{"type":"Point","coordinates":[2.5508894758064535,45.321670524193536]}}]}