{"type":"FeatureCollection","features":[{"type":"Feature","properties":{"codesPostaux":["15600"],"population":2165,"nom":"Maurs","code":"15122"},"geometry":{"type":"Point","coordinates":[2.1687798581560265,44.7169624113475]}}]}