{"type":"FeatureCollection","features":[{"type":"Feature","properties":{"codesPostaux":["15250"],"population":1929,"nom":"Naucelles","code":"15140"},"geometry":{"type":"Point","coordinates":[2.41389504,44.95264284000002]}}]}