{"type":"FeatureCollection","features":[{"type":"Feature","properties":{"codesPostaux":["15600"],"population":129,"nom":"Rouziers","code":"15167"},"geometry":{"type":"Point","coordinates":[2.2066683271375465,44.79826977695169]}}]}