{"type":"FeatureCollection","features":[{"type":"Feature","properties":{"codesPostaux":["15100"],"population":607,"nom":"Roffiac","code":"15164"},"geometry":{"type":"Point","coordinates":[3.0146798251748246,45.04695958041956]}}]}