{"type":"FeatureCollection","features":[{"type":"Feature","properties":{"codesPostaux":["15590"],"population":132,"nom":"Saint-Cirgues-de-Jordanne","code":"15178"},"geometry":{"type":"Point","coordinates":[2.5989793749999994,45.04041791666667]}}]}