{"type":"FeatureCollection","features":[{"type":"Feature","properties":{"codesPostaux":["15190"],"population":223,"nom":"Saint-Amandin","code":"15170"},"geometry":{"type":"Point","coordinates":[2.710523580786025,45.32335672489083]}}]}