{"type":"FeatureCollection","features":[{"type":"Feature","properties":{"codesPostaux":["15140"],"population":202,"nom":"Sainte-Eulalie","code":"15186"},"geometry":{"type":"Point","coordinates":[2.3798100520833345,45.125272812499965]}}]}