{"type":"FeatureCollection","features":[{"type":"Feature","properties":{"codesPostaux":["15250"],"population":1528,"nom":"Saint-Paul-des-Landes","code":"15204"},"geometry":{"type":"Point","coordinates":[2.309864311594203,44.94700963768117]}}]}