{"type":"FeatureCollection","features":[{"type":"Feature","properties":{"codesPostaux":["15350"],"population":146,"nom":"Saint-Pierre","code":"15206"},"geometry":{"type":"Point","coordinates":[2.3765880327868856,45.39976934426229]}}]}