{"type":"FeatureCollection","features":[{"type":"Feature","properties":{"codesPostaux":["15380"],"population":70,"nom":"Saint-Vincent-de-Salers","code":"15218"},"geometry":{"type":"Point","coordinates":[2.5340747014925378,45.20886324626869]}}]}