{"type":"FeatureCollection","features":[{"type":"Feature","properties":{"codesPostaux":["15110"],"population":511,"nom":"Saint-Urcize","code":"15216"},"geometry":{"type":"Point","coordinates":[2.9862272435897443,44.6992084615385]}}]}