{"type":"FeatureCollection","features":[{"type":"Feature","properties":{"codesPostaux":["15130"],"population":1143,"nom":"Saint-Simon","code":"15215"},"geometry":{"type":"Point","coordinates":[2.492307878787878,44.966776410256465]}}]}