{"type":"FeatureCollection","features":[{"type":"Feature","properties":{"codesPostaux":["15120"],"population":225,"nom":"Sansac-Veinaz\u00e8s","code":"15222"},"geometry":{"type":"Point","coordinates":[2.430507567567567,44.74435047297296]}}]}