{"type":"FeatureCollection","features":[{"type":"Feature","properties":{"codesPostaux":["15150"],"population":494,"nom":"Siran","code":"15228"},"geometry":{"type":"Point","coordinates":[2.116368453333333,44.94303029333335]}}]}