{"type":"FeatureCollection","features":[{"type":"Feature","properties":{"codesPostaux":["15800"],"population":614,"nom":"Thi\u00e9zac","code":"15236"},"geometry":{"type":"Point","coordinates":[2.6657116806722696,45.019315588235294]}}]}