{"type":"FeatureCollection","features":[{"type":"Feature","properties":{"codesPostaux":["15400"],"population":509,"nom":"Trizac","code":"15243"},"geometry":{"type":"Point","coordinates":[2.533704772234274,45.247843882863336]}}]}