{"type":"FeatureCollection","features":[{"type":"Feature","properties":{"codesPostaux":["15270"],"population":182,"nom":"Tr\u00e9mouille","code":"15240"},"geometry":{"type":"Point","coordinates":[2.668591159420291,45.391664492753584]}}]}