{"type":"FeatureCollection","features":[{"type":"Feature","properties":{"codesPostaux":["15300"],"population":559,"nom":"Valu\u00e9jols","code":"15248"},"geometry":{"type":"Point","coordinates":[2.9219210958904114,45.05528248858447]}}]}