{"type":"FeatureCollection","features":[{"type":"Feature","properties":{"codesPostaux":["15240"],"population":497,"nom":"Vebret","code":"15250"},"geometry":{"type":"Point","coordinates":[2.5174030154639158,45.34837739690726]}}]}