{"type":"FeatureCollection","features":[{"type":"Feature","properties":{"codesPostaux":["15590"],"population":406,"nom":"Velzic","code":"15252"},"geometry":{"type":"Point","coordinates":[2.5546792499999995,44.99630700000002]}}]}