{"type":"FeatureCollection","features":[{"type":"Feature","properties":{"codesPostaux":["16140"],"population":1088,"nom":"Aigre","code":"16005"},"geometry":{"type":"Point","coordinates":[0.0022199999999999993,45.89154195652175]}}]}