{"type":"FeatureCollection","features":[{"type":"Feature","properties":{"codesPostaux":["16130"],"population":509,"nom":"Angeac-Champagne","code":"16012"},"geometry":{"type":"Point","coordinates":[-0.2941832298136646,45.608521987577646]}}]}