{"type":"FeatureCollection","features":[{"type":"Feature","properties":{"codesPostaux":["16500"],"population":856,"nom":"Ansac-sur-Vienne","code":"16016"},"geometry":{"type":"Point","coordinates":[0.6245980219780219,46.00230076923076]}}]}