{"type":"FeatureCollection","features":[{"type":"Feature","properties":{"codesPostaux":["16390"],"population":410,"nom":"Aubeterre-sur-Dronne","code":"16020"},"geometry":{"type":"Point","coordinates":[0.16934984615384616,45.26268061538461]}}]}