{"type":"FeatureCollection","features":[{"type":"Feature","properties":{"codesPostaux":["16250"],"population":308,"nom":"B\u00e9cheresse","code":"16036"},"geometry":{"type":"Point","coordinates":[0.08064319587628867,45.50156164948453]}}]}