{"type":"FeatureCollection","features":[{"type":"Feature","properties":{"codesPostaux":["16210"],"population":156,"nom":"Bazac","code":"16034"},"geometry":{"type":"Point","coordinates":[0.03649238532110092,45.223303853211014]}}]}