{"type":"FeatureCollection","features":[{"type":"Feature","properties":{"codesPostaux":["16480"],"population":131,"nom":"Boisbreteau","code":"16048"},"geometry":{"type":"Point","coordinates":[-0.1615126086956522,45.33339342995169]}}]}