{"type":"FeatureCollection","features":[{"type":"Feature","properties":{"codesPostaux":["16360"],"population":123,"nom":"Bors (Canton de Charente-Sud)","code":"16053"},"geometry":{"type":"Point","coordinates":[-0.1939245112781956,45.31940165413532]}}]}