{"type":"FeatureCollection","features":[{"type":"Feature","properties":{"codesPostaux":["16120"],"population":262,"nom":"Bonneuil","code":"16050"},"geometry":{"type":"Point","coordinates":[-0.14075525000000003,45.57580783333335]}}]}