{"type":"FeatureCollection","features":[{"type":"Feature","properties":{"codesPostaux":["16100"],"population":1462,"nom":"Boutiers-Saint-Trojan","code":"16058"},"geometry":{"type":"Point","coordinates":[-0.294019504950495,45.70884396039605]}}]}