{"type":"FeatureCollection","features":[{"type":"Feature","properties":{"codesPostaux":["16190"],"population":249,"nom":"Bors (Canton de Tude-et-Lavalette)","code":"16052"},"geometry":{"type":"Point","coordinates":[0.14881543956043952,45.340451318681296]}}]}