{"type":"FeatureCollection","features":[{"type":"Feature","properties":{"codesPostaux":["16420"],"population":1055,"nom":"Brigueuil","code":"16064"},"geometry":{"type":"Point","coordinates":[0.8771625671641792,45.95095202985076]}}]}