{"type":"FeatureCollection","features":[{"type":"Feature","properties":{"codesPostaux":["16270"],"population":614,"nom":"Genouillac","code":"16149"},"geometry":{"type":"Point","coordinates":[0.574957207207207,45.847170675675706]}}]}