{"type":"FeatureCollection","features":[{"type":"Feature","properties":{"codesPostaux":["16230"],"population":344,"nom":"Fontenille","code":"16141"},"geometry":{"type":"Point","coordinates":[0.17543028301886796,45.9116653773585]}}]}