{"type":"FeatureCollection","features":[{"type":"Feature","properties":{"codesPostaux":["16140"],"population":126,"nom":"Les Gours","code":"16155"},"geometry":{"type":"Point","coordinates":[-0.07365592105263158,45.95936894736843]}}]}