{"type":"FeatureCollection","features":[{"type":"Feature","properties":{"codesPostaux":["16170"],"population":625,"nom":"Gourville","code":"16156"},"geometry":{"type":"Point","coordinates":[-0.023255520000000005,45.8262988]}}]}