{"type":"FeatureCollection","features":[{"type":"Feature","properties":{"codesPostaux":["16200"],"population":4449,"nom":"Jarnac","code":"16167"},"geometry":{"type":"Point","coordinates":[-0.16429253246753242,45.68449753246754]}}]}