{"type":"FeatureCollection","features":[{"type":"Feature","properties":{"codesPostaux":["16140"],"population":162,"nom":"Lign\u00e9","code":"16185"},"geometry":{"type":"Point","coordinates":[0.10411952380952384,45.91562273809524]}}]}