{"type":"FeatureCollection","features":[{"type":"Feature","properties":{"codesPostaux":["16230"],"population":732,"nom":"Lux\u00e9","code":"16196"},"geometry":{"type":"Point","coordinates":[0.1213596226415094,45.89547528301886]}}]}