{"type":"FeatureCollection","features":[{"type":"Feature","properties":{"codesPostaux":["16240"],"population":211,"nom":"Longr\u00e9","code":"16190"},"geometry":{"type":"Point","coordinates":[-0.023903708609271532,45.99680953642383]}}]}