{"type":"FeatureCollection","features":[{"type":"Feature","properties":{"codesPostaux":["16200"],"population":696,"nom":"Mainxe","code":"16202"},"geometry":{"type":"Point","coordinates":[-0.18305062499999997,45.66300640625001]}}]}