{"type":"FeatureCollection","features":[{"type":"Feature","properties":{"codesPostaux":["16210"],"population":158,"nom":"M\u00e9dillac","code":"16215"},"geometry":{"type":"Point","coordinates":[0.01792849056603773,45.21704735849056]}}]}