{"type":"FeatureCollection","features":[{"type":"Feature","properties":{"codesPostaux":["16570"],"population":843,"nom":"Marsac","code":"16210"},"geometry":{"type":"Point","coordinates":[0.08413707142857142,45.74424100000001]}}]}