{"type":"FeatureCollection","features":[{"type":"Feature","properties":{"codesPostaux":["16310"],"population":686,"nom":"Montemb\u0153uf","code":"16225"},"geometry":{"type":"Point","coordinates":[0.5479919480519481,45.77630688311688]}}]}