{"type":"FeatureCollection","features":[{"type":"Feature","properties":{"codesPostaux":["16190"],"population":303,"nom":"Nonac","code":"16246"},"geometry":{"type":"Point","coordinates":[0.048651584699453534,45.42390655737708]}}]}