{"type":"FeatureCollection","features":[{"type":"Feature","properties":{"codesPostaux":["16390"],"population":270,"nom":"Pillac","code":"16260"},"geometry":{"type":"Point","coordinates":[0.18067922448979598,45.32383853061224]}}]}