{"type":"FeatureCollection","features":[{"type":"Feature","properties":{"codesPostaux":["16110"],"population":541,"nom":"La Rochette","code":"16282"},"geometry":{"type":"Point","coordinates":[0.3122771052631577,45.802321842105265]}}]}