{"type":"FeatureCollection","features":[{"type":"Feature","properties":{"codesPostaux":["16320"],"population":414,"nom":"Rougnac","code":"16285"},"geometry":{"type":"Point","coordinates":[0.34829159090909084,45.53846693181821]}}]}