{"type":"FeatureCollection","features":[{"type":"Feature","properties":{"codesPostaux":["16110"],"population":1927,"nom":"Rivi\u00e8res","code":"16280"},"geometry":{"type":"Point","coordinates":[0.35462833333333327,45.761520263157905]}}]}