{"type":"FeatureCollection","features":[{"type":"Feature","properties":{"codesPostaux":["16600"],"population":7357,"nom":"Ruelle-sur-Touvre","code":"16291"},"geometry":{"type":"Point","coordinates":[0.23282658730158737,45.68471404761905]}}]}