{"type":"FeatureCollection","features":[{"type":"Feature","properties":{"codesPostaux":["16570"],"population":902,"nom":"Saint-Genis-d'Hiersac","code":"16320"},"geometry":{"type":"Point","coordinates":[0.03833071794871798,45.75212841025639]}}]}