{"type":"FeatureCollection","features":[{"type":"Feature","properties":{"codesPostaux":["16460"],"population":33,"nom":"Saint-Sulpice-de-Ruffec","code":"16356"},"geometry":{"type":"Point","coordinates":[0.3166976190476191,45.938025555555555]}}]}