{"type":"FeatureCollection","features":[{"type":"Feature","properties":{"codesPostaux":["16370"],"population":1266,"nom":"Saint-Sulpice-de-Cognac","code":"16355"},"geometry":{"type":"Point","coordinates":[-0.3991266666666667,45.76522596899222]}}]}