{"type":"FeatureCollection","features":[{"type":"Feature","properties":{"codesPostaux":["16410"],"population":823,"nom":"Sers","code":"16368"},"geometry":{"type":"Point","coordinates":[0.3181856666666667,45.583505466666686]}}]}