{"type":"FeatureCollection","features":[{"type":"Feature","properties":{"codesPostaux":["16420"],"population":505,"nom":"Saulgond","code":"16363"},"geometry":{"type":"Point","coordinates":[0.7891897286821701,45.95007337209302]}}]}