{"type":"FeatureCollection","features":[{"type":"Feature","properties":{"codesPostaux":["16260"],"population":101,"nom":"La T\u00e2che","code":"16377"},"geometry":{"type":"Point","coordinates":[0.3599041975308642,45.87181876543209]}}]}