{"type":"FeatureCollection","features":[{"type":"Feature","properties":{"codesPostaux":["16240"],"population":167,"nom":"Theil-Rabier","code":"16381"},"geometry":{"type":"Point","coordinates":[0.042499000000000016,46.053126857142864]}}]}