{"type":"FeatureCollection","features":[{"type":"Feature","properties":{"codesPostaux":["16330"],"population":2021,"nom":"Vars","code":"16393"},"geometry":{"type":"Point","coordinates":[0.12734456730769225,45.755310336538464]}}]}