{"type":"FeatureCollection","features":[{"type":"Feature","properties":{"codesPostaux":["16330"],"population":147,"nom":"Vervant","code":"16401"},"geometry":{"type":"Point","coordinates":[0.12610945454545455,45.82896636363636]}}]}