{"type":"FeatureCollection","features":[{"type":"Feature","properties":{"codesPostaux":["16240"],"population":997,"nom":"Villefagnan","code":"16409"},"geometry":{"type":"Point","coordinates":[0.09145429824561405,46.012784649122814]}}]}