{"type":"FeatureCollection","features":[{"type":"Feature","properties":{"codesPostaux":["16330"],"population":305,"nom":"Xambes","code":"16423"},"geometry":{"type":"Point","coordinates":[0.1059016091954023,45.82375574712642]}}]}