{"type":"FeatureCollection","features":[{"type":"Feature","properties":{"codesPostaux":["17470"],"population":1415,"nom":"Aulnay","code":"17024"},"geometry":{"type":"Point","coordinates":[-0.3486519565217391,46.01830445652171]}}]}