{"type":"FeatureCollection","features":[{"type":"Feature","properties":{"codesPostaux":["17470"],"population":88,"nom":"Blanzay-sur-Boutonne","code":"17049"},"geometry":{"type":"Point","coordinates":[-0.426840925925926,46.05415657407406]}}]}