{"type":"FeatureCollection","features":[{"type":"Feature","properties":{"codesPostaux":["17240"],"population":543,"nom":"Bois","code":"17050"},"geometry":{"type":"Point","coordinates":[-0.6116477049180328,45.481084180327855]}}]}