{"type":"FeatureCollection","features":[{"type":"Feature","properties":{"codesPostaux":["17430"],"population":1321,"nom":"Bords","code":"17053"},"geometry":{"type":"Point","coordinates":[-0.7810530476190476,45.89907495238097]}}]}