{"type":"FeatureCollection","features":[{"type":"Feature","properties":{"codesPostaux":["17580"],"population":2350,"nom":"Le Bois-Plage-en-R\u00e9","code":"17051"},"geometry":{"type":"Point","coordinates":[-1.3711117204301073,46.18113698924731]}}]}