{"type":"FeatureCollection","features":[{"type":"Feature","properties":{"codesPostaux":["17800"],"population":253,"nom":"Brives-sur-Charente","code":"17069"},"geometry":{"type":"Point","coordinates":[-0.45511810344827597,45.666888103448265]}}]}