{"type":"FeatureCollection","features":[{"type":"Feature","properties":{"codesPostaux":["17270"],"population":1208,"nom":"Cercoux","code":"17077"},"geometry":{"type":"Point","coordinates":[-0.20661676348547725,45.1303460165975]}}]}