{"type":"FeatureCollection","features":[{"type":"Feature","properties":{"codesPostaux":["17270"],"population":986,"nom":"Cl\u00e9rac","code":"17110"},"geometry":{"type":"Point","coordinates":[-0.24213075268817208,45.17011268817205]}}]}