{"type":"FeatureCollection","features":[{"type":"Feature","properties":{"codesPostaux":["17330"],"population":234,"nom":"Coivert","code":"17114"},"geometry":{"type":"Point","coordinates":[-0.45282633333333333,46.06681338888888]}}]}