{"type":"FeatureCollection","features":[{"type":"Feature","properties":{"codesPostaux":["17220"],"population":1228,"nom":"Croix-Chapeau","code":"17136"},"geometry":{"type":"Point","coordinates":[-0.9971139130434783,46.10507869565218]}}]}