{"type":"FeatureCollection","features":[{"type":"Feature","properties":{"codesPostaux":["17130"],"population":129,"nom":"Expiremont","code":"17156"},"geometry":{"type":"Point","coordinates":[-0.373000634920635,45.33051063492065]}}]}