{"type":"FeatureCollection","features":[{"type":"Feature","properties":{"codesPostaux":["17400"],"population":400,"nom":"Fontenet","code":"17165"},"geometry":{"type":"Point","coordinates":[-0.4634332727272725,45.909246090909114]}}]}