{"type":"FeatureCollection","features":[{"type":"Feature","properties":{"codesPostaux":["17320"],"population":643,"nom":"Hiers-Brouage","code":"17189"},"geometry":{"type":"Point","coordinates":[-1.053887044334976,45.84476369458128]}}]}