{"type":"FeatureCollection","features":[{"type":"Feature","properties":{"codesPostaux":["17111"],"population":677,"nom":"Loix","code":"17207"},"geometry":{"type":"Point","coordinates":[-1.4501707812499995,46.21988742187499]}}]}