{"type":"FeatureCollection","features":[{"type":"Feature","properties":{"codesPostaux":["17570"],"population":1807,"nom":"Les Mathes","code":"17225"},"geometry":{"type":"Point","coordinates":[-1.1858617117117114,45.693610270270256]}}]}