{"type":"FeatureCollection","features":[{"type":"Feature","properties":{"codesPostaux":["17770"],"population":733,"nom":"Migron","code":"17235"},"geometry":{"type":"Point","coordinates":[-0.393191607142857,45.80424880952383]}}]}