{"type":"FeatureCollection","features":[{"type":"Feature","properties":{"codesPostaux":["17132"],"population":3031,"nom":"Meschers-sur-Gironde","code":"17230"},"geometry":{"type":"Point","coordinates":[-0.9553622043010754,45.567975591397875]}}]}