{"type":"FeatureCollection","features":[{"type":"Feature","properties":{"codesPostaux":["17113"],"population":831,"nom":"Mornac-sur-Seudre","code":"17247"},"geometry":{"type":"Point","coordinates":[-1.023605824175824,45.71271274725276]}}]}