{"type":"FeatureCollection","features":[{"type":"Feature","properties":{"codesPostaux":["17520"],"population":307,"nom":"Neuillac","code":"17258"},"geometry":{"type":"Point","coordinates":[-0.398763287671233,45.50743815068494]}}]}