{"type":"FeatureCollection","features":[{"type":"Feature","properties":{"codesPostaux":["17160"],"population":290,"nom":"Prignac","code":"17290"},"geometry":{"type":"Point","coordinates":[-0.35023338582677166,45.831665826771676]}}]}