{"type":"FeatureCollection","features":[{"type":"Feature","properties":{"codesPostaux":["17150"],"population":260,"nom":"Saint-Georges-des-Ago\u00fbts","code":"17335"},"geometry":{"type":"Point","coordinates":[-0.6511216814159292,45.37513398230089]}}]}