{"type":"FeatureCollection","features":[{"type":"Feature","properties":{"codesPostaux":["17770"],"population":1201,"nom":"Saint-Hilaire-de-Villefranche","code":"17344"},"geometry":{"type":"Point","coordinates":[-0.5380121142857146,45.859834571428564]}}]}