{"type":"FeatureCollection","features":[{"type":"Feature","properties":{"codesPostaux":["17620"],"population":677,"nom":"Saint-Jean-d'Angle","code":"17348"},"geometry":{"type":"Point","coordinates":[-0.9682320952380948,45.829117571428554]}}]}