{"type":"FeatureCollection","features":[{"type":"Feature","properties":{"codesPostaux":["17430"],"population":1396,"nom":"Saint-Hippolyte","code":"17346"},"geometry":{"type":"Point","coordinates":[-0.9121514615384614,45.92141215384612]}}]}