{"type":"FeatureCollection","features":[{"type":"Feature","properties":{"codesPostaux":["17360"],"population":439,"nom":"Saint-Martin-de-Coux","code":"17366"},"geometry":{"type":"Point","coordinates":[-0.105733717948718,45.14496025641027]}}]}