{"type":"FeatureCollection","features":[{"type":"Feature","properties":{"codesPostaux":["17330"],"population":123,"nom":"Saint-Martial","code":"17361"},"geometry":{"type":"Point","coordinates":[-0.4559737837837837,46.04632418918919]}}]}