{"type":"FeatureCollection","features":[{"type":"Feature","properties":{"codesPostaux":["17220"],"population":2038,"nom":"Saint-M\u00e9dard-d'Aunis","code":"17373"},"geometry":{"type":"Point","coordinates":[-0.9633596039603959,46.158159009901006]}}]}