{"type":"FeatureCollection","features":[{"type":"Feature","properties":{"codesPostaux":["17800"],"population":210,"nom":"Saint-Palais-de-Phiolin","code":"17379"},"geometry":{"type":"Point","coordinates":[-0.5954829113924051,45.51539924050635]}}]}