{"type":"FeatureCollection","features":[{"type":"Feature","properties":{"codesPostaux":["17400"],"population":225,"nom":"Saint-Pardoult","code":"17381"},"geometry":{"type":"Point","coordinates":[-0.4538471276595742,46.00613361702126]}}]}