{"type":"FeatureCollection","features":[{"type":"Feature","properties":{"codesPostaux":["17310"],"population":6637,"nom":"Saint-Pierre-d'Ol\u00e9ron","code":"17385"},"geometry":{"type":"Point","coordinates":[-1.2818462269129292,45.94249055408973]}}]}