{"type":"FeatureCollection","features":[{"type":"Feature","properties":{"codesPostaux":["17800"],"population":164,"nom":"Saint-Seurin-de-Palenne","code":"17398"},"geometry":{"type":"Point","coordinates":[-0.5180895918367346,45.620597755102025]}}]}