{"type":"FeatureCollection","features":[{"type":"Feature","properties":{"codesPostaux":["17610"],"population":497,"nom":"Saint-Sauvant","code":"17395"},"geometry":{"type":"Point","coordinates":[-0.49958607142857153,45.73493133928571]}}]}