{"type":"FeatureCollection","features":[{"type":"Feature","properties":{"codesPostaux":["17330"],"population":108,"nom":"Saint-S\u00e9verin-sur-Boutonne","code":"17401"},"geometry":{"type":"Point","coordinates":[-0.4252263000000001,46.088479799999995]}}]}