{"type":"FeatureCollection","features":[{"type":"Feature","properties":{"codesPostaux":["17100"],"population":571,"nom":"Saint-Vaize","code":"17412"},"geometry":{"type":"Point","coordinates":[-0.6217097368421055,45.81634894736842]}}]}