{"type":"FeatureCollection","features":[{"type":"Feature","properties":{"codesPostaux":["17780"],"population":2978,"nom":"Soubise","code":"17429"},"geometry":{"type":"Point","coordinates":[-1.0008316326530613,45.9086512244898]}}]}