{"type":"FeatureCollection","features":[{"type":"Feature","properties":{"codesPostaux":["17510"],"population":93,"nom":"Seign\u00e9","code":"17422"},"geometry":{"type":"Point","coordinates":[-0.20948348484848486,45.95571803030304]}}]}