{"type":"FeatureCollection","features":[{"type":"Feature","properties":{"codesPostaux":["17170"],"population":814,"nom":"Taugon","code":"17439"},"geometry":{"type":"Point","coordinates":[-0.8341081690140848,46.325929718309844]}}]}