{"type":"FeatureCollection","features":[{"type":"Feature","properties":{"codesPostaux":["17250"],"population":731,"nom":"Soulignonne","code":"17431"},"geometry":{"type":"Point","coordinates":[-0.789891111111111,45.7765712962963]}}]}