{"type":"FeatureCollection","features":[{"type":"Feature","properties":{"codesPostaux":["17150"],"population":392,"nom":"Soubran","code":"17430"},"geometry":{"type":"Point","coordinates":[-0.5187813970588234,45.35391749999997]}}]}