{"type":"FeatureCollection","features":[{"type":"Feature","properties":{"codesPostaux":["17390"],"population":4782,"nom":"La Tremblade","code":"17452"},"geometry":{"type":"Point","coordinates":[-1.160815876288659,45.7764912886598]}}]}