{"type":"FeatureCollection","features":[{"type":"Feature","properties":{"codesPostaux":["17500"],"population":171,"nom":"Vanzac","code":"17458"},"geometry":{"type":"Point","coordinates":[-0.298753417721519,45.3574358227848]}}]}