{"type":"FeatureCollection","features":[{"type":"Feature","properties":{"codesPostaux":["17160"],"population":566,"nom":"Les Touches-de-P\u00e9rigny","code":"17451"},"geometry":{"type":"Point","coordinates":[-0.265968376068376,45.90559752136752]}}]}