{"type":"FeatureCollection","features":[{"type":"Feature","properties":{"codesPostaux":["17770"],"population":264,"nom":"Villars-les-Bois","code":"17470"},"geometry":{"type":"Point","coordinates":[-0.43389600000000006,45.79365319999999]}}]}