{"type":"FeatureCollection","features":[{"type":"Feature","properties":{"codesPostaux":["17230"],"population":2125,"nom":"Villedoux","code":"17472"},"geometry":{"type":"Point","coordinates":[-1.0766109933774832,46.250453708609264]}}]}