{"type":"FeatureCollection","features":[{"type":"Feature","properties":{"codesPostaux":["17500"],"population":257,"nom":"Villexavier","code":"17476"},"geometry":{"type":"Point","coordinates":[-0.44289780821917796,45.38032452054795]}}]}