{"type":"FeatureCollection","features":[{"type":"Feature","properties":{"codesPostaux":["18260"],"population":161,"nom":"Assigny","code":"18014"},"geometry":{"type":"Point","coordinates":[2.7416590000000007,47.426562]}}]}