{"type":"FeatureCollection","features":[{"type":"Feature","properties":{"codesPostaux":["18170"],"population":212,"nom":"Ardenais","code":"18010"},"geometry":{"type":"Point","coordinates":[2.359317688888889,46.642580266666634]}}]}