{"type":"FeatureCollection","features":[{"type":"Feature","properties":{"codesPostaux":["18520"],"population":680,"nom":"Bengy-sur-Craon","code":"18027"},"geometry":{"type":"Point","coordinates":[2.738846190476192,46.99762809523809]}}]}