{"type":"FeatureCollection","features":[{"type":"Feature","properties":{"codesPostaux":["18200"],"population":326,"nom":"Bouzais","code":"18034"},"geometry":{"type":"Point","coordinates":[2.469606440677967,46.704676779661014]}}]}