{"type":"FeatureCollection","features":[{"type":"Feature","properties":{"codesPostaux":["18120"],"population":531,"nom":"Brinay","code":"18036"},"geometry":{"type":"Point","coordinates":[2.111559194630871,47.17034409395973]}}]}