{"type":"FeatureCollection","features":[{"type":"Feature","properties":{"codesPostaux":["18140"],"population":493,"nom":"La Chapelle-Montlinard","code":"18049"},"geometry":{"type":"Point","coordinates":[2.979202686567165,47.17492895522387]}}]}