{"type":"FeatureCollection","features":[{"type":"Feature","properties":{"codesPostaux":["18150"],"population":399,"nom":"La Chapelle-Hugon","code":"18048"},"geometry":{"type":"Point","coordinates":[2.9436748936170214,46.8971590780142]}}]}