{"type":"FeatureCollection","features":[{"type":"Feature","properties":{"codesPostaux":["18300"],"population":198,"nom":"Couargues","code":"18074"},"geometry":{"type":"Point","coordinates":[2.9238839473684206,47.286925526315784]}}]}