{"type":"FeatureCollection","features":[{"type":"Feature","properties":{"codesPostaux":["18190"],"population":61,"nom":"Cr\u00e9zan\u00e7ay-sur-Cher","code":"18078"},"geometry":{"type":"Point","coordinates":[2.3473736231884055,46.815805942028966]}}]}