{"type":"FeatureCollection","features":[{"type":"Feature","properties":{"codesPostaux":["18130"],"population":35,"nom":"Contres","code":"18071"},"geometry":{"type":"Point","coordinates":[2.4979407142857144,46.851327738095236]}}]}