{"type":"FeatureCollection","features":[{"type":"Feature","properties":{"codesPostaux":["18340"],"population":365,"nom":"Crosses","code":"18081"},"geometry":{"type":"Point","coordinates":[2.570547177419356,47.00752193548392]}}]}