{"type":"FeatureCollection","features":[{"type":"Feature","properties":{"codesPostaux":["18270"],"population":770,"nom":"Culan","code":"18083"},"geometry":{"type":"Point","coordinates":[2.3623603289473665,46.547930263157916]}}]}