{"type":"FeatureCollection","features":[{"type":"Feature","properties":{"codesPostaux":["18310"],"population":259,"nom":"Dampierre-en-Gra\u00e7ay","code":"18085"},"geometry":{"type":"Point","coordinates":[1.939525396825397,47.18555793650795]}}]}