{"type":"FeatureCollection","features":[{"type":"Feature","properties":{"codesPostaux":["18130"],"population":4121,"nom":"Dun-sur-Auron","code":"18087"},"geometry":{"type":"Point","coordinates":[2.575485566502464,46.87857586206894]}}]}