{"type":"FeatureCollection","features":[{"type":"Feature","properties":{"codesPostaux":["18800"],"population":1049,"nom":"Farges-en-Septaine","code":"18092"},"geometry":{"type":"Point","coordinates":[2.644306265822785,47.05790392405064]}}]}