{"type":"FeatureCollection","features":[{"type":"Feature","properties":{"codesPostaux":["18300"],"population":146,"nom":"Gardefort","code":"18098"},"geometry":{"type":"Point","coordinates":[2.8200552830188683,47.2593141509434]}}]}