{"type":"FeatureCollection","features":[{"type":"Feature","properties":{"codesPostaux":["18600"],"population":288,"nom":"Grossouvre","code":"18106"},"geometry":{"type":"Point","coordinates":[2.9311275694444436,46.87434527777778]}}]}