{"type":"FeatureCollection","features":[{"type":"Feature","properties":{"codesPostaux":["18200"],"population":130,"nom":"La Groutte","code":"18107"},"geometry":{"type":"Point","coordinates":[2.5135180000000004,46.690250400000004]}}]}