{"type":"FeatureCollection","features":[{"type":"Feature","properties":{"codesPostaux":["18260"],"population":525,"nom":"Jars","code":"18117"},"geometry":{"type":"Point","coordinates":[2.673660648148151,47.396620740740715]}}]}