{"type":"FeatureCollection","features":[{"type":"Feature","properties":{"codesPostaux":["18320"],"population":1416,"nom":"Jouet-sur-l'Aubois","code":"18118"},"geometry":{"type":"Point","coordinates":[3.0007008333333354,47.04436408333332]}}]}