{"type":"FeatureCollection","features":[{"type":"Feature","properties":{"codesPostaux":["18800"],"population":52,"nom":"Laverdines","code":"18123"},"geometry":{"type":"Point","coordinates":[2.7963838888888883,47.03328611111112]}}]}