{"type":"FeatureCollection","features":[{"type":"Feature","properties":{"codesPostaux":["18120"],"population":701,"nom":"Lury-sur-Arnon","code":"18134"},"geometry":{"type":"Point","coordinates":[2.0561048920863305,47.13571561151078]}}]}