{"type":"FeatureCollection","features":[{"type":"Feature","properties":{"codesPostaux":["18170"],"population":235,"nom":"Maisonnais","code":"18135"},"geometry":{"type":"Point","coordinates":[2.214118742857142,46.637624914285745]}}]}