{"type":"FeatureCollection","features":[{"type":"Feature","properties":{"codesPostaux":["18320"],"population":671,"nom":"Marseilles-l\u00e8s-Aubigny","code":"18139"},"geometry":{"type":"Point","coordinates":[2.990033521126761,47.06932492957746]}}]}