{"type":"FeatureCollection","features":[{"type":"Feature","properties":{"codesPostaux":["18170"],"population":311,"nom":"Mar\u00e7ais","code":"18136"},"geometry":{"type":"Point","coordinates":[2.3475536641221386,46.69719114503816]}}]}