{"type":"FeatureCollection","features":[{"type":"Feature","properties":{"codesPostaux":["18250"],"population":385,"nom":"Montigny","code":"18151"},"geometry":{"type":"Point","coordinates":[2.6976686746987952,47.23598987951806]}}]}