{"type":"FeatureCollection","features":[{"type":"Feature","properties":{"codesPostaux":["18600"],"population":419,"nom":"Mornay-sur-Allier","code":"18155"},"geometry":{"type":"Point","coordinates":[3.0099762626262625,46.81947484848482]}}]}