{"type":"FeatureCollection","features":[{"type":"Feature","properties":{"codesPostaux":["18170"],"population":322,"nom":"Morlac","code":"18153"},"geometry":{"type":"Point","coordinates":[2.3169263114754104,46.7206563934426]}}]}