{"type":"FeatureCollection","features":[{"type":"Feature","properties":{"codesPostaux":["18260"],"population":229,"nom":"Le Noyer","code":"18168"},"geometry":{"type":"Point","coordinates":[2.661628750000001,47.37340595588234]}}]}