{"type":"FeatureCollection","features":[{"type":"Feature","properties":{"codesPostaux":["18250"],"population":235,"nom":"Neuilly-en-Sancerre","code":"18162"},"geometry":{"type":"Point","coordinates":[2.6504699350649354,47.309015844155866]}}]}