{"type":"FeatureCollection","features":[{"type":"Feature","properties":{"codesPostaux":["18130"],"population":52,"nom":"Parnay","code":"18177"},"geometry":{"type":"Point","coordinates":[2.561347519379846,46.85198263565895]}}]}