{"type":"FeatureCollection","features":[{"type":"Feature","properties":{"codesPostaux":["18200"],"population":1882,"nom":"Orval","code":"18172"},"geometry":{"type":"Point","coordinates":[2.4661628235294115,46.721028352941175]}}]}