{"type":"FeatureCollection","features":[{"type":"Feature","properties":{"codesPostaux":["18200"],"population":230,"nom":"La Perche","code":"18178"},"geometry":{"type":"Point","coordinates":[2.573211267605633,46.63535450704226]}}]}