{"type":"FeatureCollection","features":[{"type":"Feature","properties":{"codesPostaux":["18340"],"population":1861,"nom":"Plaimpied-Givaudins","code":"18180"},"geometry":{"type":"Point","coordinates":[2.4297390131578953,47.0151040131579]}}]}