{"type":"FeatureCollection","features":[{"type":"Feature","properties":{"codesPostaux":["18290"],"population":525,"nom":"Plou","code":"18181"},"geometry":{"type":"Point","coordinates":[2.1546380662983435,47.03702629834254]}}]}