{"type":"FeatureCollection","features":[{"type":"Feature","properties":{"codesPostaux":["18110"],"population":1547,"nom":"Saint-\u00c9loy-de-Gy","code":"18206"},"geometry":{"type":"Point","coordinates":[2.329353165467626,47.16803021582733]}}]}