{"type":"FeatureCollection","features":[{"type":"Feature","properties":{"codesPostaux":["18320","18350"],"population":177,"nom":"Saint-Hilaire-de-Gondilly","code":"18215"},"geometry":{"type":"Point","coordinates":[2.9041581538461547,47.028035923076914]}}]}