{"type":"FeatureCollection","features":[{"type":"Feature","properties":{"codesPostaux":["18370"],"population":175,"nom":"Saint-Jeanvrin","code":"18217"},"geometry":{"type":"Point","coordinates":[2.243853576158942,46.596462450331146]}}]}