{"type":"FeatureCollection","features":[{"type":"Feature","properties":{"codesPostaux":["18140"],"population":369,"nom":"Saint-L\u00e9ger-le-Petit","code":"18220"},"geometry":{"type":"Point","coordinates":[2.9964113793103455,47.11371051724137]}}]}