{"type":"FeatureCollection","features":[{"type":"Feature","properties":{"codesPostaux":["18800"],"population":190,"nom":"Saligny-le-Vif","code":"18239"},"geometry":{"type":"Point","coordinates":[2.7659094339622636,47.040668301886775]}}]}