{"type":"FeatureCollection","features":[{"type":"Feature","properties":{"codesPostaux":["18300"],"population":413,"nom":"Sens-Beaujeu","code":"18249"},"geometry":{"type":"Point","coordinates":[2.68662932330827,47.33415714285713]}}]}