{"type":"FeatureCollection","features":[{"type":"Feature","properties":{"codesPostaux":["18390"],"population":699,"nom":"Savigny-en-Septaine","code":"18247"},"geometry":{"type":"Point","coordinates":[2.572327647058824,47.046055966386554]}}]}