{"type":"FeatureCollection","features":[{"type":"Feature","properties":{"codesPostaux":["18140"],"population":79,"nom":"S\u00e9vry","code":"18251"},"geometry":{"type":"Point","coordinates":[2.824251034482758,47.133709482758604]}}]}