{"type":"FeatureCollection","features":[{"type":"Feature","properties":{"codesPostaux":["18300"],"population":687,"nom":"Veaugues","code":"18272"},"geometry":{"type":"Point","coordinates":[2.754316132075473,47.26747132075475]}}]}