{"type":"FeatureCollection","features":[{"type":"Feature","properties":{"codesPostaux":["18210"],"population":37,"nom":"Verneuil","code":"18277"},"geometry":{"type":"Point","coordinates":[2.597696464646465,46.82179242424243]}}]}