{"type":"FeatureCollection","features":[{"type":"Feature","properties":{"codesPostaux":["18330"],"population":547,"nom":"Vouzeron","code":"18290"},"geometry":{"type":"Point","coordinates":[2.212299171974522,47.26844490445861]}}]}