{"type":"FeatureCollection","features":[{"type":"Feature","properties":{"codesPostaux":["19220"],"population":232,"nom":"Auriac","code":"19014"},"geometry":{"type":"Point","coordinates":[2.13842377952756,45.19904082677162]}}]}