{"type":"FeatureCollection","features":[{"type":"Feature","properties":{"codesPostaux":["19230"],"population":1156,"nom":"Arnac-Pompadour","code":"19011"},"geometry":{"type":"Point","coordinates":[1.3665513669064746,45.41362122302157]}}]}