{"type":"FeatureCollection","features":[{"type":"Feature","properties":{"codesPostaux":["19120"],"population":223,"nom":"Astaillac","code":"19012"},"geometry":{"type":"Point","coordinates":[1.8267834999999997,44.95322091666667]}}]}