{"type":"FeatureCollection","features":[{"type":"Feature","properties":{"codesPostaux":["19500"],"population":261,"nom":"Branceilles","code":"19029"},"geometry":{"type":"Point","coordinates":[1.7123006923076918,45.008223615384594]}}]}