{"type":"FeatureCollection","features":[{"type":"Feature","properties":{"codesPostaux":["19350"],"population":576,"nom":"Chabrignac","code":"19035"},"geometry":{"type":"Point","coordinates":[1.3415951999999998,45.31132559999999]}}]}