{"type":"FeatureCollection","features":[{"type":"Feature","properties":{"codesPostaux":["19450"],"population":1177,"nom":"Chamboulive","code":"19037"},"geometry":{"type":"Point","coordinates":[1.71028075,45.427699999999966]}}]}