{"type":"FeatureCollection","features":[{"type":"Feature","properties":{"codesPostaux":["19150"],"population":498,"nom":"Chanac-les-Mines","code":"19041"},"geometry":{"type":"Point","coordinates":[1.8141932701421801,45.26618677725116]}}]}