{"type":"FeatureCollection","features":[{"type":"Feature","properties":{"codesPostaux":["19190"],"population":372,"nom":"Le Chastang","code":"19048"},"geometry":{"type":"Point","coordinates":[1.734619591836735,45.179811020408195]}}]}