{"type":"FeatureCollection","features":[{"type":"Feature","properties":{"codesPostaux":["19600"],"population":679,"nom":"Chasteaux","code":"19049"},"geometry":{"type":"Point","coordinates":[1.466965495049506,45.08507900990099]}}]}