{"type":"FeatureCollection","features":[{"type":"Feature","properties":{"codesPostaux":["19500"],"population":413,"nom":"Chauffour-sur-Vell","code":"19050"},"geometry":{"type":"Point","coordinates":[1.6735162745098036,45.01972549019607]}}]}