{"type":"FeatureCollection","features":[{"type":"Feature","properties":{"codesPostaux":["19390"],"population":162,"nom":"Chaumeil","code":"19051"},"geometry":{"type":"Point","coordinates":[1.884300285714287,45.451981380952404]}}]}