{"type":"FeatureCollection","features":[{"type":"Feature","properties":{"codesPostaux":["19200"],"population":202,"nom":"Chaveroche","code":"19053"},"geometry":{"type":"Point","coordinates":[2.2497303813559326,45.56089563559323]}}]}