{"type":"FeatureCollection","features":[{"type":"Feature","properties":{"codesPostaux":["19150"],"population":1399,"nom":"Cornil","code":"19061"},"geometry":{"type":"Point","coordinates":[1.7028844848484848,45.21304203030304]}}]}