{"type":"FeatureCollection","features":[{"type":"Feature","properties":{"codesPostaux":["19340"],"population":76,"nom":"Couffy-sur-Sarsonne","code":"19064"},"geometry":{"type":"Point","coordinates":[2.34123593939394,45.66836678787878]}}]}