{"type":"FeatureCollection","features":[{"type":"Feature","properties":{"codesPostaux":["19600"],"population":122,"nom":"Estivals","code":"19077"},"geometry":{"type":"Point","coordinates":[1.4601652173913044,45.033845543478265]}}]}