{"type":"FeatureCollection","features":[{"type":"Feature","properties":{"codesPostaux":["19270"],"population":2602,"nom":"Donzenac","code":"19072"},"geometry":{"type":"Point","coordinates":[1.5295850359712237,45.23048381294963]}}]}