{"type":"FeatureCollection","features":[{"type":"Feature","properties":{"codesPostaux":["19300"],"population":4334,"nom":"\u00c9gletons","code":"19073"},"geometry":{"type":"Point","coordinates":[2.0353454666666657,45.423018666666685]}}]}