{"type":"FeatureCollection","features":[{"type":"Feature","properties":{"codesPostaux":["19300"],"population":45,"nom":"Grandsaigne","code":"19088"},"geometry":{"type":"Point","coordinates":[1.9319546718146712,45.48751135135133]}}]}