{"type":"FeatureCollection","features":[{"type":"Feature","properties":{"codesPostaux":["19340"],"population":135,"nom":"Feyt","code":"19083"},"geometry":{"type":"Point","coordinates":[2.4851278354978357,45.682329004328984]}}]}