{"type":"FeatureCollection","features":[{"type":"Feature","properties":{"codesPostaux":["19320"],"population":118,"nom":"Lafage-sur-Sombre","code":"19097"},"geometry":{"type":"Point","coordinates":[2.07108744680851,45.29173706382977]}}]}