{"type":"FeatureCollection","features":[{"type":"Feature","properties":{"codesPostaux":["19500"],"population":321,"nom":"Ligneyrac","code":"19115"},"geometry":{"type":"Point","coordinates":[1.618961897810219,45.04942306569341]}}]}