{"type":"FeatureCollection","features":[{"type":"Feature","properties":{"codesPostaux":["19210"],"population":235,"nom":"Montgibaud","code":"19144"},"geometry":{"type":"Point","coordinates":[1.4200664766839388,45.511135699481855]}}]}