{"type":"FeatureCollection","features":[{"type":"Feature","properties":{"codesPostaux":["19160"],"population":1760,"nom":"Neuvic","code":"19148"},"geometry":{"type":"Point","coordinates":[2.2585705594405607,45.35776303030303]}}]}