{"type":"FeatureCollection","features":[{"type":"Feature","properties":{"codesPostaux":["19130"],"population":3534,"nom":"Objat","code":"19153"},"geometry":{"type":"Point","coordinates":[1.4115421505376349,45.26558102150537]}}]}