{"type":"FeatureCollection","features":[{"type":"Feature","properties":{"codesPostaux":["19190"],"population":128,"nom":"Palazinges","code":"19156"},"geometry":{"type":"Point","coordinates":[1.6900519047619047,45.165437936507956]}}]}