{"type":"FeatureCollection","features":[{"type":"Feature","properties":{"codesPostaux":["19120"],"population":277,"nom":"Puy-d'Arnac","code":"19169"},"geometry":{"type":"Point","coordinates":[1.7765925294117648,45.024275882352924]}}]}