{"type":"FeatureCollection","features":[{"type":"Feature","properties":{"codesPostaux":["19350"],"population":190,"nom":"Rosiers-de-Juillac","code":"19177"},"geometry":{"type":"Point","coordinates":[1.3044442076502738,45.28802284153007]}}]}