{"type":"FeatureCollection","features":[{"type":"Feature","properties":{"codesPostaux":["19130"],"population":377,"nom":"Saint-Bonnet-la-Rivi\u00e8re","code":"19187"},"geometry":{"type":"Point","coordinates":[1.3569149230769237,45.29291569230771]}}]}