{"type":"FeatureCollection","features":[{"type":"Feature","properties":{"codesPostaux":["19600"],"population":658,"nom":"Saint-Cernin-de-Larche","code":"19191"},"geometry":{"type":"Point","coordinates":[1.4154680701754385,45.092797192982445]}}]}