{"type":"FeatureCollection","features":[{"type":"Feature","properties":{"codesPostaux":["19270"],"population":1828,"nom":"Sainte-F\u00e9r\u00e9ole","code":"19202"},"geometry":{"type":"Point","coordinates":[1.593271824644549,45.2312001421801]}}]}