{"type":"FeatureCollection","features":[{"type":"Feature","properties":{"codesPostaux":["19200"],"population":575,"nom":"Saint-Exup\u00e9ry-les-Roches","code":"19201"},"geometry":{"type":"Point","coordinates":[2.3664872843450486,45.5078627476038]}}]}