{"type":"FeatureCollection","features":[{"type":"Feature","properties":{"codesPostaux":["19160"],"population":63,"nom":"Sainte-Marie-Lapanouze","code":"19219"},"geometry":{"type":"Point","coordinates":[2.344516536585365,45.43366692682928]}}]}