{"type":"FeatureCollection","features":[{"type":"Feature","properties":{"codesPostaux":["19150"],"population":214,"nom":"Saint-Paul","code":"19235"},"geometry":{"type":"Point","coordinates":[1.8971592410714284,45.205648303571415]}}]}