{"type":"FeatureCollection","features":[{"type":"Feature","properties":{"codesPostaux":["19260"],"population":68,"nom":"Veix","code":"19281"},"geometry":{"type":"Point","coordinates":[1.8371928415300545,45.50335322404371]}}]}