{"type":"FeatureCollection","features":[{"type":"Feature","properties":{"codesPostaux":["19800"],"population":255,"nom":"Vitrac-sur-Montane","code":"19287"},"geometry":{"type":"Point","coordinates":[1.9269665410958912,45.37444852739725]}}]}