{"type":"FeatureCollection","features":[{"type":"Feature","properties":{"codesPostaux":["21400"],"population":185,"nom":"Aisey-sur-Seine","code":"21006"},"geometry":{"type":"Point","coordinates":[4.58760343023256,47.74789558139536]}}]}