{"type":"FeatureCollection","features":[{"type":"Feature","properties":{"codesPostaux":["21110"],"population":1358,"nom":"Aiserey","code":"21005"},"geometry":{"type":"Point","coordinates":[5.166753124999999,47.169830937500016]}}]}