{"type":"FeatureCollection","features":[{"type":"Feature","properties":{"codesPostaux":["21310"],"population":779,"nom":"Arceau","code":"21016"},"geometry":{"type":"Point","coordinates":[5.193940740740739,47.36660296296298]}}]}