{"type":"FeatureCollection","features":[{"type":"Feature","properties":{"codesPostaux":["21360"],"population":103,"nom":"Aubaine","code":"21030"},"geometry":{"type":"Point","coordinates":[4.729080729166665,47.136192864583286]}}]}