{"type":"FeatureCollection","features":[{"type":"Feature","properties":{"codesPostaux":["21360"],"population":847,"nom":"Bligny-sur-Ouche","code":"21087"},"geometry":{"type":"Point","coordinates":[4.67813205128205,47.11735394871796]}}]}