{"type":"FeatureCollection","features":[{"type":"Feature","properties":{"codesPostaux":["21690"],"population":133,"nom":"Boux-sous-Salmaise","code":"21098"},"geometry":{"type":"Point","coordinates":[4.649944436090228,47.47284263157896]}}]}