{"type":"FeatureCollection","features":[{"type":"Feature","properties":{"codesPostaux":["21560"],"population":836,"nom":"Bressey-sur-Tille","code":"21105"},"geometry":{"type":"Point","coordinates":[5.183278333333332,47.30763074074074]}}]}