{"type":"FeatureCollection","features":[{"type":"Feature","properties":{"codesPostaux":["21570"],"population":227,"nom":"Brion-sur-Ource","code":"21109"},"geometry":{"type":"Point","coordinates":[4.671166097560976,47.90742845528456]}}]}