{"type":"FeatureCollection","features":[{"type":"Feature","properties":{"codesPostaux":["21490"],"population":272,"nom":"Brognon","code":"21111"},"geometry":{"type":"Point","coordinates":[5.168996981132073,47.41313207547171]}}]}