{"type":"FeatureCollection","features":[{"type":"Feature","properties":{"codesPostaux":["21220"],"population":678,"nom":"Brochon","code":"21110"},"geometry":{"type":"Point","coordinates":[4.953834117647059,47.23721126050423]}}]}