{"type":"FeatureCollection","features":[{"type":"Feature","properties":{"codesPostaux":["21120"],"population":549,"nom":"Chaignay","code":"21127"},"geometry":{"type":"Point","coordinates":[5.0626913541666685,47.47697255208336]}}]}