{"type":"FeatureCollection","features":[{"type":"Feature","properties":{"codesPostaux":["21690"],"population":32,"nom":"Champrenault","code":"21141"},"geometry":{"type":"Point","coordinates":[4.679720789473684,47.400695921052616]}}]}