{"type":"FeatureCollection","features":[{"type":"Feature","properties":{"codesPostaux":["21400"],"population":170,"nom":"Charrey-sur-Seine","code":"21149"},"geometry":{"type":"Point","coordinates":[4.534189687499999,47.949346875]}}]}