{"type":"FeatureCollection","features":[{"type":"Feature","properties":{"codesPostaux":["21320"],"population":85,"nom":"Ch\u00e2teauneuf","code":"21152"},"geometry":{"type":"Point","coordinates":[4.643941371428571,47.21824422857143]}}]}