{"type":"FeatureCollection","features":[{"type":"Feature","properties":{"codesPostaux":["21610"],"population":171,"nom":"Chaume-et-Courchamp","code":"21158"},"geometry":{"type":"Point","coordinates":[5.36478291891892,47.583628648648656]}}]}