{"type":"FeatureCollection","features":[{"type":"Feature","properties":{"codesPostaux":["21400"],"population":5478,"nom":"Ch\u00e2tillon-sur-Seine","code":"21154"},"geometry":{"type":"Point","coordinates":[4.589944,47.860875931034485]}}]}