{"type":"FeatureCollection","features":[{"type":"Feature","properties":{"codesPostaux":["21110"],"population":815,"nom":"Collonges-l\u00e8s-Premi\u00e8res","code":"21183"},"geometry":{"type":"Point","coordinates":[5.2924725806451605,47.225156344086]}}]}