{"type":"FeatureCollection","features":[{"type":"Feature","properties":{"codesPostaux":["21160"],"population":655,"nom":"Corcelles-les-Monts","code":"21192"},"geometry":{"type":"Point","coordinates":[4.936516442307694,47.30335807692307]}}]}