{"type":"FeatureCollection","features":[{"type":"Feature","properties":{"codesPostaux":["21520"],"population":172,"nom":"Courban","code":"21202"},"geometry":{"type":"Point","coordinates":[4.737491328125001,47.91313734375]}}]}