{"type":"FeatureCollection","features":[{"type":"Feature","properties":{"codesPostaux":["21360"],"population":65,"nom":"Cussy-la-Colonne","code":"21221"},"geometry":{"type":"Point","coordinates":[4.647224318181819,47.04192011363637]}}]}