{"type":"FeatureCollection","features":[{"type":"Feature","properties":{"codesPostaux":["21150"],"population":339,"nom":"Darcey","code":"21226"},"geometry":{"type":"Point","coordinates":[4.571883853211008,47.54619733944953]}}]}