{"type":"FeatureCollection","features":[{"type":"Feature","properties":{"codesPostaux":["21510"],"population":46,"nom":"Duesme","code":"21235"},"geometry":{"type":"Point","coordinates":[4.691997551020409,47.63882027210885]}}]}