{"type":"FeatureCollection","features":[{"type":"Feature","properties":{"codesPostaux":["21190"],"population":249,"nom":"\u00c9baty","code":"21236"},"geometry":{"type":"Point","coordinates":[4.7828625925925925,46.925785000000005]}}]}