{"type":"FeatureCollection","features":[{"type":"Feature","properties":{"codesPostaux":["21270"],"population":308,"nom":"\u00c9tevaux","code":"21256"},"geometry":{"type":"Point","coordinates":[5.318162033898305,47.324026949152554]}}]}