{"type":"FeatureCollection","features":[{"type":"Feature","properties":{"codesPostaux":["21510"],"population":130,"nom":"\u00c9talante","code":"21253"},"geometry":{"type":"Point","coordinates":[4.759711428571429,47.63022851428572]}}]}