{"type":"FeatureCollection","features":[{"type":"Feature","properties":{"codesPostaux":["21490"],"population":152,"nom":"Flacey","code":"21266"},"geometry":{"type":"Point","coordinates":[5.142383098591549,47.4336442253521]}}]}