{"type":"FeatureCollection","features":[{"type":"Feature","properties":{"codesPostaux":["21150"],"population":304,"nom":"Flavigny-sur-Ozerain","code":"21271"},"geometry":{"type":"Point","coordinates":[4.518646185567007,47.50642525773195]}}]}