{"type":"FeatureCollection","features":[{"type":"Feature","properties":{"codesPostaux":["21580"],"population":60,"nom":"Fraignot-et-Vesvrotte","code":"21283"},"geometry":{"type":"Point","coordinates":[4.934462177419355,47.65090653225807]}}]}