{"type":"FeatureCollection","features":[{"type":"Feature","properties":{"codesPostaux":["21440"],"population":246,"nom":"Francheville","code":"21284"},"geometry":{"type":"Point","coordinates":[4.872639414634147,47.45270980487806]}}]}