{"type":"FeatureCollection","features":[{"type":"Feature","properties":{"codesPostaux":["21610"],"population":157,"nom":"Fontenelle","code":"21281"},"geometry":{"type":"Point","coordinates":[5.365976822429906,47.50281037383177]}}]}