{"type":"FeatureCollection","features":[{"type":"Feature","properties":{"codesPostaux":["21120"],"population":883,"nom":"Gemeaux","code":"21290"},"geometry":{"type":"Point","coordinates":[5.137876927710844,47.475695662650615]}}]}