{"type":"FeatureCollection","features":[{"type":"Feature","properties":{"codesPostaux":["21580"],"population":263,"nom":"Grancey-le-Ch\u00e2teau-Neuvelle","code":"21304"},"geometry":{"type":"Point","coordinates":[5.021225574468086,47.67628234042552]}}]}