{"type":"FeatureCollection","features":[{"type":"Feature","properties":{"codesPostaux":["21540"],"population":209,"nom":"Grenant-l\u00e8s-Sombernon","code":"21306"},"geometry":{"type":"Point","coordinates":[4.713307124999998,47.26845325000001]}}]}