{"type":"FeatureCollection","features":[{"type":"Feature","properties":{"codesPostaux":["21210"],"population":132,"nom":"Lacour-d'Arcenay","code":"21335"},"geometry":{"type":"Point","coordinates":[4.239021396648045,47.36290139664803]}}]}