{"type":"FeatureCollection","features":[{"type":"Feature","properties":{"codesPostaux":["21440"],"population":153,"nom":"Lamargelle","code":"21338"},"geometry":{"type":"Point","coordinates":[4.835849621993128,47.51548896907213]}}]}