{"type":"FeatureCollection","features":[{"type":"Feature","properties":{"codesPostaux":["21130"],"population":331,"nom":"Labergement-l\u00e8s-Auxonne","code":"21331"},"geometry":{"type":"Point","coordinates":[5.382588852459014,47.16089409836064]}}]}