{"type":"FeatureCollection","features":[{"type":"Feature","properties":{"codesPostaux":["21200"],"population":296,"nom":"Levernois","code":"21347"},"geometry":{"type":"Point","coordinates":[4.872788695652175,46.99230673913045]}}]}