{"type":"FeatureCollection","features":[{"type":"Feature","properties":{"codesPostaux":["21290"],"population":322,"nom":"Leuglay","code":"21346"},"geometry":{"type":"Point","coordinates":[4.816539922480618,47.81155147286823]}}]}