{"type":"FeatureCollection","features":[{"type":"Feature","properties":{"codesPostaux":["21600"],"population":8981,"nom":"Longvic","code":"21355"},"geometry":{"type":"Point","coordinates":[5.052207142857142,47.28963095238093]}}]}