{"type":"FeatureCollection","features":[{"type":"Feature","properties":{"codesPostaux":["21230"],"population":341,"nom":"Magnien","code":"21363"},"geometry":{"type":"Point","coordinates":[4.4333104104477625,47.107695447761174]}}]}