{"type":"FeatureCollection","features":[{"type":"Feature","properties":{"codesPostaux":["21130"],"population":267,"nom":"Magny-Montarlot","code":"21367"},"geometry":{"type":"Point","coordinates":[5.345618904109589,47.246661506849314]}}]}