{"type":"FeatureCollection","features":[{"type":"Feature","properties":{"codesPostaux":["21410"],"population":730,"nom":"M\u00e2lain","code":"21373"},"geometry":{"type":"Point","coordinates":[4.795599272727272,47.32027281818183]}}]}