{"type":"FeatureCollection","features":[{"type":"Feature","properties":{"codesPostaux":["21120"],"population":321,"nom":"Marey-sur-Tille","code":"21385"},"geometry":{"type":"Point","coordinates":[5.0796699378882,47.59262049689439]}}]}