{"type":"FeatureCollection","features":[{"type":"Feature","properties":{"codesPostaux":["21400"],"population":154,"nom":"Massingy","code":"21393"},"geometry":{"type":"Point","coordinates":[4.59939443298969,47.90124927835052]}}]}