{"type":"FeatureCollection","features":[{"type":"Feature","properties":{"codesPostaux":["21320"],"population":65,"nom":"Martrois","code":"21392"},"geometry":{"type":"Point","coordinates":[4.551082033898304,47.305914830508485]}}]}