{"type":"FeatureCollection","features":[{"type":"Feature","properties":{"codesPostaux":["21380"],"population":1577,"nom":"Messigny-et-Vantoux","code":"21408"},"geometry":{"type":"Point","coordinates":[4.995675248226952,47.42242226950353]}}]}