{"type":"FeatureCollection","features":[{"type":"Feature","properties":{"codesPostaux":["21510"],"population":37,"nom":"Meulson","code":"21410"},"geometry":{"type":"Point","coordinates":[4.700173370786515,47.69000191011235]}}]}