{"type":"FeatureCollection","features":[{"type":"Feature","properties":{"codesPostaux":["21510"],"population":205,"nom":"Minot","code":"21415"},"geometry":{"type":"Point","coordinates":[4.878520716845875,47.664375555555516]}}]}