{"type":"FeatureCollection","features":[{"type":"Feature","properties":{"codesPostaux":["21140"],"population":374,"nom":"Millery","code":"21413"},"geometry":{"type":"Point","coordinates":[4.3204936419753075,47.51648450617284]}}]}