{"type":"FeatureCollection","features":[{"type":"Feature","properties":{"codesPostaux":["21290"],"population":92,"nom":"Montmoyen","code":"21438"},"geometry":{"type":"Point","coordinates":[4.790651526717557,47.7249728244275]}}]}