{"type":"FeatureCollection","features":[{"type":"Feature","properties":{"codesPostaux":["21210"],"population":153,"nom":"Montlay-en-Auxois","code":"21434"},"geometry":{"type":"Point","coordinates":[4.2710905907173,47.33306092827006]}}]}