{"type":"FeatureCollection","features":[{"type":"Feature","properties":{"codesPostaux":["21700"],"population":5572,"nom":"Nuits-Saint-Georges","code":"21464"},"geometry":{"type":"Point","coordinates":[4.932241818181816,47.14961532467533]}}]}