{"type":"FeatureCollection","features":[{"type":"Feature","properties":{"codesPostaux":["21450"],"population":37,"nom":"Oigny","code":"21466"},"geometry":{"type":"Point","coordinates":[4.72439824,47.585963520000014]}}]}