{"type":"FeatureCollection","features":[{"type":"Feature","properties":{"codesPostaux":["21510"],"population":49,"nom":"Origny","code":"21470"},"geometry":{"type":"Point","coordinates":[4.631008390804599,47.711336091954024]}}]}