{"type":"FeatureCollection","features":[{"type":"Feature","properties":{"codesPostaux":["21370"],"population":390,"nom":"Prenois","code":"21508"},"geometry":{"type":"Point","coordinates":[4.907540560747665,47.37439495327102]}}]}