{"type":"FeatureCollection","features":[{"type":"Feature","properties":{"codesPostaux":["21560"],"population":812,"nom":"Remilly-sur-Tille","code":"21521"},"geometry":{"type":"Point","coordinates":[5.2338875280898876,47.306970561797755]}}]}