{"type":"FeatureCollection","features":[{"type":"Feature","properties":{"codesPostaux":["21150"],"population":152,"nom":"La Roche-Vanneau","code":"21528"},"geometry":{"type":"Point","coordinates":[4.525832727272729,47.468146909090926]}}]}