{"type":"FeatureCollection","features":[{"type":"Feature","properties":{"codesPostaux":["21390"],"population":42,"nom":"Roilly","code":"21529"},"geometry":{"type":"Point","coordinates":[4.34307021978022,47.416745604395594]}}]}