{"type":"FeatureCollection","features":[{"type":"Feature","properties":{"codesPostaux":["21260"],"population":270,"nom":"Sacquenay","code":"21536"},"geometry":{"type":"Point","coordinates":[5.325614000000002,47.58630838709677]}}]}