{"type":"FeatureCollection","features":[{"type":"Feature","properties":{"codesPostaux":["21530"],"population":164,"nom":"Saint-Germain-de-Mod\u00e9on","code":"21548"},"geometry":{"type":"Point","coordinates":[4.125967335907334,47.37321837837838]}}]}