{"type":"FeatureCollection","features":[{"type":"Feature","properties":{"codesPostaux":["21410"],"population":124,"nom":"Saint-Jean-de-B\u0153uf","code":"21553"},"geometry":{"type":"Point","coordinates":[4.761048947368419,47.21171221052632]}}]}