{"type":"FeatureCollection","features":[{"type":"Feature","properties":{"codesPostaux":["21350"],"population":162,"nom":"Saint-Thibault","code":"21576"},"geometry":{"type":"Point","coordinates":[4.461812463768118,47.37512543478259]}}]}