{"type":"FeatureCollection","features":[{"type":"Feature","properties":{"codesPostaux":["21910"],"population":691,"nom":"Saulon-la-Rue","code":"21586"},"geometry":{"type":"Point","coordinates":[5.053193928571427,47.22494607142856]}}]}