{"type":"FeatureCollection","features":[{"type":"Feature","properties":{"codesPostaux":["21380"],"population":96,"nom":"Saussy","code":"21589"},"geometry":{"type":"Point","coordinates":[4.980743771929824,47.46132078947368]}}]}