{"type":"FeatureCollection","features":[{"type":"Feature","properties":{"codesPostaux":["21260"],"population":2438,"nom":"Selongey","code":"21599"},"geometry":{"type":"Point","coordinates":[5.194682564102564,47.59751970695969]}}]}