{"type":"FeatureCollection","features":[{"type":"Feature","properties":{"codesPostaux":["21420"],"population":1332,"nom":"Savigny-l\u00e8s-Beaune","code":"21590"},"geometry":{"type":"Point","coordinates":[4.8048413372093,47.08515215116279]}}]}