{"type":"FeatureCollection","features":[{"type":"Feature","properties":{"codesPostaux":["21250"],"population":2435,"nom":"Seurre","code":"21607"},"geometry":{"type":"Point","coordinates":[5.153501649484538,47.00576835051545]}}]}