{"type":"FeatureCollection","features":[{"type":"Feature","properties":{"codesPostaux":["21540"],"population":969,"nom":"Sombernon","code":"21611"},"geometry":{"type":"Point","coordinates":[4.706567062937065,47.30982657342655]}}]}