{"type":"FeatureCollection","features":[{"type":"Feature","properties":{"codesPostaux":["21110"],"population":221,"nom":"Tart-le-Bas","code":"21622"},"geometry":{"type":"Point","coordinates":[5.2293871951219515,47.20449280487806]}}]}