{"type":"FeatureCollection","features":[{"type":"Feature","properties":{"codesPostaux":["21270"],"population":144,"nom":"Tellecey","code":"21624"},"geometry":{"type":"Point","coordinates":[5.297161071428569,47.29129488095237]}}]}