{"type":"FeatureCollection","features":[{"type":"Feature","properties":{"codesPostaux":["21310"],"population":166,"nom":"Troch\u00e8res","code":"21644"},"geometry":{"type":"Point","coordinates":[5.315021555555554,47.34831788888888]}}]}