{"type":"FeatureCollection","features":[{"type":"Feature","properties":{"codesPostaux":["21500"],"population":459,"nom":"Touillon","code":"21641"},"geometry":{"type":"Point","coordinates":[4.42901119402985,47.654907985074644]}}]}