{"type":"FeatureCollection","features":[{"type":"Feature","properties":{"codesPostaux":["21170"],"population":628,"nom":"Trouhans","code":"21645"},"geometry":{"type":"Point","coordinates":[5.268060125,47.15133687500001]}}]}