{"type":"FeatureCollection","features":[{"type":"Feature","properties":{"codesPostaux":["21460"],"population":451,"nom":"Toutry","code":"21642"},"geometry":{"type":"Point","coordinates":[4.129527075471697,47.50043518867923]}}]}