{"type":"FeatureCollection","features":[{"type":"Feature","properties":{"codesPostaux":["21430"],"population":45,"nom":"Villiers-en-Morvan","code":"21703"},"geometry":{"type":"Point","coordinates":[4.260728796992481,47.1435154887218]}}]}