{"type":"FeatureCollection","features":[{"type":"Feature","properties":{"codesPostaux":["22100"],"population":1069,"nom":"Bobital","code":"22008"},"geometry":{"type":"Point","coordinates":[-2.096685567010309,48.41252618556698]}}]}