{"type":"FeatureCollection","features":[{"type":"Feature","properties":{"codesPostaux":["22810"],"population":1102,"nom":"Belle-Isle-en-Terre","code":"22005"},"geometry":{"type":"Point","coordinates":[-3.379740602409641,48.532159638554205]}}]}