{"type":"FeatureCollection","features":[{"type":"Feature","properties":{"codesPostaux":["22390"],"population":2339,"nom":"Bourbriac","code":"22013"},"geometry":{"type":"Point","coordinates":[-3.1958220000000033,48.47142628571429]}}]}