{"type":"FeatureCollection","features":[{"type":"Feature","properties":{"codesPostaux":["22130"],"population":1118,"nom":"Bourseul","code":"22014"},"geometry":{"type":"Point","coordinates":[-2.2597907567567566,48.478223]}}]}