{"type":"FeatureCollection","features":[{"type":"Feature","properties":{"codesPostaux":["22450"],"population":882,"nom":"Camlez","code":"22028"},"geometry":{"type":"Point","coordinates":[-3.3162391978609636,48.783132085561505]}}]}