{"type":"FeatureCollection","features":[{"type":"Feature","properties":{"codesPostaux":["22160"],"population":369,"nom":"Duault","code":"22052"},"geometry":{"type":"Point","coordinates":[-3.4391054976303326,48.36386362559244]}}]}