{"type":"FeatureCollection","features":[{"type":"Feature","properties":{"codesPostaux":["22610"],"population":314,"nom":"Kerbors","code":"22085"},"geometry":{"type":"Point","coordinates":[-3.181436296296295,48.823122370370356]}}]}