{"type":"FeatureCollection","features":[{"type":"Feature","properties":{"codesPostaux":["22400"],"population":1372,"nom":"Land\u00e9hen","code":"22098"},"geometry":{"type":"Point","coordinates":[-2.5423380158730167,48.419019999999975]}}]}