{"type":"FeatureCollection","features":[{"type":"Feature","properties":{"codesPostaux":["22360"],"population":7427,"nom":"Langueux","code":"22106"},"geometry":{"type":"Point","coordinates":[-2.707515165562915,48.500692582781454]}}]}