{"type":"FeatureCollection","features":[{"type":"Feature","properties":{"codesPostaux":["22580"],"population":264,"nom":"Lanloup","code":"22109"},"geometry":{"type":"Point","coordinates":[-2.9695821126760555,48.709602112676066]}}]}