{"type":"FeatureCollection","features":[{"type":"Feature","properties":{"codesPostaux":["22170"],"population":1252,"nom":"Lanrodec","code":"22116"},"geometry":{"type":"Point","coordinates":[-3.046915314960631,48.4962087007874]}}]}