{"type":"FeatureCollection","features":[{"type":"Feature","properties":{"codesPostaux":["22420"],"population":572,"nom":"Lanvellec","code":"22119"},"geometry":{"type":"Point","coordinates":[-3.531475192307694,48.60976392857142]}}]}