{"type":"FeatureCollection","features":[{"type":"Feature","properties":{"codesPostaux":["22480"],"population":537,"nom":"Lanrivain","code":"22115"},"geometry":{"type":"Point","coordinates":[-3.2177747991543364,48.35728695560255]}}]}