{"type":"FeatureCollection","features":[{"type":"Feature","properties":{"codesPostaux":["22810"],"population":66,"nom":"Loc-Envel","code":"22129"},"geometry":{"type":"Point","coordinates":[-3.411728947368422,48.508800131578965]}}]}