{"type":"FeatureCollection","features":[{"type":"Feature","properties":{"codesPostaux":["22570"],"population":209,"nom":"Lescou\u00ebt-Gouarec","code":"22124"},"geometry":{"type":"Point","coordinates":[-3.2105022549019604,48.165493006535954]}}]}