{"type":"FeatureCollection","features":[{"type":"Feature","properties":{"codesPostaux":["22960"],"population":6346,"nom":"Pl\u00e9dran","code":"22176"},"geometry":{"type":"Point","coordinates":[-2.7379867866323906,48.44447151670953]}}]}