{"type":"FeatureCollection","features":[{"type":"Feature","properties":{"codesPostaux":["22940"],"population":4246,"nom":"Plaintel","code":"22171"},"geometry":{"type":"Point","coordinates":[-2.8099954938271625,48.4042018312757]}}]}