{"type":"FeatureCollection","features":[{"type":"Feature","properties":{"codesPostaux":["22560"],"population":3983,"nom":"Pleumeur-Bodou","code":"22198"},"geometry":{"type":"Point","coordinates":[-3.5461523255813923,48.79805375415284]}}]}