{"type":"FeatureCollection","features":[{"type":"Feature","properties":{"codesPostaux":["22260"],"population":1272,"nom":"Plo\u00ebzal","code":"22204"},"geometry":{"type":"Point","coordinates":[-3.1826846808510636,48.71887493617024]}}]}