{"type":"FeatureCollection","features":[{"type":"Feature","properties":{"codesPostaux":["22780"],"population":422,"nom":"Plougras","code":"22217"},"geometry":{"type":"Point","coordinates":[-3.559425187165778,48.506401550802096]}}]}