{"type":"FeatureCollection","features":[{"type":"Feature","properties":{"codesPostaux":["22440"],"population":11569,"nom":"Ploufragan","code":"22215"},"geometry":{"type":"Point","coordinates":[-2.8032516727272716,48.4887625090909]}}]}