{"type":"FeatureCollection","features":[{"type":"Feature","properties":{"codesPostaux":["22780"],"population":735,"nom":"Ploun\u00e9rin","code":"22227"},"geometry":{"type":"Point","coordinates":[-3.5485570802919697,48.56597766423356]}}]}