{"type":"FeatureCollection","features":[{"type":"Feature","properties":{"codesPostaux":["22110"],"population":1742,"nom":"Plouguern\u00e9vel","code":"22220"},"geometry":{"type":"Point","coordinates":[-3.242454474474473,48.239518258258265]}}]}