{"type":"FeatureCollection","features":[{"type":"Feature","properties":{"codesPostaux":["22170"],"population":1133,"nom":"Plouvara","code":"22234"},"geometry":{"type":"Point","coordinates":[-2.9378765109890104,48.49677085164835]}}]}