{"type":"FeatureCollection","features":[{"type":"Feature","properties":{"codesPostaux":["22310"],"population":554,"nom":"Plufur","code":"22238"},"geometry":{"type":"Point","coordinates":[-3.5746005208333327,48.61578927083331]}}]}