{"type":"FeatureCollection","features":[{"type":"Feature","properties":{"codesPostaux":["22290"],"population":749,"nom":"Pludual","code":"22236"},"geometry":{"type":"Point","coordinates":[-2.991561721611722,48.66537435897432]}}]}