{"type":"FeatureCollection","features":[{"type":"Feature","properties":{"codesPostaux":["22320"],"population":507,"nom":"Plussulien","code":"22244"},"geometry":{"type":"Point","coordinates":[-3.0645831545741307,48.28355451104102]}}]}