{"type":"FeatureCollection","features":[{"type":"Feature","properties":{"codesPostaux":["22140"],"population":1015,"nom":"Pluzunet","code":"22245"},"geometry":{"type":"Point","coordinates":[-3.374653839285713,48.63489089285715]}}]}