{"type":"FeatureCollection","features":[{"type":"Feature","properties":{"codesPostaux":["22450"],"population":395,"nom":"Quemperven","code":"22257"},"geometry":{"type":"Point","coordinates":[-3.3397067015706794,48.72752795811522]}}]}