{"type":"FeatureCollection","features":[{"type":"Feature","properties":{"codesPostaux":["22260"],"population":234,"nom":"Runan","code":"22269"},"geometry":{"type":"Point","coordinates":[-3.2303298757763983,48.685105838509315]}}]}