{"type":"FeatureCollection","features":[{"type":"Feature","properties":{"codesPostaux":["22110"],"population":3224,"nom":"Rostrenen","code":"22266"},"geometry":{"type":"Point","coordinates":[-3.30805782312925,48.22066819727888]}}]}