{"type":"FeatureCollection","features":[{"type":"Feature","properties":{"codesPostaux":["22380"],"population":3449,"nom":"Saint-Cast-le-Guildo","code":"22282"},"geometry":{"type":"Point","coordinates":[-2.2479019325153398,48.60827395705522]}}]}