{"type":"FeatureCollection","features":[{"type":"Feature","properties":{"codesPostaux":["22800"],"population":289,"nom":"Saint-Gildas","code":"22291"},"geometry":{"type":"Point","coordinates":[-3.007460752212388,48.42031699115045]}}]}