{"type":"FeatureCollection","features":[{"type":"Feature","properties":{"codesPostaux":["22290"],"population":412,"nom":"Saint-Gilles-les-Bois","code":"22293"},"geometry":{"type":"Point","coordinates":[-3.0885049999999996,48.658338205128224]}}]}