{"type":"FeatureCollection","features":[{"type":"Feature","properties":{"codesPostaux":["22350"],"population":477,"nom":"Saint-Jouan-de-l'Isle","code":"22305"},"geometry":{"type":"Point","coordinates":[-2.175424630872483,48.265142147651005]}}]}