{"type":"FeatureCollection","features":[{"type":"Feature","properties":{"codesPostaux":["22140"],"population":521,"nom":"Saint-Laurent","code":"22310"},"geometry":{"type":"Point","coordinates":[-3.2444728921568626,48.616115147058814]}}]}