{"type":"FeatureCollection","features":[{"type":"Feature","properties":{"codesPostaux":["22410"],"population":2995,"nom":"Saint-Quay-Portrieux","code":"22325"},"geometry":{"type":"Point","coordinates":[-2.8380658333333333,48.656857555555575]}}]}