{"type":"FeatureCollection","features":[{"type":"Feature","properties":{"codesPostaux":["22270"],"population":535,"nom":"Saint-Rieul","code":"22326"},"geometry":{"type":"Point","coordinates":[-2.4144089333333336,48.44387879999999]}}]}