{"type":"FeatureCollection","features":[{"type":"Feature","properties":{"codesPostaux":["22510"],"population":477,"nom":"Saint-Trimo\u00ebl","code":"22332"},"geometry":{"type":"Point","coordinates":[-2.543841049382717,48.397739259259275]}}]}