{"type":"FeatureCollection","features":[{"type":"Feature","properties":{"codesPostaux":["22200"],"population":802,"nom":"Squiffiec","code":"22338"},"geometry":{"type":"Point","coordinates":[-3.1610004385964925,48.63558368421055]}}]}