{"type":"FeatureCollection","features":[{"type":"Feature","properties":{"codesPostaux":["22570"],"population":137,"nom":"Saint-Igeaux","code":"22334"},"geometry":{"type":"Point","coordinates":[-3.1188502966101685,48.283180932203415]}}]}