{"type":"FeatureCollection","features":[{"type":"Feature","properties":{"codesPostaux":["22340"],"population":700,"nom":"Tr\u00e9brivan","code":"22344"},"geometry":{"type":"Point","coordinates":[-3.4803542929292943,48.31835388888887]}}]}