{"type":"FeatureCollection","features":[{"type":"Feature","properties":{"codesPostaux":["22300"],"population":1432,"nom":"Tr\u00e9drez-Locqu\u00e9meau","code":"22349"},"geometry":{"type":"Point","coordinates":[-3.5644840131578936,48.709450131578954]}}]}