{"type":"FeatureCollection","features":[{"type":"Feature","properties":{"codesPostaux":["22540"],"population":981,"nom":"Tr\u00e9glamus","code":"22354"},"geometry":{"type":"Point","coordinates":[-3.2632346538461556,48.55950892307693]}}]}