{"type":"FeatureCollection","features":[{"type":"Feature","properties":{"codesPostaux":["22950"],"population":8172,"nom":"Tr\u00e9gueux","code":"22360"},"geometry":{"type":"Point","coordinates":[-2.7443258904109586,48.477143869863006]}}]}