{"type":"FeatureCollection","features":[{"type":"Feature","properties":{"codesPostaux":["22290"],"population":345,"nom":"Tr\u00e9m\u00e9ven","code":"22370"},"geometry":{"type":"Point","coordinates":[-3.034967197802199,48.67476895604397]}}]}