{"type":"FeatureCollection","features":[{"type":"Feature","properties":{"codesPostaux":["23480"],"population":260,"nom":"Ars","code":"23007"},"geometry":{"type":"Point","coordinates":[2.087359678456591,46.002238906752375]}}]}