{"type":"FeatureCollection","features":[{"type":"Feature","properties":{"codesPostaux":["23150"],"population":1497,"nom":"Ahun","code":"23001"},"geometry":{"type":"Point","coordinates":[2.0229855742296925,46.08918717086837]}}]}