{"type":"FeatureCollection","features":[{"type":"Feature","properties":{"codesPostaux":["23170"],"population":768,"nom":"Budeli\u00e8re","code":"23035"},"geometry":{"type":"Point","coordinates":[2.4714254444444452,46.22204340740739]}}]}