{"type":"FeatureCollection","features":[{"type":"Feature","properties":{"codesPostaux":["23130"],"population":110,"nom":"Le Chauchet","code":"23058"},"geometry":{"type":"Point","coordinates":[2.32943396694215,46.10770169421489]}}]}