{"type":"FeatureCollection","features":[{"type":"Feature","properties":{"codesPostaux":["23700"],"population":202,"nom":"Chard","code":"23053"},"geometry":{"type":"Point","coordinates":[2.4881840760869554,45.9504548369565]}}]}