{"type":"FeatureCollection","features":[{"type":"Feature","properties":{"codesPostaux":["23480"],"population":187,"nom":"Le Donzeil","code":"23074"},"geometry":{"type":"Point","coordinates":[1.9874360621761658,46.03573590673573]}}]}