{"type":"FeatureCollection","features":[{"type":"Feature","properties":{"codesPostaux":["23110"],"population":260,"nom":"Fontani\u00e8res","code":"23083"},"geometry":{"type":"Point","coordinates":[2.5232490566037735,46.106509874213835]}}]}