{"type":"FeatureCollection","features":[{"type":"Feature","properties":{"codesPostaux":["23480"],"population":247,"nom":"Frans\u00e8ches","code":"23086"},"geometry":{"type":"Point","coordinates":[2.0454304225352122,46.030465739436636]}}]}