{"type":"FeatureCollection","features":[{"type":"Feature","properties":{"codesPostaux":["23220"],"population":167,"nom":"Linard","code":"23109"},"geometry":{"type":"Point","coordinates":[1.8768808000000008,46.36696]}}]}