{"type":"FeatureCollection","features":[{"type":"Feature","properties":{"codesPostaux":["23150"],"population":204,"nom":"Maisonnisses","code":"23118"},"geometry":{"type":"Point","coordinates":[1.904612146596859,46.05780083769632]}}]}