{"type":"FeatureCollection","features":[{"type":"Feature","properties":{"codesPostaux":["23150"],"population":162,"nom":"Moutier-d'Ahun","code":"23138"},"geometry":{"type":"Point","coordinates":[2.0643851879699238,46.10011894736844]}}]}