{"type":"FeatureCollection","features":[{"type":"Feature","properties":{"codesPostaux":["23360"],"population":564,"nom":"M\u00e9asnes","code":"23130"},"geometry":{"type":"Point","coordinates":[1.7761653061224485,46.42810721088434]}}]}