{"type":"FeatureCollection","features":[{"type":"Feature","properties":{"codesPostaux":["23500"],"population":253,"nom":"La Nouaille","code":"23144"},"geometry":{"type":"Point","coordinates":[2.075224072948328,45.8465819148936]}}]}