{"type":"FeatureCollection","features":[{"type":"Feature","properties":{"codesPostaux":["23200"],"population":297,"nom":"N\u00e9oux","code":"23142"},"geometry":{"type":"Point","coordinates":[2.257892011834321,45.91759869822482]}}]}