{"type":"FeatureCollection","features":[{"type":"Feature","properties":{"codesPostaux":["23500"],"population":138,"nom":"Poussanges","code":"23158"},"geometry":{"type":"Point","coordinates":[2.2200273451327446,45.82356345132741]}}]}