{"type":"FeatureCollection","features":[{"type":"Feature","properties":{"codesPostaux":["23250"],"population":364,"nom":"Pontarion","code":"23155"},"geometry":{"type":"Point","coordinates":[1.84835485380117,45.99664783625732]}}]}