{"type":"FeatureCollection","features":[{"type":"Feature","properties":{"codesPostaux":["23110"],"population":403,"nom":"Sannat","code":"23167"},"geometry":{"type":"Point","coordinates":[2.4149057881773386,46.12414849753696]}}]}