{"type":"FeatureCollection","features":[{"type":"Feature","properties":{"codesPostaux":["23700"],"population":123,"nom":"Sermur","code":"23171"},"geometry":{"type":"Point","coordinates":[2.415935592417063,45.972839620853094]}}]}