{"type":"FeatureCollection","features":[{"type":"Feature","properties":{"codesPostaux":["23130"],"population":212,"nom":"Saint-Dizier-la-Tour","code":"23187"},"geometry":{"type":"Point","coordinates":[2.1492332936507936,46.141663928571425]}}]}