{"type":"FeatureCollection","features":[{"type":"Feature","properties":{"codesPostaux":["23250"],"population":361,"nom":"Saint-Georges-la-Pouge","code":"23197"},"geometry":{"type":"Point","coordinates":[1.9613294883720942,46.00073320930232]}}]}