{"type":"FeatureCollection","features":[{"type":"Feature","properties":{"codesPostaux":["23000"],"population":2444,"nom":"Sainte-Feyre","code":"23193"},"geometry":{"type":"Point","coordinates":[1.9135064387464358,46.15655279202279]}}]}