{"type":"FeatureCollection","features":[{"type":"Feature","properties":{"codesPostaux":["23500"],"population":144,"nom":"Saint-Georges-Nigremont","code":"23198"},"geometry":{"type":"Point","coordinates":[2.2735924806201546,45.8372911627907]}}]}