{"type":"FeatureCollection","features":[{"type":"Feature","properties":{"codesPostaux":["23190"],"population":169,"nom":"Saint-Domet","code":"23190"},"geometry":{"type":"Point","coordinates":[2.2988026315789463,46.04641931888547]}}]}