{"type":"FeatureCollection","features":[{"type":"Feature","properties":{"codesPostaux":["23130"],"population":155,"nom":"Saint-Julien-le-Ch\u00e2tel","code":"23204"},"geometry":{"type":"Point","coordinates":[2.2652976760563375,46.11929535211267]}}]}