{"type":"FeatureCollection","features":[{"type":"Feature","properties":{"codesPostaux":["23150"],"population":210,"nom":"Saint-Hilaire-la-Plaine","code":"23201"},"geometry":{"type":"Point","coordinates":[1.9861960071942455,46.115327661870545]}}]}