{"type":"FeatureCollection","features":[{"type":"Feature","properties":{"codesPostaux":["23460"],"population":139,"nom":"Saint-Marc-\u00e0-Loubaud","code":"23212"},"geometry":{"type":"Point","coordinates":[1.9785274429223747,45.845492876712356]}}]}