{"type":"FeatureCollection","features":[{"type":"Feature","properties":{"codesPostaux":["23400"],"population":227,"nom":"Saint-Moreil","code":"23223"},"geometry":{"type":"Point","coordinates":[1.6931167834394898,45.862352261146505]}}]}