{"type":"FeatureCollection","features":[{"type":"Feature","properties":{"codesPostaux":["23260"],"population":111,"nom":"Saint-Oradoux-pr\u00e8s-Crocq","code":"23225"},"geometry":{"type":"Point","coordinates":[2.375459827586207,45.88898193965515]}}]}