{"type":"FeatureCollection","features":[{"type":"Feature","properties":{"codesPostaux":["23230"],"population":121,"nom":"Trois-Fonds","code":"23255"},"geometry":{"type":"Point","coordinates":[2.2356347096774187,46.242183419354845]}}]}