{"type":"FeatureCollection","features":[{"type":"Feature","properties":{"codesPostaux":["23170"],"population":144,"nom":"Tardes","code":"23251"},"geometry":{"type":"Point","coordinates":[2.362861901140684,46.14387536121669]}}]}