{"type":"FeatureCollection","features":[{"type":"Feature","properties":{"codesPostaux":["23260"],"population":80,"nom":"La Villeneuve","code":"23265"},"geometry":{"type":"Point","coordinates":[2.414742622950819,45.89616991803277]}}]}