{"type":"FeatureCollection","features":[{"type":"Feature","properties":{"codesPostaux":["24260"],"population":288,"nom":"Audrix","code":"24015"},"geometry":{"type":"Point","coordinates":[0.9433085161290322,44.884207612903204]}}]}