{"type":"FeatureCollection","features":[{"type":"Feature","properties":{"codesPostaux":["24420"],"population":1213,"nom":"Antonne-et-Trigonant","code":"24011"},"geometry":{"type":"Point","coordinates":[0.8297980745341617,45.22371031055899]}}]}