{"type":"FeatureCollection","features":[{"type":"Feature","properties":{"codesPostaux":["24290"],"population":400,"nom":"Auriac-du-P\u00e9rigord","code":"24018"},"geometry":{"type":"Point","coordinates":[1.119134979079497,45.11301673640163]}}]}