{"type":"FeatureCollection","features":[{"type":"Feature","properties":{"codesPostaux":["24230"],"population":296,"nom":"Bonneville-et-Saint-Avit-de-Fumadi\u00e8res","code":"24048"},"geometry":{"type":"Point","coordinates":[0.07928486956521741,44.886904173913]}}]}