{"type":"FeatureCollection","features":[{"type":"Feature","properties":{"codesPostaux":["24540"],"population":188,"nom":"Biron","code":"24043"},"geometry":{"type":"Point","coordinates":[0.8724536538461538,44.621476923076926]}}]}