{"type":"FeatureCollection","features":[{"type":"Feature","properties":{"codesPostaux":["24130"],"population":198,"nom":"Bosset","code":"24051"},"geometry":{"type":"Point","coordinates":[0.36311614035087714,44.95138690058479]}}]}