{"type":"FeatureCollection","features":[{"type":"Feature","properties":{"codesPostaux":["24350"],"population":375,"nom":"Bussac","code":"24069"},"geometry":{"type":"Point","coordinates":[0.601372451612903,45.27226670967745]}}]}