{"type":"FeatureCollection","features":[{"type":"Feature","properties":{"codesPostaux":["24550"],"population":289,"nom":"Campagnac-l\u00e8s-Quercy","code":"24075"},"geometry":{"type":"Point","coordinates":[1.183685906432748,44.699948128654974]}}]}