{"type":"FeatureCollection","features":[{"type":"Feature","properties":{"codesPostaux":["24290"],"population":516,"nom":"La Chapelle-Aubareil","code":"24106"},"geometry":{"type":"Point","coordinates":[1.1905900507614218,45.003254111675105]}}]}