{"type":"FeatureCollection","features":[{"type":"Feature","properties":{"codesPostaux":["24650"],"population":4293,"nom":"Chancelade","code":"24102"},"geometry":{"type":"Point","coordinates":[0.6572336986301369,45.212645890411]}}]}