{"type":"FeatureCollection","features":[{"type":"Feature","properties":{"codesPostaux":["24360"],"population":497,"nom":"Champniers-et-Reilhac","code":"24100"},"geometry":{"type":"Point","coordinates":[0.715343039647577,45.67693083700445]}}]}