{"type":"FeatureCollection","features":[{"type":"Feature","properties":{"codesPostaux":["24320"],"population":282,"nom":"Cherval","code":"24119"},"geometry":{"type":"Point","coordinates":[0.38518180451127804,45.390320902255645]}}]}