{"type":"FeatureCollection","features":[{"type":"Feature","properties":{"codesPostaux":["24140"],"population":112,"nom":"Clermont-de-Beauregard","code":"24123"},"geometry":{"type":"Point","coordinates":[0.6444101869158881,44.94736476635515]}}]}