{"type":"FeatureCollection","features":[{"type":"Feature","properties":{"codesPostaux":["24570"],"population":913,"nom":"Condat-sur-V\u00e9z\u00e8re","code":"24130"},"geometry":{"type":"Point","coordinates":[1.2342175609756096,45.105588292682924]}}]}