{"type":"FeatureCollection","features":[{"type":"Feature","properties":{"codesPostaux":["24240"],"population":297,"nom":"Cun\u00e8ges","code":"24148"},"geometry":{"type":"Point","coordinates":[0.37461246913580243,44.78582481481484]}}]}