{"type":"FeatureCollection","features":[{"type":"Feature","properties":{"codesPostaux":["24150"],"population":738,"nom":"Couze-et-Saint-Front","code":"24143"},"geometry":{"type":"Point","coordinates":[0.7210768316831689,44.822772475247554]}}]}