{"type":"FeatureCollection","features":[{"type":"Feature","properties":{"codesPostaux":["24220"],"population":1210,"nom":"Coux et Bigaroque-Mouzens","code":"24142"},"geometry":{"type":"Point","coordinates":[0.9721428799999997,44.8544712]}}]}