{"type":"FeatureCollection","features":[{"type":"Feature","properties":{"codesPostaux":["24190"],"population":806,"nom":"Douzillac","code":"24157"},"geometry":{"type":"Point","coordinates":[0.3981068421052631,45.0943735526316]}}]}