{"type":"FeatureCollection","features":[{"type":"Feature","properties":{"codesPostaux":["24330"],"population":1119,"nom":"La Douze","code":"24156"},"geometry":{"type":"Point","coordinates":[0.8624618181818181,45.07144048484847]}}]}