{"type":"FeatureCollection","features":[{"type":"Feature","properties":{"codesPostaux":["24500"],"population":2639,"nom":"Eymet","code":"24167"},"geometry":{"type":"Point","coordinates":[0.3837476221498372,44.673957166123756]}}]}