{"type":"FeatureCollection","features":[{"type":"Feature","properties":{"codesPostaux":["24560"],"population":604,"nom":"Faux","code":"24177"},"geometry":{"type":"Point","coordinates":[0.6475213291139238,44.78712620253168]}}]}