{"type":"FeatureCollection","features":[{"type":"Feature","properties":{"codesPostaux":["24240"],"population":320,"nom":"Flaugeac","code":"24181"},"geometry":{"type":"Point","coordinates":[0.43588153284671527,44.75848474452554]}}]}