{"type":"FeatureCollection","features":[{"type":"Feature","properties":{"codesPostaux":["24310"],"population":251,"nom":"La Gonterie-Boulouneix","code":"24198"},"geometry":{"type":"Point","coordinates":[0.5804771038251367,45.38002803278687]}}]}