{"type":"FeatureCollection","features":[{"type":"Feature","properties":{"codesPostaux":["24320"],"population":387,"nom":"Gout-Rossignol","code":"24199"},"geometry":{"type":"Point","coordinates":[0.40849137931034485,45.41144528735634]}}]}