{"type":"FeatureCollection","features":[{"type":"Feature","properties":{"codesPostaux":["24380"],"population":650,"nom":"Lacropte","code":"24220"},"geometry":{"type":"Point","coordinates":[0.8325806382978722,45.04589441489364]}}]}