{"type":"FeatureCollection","features":[{"type":"Feature","properties":{"codesPostaux":["24300"],"population":311,"nom":"Lussas-et-Nontronneau","code":"24248"},"geometry":{"type":"Point","coordinates":[0.5835420080321287,45.523740401606474]}}]}