{"type":"FeatureCollection","features":[{"type":"Feature","properties":{"codesPostaux":["24620"],"population":157,"nom":"Manaurie","code":"24249"},"geometry":{"type":"Point","coordinates":[0.987387628865979,44.963023402061886]}}]}