{"type":"FeatureCollection","features":[{"type":"Feature","properties":{"codesPostaux":["24200"],"population":786,"nom":"Marcillac-Saint-Quentin","code":"24252"},"geometry":{"type":"Point","coordinates":[1.1980936507936508,44.95858880952381]}}]}