{"type":"FeatureCollection","features":[{"type":"Feature","properties":{"codesPostaux":["24550"],"population":338,"nom":"Mazeyrolles","code":"24263"},"geometry":{"type":"Point","coordinates":[0.9981049777777773,44.66604577777777]}}]}