{"type":"FeatureCollection","features":[{"type":"Feature","properties":{"codesPostaux":["24230"],"population":1437,"nom":"Montcaret","code":"24289"},"geometry":{"type":"Point","coordinates":[0.06464018264840185,44.86485488584471]}}]}