{"type":"FeatureCollection","features":[{"type":"Feature","properties":{"codesPostaux":["24520"],"population":1183,"nom":"Mouleydier","code":"24296"},"geometry":{"type":"Point","coordinates":[0.6122793975903617,44.86005903614457]}}]}