{"type":"FeatureCollection","features":[{"type":"Feature","properties":{"codesPostaux":["24110"],"population":1262,"nom":"Montrem","code":"24295"},"geometry":{"type":"Point","coordinates":[0.578138041958042,45.134410419580426]}}]}