{"type":"FeatureCollection","features":[{"type":"Feature","properties":{"codesPostaux":["24290"],"population":2814,"nom":"Montignac","code":"24291"},"geometry":{"type":"Point","coordinates":[1.1520259405940592,45.06365495049502]}}]}