{"type":"FeatureCollection","features":[{"type":"Feature","properties":{"codesPostaux":["24610"],"population":458,"nom":"Montpeyroux","code":"24292"},"geometry":{"type":"Point","coordinates":[0.058298549382716024,44.911094074074114]}}]}