{"type":"FeatureCollection","features":[{"type":"Feature","properties":{"codesPostaux":["24170"],"population":61,"nom":"Orliac","code":"24313"},"geometry":{"type":"Point","coordinates":[1.0626371028037385,44.712936261682266]}}]}