{"type":"FeatureCollection","features":[{"type":"Feature","properties":{"codesPostaux":["24300"],"population":3196,"nom":"Nontron","code":"24311"},"geometry":{"type":"Point","coordinates":[0.6747205970149254,45.53322069651742]}}]}