{"type":"FeatureCollection","features":[{"type":"Feature","properties":{"codesPostaux":["24270"],"population":1005,"nom":"Payzac","code":"24320"},"geometry":{"type":"Point","coordinates":[1.2415624871794873,45.41751238461534]}}]}