{"type":"FeatureCollection","features":[{"type":"Feature","properties":{"codesPostaux":["24160"],"population":173,"nom":"Preyssac-d'Excideuil","code":"24339"},"geometry":{"type":"Point","coordinates":[1.1092305555555557,45.34121351851851]}}]}