{"type":"FeatureCollection","features":[{"type":"Feature","properties":{"codesPostaux":["24240"],"population":820,"nom":"Pomport","code":"24331"},"geometry":{"type":"Point","coordinates":[0.4109238723404256,44.78866744680852]}}]}