{"type":"FeatureCollection","features":[{"type":"Feature","properties":{"codesPostaux":["24240"],"population":331,"nom":"Ribagnac","code":"24351"},"geometry":{"type":"Point","coordinates":[0.4789203846153845,44.7605098076923]}}]}