{"type":"FeatureCollection","features":[{"type":"Feature","properties":{"codesPostaux":["24540"],"population":76,"nom":"Saint-Avit-Rivi\u00e8re","code":"24378"},"geometry":{"type":"Point","coordinates":[0.9103886127167625,44.74236190751445]}}]}