{"type":"FeatureCollection","features":[{"type":"Feature","properties":{"codesPostaux":["24230"],"population":1967,"nom":"Saint-Antoine-de-Breuilh","code":"24370"},"geometry":{"type":"Point","coordinates":[0.1425803797468354,44.84327867088609]}}]}