{"type":"FeatureCollection","features":[{"type":"Feature","properties":{"codesPostaux":["24270"],"population":278,"nom":"Saint-Cyr-les-Champagnes","code":"24397"},"geometry":{"type":"Point","coordinates":[1.2888767326732673,45.377326237623784]}}]}