{"type":"FeatureCollection","features":[{"type":"Feature","properties":{"codesPostaux":["24590"],"population":544,"nom":"Saint-Cr\u00e9pin-et-Carlucet","code":"24392"},"geometry":{"type":"Point","coordinates":[1.2780913605442177,44.953665442176884]}}]}