{"type":"FeatureCollection","features":[{"type":"Feature","properties":{"codesPostaux":["24520"],"population":784,"nom":"Saint-Germain-et-Mons","code":"24419"},"geometry":{"type":"Point","coordinates":[0.5898363199999997,44.82308384]}}]}