{"type":"FeatureCollection","features":[{"type":"Feature","properties":{"codesPostaux":["24500"],"population":98,"nom":"Sainte-Innocence","code":"24423"},"geometry":{"type":"Point","coordinates":[0.3935905208333334,44.723802395833324]}}]}