{"type":"FeatureCollection","features":[{"type":"Feature","properties":{"codesPostaux":["24400"],"population":226,"nom":"Saint-G\u00e9ry","code":"24420"},"geometry":{"type":"Point","coordinates":[0.3262770391061453,44.97915938547485]}}]}