{"type":"FeatureCollection","features":[{"type":"Feature","properties":{"codesPostaux":["24400"],"population":278,"nom":"Saint-Louis-en-l'Isle","code":"24444"},"geometry":{"type":"Point","coordinates":[0.3870827692307691,45.06385923076924]}}]}