{"type":"FeatureCollection","features":[{"type":"Feature","properties":{"codesPostaux":["24560"],"population":114,"nom":"Saint-L\u00e9on-d'Issigeac","code":"24441"},"geometry":{"type":"Point","coordinates":[0.6992731111111113,44.71691788888888]}}]}