{"type":"FeatureCollection","features":[{"type":"Feature","properties":{"codesPostaux":["24270"],"population":293,"nom":"Saint-Mesmin","code":"24464"},"geometry":{"type":"Point","coordinates":[1.2329041960784317,45.354212705882354]}}]}