{"type":"FeatureCollection","features":[{"type":"Feature","properties":{"codesPostaux":["24170"],"population":204,"nom":"Saint-Pardoux-et-Vielvic","code":"24478"},"geometry":{"type":"Point","coordinates":[0.9632208609271526,44.76702298013245]}}]}