{"type":"FeatureCollection","features":[{"type":"Feature","properties":{"codesPostaux":["24330"],"population":860,"nom":"Saint-Pierre-de-Chignac","code":"24484"},"geometry":{"type":"Point","coordinates":[0.8611846511627909,45.10769038759686]}}]}