{"type":"FeatureCollection","features":[{"type":"Feature","properties":{"codesPostaux":["24320"],"population":267,"nom":"Saint-Paul-Lizonne","code":"24482"},"geometry":{"type":"Point","coordinates":[0.2817673446327683,45.314312146892675]}}]}