{"type":"FeatureCollection","features":[{"type":"Feature","properties":{"codesPostaux":["24560"],"population":59,"nom":"Sainte-Radegonde","code":"24492"},"geometry":{"type":"Point","coordinates":[0.673309009009009,44.68319486486486]}}]}