{"type":"FeatureCollection","features":[{"type":"Feature","properties":{"codesPostaux":["24410"],"population":1236,"nom":"Saint Privat en P\u00e9rigord","code":"24490"},"geometry":{"type":"Point","coordinates":[0.20273186486486477,45.22168789189188]}}]}