{"type":"FeatureCollection","features":[{"type":"Feature","properties":{"codesPostaux":["24700"],"population":144,"nom":"Saint-Sauveur-Lalande","code":"24500"},"geometry":{"type":"Point","coordinates":[0.25376613333333325,44.97897900000002]}}]}