{"type":"FeatureCollection","features":[{"type":"Feature","properties":{"codesPostaux":["24350"],"population":210,"nom":"Saint-Victor","code":"24508"},"geometry":{"type":"Point","coordinates":[0.43809872881355927,45.263427542372874]}}]}