{"type":"FeatureCollection","features":[{"type":"Feature","properties":{"codesPostaux":["24230"],"population":274,"nom":"Saint-Vivien","code":"24514"},"geometry":{"type":"Point","coordinates":[0.10489018404907977,44.8957036809816]}}]}