{"type":"FeatureCollection","features":[{"type":"Feature","properties":{"codesPostaux":["24200"],"population":269,"nom":"Saint-Vincent-le-Paluel","code":"24512"},"geometry":{"type":"Point","coordinates":[1.2743577777777777,44.88119404040405]}}]}