{"type":"FeatureCollection","features":[{"type":"Feature","properties":{"codesPostaux":["24800"],"population":373,"nom":"Sarrazac","code":"24522"},"geometry":{"type":"Point","coordinates":[1.0299995068493153,45.4363584383562]}}]}