{"type":"FeatureCollection","features":[{"type":"Feature","properties":{"codesPostaux":["24420"],"population":969,"nom":"Savignac-les-\u00c9glises","code":"24527"},"geometry":{"type":"Point","coordinates":[0.912128031914894,45.27542106382977]}}]}