{"type":"FeatureCollection","features":[{"type":"Feature","properties":{"codesPostaux":["24240"],"population":944,"nom":"Sigoul\u00e8s","code":"24534"},"geometry":{"type":"Point","coordinates":[0.4020486821705427,44.758641240310055]}}]}