{"type":"FeatureCollection","features":[{"type":"Feature","properties":{"codesPostaux":["24400"],"population":1107,"nom":"Sourzac","code":"24543"},"geometry":{"type":"Point","coordinates":[0.41251795698924726,45.045194516129044]}}]}