{"type":"FeatureCollection","features":[{"type":"Feature","properties":{"codesPostaux":["24390"],"population":99,"nom":"Teillots","code":"24545"},"geometry":{"type":"Point","coordinates":[1.217109932885906,45.260451946308734]}}]}