{"type":"FeatureCollection","features":[{"type":"Feature","properties":{"codesPostaux":["24510"],"population":595,"nom":"Tr\u00e9molat","code":"24558"},"geometry":{"type":"Point","coordinates":[0.8307717518248171,44.88296335766424]}}]}