{"type":"FeatureCollection","features":[{"type":"Feature","properties":{"codesPostaux":["24350"],"population":1668,"nom":"Tocane-Saint-Apre","code":"24553"},"geometry":{"type":"Point","coordinates":[0.49478858585858576,45.23906757575758]}}]}