{"type":"FeatureCollection","features":[{"type":"Feature","properties":{"codesPostaux":["24290"],"population":259,"nom":"Thonac","code":"24552"},"geometry":{"type":"Point","coordinates":[1.1006473456790122,45.04157975308643]}}]}