{"type":"FeatureCollection","features":[{"type":"Feature","properties":{"codesPostaux":["24210"],"population":1267,"nom":"Thenon","code":"24550"},"geometry":{"type":"Point","coordinates":[1.0747176821192046,45.128087483443736]}}]}