{"type":"FeatureCollection","features":[{"type":"Feature","properties":{"codesPostaux":["24390"],"population":652,"nom":"Tourtoirac","code":"24555"},"geometry":{"type":"Point","coordinates":[1.0554856372549026,45.26820539215687]}}]}