{"type":"FeatureCollection","features":[{"type":"Feature","properties":{"codesPostaux":["24120"],"population":257,"nom":"Villac","code":"24580"},"geometry":{"type":"Point","coordinates":[1.2396705084745763,45.18417689265537]}}]}