{"type":"FeatureCollection","features":[{"type":"Feature","properties":{"codesPostaux":["25440"],"population":301,"nom":"Abbans-Dessus","code":"25002"},"geometry":{"type":"Point","coordinates":[5.884294301075271,47.127860430107525]}}]}