{"type":"FeatureCollection","features":[{"type":"Feature","properties":{"codesPostaux":["25550"],"population":233,"nom":"Allondans","code":"25013"},"geometry":{"type":"Point","coordinates":[6.7508348780487815,47.522391951219504]}}]}