{"type":"FeatureCollection","features":[{"type":"Feature","properties":{"codesPostaux":["25520"],"population":232,"nom":"Aubonne","code":"25029"},"geometry":{"type":"Point","coordinates":[6.337392582781456,47.03321748344369]}}]}