{"type":"FeatureCollection","features":[{"type":"Feature","properties":{"codesPostaux":["25420"],"population":475,"nom":"Berche","code":"25054"},"geometry":{"type":"Point","coordinates":[6.749672045454545,47.464916136363634]}}]}