{"type":"FeatureCollection","features":[{"type":"Feature","properties":{"codesPostaux":["25200"],"population":5806,"nom":"Bethoncourt","code":"25057"},"geometry":{"type":"Point","coordinates":[6.799518166666666,47.53735783333334]}}]}