{"type":"FeatureCollection","features":[{"type":"Feature","properties":{"codesPostaux":["25250"],"population":195,"nom":"Blussans","code":"25067"},"geometry":{"type":"Point","coordinates":[6.609889827586209,47.414845689655166]}}]}