{"type":"FeatureCollection","features":[{"type":"Feature","properties":{"codesPostaux":["25520"],"population":617,"nom":"Bians-les-Usiers","code":"25060"},"geometry":{"type":"Point","coordinates":[6.277443658536586,46.96533292682927]}}]}