{"type":"FeatureCollection","features":[{"type":"Feature","properties":{"codesPostaux":["25210"],"population":75,"nom":"La Bosse","code":"25077"},"geometry":{"type":"Point","coordinates":[6.646357700000002,47.14513470000001]}}]}