{"type":"FeatureCollection","features":[{"type":"Feature","properties":{"codesPostaux":["25560"],"population":362,"nom":"Bonnevaux","code":"25075"},"geometry":{"type":"Point","coordinates":[6.197536078431374,46.814884183006555]}}]}