{"type":"FeatureCollection","features":[{"type":"Feature","properties":{"codesPostaux":["25640"],"population":94,"nom":"Breconchaux","code":"25088"},"geometry":{"type":"Point","coordinates":[6.270254499999998,47.34385133333332]}}]}