{"type":"FeatureCollection","features":[{"type":"Feature","properties":{"codesPostaux":["25640"],"population":64,"nom":"La Breteni\u00e8re","code":"25092"},"geometry":{"type":"Point","coordinates":[6.275670192307691,47.38051865384614]}}]}