{"type":"FeatureCollection","features":[{"type":"Feature","properties":{"codesPostaux":["25120"],"population":477,"nom":"Les Br\u00e9seux","code":"25091"},"geometry":{"type":"Point","coordinates":[6.799613333333334,47.276536239316215]}}]}