{"type":"FeatureCollection","features":[{"type":"Feature","properties":{"codesPostaux":["25120"],"population":305,"nom":"Cernay-l'\u00c9glise","code":"25108"},"geometry":{"type":"Point","coordinates":[6.834072719999999,47.249297760000005]}}]}