{"type":"FeatureCollection","features":[{"type":"Feature","properties":{"codesPostaux":["25170"],"population":260,"nom":"Champagney","code":"25115"},"geometry":{"type":"Point","coordinates":[5.894337636363635,47.25454890909091]}}]}