{"type":"FeatureCollection","features":[{"type":"Feature","properties":{"codesPostaux":["25220"],"population":362,"nom":"Chal\u00e8ze","code":"25111"},"geometry":{"type":"Point","coordinates":[6.091162835820898,47.26202477611943]}}]}