{"type":"FeatureCollection","features":[{"type":"Feature","properties":{"codesPostaux":["25240"],"population":258,"nom":"Chapelle-des-Bois","code":"25121"},"geometry":{"type":"Point","coordinates":[6.104615889570554,46.61881846625769]}}]}