{"type":"FeatureCollection","features":[{"type":"Feature","properties":{"codesPostaux":["25470"],"population":274,"nom":"Charmauvillers","code":"25124"},"geometry":{"type":"Point","coordinates":[6.915674056603772,47.23216471698112]}}]}