{"type":"FeatureCollection","features":[{"type":"Feature","properties":{"codesPostaux":["25340"],"population":172,"nom":"Chaux-l\u00e8s-Clerval","code":"25140"},"geometry":{"type":"Point","coordinates":[6.507695384615383,47.370954769230764]}}]}