{"type":"FeatureCollection","features":[{"type":"Feature","properties":{"codesPostaux":["25260"],"population":1356,"nom":"Colombier-Fontaine","code":"25159"},"geometry":{"type":"Point","coordinates":[6.692987792207792,47.447484545454564]}}]}