{"type":"FeatureCollection","features":[{"type":"Feature","properties":{"codesPostaux":["25680"],"population":286,"nom":"Cuse-et-Adrisans","code":"25184"},"geometry":{"type":"Point","coordinates":[6.3882635772357705,47.48121975609755]}}]}