{"type":"FeatureCollection","features":[{"type":"Feature","properties":{"codesPostaux":["25230"],"population":1423,"nom":"Dasle","code":"25196"},"geometry":{"type":"Point","coordinates":[6.898150128205128,47.48198448717948]}}]}