{"type":"FeatureCollection","features":[{"type":"Feature","properties":{"codesPostaux":["25300"],"population":644,"nom":"Dommartin","code":"25201"},"geometry":{"type":"Point","coordinates":[6.312506388888889,46.92800000000001]}}]}