{"type":"FeatureCollection","features":[{"type":"Feature","properties":{"codesPostaux":["25800"],"population":615,"nom":"\u00c9penoy","code":"25219"},"geometry":{"type":"Point","coordinates":[6.382446043165467,47.13263582733814]}}]}