{"type":"FeatureCollection","features":[{"type":"Feature","properties":{"codesPostaux":["25470"],"population":164,"nom":"Fessevillers","code":"25238"},"geometry":{"type":"Point","coordinates":[6.919045666666666,47.277803888888904]}}]}