{"type":"FeatureCollection","features":[{"type":"Feature","properties":{"codesPostaux":["25110"],"population":60,"nom":"Fontenotte","code":"25249"},"geometry":{"type":"Point","coordinates":[6.318551818181819,47.375095303030314]}}]}