{"type":"FeatureCollection","features":[{"type":"Feature","properties":{"codesPostaux":["25660"],"population":988,"nom":"Fontain","code":"25245"},"geometry":{"type":"Point","coordinates":[6.037738981481482,47.191855370370405]}}]}