{"type":"FeatureCollection","features":[{"type":"Feature","properties":{"codesPostaux":["25500"],"population":3022,"nom":"Les Fins","code":"25240"},"geometry":{"type":"Point","coordinates":[6.62227807511737,47.07608821596245]}}]}