{"type":"FeatureCollection","features":[{"type":"Feature","properties":{"codesPostaux":["25170"],"population":299,"nom":"Franey","code":"25257"},"geometry":{"type":"Point","coordinates":[5.814683333333334,47.258692261904756]}}]}