{"type":"FeatureCollection","features":[{"type":"Feature","properties":{"codesPostaux":["25140"],"population":865,"nom":"Frambouhans","code":"25256"},"geometry":{"type":"Point","coordinates":[6.777853263157892,47.20555789473684]}}]}