{"type":"FeatureCollection","features":[{"type":"Feature","properties":{"codesPostaux":["25620"],"population":455,"nom":"Foucherans","code":"25250"},"geometry":{"type":"Point","coordinates":[6.149330285714286,47.150930142857135]}}]}