{"type":"FeatureCollection","features":[{"type":"Feature","properties":{"codesPostaux":["25770"],"population":2115,"nom":"Franois","code":"25258"},"geometry":{"type":"Point","coordinates":[5.920443146067415,47.22982887640452]}}]}