{"type":"FeatureCollection","features":[{"type":"Feature","properties":{"codesPostaux":["25240"],"population":228,"nom":"Gellin","code":"25263"},"geometry":{"type":"Point","coordinates":[6.240284054054054,46.72759689189189]}}]}