{"type":"FeatureCollection","features":[{"type":"Feature","properties":{"codesPostaux":["25250"],"population":152,"nom":"Geney","code":"25266"},"geometry":{"type":"Point","coordinates":[6.563878596491225,47.482875614035095]}}]}