{"type":"FeatureCollection","features":[{"type":"Feature","properties":{"codesPostaux":["25190"],"population":65,"nom":"Froidevaux","code":"25261"},"geometry":{"type":"Point","coordinates":[6.692970153846151,47.300897846153845]}}]}