{"type":"FeatureCollection","features":[{"type":"Feature","properties":{"codesPostaux":["25520"],"population":727,"nom":"Goux-les-Usiers","code":"25282"},"geometry":{"type":"Point","coordinates":[6.291800632911393,46.98028443037973]}}]}