{"type":"FeatureCollection","features":[{"type":"Feature","properties":{"codesPostaux":["25160"],"population":271,"nom":"Les Grangettes","code":"25295"},"geometry":{"type":"Point","coordinates":[6.311974999999999,46.83288846153846]}}]}