{"type":"FeatureCollection","features":[{"type":"Feature","properties":{"codesPostaux":["25440"],"population":214,"nom":"Lombard","code":"25340"},"geometry":{"type":"Point","coordinates":[5.851915333333331,47.08168173333334]}}]}