{"type":"FeatureCollection","features":[{"type":"Feature","properties":{"codesPostaux":["25620"],"population":1749,"nom":"Mamirolle","code":"25364"},"geometry":{"type":"Point","coordinates":[6.163525909090908,47.198170909090905]}}]}