{"type":"FeatureCollection","features":[{"type":"Feature","properties":{"codesPostaux":["25680"],"population":125,"nom":"Montagney-Servigney","code":"25385"},"geometry":{"type":"Point","coordinates":[6.306217179487179,47.468059572649565]}}]}