{"type":"FeatureCollection","features":[{"type":"Feature","properties":{"codesPostaux":["25190"],"population":399,"nom":"Montandon","code":"25387"},"geometry":{"type":"Point","coordinates":[6.834995866666663,47.299044800000026]}}]}