{"type":"FeatureCollection","features":[{"type":"Feature","properties":{"codesPostaux":["25480"],"population":2321,"nom":"Miserey-Salines","code":"25381"},"geometry":{"type":"Point","coordinates":[5.975966464646468,47.288209191919194]}}]}