{"type":"FeatureCollection","features":[{"type":"Feature","properties":{"codesPostaux":["25260"],"population":1526,"nom":"Montenois","code":"25394"},"geometry":{"type":"Point","coordinates":[6.659467343749998,47.49469890625001]}}]}