{"type":"FeatureCollection","features":[{"type":"Feature","properties":{"codesPostaux":["25660"],"population":580,"nom":"Montrond-le-Ch\u00e2teau","code":"25406"},"geometry":{"type":"Point","coordinates":[6.046295333333332,47.14398213333334]}}]}