{"type":"FeatureCollection","features":[{"type":"Feature","properties":{"codesPostaux":["25360"],"population":1310,"nom":"Nancray","code":"25418"},"geometry":{"type":"Point","coordinates":[6.179554864864864,47.251867432432434]}}]}