{"type":"FeatureCollection","features":[{"type":"Feature","properties":{"codesPostaux":["25170"],"population":380,"nom":"Noironte","code":"25427"},"geometry":{"type":"Point","coordinates":[5.868112608695653,47.27173507246377]}}]}