{"type":"FeatureCollection","features":[{"type":"Feature","properties":{"codesPostaux":["25220"],"population":1549,"nom":"Novillars","code":"25429"},"geometry":{"type":"Point","coordinates":[6.131430689655171,47.28816655172415]}}]}