{"type":"FeatureCollection","features":[{"type":"Feature","properties":{"codesPostaux":["25500"],"population":389,"nom":"No\u00ebl-Cerneux","code":"25425"},"geometry":{"type":"Point","coordinates":[6.666465102040815,47.107332244897954]}}]}