{"type":"FeatureCollection","features":[{"type":"Feature","properties":{"codesPostaux":["25640"],"population":217,"nom":"Ougney-Douvot","code":"25439"},"geometry":{"type":"Point","coordinates":[6.2698558,47.3166135]}}]}