{"type":"FeatureCollection","features":[{"type":"Feature","properties":{"codesPostaux":["25520"],"population":371,"nom":"Ouhans","code":"25440"},"geometry":{"type":"Point","coordinates":[6.312579381443301,47.00576855670104]}}]}