{"type":"FeatureCollection","features":[{"type":"Feature","properties":{"codesPostaux":["25550"],"population":452,"nom":"Pr\u00e9sentevillers","code":"25469"},"geometry":{"type":"Point","coordinates":[6.729736829268295,47.500842926829264]}}]}