{"type":"FeatureCollection","features":[{"type":"Feature","properties":{"codesPostaux":["25640"],"population":109,"nom":"Le Puy","code":"25474"},"geometry":{"type":"Point","coordinates":[6.229876235294117,47.34551564705882]}}]}