{"type":"FeatureCollection","features":[{"type":"Feature","properties":{"codesPostaux":["25440"],"population":88,"nom":"Rennes-sur-Loue","code":"25488"},"geometry":{"type":"Point","coordinates":[5.8551649999999995,47.014969]}}]}