{"type":"FeatureCollection","features":[{"type":"Feature","properties":{"codesPostaux":["25310"],"population":636,"nom":"Roches-l\u00e8s-Blamont","code":"25497"},"geometry":{"type":"Point","coordinates":[6.852636599999999,47.411468000000006]}}]}