{"type":"FeatureCollection","features":[{"type":"Feature","properties":{"codesPostaux":["25220"],"population":2020,"nom":"Roche-lez-Beaupr\u00e9","code":"25495"},"geometry":{"type":"Point","coordinates":[6.104375357142856,47.281681964285724]}}]}