{"type":"FeatureCollection","features":[{"type":"Feature","properties":{"codesPostaux":["25640"],"population":89,"nom":"Rougemontot","code":"25506"},"geometry":{"type":"Point","coordinates":[6.264065967741936,47.39004096774195]}}]}