{"type":"FeatureCollection","features":[{"type":"Feature","properties":{"codesPostaux":["25190"],"population":111,"nom":"Rosi\u00e8res-sur-Barb\u00e8che","code":"25503"},"geometry":{"type":"Point","coordinates":[6.660697999999998,47.31513650000001]}}]}