{"type":"FeatureCollection","features":[{"type":"Feature","properties":{"codesPostaux":["25440"],"population":89,"nom":"Rouhe","code":"25507"},"geometry":{"type":"Point","coordinates":[5.970205942028985,47.08713710144927]}}]}