{"type":"FeatureCollection","features":[{"type":"Feature","properties":{"codesPostaux":["25210"],"population":2245,"nom":"Le Russey","code":"25512"},"geometry":{"type":"Point","coordinates":[6.722129239130432,47.15546510869566]}}]}