{"type":"FeatureCollection","features":[{"type":"Feature","properties":{"codesPostaux":["25270"],"population":34,"nom":"Sainte-Anne","code":"25513"},"geometry":{"type":"Point","coordinates":[5.988179369369369,46.951361531531525]}}]}