{"type":"FeatureCollection","features":[{"type":"Feature","properties":{"codesPostaux":["25230"],"population":5946,"nom":"Seloncourt","code":"25539"},"geometry":{"type":"Point","coordinates":[6.863956578947367,47.45650065789472]}}]}