{"type":"FeatureCollection","features":[{"type":"Feature","properties":{"codesPostaux":["25240"],"population":175,"nom":"Sarrageois","code":"25534"},"geometry":{"type":"Point","coordinates":[6.228451464968153,46.708881464968144]}}]}