{"type":"FeatureCollection","features":[{"type":"Feature","properties":{"codesPostaux":["25430"],"population":195,"nom":"Servin","code":"25544"},"geometry":{"type":"Point","coordinates":[6.473031847826089,47.31044391304347]}}]}