{"type":"FeatureCollection","features":[{"type":"Feature","properties":{"codesPostaux":["25110"],"population":54,"nom":"Silley-Bl\u00e9fond","code":"25546"},"geometry":{"type":"Point","coordinates":[6.3320797468354435,47.321190506329124]}}]}