{"type":"FeatureCollection","features":[{"type":"Feature","properties":{"codesPostaux":["25330"],"population":128,"nom":"Silley-Amancey","code":"25545"},"geometry":{"type":"Point","coordinates":[6.1341988695652185,47.03382739130435]}}]}