{"type":"FeatureCollection","features":[{"type":"Feature","properties":{"codesPostaux":["25380"],"population":130,"nom":"Surmont","code":"25554"},"geometry":{"type":"Point","coordinates":[6.608594690265483,47.27728973451328]}}]}