{"type":"FeatureCollection","features":[{"type":"Feature","properties":{"codesPostaux":["25400"],"population":1069,"nom":"Taillecourt","code":"25555"},"geometry":{"type":"Point","coordinates":[6.850477916666666,47.49430375]}}]}