{"type":"FeatureCollection","features":[{"type":"Feature","properties":{"codesPostaux":["25470"],"population":238,"nom":"Thi\u00e9bouhans","code":"25559"},"geometry":{"type":"Point","coordinates":[6.842834513274336,47.26870292035399]}}]}