{"type":"FeatureCollection","features":[{"type":"Feature","properties":{"codesPostaux":["25800"],"population":5213,"nom":"Valdahon","code":"25578"},"geometry":{"type":"Point","coordinates":[6.3324358762886614,47.16156077319588]}}]}