{"type":"FeatureCollection","features":[{"type":"Feature","properties":{"codesPostaux":["25870"],"population":155,"nom":"Valleroy","code":"25582"},"geometry":{"type":"Point","coordinates":[6.123184210526316,47.38625736842108]}}]}