{"type":"FeatureCollection","features":[{"type":"Feature","properties":{"codesPostaux":["25190"],"population":244,"nom":"Valonne","code":"25583"},"geometry":{"type":"Point","coordinates":[6.669002597402602,47.34075792207791]}}]}