{"type":"FeatureCollection","features":[{"type":"Feature","properties":{"codesPostaux":["25870"],"population":506,"nom":"Venise","code":"25598"},"geometry":{"type":"Point","coordinates":[6.112429999999999,47.35289222222222]}}]}