{"type":"FeatureCollection","features":[{"type":"Feature","properties":{"codesPostaux":["25110"],"population":102,"nom":"Vergranne","code":"25602"},"geometry":{"type":"Point","coordinates":[6.393674383561644,47.40766712328769]}}]}