{"type":"FeatureCollection","features":[{"type":"Feature","properties":{"codesPostaux":["25410"],"population":254,"nom":"Villars-Saint-Georges","code":"25616"},"geometry":{"type":"Point","coordinates":[5.827728260869565,47.124318913043474]}}]}