{"type":"FeatureCollection","features":[{"type":"Feature","properties":{"codesPostaux":["25240"],"population":198,"nom":"Les Villedieu","code":"25619"},"geometry":{"type":"Point","coordinates":[6.267730921985816,46.72119709219858]}}]}