{"type":"FeatureCollection","features":[{"type":"Feature","properties":{"codesPostaux":["25300"],"population":593,"nom":"Vuillecin","code":"25634"},"geometry":{"type":"Point","coordinates":[6.338074366197184,46.94942380281691]}}]}