{"type":"FeatureCollection","features":[{"type":"Feature","properties":{"codesPostaux":["26140"],"population":1319,"nom":"Andancette","code":"26009"},"geometry":{"type":"Point","coordinates":[4.810962608695652,45.249683043478264]}}]}