{"type":"FeatureCollection","features":[{"type":"Feature","properties":{"codesPostaux":["26300"],"population":1154,"nom":"B\u00e9sayes","code":"26049"},"geometry":{"type":"Point","coordinates":[5.0930984042553185,44.964241595744674]}}]}