{"type":"FeatureCollection","features":[{"type":"Feature","properties":{"codesPostaux":["26800"],"population":1573,"nom":"Beauvallon","code":"26042"},"geometry":{"type":"Point","coordinates":[4.901482592592593,44.856004074074086]}}]}