{"type":"FeatureCollection","features":[{"type":"Feature","properties":{"codesPostaux":["26110"],"population":93,"nom":"Bellecombe-Tarendol","code":"26046"},"geometry":{"type":"Point","coordinates":[5.353781203703706,44.35182981481483]}}]}