{"type":"FeatureCollection","features":[{"type":"Feature","properties":{"codesPostaux":["26450"],"population":841,"nom":"Charols","code":"26078"},"geometry":{"type":"Point","coordinates":[4.956151645569619,44.586817341772154]}}]}