{"type":"FeatureCollection","features":[{"type":"Feature","properties":{"codesPostaux":["26600"],"population":1205,"nom":"Chantemerle-les-Bl\u00e9s","code":"26072"},"geometry":{"type":"Point","coordinates":[4.8853107692307685,45.115124615384616]}}]}