{"type":"FeatureCollection","features":[{"type":"Feature","properties":{"codesPostaux":["26230"],"population":561,"nom":"Chamaret","code":"26070"},"geometry":{"type":"Point","coordinates":[4.870225779816513,44.393293486238534]}}]}