{"type":"FeatureCollection","features":[{"type":"Feature","properties":{"codesPostaux":["26330"],"population":1752,"nom":"Ch\u00e2teauneuf-de-Galaure","code":"26083"},"geometry":{"type":"Point","coordinates":[4.961242857142856,45.236552738095256]}}]}