{"type":"FeatureCollection","features":[{"type":"Feature","properties":{"codesPostaux":["26340"],"population":42,"nom":"Chastel-Arnaud","code":"26080"},"geometry":{"type":"Point","coordinates":[5.207073941605837,44.659178686131405]}}]}