{"type":"FeatureCollection","features":[{"type":"Feature","properties":{"codesPostaux":["26510"],"population":45,"nom":"Chauvac-Laux-Montaux","code":"26091"},"geometry":{"type":"Point","coordinates":[5.538012222222221,44.32379185185185]}}]}