{"type":"FeatureCollection","features":[{"type":"Feature","properties":{"codesPostaux":["26270"],"population":663,"nom":"Cliousclat","code":"26097"},"geometry":{"type":"Point","coordinates":[4.837584871794872,44.72194358974358]}}]}