{"type":"FeatureCollection","features":[{"type":"Feature","properties":{"codesPostaux":["26400"],"population":8181,"nom":"Crest","code":"26108"},"geometry":{"type":"Point","coordinates":[5.0300568354430375,44.73496898734178]}}]}