{"type":"FeatureCollection","features":[{"type":"Feature","properties":{"codesPostaux":["26400"],"population":609,"nom":"Divajeu","code":"26115"},"geometry":{"type":"Point","coordinates":[5.00570099378882,44.701386770186325]}}]}