{"type":"FeatureCollection","features":[{"type":"Feature","properties":{"codesPostaux":["26780"],"population":1049,"nom":"Espeluche","code":"26121"},"geometry":{"type":"Point","coordinates":[4.821653544303797,44.52527493670887]}}]}