{"type":"FeatureCollection","features":[{"type":"Feature","properties":{"codesPostaux":["26400"],"population":52,"nom":"Eygluy-Escoulin","code":"26128"},"geometry":{"type":"Point","coordinates":[5.206012948717948,44.79474429487178]}}]}