{"type":"FeatureCollection","features":[{"type":"Feature","properties":{"codesPostaux":["26160"],"population":132,"nom":"Eyzahut","code":"26131"},"geometry":{"type":"Point","coordinates":[5.006196075949366,44.56317632911392]}}]}