{"type":"FeatureCollection","features":[{"type":"Feature","properties":{"codesPostaux":["26110"],"population":30,"nom":"Eyroles","code":"26130"},"geometry":{"type":"Point","coordinates":[5.246867307692307,44.417063692307686]}}]}