{"type":"FeatureCollection","features":[{"type":"Feature","properties":{"codesPostaux":["26240"],"population":168,"nom":"Fay-le-Clos","code":"26133"},"geometry":{"type":"Point","coordinates":[4.905947499999999,45.222283749999995]}}]}