{"type":"FeatureCollection","features":[{"type":"Feature","properties":{"codesPostaux":["26470"],"population":22,"nom":"Gumiane","code":"26147"},"geometry":{"type":"Point","coordinates":[5.26617967032967,44.51226846153845]}}]}