{"type":"FeatureCollection","features":[{"type":"Feature","properties":{"codesPostaux":["26530"],"population":900,"nom":"Le Grand-Serre","code":"26143"},"geometry":{"type":"Point","coordinates":[5.103350923913043,45.264720217391314]}}]}