{"type":"FeatureCollection","features":[{"type":"Feature","properties":{"codesPostaux":["26560"],"population":9,"nom":"Izon-la-Bruisse","code":"26150"},"geometry":{"type":"Point","coordinates":[5.602073722627738,44.26360058394161]}}]}