{"type":"FeatureCollection","features":[{"type":"Feature","properties":{"codesPostaux":["26150"],"population":131,"nom":"Laval-d'Aix","code":"26159"},"geometry":{"type":"Point","coordinates":[5.452346486486487,44.74151477477479]}}]}