{"type":"FeatureCollection","features":[{"type":"Feature","properties":{"codesPostaux":["26600"],"population":2538,"nom":"Mercurol-Veaunes","code":"26179"},"geometry":{"type":"Point","coordinates":[4.893865649350649,45.078533896103906]}}]}