{"type":"FeatureCollection","features":[{"type":"Feature","properties":{"codesPostaux":["26300"],"population":782,"nom":"Marches","code":"26173"},"geometry":{"type":"Point","coordinates":[5.1176900000000005,44.97893595238094]}}]}