{"type":"FeatureCollection","features":[{"type":"Feature","properties":{"codesPostaux":["26110"],"population":1559,"nom":"Mirabel-aux-Baronnies","code":"26182"},"geometry":{"type":"Point","coordinates":[5.111874176470584,44.313399705882354]}}]}