{"type":"FeatureCollection","features":[{"type":"Feature","properties":{"codesPostaux":["26270"],"population":508,"nom":"Mirmande","code":"26185"},"geometry":{"type":"Point","coordinates":[4.836762480000002,44.69142239999997]}}]}