{"type":"FeatureCollection","features":[{"type":"Feature","properties":{"codesPostaux":["26510"],"population":34,"nom":"Montferrand-la-Fare","code":"26199"},"geometry":{"type":"Point","coordinates":[5.449894666666667,44.343381047619054]}}]}