{"type":"FeatureCollection","features":[{"type":"Feature","properties":{"codesPostaux":["26570"],"population":410,"nom":"Montbrun-les-Bains","code":"26193"},"geometry":{"type":"Point","coordinates":[5.43492343283582,44.18513776119404]}}]}