{"type":"FeatureCollection","features":[{"type":"Feature","properties":{"codesPostaux":["26170"],"population":44,"nom":"Montguers","code":"26201"},"geometry":{"type":"Point","coordinates":[5.472571505376344,44.29735096774193]}}]}