{"type":"FeatureCollection","features":[{"type":"Feature","properties":{"codesPostaux":["26800"],"population":1871,"nom":"Montoison","code":"26208"},"geometry":{"type":"Point","coordinates":[4.926129666666665,44.79812755555555]}}]}