{"type":"FeatureCollection","features":[{"type":"Feature","properties":{"codesPostaux":["26540"],"population":2908,"nom":"Mours-Saint-Eus\u00e8be","code":"26218"},"geometry":{"type":"Point","coordinates":[5.058109726027398,45.07425821917808]}}]}