{"type":"FeatureCollection","features":[{"type":"Feature","properties":{"codesPostaux":["26400"],"population":120,"nom":"Plan-de-Baix","code":"26240"},"geometry":{"type":"Point","coordinates":[5.169253491124263,44.82416757396449]}}]}