{"type":"FeatureCollection","features":[{"type":"Feature","properties":{"codesPostaux":["26160"],"population":643,"nom":"Pont-de-Barret","code":"26249"},"geometry":{"type":"Point","coordinates":[4.997574125000004,44.58592806250002]}}]}