{"type":"FeatureCollection","features":[{"type":"Feature","properties":{"codesPostaux":["26160"],"population":120,"nom":"Rochebaudin","code":"26268"},"geometry":{"type":"Point","coordinates":[5.026849494949497,44.574764040404034]}}]}