{"type":"FeatureCollection","features":[{"type":"Feature","properties":{"codesPostaux":["26340"],"population":1,"nom":"Rochefourchat","code":"26274"},"geometry":{"type":"Point","coordinates":[5.245080576923078,44.606635769230756]}}]}