{"type":"FeatureCollection","features":[{"type":"Feature","properties":{"codesPostaux":["26190"],"population":106,"nom":"Rochechinard","code":"26270"},"geometry":{"type":"Point","coordinates":[5.249148684210527,45.02949223684211]}}]}