{"type":"FeatureCollection","features":[{"type":"Feature","properties":{"codesPostaux":["26150"],"population":213,"nom":"Romeyer","code":"26282"},"geometry":{"type":"Point","coordinates":[5.4412220673076925,44.792574471153834]}}]}