{"type":"FeatureCollection","features":[{"type":"Feature","properties":{"codesPostaux":["26340"],"population":26,"nom":"Saint-Benoit-en-Diois","code":"26296"},"geometry":{"type":"Point","coordinates":[5.2678548039215665,44.65602823529412]}}]}