{"type":"FeatureCollection","features":[{"type":"Feature","properties":{"codesPostaux":["26240"],"population":1881,"nom":"Saint-Barth\u00e9lemy-de-Vals","code":"26295"},"geometry":{"type":"Point","coordinates":[4.865121224489798,45.16979585034013]}}]}