{"type":"FeatureCollection","features":[{"type":"Feature","properties":{"codesPostaux":["26260"],"population":580,"nom":"Saint-Bardoux","code":"26294"},"geometry":{"type":"Point","coordinates":[4.988836161616161,45.087169696969696]}}]}