{"type":"FeatureCollection","features":[{"type":"Feature","properties":{"codesPostaux":["26190"],"population":566,"nom":"Sainte-Eulalie-en-Royans","code":"26302"},"geometry":{"type":"Point","coordinates":[5.345384639175259,45.043904226804116]}}]}