{"type":"FeatureCollection","features":[{"type":"Feature","properties":{"codesPostaux":["26420"],"population":421,"nom":"Saint-Martin-en-Vercors","code":"26315"},"geometry":{"type":"Point","coordinates":[5.437584141414141,45.01887858585859]}}]}