{"type":"FeatureCollection","features":[{"type":"Feature","properties":{"codesPostaux":["26750"],"population":545,"nom":"Saint-Michel-sur-Savasse","code":"26319"},"geometry":{"type":"Point","coordinates":[5.122953254437868,45.14676426035503]}}]}