{"type":"FeatureCollection","features":[{"type":"Feature","properties":{"codesPostaux":["26190"],"population":795,"nom":"Saint-Nazaire-en-Royans","code":"26320"},"geometry":{"type":"Point","coordinates":[5.244898266666668,45.057612533333334]}}]}