{"type":"FeatureCollection","features":[{"type":"Feature","properties":{"codesPostaux":["26770"],"population":172,"nom":"Salles-sous-Bois","code":"26335"},"geometry":{"type":"Point","coordinates":[4.937582018348625,44.46715275229359]}}]}