{"type":"FeatureCollection","features":[{"type":"Feature","properties":{"codesPostaux":["26210"],"population":2209,"nom":"Saint-Sorlin-en-Valloire","code":"26330"},"geometry":{"type":"Point","coordinates":[4.966712519685039,45.2717925984252]}}]}