{"type":"FeatureCollection","features":[{"type":"Feature","properties":{"codesPostaux":["26400"],"population":365,"nom":"Soyans","code":"26344"},"geometry":{"type":"Point","coordinates":[5.0223665921787735,44.64115201117319]}}]}