{"type":"FeatureCollection","features":[{"type":"Feature","properties":{"codesPostaux":["26120"],"population":1532,"nom":"Upie","code":"26358"},"geometry":{"type":"Point","coordinates":[4.972975512820513,44.79217358974359]}}]}