{"type":"FeatureCollection","features":[{"type":"Feature","properties":{"codesPostaux":["26150"],"population":32,"nom":"Vach\u00e8res-en-Quint","code":"26359"},"geometry":{"type":"Point","coordinates":[5.2533676315789455,44.784058157894734]}}]}