{"type":"FeatureCollection","features":[{"type":"Feature","properties":{"codesPostaux":["26000"],"population":61767,"nom":"Valence","code":"26362"},"geometry":{"type":"Point","coordinates":[4.923015079365081,44.92973269841271]}}]}