{"type":"FeatureCollection","features":[{"type":"Feature","properties":{"codesPostaux":["26230"],"population":575,"nom":"Valaurie","code":"26360"},"geometry":{"type":"Point","coordinates":[4.808378103448276,44.416254310344854]}}]}