{"type":"FeatureCollection","features":[{"type":"Feature","properties":{"codesPostaux":["26310"],"population":140,"nom":"Valdr\u00f4me","code":"26361"},"geometry":{"type":"Point","coordinates":[5.569994615384615,44.498565976331356]}}]}