{"type":"FeatureCollection","features":[{"type":"Feature","properties":{"codesPostaux":["27400"],"population":1531,"nom":"Acquigny","code":"27003"},"geometry":{"type":"Point","coordinates":[1.1727592746113993,49.160300310880835]}}]}