{"type":"FeatureCollection","features":[{"type":"Feature","properties":{"codesPostaux":["27460"],"population":1468,"nom":"Alizay","code":"27008"},"geometry":{"type":"Point","coordinates":[1.1800950000000001,49.32375555555556]}}]}