{"type":"FeatureCollection","features":[{"type":"Feature","properties":{"codesPostaux":["27400"],"population":777,"nom":"Amfreville-sur-Iton","code":"27014"},"geometry":{"type":"Point","coordinates":[1.1438842857142848,49.15657583333332]}}]}