{"type":"FeatureCollection","features":[{"type":"Feature","properties":{"codesPostaux":["27440"],"population":596,"nom":"Bacqueville","code":"27034"},"geometry":{"type":"Point","coordinates":[1.3643035294117645,49.317937647058834]}}]}