{"type":"FeatureCollection","features":[{"type":"Feature","properties":{"codesPostaux":["27170"],"population":431,"nom":"Barquet","code":"27040"},"geometry":{"type":"Point","coordinates":[0.843744764397905,49.03604570680629]}}]}