{"type":"FeatureCollection","features":[{"type":"Feature","properties":{"codesPostaux":["27480"],"population":274,"nom":"B\u00e9zu-la-For\u00eat","code":"27066"},"geometry":{"type":"Point","coordinates":[1.6258466666666662,49.40081947916668]}}]}