{"type":"FeatureCollection","features":[{"type":"Feature","properties":{"codesPostaux":["27330"],"population":380,"nom":"Bois-Normand-pr\u00e8s-Lyre","code":"27075"},"geometry":{"type":"Point","coordinates":[0.6896029752066116,48.89941355371902]}}]}