{"type":"FeatureCollection","features":[{"type":"Feature","properties":{"codesPostaux":["27220"],"population":271,"nom":"La Boissi\u00e8re","code":"27078"},"geometry":{"type":"Point","coordinates":[1.3659417021276594,48.95290340425532]}}]}