{"type":"FeatureCollection","features":[{"type":"Feature","properties":{"codesPostaux":["27800"],"population":288,"nom":"Boisney","code":"27074"},"geometry":{"type":"Point","coordinates":[0.6537344680851064,49.15446659574466]}}]}