{"type":"FeatureCollection","features":[{"type":"Feature","properties":{"codesPostaux":["27310"],"population":1293,"nom":"Flancourt-Crescy-en-Roumois","code":"27085"},"geometry":{"type":"Point","coordinates":[0.775777573964497,49.32419437869823]}}]}