{"type":"FeatureCollection","features":[{"type":"Feature","properties":{"codesPostaux":["27310"],"population":3235,"nom":"Bourg-Achard","code":"27103"},"geometry":{"type":"Point","coordinates":[0.8059694318181816,49.343357954545475]}}]}