{"type":"FeatureCollection","features":[{"type":"Feature","properties":{"codesPostaux":["27310"],"population":1080,"nom":"Bouquetot","code":"27102"},"geometry":{"type":"Point","coordinates":[0.7685505940594058,49.360779603960395]}}]}