{"type":"FeatureCollection","features":[{"type":"Feature","properties":{"codesPostaux":["27570"],"population":350,"nom":"Breux-sur-Avre","code":"27115"},"geometry":{"type":"Point","coordinates":[1.075167011494253,48.76572816091954]}}]}