{"type":"FeatureCollection","features":[{"type":"Feature","properties":{"codesPostaux":["27490"],"population":221,"nom":"Cailly-sur-Eure","code":"27124"},"geometry":{"type":"Point","coordinates":[1.2161880327868853,49.11911377049181]}}]}