{"type":"FeatureCollection","features":[{"type":"Feature","properties":{"codesPostaux":["27270"],"population":389,"nom":"Chamblac","code":"27138"},"geometry":{"type":"Point","coordinates":[0.565315130434783,48.99277495652173]}}]}