{"type":"FeatureCollection","features":[{"type":"Feature","properties":{"codesPostaux":["27930"],"population":555,"nom":"La Chapelle-du-Bois-des-Faulx","code":"27147"},"geometry":{"type":"Point","coordinates":[1.170748921568628,49.11022901960786]}}]}