{"type":"FeatureCollection","features":[{"type":"Feature","properties":{"codesPostaux":["27380"],"population":1840,"nom":"Charleval","code":"27151"},"geometry":{"type":"Point","coordinates":[1.3821236842105267,49.373623333333335]}}]}