{"type":"FeatureCollection","features":[{"type":"Feature","properties":{"codesPostaux":["27150"],"population":351,"nom":"Chauvincourt-Provemont","code":"27153"},"geometry":{"type":"Point","coordinates":[1.650349367088608,49.282397721519]}}]}