{"type":"FeatureCollection","features":[{"type":"Feature","properties":{"codesPostaux":["27500"],"population":193,"nom":"Colletot","code":"27163"},"geometry":{"type":"Point","coordinates":[0.6189364705882352,49.35072686274509]}}]}