{"type":"FeatureCollection","features":[{"type":"Feature","properties":{"codesPostaux":["27290"],"population":615,"nom":"Cond\u00e9-sur-Risle","code":"27167"},"geometry":{"type":"Point","coordinates":[0.6069082352941179,49.30936529411766]}}]}