{"type":"FeatureCollection","features":[{"type":"Feature","properties":{"codesPostaux":["27110"],"population":276,"nom":"Criquebeuf-la-Campagne","code":"27187"},"geometry":{"type":"Point","coordinates":[0.9959079032258068,49.19901112903225]}}]}