{"type":"FeatureCollection","features":[{"type":"Feature","properties":{"codesPostaux":["27940"],"population":1919,"nom":"Courcelles-sur-Seine","code":"27180"},"geometry":{"type":"Point","coordinates":[1.3630010526315788,49.183442631578956]}}]}