{"type":"FeatureCollection","features":[{"type":"Feature","properties":{"codesPostaux":["27160","27240"],"population":4483,"nom":"Mesnils-sur-Iton","code":"27198"},"geometry":{"type":"Point","coordinates":[1.0311656666666669,48.868434399999956]}}]}