{"type":"FeatureCollection","features":[{"type":"Feature","properties":{"codesPostaux":["27110"],"population":232,"nom":"Daubeuf-la-Campagne","code":"27201"},"geometry":{"type":"Point","coordinates":[1.0318729761904764,49.18701238095239]}}]}