{"type":"FeatureCollection","features":[{"type":"Feature","properties":{"codesPostaux":["27120"],"population":476,"nom":"Douains","code":"27203"},"geometry":{"type":"Point","coordinates":[1.4297172619047624,49.03892869047619]}}]}