{"type":"FeatureCollection","features":[{"type":"Feature","properties":{"codesPostaux":["27730"],"population":374,"nom":"\u00c9pieds","code":"27220"},"geometry":{"type":"Point","coordinates":[1.3964656410256413,48.93632115384615]}}]}