{"type":"FeatureCollection","features":[{"type":"Feature","properties":{"codesPostaux":["27190"],"population":134,"nom":"Faverolles-la-Campagne","code":"27235"},"geometry":{"type":"Point","coordinates":[0.9267118181818181,49.02343480519482]}}]}