{"type":"FeatureCollection","features":[{"type":"Feature","properties":{"codesPostaux":["27380"],"population":1910,"nom":"Fleury-sur-Andelle","code":"27246"},"geometry":{"type":"Point","coordinates":[1.3540256578947365,49.36267671052631]}}]}