{"type":"FeatureCollection","features":[{"type":"Feature","properties":{"codesPostaux":["27480"],"population":280,"nom":"Fleury-la-For\u00eat","code":"27245"},"geometry":{"type":"Point","coordinates":[1.557216588235294,49.4276154117647]}}]}