{"type":"FeatureCollection","features":[{"type":"Feature","properties":{"codesPostaux":["27500"],"population":643,"nom":"Fourmetot","code":"27263"},"geometry":{"type":"Point","coordinates":[0.5846285057471264,49.375163678160916]}}]}