{"type":"FeatureCollection","features":[{"type":"Feature","properties":{"codesPostaux":["27220"],"population":684,"nom":"La Baronnie","code":"27277"},"geometry":{"type":"Point","coordinates":[1.2632586170212763,48.943796063829794]}}]}