{"type":"FeatureCollection","features":[{"type":"Feature","properties":{"codesPostaux":["27780"],"population":1863,"nom":"Garennes-sur-Eure","code":"27278"},"geometry":{"type":"Point","coordinates":[1.4358175,48.91163035714284]}}]}