{"type":"FeatureCollection","features":[{"type":"Feature","properties":{"codesPostaux":["27190"],"population":821,"nom":"Glisolles","code":"27287"},"geometry":{"type":"Point","coordinates":[1.0036487412587414,48.98855237762239]}}]}