{"type":"FeatureCollection","features":[{"type":"Feature","properties":{"codesPostaux":["27390"],"population":170,"nom":"La Goulafri\u00e8re","code":"27289"},"geometry":{"type":"Point","coordinates":[0.4354162280701754,48.948999122806995]}}]}