{"type":"FeatureCollection","features":[{"type":"Feature","properties":{"codesPostaux":["27220"],"population":1063,"nom":"Gross\u0153uvre","code":"27301"},"geometry":{"type":"Point","coordinates":[1.1852146236559145,48.940123655913986]}}]}