{"type":"FeatureCollection","features":[{"type":"Feature","properties":{"codesPostaux":["27350"],"population":466,"nom":"La Haye-Aubr\u00e9e","code":"27317"},"geometry":{"type":"Point","coordinates":[0.697294578313253,49.39458204819279]}}]}