{"type":"FeatureCollection","features":[{"type":"Feature","properties":{"codesPostaux":["27120"],"population":258,"nom":"Hardencourt-Cocherel","code":"27312"},"geometry":{"type":"Point","coordinates":[1.3133456410256408,49.04123743589743]}}]}