{"type":"FeatureCollection","features":[{"type":"Feature","properties":{"codesPostaux":["27400"],"population":1476,"nom":"La Haye-Malherbe","code":"27322"},"geometry":{"type":"Point","coordinates":[1.0694113138686125,49.231357591240894]}}]}