{"type":"FeatureCollection","features":[{"type":"Feature","properties":{"codesPostaux":["27860"],"population":638,"nom":"Heudicourt","code":"27333"},"geometry":{"type":"Point","coordinates":[1.659995428571429,49.33068585714285]}}]}