{"type":"FeatureCollection","features":[{"type":"Feature","properties":{"codesPostaux":["27460"],"population":1658,"nom":"Igoville","code":"27348"},"geometry":{"type":"Point","coordinates":[1.1542315384615383,49.32838861538461]}}]}