{"type":"FeatureCollection","features":[{"type":"Feature","properties":{"codesPostaux":["27310"],"population":658,"nom":"Honguemare-Guenouville","code":"27340"},"geometry":{"type":"Point","coordinates":[0.8209821249999996,49.37966299999999]}}]}