{"type":"FeatureCollection","features":[{"type":"Feature","properties":{"codesPostaux":["27470"],"population":213,"nom":"Launay","code":"27364"},"geometry":{"type":"Point","coordinates":[0.735991195652174,49.108113913043475]}}]}