{"type":"FeatureCollection","features":[{"type":"Feature","properties":{"codesPostaux":["27220"],"population":293,"nom":"Lignerolles","code":"27368"},"geometry":{"type":"Point","coordinates":[1.2757525,48.84416514705883]}}]}