{"type":"FeatureCollection","features":[{"type":"Feature","properties":{"codesPostaux":["27800"],"population":251,"nom":"Malleville-sur-le-Bec","code":"27380"},"geometry":{"type":"Point","coordinates":[0.7488143396226414,49.240479622641516]}}]}