{"type":"FeatureCollection","features":[{"type":"Feature","properties":{"codesPostaux":["27400"],"population":232,"nom":"Le Mesnil-Jourdain","code":"27403"},"geometry":{"type":"Point","coordinates":[1.1308368695652176,49.18375]}}]}