{"type":"FeatureCollection","features":[{"type":"Feature","properties":{"codesPostaux":["27260"],"population":385,"nom":"Morainville-Jouveaux","code":"27415"},"geometry":{"type":"Point","coordinates":[0.4470416483516483,49.222616318681325]}}]}