{"type":"FeatureCollection","features":[{"type":"Feature","properties":{"codesPostaux":["27170","27300","27550"],"population":2395,"nom":"Nassandres sur Risle","code":"27425"},"geometry":{"type":"Point","coordinates":[0.7156778095238093,49.143022476190495]}}]}