{"type":"FeatureCollection","features":[{"type":"Feature","properties":{"codesPostaux":["27190"],"population":326,"nom":"Nagel-S\u00e9ez-Mesnil","code":"27424"},"geometry":{"type":"Point","coordinates":[0.947315396825397,48.92006555555557]}}]}