{"type":"FeatureCollection","features":[{"type":"Feature","properties":{"codesPostaux":["27320"],"population":2310,"nom":"Nonancourt","code":"27438"},"geometry":{"type":"Point","coordinates":[1.1901514159292035,48.77224893805311]}}]}