{"type":"FeatureCollection","features":[{"type":"Feature","properties":{"codesPostaux":["27150"],"population":328,"nom":"Nojeon-en-Vexin","code":"27437"},"geometry":{"type":"Point","coordinates":[1.56065925925926,49.33403641975308]}}]}