{"type":"FeatureCollection","features":[{"type":"Feature","properties":{"codesPostaux":["27120"],"population":5129,"nom":"Pacy-sur-Eure","code":"27448"},"geometry":{"type":"Point","coordinates":[1.383646114285715,49.018943428571404]}}]}