{"type":"FeatureCollection","features":[{"type":"Feature","properties":{"codesPostaux":["27390"],"population":221,"nom":"Notre-Dame-du-Hamel","code":"27442"},"geometry":{"type":"Point","coordinates":[0.5103487037037037,48.89064999999999]}}]}