{"type":"FeatureCollection","features":[{"type":"Feature","properties":{"codesPostaux":["27180"],"population":298,"nom":"Parville","code":"27451"},"geometry":{"type":"Point","coordinates":[1.0923710526315789,49.03357175438596]}}]}