{"type":"FeatureCollection","features":[{"type":"Feature","properties":{"codesPostaux":["27120"],"population":396,"nom":"Le Plessis-H\u00e9bert","code":"27465"},"geometry":{"type":"Point","coordinates":[1.3659093999999992,48.979238199999976]}}]}