{"type":"FeatureCollection","features":[{"type":"Feature","properties":{"codesPostaux":["27560"],"population":172,"nom":"La Poterie-Mathieu","code":"27475"},"geometry":{"type":"Point","coordinates":[0.5217344086021508,49.25244795698924]}}]}