{"type":"FeatureCollection","features":[{"type":"Feature","properties":{"codesPostaux":["27510"],"population":706,"nom":"Pressagny-l'Orgueilleux","code":"27477"},"geometry":{"type":"Point","coordinates":[1.4596615068493153,49.13227315068493]}}]}