{"type":"FeatureCollection","features":[{"type":"Feature","properties":{"codesPostaux":["27370"],"population":154,"nom":"La Pyle","code":"27482"},"geometry":{"type":"Point","coordinates":[0.8970575609756098,49.198749268292694]}}]}