{"type":"FeatureCollection","features":[{"type":"Feature","properties":{"codesPostaux":["27170"],"population":322,"nom":"Romilly-la-Puthenaye","code":"27492"},"geometry":{"type":"Point","coordinates":[0.8324185937500002,49.016747031250034]}}]}