{"type":"FeatureCollection","features":[{"type":"Feature","properties":{"codesPostaux":["27110"],"population":681,"nom":"Saint-Aubin-d'\u00c9crosville","code":"27511"},"geometry":{"type":"Point","coordinates":[0.9863775609756098,49.14309780487804]}}]}