{"type":"FeatureCollection","features":[{"type":"Feature","properties":{"codesPostaux":["27100"],"population":3669,"nom":"Le Vaudreuil","code":"27528"},"geometry":{"type":"Point","coordinates":[1.2035301775147933,49.26011633136097]}}]}