{"type":"FeatureCollection","features":[{"type":"Feature","properties":{"codesPostaux":["27450"],"population":126,"nom":"Saint-Beno\u00eet-des-Ombres","code":"27520"},"geometry":{"type":"Point","coordinates":[0.6193542622950821,49.22734524590163]}}]}