{"type":"FeatureCollection","features":[{"type":"Feature","properties":{"codesPostaux":["27920"],"population":419,"nom":"Saint-\u00c9tienne-sous-Bailleul","code":"27539"},"geometry":{"type":"Point","coordinates":[1.4038448780487809,49.11676951219512]}}]}