{"type":"FeatureCollection","features":[{"type":"Feature","properties":{"codesPostaux":["27190"],"population":443,"nom":"Saint-\u00c9lier","code":"27535"},"geometry":{"type":"Point","coordinates":[0.9605179629629629,48.985655925925904]}}]}