{"type":"FeatureCollection","features":[{"type":"Feature","properties":{"codesPostaux":["27600"],"population":394,"nom":"Saint-Julien-de-la-Li\u00e8gue","code":"27553"},"geometry":{"type":"Point","coordinates":[1.2878887719298246,49.13933736842105]}}]}