{"type":"FeatureCollection","features":[{"type":"Feature","properties":{"codesPostaux":["27930"],"population":255,"nom":"Saint-Luc","code":"27560"},"geometry":{"type":"Point","coordinates":[1.2316855405405407,48.97434283783786]}}]}