{"type":"FeatureCollection","features":[{"type":"Feature","properties":{"codesPostaux":["27950"],"population":4657,"nom":"Saint-Marcel","code":"27562"},"geometry":{"type":"Point","coordinates":[1.4410155223880594,49.0933723880597]}}]}