{"type":"FeatureCollection","features":[{"type":"Feature","properties":{"codesPostaux":["27680"],"population":444,"nom":"Sainte-Opportune-la-Mare","code":"27577"},"geometry":{"type":"Point","coordinates":[0.546606179775281,49.42422561797753]}}]}