{"type":"FeatureCollection","features":[{"type":"Feature","properties":{"codesPostaux":["27370"],"population":1090,"nom":"Saint-Pierre-du-Bosgu\u00e9rard","code":"27595"},"geometry":{"type":"Point","coordinates":[0.8973189830508472,49.26012110169492]}}]}