{"type":"FeatureCollection","features":[{"type":"Feature","properties":{"codesPostaux":["27430"],"population":1309,"nom":"Saint-Pierre-du-Vauvray","code":"27598"},"geometry":{"type":"Point","coordinates":[1.215565849056604,49.22450735849056]}}]}