{"type":"FeatureCollection","features":[{"type":"Feature","properties":{"codesPostaux":["27180"],"population":5167,"nom":"Saint-S\u00e9bastien-de-Morsent","code":"27602"},"geometry":{"type":"Point","coordinates":[1.068387755102041,49.013604183673465]}}]}