{"type":"FeatureCollection","features":[{"type":"Feature","properties":{"codesPostaux":["27150"],"population":493,"nom":"Saussay-la-Campagne","code":"27617"},"geometry":{"type":"Point","coordinates":[1.50659,49.317433428571434]}}]}