{"type":"FeatureCollection","features":[{"type":"Feature","properties":{"codesPostaux":["27230"],"population":253,"nom":"Le Theil-Nolent","code":"27627"},"geometry":{"type":"Point","coordinates":[0.5323901639344261,49.150961475409844]}}]}