{"type":"FeatureCollection","features":[{"type":"Feature","properties":{"codesPostaux":["27220"],"population":139,"nom":"Serez","code":"27621"},"geometry":{"type":"Point","coordinates":[1.3570265714285716,48.936043857142856]}}]}