{"type":"FeatureCollection","features":[{"type":"Feature","properties":{"codesPostaux":["27700"],"population":142,"nom":"Le Thuit","code":"27635"},"geometry":{"type":"Point","coordinates":[1.3691856862745102,49.26232313725491]}}]}