{"type":"FeatureCollection","features":[{"type":"Feature","properties":{"codesPostaux":["27370"],"population":1011,"nom":"Tourville-la-Campagne","code":"27654"},"geometry":{"type":"Point","coordinates":[0.9006185915492957,49.22649563380281]}}]}