{"type":"FeatureCollection","features":[{"type":"Feature","properties":{"codesPostaux":["27350"],"population":352,"nom":"Valletot","code":"27669"},"geometry":{"type":"Point","coordinates":[0.6080621621621625,49.36531783783782]}}]}