{"type":"FeatureCollection","features":[{"type":"Feature","properties":{"codesPostaux":["27480"],"population":507,"nom":"Le Tronquay","code":"27664"},"geometry":{"type":"Point","coordinates":[1.4633235294117652,49.43387399999999]}}]}