{"type":"FeatureCollection","features":[{"type":"Feature","properties":{"codesPostaux":["27700"],"population":260,"nom":"V\u00e9zillon","code":"27683"},"geometry":{"type":"Point","coordinates":[1.3992045454545456,49.22233977272727]}}]}