{"type":"FeatureCollection","features":[{"type":"Feature","properties":{"codesPostaux":["27400"],"population":314,"nom":"Vironvay","code":"27697"},"geometry":{"type":"Point","coordinates":[1.2156815909090908,49.20410477272726]}}]}