{"type":"FeatureCollection","features":[{"type":"Feature","properties":{"codesPostaux":["27110"],"population":185,"nom":"Villettes","code":"27692"},"geometry":{"type":"Point","coordinates":[1.0491471717171719,49.155131818181815]}}]}