{"type":"FeatureCollection","features":[{"type":"Feature","properties":{"codesPostaux":["27420"],"population":304,"nom":"Villers-en-Vexin","code":"27690"},"geometry":{"type":"Point","coordinates":[1.593133157894737,49.24712236842105]}}]}