{"type":"FeatureCollection","features":[{"type":"Feature","properties":{"codesPostaux":["27950"],"population":315,"nom":"Villez-sous-Bailleul","code":"27694"},"geometry":{"type":"Point","coordinates":[1.3696404166666667,49.11009972222223]}}]}