{"type":"FeatureCollection","features":[{"type":"Feature","properties":{"codesPostaux":["27640"],"population":873,"nom":"Villiers-en-D\u00e9s\u0153uvre","code":"27696"},"geometry":{"type":"Point","coordinates":[1.4852373404255317,48.95984276595744]}}]}