{"type":"FeatureCollection","features":[{"type":"Feature","properties":{"codesPostaux":["27110"],"population":275,"nom":"Villez-sur-le-Neubourg","code":"27695"},"geometry":{"type":"Point","coordinates":[0.8560530769230769,49.149836025641015]}}]}