{"type":"FeatureCollection","features":[{"type":"Feature","properties":{"codesPostaux":["28410"],"population":2246,"nom":"Abondant","code":"28001"},"geometry":{"type":"Point","coordinates":[1.4142903743315516,48.801107754010665]}}]}