{"type":"FeatureCollection","features":[{"type":"Feature","properties":{"codesPostaux":["28140"],"population":253,"nom":"Bazoches-en-Dunois","code":"28028"},"geometry":{"type":"Point","coordinates":[1.5763088000000003,48.0943571]}}]}