{"type":"FeatureCollection","features":[{"type":"Feature","properties":{"codesPostaux":["28120"],"population":1504,"nom":"Bailleau-le-Pin","code":"28021"},"geometry":{"type":"Point","coordinates":[1.3238985416666673,48.35696364583333]}}]}