{"type":"FeatureCollection","features":[{"type":"Feature","properties":{"codesPostaux":["28300"],"population":1181,"nom":"Bailleau-l'\u00c9v\u00eaque","code":"28022"},"geometry":{"type":"Point","coordinates":[1.3886819999999997,48.48827496774193]}}]}