{"type":"FeatureCollection","features":[{"type":"Feature","properties":{"codesPostaux":["28700"],"population":1536,"nom":"B\u00e9ville-le-Comte","code":"28039"},"geometry":{"type":"Point","coordinates":[1.7077362711864408,48.44327550847458]}}]}