{"type":"FeatureCollection","features":[{"type":"Feature","properties":{"codesPostaux":["28170"],"population":263,"nom":"Le Boullay-les-Deux-\u00c9glises","code":"28053"},"geometry":{"type":"Point","coordinates":[1.3215346728971966,48.63069074766355]}}]}