{"type":"FeatureCollection","features":[{"type":"Feature","properties":{"codesPostaux":["28260"],"population":272,"nom":"Boncourt","code":"28050"},"geometry":{"type":"Point","coordinates":[1.4615042352941174,48.84586364705882]}}]}