{"type":"FeatureCollection","features":[{"type":"Feature","properties":{"codesPostaux":["28800"],"population":574,"nom":"Bouville","code":"28057"},"geometry":{"type":"Point","coordinates":[1.3818348913043483,48.2625479347826]}}]}