{"type":"FeatureCollection","features":[{"type":"Feature","properties":{"codesPostaux":["28500"],"population":187,"nom":"La Chapelle-Forainvilliers","code":"28076"},"geometry":{"type":"Point","coordinates":[1.490421166666667,48.72729633333335]}}]}