{"type":"FeatureCollection","features":[{"type":"Feature","properties":{"codesPostaux":["28400"],"population":395,"nom":"Champrond-en-Perchet","code":"28072"},"geometry":{"type":"Point","coordinates":[0.8960483098591552,48.30663190140846]}}]}