{"type":"FeatureCollection","features":[{"type":"Feature","properties":{"codesPostaux":["28270"],"population":243,"nom":"Ch\u00e2taincourt","code":"28087"},"geometry":{"type":"Point","coordinates":[1.2379617582417581,48.694675934065934]}}]}