{"type":"FeatureCollection","features":[{"type":"Feature","properties":{"codesPostaux":["28220"],"population":5773,"nom":"Cloyes-les-Trois-Rivi\u00e8res","code":"28103"},"geometry":{"type":"Point","coordinates":[1.296625529157669,48.00319475161982]}}]}