{"type":"FeatureCollection","features":[{"type":"Feature","properties":{"codesPostaux":["28300"],"population":412,"nom":"Cintray","code":"28100"},"geometry":{"type":"Point","coordinates":[1.365579333333334,48.44518022222222]}}]}