{"type":"FeatureCollection","features":[{"type":"Feature","properties":{"codesPostaux":["28210"],"population":1436,"nom":"Coulombs","code":"28113"},"geometry":{"type":"Point","coordinates":[1.5474721472392627,48.655316441717794]}}]}