{"type":"FeatureCollection","features":[{"type":"Feature","properties":{"codesPostaux":["28190"],"population":429,"nom":"Dangers","code":"28128"},"geometry":{"type":"Point","coordinates":[1.351748805970149,48.50655537313431]}}]}