{"type":"FeatureCollection","features":[{"type":"Feature","properties":{"codesPostaux":["28320"],"population":842,"nom":"\u00c9crosnes","code":"28137"},"geometry":{"type":"Point","coordinates":[1.7354415116279072,48.5554276744186]}}]}