{"type":"FeatureCollection","features":[{"type":"Feature","properties":{"codesPostaux":["28800"],"population":216,"nom":"Flacey","code":"28153"},"geometry":{"type":"Point","coordinates":[1.3319241463414635,48.15286926829269]}}]}