{"type":"FeatureCollection","features":[{"type":"Feature","properties":{"codesPostaux":["28270"],"population":172,"nom":"Fessanvilliers-Mattanvilliers","code":"28151"},"geometry":{"type":"Point","coordinates":[1.0348601666666666,48.70425625]}}]}