{"type":"FeatureCollection","features":[{"type":"Feature","properties":{"codesPostaux":["28480"],"population":498,"nom":"Fr\u00e9tigny","code":"28165"},"geometry":{"type":"Point","coordinates":[1.0057162139917695,48.36324637860079]}}]}