{"type":"FeatureCollection","features":[{"type":"Feature","properties":{"codesPostaux":["28500"],"population":283,"nom":"Garanci\u00e8res-en-Drouais","code":"28170"},"geometry":{"type":"Point","coordinates":[1.2857633928571433,48.701061964285714]}}]}