{"type":"FeatureCollection","features":[{"type":"Feature","properties":{"codesPostaux":["28410"],"population":126,"nom":"Havelu","code":"28193"},"geometry":{"type":"Point","coordinates":[1.536214047619048,48.78634904761905]}}]}