{"type":"FeatureCollection","features":[{"type":"Feature","properties":{"codesPostaux":["28500"],"population":204,"nom":"Louvilliers-en-Drouais","code":"28216"},"geometry":{"type":"Point","coordinates":[1.2842259375,48.732921562499996]}}]}