{"type":"FeatureCollection","features":[{"type":"Feature","properties":{"codesPostaux":["28600"],"population":6720,"nom":"Luisant","code":"28220"},"geometry":{"type":"Point","coordinates":[1.474776216216216,48.42511621621621]}}]}