{"type":"FeatureCollection","features":[{"type":"Feature","properties":{"codesPostaux":["28140"],"population":184,"nom":"Lumeau","code":"28221"},"geometry":{"type":"Point","coordinates":[1.7874163636363638,48.10366522727272]}}]}