{"type":"FeatureCollection","features":[{"type":"Feature","properties":{"codesPostaux":["28700"],"population":147,"nom":"Moinville-la-Jeulin","code":"28255"},"geometry":{"type":"Point","coordinates":[1.6977038888888887,48.37880972222221]}}]}