{"type":"FeatureCollection","features":[{"type":"Feature","properties":{"codesPostaux":["28120"],"population":652,"nom":"Montigny-le-Chartif","code":"28261"},"geometry":{"type":"Point","coordinates":[1.1259736756756757,48.29329497297297]}}]}