{"type":"FeatureCollection","features":[{"type":"Feature","properties":{"codesPostaux":["28210"],"population":629,"nom":"N\u00e9ron","code":"28275"},"geometry":{"type":"Point","coordinates":[1.4983886507936515,48.59391888888888]}}]}