{"type":"FeatureCollection","features":[{"type":"Feature","properties":{"codesPostaux":["28800"],"population":332,"nom":"Neuvy-en-Dunois","code":"28277"},"geometry":{"type":"Point","coordinates":[1.5393963157894743,48.203648947368414]}}]}