{"type":"FeatureCollection","features":[{"type":"Feature","properties":{"codesPostaux":["28120"],"population":427,"nom":"Nonvilliers-Grandhoux","code":"28282"},"geometry":{"type":"Point","coordinates":[1.145812542372882,48.33582491525421]}}]}