{"type":"FeatureCollection","features":[{"type":"Feature","properties":{"codesPostaux":["28210"],"population":243,"nom":"Ormoy","code":"28289"},"geometry":{"type":"Point","coordinates":[1.4687825862068964,48.624444482758605]}}]}