{"type":"FeatureCollection","features":[{"type":"Feature","properties":{"codesPostaux":["28140"],"population":271,"nom":"P\u00e9ronville","code":"28296"},"geometry":{"type":"Point","coordinates":[1.5804739000000003,48.062257800000005]}}]}