{"type":"FeatureCollection","features":[{"type":"Feature","properties":{"codesPostaux":["28360"],"population":1040,"nom":"Prunay-le-Gillon","code":"28309"},"geometry":{"type":"Point","coordinates":[1.6285439189189186,48.36305905405405]}}]}