{"type":"FeatureCollection","features":[{"type":"Feature","properties":{"codesPostaux":["28140"],"population":102,"nom":"Poupry","code":"28303"},"geometry":{"type":"Point","coordinates":[1.8311244444444446,48.098080634920635]}}]}