{"type":"FeatureCollection","features":[{"type":"Feature","properties":{"codesPostaux":["28310"],"population":464,"nom":"Rouvray-Saint-Denis","code":"28319"},"geometry":{"type":"Point","coordinates":[1.949322653061226,48.2790742857143]}}]}