{"type":"FeatureCollection","features":[{"type":"Feature","properties":{"codesPostaux":["28270"],"population":22,"nom":"Revercourt","code":"28315"},"geometry":{"type":"Point","coordinates":[1.0819664473684212,48.72294381578946]}}]}