{"type":"FeatureCollection","features":[{"type":"Feature","properties":{"codesPostaux":["28340"],"population":149,"nom":"Rohaire","code":"28316"},"geometry":{"type":"Point","coordinates":[0.8424075294117646,48.66775470588236]}}]}