{"type":"FeatureCollection","features":[{"type":"Feature","properties":{"codesPostaux":["28410"],"population":916,"nom":"Saint-Lubin-de-la-Haye","code":"28347"},"geometry":{"type":"Point","coordinates":[1.56250847826087,48.821181521739156]}}]}