{"type":"FeatureCollection","features":[{"type":"Feature","properties":{"codesPostaux":["28120"],"population":389,"nom":"Sandarville","code":"28365"},"geometry":{"type":"Point","coordinates":[1.347160357142857,48.34489428571429]}}]}