{"type":"FeatureCollection","features":[{"type":"Feature","properties":{"codesPostaux":["28800"],"population":837,"nom":"Sancheville","code":"28364"},"geometry":{"type":"Point","coordinates":[1.5841852857142864,48.18163328571429]}}]}