{"type":"FeatureCollection","features":[{"type":"Feature","properties":{"codesPostaux":["28240"],"population":512,"nom":"Saint-Victor-de-Buthon","code":"28362"},"geometry":{"type":"Point","coordinates":[0.9761997046413502,48.40045987341772]}}]}