{"type":"FeatureCollection","features":[{"type":"Feature","properties":{"codesPostaux":["28250"],"population":3121,"nom":"Senonches","code":"28373"},"geometry":{"type":"Point","coordinates":[1.0229439114391148,48.56063590405908]}}]}