{"type":"FeatureCollection","features":[{"type":"Feature","properties":{"codesPostaux":["28630"],"population":1916,"nom":"Sours","code":"28380"},"geometry":{"type":"Point","coordinates":[1.5931576146788986,48.42348770642203]}}]}