{"type":"FeatureCollection","features":[{"type":"Feature","properties":{"codesPostaux":["28630"],"population":1042,"nom":"Thivars","code":"28388"},"geometry":{"type":"Point","coordinates":[1.446940298507463,48.382867910447764]}}]}