{"type":"FeatureCollection","features":[{"type":"Feature","properties":{"codesPostaux":["28160"],"population":1259,"nom":"Unverre","code":"28398"},"geometry":{"type":"Point","coordinates":[1.060759369085173,48.19296280757093]}}]}