{"type":"FeatureCollection","features":[{"type":"Feature","properties":{"codesPostaux":["28310"],"population":175,"nom":"Trancrainville","code":"28392"},"geometry":{"type":"Point","coordinates":[1.8628688888888891,48.238518194444445]}}]}