{"type":"FeatureCollection","features":[{"type":"Feature","properties":{"codesPostaux":["28700"],"population":414,"nom":"Umpeau","code":"28397"},"geometry":{"type":"Point","coordinates":[1.6694051785714288,48.468438750000004]}}]}