{"type":"FeatureCollection","features":[{"type":"Feature","properties":{"codesPostaux":["28400"],"population":463,"nom":"Trizay-Coutretot-Saint-Serge","code":"28395"},"geometry":{"type":"Point","coordinates":[0.878222649006623,48.28979867549669]}}]}