{"type":"FeatureCollection","features":[{"type":"Feature","properties":{"codesPostaux":["28500"],"population":1177,"nom":"Vert-en-Drouais","code":"28405"},"geometry":{"type":"Point","coordinates":[1.2974530681818182,48.75108829545456]}}]}