{"type":"FeatureCollection","features":[{"type":"Feature","properties":{"codesPostaux":["28150"],"population":487,"nom":"Ymonville","code":"28426"},"geometry":{"type":"Point","coordinates":[1.7422646153846146,48.24301288461541]}}]}