{"type":"FeatureCollection","features":[{"type":"Feature","properties":{"codesPostaux":["28700"],"population":296,"nom":"Voise","code":"28421"},"geometry":{"type":"Point","coordinates":[1.7078694545454542,48.404585454545455]}}]}