{"type":"FeatureCollection","features":[{"type":"Feature","properties":{"codesPostaux":["29300"],"population":1384,"nom":"Arzano","code":"29002"},"geometry":{"type":"Point","coordinates":[-3.44289206751055,47.890537890295356]}}]}