{"type":"FeatureCollection","features":[{"type":"Feature","properties":{"codesPostaux":["29650"],"population":448,"nom":"Botsorhel","code":"29014"},"geometry":{"type":"Point","coordinates":[-3.63134465671642,48.50844146268656]}}]}