{"type":"FeatureCollection","features":[{"type":"Feature","properties":{"codesPostaux":["29820"],"population":3528,"nom":"Bohars","code":"29011"},"geometry":{"type":"Point","coordinates":[-4.521650650406505,48.429689105691075]}}]}