{"type":"FeatureCollection","features":[{"type":"Feature","properties":{"codesPostaux":["29200"],"population":139386,"nom":"Brest","code":"29019"},"geometry":{"type":"Point","coordinates":[-4.501745593952485,48.402931706263466]}}]}