{"type":"FeatureCollection","features":[{"type":"Feature","properties":{"codesPostaux":["29150"],"population":5177,"nom":"Ch\u00e2teaulin","code":"29026"},"geometry":{"type":"Point","coordinates":[-4.077768230088496,48.20340548672571]}}]}