{"type":"FeatureCollection","features":[{"type":"Feature","properties":{"codesPostaux":["29660"],"population":3151,"nom":"Carantec","code":"29023"},"geometry":{"type":"Point","coordinates":[-3.91039683516484,48.67437676923073]}}]}