{"type":"FeatureCollection","features":[{"type":"Feature","properties":{"codesPostaux":["29450"],"population":1080,"nom":"Commana","code":"29038"},"geometry":{"type":"Point","coordinates":[-3.9733237499999996,48.41331173076922]}}]}