{"type":"FeatureCollection","features":[{"type":"Feature","properties":{"codesPostaux":["29370"],"population":1904,"nom":"Coray","code":"29041"},"geometry":{"type":"Point","coordinates":[-3.8569363963963994,48.07048534534531]}}]}