{"type":"FeatureCollection","features":[{"type":"Feature","properties":{"codesPostaux":["29860"],"population":1772,"nom":"Le Drennec","code":"29047"},"geometry":{"type":"Point","coordinates":[-4.379001344537818,48.53254756302521]}}]}