{"type":"FeatureCollection","features":[{"type":"Feature","properties":{"codesPostaux":["29510"],"population":2202,"nom":"Edern","code":"29048"},"geometry":{"type":"Point","coordinates":[-3.9648198044692746,48.1117274022346]}}]}