{"type":"FeatureCollection","features":[{"type":"Feature","properties":{"codesPostaux":["29890"],"population":436,"nom":"Goulven","code":"29064"},"geometry":{"type":"Point","coordinates":[-4.292834736842105,48.62770842105262]}}]}