{"type":"FeatureCollection","features":[{"type":"Feature","properties":{"codesPostaux":["29620"],"population":974,"nom":"Guima\u00ebc","code":"29073"},"geometry":{"type":"Point","coordinates":[-3.7014610031347965,48.678284200627]}}]}