{"type":"FeatureCollection","features":[{"type":"Feature","properties":{"codesPostaux":["29880"],"population":2024,"nom":"Guiss\u00e9ny","code":"29077"},"geometry":{"type":"Point","coordinates":[-4.4107463188405776,48.62498185507245]}}]}