{"type":"FeatureCollection","features":[{"type":"Feature","properties":{"codesPostaux":["29870"],"population":5378,"nom":"Lannilis","code":"29117"},"geometry":{"type":"Point","coordinates":[-4.525883166023168,48.5683622779923]}}]}