{"type":"FeatureCollection","features":[{"type":"Feature","properties":{"codesPostaux":["29840"],"population":949,"nom":"Lanildut","code":"29112"},"geometry":{"type":"Point","coordinates":[-4.7423220297029705,48.47894336633663]}}]}