{"type":"FeatureCollection","features":[{"type":"Feature","properties":{"codesPostaux":["29260"],"population":7229,"nom":"Lesneven","code":"29124"},"geometry":{"type":"Point","coordinates":[-4.311371960784315,48.581156813725485]}}]}