{"type":"FeatureCollection","features":[{"type":"Feature","properties":{"codesPostaux":["29590"],"population":835,"nom":"Lop\u00e9rec","code":"29139"},"geometry":{"type":"Point","coordinates":[-4.033730863787377,48.30564518272423]}}]}