{"type":"FeatureCollection","features":[{"type":"Feature","properties":{"codesPostaux":["29460"],"population":2110,"nom":"Logonna-Daoulas","code":"29137"},"geometry":{"type":"Point","coordinates":[-4.300371566579633,48.32567154046993]}}]}