{"type":"FeatureCollection","features":[{"type":"Feature","properties":{"codesPostaux":["29190"],"population":461,"nom":"Lothey","code":"29142"},"geometry":{"type":"Point","coordinates":[-4.0225219780219765,48.18250307692309]}}]}