{"type":"FeatureCollection","features":[{"type":"Feature","properties":{"codesPostaux":["29140"],"population":3408,"nom":"Melgven","code":"29146"},"geometry":{"type":"Point","coordinates":[-3.840628473282442,47.912335496183175]}}]}