{"type":"FeatureCollection","features":[{"type":"Feature","properties":{"codesPostaux":["29800"],"population":1862,"nom":"Pencran","code":"29156"},"geometry":{"type":"Point","coordinates":[-4.21725062111801,48.44570975155281]}}]}