{"type":"FeatureCollection","features":[{"type":"Feature","properties":{"codesPostaux":["29190"],"population":3710,"nom":"Pleyben","code":"29162"},"geometry":{"type":"Point","coordinates":[-3.9647439344262314,48.24634814207651]}}]}