{"type":"FeatureCollection","features":[{"type":"Feature","properties":{"codesPostaux":["29550"],"population":2148,"nom":"Plomodiern","code":"29172"},"geometry":{"type":"Point","coordinates":[-4.21682294594595,48.17590610810813]}}]}