{"type":"FeatureCollection","features":[{"type":"Feature","properties":{"codesPostaux":["29252"],"population":1590,"nom":"Plouezoc'h","code":"29186"},"geometry":{"type":"Point","coordinates":[-3.816828262295081,48.63895009836066]}}]}