{"type":"FeatureCollection","features":[{"type":"Feature","properties":{"codesPostaux":["29260"],"population":1972,"nom":"Plouider","code":"29198"},"geometry":{"type":"Point","coordinates":[-4.302543738872405,48.60495367952521]}}]}