{"type":"FeatureCollection","features":[{"type":"Feature","properties":{"codesPostaux":["29640"],"population":3371,"nom":"Plougonven","code":"29191"},"geometry":{"type":"Point","coordinates":[-3.7320820740740785,48.51366172222223]}}]}