{"type":"FeatureCollection","features":[{"type":"Feature","properties":{"codesPostaux":["29410"],"population":1283,"nom":"Ploun\u00e9our-M\u00e9nez","code":"29202"},"geometry":{"type":"Point","coordinates":[-3.8844279487179505,48.45120096866097]}}]}