{"type":"FeatureCollection","features":[{"type":"Feature","properties":{"codesPostaux":["29720"],"population":669,"nom":"Plovan","code":"29214"},"geometry":{"type":"Point","coordinates":[-4.349092391304346,47.9414268115942]}}]}