{"type":"FeatureCollection","features":[{"type":"Feature","properties":{"codesPostaux":["29180"],"population":1134,"nom":"Qu\u00e9m\u00e9n\u00e9ven","code":"29229"},"geometry":{"type":"Point","coordinates":[-4.142706754385966,48.11841311403507]}}]}