{"type":"FeatureCollection","features":[{"type":"Feature","properties":{"codesPostaux":["29000"],"population":63532,"nom":"Quimper","code":"29232"},"geometry":{"type":"Point","coordinates":[-4.091922355769229,47.99010443509615]}}]}