{"type":"FeatureCollection","features":[{"type":"Feature","properties":{"codesPostaux":["29680"],"population":3434,"nom":"Roscoff","code":"29239"},"geometry":{"type":"Point","coordinates":[-3.987265447154471,48.71853284552851]}}]}