{"type":"FeatureCollection","features":[{"type":"Feature","properties":{"codesPostaux":["29260"],"population":869,"nom":"Saint-M\u00e9en","code":"29255"},"geometry":{"type":"Point","coordinates":[-4.256493408071748,48.55531892376682]}}]}