{"type":"FeatureCollection","features":[{"type":"Feature","properties":{"codesPostaux":["29120"],"population":1006,"nom":"Saint-Jean-Trolimon","code":"29252"},"geometry":{"type":"Point","coordinates":[-4.3090200896861015,47.870939955156935]}}]}