{"type":"FeatureCollection","features":[{"type":"Feature","properties":{"codesPostaux":["29250"],"population":2335,"nom":"Santec","code":"29273"},"geometry":{"type":"Point","coordinates":[-4.037837119565217,48.702939021739134]}}]}