{"type":"FeatureCollection","features":[{"type":"Feature","properties":{"codesPostaux":["29140"],"population":2939,"nom":"Saint-Yvi","code":"29272"},"geometry":{"type":"Point","coordinates":[-3.9442460000000015,47.959452382352914]}}]}