{"type":"FeatureCollection","features":[{"type":"Feature","properties":{"codesPostaux":["29720"],"population":563,"nom":"Tr\u00e9ogat","code":"29298"},"geometry":{"type":"Point","coordinates":[-4.3353428037383175,47.90993074766356]}}]}