{"type":"FeatureCollection","features":[{"type":"Feature","properties":{"codesPostaux":["20112"],"population":46,"nom":"Altag\u00e8ne","code":"2A011"},"geometry":{"type":"Point","coordinates":[9.070252499999999,41.70849721153844]}}]}