{"type":"FeatureCollection","features":[{"type":"Feature","properties":{"codesPostaux":["20119"],"population":546,"nom":"Bastelica","code":"2A031"},"geometry":{"type":"Point","coordinates":[9.044137302631578,41.98189054276319]}}]}