{"type":"FeatureCollection","features":[{"type":"Feature","properties":{"codesPostaux":["20169"],"population":2961,"nom":"Bonifacio","code":"2A041"},"geometry":{"type":"Point","coordinates":[9.204374804492526,41.40321238352737]}}]}