{"type":"FeatureCollection","features":[{"type":"Feature","properties":{"codesPostaux":["20117"],"population":1323,"nom":"Cauro","code":"2A085"},"geometry":{"type":"Point","coordinates":[8.885042334630345,41.90477381322959]}}]}