{"type":"FeatureCollection","features":[{"type":"Feature","properties":{"codesPostaux":["20134"],"population":134,"nom":"Ciamannacce","code":"2A089"},"geometry":{"type":"Point","coordinates":[9.135923828828828,41.968656126126156]}}]}