{"type":"FeatureCollection","features":[{"type":"Feature","properties":{"codesPostaux":["20100"],"population":144,"nom":"Foce","code":"2A115"},"geometry":{"type":"Point","coordinates":[9.041673040935674,41.624408128655]}}]}