{"type":"FeatureCollection","features":[{"type":"Feature","properties":{"codesPostaux":["20157"],"population":122,"nom":"Frasseto","code":"2A119"},"geometry":{"type":"Point","coordinates":[9.037721717171713,41.91847601010102]}}]}