{"type":"FeatureCollection","features":[{"type":"Feature","properties":{"codesPostaux":["20150"],"population":596,"nom":"Ota","code":"2A198"},"geometry":{"type":"Point","coordinates":[8.731029631336403,42.25633580645162]}}]}