{"type":"FeatureCollection","features":[{"type":"Feature","properties":{"codesPostaux":["20167"],"population":1806,"nom":"Peri","code":"2A209"},"geometry":{"type":"Point","coordinates":[8.90091852941176,42.00296815126054]}}]}