{"type":"FeatureCollection","features":[{"type":"Feature","properties":{"codesPostaux":["20131"],"population":940,"nom":"Pianottoli-Caldarello","code":"2A215"},"geometry":{"type":"Point","coordinates":[9.044132934232717,41.49305497470488]}}]}