{"type":"FeatureCollection","features":[{"type":"Feature","properties":{"codesPostaux":["20110"],"population":3734,"nom":"Propriano","code":"2A249"},"geometry":{"type":"Point","coordinates":[8.895465096153844,41.65713100961538]}}]}