{"type":"FeatureCollection","features":[{"type":"Feature","properties":{"codesPostaux":["20137"],"population":11354,"nom":"Porto-Vecchio","code":"2A247"},"geometry":{"type":"Point","coordinates":[9.299950274999997,41.56623046666673]}}]}