{"type":"FeatureCollection","features":[{"type":"Feature","properties":{"codesPostaux":["20121"],"population":53,"nom":"Rezza","code":"2A259"},"geometry":{"type":"Point","coordinates":[8.951653538461542,42.12786823076927]}}]}