{"type":"FeatureCollection","features":[{"type":"Feature","properties":{"codesPostaux":["20146"],"population":1123,"nom":"Sotta","code":"2A288"},"geometry":{"type":"Point","coordinates":[9.18047055749129,41.551049407665516]}}]}