{"type":"FeatureCollection","features":[{"type":"Feature","properties":{"codesPostaux":["20151"],"population":75,"nom":"Sant'Andr\u00e9a-d'Orcino","code":"2A295"},"geometry":{"type":"Point","coordinates":[8.779284472049692,42.049673975155265]}}]}