{"type":"FeatureCollection","features":[{"type":"Feature","properties":{"codesPostaux":["20128"],"population":71,"nom":"Urbalacone","code":"2A331"},"geometry":{"type":"Point","coordinates":[8.948975144927534,41.826377681159435]}}]}