{"type":"FeatureCollection","features":[{"type":"Feature","properties":{"codesPostaux":["20173"],"population":61,"nom":"Z\u00e9vaco","code":"2A358"},"geometry":{"type":"Point","coordinates":[9.047977745664735,41.88900317919075]}}]}