{"type":"FeatureCollection","features":[{"type":"Feature","properties":{"codesPostaux":["20220"],"population":301,"nom":"Algajola","code":"2B010"},"geometry":{"type":"Point","coordinates":[8.858076666666667,42.606024367816104]}}]}