{"type":"FeatureCollection","features":[{"type":"Feature","properties":{"codesPostaux":["20235"],"population":96,"nom":"Canavaggia","code":"2B059"},"geometry":{"type":"Point","coordinates":[9.230967421052622,42.50244831578946]}}]}