{"type":"FeatureCollection","features":[{"type":"Feature","properties":{"codesPostaux":["20230"],"population":205,"nom":"Chiatra","code":"2B088"},"geometry":{"type":"Point","coordinates":[9.490332622950817,42.28895926229508]}}]}