{"type":"FeatureCollection","features":[{"type":"Feature","properties":{"codesPostaux":["20290"],"population":54,"nom":"Crocicchia","code":"2B102"},"geometry":{"type":"Point","coordinates":[9.353534950495051,42.47520683168318]}}]}