{"type":"FeatureCollection","features":[{"type":"Feature","properties":{"codesPostaux":["20212"],"population":106,"nom":"Erbajolo","code":"2B105"},"geometry":{"type":"Point","coordinates":[9.266818108108106,42.25207304054053]}}]}