{"type":"FeatureCollection","features":[{"type":"Feature","properties":{"codesPostaux":["20219"],"population":40,"nom":"Muracciole","code":"2B171"},"geometry":{"type":"Point","coordinates":[9.18645922413793,42.17430413793106]}}]}