{"type":"FeatureCollection","features":[{"type":"Feature","properties":{"codesPostaux":["20234"],"population":56,"nom":"Novale","code":"2B179"},"geometry":{"type":"Point","coordinates":[9.412850808080806,42.305536464646444]}}]}