{"type":"FeatureCollection","features":[{"type":"Feature","properties":{"codesPostaux":["20225"],"population":233,"nom":"Muro","code":"2B173"},"geometry":{"type":"Point","coordinates":[8.918790425531911,42.54253609929076]}}]}