{"type":"FeatureCollection","features":[{"type":"Feature","properties":{"codesPostaux":["20229"],"population":49,"nom":"Piazzole","code":"2B217"},"geometry":{"type":"Point","coordinates":[9.404402613636366,42.39500874999999]}}]}