{"type":"FeatureCollection","features":[{"type":"Feature","properties":{"codesPostaux":["20218"],"population":152,"nom":"Piedigriggio","code":"2B220"},"geometry":{"type":"Point","coordinates":[9.183919587628866,42.44532288659791]}}]}