{"type":"FeatureCollection","features":[{"type":"Feature","properties":{"codesPostaux":["20218"],"population":43,"nom":"Prato-di-Giovellina","code":"2B248"},"geometry":{"type":"Point","coordinates":[9.1662003030303,42.41554212121212]}}]}