{"type":"FeatureCollection","features":[{"type":"Feature","properties":{"codesPostaux":["20246"],"population":137,"nom":"Sorio","code":"2B287"},"geometry":{"type":"Point","coordinates":[9.250991545454546,42.57945472727272]}}]}