{"type":"FeatureCollection","features":[{"type":"Feature","properties":{"codesPostaux":["20213"],"population":55,"nom":"San-Damiano","code":"2B297"},"geometry":{"type":"Point","coordinates":[9.41162465346535,42.40516712871286]}}]}