{"type":"FeatureCollection","features":[{"type":"Feature","properties":{"codesPostaux":["20200"],"population":2941,"nom":"San-Martino-di-Lota","code":"2B305"},"geometry":{"type":"Point","coordinates":[9.439108174603179,42.73295380952378]}}]}