{"type":"FeatureCollection","features":[{"type":"Feature","properties":{"codesPostaux":["20214"],"population":294,"nom":"Zilia","code":"2B361"},"geometry":{"type":"Point","coordinates":[8.898984085365855,42.52273640243902]}}]}