{"type":"FeatureCollection","features":[{"type":"Feature","properties":{"codesPostaux":["30770"],"population":196,"nom":"Alzon","code":"30009"},"geometry":{"type":"Point","coordinates":[3.4475774122806992,43.966228552631556]}}]}