{"type":"FeatureCollection","features":[{"type":"Feature","properties":{"codesPostaux":["30470"],"population":5074,"nom":"Aimargues","code":"30006"},"geometry":{"type":"Point","coordinates":[4.2052580341880335,43.67089213675212]}}]}