{"type":"FeatureCollection","features":[{"type":"Feature","properties":{"codesPostaux":["30210"],"population":445,"nom":"Argilliers","code":"30013"},"geometry":{"type":"Point","coordinates":[4.490676617647057,43.979379558823524]}}]}