{"type":"FeatureCollection","features":[{"type":"Feature","properties":{"codesPostaux":["30770"],"population":206,"nom":"Arrigas","code":"30017"},"geometry":{"type":"Point","coordinates":[3.4857871250000008,43.989113625]}}]}