{"type":"FeatureCollection","features":[{"type":"Feature","properties":{"codesPostaux":["30700"],"population":353,"nom":"Baron","code":"30030"},"geometry":{"type":"Point","coordinates":[4.281415999999999,44.054111125000006]}}]}