{"type":"FeatureCollection","features":[{"type":"Feature","properties":{"codesPostaux":["30580"],"population":172,"nom":"Bouquet","code":"30048"},"geometry":{"type":"Point","coordinates":[4.30453480392157,44.151647745098046]}}]}