{"type":"FeatureCollection","features":[{"type":"Feature","properties":{"codesPostaux":["30190"],"population":796,"nom":"Brignon","code":"30053"},"geometry":{"type":"Point","coordinates":[4.212508493150687,44.00055082191781]}}]}