{"type":"FeatureCollection","features":[{"type":"Feature","properties":{"codesPostaux":["30120"],"population":414,"nom":"Br\u00e9au-et-Salagosse","code":"30052"},"geometry":{"type":"Point","coordinates":[3.5595532663316565,44.01893442211054]}}]}