{"type":"FeatureCollection","features":[{"type":"Feature","properties":{"codesPostaux":["30740"],"population":2370,"nom":"Le Cailar","code":"30059"},"geometry":{"type":"Point","coordinates":[4.242095549132947,43.66208687861273]}}]}