{"type":"FeatureCollection","features":[{"type":"Feature","properties":{"codesPostaux":["30260"],"population":153,"nom":"Bragassargues","code":"30050"},"geometry":{"type":"Point","coordinates":[4.045877246376813,43.92234347826087]}}]}