{"type":"FeatureCollection","features":[{"type":"Feature","properties":{"codesPostaux":["30450"],"population":258,"nom":"Concoules","code":"30090"},"geometry":{"type":"Point","coordinates":[3.950968058823531,44.37599941176471]}}]}