{"type":"FeatureCollection","features":[{"type":"Feature","properties":{"codesPostaux":["30190"],"population":598,"nom":"Dions","code":"30102"},"geometry":{"type":"Point","coordinates":[4.297483214285713,43.920234404761906]}}]}