{"type":"FeatureCollection","features":[{"type":"Feature","properties":{"codesPostaux":["30350"],"population":681,"nom":"Domessargues","code":"30104"},"geometry":{"type":"Point","coordinates":[4.16291255319149,43.97630872340425]}}]}