{"type":"FeatureCollection","features":[{"type":"Feature","properties":{"codesPostaux":["30170"],"population":726,"nom":"Durfort-et-Saint-Martin-de-Sossenac","code":"30106"},"geometry":{"type":"Point","coordinates":[3.9524433124999994,43.98580475000003]}}]}