{"type":"FeatureCollection","features":[{"type":"Feature","properties":{"codesPostaux":["30250"],"population":660,"nom":"Fontan\u00e8s","code":"30114"},"geometry":{"type":"Point","coordinates":[4.096781521739132,43.829818333333364]}}]}