{"type":"FeatureCollection","features":[{"type":"Feature","properties":{"codesPostaux":["30700"],"population":325,"nom":"Flaux","code":"30110"},"geometry":{"type":"Point","coordinates":[4.51102268907563,44.007337563025224]}}]}