{"type":"FeatureCollection","features":[{"type":"Feature","properties":{"codesPostaux":["30510"],"population":4024,"nom":"G\u00e9n\u00e9rac","code":"30128"},"geometry":{"type":"Point","coordinates":[4.35087456521739,43.726296304347834]}}]}