{"type":"FeatureCollection","features":[{"type":"Feature","properties":{"codesPostaux":["30250"],"population":1079,"nom":"Junas","code":"30136"},"geometry":{"type":"Point","coordinates":[4.112449999999999,43.761176448598135]}}]}