{"type":"FeatureCollection","features":[{"type":"Feature","properties":{"codesPostaux":["30110"],"population":1178,"nom":"Laval-Pradel","code":"30142"},"geometry":{"type":"Point","coordinates":[4.068920000000002,44.214576860465115]}}]}