{"type":"FeatureCollection","features":[{"type":"Feature","properties":{"codesPostaux":["30450"],"population":118,"nom":"Malons-et-Elze","code":"30153"},"geometry":{"type":"Point","coordinates":[4.015995486381326,44.42627171206229]}}]}