{"type":"FeatureCollection","features":[{"type":"Feature","properties":{"codesPostaux":["30140"],"population":671,"nom":"Massillargues-Attuech","code":"30162"},"geometry":{"type":"Point","coordinates":[4.021165277777778,44.01612444444444]}}]}