{"type":"FeatureCollection","features":[{"type":"Feature","properties":{"codesPostaux":["30200"],"population":1079,"nom":"Orsan","code":"30191"},"geometry":{"type":"Point","coordinates":[4.6610003125000015,44.135239895833344]}}]}