{"type":"FeatureCollection","features":[{"type":"Feature","properties":{"codesPostaux":["30530"],"population":368,"nom":"Portes","code":"30203"},"geometry":{"type":"Point","coordinates":[4.040003103448274,44.26440868965518]}}]}