{"type":"FeatureCollection","features":[{"type":"Feature","properties":{"codesPostaux":["30150"],"population":5458,"nom":"Roquemaure","code":"30221"},"geometry":{"type":"Point","coordinates":[4.761191885245903,44.04034770491803]}}]}