{"type":"FeatureCollection","features":[{"type":"Feature","properties":{"codesPostaux":["30330"],"population":411,"nom":"Saint-Andr\u00e9-d'Ol\u00e9rargues","code":"30232"},"geometry":{"type":"Point","coordinates":[4.500032962962962,44.16896425925928]}}]}