{"type":"FeatureCollection","features":[{"type":"Feature","properties":{"codesPostaux":["30440"],"population":54,"nom":"Saint-Bresson","code":"30238"},"geometry":{"type":"Point","coordinates":[3.6461734313725476,43.954265196078445]}}]}