{"type":"FeatureCollection","features":[{"type":"Feature","properties":{"codesPostaux":["30380"],"population":6863,"nom":"Saint-Christol-l\u00e8s-Al\u00e8s","code":"30243"},"geometry":{"type":"Point","coordinates":[4.0740407831325305,44.08726590361446]}}]}