{"type":"FeatureCollection","features":[{"type":"Feature","properties":{"codesPostaux":["30360"],"population":162,"nom":"Saint-Jean-de-Ceyrargues","code":"30264"},"geometry":{"type":"Point","coordinates":[4.224312745098041,44.05576686274511]}}]}