{"type":"FeatureCollection","features":[{"type":"Feature","properties":{"codesPostaux":["30340"],"population":3268,"nom":"Saint-Julien-les-Rosiers","code":"30274"},"geometry":{"type":"Point","coordinates":[4.095767218543046,44.19501086092715]}}]}