{"type":"FeatureCollection","features":[{"type":"Feature","properties":{"codesPostaux":["30440"],"population":360,"nom":"Saint-Laurent-le-Minier","code":"30280"},"geometry":{"type":"Point","coordinates":[3.6518431707317074,43.92663666666667]}}]}