{"type":"FeatureCollection","features":[{"type":"Feature","properties":{"codesPostaux":["30130"],"population":1783,"nom":"Saint-Paulet-de-Caisson","code":"30290"},"geometry":{"type":"Point","coordinates":[4.581482920353982,44.2626195575221]}}]}