{"type":"FeatureCollection","features":[{"type":"Feature","properties":{"codesPostaux":["30140"],"population":530,"nom":"Saint-S\u00e9bastien-d'Aigrefeuille","code":"30298"},"geometry":{"type":"Point","coordinates":[3.984279809523809,44.12108561904762]}}]}