{"type":"FeatureCollection","features":[{"type":"Feature","properties":{"codesPostaux":["30700"],"population":304,"nom":"Saint-Victor-des-Oules","code":"30301"},"geometry":{"type":"Point","coordinates":[4.481467555555556,44.04418711111111]}}]}