{"type":"FeatureCollection","features":[{"type":"Feature","properties":{"codesPostaux":["30340"],"population":3209,"nom":"Salindres","code":"30305"},"geometry":{"type":"Point","coordinates":[4.163688924731183,44.162486559139786]}}]}