{"type":"FeatureCollection","features":[{"type":"Feature","properties":{"codesPostaux":["30610"],"population":1974,"nom":"Sauve","code":"30311"},"geometry":{"type":"Point","coordinates":[3.957410063291141,43.935965759493655]}}]}