{"type":"FeatureCollection","features":[{"type":"Feature","properties":{"codesPostaux":["30440"],"population":1626,"nom":"Sum\u00e8ne","code":"30325"},"geometry":{"type":"Point","coordinates":[3.731845384615387,43.99010639676112]}}]}