{"type":"FeatureCollection","features":[{"type":"Feature","properties":{"codesPostaux":["30620"],"population":4219,"nom":"Uchaud","code":"30333"},"geometry":{"type":"Point","coordinates":[4.268300961538462,43.75696394230768]}}]}