{"type":"FeatureCollection","features":[{"type":"Feature","properties":{"codesPostaux":["30630"],"population":619,"nom":"Verfeuil","code":"30343"},"geometry":{"type":"Point","coordinates":[4.458754933333333,44.170588488888896]}}]}