{"type":"FeatureCollection","features":[{"type":"Feature","properties":{"codesPostaux":["30210"],"population":555,"nom":"Valligui\u00e8res","code":"30340"},"geometry":{"type":"Point","coordinates":[4.593902110091744,44.0096618348624]}}]}