{"type":"FeatureCollection","features":[{"type":"Feature","properties":{"codesPostaux":["30770"],"population":55,"nom":"Vissec","code":"30353"},"geometry":{"type":"Point","coordinates":[3.4563466153846147,43.901673461538465]}}]}