{"type":"FeatureCollection","features":[{"type":"Feature","properties":{"codesPostaux":["30400"],"population":11833,"nom":"Villeneuve-l\u00e8s-Avignon","code":"30351"},"geometry":{"type":"Point","coordinates":[4.805517843137256,43.98269529411764]}}]}