{"type":"FeatureCollection","features":[{"type":"Feature","properties":{"codesPostaux":["31420"],"population":321,"nom":"Alan","code":"31005"},"geometry":{"type":"Point","coordinates":[0.9300576047904191,43.225228622754486]}}]}