{"type":"FeatureCollection","features":[{"type":"Feature","properties":{"codesPostaux":["31110"],"population":30,"nom":"Artigue","code":"31019"},"geometry":{"type":"Point","coordinates":[0.6418471428571428,42.82714285714287]}}]}