{"type":"FeatureCollection","features":[{"type":"Feature","properties":{"codesPostaux":["31320"],"population":810,"nom":"Aureville","code":"31025"},"geometry":{"type":"Point","coordinates":[1.4589804123711334,43.48017432989691]}}]}