{"type":"FeatureCollection","features":[{"type":"Feature","properties":{"codesPostaux":["31190"],"population":224,"nom":"Auribail","code":"31027"},"geometry":{"type":"Point","coordinates":[1.3759121367521367,43.34797282051281]}}]}