{"type":"FeatureCollection","features":[{"type":"Feature","properties":{"codesPostaux":["31130"],"population":14929,"nom":"Balma","code":"31044"},"geometry":{"type":"Point","coordinates":[1.5131594444444443,43.60858122222221]}}]}