{"type":"FeatureCollection","features":[{"type":"Feature","properties":{"codesPostaux":["31460"],"population":150,"nom":"Beauville","code":"31055"},"geometry":{"type":"Point","coordinates":[1.7695195121951222,43.46711195121951]}}]}