{"type":"FeatureCollection","features":[{"type":"Feature","properties":{"codesPostaux":["31700"],"population":5824,"nom":"Beauzelle","code":"31056"},"geometry":{"type":"Point","coordinates":[1.3727568333333333,43.670451833333324]}}]}