{"type":"FeatureCollection","features":[{"type":"Feature","properties":{"codesPostaux":["31110"],"population":25,"nom":"Benque-Dessous-et-Dessus","code":"31064"},"geometry":{"type":"Point","coordinates":[0.5472420512820512,42.81953025641027]}}]}