{"type":"FeatureCollection","features":[{"type":"Feature","properties":{"codesPostaux":["31350"],"population":504,"nom":"Blajan","code":"31070"},"geometry":{"type":"Point","coordinates":[0.644943269230769,43.25371769230766]}}]}