{"type":"FeatureCollection","features":[{"type":"Feature","properties":{"codesPostaux":["31230"],"population":77,"nom":"Boiss\u00e8de","code":"31072"},"geometry":{"type":"Point","coordinates":[0.8250081818181818,43.40703054545454]}}]}