{"type":"FeatureCollection","features":[{"type":"Feature","properties":{"codesPostaux":["31530"],"population":603,"nom":"Bretx","code":"31089"},"geometry":{"type":"Point","coordinates":[1.1958637647058825,43.70368376470589]}}]}