{"type":"FeatureCollection","features":[{"type":"Feature","properties":{"codesPostaux":["31420"],"population":90,"nom":"Bouzin","code":"31086"},"geometry":{"type":"Point","coordinates":[0.887109708737864,43.18823126213592]}}]}