{"type":"FeatureCollection","features":[{"type":"Feature","properties":{"codesPostaux":["31160"],"population":135,"nom":"Cabanac-Cazaux","code":"31095"},"geometry":{"type":"Point","coordinates":[0.7379628947368423,43.037482368421045]}}]}