{"type":"FeatureCollection","features":[{"type":"Feature","properties":{"codesPostaux":["31260"],"population":181,"nom":"Castagn\u00e8de","code":"31112"},"geometry":{"type":"Point","coordinates":[0.9769331481481478,43.05134833333333]}}]}