{"type":"FeatureCollection","features":[{"type":"Feature","properties":{"codesPostaux":["31350"],"population":228,"nom":"Charlas","code":"31138"},"geometry":{"type":"Point","coordinates":[0.6931955263157896,43.23468692982455]}}]}