{"type":"FeatureCollection","features":[{"type":"Feature","properties":{"codesPostaux":["31110"],"population":12,"nom":"Cir\u00e8s","code":"31146"},"geometry":{"type":"Point","coordinates":[0.5069719047619047,42.85332071428572]}}]}