{"type":"FeatureCollection","features":[{"type":"Feature","properties":{"codesPostaux":["31160"],"population":233,"nom":"Couret","code":"31155"},"geometry":{"type":"Point","coordinates":[0.8171287234042552,43.04993957446809]}}]}