{"type":"FeatureCollection","features":[{"type":"Feature","properties":{"codesPostaux":["31480"],"population":199,"nom":"Drudas","code":"31164"},"geometry":{"type":"Point","coordinates":[1.1007578102189777,43.76794445255474]}}]}