{"type":"FeatureCollection","features":[{"type":"Feature","properties":{"codesPostaux":["31280"],"population":2477,"nom":"Dr\u00e9mil-Lafage","code":"31163"},"geometry":{"type":"Point","coordinates":[1.6002056716417914,43.58920716417913]}}]}