{"type":"FeatureCollection","features":[{"type":"Feature","properties":{"codesPostaux":["31190"],"population":253,"nom":"Esperce","code":"31173"},"geometry":{"type":"Point","coordinates":[1.4064085217391311,43.30547582608696]}}]}