{"type":"FeatureCollection","features":[{"type":"Feature","properties":{"codesPostaux":["31440"],"population":131,"nom":"Eup","code":"31177"},"geometry":{"type":"Point","coordinates":[0.6828633333333332,42.92540148148147]}}]}