{"type":"FeatureCollection","features":[{"type":"Feature","properties":{"codesPostaux":["31470"],"population":11786,"nom":"Fonsorbes","code":"31187"},"geometry":{"type":"Point","coordinates":[1.2395129357798167,43.52665128440367]}}]}