{"type":"FeatureCollection","features":[{"type":"Feature","properties":{"codesPostaux":["31440"],"population":198,"nom":"Fronsac","code":"31199"},"geometry":{"type":"Point","coordinates":[0.6543154166666665,42.954661249999994]}}]}