{"type":"FeatureCollection","features":[{"type":"Feature","properties":{"codesPostaux":["31260"],"population":18,"nom":"Francazal","code":"31195"},"geometry":{"type":"Point","coordinates":[1.0042154098360654,43.01064409836065]}}]}