{"type":"FeatureCollection","features":[{"type":"Feature","properties":{"codesPostaux":["31230"],"population":61,"nom":"Frontignan-Sav\u00e8s","code":"31201"},"geometry":{"type":"Point","coordinates":[0.9126781818181819,43.399882954545454]}}]}