{"type":"FeatureCollection","features":[{"type":"Feature","properties":{"codesPostaux":["31550"],"population":1245,"nom":"Gaillac-Toulza","code":"31206"},"geometry":{"type":"Point","coordinates":[1.4589073205741632,43.260089569377975]}}]}