{"type":"FeatureCollection","features":[{"type":"Feature","properties":{"codesPostaux":["31380"],"population":1712,"nom":"Garidech","code":"31212"},"geometry":{"type":"Point","coordinates":[1.5555793650793648,43.71463841269842]}}]}