{"type":"FeatureCollection","features":[{"type":"Feature","properties":{"codesPostaux":["31430"],"population":666,"nom":"Gratens","code":"31229"},"geometry":{"type":"Point","coordinates":[1.1304543971631202,43.32289226950353]}}]}