{"type":"FeatureCollection","features":[{"type":"Feature","properties":{"codesPostaux":["31310"],"population":84,"nom":"Gouzens","code":"31226"},"geometry":{"type":"Point","coordinates":[1.1846434375000003,43.18034083333334]}}]}