{"type":"FeatureCollection","features":[{"type":"Feature","properties":{"codesPostaux":["31440"],"population":48,"nom":"Guran","code":"31235"},"geometry":{"type":"Point","coordinates":[0.6039046268656717,42.88578567164179]}}]}