{"type":"FeatureCollection","features":[{"type":"Feature","properties":{"codesPostaux":["31510"],"population":325,"nom":"Labroqu\u00e8re","code":"31255"},"geometry":{"type":"Point","coordinates":[0.5846763492063491,43.04143714285714]}}]}