{"type":"FeatureCollection","features":[{"type":"Feature","properties":{"codesPostaux":["31800"],"population":138,"nom":"Lalouret-Laffiteau","code":"31268"},"geometry":{"type":"Point","coordinates":[0.7045894999999999,43.18607816666667]}}]}