{"type":"FeatureCollection","features":[{"type":"Feature","properties":{"codesPostaux":["31580"],"population":245,"nom":"L\u00e9cussan","code":"31289"},"geometry":{"type":"Point","coordinates":[0.5023455434782608,43.15485032608695]}}]}