{"type":"FeatureCollection","features":[{"type":"Feature","properties":{"codesPostaux":["31220"],"population":593,"nom":"Lavelanet-de-Comminges","code":"31286"},"geometry":{"type":"Point","coordinates":[1.108348387096774,43.25818376344085]}}]}