{"type":"FeatureCollection","features":[{"type":"Feature","properties":{"codesPostaux":["31330"],"population":1355,"nom":"Launac","code":"31281"},"geometry":{"type":"Point","coordinates":[1.1647192352941171,43.752724470588205]}}]}