{"type":"FeatureCollection","features":[{"type":"Feature","properties":{"codesPostaux":["31350"],"population":79,"nom":"Lespugue","code":"31295"},"geometry":{"type":"Point","coordinates":[0.6649723853211013,43.231401009174334]}}]}