{"type":"FeatureCollection","features":[{"type":"Feature","properties":{"codesPostaux":["31220"],"population":67,"nom":"Lescuns","code":"31292"},"geometry":{"type":"Point","coordinates":[1.0034053333333333,43.24650216666665]}}]}