{"type":"FeatureCollection","features":[{"type":"Feature","properties":{"codesPostaux":["31210"],"population":407,"nom":"Martres-de-Rivi\u00e8re","code":"31323"},"geometry":{"type":"Point","coordinates":[0.647583157894737,43.07765526315789]}}]}