{"type":"FeatureCollection","features":[{"type":"Feature","properties":{"codesPostaux":["31260"],"population":118,"nom":"Marsoulas","code":"31321"},"geometry":{"type":"Point","coordinates":[0.995765,43.10835500000001]}}]}