{"type":"FeatureCollection","features":[{"type":"Feature","properties":{"codesPostaux":["31190"],"population":491,"nom":"Mauressac","code":"31330"},"geometry":{"type":"Point","coordinates":[1.4317935555555563,43.32179388888889]}}]}