{"type":"FeatureCollection","features":[{"type":"Feature","properties":{"codesPostaux":["31190"],"population":227,"nom":"Mauvaisin","code":"31332"},"geometry":{"type":"Point","coordinates":[1.5363948314606737,43.35628910112359]}}]}