{"type":"FeatureCollection","features":[{"type":"Feature","properties":{"codesPostaux":["31350"],"population":96,"nom":"Mondilhan","code":"31350"},"geometry":{"type":"Point","coordinates":[0.7095154782608699,43.291896434782615]}}]}