{"type":"FeatureCollection","features":[{"type":"Feature","properties":{"codesPostaux":["31160"],"population":263,"nom":"Montastruc-de-Salies","code":"31357"},"geometry":{"type":"Point","coordinates":[0.9050583076923078,43.048654538461555]}}]}