{"type":"FeatureCollection","features":[{"type":"Feature","properties":{"codesPostaux":["31410"],"population":175,"nom":"Montgazin","code":"31379"},"geometry":{"type":"Point","coordinates":[1.2986108403361352,43.30616352941176]}}]}