{"type":"FeatureCollection","features":[{"type":"Feature","properties":{"codesPostaux":["31540"],"population":475,"nom":"Mont\u00e9gut-Lauragais","code":"31371"},"geometry":{"type":"Point","coordinates":[1.9366990804597708,43.47781678160919]}}]}