{"type":"FeatureCollection","features":[{"type":"Feature","properties":{"codesPostaux":["31540"],"population":167,"nom":"Mourvilles-Hautes","code":"31393"},"geometry":{"type":"Point","coordinates":[1.8199492857142856,43.42496089285713]}}]}