{"type":"FeatureCollection","features":[{"type":"Feature","properties":{"codesPostaux":["31460"],"population":73,"nom":"Mourvilles-Basses","code":"31392"},"geometry":{"type":"Point","coordinates":[1.6971820000000002,43.48922849999999]}}]}