{"type":"FeatureCollection","features":[{"type":"Feature","properties":{"codesPostaux":["31600"],"population":24725,"nom":"Muret","code":"31395"},"geometry":{"type":"Point","coordinates":[1.309145087719299,43.446895052631575]}}]}