{"type":"FeatureCollection","features":[{"type":"Feature","properties":{"codesPostaux":["31420"],"population":80,"nom":"Peyrissas","code":"31414"},"geometry":{"type":"Point","coordinates":[0.911588761904762,43.2882537142857]}}]}