{"type":"FeatureCollection","features":[{"type":"Feature","properties":{"codesPostaux":["31110"],"population":75,"nom":"Poubeau","code":"31434"},"geometry":{"type":"Point","coordinates":[0.4905713559322034,42.82721576271186]}}]}