{"type":"FeatureCollection","features":[{"type":"Feature","properties":{"codesPostaux":["31190"],"population":443,"nom":"Puydaniel","code":"31442"},"geometry":{"type":"Point","coordinates":[1.4206249504950497,43.329867722772285]}}]}