{"type":"FeatureCollection","features":[{"type":"Feature","properties":{"codesPostaux":["31570"],"population":2001,"nom":"Sainte-Foy-d'Aigrefeuille","code":"31480"},"geometry":{"type":"Point","coordinates":[1.5987295918367344,43.54995265306124]}}]}