{"type":"FeatureCollection","features":[{"type":"Feature","properties":{"codesPostaux":["31180"],"population":2153,"nom":"Saint-Geni\u00e8s-Bellevue","code":"31484"},"geometry":{"type":"Point","coordinates":[1.4828508163265308,43.68335591836735]}}]}