{"type":"FeatureCollection","features":[{"type":"Feature","properties":{"codesPostaux":["31140"],"population":1865,"nom":"Saint-Loup-Cammas","code":"31497"},"geometry":{"type":"Point","coordinates":[1.4763354444444445,43.69676766666667]}}]}