{"type":"FeatureCollection","features":[{"type":"Feature","properties":{"codesPostaux":["31470"],"population":555,"nom":"Saint-Thomas","code":"31518"},"geometry":{"type":"Point","coordinates":[1.0800402,43.513744899999985]}}]}