{"type":"FeatureCollection","features":[{"type":"Feature","properties":{"codesPostaux":["31350"],"population":126,"nom":"Saint-P\u00e9-Delbosc","code":"31510"},"geometry":{"type":"Point","coordinates":[0.6981295081967214,43.26710819672131]}}]}