{"type":"FeatureCollection","features":[{"type":"Feature","properties":{"codesPostaux":["31370"],"population":200,"nom":"Sav\u00e8res","code":"31538"},"geometry":{"type":"Point","coordinates":[1.10291796460177,43.37538132743364]}}]}