{"type":"FeatureCollection","features":[{"type":"Feature","properties":{"codesPostaux":["31350"],"population":97,"nom":"Sarremezan","code":"31532"},"geometry":{"type":"Point","coordinates":[0.6633238888888893,43.21303066666666]}}]}