{"type":"FeatureCollection","features":[{"type":"Feature","properties":{"codesPostaux":["31510"],"population":201,"nom":"Seilhan","code":"31542"},"geometry":{"type":"Point","coordinates":[0.5777457534246575,43.05143958904109]}}]}