{"type":"FeatureCollection","features":[{"type":"Feature","properties":{"codesPostaux":["31110"],"population":6,"nom":"Tr\u00e9bons-de-Luchon","code":"31559"},"geometry":{"type":"Point","coordinates":[0.5663660869565217,42.80301391304347]}}]}