{"type":"FeatureCollection","features":[{"type":"Feature","properties":{"codesPostaux":["31290"],"population":527,"nom":"Vall\u00e8gue","code":"31566"},"geometry":{"type":"Point","coordinates":[1.756377872340425,43.42681606382981]}}]}