{"type":"FeatureCollection","features":[{"type":"Feature","properties":{"codesPostaux":["31330"],"population":1638,"nom":"Larra","code":"31592"},"geometry":{"type":"Point","coordinates":[1.2272613375796182,43.73066656050956]}}]}