{"type":"FeatureCollection","features":[{"type":"Feature","properties":{"codesPostaux":["32430"],"population":203,"nom":"Ardizas","code":"32007"},"geometry":{"type":"Point","coordinates":[0.9982584615384612,43.72539934065934]}}]}