{"type":"FeatureCollection","features":[{"type":"Feature","properties":{"codesPostaux":["32120"],"population":101,"nom":"Augnax","code":"32014"},"geometry":{"type":"Point","coordinates":[0.7770298412698415,43.72652317460317]}}]}