{"type":"FeatureCollection","features":[{"type":"Feature","properties":{"codesPostaux":["32170"],"population":111,"nom":"Barcugnan","code":"32028"},"geometry":{"type":"Point","coordinates":[0.397327142857143,43.37540464285711]}}]}