{"type":"FeatureCollection","features":[{"type":"Feature","properties":{"codesPostaux":["32290"],"population":149,"nom":"Av\u00e9ron-Bergelle","code":"32022"},"geometry":{"type":"Point","coordinates":[0.06610154285714284,43.76157154285713]}}]}