{"type":"FeatureCollection","features":[{"type":"Feature","properties":{"codesPostaux":["32110"],"population":96,"nom":"B\u00e9tous","code":"32049"},"geometry":{"type":"Point","coordinates":[0.022101551724137938,43.71901241379311]}}]}