{"type":"FeatureCollection","features":[{"type":"Feature","properties":{"codesPostaux":["32410"],"population":127,"nom":"Bonas","code":"32059"},"geometry":{"type":"Point","coordinates":[0.4026187037037036,43.77978277777779]}}]}