{"type":"FeatureCollection","features":[{"type":"Feature","properties":{"codesPostaux":["32290"],"population":193,"nom":"Bouzon-Gellenave","code":"32063"},"geometry":{"type":"Point","coordinates":[0.022792959641255613,43.688797623318386]}}]}