{"type":"FeatureCollection","features":[{"type":"Feature","properties":{"codesPostaux":["32500"],"population":226,"nom":"Castelnau-d'Arbieu","code":"32078"},"geometry":{"type":"Point","coordinates":[0.6814044755244751,43.88445867132865]}}]}