{"type":"FeatureCollection","features":[{"type":"Feature","properties":{"codesPostaux":["32290"],"population":128,"nom":"Castelnavet","code":"32081"},"geometry":{"type":"Point","coordinates":[0.13519143835616443,43.67164506849316]}}]}