{"type":"FeatureCollection","features":[{"type":"Feature","properties":{"codesPostaux":["32490"],"population":298,"nom":"Castillon-Sav\u00e8s","code":"32090"},"geometry":{"type":"Point","coordinates":[0.9875161240310073,43.563310310077526]}}]}