{"type":"FeatureCollection","features":[{"type":"Feature","properties":{"codesPostaux":["32100"],"population":588,"nom":"Caussens","code":"32095"},"geometry":{"type":"Point","coordinates":[0.4411660909090907,43.94691327272725]}}]}