{"type":"FeatureCollection","features":[{"type":"Feature","properties":{"codesPostaux":["32190"],"population":119,"nom":"Cazaux-d'Angl\u00e8s","code":"32097"},"geometry":{"type":"Point","coordinates":[0.2597042857142856,43.65767186813189]}}]}