{"type":"FeatureCollection","features":[{"type":"Feature","properties":{"codesPostaux":["32170"],"population":138,"nom":"Duffort","code":"32116"},"geometry":{"type":"Point","coordinates":[0.42571419642857133,43.340870267857156]}}]}