{"type":"FeatureCollection","features":[{"type":"Feature","properties":{"codesPostaux":["32800"],"population":3877,"nom":"Eauze","code":"32119"},"geometry":{"type":"Point","coordinates":[0.10211388308977035,43.86099517745304]}}]}