{"type":"FeatureCollection","features":[{"type":"Feature","properties":{"codesPostaux":["32380"],"population":134,"nom":"Estramiac","code":"32129"},"geometry":{"type":"Point","coordinates":[0.8444161538461536,43.83415892307695]}}]}