{"type":"FeatureCollection","features":[{"type":"Feature","properties":{"codesPostaux":["32300"],"population":208,"nom":"Estipouy","code":"32128"},"geometry":{"type":"Point","coordinates":[0.39128237762237744,43.548775734265746]}}]}