{"type":"FeatureCollection","features":[{"type":"Feature","properties":{"codesPostaux":["32220"],"population":145,"nom":"Garravet","code":"32138"},"geometry":{"type":"Point","coordinates":[0.9022756410256407,43.418891965811966]}}]}