{"type":"FeatureCollection","features":[{"type":"Feature","properties":{"codesPostaux":["32450"],"population":225,"nom":"Faget-Abbatial","code":"32130"},"geometry":{"type":"Point","coordinates":[0.6918626984126987,43.502138730158755]}}]}