{"type":"FeatureCollection","features":[{"type":"Feature","properties":{"codesPostaux":["32230"],"population":83,"nom":"Gazax-et-Baccarisse","code":"32144"},"geometry":{"type":"Point","coordinates":[0.1994608196721311,43.60015909836065]}}]}