{"type":"FeatureCollection","features":[{"type":"Feature","properties":{"codesPostaux":["32460"],"population":1193,"nom":"Le Houga","code":"32155"},"geometry":{"type":"Point","coordinates":[-0.18822962025316453,43.769863924050654]}}]}