{"type":"FeatureCollection","features":[{"type":"Feature","properties":{"codesPostaux":["32730"],"population":336,"nom":"Haget","code":"32152"},"geometry":{"type":"Point","coordinates":[0.16043487654320976,43.41911512345682]}}]}