{"type":"FeatureCollection","features":[{"type":"Feature","properties":{"codesPostaux":["32230"],"population":265,"nom":"Ladev\u00e8ze-Ville","code":"32175"},"geometry":{"type":"Point","coordinates":[0.0626539655172414,43.539986120689655]}}]}