{"type":"FeatureCollection","features":[{"type":"Feature","properties":{"codesPostaux":["32230"],"population":224,"nom":"Ladev\u00e8ze-Rivi\u00e8re","code":"32174"},"geometry":{"type":"Point","coordinates":[0.09155695431472077,43.55059832487308]}}]}