{"type":"FeatureCollection","features":[{"type":"Feature","properties":{"codesPostaux":["32130"],"population":152,"nom":"Labastide-Sav\u00e8s","code":"32171"},"geometry":{"type":"Point","coordinates":[0.9778276470588234,43.519956617647075]}}]}