{"type":"FeatureCollection","features":[{"type":"Feature","properties":{"codesPostaux":["32100"],"population":235,"nom":"Larroque-sur-l'Osse","code":"32197"},"geometry":{"type":"Point","coordinates":[0.2870493548387097,43.97603607526881]}}]}