{"type":"FeatureCollection","features":[{"type":"Feature","properties":{"codesPostaux":["32360"],"population":399,"nom":"Lavardens","code":"32204"},"geometry":{"type":"Point","coordinates":[0.5260541255605382,43.7681228251121]}}]}