{"type":"FeatureCollection","features":[{"type":"Feature","properties":{"codesPostaux":["32230"],"population":111,"nom":"Lavera\u00ebt","code":"32205"},"geometry":{"type":"Point","coordinates":[0.21202983050847463,43.52523796610167]}}]}