{"type":"FeatureCollection","features":[{"type":"Feature","properties":{"codesPostaux":["32120"],"population":45,"nom":"Maravat","code":"32232"},"geometry":{"type":"Point","coordinates":[0.7689438095238094,43.759409047619044]}}]}