{"type":"FeatureCollection","features":[{"type":"Feature","properties":{"codesPostaux":["32700"],"population":176,"nom":"Mas-d'Auvignon","code":"32241"},"geometry":{"type":"Point","coordinates":[0.50776359375,43.89003734375001]}}]}