{"type":"FeatureCollection","features":[{"type":"Feature","properties":{"codesPostaux":["32230"],"population":65,"nom":"Mascaras","code":"32240"},"geometry":{"type":"Point","coordinates":[0.22409109756097562,43.5552112195122]}}]}