{"type":"FeatureCollection","features":[{"type":"Feature","properties":{"codesPostaux":["32420"],"population":87,"nom":"Meilhan","code":"32250"},"geometry":{"type":"Point","coordinates":[0.6788089285714286,43.42061803571428]}}]}