{"type":"FeatureCollection","features":[{"type":"Feature","properties":{"codesPostaux":["32390"],"population":725,"nom":"Montestruc-sur-Gers","code":"32286"},"geometry":{"type":"Point","coordinates":[0.6394956746031747,43.79829333333333]}}]}