{"type":"FeatureCollection","features":[{"type":"Feature","properties":{"codesPostaux":["32420"],"population":76,"nom":"Monties","code":"32287"},"geometry":{"type":"Point","coordinates":[0.6840308333333335,43.39309680555554]}}]}