{"type":"FeatureCollection","features":[{"type":"Feature","properties":{"codesPostaux":["32320"],"population":157,"nom":"Peyrusse-Grande","code":"32315"},"geometry":{"type":"Point","coordinates":[0.22179000000000018,43.63200541237113]}}]}