{"type":"FeatureCollection","features":[{"type":"Feature","properties":{"codesPostaux":["32500"],"population":97,"nom":"Pis","code":"32318"},"geometry":{"type":"Point","coordinates":[0.7104449315068492,43.78677506849315]}}]}