{"type":"FeatureCollection","features":[{"type":"Feature","properties":{"codesPostaux":["32160"],"population":1499,"nom":"Plaisance","code":"32319"},"geometry":{"type":"Point","coordinates":[0.04770506024096385,43.59756054216869]}}]}