{"type":"FeatureCollection","features":[{"type":"Feature","properties":{"codesPostaux":["32400"],"population":1710,"nom":"Riscle","code":"32344"},"geometry":{"type":"Point","coordinates":[-0.08543325757575752,43.64316314393939]}}]}