{"type":"FeatureCollection","features":[{"type":"Feature","properties":{"codesPostaux":["32300"],"population":263,"nom":"Saint-Michel","code":"32397"},"geometry":{"type":"Point","coordinates":[0.40236592105263186,43.431278684210525]}}]}