{"type":"FeatureCollection","features":[{"type":"Feature","properties":{"codesPostaux":["32450"],"population":88,"nom":"Saint-Martin-Gimois","code":"32392"},"geometry":{"type":"Point","coordinates":[0.8099731818181817,43.522037840909086]}}]}