{"type":"FeatureCollection","features":[{"type":"Feature","properties":{"codesPostaux":["32220"],"population":161,"nom":"Saint-Soulan","code":"32407"},"geometry":{"type":"Point","coordinates":[0.8599411999999996,43.510602899999974]}}]}