{"type":"FeatureCollection","features":[{"type":"Feature","properties":{"codesPostaux":["32120"],"population":395,"nom":"Sarrant","code":"32416"},"geometry":{"type":"Point","coordinates":[0.9223169565217394,43.76959729468597]}}]}