{"type":"FeatureCollection","features":[{"type":"Feature","properties":{"codesPostaux":["32700"],"population":388,"nom":"Terraube","code":"32442"},"geometry":{"type":"Point","coordinates":[0.5430270000000004,43.90685985714286]}}]}