{"type":"FeatureCollection","features":[{"type":"Feature","properties":{"codesPostaux":["32240"],"population":221,"nom":"Toujouse","code":"32449"},"geometry":{"type":"Point","coordinates":[-0.17711952095808384,43.82635389221558]}}]}