{"type":"FeatureCollection","features":[{"type":"Feature","properties":{"codesPostaux":["32310"],"population":1140,"nom":"Valence-sur-Ba\u00efse","code":"32459"},"geometry":{"type":"Point","coordinates":[0.364508057742782,43.87062847769027]}}]}