{"type":"FeatureCollection","features":[{"type":"Feature","properties":{"codesPostaux":["32110"],"population":249,"nom":"Urgosse","code":"32458"},"geometry":{"type":"Point","coordinates":[-0.01784179487179487,43.740109487179474]}}]}