{"type":"FeatureCollection","features":[{"type":"Feature","properties":{"codesPostaux":["32390"],"population":121,"nom":"Tourrenquets","code":"32453"},"geometry":{"type":"Point","coordinates":[0.7009464999999996,43.74896559999999]}}]}