{"type":"FeatureCollection","features":[{"type":"Feature","properties":{"codesPostaux":["32720"],"population":293,"nom":"Vergoignan","code":"32460"},"geometry":{"type":"Point","coordinates":[-0.19089061224489798,43.72359622448976]}}]}