{"type":"FeatureCollection","features":[{"type":"Feature","properties":{"codesPostaux":["32300"],"population":99,"nom":"Viozan","code":"32466"},"geometry":{"type":"Point","coordinates":[0.4631366326530611,43.3944886734694]}}]}