{"type":"FeatureCollection","features":[{"type":"Feature","properties":{"codesPostaux":["33510"],"population":11575,"nom":"Andernos-les-Bains","code":"33005"},"geometry":{"type":"Point","coordinates":[-1.0977759482758627,44.75115396551724]}}]}