{"type":"FeatureCollection","features":[{"type":"Feature","properties":{"codesPostaux":["33460"],"population":450,"nom":"Arcins","code":"33010"},"geometry":{"type":"Point","coordinates":[-0.7103729807692308,45.07565432692308]}}]}