{"type":"FeatureCollection","features":[{"type":"Feature","properties":{"codesPostaux":["33570"],"population":1085,"nom":"Les Artigues-de-Lussac","code":"33014"},"geometry":{"type":"Point","coordinates":[-0.1322726506024097,44.97066108433733]}}]}