{"type":"FeatureCollection","features":[{"type":"Feature","properties":{"codesPostaux":["33430"],"population":267,"nom":"Aubiac","code":"33017"},"geometry":{"type":"Point","coordinates":[-0.2475095652173914,44.471003260869566]}}]}