{"type":"FeatureCollection","features":[{"type":"Feature","properties":{"codesPostaux":["33980"],"population":6899,"nom":"Audenge","code":"33019"},"geometry":{"type":"Point","coordinates":[-1.003109202453988,44.69786975460122]}}]}