{"type":"FeatureCollection","features":[{"type":"Feature","properties":{"codesPostaux":["33720"],"population":2089,"nom":"Barsac","code":"33030"},"geometry":{"type":"Point","coordinates":[-0.32365540000000004,44.5987131]}}]}