{"type":"FeatureCollection","features":[{"type":"Feature","properties":{"codesPostaux":["33270"],"population":3228,"nom":"Bouliac","code":"33065"},"geometry":{"type":"Point","coordinates":[-0.4981823456790123,44.81885716049383]}}]}