{"type":"FeatureCollection","features":[{"type":"Feature","properties":{"codesPostaux":["33710"],"population":2187,"nom":"Bourg","code":"33067"},"geometry":{"type":"Point","coordinates":[-0.5504260919540229,45.04596965517242]}}]}