{"type":"FeatureCollection","features":[{"type":"Feature","properties":{"codesPostaux":["33360"],"population":2779,"nom":"Camblanes-et-Meynac","code":"33085"},"geometry":{"type":"Point","coordinates":[-0.47736813559322033,44.765764406779645]}}]}