{"type":"FeatureCollection","features":[{"type":"Feature","properties":{"codesPostaux":["33720"],"population":2085,"nom":"C\u00e9rons","code":"33120"},"geometry":{"type":"Point","coordinates":[-0.34046761904761896,44.62761476190475]}}]}