{"type":"FeatureCollection","features":[{"type":"Feature","properties":{"codesPostaux":["33340"],"population":260,"nom":"Couqu\u00e8ques","code":"33134"},"geometry":{"type":"Point","coordinates":[-0.8434254545454544,45.34392649350649]}}]}