{"type":"FeatureCollection","features":[{"type":"Feature","properties":{"codesPostaux":["33230"],"population":8276,"nom":"Coutras","code":"33138"},"geometry":{"type":"Point","coordinates":[-0.10063727611940299,45.03716272388058]}}]}