{"type":"FeatureCollection","features":[{"type":"Feature","properties":{"codesPostaux":["33540"],"population":151,"nom":"Daub\u00e8ze","code":"33149"},"geometry":{"type":"Point","coordinates":[-0.13559418367346937,44.70843918367348]}}]}