{"type":"FeatureCollection","features":[{"type":"Feature","properties":{"codesPostaux":["33580"],"population":323,"nom":"Dieulivol","code":"33150"},"geometry":{"type":"Point","coordinates":[0.10924149350649347,44.675826948051935]}}]}