{"type":"FeatureCollection","features":[{"type":"Feature","properties":{"codesPostaux":["33760"],"population":332,"nom":"Escoussans","code":"33156"},"geometry":{"type":"Point","coordinates":[-0.2754671428571429,44.67395]}}]}