{"type":"FeatureCollection","features":[{"type":"Feature","properties":{"codesPostaux":["33270"],"population":16531,"nom":"Floirac","code":"33167"},"geometry":{"type":"Point","coordinates":[-0.5149105454545456,44.833719636363654]}}]}