{"type":"FeatureCollection","features":[{"type":"Feature","properties":{"codesPostaux":["33320"],"population":21762,"nom":"Eysines","code":"33162"},"geometry":{"type":"Point","coordinates":[-0.6458109195402296,44.880915747126444]}}]}