{"type":"FeatureCollection","features":[{"type":"Feature","properties":{"codesPostaux":["33133"],"population":2998,"nom":"Galgon","code":"33179"},"geometry":{"type":"Point","coordinates":[-0.27451827906976733,44.993379441860455]}}]}