{"type":"FeatureCollection","features":[{"type":"Feature","properties":{"codesPostaux":["33420"],"population":1886,"nom":"G\u00e9nissac","code":"33185"},"geometry":{"type":"Point","coordinates":[-0.2469609523809524,44.85774603174603]}}]}