{"type":"FeatureCollection","features":[{"type":"Feature","properties":{"codesPostaux":["33470"],"population":20294,"nom":"Gujan-Mestras","code":"33199"},"geometry":{"type":"Point","coordinates":[-1.0770269191919184,44.64004247474747]}}]}