{"type":"FeatureCollection","features":[{"type":"Feature","properties":{"codesPostaux":["33720"],"population":1354,"nom":"Illats","code":"33205"},"geometry":{"type":"Point","coordinates":[-0.3674601351351351,44.61035256756757]}}]}