{"type":"FeatureCollection","features":[{"type":"Feature","properties":{"codesPostaux":["33420"],"population":286,"nom":"Jugazan","code":"33209"},"geometry":{"type":"Point","coordinates":[-0.1521914814814815,44.78103283950616]}}]}