{"type":"FeatureCollection","features":[{"type":"Feature","properties":{"codesPostaux":["33620"],"population":2552,"nom":"Laruscade","code":"33233"},"geometry":{"type":"Point","coordinates":[-0.34433042016806725,45.11618907563025]}}]}