{"type":"FeatureCollection","features":[{"type":"Feature","properties":{"codesPostaux":["33620"],"population":491,"nom":"Lapouyade","code":"33230"},"geometry":{"type":"Point","coordinates":[-0.29645900355871885,45.11565213523132]}}]}