{"type":"FeatureCollection","features":[{"type":"Feature","properties":{"codesPostaux":["33690"],"population":253,"nom":"Lavazan","code":"33235"},"geometry":{"type":"Point","coordinates":[-0.11641144000000003,44.389225279999984]}}]}