{"type":"FeatureCollection","features":[{"type":"Feature","properties":{"codesPostaux":["33340"],"population":5588,"nom":"Lesparre-M\u00e9doc","code":"33240"},"geometry":{"type":"Point","coordinates":[-0.9275503333333334,45.29243099999999]}}]}