{"type":"FeatureCollection","features":[{"type":"Feature","properties":{"codesPostaux":["33370"],"population":706,"nom":"Loupes","code":"33252"},"geometry":{"type":"Point","coordinates":[-0.39388775510204105,44.80949561224487]}}]}