{"type":"FeatureCollection","features":[{"type":"Feature","properties":{"codesPostaux":["33420"],"population":429,"nom":"Lugaignac","code":"33257"},"geometry":{"type":"Point","coordinates":[-0.1952898461538462,44.81471169230768]}}]}