{"type":"FeatureCollection","features":[{"type":"Feature","properties":{"codesPostaux":["33570"],"population":1314,"nom":"Lussac","code":"33261"},"geometry":{"type":"Point","coordinates":[-0.09311066390041496,44.96960639004148]}}]}