{"type":"FeatureCollection","features":[{"type":"Feature","properties":{"codesPostaux":["33860"],"population":1201,"nom":"Marcillac","code":"33267"},"geometry":{"type":"Point","coordinates":[-0.50330398467433,45.27640038314181]}}]}