{"type":"FeatureCollection","features":[{"type":"Feature","properties":{"codesPostaux":["33700"],"population":68386,"nom":"M\u00e9rignac","code":"33281"},"geometry":{"type":"Point","coordinates":[-0.6576227814569534,44.83072211920527]}}]}