{"type":"FeatureCollection","features":[{"type":"Feature","properties":{"codesPostaux":["33410"],"population":378,"nom":"Mourens","code":"33299"},"geometry":{"type":"Point","coordinates":[-0.214380325203252,44.64430829268293]}}]}