{"type":"FeatureCollection","features":[{"type":"Feature","properties":{"codesPostaux":["33600"],"population":60763,"nom":"Pessac","code":"33318"},"geometry":{"type":"Point","coordinates":[-0.6512392968749999,44.802078984374965]}}]}