{"type":"FeatureCollection","features":[{"type":"Feature","properties":{"codesPostaux":["33240"],"population":1091,"nom":"P\u00e9rissac","code":"33317"},"geometry":{"type":"Point","coordinates":[-0.31318183246073306,45.025694397905745]}}]}