{"type":"FeatureCollection","features":[{"type":"Feature","properties":{"codesPostaux":["33500"],"population":691,"nom":"Pomerol","code":"33328"},"geometry":{"type":"Point","coordinates":[-0.19935017543859657,44.93405333333331]}}]}