{"type":"FeatureCollection","features":[{"type":"Feature","properties":{"codesPostaux":["33390"],"population":869,"nom":"Plassac","code":"33325"},"geometry":{"type":"Point","coordinates":[-0.6502007526881725,45.09459112903224]}}]}