{"type":"FeatureCollection","features":[{"type":"Feature","properties":{"codesPostaux":["33570"],"population":788,"nom":"Petit-Palais-et-Cornemps","code":"33320"},"geometry":{"type":"Point","coordinates":[-0.057340440251572325,44.98227081761007]}}]}