{"type":"FeatureCollection","features":[{"type":"Feature","properties":{"codesPostaux":["33710"],"population":1394,"nom":"Prignac-et-Marcamps","code":"33339"},"geometry":{"type":"Point","coordinates":[-0.48933510204081654,45.03476173469387]}}]}