{"type":"FeatureCollection","features":[{"type":"Feature","properties":{"codesPostaux":["33126"],"population":374,"nom":"La Rivi\u00e8re","code":"33356"},"geometry":{"type":"Point","coordinates":[-0.31466097560975614,44.93972195121952]}}]}