{"type":"FeatureCollection","features":[{"type":"Feature","properties":{"codesPostaux":["33760"],"population":454,"nom":"Romagne","code":"33358"},"geometry":{"type":"Point","coordinates":[-0.20445818181818182,44.767246623376636]}}]}