{"type":"FeatureCollection","features":[{"type":"Feature","properties":{"codesPostaux":["33126"],"population":222,"nom":"Saint-Aignan","code":"33365"},"geometry":{"type":"Point","coordinates":[-0.29681942857142857,44.946948000000006]}}]}