{"type":"FeatureCollection","features":[{"type":"Feature","properties":{"codesPostaux":["33240"],"population":10495,"nom":"Saint-Andr\u00e9-de-Cubzac","code":"33366"},"geometry":{"type":"Point","coordinates":[-0.42334150943396254,44.993426666666664]}}]}