{"type":"FeatureCollection","features":[{"type":"Feature","properties":{"codesPostaux":["33160"],"population":6539,"nom":"Saint-Aubin-de-M\u00e9doc","code":"33376"},"geometry":{"type":"Point","coordinates":[-0.7420565384615384,44.91837576923077]}}]}