{"type":"FeatureCollection","features":[{"type":"Feature","properties":{"codesPostaux":["33660"],"population":568,"nom":"Saint-Antoine-sur-l'Isle","code":"33373"},"geometry":{"type":"Point","coordinates":[0.037671724137931024,45.03907870689654]}}]}