{"type":"FeatureCollection","features":[{"type":"Feature","properties":{"codesPostaux":["33220"],"population":79,"nom":"Saint-Avit-de-Soul\u00e8ge","code":"33377"},"geometry":{"type":"Point","coordinates":[0.11821548780487806,44.811934268292674]}}]}