{"type":"FeatureCollection","features":[{"type":"Feature","properties":{"codesPostaux":["33880"],"population":2744,"nom":"Saint-Caprais-de-Bordeaux","code":"33381"},"geometry":{"type":"Point","coordinates":[-0.4305185365853659,44.75180121951219]}}]}