{"type":"FeatureCollection","features":[{"type":"Feature","properties":{"codesPostaux":["33180"],"population":1650,"nom":"Saint-Est\u00e8phe","code":"33395"},"geometry":{"type":"Point","coordinates":[-0.7743257647058817,45.258426823529376]}}]}