{"type":"FeatureCollection","features":[{"type":"Feature","properties":{"codesPostaux":["33760"],"population":95,"nom":"Saint-Genis-du-Bois","code":"33409"},"geometry":{"type":"Point","coordinates":[-0.17955067796610166,44.70171661016947]}}]}