{"type":"FeatureCollection","features":[{"type":"Feature","properties":{"codesPostaux":["33490"],"population":155,"nom":"Saint-Germain-de-Grave","code":"33411"},"geometry":{"type":"Point","coordinates":[-0.21540831999999996,44.62123016]}}]}