{"type":"FeatureCollection","features":[{"type":"Feature","properties":{"codesPostaux":["33112"],"population":4433,"nom":"Saint-Laurent-M\u00e9doc","code":"33424"},"geometry":{"type":"Point","coordinates":[-0.8196772151898739,45.12144025316455]}}]}