{"type":"FeatureCollection","features":[{"type":"Feature","properties":{"codesPostaux":["33490"],"population":2070,"nom":"Saint-Macaire","code":"33435"},"geometry":{"type":"Point","coordinates":[-0.230584,44.563888399999996]}}]}