{"type":"FeatureCollection","features":[{"type":"Feature","properties":{"codesPostaux":["33620"],"population":1590,"nom":"Saint-Mariens","code":"33439"},"geometry":{"type":"Point","coordinates":[-0.4041869465648856,45.12016129770994]}}]}