{"type":"FeatureCollection","features":[{"type":"Feature","properties":{"codesPostaux":["33490"],"population":1760,"nom":"Saint-Maixant","code":"33438"},"geometry":{"type":"Point","coordinates":[-0.23754456310679617,44.58695029126215]}}]}