{"type":"FeatureCollection","features":[{"type":"Feature","properties":{"codesPostaux":["33230"],"population":2392,"nom":"Saint-M\u00e9dard-de-Guizi\u00e8res","code":"33447"},"geometry":{"type":"Point","coordinates":[-0.07741742424242423,45.00846613636364]}}]}