{"type":"FeatureCollection","features":[{"type":"Feature","properties":{"codesPostaux":["33910"],"population":840,"nom":"Saint-Martin-du-Bois","code":"33445"},"geometry":{"type":"Point","coordinates":[-0.26311280000000004,45.01669188571427]}}]}