{"type":"FeatureCollection","features":[{"type":"Feature","properties":{"codesPostaux":["33650"],"population":1577,"nom":"Saint-Morillon","code":"33454"},"geometry":{"type":"Point","coordinates":[-0.5249125352112675,44.636411478873256]}}]}