{"type":"FeatureCollection","features":[{"type":"Feature","properties":{"codesPostaux":["33820"],"population":512,"nom":"Saint-Palais","code":"33456"},"geometry":{"type":"Point","coordinates":[-0.5962237704918033,45.30913795081967]}}]}