{"type":"FeatureCollection","features":[{"type":"Feature","properties":{"codesPostaux":["33350"],"population":391,"nom":"Saint-Philippe-d'Aiguille","code":"33461"},"geometry":{"type":"Point","coordinates":[-0.03985380530973453,44.91584681415928]}}]}