{"type":"FeatureCollection","features":[{"type":"Feature","properties":{"codesPostaux":["33180"],"population":711,"nom":"Saint-Seurin-de-Cadourne","code":"33476"},"geometry":{"type":"Point","coordinates":[-0.794589537037037,45.293084259259274]}}]}