{"type":"FeatureCollection","features":[{"type":"Feature","properties":{"codesPostaux":["33450"],"population":4552,"nom":"Saint-Sulpice-et-Cameyrac","code":"33483"},"geometry":{"type":"Point","coordinates":[-0.3832076642335766,44.90246277372265]}}]}