{"type":"FeatureCollection","features":[{"type":"Feature","properties":{"codesPostaux":["33124"],"population":620,"nom":"Savignac","code":"33508"},"geometry":{"type":"Point","coordinates":[-0.10204007812500002,44.513468984374995]}}]}