{"type":"FeatureCollection","features":[{"type":"Feature","properties":{"codesPostaux":["33430"],"population":314,"nom":"Sauviac","code":"33507"},"geometry":{"type":"Point","coordinates":[-0.18306428571428562,44.399790499999995]}}]}