{"type":"FeatureCollection","features":[{"type":"Feature","properties":{"codesPostaux":["33780"],"population":2523,"nom":"Soulac-sur-Mer","code":"33514"},"geometry":{"type":"Point","coordinates":[-1.0980629496402876,45.49744079136691]}}]}