{"type":"FeatureCollection","features":[{"type":"Feature","properties":{"codesPostaux":["33760"],"population":1933,"nom":"Targon","code":"33523"},"geometry":{"type":"Point","coordinates":[-0.26548356249999994,44.73472774999998]}}]}