{"type":"FeatureCollection","features":[{"type":"Feature","properties":{"codesPostaux":["33680"],"population":535,"nom":"Le Temple","code":"33528"},"geometry":{"type":"Point","coordinates":[-0.961090681818182,44.863674545454536]}}]}