{"type":"FeatureCollection","features":[{"type":"Feature","properties":{"codesPostaux":["33125"],"population":257,"nom":"Le Tuzan","code":"33536"},"geometry":{"type":"Point","coordinates":[-0.5903866666666666,44.452624444444446]}}]}