{"type":"FeatureCollection","features":[{"type":"Feature","properties":{"codesPostaux":["33550"],"population":773,"nom":"Le Tourne","code":"33534"},"geometry":{"type":"Point","coordinates":[-0.3943545000000002,44.72030499999999]}}]}