{"type":"FeatureCollection","features":[{"type":"Feature","properties":{"codesPostaux":["33590"],"population":937,"nom":"Vensac","code":"33541"},"geometry":{"type":"Point","coordinates":[-1.0702604040404036,45.39917171717172]}}]}