{"type":"FeatureCollection","features":[{"type":"Feature","properties":{"codesPostaux":["33370"],"population":2865,"nom":"Yvrac","code":"33554"},"geometry":{"type":"Point","coordinates":[-0.4692864102564104,44.884181923076916]}}]}