{"type":"FeatureCollection","features":[{"type":"Feature","properties":{"codesPostaux":["34600"],"population":6241,"nom":"B\u00e9darieux","code":"34028"},"geometry":{"type":"Point","coordinates":[3.1508662295081966,43.60681147540984]}}]}