{"type":"FeatureCollection","features":[{"type":"Feature","properties":{"codesPostaux":["34550"],"population":4703,"nom":"Bessan","code":"34031"},"geometry":{"type":"Point","coordinates":[3.4170898591549306,43.35909971830988]}}]}