{"type":"FeatureCollection","features":[{"type":"Feature","properties":{"codesPostaux":["34360"],"population":200,"nom":"Berlou","code":"34030"},"geometry":{"type":"Point","coordinates":[2.945642810457517,43.49861751633986]}}]}