{"type":"FeatureCollection","features":[{"type":"Feature","properties":{"codesPostaux":["34800"],"population":483,"nom":"Cabri\u00e8res","code":"34045"},"geometry":{"type":"Point","coordinates":[3.3522139644970417,43.577780769230756]}}]}