{"type":"FeatureCollection","features":[{"type":"Feature","properties":{"codesPostaux":["34650"],"population":50,"nom":"Brenas","code":"34040"},"geometry":{"type":"Point","coordinates":[3.2548988095238105,43.641616746031715]}}]}