{"type":"FeatureCollection","features":[{"type":"Feature","properties":{"codesPostaux":["34800"],"population":3484,"nom":"Canet","code":"34051"},"geometry":{"type":"Point","coordinates":[3.48238048192771,43.59769409638555]}}]}