{"type":"FeatureCollection","features":[{"type":"Feature","properties":{"codesPostaux":["34520"],"population":441,"nom":"Le Caylar","code":"34064"},"geometry":{"type":"Point","coordinates":[3.310423867924529,43.86840377358492]}}]}