{"type":"FeatureCollection","features":[{"type":"Feature","properties":{"codesPostaux":["34120"],"population":394,"nom":"Cazouls-d'H\u00e9rault","code":"34068"},"geometry":{"type":"Point","coordinates":[3.455841718750001,43.5025078125]}}]}