{"type":"FeatureCollection","features":[{"type":"Feature","properties":{"codesPostaux":["34420"],"population":2260,"nom":"Cers","code":"34073"},"geometry":{"type":"Point","coordinates":[3.3167879746835456,43.327612531645585]}}]}