{"type":"FeatureCollection","features":[{"type":"Feature","properties":{"codesPostaux":["34220"],"population":606,"nom":"Courniou","code":"34086"},"geometry":{"type":"Point","coordinates":[2.697314409937888,43.486755341614895]}}]}