{"type":"FeatureCollection","features":[{"type":"Feature","properties":{"codesPostaux":["34290"],"population":1012,"nom":"Espondeilhan","code":"34094"},"geometry":{"type":"Point","coordinates":[3.2589209259259255,43.43707222222221]}}]}