{"type":"FeatureCollection","features":[{"type":"Feature","properties":{"codesPostaux":["34270"],"population":329,"nom":"Fontan\u00e8s","code":"34102"},"geometry":{"type":"Point","coordinates":[3.9165138571428577,43.792981571428555]}}]}