{"type":"FeatureCollection","features":[{"type":"Feature","properties":{"codesPostaux":["34190"],"population":118,"nom":"Gorni\u00e8s","code":"34115"},"geometry":{"type":"Point","coordinates":[3.625261642857142,43.8866427857143]}}]}