{"type":"FeatureCollection","features":[{"type":"Feature","properties":{"codesPostaux":["34150"],"population":110,"nom":"Lagamas","code":"34125"},"geometry":{"type":"Point","coordinates":[3.534846428571428,43.675509761904785]}}]}