{"type":"FeatureCollection","features":[{"type":"Feature","properties":{"codesPostaux":["34700"],"population":197,"nom":"Lauroux","code":"34132"},"geometry":{"type":"Point","coordinates":[3.279593821656052,43.79538490445858]}}]}