{"type":"FeatureCollection","features":[{"type":"Feature","properties":{"codesPostaux":["34210"],"population":132,"nom":"Minerve","code":"34158"},"geometry":{"type":"Point","coordinates":[2.719696166666667,43.364041458333325]}}]}