{"type":"FeatureCollection","features":[{"type":"Feature","properties":{"codesPostaux":["34390"],"population":580,"nom":"Mons","code":"34160"},"geometry":{"type":"Point","coordinates":[2.9684215525114164,43.569017031963476]}}]}