{"type":"FeatureCollection","features":[{"type":"Feature","properties":{"codesPostaux":["34570"],"population":2586,"nom":"Montarnaud","code":"34163"},"geometry":{"type":"Point","coordinates":[3.7027688157894723,43.647795986842105]}}]}