{"type":"FeatureCollection","features":[{"type":"Feature","properties":{"codesPostaux":["34850"],"population":1462,"nom":"Pinet","code":"34203"},"geometry":{"type":"Point","coordinates":[3.512371639344261,43.406329016393435]}}]}