{"type":"FeatureCollection","features":[{"type":"Feature","properties":{"codesPostaux":["34700"],"population":153,"nom":"Poujols","code":"34212"},"geometry":{"type":"Point","coordinates":[3.319329855072465,43.771971014492735]}}]}