{"type":"FeatureCollection","features":[{"type":"Feature","properties":{"codesPostaux":["34160"],"population":1642,"nom":"Restincli\u00e8res","code":"34227"},"geometry":{"type":"Point","coordinates":[4.03626484375,43.720438281250026]}}]}