{"type":"FeatureCollection","features":[{"type":"Feature","properties":{"codesPostaux":["34220"],"population":763,"nom":"Riols","code":"34229"},"geometry":{"type":"Point","coordinates":[2.7986338679245284,43.50217820754723]}}]}