{"type":"FeatureCollection","features":[{"type":"Feature","properties":{"codesPostaux":["34480"],"population":1040,"nom":"Puimisson","code":"34223"},"geometry":{"type":"Point","coordinates":[3.210042522522523,43.43810297297297]}}]}