{"type":"FeatureCollection","features":[{"type":"Feature","properties":{"codesPostaux":["34520"],"population":143,"nom":"Les Rives","code":"34230"},"geometry":{"type":"Point","coordinates":[3.26489641509434,43.84611754716982]}}]}