{"type":"FeatureCollection","features":[{"type":"Feature","properties":{"codesPostaux":["34650"],"population":23,"nom":"Romigui\u00e8res","code":"34231"},"geometry":{"type":"Point","coordinates":[3.2369438709677416,43.8175853763441]}}]}