{"type":"FeatureCollection","features":[{"type":"Feature","properties":{"codesPostaux":["34460"],"population":590,"nom":"Roquebrun","code":"34232"},"geometry":{"type":"Point","coordinates":[3.004042041666671,43.50851616666667]}}]}