{"type":"FeatureCollection","features":[{"type":"Feature","properties":{"codesPostaux":["34360"],"population":1812,"nom":"Saint-Chinian","code":"34245"},"geometry":{"type":"Point","coordinates":[2.9338012857142837,43.4306632857143]}}]}