{"type":"FeatureCollection","features":[{"type":"Feature","properties":{"codesPostaux":["34160"],"population":2270,"nom":"Saint-Dr\u00e9z\u00e9ry","code":"34249"},"geometry":{"type":"Point","coordinates":[3.9812759482758615,43.7318726724138]}}]}