{"type":"FeatureCollection","features":[{"type":"Feature","properties":{"codesPostaux":["34260"],"population":271,"nom":"Saint-\u00c9tienne-Estr\u00e9choux","code":"34252"},"geometry":{"type":"Point","coordinates":[3.1041111594202913,43.66227173913044]}}]}