{"type":"FeatureCollection","features":[{"type":"Feature","properties":{"codesPostaux":["34520"],"population":35,"nom":"Saint-F\u00e9lix-de-l'H\u00e9ras","code":"34253"},"geometry":{"type":"Point","coordinates":[3.307626859504132,43.83949793388431]}}]}