{"type":"FeatureCollection","features":[{"type":"Feature","properties":{"codesPostaux":["34480"],"population":1479,"nom":"Saint-Geni\u00e8s-de-Fontedit","code":"34258"},"geometry":{"type":"Point","coordinates":[3.1710790647482012,43.46813913669067]}}]}