{"type":"FeatureCollection","features":[{"type":"Feature","properties":{"codesPostaux":["34270"],"population":482,"nom":"Saint-Jean-de-Cuculles","code":"34266"},"geometry":{"type":"Point","coordinates":[3.833278224299065,43.74860242990653]}}]}