{"type":"FeatureCollection","features":[{"type":"Feature","properties":{"codesPostaux":["34360"],"population":145,"nom":"Saint-Jean-de-Minervois","code":"34269"},"geometry":{"type":"Point","coordinates":[2.8216404366812213,43.40042563318776]}}]}