{"type":"FeatureCollection","features":[{"type":"Feature","properties":{"codesPostaux":["34610"],"population":866,"nom":"Saint-Gervais-sur-Mare","code":"34260"},"geometry":{"type":"Point","coordinates":[3.043471606217615,43.663696217616604]}}]}