{"type":"FeatureCollection","features":[{"type":"Feature","properties":{"codesPostaux":["34400"],"population":2962,"nom":"Saint-Just","code":"34272"},"geometry":{"type":"Point","coordinates":[4.112989382716048,43.654230000000005]}}]}