{"type":"FeatureCollection","features":[{"type":"Feature","properties":{"codesPostaux":["34190","34520"],"population":169,"nom":"Saint-Maurice-Navacelles","code":"34277"},"geometry":{"type":"Point","coordinates":[3.517102186234817,43.857750485829975]}}]}