{"type":"FeatureCollection","features":[{"type":"Feature","properties":{"codesPostaux":["34570"],"population":1058,"nom":"Saint-Paul-et-Valmalle","code":"34282"},"geometry":{"type":"Point","coordinates":[3.687359924812029,43.61173879699247]}}]}