{"type":"FeatureCollection","features":[{"type":"Feature","properties":{"codesPostaux":["34220"],"population":1993,"nom":"Saint-Pons-de-Thomi\u00e8res","code":"34284"},"geometry":{"type":"Point","coordinates":[2.7475829583333327,43.48139420833332]}}]}