{"type":"FeatureCollection","features":[{"type":"Feature","properties":{"codesPostaux":["34400"],"population":591,"nom":"Saint-Nazaire-de-P\u00e9zan","code":"34280"},"geometry":{"type":"Point","coordinates":[4.1155206122448975,43.63836714285714]}}]}