{"type":"FeatureCollection","features":[{"type":"Feature","properties":{"codesPostaux":["34520"],"population":107,"nom":"Saint-Pierre-de-la-Fage","code":"34283"},"geometry":{"type":"Point","coordinates":[3.4187751351351356,43.792289999999994]}}]}