{"type":"FeatureCollection","features":[{"type":"Feature","properties":{"codesPostaux":["34320"],"population":163,"nom":"Vailhan","code":"34319"},"geometry":{"type":"Point","coordinates":[3.2959324999999997,43.55486991666667]}}]}