{"type":"FeatureCollection","features":[{"type":"Feature","properties":{"codesPostaux":["34270"],"population":403,"nom":"Le Triadou","code":"34314"},"geometry":{"type":"Point","coordinates":[3.852409882352941,43.73634129411766]}}]}