{"type":"FeatureCollection","features":[{"type":"Feature","properties":{"codesPostaux":["34420","34500"],"population":4203,"nom":"Villeneuve-l\u00e8s-B\u00e9ziers","code":"34336"},"geometry":{"type":"Point","coordinates":[3.2914207692307693,43.31734804195806]}}]}