{"type":"FeatureCollection","features":[{"type":"Feature","properties":{"codesPostaux":["35370"],"population":705,"nom":"Brielles","code":"35042"},"geometry":{"type":"Point","coordinates":[-1.0948768339768344,48.00730104247108]}}]}