{"type":"FeatureCollection","features":[{"type":"Feature","properties":{"codesPostaux":["35150"],"population":850,"nom":"Brie","code":"35041"},"geometry":{"type":"Point","coordinates":[-1.5498969421487603,47.95149280991736]}}]}