{"type":"FeatureCollection","features":[{"type":"Feature","properties":{"codesPostaux":["35120"],"population":386,"nom":"Broualan","code":"35044"},"geometry":{"type":"Point","coordinates":[-1.659550659898477,48.47557548223351]}}]}