{"type":"FeatureCollection","features":[{"type":"Feature","properties":{"codesPostaux":["35160"],"population":3460,"nom":"Breteil","code":"35040"},"geometry":{"type":"Point","coordinates":[-1.9089598198198199,48.13830207207207]}}]}