{"type":"FeatureCollection","features":[{"type":"Feature","properties":{"codesPostaux":["35510"],"population":16784,"nom":"Cesson-S\u00e9vign\u00e9","code":"35051"},"geometry":{"type":"Point","coordinates":[-1.5913900392156866,48.1207512941176]}}]}