{"type":"FeatureCollection","features":[{"type":"Feature","properties":{"codesPostaux":["35135"],"population":10410,"nom":"Chantepie","code":"35055"},"geometry":{"type":"Point","coordinates":[-1.6099723589743582,48.08252184615382]}}]}