{"type":"FeatureCollection","features":[{"type":"Feature","properties":{"codesPostaux":["35131"],"population":7395,"nom":"Chartres-de-Bretagne","code":"35066"},"geometry":{"type":"Point","coordinates":[-1.7069196402877693,48.04385474820144]}}]}