{"type":"FeatureCollection","features":[{"type":"Feature","properties":{"codesPostaux":["35250"],"population":1489,"nom":"Chasn\u00e9-sur-Illet","code":"35067"},"geometry":{"type":"Point","coordinates":[-1.5731090995260664,48.23969668246439]}}]}