{"type":"FeatureCollection","features":[{"type":"Feature","properties":{"codesPostaux":["35250"],"population":1958,"nom":"Chevaign\u00e9","code":"35079"},"geometry":{"type":"Point","coordinates":[-1.6371880487804875,48.22779243902439]}}]}