{"type":"FeatureCollection","features":[{"type":"Feature","properties":{"codesPostaux":["35410"],"population":2879,"nom":"Domloup","code":"35099"},"geometry":{"type":"Point","coordinates":[-1.543593063583815,48.06992630057804]}}]}