{"type":"FeatureCollection","features":[{"type":"Feature","properties":{"codesPostaux":["35290"],"population":542,"nom":"Le Crouais","code":"35091"},"geometry":{"type":"Point","coordinates":[-2.1508680180180177,48.21006567567566]}}]}