{"type":"FeatureCollection","features":[{"type":"Feature","properties":{"codesPostaux":["35620"],"population":1517,"nom":"Erc\u00e9-en-Lam\u00e9e","code":"35106"},"geometry":{"type":"Point","coordinates":[-1.5718071118012427,47.82486537267082]}}]}