{"type":"FeatureCollection","features":[{"type":"Feature","properties":{"codesPostaux":["35150"],"population":1122,"nom":"Ess\u00e9","code":"35108"},"geometry":{"type":"Point","coordinates":[-1.4301676630434785,47.95054777173913]}}]}