{"type":"FeatureCollection","features":[{"type":"Feature","properties":{"codesPostaux":["35111"],"population":2308,"nom":"La Fresnais","code":"35116"},"geometry":{"type":"Point","coordinates":[-1.8332048717948726,48.595152991453006]}}]}