{"type":"FeatureCollection","features":[{"type":"Feature","properties":{"codesPostaux":["35640"],"population":275,"nom":"Forges-la-For\u00eat","code":"35114"},"geometry":{"type":"Point","coordinates":[-1.2896000540540544,47.858767135135146]}}]}