{"type":"FeatureCollection","features":[{"type":"Feature","properties":{"codesPostaux":["35850"],"population":4843,"nom":"G\u00e9vez\u00e9","code":"35120"},"geometry":{"type":"Point","coordinates":[-1.796652013651876,48.2108793174061]}}]}