{"type":"FeatureCollection","features":[{"type":"Feature","properties":{"codesPostaux":["35580"],"population":3644,"nom":"Guignen","code":"35127"},"geometry":{"type":"Point","coordinates":[-1.8621560489510487,47.938043881118894]}}]}