{"type":"FeatureCollection","features":[{"type":"Feature","properties":{"codesPostaux":["35890"],"population":4951,"nom":"Laill\u00e9","code":"35139"},"geometry":{"type":"Point","coordinates":[-1.7090698513011147,47.96357899628252]}}]}