{"type":"FeatureCollection","features":[{"type":"Feature","properties":{"codesPostaux":["35720"],"population":988,"nom":"Lanh\u00e9lin","code":"35147"},"geometry":{"type":"Point","coordinates":[-1.8303495454545458,48.455394]}}]}