{"type":"FeatureCollection","features":[{"type":"Feature","properties":{"codesPostaux":["35550"],"population":783,"nom":"Lieuron","code":"35151"},"geometry":{"type":"Point","coordinates":[-1.9356218787878778,47.852129030303054]}}]}