{"type":"FeatureCollection","features":[{"type":"Feature","properties":{"codesPostaux":["35270"],"population":340,"nom":"Lourmais","code":"35159"},"geometry":{"type":"Point","coordinates":[-1.7305297247706426,48.44115862385319]}}]}