{"type":"FeatureCollection","features":[{"type":"Feature","properties":{"codesPostaux":["35133"],"population":1306,"nom":"Luitr\u00e9","code":"35163"},"geometry":{"type":"Point","coordinates":[-1.136873155893537,48.29272817490496]}}]}