{"type":"FeatureCollection","features":[{"type":"Feature","properties":{"codesPostaux":["35420"],"population":3435,"nom":"Louvign\u00e9-du-D\u00e9sert","code":"35162"},"geometry":{"type":"Point","coordinates":[-1.1196090144230775,48.48251084134615]}}]}