{"type":"FeatureCollection","features":[{"type":"Feature","properties":{"codesPostaux":["35140"],"population":1622,"nom":"M\u00e9zi\u00e8res-sur-Couesnon","code":"35178"},"geometry":{"type":"Point","coordinates":[-1.426136395348837,48.29660226744186]}}]}