{"type":"FeatureCollection","features":[{"type":"Feature","properties":{"codesPostaux":["35160"],"population":1316,"nom":"Monterfil","code":"35187"},"geometry":{"type":"Point","coordinates":[-1.9846797454545453,48.06188770909086]}}]}