{"type":"FeatureCollection","features":[{"type":"Feature","properties":{"codesPostaux":["35870"],"population":1410,"nom":"Le Minihic-sur-Rance","code":"35181"},"geometry":{"type":"Point","coordinates":[-2.011392834645669,48.57562181102363]}}]}