{"type":"FeatureCollection","features":[{"type":"Feature","properties":{"codesPostaux":["35360"],"population":5019,"nom":"Montauban-de-Bretagne","code":"35184"},"geometry":{"type":"Point","coordinates":[-2.0563651149425293,48.20031043103449]}}]}