{"type":"FeatureCollection","features":[{"type":"Feature","properties":{"codesPostaux":["35310"],"population":7168,"nom":"Mordelles","code":"35196"},"geometry":{"type":"Point","coordinates":[-1.841297333333334,48.08675360606058]}}]}