{"type":"FeatureCollection","features":[{"type":"Feature","properties":{"codesPostaux":["35210"],"population":241,"nom":"Montreuil-des-Landes","code":"35192"},"geometry":{"type":"Point","coordinates":[-1.2250137815126048,48.25092873949579]}}]}