{"type":"FeatureCollection","features":[{"type":"Feature","properties":{"codesPostaux":["35130"],"population":952,"nom":"Moutiers","code":"35200"},"geometry":{"type":"Point","coordinates":[-1.2084290592334497,47.97345940766551]}}]}