{"type":"FeatureCollection","features":[{"type":"Feature","properties":{"codesPostaux":["35410"],"population":2831,"nom":"Nouvoitou","code":"35204"},"geometry":{"type":"Point","coordinates":[-1.5570886813186808,48.03197532967032]}}]}