{"type":"FeatureCollection","features":[{"type":"Feature","properties":{"codesPostaux":["35290"],"population":884,"nom":"Muel","code":"35201"},"geometry":{"type":"Point","coordinates":[-2.1585497549019608,48.1199044607843]}}]}