{"type":"FeatureCollection","features":[{"type":"Feature","properties":{"codesPostaux":["35730"],"population":6399,"nom":"Pleurtuit","code":"35228"},"geometry":{"type":"Point","coordinates":[-2.060034375,48.58295859374998]}}]}