{"type":"FeatureCollection","features":[{"type":"Feature","properties":{"codesPostaux":["35210"],"population":577,"nom":"Saint-Christophe-des-Bois","code":"35260"},"geometry":{"type":"Point","coordinates":[-1.2363625781249996,48.22629164062501]}}]}