{"type":"FeatureCollection","features":[{"type":"Feature","properties":{"codesPostaux":["35460"],"population":1329,"nom":"Saint-Marc-le-Blanc","code":"35292"},"geometry":{"type":"Point","coordinates":[-1.410930483870968,48.37282698924731]}}]}