{"type":"FeatureCollection","features":[{"type":"Feature","properties":{"codesPostaux":["35750"],"population":568,"nom":"Saint-Maugan","code":"35295"},"geometry":{"type":"Point","coordinates":[-2.101133362831859,48.13457097345132]}}]}