{"type":"FeatureCollection","features":[{"type":"Feature","properties":{"codesPostaux":["35600"],"population":2299,"nom":"Sainte-Marie","code":"35294"},"geometry":{"type":"Point","coordinates":[-2.0061692982456143,47.6985635087719]}}]}