{"type":"FeatureCollection","features":[{"type":"Feature","properties":{"codesPostaux":["35360"],"population":530,"nom":"Saint-M'Hervon","code":"35301"},"geometry":{"type":"Point","coordinates":[-2.064687692307692,48.229876538461546]}}]}