{"type":"FeatureCollection","features":[{"type":"Feature","properties":{"codesPostaux":["35310"],"population":2045,"nom":"Saint-Thurial","code":"35319"},"geometry":{"type":"Point","coordinates":[-1.9380379279279272,48.03433013513518]}}]}