{"type":"FeatureCollection","features":[{"type":"Feature","properties":{"codesPostaux":["35550"],"population":2105,"nom":"Sixt-sur-Aff","code":"35328"},"geometry":{"type":"Point","coordinates":[-2.0506166433566437,47.77072220279718]}}]}