{"type":"FeatureCollection","features":[{"type":"Feature","properties":{"codesPostaux":["35490"],"population":2559,"nom":"Sens-de-Bretagne","code":"35326"},"geometry":{"type":"Point","coordinates":[-1.5476409205020916,48.34736414225942]}}]}