{"type":"FeatureCollection","features":[{"type":"Feature","properties":{"codesPostaux":["35190"],"population":190,"nom":"Trimer","code":"35346"},"geometry":{"type":"Point","coordinates":[-1.899490638297872,48.34849372340426]}}]}