{"type":"FeatureCollection","features":[{"type":"Feature","properties":{"codesPostaux":["35460"],"population":1551,"nom":"Tremblay","code":"35341"},"geometry":{"type":"Point","coordinates":[-1.4557657971014488,48.42105385507245]}}]}