{"type":"FeatureCollection","features":[{"type":"Feature","properties":{"codesPostaux":["35160"],"population":1464,"nom":"Le Verger","code":"35351"},"geometry":{"type":"Point","coordinates":[-1.920293699186991,48.06657178861789]}}]}