{"type":"FeatureCollection","features":[{"type":"Feature","properties":{"codesPostaux":["36120"],"population":3859,"nom":"Ardentes","code":"36005"},"geometry":{"type":"Point","coordinates":[1.834812680412371,46.742322268041235]}}]}