{"type":"FeatureCollection","features":[{"type":"Feature","properties":{"codesPostaux":["36150"],"population":120,"nom":"Aize","code":"36002"},"geometry":{"type":"Point","coordinates":[1.7026386627906978,47.10940151162791]}}]}