{"type":"FeatureCollection","features":[{"type":"Feature","properties":{"codesPostaux":["36120"],"population":297,"nom":"Bommiers","code":"36019"},"geometry":{"type":"Point","coordinates":[1.9965558563535908,46.78028817679559]}}]}