{"type":"FeatureCollection","features":[{"type":"Feature","properties":{"codesPostaux":["36270"],"population":217,"nom":"Bazaiges","code":"36014"},"geometry":{"type":"Point","coordinates":[1.5271178787878794,46.47269674242423]}}]}