{"type":"FeatureCollection","features":[{"type":"Feature","properties":{"codesPostaux":["36500"],"population":123,"nom":"La Chapelle-Orthemale","code":"36040"},"geometry":{"type":"Point","coordinates":[1.4524667701863354,46.835436459627346]}}]}