{"type":"FeatureCollection","features":[{"type":"Feature","properties":{"codesPostaux":["36150"],"population":138,"nom":"La Chapelle-Saint-Laurian","code":"36041"},"geometry":{"type":"Point","coordinates":[1.7859730434782606,47.05524202898551]}}]}