{"type":"FeatureCollection","features":[{"type":"Feature","properties":{"codesPostaux":["36230"],"population":340,"nom":"Fougerolles","code":"36078"},"geometry":{"type":"Point","coordinates":[1.864643195876289,46.56594979381443]}}]}