{"type":"FeatureCollection","features":[{"type":"Feature","properties":{"codesPostaux":["36360"],"population":348,"nom":"Faverolles-en-Berry","code":"36072"},"geometry":{"type":"Point","coordinates":[1.3916019277108431,47.169209759036164]}}]}