{"type":"FeatureCollection","features":[{"type":"Feature","properties":{"codesPostaux":["36190"],"population":306,"nom":"Gargilesse-Dampierre","code":"36081"},"geometry":{"type":"Point","coordinates":[1.6283991266375542,46.503175196506575]}}]}