{"type":"FeatureCollection","features":[{"type":"Feature","properties":{"codesPostaux":["36290"],"population":1067,"nom":"M\u00e9zi\u00e8res-en-Brenne","code":"36123"},"geometry":{"type":"Point","coordinates":[1.2640003191489362,46.80592482269503]}}]}