{"type":"FeatureCollection","features":[{"type":"Feature","properties":{"codesPostaux":["36500"],"population":677,"nom":"Neuillay-les-Bois","code":"36139"},"geometry":{"type":"Point","coordinates":[1.4741981694915252,46.76037440677967]}}]}