{"type":"FeatureCollection","features":[{"type":"Feature","properties":{"codesPostaux":["36400"],"population":105,"nom":"Montlevicq","code":"36130"},"geometry":{"type":"Point","coordinates":[2.0815643023255817,46.57507779069766]}}]}