{"type":"FeatureCollection","features":[{"type":"Feature","properties":{"codesPostaux":["36160"],"population":39,"nom":"La Motte-Feuilly","code":"36132"},"geometry":{"type":"Point","coordinates":[2.068815925925926,46.54736000000001]}}]}