{"type":"FeatureCollection","features":[{"type":"Feature","properties":{"codesPostaux":["36260"],"population":489,"nom":"Paudy","code":"36152"},"geometry":{"type":"Point","coordinates":[1.9268971604938268,47.032996172839496]}}]}