{"type":"FeatureCollection","features":[{"type":"Feature","properties":{"codesPostaux":["36200"],"population":1867,"nom":"Le P\u00eachereau","code":"36154"},"geometry":{"type":"Point","coordinates":[1.573283298969072,46.581545567010316]}}]}