{"type":"FeatureCollection","features":[{"type":"Feature","properties":{"codesPostaux":["36370"],"population":664,"nom":"Prissac","code":"36168"},"geometry":{"type":"Point","coordinates":[1.2953741479099676,46.51160649517684]}}]}