{"type":"FeatureCollection","features":[{"type":"Feature","properties":{"codesPostaux":["36800"],"population":924,"nom":"Le Pont-Chr\u00e9tien-Chabenet","code":"36161"},"geometry":{"type":"Point","coordinates":[1.500392558139535,46.62822034883719]}}]}