{"type":"FeatureCollection","features":[{"type":"Feature","properties":{"codesPostaux":["36400"],"population":239,"nom":"Saint-Christophe-en-Boucherie","code":"36186"},"geometry":{"type":"Point","coordinates":[2.1197100636942676,46.67230305732484]}}]}