{"type":"FeatureCollection","features":[{"type":"Feature","properties":{"codesPostaux":["36100"],"population":198,"nom":"Saint-Aubin","code":"36181"},"geometry":{"type":"Point","coordinates":[2.0416185074626867,46.85413731343283]}}]}