{"type":"FeatureCollection","features":[{"type":"Feature","properties":{"codesPostaux":["36170"],"population":177,"nom":"Saint-Civran","code":"36187"},"geometry":{"type":"Point","coordinates":[1.4014581060606057,46.49052856060607]}}]}