{"type":"FeatureCollection","features":[{"type":"Feature","properties":{"codesPostaux":["36100"],"population":285,"nom":"Sainte-Fauste","code":"36190"},"geometry":{"type":"Point","coordinates":[1.8791071171171172,46.84910774774774]}}]}