{"type":"FeatureCollection","features":[{"type":"Feature","properties":{"codesPostaux":["36100"],"population":282,"nom":"Saint-Valentin","code":"36209"},"geometry":{"type":"Point","coordinates":[1.8717133636363643,46.95495836363637]}}]}