{"type":"FeatureCollection","features":[{"type":"Feature","properties":{"codesPostaux":["36180"],"population":72,"nom":"Selles-sur-Nahon","code":"36216"},"geometry":{"type":"Point","coordinates":[1.4574509821428572,47.01834651785714]}}]}