{"type":"FeatureCollection","features":[{"type":"Feature","properties":{"codesPostaux":["36200"],"population":649,"nom":"Tendu","code":"36219"},"geometry":{"type":"Point","coordinates":[1.5616287431693991,46.64403890710385]}}]}