{"type":"FeatureCollection","features":[{"type":"Feature","properties":{"codesPostaux":["36500"],"population":373,"nom":"Villegouin","code":"36243"},"geometry":{"type":"Point","coordinates":[1.3710702020202017,46.95869878787881]}}]}