{"type":"FeatureCollection","features":[{"type":"Feature","properties":{"codesPostaux":["37350"],"population":526,"nom":"Barrou","code":"37019"},"geometry":{"type":"Point","coordinates":[0.7851776258992809,46.87622316546761]}}]}