{"type":"FeatureCollection","features":[{"type":"Feature","properties":{"codesPostaux":["37340"],"population":473,"nom":"Avrill\u00e9-les-Ponceaux","code":"37013"},"geometry":{"type":"Point","coordinates":[0.3082549999999999,47.38748089285718]}}]}