{"type":"FeatureCollection","features":[{"type":"Feature","properties":{"codesPostaux":["37220"],"population":564,"nom":"Avon-les-Roches","code":"37012"},"geometry":{"type":"Point","coordinates":[0.46138575757575767,47.18279767676767]}}]}