{"type":"FeatureCollection","features":[{"type":"Feature","properties":{"codesPostaux":["37600"],"population":573,"nom":"Betz-le-Ch\u00e2teau","code":"37026"},"geometry":{"type":"Point","coordinates":[0.9610733333333337,46.989069224806215]}}]}