{"type":"FeatureCollection","features":[{"type":"Feature","properties":{"codesPostaux":["37360","37370"],"population":1598,"nom":"Beaumont-Louestault","code":"37021"},"geometry":{"type":"Point","coordinates":[0.6666380505415161,47.591218844765336]}}]}