{"type":"FeatureCollection","features":[{"type":"Feature","properties":{"codesPostaux":["37460"],"population":280,"nom":"Beaumont-Village","code":"37023"},"geometry":{"type":"Point","coordinates":[1.2028071014492758,47.17679623188405]}}]}