{"type":"FeatureCollection","features":[{"type":"Feature","properties":{"codesPostaux":["37510"],"population":739,"nom":"Berthenay","code":"37025"},"geometry":{"type":"Point","coordinates":[0.5158707692307692,47.35694211538459]}}]}