{"type":"FeatureCollection","features":[{"type":"Feature","properties":{"codesPostaux":["37130"],"population":782,"nom":"Br\u00e9h\u00e9mont","code":"37038"},"geometry":{"type":"Point","coordinates":[0.3664049112426037,47.284572485207086]}}]}