{"type":"FeatureCollection","features":[{"type":"Feature","properties":{"codesPostaux":["37220"],"population":314,"nom":"Brizay","code":"37040"},"geometry":{"type":"Point","coordinates":[0.3883778947368421,47.09903013157896]}}]}