{"type":"FeatureCollection","features":[{"type":"Feature","properties":{"codesPostaux":["37600"],"population":143,"nom":"Chanceaux-pr\u00e8s-Loches","code":"37053"},"geometry":{"type":"Point","coordinates":[0.9432795789473687,47.143753157894736]}}]}