{"type":"FeatureCollection","features":[{"type":"Feature","properties":{"codesPostaux":["37310"],"population":569,"nom":"Ch\u00e9digny","code":"37066"},"geometry":{"type":"Point","coordinates":[0.9924274452554744,47.21980204379563]}}]}