{"type":"FeatureCollection","features":[{"type":"Feature","properties":{"codesPostaux":["37110"],"population":5072,"nom":"Ch\u00e2teau-Renault","code":"37063"},"geometry":{"type":"Point","coordinates":[0.9076148809523814,47.59120166666666]}}]}