{"type":"FeatureCollection","features":[{"type":"Feature","properties":{"codesPostaux":["37160"],"population":213,"nom":"Civray-sur-Esves","code":"37080"},"geometry":{"type":"Point","coordinates":[0.7039637078651685,47.038760337078664]}}]}