{"type":"FeatureCollection","features":[{"type":"Feature","properties":{"codesPostaux":["37340"],"population":453,"nom":"Continvoir","code":"37082"},"geometry":{"type":"Point","coordinates":[0.23020964843750016,47.371473085937495]}}]}