{"type":"FeatureCollection","features":[{"type":"Feature","properties":{"codesPostaux":["37150"],"population":2156,"nom":"La Croix-en-Touraine","code":"37091"},"geometry":{"type":"Point","coordinates":[0.9926312987012983,47.34929857142858]}}]}