{"type":"FeatureCollection","features":[{"type":"Feature","properties":{"codesPostaux":["37310"],"population":670,"nom":"Dolus-le-Sec","code":"37097"},"geometry":{"type":"Point","coordinates":[0.8851888372093023,47.16155736434111]}}]}