{"type":"FeatureCollection","features":[{"type":"Feature","properties":{"codesPostaux":["37120"],"population":485,"nom":"L\u00e9mer\u00e9","code":"37125"},"geometry":{"type":"Point","coordinates":[0.33522814814814816,47.09438666666667]}}]}