{"type":"FeatureCollection","features":[{"type":"Feature","properties":{"codesPostaux":["37120"],"population":256,"nom":"Jaulnay","code":"37121"},"geometry":{"type":"Point","coordinates":[0.4302182105263158,46.957338]}}]}