{"type":"FeatureCollection","features":[{"type":"Feature","properties":{"codesPostaux":["37390"],"population":2065,"nom":"Mettray","code":"37152"},"geometry":{"type":"Point","coordinates":[0.6614501503759397,47.457347894736806]}}]}