{"type":"FeatureCollection","features":[{"type":"Feature","properties":{"codesPostaux":["37360"],"population":1916,"nom":"Neuill\u00e9-Pont-Pierre","code":"37167"},"geometry":{"type":"Point","coordinates":[0.5432913903743312,47.55323438502675]}}]}