{"type":"FeatureCollection","features":[{"type":"Feature","properties":{"codesPostaux":["37380"],"population":1277,"nom":"Nouzilly","code":"37175"},"geometry":{"type":"Point","coordinates":[0.7392576388888885,47.53762125000004]}}]}