{"type":"FeatureCollection","features":[{"type":"Feature","properties":{"codesPostaux":["37210"],"population":2292,"nom":"Par\u00e7ay-Meslay","code":"37179"},"geometry":{"type":"Point","coordinates":[0.7497955670103092,47.453231649484536]}}]}