{"type":"FeatureCollection","features":[{"type":"Feature","properties":{"codesPostaux":["37290"],"population":1029,"nom":"Preuilly-sur-Claise","code":"37189"},"geometry":{"type":"Point","coordinates":[0.9298161261261267,46.852302342342334]}}]}