{"type":"FeatureCollection","features":[{"type":"Feature","properties":{"codesPostaux":["37220"],"population":464,"nom":"Rilly-sur-Vienne","code":"37199"},"geometry":{"type":"Point","coordinates":[0.4993454054054054,47.05719108108108]}}]}