{"type":"FeatureCollection","features":[{"type":"Feature","properties":{"codesPostaux":["37800"],"population":724,"nom":"Sainte-Catherine-de-Fierbois","code":"37212"},"geometry":{"type":"Point","coordinates":[0.6776977083333332,47.153518125000005]}}]}