{"type":"FeatureCollection","features":[{"type":"Feature","properties":{"codesPostaux":["37500"],"population":873,"nom":"Saint-Beno\u00eet-la-For\u00eat","code":"37210"},"geometry":{"type":"Point","coordinates":[0.31368249999999986,47.210881875000005]}}]}