{"type":"FeatureCollection","features":[{"type":"Feature","properties":{"codesPostaux":["37530"],"population":540,"nom":"Saint-R\u00e8gle","code":"37236"},"geometry":{"type":"Point","coordinates":[1.035760153846154,47.407192769230775]}}]}