{"type":"FeatureCollection","features":[{"type":"Feature","properties":{"codesPostaux":["37360"],"population":1381,"nom":"Sonzay","code":"37249"},"geometry":{"type":"Point","coordinates":[0.48277875000000003,47.51303282608693]}}]}