{"type":"FeatureCollection","features":[{"type":"Feature","properties":{"codesPostaux":["37340"],"population":1363,"nom":"Savign\u00e9-sur-Lathan","code":"37241"},"geometry":{"type":"Point","coordinates":[0.32959521428571426,47.44307178571427]}}]}