{"type":"FeatureCollection","features":[{"type":"Feature","properties":{"codesPostaux":["37220"],"population":249,"nom":"Sazilly","code":"37244"},"geometry":{"type":"Point","coordinates":[0.351169365079365,47.12368793650791]}}]}