{"type":"FeatureCollection","features":[{"type":"Feature","properties":{"codesPostaux":["37500"],"population":283,"nom":"Thizay","code":"37258"},"geometry":{"type":"Point","coordinates":[0.13736853932584273,47.16337269662922]}}]}