{"type":"FeatureCollection","features":[{"type":"Feature","properties":{"codesPostaux":["37320"],"population":2175,"nom":"Truyes","code":"37263"},"geometry":{"type":"Point","coordinates":[0.8520433802816899,47.28230288732392]}}]}