{"type":"FeatureCollection","features":[{"type":"Feature","properties":{"codesPostaux":["37190"],"population":1023,"nom":"Villaines-les-Rochers","code":"37271"},"geometry":{"type":"Point","coordinates":[0.4952480575539571,47.21906568345326]}}]}