{"type":"FeatureCollection","features":[{"type":"Feature","properties":{"codesPostaux":["38550"],"population":1488,"nom":"Auberives-sur-Var\u00e8ze","code":"38019"},"geometry":{"type":"Point","coordinates":[4.821115116279074,45.428281162790704]}}]}