{"type":"FeatureCollection","features":[{"type":"Feature","properties":{"codesPostaux":["38630"],"population":7488,"nom":"Les Aveni\u00e8res Veyrins-Thuellin","code":"38022"},"geometry":{"type":"Point","coordinates":[5.55947982142857,45.63680220238095]}}]}