{"type":"FeatureCollection","features":[{"type":"Feature","properties":{"codesPostaux":["38270"],"population":4721,"nom":"Beaurepaire","code":"38034"},"geometry":{"type":"Point","coordinates":[5.038670476190477,45.33785619047619]}}]}