{"type":"FeatureCollection","features":[{"type":"Feature","properties":{"codesPostaux":["38150"],"population":1397,"nom":"Boug\u00e9-Chambalud","code":"38051"},"geometry":{"type":"Point","coordinates":[4.896271428571429,45.325303571428556]}}]}