{"type":"FeatureCollection","features":[{"type":"Feature","properties":{"codesPostaux":["38260"],"population":1331,"nom":"Champier","code":"38069"},"geometry":{"type":"Point","coordinates":[5.286085617283947,45.459083950617284]}}]}