{"type":"FeatureCollection","features":[{"type":"Feature","properties":{"codesPostaux":["38150"],"population":2394,"nom":"Chanas","code":"38072"},"geometry":{"type":"Point","coordinates":[4.838002638888889,45.31980833333333]}}]}