{"type":"FeatureCollection","features":[{"type":"Feature","properties":{"codesPostaux":["38730"],"population":208,"nom":"Chassignieu","code":"38089"},"geometry":{"type":"Point","coordinates":[5.519365294117647,45.50505411764707]}}]}