{"type":"FeatureCollection","features":[{"type":"Feature","properties":{"codesPostaux":["38850"],"population":1823,"nom":"Charavines","code":"38082"},"geometry":{"type":"Point","coordinates":[5.521231769230767,45.42279138461539]}}]}