{"type":"FeatureCollection","features":[{"type":"Feature","properties":{"codesPostaux":["38230"],"population":8544,"nom":"Charvieu-Chavagneux","code":"38085"},"geometry":{"type":"Point","coordinates":[5.150932051282051,45.740344743589745]}}]}