{"type":"FeatureCollection","features":[{"type":"Feature","properties":{"codesPostaux":["38460"],"population":1065,"nom":"Chozeau","code":"38109"},"geometry":{"type":"Point","coordinates":[5.207905499999999,45.696158999999994]}}]}