{"type":"FeatureCollection","features":[{"type":"Feature","properties":{"codesPostaux":["38470"],"population":645,"nom":"Cognin-les-Gorges","code":"38117"},"geometry":{"type":"Point","coordinates":[5.413786611570247,45.16576553719011]}}]}