{"type":"FeatureCollection","features":[{"type":"Feature","properties":{"codesPostaux":["38350"],"population":47,"nom":"Cognet","code":"38116"},"geometry":{"type":"Point","coordinates":[5.77491267857143,44.88042160714285]}}]}