{"type":"FeatureCollection","features":[{"type":"Feature","properties":{"codesPostaux":["38138"],"population":1947,"nom":"Les C\u00f4tes-d'Arey","code":"38131"},"geometry":{"type":"Point","coordinates":[4.875662743902439,45.45973506097559]}}]}