{"type":"FeatureCollection","features":[{"type":"Feature","properties":{"codesPostaux":["38260"],"population":980,"nom":"Faramans","code":"38161"},"geometry":{"type":"Point","coordinates":[5.153235522388058,45.388884328358216]}}]}