{"type":"FeatureCollection","features":[{"type":"Feature","properties":{"codesPostaux":["38190"],"population":3362,"nom":"Froges","code":"38175"},"geometry":{"type":"Point","coordinates":[5.927405058823531,45.26701941176469]}}]}