{"type":"FeatureCollection","features":[{"type":"Feature","properties":{"codesPostaux":["38490"],"population":472,"nom":"Granieu","code":"38183"},"geometry":{"type":"Point","coordinates":[5.589149393939394,45.59867303030304]}}]}