{"type":"FeatureCollection","features":[{"type":"Feature","properties":{"codesPostaux":["38450"],"population":1838,"nom":"Le Gua","code":"38187"},"geometry":{"type":"Point","coordinates":[5.62947813559322,45.015193728813564]}}]}