{"type":"FeatureCollection","features":[{"type":"Feature","properties":{"codesPostaux":["38320"],"population":1355,"nom":"Herbeys","code":"38188"},"geometry":{"type":"Point","coordinates":[5.7988019402985085,45.14264731343284]}}]}