{"type":"FeatureCollection","features":[{"type":"Feature","properties":{"codesPostaux":["38270"],"population":1033,"nom":"Jarcieu","code":"38198"},"geometry":{"type":"Point","coordinates":[4.9484675581395345,45.33356046511628]}}]}