{"type":"FeatureCollection","features":[{"type":"Feature","properties":{"codesPostaux":["38200"],"population":2153,"nom":"Luzinay","code":"38215"},"geometry":{"type":"Point","coordinates":[4.955414418604649,45.585216744186056]}}]}