{"type":"FeatureCollection","features":[{"type":"Feature","properties":{"codesPostaux":["38440"],"population":338,"nom":"Lieudieu","code":"38211"},"geometry":{"type":"Point","coordinates":[5.180277790697673,45.45822604651164]}}]}