{"type":"FeatureCollection","features":[{"type":"Feature","properties":{"codesPostaux":["38710"],"population":1343,"nom":"Mens","code":"38226"},"geometry":{"type":"Point","coordinates":[5.740437752293581,44.80746188073393]}}]}