{"type":"FeatureCollection","features":[{"type":"Feature","properties":{"codesPostaux":["38122"],"population":778,"nom":"Monsteroux-Milieu","code":"38244"},"geometry":{"type":"Point","coordinates":[4.949078148148148,45.43812740740745]}}]}