{"type":"FeatureCollection","features":[{"type":"Feature","properties":{"codesPostaux":["38270"],"population":699,"nom":"Moissieu-sur-Dolon","code":"38240"},"geometry":{"type":"Point","coordinates":[4.989484295302017,45.39322483221477]}}]}