{"type":"FeatureCollection","features":[{"type":"Feature","properties":{"codesPostaux":["38122"],"population":944,"nom":"Montseveroux","code":"38259"},"geometry":{"type":"Point","coordinates":[4.975821991150443,45.4293196902655]}}]}