{"type":"FeatureCollection","features":[{"type":"Feature","properties":{"codesPostaux":["38620"],"population":1696,"nom":"Montferrat","code":"38256"},"geometry":{"type":"Point","coordinates":[5.582090238095238,45.47873940476192]}}]}