{"type":"FeatureCollection","features":[{"type":"Feature","properties":{"codesPostaux":["38210"],"population":404,"nom":"Morette","code":"38263"},"geometry":{"type":"Point","coordinates":[5.452544736842105,45.28562136842105]}}]}