{"type":"FeatureCollection","features":[{"type":"Feature","properties":{"codesPostaux":["38350"],"population":474,"nom":"Nantes-en-Ratier","code":"38273"},"geometry":{"type":"Point","coordinates":[5.827138706896553,44.919533275862044]}}]}