{"type":"FeatureCollection","features":[{"type":"Feature","properties":{"codesPostaux":["38220"],"population":1205,"nom":"Notre-Dame-de-M\u00e9sage","code":"38279"},"geometry":{"type":"Point","coordinates":[5.749145967741936,45.070449999999994]}}]}