{"type":"FeatureCollection","features":[{"type":"Feature","properties":{"codesPostaux":["38144"],"population":525,"nom":"Notre-Dame-de-Vaulx","code":"38280"},"geometry":{"type":"Point","coordinates":[5.73894438095238,44.992988000000004]}}]}