{"type":"FeatureCollection","features":[{"type":"Feature","properties":{"codesPostaux":["38690"],"population":920,"nom":"Oyeu","code":"38287"},"geometry":{"type":"Point","coordinates":[5.4851007299270105,45.42563204379563]}}]}