{"type":"FeatureCollection","features":[{"type":"Feature","properties":{"codesPostaux":["38520"],"population":12,"nom":"Oulles","code":"38286"},"geometry":{"type":"Point","coordinates":[5.967201987179488,45.07056153846152]}}]}