{"type":"FeatureCollection","features":[{"type":"Feature","properties":{"codesPostaux":["38350"],"population":114,"nom":"Oris-en-Rattier","code":"38283"},"geometry":{"type":"Point","coordinates":[5.879856693548387,44.936207258064535]}}]}