{"type":"FeatureCollection","features":[{"type":"Feature","properties":{"codesPostaux":["38520"],"population":136,"nom":"Ornon","code":"38285"},"geometry":{"type":"Point","coordinates":[5.970987814207652,45.040516502732224]}}]}