{"type":"FeatureCollection","features":[{"type":"Feature","properties":{"codesPostaux":["38590"],"population":255,"nom":"Plan","code":"38308"},"geometry":{"type":"Point","coordinates":[5.388151089108911,45.31798980198018]}}]}