{"type":"FeatureCollection","features":[{"type":"Feature","properties":{"codesPostaux":["38270"],"population":539,"nom":"Pisieu","code":"38307"},"geometry":{"type":"Point","coordinates":[5.0690589130434764,45.39102594202898]}}]}