{"type":"FeatureCollection","features":[{"type":"Feature","properties":{"codesPostaux":["38270"],"population":1034,"nom":"Revel-Tourdan","code":"38335"},"geometry":{"type":"Point","coordinates":[5.029977737226278,45.373899197080306]}}]}