{"type":"FeatureCollection","features":[{"type":"Feature","properties":{"codesPostaux":["38160"],"population":1172,"nom":"Saint Antoine l'Abbaye","code":"38359"},"geometry":{"type":"Point","coordinates":[5.2226837735849045,45.17953108490562]}}]}