{"type":"FeatureCollection","features":[{"type":"Feature","properties":{"codesPostaux":["38140"],"population":1004,"nom":"Saint-Blaise-du-Buis","code":"38368"},"geometry":{"type":"Point","coordinates":[5.5102854918032795,45.381135491803256]}}]}