{"type":"FeatureCollection","features":[{"type":"Feature","properties":{"codesPostaux":["38960"],"population":2564,"nom":"Saint-\u00c9tienne-de-Crossey","code":"38383"},"geometry":{"type":"Point","coordinates":[5.639759923076922,45.37593815384616]}}]}