{"type":"FeatureCollection","features":[{"type":"Feature","properties":{"codesPostaux":["38120"],"population":15996,"nom":"Saint-\u00c9gr\u00e8ve","code":"38382"},"geometry":{"type":"Point","coordinates":[5.693597209302326,45.23592093023257]}}]}