{"type":"FeatureCollection","features":[{"type":"Feature","properties":{"codesPostaux":["38790"],"population":3273,"nom":"Saint-Georges-d'Esp\u00e9ranche","code":"38389"},"geometry":{"type":"Point","coordinates":[5.077954342105266,45.55461460526315]}}]}