{"type":"FeatureCollection","features":[{"type":"Feature","properties":{"codesPostaux":["38260"],"population":1416,"nom":"Saint-Hilaire-de-la-C\u00f4te","code":"38393"},"geometry":{"type":"Point","coordinates":[5.330676891891892,45.392488918918914]}}]}