{"type":"FeatureCollection","features":[{"type":"Feature","properties":{"codesPostaux":["38110"],"population":1521,"nom":"Saint-Jean-de-Soudain","code":"38401"},"geometry":{"type":"Point","coordinates":[5.435050340909091,45.584901249999994]}}]}