{"type":"FeatureCollection","features":[{"type":"Feature","properties":{"codesPostaux":["38480"],"population":256,"nom":"Saint-Martin-de-Vaulserre","code":"38420"},"geometry":{"type":"Point","coordinates":[5.681440307692307,45.49056692307692]}}]}