{"type":"FeatureCollection","features":[{"type":"Feature","properties":{"codesPostaux":["38570","38830"],"population":3335,"nom":"Cr\u00eats en Belledonne","code":"38439"},"geometry":{"type":"Point","coordinates":[6.033286931216932,45.361245978835996]}}]}