{"type":"FeatureCollection","features":[{"type":"Feature","properties":{"codesPostaux":["38370"],"population":1279,"nom":"Saint-Prim","code":"38448"},"geometry":{"type":"Point","coordinates":[4.799207968750002,45.44835593750001]}}]}