{"type":"FeatureCollection","features":[{"type":"Feature","properties":{"codesPostaux":["38200"],"population":846,"nom":"Saint-Sorlin-de-Vienne","code":"38459"},"geometry":{"type":"Point","coordinates":[4.936053175675677,45.478434864864845]}}]}