{"type":"FeatureCollection","features":[{"type":"Feature","properties":{"codesPostaux":["38210"],"population":1331,"nom":"Saint-Quentin-sur-Is\u00e8re","code":"38450"},"geometry":{"type":"Point","coordinates":[5.548206338797812,45.27603754098362]}}]}