{"type":"FeatureCollection","features":[{"type":"Feature","properties":{"codesPostaux":["38160"],"population":1751,"nom":"Saint-Romans","code":"38453"},"geometry":{"type":"Point","coordinates":[5.326446967213114,45.10317516393445]}}]}