{"type":"FeatureCollection","features":[{"type":"Feature","properties":{"codesPostaux":["38510"],"population":1106,"nom":"Saint-Victor-de-Morestel","code":"38465"},"geometry":{"type":"Point","coordinates":[5.494914465408804,45.70117880503146]}}]}