{"type":"FeatureCollection","features":[{"type":"Feature","properties":{"codesPostaux":["38350"],"population":322,"nom":"La Salle-en-Beaumont","code":"38470"},"geometry":{"type":"Point","coordinates":[5.8600368888888905,44.86006299999999]}}]}