{"type":"FeatureCollection","features":[{"type":"Feature","properties":{"codesPostaux":["38470"],"population":586,"nom":"T\u00eache","code":"38500"},"geometry":{"type":"Point","coordinates":[5.37834212121212,45.18574818181819]}}]}