{"type":"FeatureCollection","features":[{"type":"Feature","properties":{"codesPostaux":["38700"],"population":6657,"nom":"La Tronche","code":"38516"},"geometry":{"type":"Point","coordinates":[5.744810804597699,45.21233252873563]}}]}