{"type":"FeatureCollection","features":[{"type":"Feature","properties":{"codesPostaux":["38710"],"population":179,"nom":"Tr\u00e9minis","code":"38514"},"geometry":{"type":"Point","coordinates":[5.768932032967034,44.73182164835166]}}]}