{"type":"FeatureCollection","features":[{"type":"Feature","properties":{"codesPostaux":["38740"],"population":507,"nom":"Valbonnais","code":"38518"},"geometry":{"type":"Point","coordinates":[5.913809931972792,44.89553877551022]}}]}