{"type":"FeatureCollection","features":[{"type":"Feature","properties":{"codesPostaux":["38660"],"population":3075,"nom":"Le Touvet","code":"38511"},"geometry":{"type":"Point","coordinates":[5.947004270833333,45.354663125]}}]}