{"type":"FeatureCollection","features":[{"type":"Feature","properties":{"codesPostaux":["38890"],"population":473,"nom":"Vasselin","code":"38525"},"geometry":{"type":"Point","coordinates":[5.448046304347826,45.62750456521737]}}]}