{"type":"FeatureCollection","features":[{"type":"Feature","properties":{"codesPostaux":["38620"],"population":511,"nom":"Velanne","code":"38531"},"geometry":{"type":"Point","coordinates":[5.6406057692307705,45.48975769230771]}}]}