{"type":"FeatureCollection","features":[{"type":"Feature","properties":{"codesPostaux":["38250"],"population":4109,"nom":"Villard-de-Lans","code":"38548"},"geometry":{"type":"Point","coordinates":[5.525858220338982,45.0548477118644]}}]}