{"type":"FeatureCollection","features":[{"type":"Feature","properties":{"codesPostaux":["38520"],"population":26,"nom":"Villard-Notre-Dame","code":"38549"},"geometry":{"type":"Point","coordinates":[6.03477057142857,45.01448485714285]}}]}