{"type":"FeatureCollection","features":[{"type":"Feature","properties":{"codesPostaux":["38440"],"population":1141,"nom":"Villeneuve-de-Marc","code":"38555"},"geometry":{"type":"Point","coordinates":[5.119901893203881,45.45629529126213]}}]}