{"type":"FeatureCollection","features":[{"type":"Feature","properties":{"codesPostaux":["38460"],"population":1858,"nom":"Villemoirieu","code":"38554"},"geometry":{"type":"Point","coordinates":[5.248933690476189,45.712629761904765]}}]}