{"type":"FeatureCollection","features":[{"type":"Feature","properties":{"codesPostaux":["38340"],"population":9565,"nom":"Voreppe","code":"38565"},"geometry":{"type":"Point","coordinates":[5.650175918367348,45.29546891156462]}}]}