{"type":"FeatureCollection","features":[{"type":"Feature","properties":{"codesPostaux":["38210"],"population":1643,"nom":"Vourey","code":"38566"},"geometry":{"type":"Point","coordinates":[5.524072123893805,45.317492300884965]}}]}