{"type":"FeatureCollection","features":[{"type":"Feature","properties":{"codesPostaux":["39110"],"population":65,"nom":"Abergement-l\u00e8s-Th\u00e9sy","code":"39004"},"geometry":{"type":"Point","coordinates":[5.94281336734694,46.91469887755105]}}]}