{"type":"FeatureCollection","features":[{"type":"Feature","properties":{"codesPostaux":["39600"],"population":3529,"nom":"Arbois","code":"39013"},"geometry":{"type":"Point","coordinates":[5.77568772486772,46.90226439153438]}}]}