{"type":"FeatureCollection","features":[{"type":"Feature","properties":{"codesPostaux":["39700"],"population":284,"nom":"Audelange","code":"39024"},"geometry":{"type":"Point","coordinates":[5.58366223880597,47.13864268656716]}}]}