{"type":"FeatureCollection","features":[{"type":"Feature","properties":{"codesPostaux":["39700"],"population":200,"nom":"Auxange","code":"39031"},"geometry":{"type":"Point","coordinates":[5.654172941176471,47.17934788235295]}}]}