{"type":"FeatureCollection","features":[{"type":"Feature","properties":{"codesPostaux":["39100"],"population":492,"nom":"Baverans","code":"39042"},"geometry":{"type":"Point","coordinates":[5.53629875,47.106518750000006]}}]}