{"type":"FeatureCollection","features":[{"type":"Feature","properties":{"codesPostaux":["39800"],"population":400,"nom":"Bersaillin","code":"39049"},"geometry":{"type":"Point","coordinates":[5.600101299435026,46.85683604519773]}}]}