{"type":"FeatureCollection","features":[{"type":"Feature","properties":{"codesPostaux":["39150"],"population":77,"nom":"Bief-des-Maisons","code":"39052"},"geometry":{"type":"Point","coordinates":[6.04631906976744,46.70258558139535]}}]}