{"type":"FeatureCollection","features":[{"type":"Feature","properties":{"codesPostaux":["39140"],"population":1424,"nom":"Bletterans","code":"39056"},"geometry":{"type":"Point","coordinates":[5.425285714285711,46.72904795918367]}}]}