{"type":"FeatureCollection","features":[{"type":"Feature","properties":{"codesPostaux":["39600"],"population":128,"nom":"Champagne-sur-Loue","code":"39095"},"geometry":{"type":"Point","coordinates":[5.8068004761904755,47.032374761904734]}}]}