{"type":"FeatureCollection","features":[{"type":"Feature","properties":{"codesPostaux":["39120"],"population":1678,"nom":"Chaussin","code":"39128"},"geometry":{"type":"Point","coordinates":[5.405519533333334,46.972912466666685]}}]}