{"type":"FeatureCollection","features":[{"type":"Feature","properties":{"codesPostaux":["39230"],"population":473,"nom":"Chaumergy","code":"39124"},"geometry":{"type":"Point","coordinates":[5.471620900900898,46.84158954954956]}}]}