{"type":"FeatureCollection","features":[{"type":"Feature","properties":{"codesPostaux":["39150"],"population":412,"nom":"Chaux-des-Crotenay","code":"39129"},"geometry":{"type":"Point","coordinates":[5.956600074074076,46.66205659259259]}}]}