{"type":"FeatureCollection","features":[{"type":"Feature","properties":{"codesPostaux":["39570"],"population":653,"nom":"Chilly-le-Vignoble","code":"39146"},"geometry":{"type":"Point","coordinates":[5.496107640449439,46.65958280898875]}}]}