{"type":"FeatureCollection","features":[{"type":"Feature","properties":{"codesPostaux":["39250"],"population":236,"nom":"Cuvier","code":"39187"},"geometry":{"type":"Point","coordinates":[6.068038970588236,46.84012249999999]}}]}