{"type":"FeatureCollection","features":[{"type":"Feature","properties":{"codesPostaux":["39140"],"population":469,"nom":"Desnes","code":"39194"},"geometry":{"type":"Point","coordinates":[5.463219545454545,46.76706170454545]}}]}