{"type":"FeatureCollection","features":[{"type":"Feature","properties":{"codesPostaux":["39230"],"population":100,"nom":"Les Deux-Fays","code":"39196"},"geometry":{"type":"Point","coordinates":[5.482484677419357,46.88580209677418]}}]}