{"type":"FeatureCollection","features":[{"type":"Feature","properties":{"codesPostaux":["39210"],"population":921,"nom":"Domblans","code":"39199"},"geometry":{"type":"Point","coordinates":[5.5903091499999995,46.75922829999999]}}]}