{"type":"FeatureCollection","features":[{"type":"Feature","properties":{"codesPostaux":["39700"],"population":393,"nom":"\u00c9clans-Nenon","code":"39205"},"geometry":{"type":"Point","coordinates":[5.594621666666665,47.1261711904762]}}]}