{"type":"FeatureCollection","features":[{"type":"Feature","properties":{"codesPostaux":["39100"],"population":676,"nom":"Gevry","code":"39252"},"geometry":{"type":"Point","coordinates":[5.446851351351354,47.03290472972972]}}]}