{"type":"FeatureCollection","features":[{"type":"Feature","properties":{"codesPostaux":["39140"],"population":560,"nom":"Larnaud","code":"39279"},"geometry":{"type":"Point","coordinates":[5.467711851851851,46.698211913580245]}}]}