{"type":"FeatureCollection","features":[{"type":"Feature","properties":{"codesPostaux":["39320"],"population":245,"nom":"Montlainsia","code":"39273"},"geometry":{"type":"Point","coordinates":[5.480162798507463,46.37727835820894]}}]}