{"type":"FeatureCollection","features":[{"type":"Feature","properties":{"codesPostaux":["39170"],"population":213,"nom":"Lesch\u00e8res","code":"39293"},"geometry":{"type":"Point","coordinates":[5.828620684931508,46.469598219178096]}}]}