{"type":"FeatureCollection","features":[{"type":"Feature","properties":{"codesPostaux":["39260"],"population":208,"nom":"Martigna","code":"39318"},"geometry":{"type":"Point","coordinates":[5.701828965517242,46.38828844827585]}}]}