{"type":"FeatureCollection","features":[{"type":"Feature","properties":{"codesPostaux":["39800"],"population":118,"nom":"Molain","code":"39336"},"geometry":{"type":"Point","coordinates":[5.827427214285711,46.824143071428544]}}]}