{"type":"FeatureCollection","features":[{"type":"Feature","properties":{"codesPostaux":["39100"],"population":446,"nom":"Monni\u00e8res","code":"39345"},"geometry":{"type":"Point","coordinates":[5.4565921311475405,47.11301737704916]}}]}