{"type":"FeatureCollection","features":[{"type":"Feature","properties":{"codesPostaux":["39570"],"population":3022,"nom":"Montmorot","code":"39362"},"geometry":{"type":"Point","coordinates":[5.5197038265306135,46.68836362244898]}}]}