{"type":"FeatureCollection","features":[{"type":"Feature","properties":{"codesPostaux":["39300"],"population":68,"nom":"Moutoux","code":"39376"},"geometry":{"type":"Point","coordinates":[5.941409189189188,46.79157468468466]}}]}