{"type":"FeatureCollection","features":[{"type":"Feature","properties":{"codesPostaux":["39800"],"population":82,"nom":"Neuvilley","code":"39386"},"geometry":{"type":"Point","coordinates":[5.599497818181819,46.8960209090909]}}]}