{"type":"FeatureCollection","features":[{"type":"Feature","properties":{"codesPostaux":["39350"],"population":332,"nom":"Ougney","code":"39398"},"geometry":{"type":"Point","coordinates":[5.661798271604939,47.238908148148155]}}]}