{"type":"FeatureCollection","features":[{"type":"Feature","properties":{"codesPostaux":["39250"],"population":420,"nom":"Nozeroy","code":"39391"},"geometry":{"type":"Point","coordinates":[6.038969140625003,46.770151406249994]}}]}