{"type":"FeatureCollection","features":[{"type":"Feature","properties":{"codesPostaux":["39800"],"population":238,"nom":"Oussi\u00e8res","code":"39401"},"geometry":{"type":"Point","coordinates":[5.598049120879121,46.91680560439561]}}]}