{"type":"FeatureCollection","features":[{"type":"Feature","properties":{"codesPostaux":["39210"],"population":558,"nom":"Plainoiseau","code":"39422"},"geometry":{"type":"Point","coordinates":[5.555353333333332,46.72635345238099]}}]}