{"type":"FeatureCollection","features":[{"type":"Feature","properties":{"codesPostaux":["39270"],"population":191,"nom":"Pimorin","code":"39420"},"geometry":{"type":"Point","coordinates":[5.501109210526315,46.497655394736825]}}]}