{"type":"FeatureCollection","features":[{"type":"Feature","properties":{"codesPostaux":["39570"],"population":283,"nom":"Publy","code":"39445"},"geometry":{"type":"Point","coordinates":[5.651148309859155,46.62384556338028]}}]}