{"type":"FeatureCollection","features":[{"type":"Feature","properties":{"codesPostaux":["39120"],"population":506,"nom":"Rahon","code":"39448"},"geometry":{"type":"Point","coordinates":[5.475898124999997,46.99008730769232]}}]}