{"type":"FeatureCollection","features":[{"type":"Feature","properties":{"codesPostaux":["39350"],"population":206,"nom":"Romain","code":"39464"},"geometry":{"type":"Point","coordinates":[5.716892835820894,47.20669343283581]}}]}