{"type":"FeatureCollection","features":[{"type":"Feature","properties":{"codesPostaux":["39700"],"population":565,"nom":"Rochefort-sur-Nenon","code":"39462"},"geometry":{"type":"Point","coordinates":[5.559409186991871,47.12705284552845]}}]}