{"type":"FeatureCollection","features":[{"type":"Feature","properties":{"codesPostaux":["39190"],"population":351,"nom":"Sainte-Agn\u00e8s","code":"39474"},"geometry":{"type":"Point","coordinates":[5.473647313432835,46.613940895522376]}}]}