{"type":"FeatureCollection","features":[{"type":"Feature","properties":{"codesPostaux":["39130"],"population":231,"nom":"Saint-Maurice-Crillat","code":"39493"},"geometry":{"type":"Point","coordinates":[5.8274040206185616,46.57328587628866]}}]}