{"type":"FeatureCollection","features":[{"type":"Feature","properties":{"codesPostaux":["39270"],"population":229,"nom":"Sarrogna","code":"39504"},"geometry":{"type":"Point","coordinates":[5.619248066666665,46.47758386666667]}}]}