{"type":"FeatureCollection","features":[{"type":"Feature","properties":{"codesPostaux":["39310"],"population":831,"nom":"Septmoncel les Molunes","code":"39510"},"geometry":{"type":"Point","coordinates":[5.934890941558441,46.35375311688311]}}]}