{"type":"FeatureCollection","features":[{"type":"Feature","properties":{"codesPostaux":["39350"],"population":95,"nom":"Taxenne","code":"39527"},"geometry":{"type":"Point","coordinates":[5.68390791044776,47.21945746268657]}}]}