{"type":"FeatureCollection","features":[{"type":"Feature","properties":{"codesPostaux":["39160"],"population":38,"nom":"Thoissia","code":"39532"},"geometry":{"type":"Point","coordinates":[5.395062666666667,46.42725560000001]}}]}