{"type":"FeatureCollection","features":[{"type":"Feature","properties":{"codesPostaux":["39230"],"population":216,"nom":"Toulouse-le-Ch\u00e2teau","code":"39533"},"geometry":{"type":"Point","coordinates":[5.582489529411765,46.82334858823529]}}]}