{"type":"FeatureCollection","features":[{"type":"Feature","properties":{"codesPostaux":["39230"],"population":83,"nom":"Le Villey","code":"39575"},"geometry":{"type":"Point","coordinates":[5.50634642857143,46.847723571428595]}}]}