{"type":"FeatureCollection","features":[{"type":"Feature","properties":{"codesPostaux":["39350"],"population":261,"nom":"Vitreux","code":"39581"},"geometry":{"type":"Point","coordinates":[5.675130222222222,47.255696222222205]}}]}