{"type":"FeatureCollection","features":[{"type":"Feature","properties":{"codesPostaux":["40700"],"population":179,"nom":"Argelos","code":"40007"},"geometry":{"type":"Point","coordinates":[-0.6223444776119403,43.58422029850748]}}]}