{"type":"FeatureCollection","features":[{"type":"Feature","properties":{"codesPostaux":["40320"],"population":316,"nom":"Bats","code":"40029"},"geometry":{"type":"Point","coordinates":[-0.4649455905511813,43.64966637795275]}}]}