{"type":"FeatureCollection","features":[{"type":"Feature","properties":{"codesPostaux":["40360"],"population":266,"nom":"Bastennes","code":"40028"},"geometry":{"type":"Point","coordinates":[-0.7797865068493155,43.647841164383564]}}]}