{"type":"FeatureCollection","features":[{"type":"Feature","properties":{"codesPostaux":["40430"],"population":149,"nom":"Callen","code":"40060"},"geometry":{"type":"Point","coordinates":[-0.48798191304347827,44.282937086956544]}}]}