{"type":"FeatureCollection","features":[{"type":"Feature","properties":{"codesPostaux":["40180"],"population":787,"nom":"Candresse","code":"40063"},"geometry":{"type":"Point","coordinates":[-0.9754985593220341,43.71330322033901]}}]}