{"type":"FeatureCollection","features":[{"type":"Feature","properties":{"codesPostaux":["40090"],"population":167,"nom":"Canenx-et-R\u00e9aut","code":"40064"},"geometry":{"type":"Point","coordinates":[-0.4521552586206898,43.9907704310345]}}]}