{"type":"FeatureCollection","features":[{"type":"Feature","properties":{"codesPostaux":["40500"],"population":503,"nom":"Coudures","code":"40086"},"geometry":{"type":"Point","coordinates":[-0.5048790256410259,43.68982235897437]}}]}