{"type":"FeatureCollection","features":[{"type":"Feature","properties":{"codesPostaux":["40700"],"population":895,"nom":"Doazit","code":"40089"},"geometry":{"type":"Point","coordinates":[-0.6532165240641712,43.6917522459893]}}]}