{"type":"FeatureCollection","features":[{"type":"Feature","properties":{"codesPostaux":["40210"],"population":659,"nom":"Escource","code":"40094"},"geometry":{"type":"Point","coordinates":[-1.0946541935483873,44.18751795698926]}}]}