{"type":"FeatureCollection","features":[{"type":"Feature","properties":{"codesPostaux":["40310"],"population":1330,"nom":"Gabarret","code":"40102"},"geometry":{"type":"Point","coordinates":[0.010206022727272725,43.98256954545457]}}]}