{"type":"FeatureCollection","features":[{"type":"Feature","properties":{"codesPostaux":["40160"],"population":639,"nom":"Gastes","code":"40108"},"geometry":{"type":"Point","coordinates":[-1.1858947222222218,44.313339444444445]}}]}