{"type":"FeatureCollection","features":[{"type":"Feature","properties":{"codesPostaux":["40180"],"population":536,"nom":"Goos","code":"40113"},"geometry":{"type":"Point","coordinates":[-0.9170218934911242,43.730685562130155]}}]}