{"type":"FeatureCollection","features":[{"type":"Feature","properties":{"codesPostaux":["40280"],"population":897,"nom":"Haut-Mauco","code":"40122"},"geometry":{"type":"Point","coordinates":[-0.5705556204379559,43.819910729926995]}}]}