{"type":"FeatureCollection","features":[{"type":"Feature","properties":{"codesPostaux":["40700"],"population":250,"nom":"Lacrabe","code":"40138"},"geometry":{"type":"Point","coordinates":[-0.5958490839694659,43.60603625954198]}}]}