{"type":"FeatureCollection","features":[{"type":"Feature","properties":{"codesPostaux":["40250"],"population":306,"nom":"Lahosse","code":"40141"},"geometry":{"type":"Point","coordinates":[-0.7857001315789475,43.71582131578948]}}]}