{"type":"FeatureCollection","features":[{"type":"Feature","properties":{"codesPostaux":["40210"],"population":510,"nom":"L\u00fce","code":"40163"},"geometry":{"type":"Point","coordinates":[-0.9565702380952379,44.21739547619047]}}]}