{"type":"FeatureCollection","features":[{"type":"Feature","properties":{"codesPostaux":["40170"],"population":853,"nom":"M\u00e9zos","code":"40182"},"geometry":{"type":"Point","coordinates":[-1.1201362055335968,44.06664750988143]}}]}