{"type":"FeatureCollection","features":[{"type":"Feature","properties":{"codesPostaux":["40700"],"population":456,"nom":"Momuy","code":"40188"},"geometry":{"type":"Point","coordinates":[-0.6454859171597639,43.61338816568047]}}]}