{"type":"FeatureCollection","features":[{"type":"Feature","properties":{"codesPostaux":["40380"],"population":1161,"nom":"Montfort-en-Chalosse","code":"40194"},"geometry":{"type":"Point","coordinates":[-0.8362287272727268,43.702943212121205]}}]}