{"type":"FeatureCollection","features":[{"type":"Feature","properties":{"codesPostaux":["40380"],"population":377,"nom":"Onard","code":"40208"},"geometry":{"type":"Point","coordinates":[-0.8331375000000002,43.776581029411766]}}]}