{"type":"FeatureCollection","features":[{"type":"Feature","properties":{"codesPostaux":["40200"],"population":1518,"nom":"Pontenx-les-Forges","code":"40229"},"geometry":{"type":"Point","coordinates":[-1.1079684507042253,44.21995549295775]}}]}