{"type":"FeatureCollection","features":[{"type":"Feature","properties":{"codesPostaux":["40410"],"population":1389,"nom":"Pissos","code":"40227"},"geometry":{"type":"Point","coordinates":[-0.7688561711711712,44.30099265765767]}}]}