{"type":"FeatureCollection","features":[{"type":"Feature","properties":{"codesPostaux":["40350"],"population":2987,"nom":"Pouillon","code":"40233"},"geometry":{"type":"Point","coordinates":[-1.0063773060344832,43.6026472413793]}}]}