{"type":"FeatureCollection","features":[{"type":"Feature","properties":{"codesPostaux":["40370"],"population":2901,"nom":"Rion-des-Landes","code":"40243"},"geometry":{"type":"Point","coordinates":[-0.9536017391304344,43.909580000000005]}}]}