{"type":"FeatureCollection","features":[{"type":"Feature","properties":{"codesPostaux":["40630"],"population":1210,"nom":"Sabres","code":"40246"},"geometry":{"type":"Point","coordinates":[-0.7497507650273222,44.17939868852458]}}]}