{"type":"FeatureCollection","features":[{"type":"Feature","properties":{"codesPostaux":["40300"],"population":669,"nom":"Saint-\u00c9tienne-d'Orthe","code":"40256"},"geometry":{"type":"Point","coordinates":[-1.1920664473684213,43.59079657894737]}}]}