{"type":"FeatureCollection","features":[{"type":"Feature","properties":{"codesPostaux":["40190"],"population":280,"nom":"Sainte-Foy","code":"40258"},"geometry":{"type":"Point","coordinates":[-0.32788126315789473,43.92867115789473]}}]}