{"type":"FeatureCollection","features":[{"type":"Feature","properties":{"codesPostaux":["40240"],"population":109,"nom":"Saint-Julien-d'Armagnac","code":"40265"},"geometry":{"type":"Point","coordinates":[-0.14057930693069312,43.984806831683194]}}]}