{"type":"FeatureCollection","features":[{"type":"Feature","properties":{"codesPostaux":["40550"],"population":295,"nom":"Saint-Michel-Escalus","code":"40276"},"geometry":{"type":"Point","coordinates":[-1.2427320792079213,43.87886455445546]}}]}