{"type":"FeatureCollection","features":[{"type":"Feature","properties":{"codesPostaux":["40200"],"population":873,"nom":"Saint-Paul-en-Born","code":"40278"},"geometry":{"type":"Point","coordinates":[-1.1507935294117646,44.212269352941185]}}]}