{"type":"FeatureCollection","features":[{"type":"Feature","properties":{"codesPostaux":["40390"],"population":1106,"nom":"Sainte-Marie-de-Gosse","code":"40271"},"geometry":{"type":"Point","coordinates":[-1.240248433734939,43.55644903614456]}}]}