{"type":"FeatureCollection","features":[{"type":"Feature","properties":{"codesPostaux":["40230"],"population":7773,"nom":"Saint-Vincent-de-Tyrosse","code":"40284"},"geometry":{"type":"Point","coordinates":[-1.3085546428571426,43.66382232142856]}}]}