{"type":"FeatureCollection","features":[{"type":"Feature","properties":{"codesPostaux":["40510"],"population":3608,"nom":"Seignosse","code":"40296"},"geometry":{"type":"Point","coordinates":[-1.3935100934579445,43.68963971962616]}}]}