{"type":"FeatureCollection","features":[{"type":"Feature","properties":{"codesPostaux":["40230"],"population":1384,"nom":"Saubrigues","code":"40292"},"geometry":{"type":"Point","coordinates":[-1.3210253921568629,43.60172274509804]}}]}