{"type":"FeatureCollection","features":[{"type":"Feature","properties":{"codesPostaux":["40180"],"population":124,"nom":"Siest","code":"40301"},"geometry":{"type":"Point","coordinates":[-1.1279238,43.650603200000006]}}]}