{"type":"FeatureCollection","features":[{"type":"Feature","properties":{"codesPostaux":["40430"],"population":1071,"nom":"Sore","code":"40307"},"geometry":{"type":"Point","coordinates":[-0.5930840206185565,44.29034742268039]}}]}