{"type":"FeatureCollection","features":[{"type":"Feature","properties":{"codesPostaux":["40230"],"population":2426,"nom":"Tosse","code":"40317"},"geometry":{"type":"Point","coordinates":[-1.3271105263157896,43.693036052631584]}}]}