{"type":"FeatureCollection","features":[{"type":"Feature","properties":{"codesPostaux":["40220"],"population":12269,"nom":"Tarnos","code":"40312"},"geometry":{"type":"Point","coordinates":[-1.4508402590673577,43.52460025906735]}}]}