{"type":"FeatureCollection","features":[{"type":"Feature","properties":{"codesPostaux":["40480"],"population":1525,"nom":"Vieux-Boucau-les-Bains","code":"40328"},"geometry":{"type":"Point","coordinates":[-1.3916391935483872,43.784552419354846]}}]}