{"type":"FeatureCollection","features":[{"type":"Feature","properties":{"codesPostaux":["40240"],"population":252,"nom":"Vielle-Soubiran","code":"40327"},"geometry":{"type":"Point","coordinates":[-0.17084335403726703,44.07362236024845]}}]}