{"type":"FeatureCollection","features":[{"type":"Feature","properties":{"codesPostaux":["40420"],"population":245,"nom":"Vert","code":"40323"},"geometry":{"type":"Point","coordinates":[-0.5741784615384616,44.08720240384616]}}]}