{"type":"FeatureCollection","features":[{"type":"Feature","properties":{"codesPostaux":["41240"],"population":428,"nom":"Autainville","code":"41006"},"geometry":{"type":"Point","coordinates":[1.4242348039215689,47.88838549019606]}}]}