{"type":"FeatureCollection","features":[{"type":"Feature","properties":{"codesPostaux":["41270"],"population":189,"nom":"Boursay","code":"41024"},"geometry":{"type":"Point","coordinates":[0.9899266183574877,48.01737101449277]}}]}