{"type":"FeatureCollection","features":[{"type":"Feature","properties":{"codesPostaux":["41320"],"population":422,"nom":"La Chapelle-Montmartin","code":"41038"},"geometry":{"type":"Point","coordinates":[1.7590931081081076,47.25282635135136]}}]}