{"type":"FeatureCollection","features":[{"type":"Feature","properties":{"codesPostaux":["41120"],"population":2489,"nom":"Cellettes","code":"41031"},"geometry":{"type":"Point","coordinates":[1.390310731707317,47.51584463414635]}}]}