{"type":"FeatureCollection","features":[{"type":"Feature","properties":{"codesPostaux":["41320"],"population":1110,"nom":"Ch\u00e2tres-sur-Cher","code":"41044"},"geometry":{"type":"Point","coordinates":[1.9344098701298706,47.29708116883115]}}]}