{"type":"FeatureCollection","features":[{"type":"Feature","properties":{"codesPostaux":["41700"],"population":3530,"nom":"Contres","code":"41059"},"geometry":{"type":"Point","coordinates":[1.4049573846153838,47.415008205128174]}}]}