{"type":"FeatureCollection","features":[{"type":"Feature","properties":{"codesPostaux":["41700"],"population":336,"nom":"Choussy","code":"41054"},"geometry":{"type":"Point","coordinates":[1.347886310679611,47.36034601941745]}}]}