{"type":"FeatureCollection","features":[{"type":"Feature","properties":{"codesPostaux":["41230"],"population":519,"nom":"Courmemin","code":"41068"},"geometry":{"type":"Point","coordinates":[1.6310734426229503,47.475153606557384]}}]}