{"type":"FeatureCollection","features":[{"type":"Feature","properties":{"codesPostaux":["41160"],"population":1136,"nom":"Fr\u00e9teval","code":"41095"},"geometry":{"type":"Point","coordinates":[1.2088072357723574,47.88660081300813]}}]}