{"type":"FeatureCollection","features":[{"type":"Feature","properties":{"codesPostaux":["41190"],"population":287,"nom":"Fran\u00e7ay","code":"41093"},"geometry":{"type":"Point","coordinates":[1.1080866412213741,47.62133366412213]}}]}