{"type":"FeatureCollection","features":[{"type":"Feature","properties":{"codesPostaux":["41120"],"population":811,"nom":"Foug\u00e8res-sur-Bi\u00e8vre","code":"41092"},"geometry":{"type":"Point","coordinates":[1.3366140869565213,47.44839391304347]}}]}