{"type":"FeatureCollection","features":[{"type":"Feature","properties":{"codesPostaux":["41190"],"population":128,"nom":"Lanc\u00f4me","code":"41108"},"geometry":{"type":"Point","coordinates":[1.1249440952380956,47.65180885714285]}}]}