{"type":"FeatureCollection","features":[{"type":"Feature","properties":{"codesPostaux":["41800"],"population":190,"nom":"Les Hayes","code":"41100"},"geometry":{"type":"Point","coordinates":[0.7760076190476188,47.698112095238095]}}]}