{"type":"FeatureCollection","features":[{"type":"Feature","properties":{"codesPostaux":["41230"],"population":252,"nom":"Lassay-sur-Croisne","code":"41112"},"geometry":{"type":"Point","coordinates":[1.6322183064516127,47.37277137096776]}}]}