{"type":"FeatureCollection","features":[{"type":"Feature","properties":{"codesPostaux":["41250"],"population":742,"nom":"Maslives","code":"41129"},"geometry":{"type":"Point","coordinates":[1.4845883050847457,47.63891050847459]}}]}