{"type":"FeatureCollection","features":[{"type":"Feature","properties":{"codesPostaux":["41360"],"population":1284,"nom":"Lunay","code":"41120"},"geometry":{"type":"Point","coordinates":[0.9115417365269461,47.80194041916167]}}]}