{"type":"FeatureCollection","features":[{"type":"Feature","properties":{"codesPostaux":["41200"],"population":752,"nom":"Millan\u00e7ay","code":"41140"},"geometry":{"type":"Point","coordinates":[1.7850165948275878,47.4561775862069]}}]}