{"type":"FeatureCollection","features":[{"type":"Feature","properties":{"codesPostaux":["41230"],"population":1501,"nom":"Mur-de-Sologne","code":"41157"},"geometry":{"type":"Point","coordinates":[1.6035591769547324,47.40869123456791]}}]}