{"type":"FeatureCollection","features":[{"type":"Feature","properties":{"codesPostaux":["41250"],"population":317,"nom":"Neuvy","code":"41160"},"geometry":{"type":"Point","coordinates":[1.5947339823008855,47.56253557522125]}}]}