{"type":"FeatureCollection","features":[{"type":"Feature","properties":{"codesPostaux":["41400"],"population":1513,"nom":"Pontlevoy","code":"41180"},"geometry":{"type":"Point","coordinates":[1.234494042553191,47.39688010638298]}}]}