{"type":"FeatureCollection","features":[{"type":"Feature","properties":{"codesPostaux":["41370"],"population":71,"nom":"Roches","code":"41191"},"geometry":{"type":"Point","coordinates":[1.4506766666666666,47.79910087719299]}}]}