{"type":"FeatureCollection","features":[{"type":"Feature","properties":{"codesPostaux":["41100"],"population":867,"nom":"Saint-Firmin-des-Pr\u00e9s","code":"41209"},"geometry":{"type":"Point","coordinates":[1.1072997860962566,47.83996743315507]}}]}