{"type":"FeatureCollection","features":[{"type":"Feature","properties":{"codesPostaux":["41330"],"population":504,"nom":"Saint-Bohaire","code":"41203"},"geometry":{"type":"Point","coordinates":[1.242005563909774,47.64754082706769]}}]}