{"type":"FeatureCollection","features":[{"type":"Feature","properties":{"codesPostaux":["41400"],"population":746,"nom":"Saint-Julien-de-Ch\u00e9don","code":"41217"},"geometry":{"type":"Point","coordinates":[1.2066836458333334,47.31636364583334]}}]}