{"type":"FeatureCollection","features":[{"type":"Feature","properties":{"codesPostaux":["41320"],"population":373,"nom":"Saint-Loup","code":"41222"},"geometry":{"type":"Point","coordinates":[1.830649545454545,47.26295852272727]}}]}