{"type":"FeatureCollection","features":[{"type":"Feature","properties":{"codesPostaux":["41310"],"population":106,"nom":"Sasni\u00e8res","code":"41236"},"geometry":{"type":"Point","coordinates":[0.9244896396396395,47.7246884684685]}}]}