{"type":"FeatureCollection","features":[{"type":"Feature","properties":{"codesPostaux":["41170"],"population":175,"nom":"Le Temple","code":"41254"},"geometry":{"type":"Point","coordinates":[0.9346404166666668,47.92943864583336]}}]}