{"type":"FeatureCollection","features":[{"type":"Feature","properties":{"codesPostaux":["41220"],"population":421,"nom":"Thoury","code":"41260"},"geometry":{"type":"Point","coordinates":[1.6103456818181814,47.61886784090911]}}]}