{"type":"FeatureCollection","features":[{"type":"Feature","properties":{"codesPostaux":["41220"],"population":459,"nom":"Villeny","code":"41285"},"geometry":{"type":"Point","coordinates":[1.7465160683760685,47.613517264957274]}}]}