{"type":"FeatureCollection","features":[{"type":"Feature","properties":{"codesPostaux":["42130"],"population":148,"nom":"Ailleux","code":"42002"},"geometry":{"type":"Point","coordinates":[3.93311789473684,45.79855631578949]}}]}