{"type":"FeatureCollection","features":[{"type":"Feature","properties":{"codesPostaux":["42820"],"population":1837,"nom":"Ambierle","code":"42003"},"geometry":{"type":"Point","coordinates":[3.8955689189189178,46.10588250000003]}}]}