{"type":"FeatureCollection","features":[{"type":"Feature","properties":{"codesPostaux":["42660"],"population":417,"nom":"Le Bessat","code":"42017"},"geometry":{"type":"Point","coordinates":[4.519466329113922,45.371842405063305]}}]}