{"type":"FeatureCollection","features":[{"type":"Feature","properties":{"codesPostaux":["42130"],"population":3239,"nom":"Bo\u00ebn-sur-Lignon","code":"42019"},"geometry":{"type":"Point","coordinates":[4.004827912087913,45.75018076923078]}}]}