{"type":"FeatureCollection","features":[{"type":"Feature","properties":{"codesPostaux":["42210"],"population":1996,"nom":"Bellegarde-en-Forez","code":"42013"},"geometry":{"type":"Point","coordinates":[4.312956575342465,45.64376267123287]}}]}