{"type":"FeatureCollection","features":[{"type":"Feature","properties":{"codesPostaux":["42220"],"population":2933,"nom":"Bourg-Argental","code":"42023"},"geometry":{"type":"Point","coordinates":[4.562888372093023,45.30582681063123]}}]}