{"type":"FeatureCollection","features":[{"type":"Feature","properties":{"codesPostaux":["42140"],"population":127,"nom":"Ch\u00e2telus","code":"42055"},"geometry":{"type":"Point","coordinates":[4.461583152173912,45.58882576086956]}}]}