{"type":"FeatureCollection","features":[{"type":"Feature","properties":{"codesPostaux":["42114"],"population":387,"nom":"Chirassimont","code":"42063"},"geometry":{"type":"Point","coordinates":[4.285755955882354,45.913562794117674]}}]}