{"type":"FeatureCollection","features":[{"type":"Feature","properties":{"codesPostaux":["42430"],"population":487,"nom":"Cherier","code":"42061"},"geometry":{"type":"Point","coordinates":[3.8776319796954306,45.96715071065994]}}]}