{"type":"FeatureCollection","features":[{"type":"Feature","properties":{"codesPostaux":["42123"],"population":901,"nom":"Cordelle","code":"42070"},"geometry":{"type":"Point","coordinates":[4.061960625000001,45.94367795454547]}}]}