{"type":"FeatureCollection","features":[{"type":"Feature","properties":{"codesPostaux":["42110"],"population":682,"nom":"\u00c9percieux-Saint-Paul","code":"42088"},"geometry":{"type":"Point","coordinates":[4.2016450561797765,45.78876651685394]}}]}