{"type":"FeatureCollection","features":[{"type":"Feature","properties":{"codesPostaux":["42140"],"population":663,"nom":"Fontan\u00e8s","code":"42096"},"geometry":{"type":"Point","coordinates":[4.4282736708860755,45.54263329113921]}}]}