{"type":"FeatureCollection","features":[{"type":"Feature","properties":{"codesPostaux":["42140"],"population":287,"nom":"La Gimond","code":"42100"},"geometry":{"type":"Point","coordinates":[4.4110242647058815,45.55357705882352]}}]}