{"type":"FeatureCollection","features":[{"type":"Feature","properties":{"codesPostaux":["42260"],"population":152,"nom":"Lur\u00e9","code":"42125"},"geometry":{"type":"Point","coordinates":[3.9293121348314575,45.88269651685393]}}]}