{"type":"FeatureCollection","features":[{"type":"Feature","properties":{"codesPostaux":["42130"],"population":1345,"nom":"Marcilly-le-Ch\u00e2tel","code":"42134"},"geometry":{"type":"Point","coordinates":[4.023804397590357,45.68574144578312]}}]}