{"type":"FeatureCollection","features":[{"type":"Feature","properties":{"codesPostaux":["42560"],"population":418,"nom":"Marols","code":"42140"},"geometry":{"type":"Point","coordinates":[4.0459963541666575,45.471639479166654]}}]}