{"type":"FeatureCollection","features":[{"type":"Feature","properties":{"codesPostaux":["42600"],"population":405,"nom":"Mornand-en-Forez","code":"42151"},"geometry":{"type":"Point","coordinates":[4.116964545454548,45.67876285714287]}}]}