{"type":"FeatureCollection","features":[{"type":"Feature","properties":{"codesPostaux":["42410"],"population":360,"nom":"Pavezin","code":"42167"},"geometry":{"type":"Point","coordinates":[4.662320618556699,45.47267855670104]}}]}