{"type":"FeatureCollection","features":[{"type":"Feature","properties":{"codesPostaux":["42110"],"population":1218,"nom":"Pouilly-l\u00e8s-Feurs","code":"42175"},"geometry":{"type":"Point","coordinates":[4.235837741935486,45.796748145161295]}}]}