{"type":"FeatureCollection","features":[{"type":"Feature","properties":{"codesPostaux":["42600"],"population":878,"nom":"Pralong","code":"42179"},"geometry":{"type":"Point","coordinates":[4.010036065573771,45.65948704918031]}}]}