{"type":"FeatureCollection","features":[{"type":"Feature","properties":{"codesPostaux":["42590"],"population":274,"nom":"Pinay","code":"42171"},"geometry":{"type":"Point","coordinates":[4.133809015151516,45.8711162878788]}}]}