{"type":"FeatureCollection","features":[{"type":"Feature","properties":{"codesPostaux":["42810"],"population":1407,"nom":"Rozier-en-Donzy","code":"42193"},"geometry":{"type":"Point","coordinates":[4.276059337748344,45.80350649006624]}}]}