{"type":"FeatureCollection","features":[{"type":"Feature","properties":{"codesPostaux":["42320"],"population":1838,"nom":"Saint-Christo-en-Jarez","code":"42208"},"geometry":{"type":"Point","coordinates":[4.470060424242424,45.539969696969706]}}]}