{"type":"FeatureCollection","features":[{"type":"Feature","properties":{"codesPostaux":["42210"],"population":930,"nom":"Saint-Cyr-les-Vignes","code":"42214"},"geometry":{"type":"Point","coordinates":[4.293044055555555,45.67619966666667]}}]}