{"type":"FeatureCollection","features":[{"type":"Feature","properties":{"codesPostaux":["42670"],"population":239,"nom":"Saint-Germain-la-Montagne","code":"42229"},"geometry":{"type":"Point","coordinates":[4.3885730370370375,46.19633111111109]}}]}