{"type":"FeatureCollection","features":[{"type":"Feature","properties":{"codesPostaux":["42440"],"population":341,"nom":"Saint-Jean-la-V\u00eatre","code":"42238"},"geometry":{"type":"Point","coordinates":[3.792696684782609,45.7798392391304]}}]}