{"type":"FeatureCollection","features":[{"type":"Feature","properties":{"codesPostaux":["42220"],"population":1235,"nom":"Saint-Julien-Molin-Molette","code":"42246"},"geometry":{"type":"Point","coordinates":[4.614413783783782,45.31633304054052]}}]}