{"type":"FeatureCollection","features":[{"type":"Feature","properties":{"codesPostaux":["42130"],"population":242,"nom":"Saint-Laurent-Rochefort","code":"42252"},"geometry":{"type":"Point","coordinates":[3.904822222222221,45.77561722222224]}}]}