{"type":"FeatureCollection","features":[{"type":"Feature","properties":{"codesPostaux":["42210"],"population":611,"nom":"Saint-Laurent-la-Conche","code":"42251"},"geometry":{"type":"Point","coordinates":[4.231964528301886,45.68550820754716]}}]}