{"type":"FeatureCollection","features":[{"type":"Feature","properties":{"codesPostaux":["42620"],"population":883,"nom":"Saint-Martin-d'Estr\u00e9aux","code":"42257"},"geometry":{"type":"Point","coordinates":[3.8275078277153534,46.20936247191008]}}]}