{"type":"FeatureCollection","features":[{"type":"Feature","properties":{"codesPostaux":["42590"],"population":338,"nom":"Saint-Priest-la-Roche","code":"42277"},"geometry":{"type":"Point","coordinates":[4.107801801242238,45.91851155279505]}}]}