{"type":"FeatureCollection","features":[{"type":"Feature","properties":{"codesPostaux":["42270"],"population":6125,"nom":"Saint-Priest-en-Jarez","code":"42275"},"geometry":{"type":"Point","coordinates":[4.3727716470588245,45.473911647058834]}}]}