{"type":"FeatureCollection","features":[{"type":"Feature","properties":{"codesPostaux":["42240"],"population":1345,"nom":"Saint-Paul-en-Cornillon","code":"42270"},"geometry":{"type":"Point","coordinates":[4.241246029411764,45.3962925]}}]}