{"type":"FeatureCollection","features":[{"type":"Feature","properties":{"codesPostaux":["42660"],"population":379,"nom":"Saint-R\u00e9gis-du-Coin","code":"42280"},"geometry":{"type":"Point","coordinates":[4.457269715909093,45.28618630681819]}}]}