{"type":"FeatureCollection","features":[{"type":"Feature","properties":{"codesPostaux":["42600"],"population":589,"nom":"Saint-Thomas-la-Garde","code":"42290"},"geometry":{"type":"Point","coordinates":[4.081847407407408,45.569596481481476]}}]}