{"type":"FeatureCollection","features":[{"type":"Feature","properties":{"codesPostaux":["42260"],"population":295,"nom":"Souternon","code":"42303"},"geometry":{"type":"Point","coordinates":[3.993821015228425,45.87555467005077]}}]}