{"type":"FeatureCollection","features":[{"type":"Feature","properties":{"codesPostaux":["42380"],"population":563,"nom":"La Tourette","code":"42312"},"geometry":{"type":"Point","coordinates":[4.0847216374269,45.424459239766094]}}]}