{"type":"FeatureCollection","features":[{"type":"Feature","properties":{"codesPostaux":["42830"],"population":280,"nom":"La Tuili\u00e8re","code":"42314"},"geometry":{"type":"Point","coordinates":[3.8148167586206885,45.96051620689655]}}]}