{"type":"FeatureCollection","features":[{"type":"Feature","properties":{"codesPostaux":["42220"],"population":364,"nom":"La Versanne","code":"42329"},"geometry":{"type":"Point","coordinates":[4.516520285714286,45.321212142857135]}}]}