{"type":"FeatureCollection","features":[{"type":"Feature","properties":{"codesPostaux":["42111"],"population":117,"nom":"La Valla-sur-Rochefort","code":"42321"},"geometry":{"type":"Point","coordinates":[3.846873720930233,45.756825058139555]}}]}