{"type":"FeatureCollection","features":[{"type":"Feature","properties":{"codesPostaux":["42140"],"population":614,"nom":"Virigneux","code":"42336"},"geometry":{"type":"Point","coordinates":[4.34792881889764,45.685747480314966]}}]}