{"type":"FeatureCollection","features":[{"type":"Feature","properties":{"codesPostaux":["43700"],"population":1241,"nom":"Arsac-en-Velay","code":"43010"},"geometry":{"type":"Point","coordinates":[3.9542797975708517,44.99343838056678]}}]}