{"type":"FeatureCollection","features":[{"type":"Feature","properties":{"codesPostaux":["43300"],"population":337,"nom":"Vissac-Auteyrac","code":"43013"},"geometry":{"type":"Point","coordinates":[3.6194819064748187,45.11574586330932]}}]}