{"type":"FeatureCollection","features":[{"type":"Feature","properties":{"codesPostaux":["43340"],"population":78,"nom":"Barges","code":"43019"},"geometry":{"type":"Point","coordinates":[3.899015942028984,44.836474420289875]}}]}