{"type":"FeatureCollection","features":[{"type":"Feature","properties":{"codesPostaux":["43590"],"population":2805,"nom":"Beauzac","code":"43025"},"geometry":{"type":"Point","coordinates":[4.0886370676691755,45.25546578947368]}}]}