{"type":"FeatureCollection","features":[{"type":"Feature","properties":{"codesPostaux":["43100"],"population":276,"nom":"Beaumont","code":"43022"},"geometry":{"type":"Point","coordinates":[3.3298432307692347,45.31027974358976]}}]}