{"type":"FeatureCollection","features":[{"type":"Feature","properties":{"codesPostaux":["43450"],"population":615,"nom":"Blesle","code":"43033"},"geometry":{"type":"Point","coordinates":[3.169864987654321,45.31762501234566]}}]}