{"type":"FeatureCollection","features":[{"type":"Feature","properties":{"codesPostaux":["43510"],"population":267,"nom":"Le Bouchet-Saint-Nicolas","code":"43037"},"geometry":{"type":"Point","coordinates":[3.783746702702702,44.88419708108107]}}]}