{"type":"FeatureCollection","features":[{"type":"Feature","properties":{"codesPostaux":["43120"],"population":941,"nom":"La Chapelle-d'Aurec","code":"43058"},"geometry":{"type":"Point","coordinates":[4.198084970059878,45.33005131736529]}}]}