{"type":"FeatureCollection","features":[{"type":"Feature","properties":{"codesPostaux":["43700"],"population":783,"nom":"Chaspinhac","code":"43061"},"geometry":{"type":"Point","coordinates":[3.9328631627906954,45.08771502325577]}}]}