{"type":"FeatureCollection","features":[{"type":"Feature","properties":{"codesPostaux":["43500"],"population":2192,"nom":"Craponne-sur-Arzon","code":"43080"},"geometry":{"type":"Point","coordinates":[3.8438271394799037,45.33463106382976]}}]}