{"type":"FeatureCollection","features":[{"type":"Feature","properties":{"codesPostaux":["43170"],"population":144,"nom":"Cubelles","code":"43083"},"geometry":{"type":"Point","coordinates":[3.5636098113207555,44.997053396226434]}}]}