{"type":"FeatureCollection","features":[{"type":"Feature","properties":{"codesPostaux":["43300"],"population":82,"nom":"Ferrussac","code":"43094"},"geometry":{"type":"Point","coordinates":[3.406850942760941,45.083973535353564]}}]}