{"type":"FeatureCollection","features":[{"type":"Feature","properties":{"codesPostaux":["43100"],"population":199,"nom":"Javaugues","code":"43105"},"geometry":{"type":"Point","coordinates":[3.492234959349594,45.29251756097562]}}]}