{"type":"FeatureCollection","features":[{"type":"Feature","properties":{"codesPostaux":["43440"],"population":64,"nom":"Laval-sur-Doulon","code":"43116"},"geometry":{"type":"Point","coordinates":[3.563699461077843,45.35177041916167]}}]}