{"type":"FeatureCollection","features":[{"type":"Feature","properties":{"codesPostaux":["43380"],"population":285,"nom":"Lavo\u00fbte-Chilhac","code":"43118"},"geometry":{"type":"Point","coordinates":[3.4091393478260854,45.15605760869564]}}]}