{"type":"FeatureCollection","features":[{"type":"Feature","properties":{"codesPostaux":["43100"],"population":855,"nom":"Lamothe","code":"43110"},"geometry":{"type":"Point","coordinates":[3.4333213875598108,45.316991052631614]}}]}