{"type":"FeatureCollection","features":[{"type":"Feature","properties":{"codesPostaux":["43260"],"population":138,"nom":"Montusclat","code":"43143"},"geometry":{"type":"Point","coordinates":[4.110765555555556,45.007275185185186]}}]}