{"type":"FeatureCollection","features":[{"type":"Feature","properties":{"codesPostaux":["43300"],"population":67,"nom":"Prades","code":"43155"},"geometry":{"type":"Point","coordinates":[3.5963988961038966,45.02475603896105]}}]}