{"type":"FeatureCollection","features":[{"type":"Feature","properties":{"codesPostaux":["43330"],"population":1979,"nom":"Pont-Salomon","code":"43153"},"geometry":{"type":"Point","coordinates":[4.24512580882353,45.33383816176469]}}]}