{"type":"FeatureCollection","features":[{"type":"Feature","properties":{"codesPostaux":["43420"],"population":602,"nom":"Pradelles","code":"43154"},"geometry":{"type":"Point","coordinates":[3.866758476821193,44.759246688741754]}}]}