{"type":"FeatureCollection","features":[{"type":"Feature","properties":{"codesPostaux":["43800"],"population":1526,"nom":"Rosi\u00e8res","code":"43165"},"geometry":{"type":"Point","coordinates":[4.005212765957442,45.1304596099291]}}]}