{"type":"FeatureCollection","features":[{"type":"Feature","properties":{"codesPostaux":["43370"],"population":960,"nom":"Saint-Christophe-sur-Dolaison","code":"43174"},"geometry":{"type":"Point","coordinates":[3.8295180341880326,44.992778931623945]}}]}