{"type":"FeatureCollection","features":[{"type":"Feature","properties":{"codesPostaux":["43550"],"population":435,"nom":"Saint-Front","code":"43186"},"geometry":{"type":"Point","coordinates":[4.133168880778588,44.97531394160581]}}]}