{"type":"FeatureCollection","features":[{"type":"Feature","properties":{"codesPostaux":["43350"],"population":308,"nom":"Saint-Geneys-pr\u00e8s-Saint-Paulien","code":"43187"},"geometry":{"type":"Point","coordinates":[3.833166381909549,45.17839929648244]}}]}