{"type":"FeatureCollection","features":[{"type":"Feature","properties":{"codesPostaux":["43360"],"population":251,"nom":"Saint-G\u00e9ron","code":"43191"},"geometry":{"type":"Point","coordinates":[3.296338775510205,45.33234768707484]}}]}