{"type":"FeatureCollection","features":[{"type":"Feature","properties":{"codesPostaux":["43100"],"population":247,"nom":"Saint-Laurent-Chabreuges","code":"43207"},"geometry":{"type":"Point","coordinates":[3.3482663499999994,45.2784221]}}]}