{"type":"FeatureCollection","features":[{"type":"Feature","properties":{"codesPostaux":["43420"],"population":207,"nom":"Saint-Paul-de-Tartas","code":"43215"},"geometry":{"type":"Point","coordinates":[3.8959347547169796,44.79848064150947]}}]}