{"type":"FeatureCollection","features":[{"type":"Feature","properties":{"codesPostaux":["43350"],"population":2406,"nom":"Saint-Paulien","code":"43216"},"geometry":{"type":"Point","coordinates":[3.8143827793696228,45.13509421203445]}}]}