{"type":"FeatureCollection","features":[{"type":"Feature","properties":{"codesPostaux":["43450"],"population":72,"nom":"Torsiac","code":"43247"},"geometry":{"type":"Point","coordinates":[3.195066918604651,45.3506666860465]}}]}