{"type":"FeatureCollection","features":[{"type":"Feature","properties":{"codesPostaux":["43390"],"population":568,"nom":"V\u00e9z\u00e9zoux","code":"43261"},"geometry":{"type":"Point","coordinates":[3.3449270967741933,45.40507548387095]}}]}