{"type":"FeatureCollection","features":[{"type":"Feature","properties":{"codesPostaux":["44170"],"population":1984,"nom":"Abbaretz","code":"44001"},"geometry":{"type":"Point","coordinates":[-1.4944954822335017,47.55254263959393]}}]}