{"type":"FeatureCollection","features":[{"type":"Feature","properties":{"codesPostaux":["44115"],"population":8361,"nom":"Basse-Goulaine","code":"44009"},"geometry":{"type":"Point","coordinates":[-1.460538016528926,47.207485041322315]}}]}