{"type":"FeatureCollection","features":[{"type":"Feature","properties":{"codesPostaux":["44160"],"population":2819,"nom":"Besn\u00e9","code":"44013"},"geometry":{"type":"Point","coordinates":[-2.0770979710144926,47.38456536231883]}}]}