{"type":"FeatureCollection","features":[{"type":"Feature","properties":{"codesPostaux":["44130"],"population":3018,"nom":"Bouvron","code":"44023"},"geometry":{"type":"Point","coordinates":[-1.872158819444444,47.415351840277786]}}]}