{"type":"FeatureCollection","features":[{"type":"Feature","properties":{"codesPostaux":["44750"],"population":3904,"nom":"Campbon","code":"44025"},"geometry":{"type":"Point","coordinates":[-1.9611371331058018,47.420637576791776]}}]}