{"type":"FeatureCollection","features":[{"type":"Feature","properties":{"codesPostaux":["44260"],"population":2810,"nom":"La Chapelle-Launay","code":"44033"},"geometry":{"type":"Point","coordinates":[-1.9788309359605927,47.35746847290643]}}]}