{"type":"FeatureCollection","features":[{"type":"Feature","properties":{"codesPostaux":["44560"],"population":2710,"nom":"Corsept","code":"44046"},"geometry":{"type":"Point","coordinates":[-2.0966185365853667,47.26046646341464]}}]}