{"type":"FeatureCollection","features":[{"type":"Feature","properties":{"codesPostaux":["44520"],"population":807,"nom":"Grand-Auvern\u00e9","code":"44065"},"geometry":{"type":"Point","coordinates":[-1.3108622839506177,47.579283888888874]}}]}