{"type":"FeatureCollection","features":[{"type":"Feature","properties":{"codesPostaux":["44115"],"population":5572,"nom":"Haute-Goulaine","code":"44071"},"geometry":{"type":"Point","coordinates":[-1.41851785046729,47.19647822429905]}}]}