{"type":"FeatureCollection","features":[{"type":"Feature","properties":{"codesPostaux":["44810"],"population":5661,"nom":"H\u00e9ric","code":"44073"},"geometry":{"type":"Point","coordinates":[-1.6464807911392407,47.42356537974682]}}]}