{"type":"FeatureCollection","features":[{"type":"Feature","properties":{"codesPostaux":["44590"],"population":1026,"nom":"Lusanger","code":"44086"},"geometry":{"type":"Point","coordinates":[-1.5869156296296296,47.67563222222225]}}]}