{"type":"FeatureCollection","features":[{"type":"Feature","properties":{"codesPostaux":["44260"],"population":750,"nom":"Lavau-sur-Loire","code":"44080"},"geometry":{"type":"Point","coordinates":[-1.954301512605042,47.32664697478991]}}]}