{"type":"FeatureCollection","features":[{"type":"Feature","properties":{"codesPostaux":["44370"],"population":864,"nom":"Montrelais","code":"44104"},"geometry":{"type":"Point","coordinates":[-0.9744839999999999,47.405471000000006]}}]}