{"type":"FeatureCollection","features":[{"type":"Feature","properties":{"codesPostaux":["44130"],"population":2012,"nom":"Notre-Dame-des-Landes","code":"44111"},"geometry":{"type":"Point","coordinates":[-1.7242178651685396,47.38507056179774]}}]}