{"type":"FeatureCollection","features":[{"type":"Feature","properties":{"codesPostaux":["44560"],"population":3260,"nom":"Paimb\u0153uf","code":"44116"},"geometry":{"type":"Point","coordinates":[-2.0274506060606057,47.28560939393939]}}]}