{"type":"FeatureCollection","features":[{"type":"Feature","properties":{"codesPostaux":["44860"],"population":5640,"nom":"Pont-Saint-Martin","code":"44130"},"geometry":{"type":"Point","coordinates":[-1.564660714285714,47.12893650000001]}}]}