{"type":"FeatureCollection","features":[{"type":"Feature","properties":{"codesPostaux":["44430"],"population":1241,"nom":"La Remaudi\u00e8re","code":"44141"},"geometry":{"type":"Point","coordinates":[-1.2214806437768255,47.22790068669525]}}]}