{"type":"FeatureCollection","features":[{"type":"Feature","properties":{"codesPostaux":["44117"],"population":5883,"nom":"Saint-Andr\u00e9-des-Eaux","code":"44151"},"geometry":{"type":"Point","coordinates":[-2.3053199382716048,47.325561543209886]}}]}