{"type":"FeatureCollection","features":[{"type":"Feature","properties":{"codesPostaux":["44690"],"population":1147,"nom":"Saint-Fiacre-sur-Maine","code":"44159"},"geometry":{"type":"Point","coordinates":[-1.418217868852459,47.14392344262296]}}]}