{"type":"FeatureCollection","features":[{"type":"Feature","properties":{"codesPostaux":["44720"],"population":3917,"nom":"Saint-Joachim","code":"44168"},"geometry":{"type":"Point","coordinates":[-2.255492389380534,47.36444274336285]}}]}