{"type":"FeatureCollection","features":[{"type":"Feature","properties":{"codesPostaux":["44410"],"population":4482,"nom":"Saint-Lyphard","code":"44175"},"geometry":{"type":"Point","coordinates":[-2.339500037593986,47.374619398496264]}}]}