{"type":"FeatureCollection","features":[{"type":"Feature","properties":{"codesPostaux":["44710"],"population":1602,"nom":"Saint-L\u00e9ger-les-Vignes","code":"44171"},"geometry":{"type":"Point","coordinates":[-1.7125843243243248,47.14294256756757]}}]}