{"type":"FeatureCollection","features":[{"type":"Feature","properties":{"codesPostaux":["44680"],"population":2587,"nom":"Saint-Mars-de-Coutais","code":"44178"},"geometry":{"type":"Point","coordinates":[-1.7482584864864865,47.075995351351345]}}]}