{"type":"FeatureCollection","features":[{"type":"Feature","properties":{"codesPostaux":["44590"],"population":1678,"nom":"Sion-les-Mines","code":"44197"},"geometry":{"type":"Point","coordinates":[-1.5755288498402562,47.729795910543125]}}]}