{"type":"FeatureCollection","features":[{"type":"Feature","properties":{"codesPostaux":["44110"],"population":1983,"nom":"Soudan","code":"44199"},"geometry":{"type":"Point","coordinates":[-1.2918794067796606,47.73323292372883]}}]}