{"type":"FeatureCollection","features":[{"type":"Feature","properties":{"codesPostaux":["44170"],"population":2047,"nom":"Vay","code":"44214"},"geometry":{"type":"Point","coordinates":[-1.7048221164021164,47.53575624338623]}}]}