{"type":"FeatureCollection","features":[{"type":"Feature","properties":{"codesPostaux":["44110"],"population":663,"nom":"Villepot","code":"44218"},"geometry":{"type":"Point","coordinates":[-1.2790446892655363,47.764406327683616]}}]}