{"type":"FeatureCollection","features":[{"type":"Feature","properties":{"codesPostaux":["45130"],"population":715,"nom":"Baccon","code":"45019"},"geometry":{"type":"Point","coordinates":[1.6362486486486496,47.88647531531532]}}]}