{"type":"FeatureCollection","features":[{"type":"Feature","properties":{"codesPostaux":["45170"],"population":215,"nom":"Attray","code":"45011"},"geometry":{"type":"Point","coordinates":[2.131501818181818,48.117305252525256]}}]}