{"type":"FeatureCollection","features":[{"type":"Feature","properties":{"codesPostaux":["45130"],"population":2044,"nom":"Baule","code":"45024"},"geometry":{"type":"Point","coordinates":[1.6665999999999999,47.8112228]}}]}