{"type":"FeatureCollection","features":[{"type":"Feature","properties":{"codesPostaux":["45340"],"population":1986,"nom":"Beaune-la-Rolande","code":"45030"},"geometry":{"type":"Point","coordinates":[2.4325007272727275,48.07430045454546]}}]}