{"type":"FeatureCollection","features":[{"type":"Feature","properties":{"codesPostaux":["45480"],"population":450,"nom":"Boisseaux","code":"45037"},"geometry":{"type":"Point","coordinates":[1.9831154285714288,48.25288128571428]}}]}