{"type":"FeatureCollection","features":[{"type":"Feature","properties":{"codesPostaux":["45460"],"population":1846,"nom":"Les Bordes","code":"45042"},"geometry":{"type":"Point","coordinates":[2.4177368852459016,47.807641639344254]}}]}