{"type":"FeatureCollection","features":[{"type":"Feature","properties":{"codesPostaux":["45250"],"population":74,"nom":"Breteau","code":"45052"},"geometry":{"type":"Point","coordinates":[2.890293417721518,47.676741392405084]}}]}