{"type":"FeatureCollection","features":[{"type":"Feature","properties":{"codesPostaux":["45140"],"population":199,"nom":"Bucy-Saint-Liphard","code":"45059"},"geometry":{"type":"Point","coordinates":[1.7465720253164552,47.93572835443037]}}]}