{"type":"FeatureCollection","features":[{"type":"Feature","properties":{"codesPostaux":["45340"],"population":934,"nom":"Chambon-la-For\u00eat","code":"45069"},"geometry":{"type":"Point","coordinates":[2.291462187500001,48.05561124999999]}}]}