{"type":"FeatureCollection","features":[{"type":"Feature","properties":{"codesPostaux":["45210"],"population":250,"nom":"La Chapelle-Saint-S\u00e9pulcre","code":"45076"},"geometry":{"type":"Point","coordinates":[2.8451916,48.0117074]}}]}