{"type":"FeatureCollection","features":[{"type":"Feature","properties":{"codesPostaux":["45210"],"population":230,"nom":"Chevry-sous-le-Bignon","code":"45094"},"geometry":{"type":"Point","coordinates":[2.896341562500001,48.143987968750004]}}]}