{"type":"FeatureCollection","features":[{"type":"Feature","properties":{"codesPostaux":["45260"],"population":346,"nom":"Coudroy","code":"45107"},"geometry":{"type":"Point","coordinates":[2.4739150793650793,47.90137428571427]}}]}