{"type":"FeatureCollection","features":[{"type":"Feature","properties":{"codesPostaux":["45300"],"population":282,"nom":"Courcelles","code":"45110"},"geometry":{"type":"Point","coordinates":[2.325888333333334,48.09725791666667]}}]}