{"type":"FeatureCollection","features":[{"type":"Feature","properties":{"codesPostaux":["45170"],"population":333,"nom":"Crottes-en-Pithiverais","code":"45118"},"geometry":{"type":"Point","coordinates":[2.067180540540541,48.11427756756757]}}]}