{"type":"FeatureCollection","features":[{"type":"Feature","properties":{"codesPostaux":["45320"],"population":311,"nom":"Foucherolles","code":"45149"},"geometry":{"type":"Point","coordinates":[3.015644698795181,48.09344951807228]}}]}