{"type":"FeatureCollection","features":[{"type":"Feature","properties":{"codesPostaux":["45240"],"population":7219,"nom":"La Fert\u00e9-Saint-Aubin","code":"45146"},"geometry":{"type":"Point","coordinates":[1.9157851666666668,47.70319854761907]}}]}