{"type":"FeatureCollection","features":[{"type":"Feature","properties":{"codesPostaux":["45500"],"population":14624,"nom":"Gien","code":"45155"},"geometry":{"type":"Point","coordinates":[2.6700931372549004,47.70903215686272]}}]}