{"type":"FeatureCollection","features":[{"type":"Feature","properties":{"codesPostaux":["45130"],"population":1663,"nom":"Huisseau-sur-Mauves","code":"45167"},"geometry":{"type":"Point","coordinates":[1.690840522875817,47.88753784313725]}}]}