{"type":"FeatureCollection","features":[{"type":"Feature","properties":{"codesPostaux":["45480"],"population":668,"nom":"Greneville-en-Beauce","code":"45160"},"geometry":{"type":"Point","coordinates":[2.1164679000000004,48.18911309999999]}}]}