{"type":"FeatureCollection","features":[{"type":"Feature","properties":{"codesPostaux":["45140"],"population":8282,"nom":"Ingr\u00e9","code":"45169"},"geometry":{"type":"Point","coordinates":[1.8235978740157477,47.91808826771655]}}]}