{"type":"FeatureCollection","features":[{"type":"Feature","properties":{"codesPostaux":["45210"],"population":179,"nom":"M\u00e9rinville","code":"45201"},"geometry":{"type":"Point","coordinates":[2.946961818181818,48.09385010101012]}}]}