{"type":"FeatureCollection","features":[{"type":"Feature","properties":{"codesPostaux":["45210"],"population":1430,"nom":"Nargis","code":"45222"},"geometry":{"type":"Point","coordinates":[2.7482309523809514,48.105864000000004]}}]}