{"type":"FeatureCollection","features":[{"type":"Feature","properties":{"codesPostaux":["45170"],"population":137,"nom":"Oison","code":"45231"},"geometry":{"type":"Point","coordinates":[1.9778010169491527,48.13360016949153]}}]}