{"type":"FeatureCollection","features":[{"type":"Feature","properties":{"codesPostaux":["45150"],"population":574,"nom":"Ouvrouer-les-Champs","code":"45241"},"geometry":{"type":"Point","coordinates":[2.1759728070175437,47.83223719298245]}}]}