{"type":"FeatureCollection","features":[{"type":"Feature","properties":{"codesPostaux":["45290"],"population":266,"nom":"Ouzouer-des-Champs","code":"45242"},"geometry":{"type":"Point","coordinates":[2.7048556043956054,47.874815934065914]}}]}