{"type":"FeatureCollection","features":[{"type":"Feature","properties":{"codesPostaux":["45260"],"population":245,"nom":"Presnoy","code":"45256"},"geometry":{"type":"Point","coordinates":[2.556898352941176,47.957467411764725]}}]}