{"type":"FeatureCollection","features":[{"type":"Feature","properties":{"codesPostaux":["45360"],"population":290,"nom":"Pierrefitte-\u00e8s-Bois","code":"45251"},"geometry":{"type":"Point","coordinates":[2.7009266906474823,47.512552086330906]}}]}