{"type":"FeatureCollection","features":[{"type":"Feature","properties":{"codesPostaux":["45490"],"population":455,"nom":"Pr\u00e9fontaines","code":"45255"},"geometry":{"type":"Point","coordinates":[2.686026393442623,48.10908032786884]}}]}