{"type":"FeatureCollection","features":[{"type":"Feature","properties":{"codesPostaux":["45470"],"population":1362,"nom":"Rebr\u00e9chien","code":"45261"},"geometry":{"type":"Point","coordinates":[2.0323304,47.991187600000025]}}]}