{"type":"FeatureCollection","features":[{"type":"Feature","properties":{"codesPostaux":["45310"],"population":727,"nom":"Saint-P\u00e9ravy-la-Colombe","code":"45296"},"geometry":{"type":"Point","coordinates":[1.6929398305084744,48.005365593220354]}}]}