{"type":"FeatureCollection","features":[{"type":"Feature","properties":{"codesPostaux":["45210"],"population":1049,"nom":"La Selle-sur-le-Bied","code":"45307"},"geometry":{"type":"Point","coordinates":[2.886216019417477,48.075477766990275]}}]}