{"type":"FeatureCollection","features":[{"type":"Feature","properties":{"codesPostaux":["45770"],"population":15449,"nom":"Saran","code":"45302"},"geometry":{"type":"Point","coordinates":[1.8782982089552236,47.949655820895515]}}]}