{"type":"FeatureCollection","features":[{"type":"Feature","properties":{"codesPostaux":["45510"],"population":2288,"nom":"Tigy","code":"45324"},"geometry":{"type":"Point","coordinates":[2.1842955172413787,47.77948027586206]}}]}