{"type":"FeatureCollection","features":[{"type":"Feature","properties":{"codesPostaux":["45210"],"population":177,"nom":"Thorailles","code":"45322"},"geometry":{"type":"Point","coordinates":[2.8959019354838715,48.02807903225807]}}]}