{"type":"FeatureCollection","features":[{"type":"Feature","properties":{"codesPostaux":["45260"],"population":742,"nom":"Thimory","code":"45321"},"geometry":{"type":"Point","coordinates":[2.592486470588236,47.92500258823531]}}]}