{"type":"FeatureCollection","features":[{"type":"Feature","properties":{"codesPostaux":["45600"],"population":888,"nom":"Viglain","code":"45336"},"geometry":{"type":"Point","coordinates":[2.2944806217616582,47.73006119170986]}}]}