{"type":"FeatureCollection","features":[{"type":"Feature","properties":{"codesPostaux":["45700"],"population":214,"nom":"Villevoques","code":"45343"},"geometry":{"type":"Point","coordinates":[2.624176923076923,48.02746038461539]}}]}