{"type":"FeatureCollection","features":[{"type":"Feature","properties":{"codesPostaux":["45600"],"population":621,"nom":"Villemurlin","code":"45340"},"geometry":{"type":"Point","coordinates":[2.3384945714285723,47.690398357142854]}}]}