{"type":"FeatureCollection","features":[{"type":"Feature","properties":{"codesPostaux":["46600"],"population":405,"nom":"Baladou","code":"46016"},"geometry":{"type":"Point","coordinates":[1.56178809859155,44.922558028169014]}}]}