{"type":"FeatureCollection","features":[{"type":"Feature","properties":{"codesPostaux":["46120"],"population":596,"nom":"Aynac","code":"46012"},"geometry":{"type":"Point","coordinates":[1.8591447598253277,44.787428995633164]}}]}