{"type":"FeatureCollection","features":[{"type":"Feature","properties":{"codesPostaux":["46130"],"population":370,"nom":"Belmont-Bretenoux","code":"46024"},"geometry":{"type":"Point","coordinates":[1.8846964492753628,44.888473260869574]}}]}