{"type":"FeatureCollection","features":[{"type":"Feature","properties":{"codesPostaux":["46160"],"population":211,"nom":"Calvignac","code":"46049"},"geometry":{"type":"Point","coordinates":[1.7842155151515133,44.449363030303005]}}]}