{"type":"FeatureCollection","features":[{"type":"Feature","properties":{"codesPostaux":["46100"],"population":588,"nom":"Cardaillac","code":"46057"},"geometry":{"type":"Point","coordinates":[2.014727714285714,44.68327624489799]}}]}