{"type":"FeatureCollection","features":[{"type":"Feature","properties":{"codesPostaux":["46110"],"population":406,"nom":"Carennac","code":"46058"},"geometry":{"type":"Point","coordinates":[1.7259524000000004,44.91006560000001]}}]}