{"type":"FeatureCollection","features":[{"type":"Feature","properties":{"codesPostaux":["46700"],"population":205,"nom":"Cassagnes","code":"46061"},"geometry":{"type":"Point","coordinates":[1.1315364150943394,44.56409603773583]}}]}