{"type":"FeatureCollection","features":[{"type":"Feature","properties":{"codesPostaux":["46150"],"population":899,"nom":"Catus","code":"46064"},"geometry":{"type":"Point","coordinates":[1.3373500641025637,44.55657653846153]}}]}