{"type":"FeatureCollection","features":[{"type":"Feature","properties":{"codesPostaux":["46500"],"population":106,"nom":"Couzou","code":"46078"},"geometry":{"type":"Point","coordinates":[1.6344978106508885,44.774616568047335]}}]}