{"type":"FeatureCollection","features":[{"type":"Feature","properties":{"codesPostaux":["46110"],"population":397,"nom":"Condat","code":"46074"},"geometry":{"type":"Point","coordinates":[1.6658525471698111,44.99051735849057]}}]}