{"type":"FeatureCollection","features":[{"type":"Feature","properties":{"codesPostaux":["46140"],"population":830,"nom":"Douelle","code":"46088"},"geometry":{"type":"Point","coordinates":[1.3594468367346935,44.46960071428569]}}]}