{"type":"FeatureCollection","features":[{"type":"Feature","properties":{"codesPostaux":["46130"],"population":682,"nom":"Gagnac-sur-C\u00e8re","code":"46117"},"geometry":{"type":"Point","coordinates":[1.8856679888268146,44.93908]}}]}