{"type":"FeatureCollection","features":[{"type":"Feature","properties":{"codesPostaux":["46250"],"population":231,"nom":"Goujounac","code":"46126"},"geometry":{"type":"Point","coordinates":[1.2056490999999996,44.576547900000016]}}]}