{"type":"FeatureCollection","features":[{"type":"Feature","properties":{"codesPostaux":["46200"],"population":280,"nom":"Lacave","code":"46144"},"geometry":{"type":"Point","coordinates":[1.5539665605095547,44.84055503184713]}}]}