{"type":"FeatureCollection","features":[{"type":"Feature","properties":{"codesPostaux":["46120"],"population":1334,"nom":"Lacapelle-Marival","code":"46143"},"geometry":{"type":"Point","coordinates":[1.9360124264705878,44.72922772058822]}}]}