{"type":"FeatureCollection","features":[{"type":"Feature","properties":{"codesPostaux":["46400"],"population":109,"nom":"Ladirat","code":"46146"},"geometry":{"type":"Point","coordinates":[1.9677954705882337,44.823996588235275]}}]}