{"type":"FeatureCollection","features":[{"type":"Feature","properties":{"codesPostaux":["46200"],"population":621,"nom":"Lanzac","code":"46153"},"geometry":{"type":"Point","coordinates":[1.4687928000000006,44.86939249999998]}}]}