{"type":"FeatureCollection","features":[{"type":"Feature","properties":{"codesPostaux":["46120"],"population":947,"nom":"Leyme","code":"46170"},"geometry":{"type":"Point","coordinates":[1.8955216091954026,44.781519712643664]}}]}