{"type":"FeatureCollection","features":[{"type":"Feature","properties":{"codesPostaux":["46350"],"population":253,"nom":"Loupiac","code":"46178"},"geometry":{"type":"Point","coordinates":[1.4722162043795624,44.82513948905111]}}]}