{"type":"FeatureCollection","features":[{"type":"Feature","properties":{"codesPostaux":["46170"],"population":458,"nom":"Lhospitalet","code":"46172"},"geometry":{"type":"Point","coordinates":[1.4242203529411768,44.355422647058816]}}]}