{"type":"FeatureCollection","features":[{"type":"Feature","properties":{"codesPostaux":["46090"],"population":1020,"nom":"Mercu\u00e8s","code":"46191"},"geometry":{"type":"Point","coordinates":[1.3898259139784948,44.498726129032256]}}]}