{"type":"FeatureCollection","features":[{"type":"Feature","properties":{"codesPostaux":["46160"],"population":104,"nom":"Montbrun","code":"46198"},"geometry":{"type":"Point","coordinates":[1.9055192783505155,44.51050567010307]}}]}