{"type":"FeatureCollection","features":[{"type":"Feature","properties":{"codesPostaux":["46700"],"population":343,"nom":"Montcabrier","code":"46199"},"geometry":{"type":"Point","coordinates":[1.0814981395348842,44.550749069767434]}}]}