{"type":"FeatureCollection","features":[{"type":"Feature","properties":{"codesPostaux":["46240"],"population":562,"nom":"Montfaucon","code":"46204"},"geometry":{"type":"Point","coordinates":[1.5654609090909095,44.68713916083919]}}]}