{"type":"FeatureCollection","features":[{"type":"Feature","properties":{"codesPostaux":["46600"],"population":294,"nom":"Montvalent","code":"46208"},"geometry":{"type":"Point","coordinates":[1.6363164285714282,44.87292181818178]}}]}