{"type":"FeatureCollection","features":[{"type":"Feature","properties":{"codesPostaux":["46200"],"population":754,"nom":"Pinsac","code":"46220"},"geometry":{"type":"Point","coordinates":[1.5207287116564414,44.861765889570556]}}]}