{"type":"FeatureCollection","features":[{"type":"Feature","properties":{"codesPostaux":["46500"],"population":267,"nom":"Rignac","code":"46238"},"geometry":{"type":"Point","coordinates":[1.7017776543209875,44.8064701234568]}}]}