{"type":"FeatureCollection","features":[{"type":"Feature","properties":{"codesPostaux":["46120"],"population":211,"nom":"Rueyres","code":"46243"},"geometry":{"type":"Point","coordinates":[1.8551384210526316,44.75289015037595]}}]}