{"type":"FeatureCollection","features":[{"type":"Feature","properties":{"codesPostaux":["46600"],"population":323,"nom":"Saint-Denis-l\u00e8s-Martel","code":"46265"},"geometry":{"type":"Point","coordinates":[1.6566800598802405,44.94058353293413]}}]}