{"type":"FeatureCollection","features":[{"type":"Feature","properties":{"codesPostaux":["46330"],"population":173,"nom":"Saint-Martin-Labouval","code":"46276"},"geometry":{"type":"Point","coordinates":[1.7339200900900904,44.47868243243242]}}]}