{"type":"FeatureCollection","features":[{"type":"Feature","properties":{"codesPostaux":["46400"],"population":407,"nom":"Saint-Jean-Lespinasse","code":"46271"},"geometry":{"type":"Point","coordinates":[1.860662325581395,44.8623358139535]}}]}