{"type":"FeatureCollection","features":[{"type":"Feature","properties":{"codesPostaux":["46100"],"population":194,"nom":"Saint-Perdoux","code":"46288"},"geometry":{"type":"Point","coordinates":[2.0515903225806436,44.6818629032258]}}]}