{"type":"FeatureCollection","features":[{"type":"Feature","properties":{"codesPostaux":["46330"],"population":119,"nom":"Sauliac-sur-C\u00e9l\u00e9","code":"46299"},"geometry":{"type":"Point","coordinates":[1.7184940579710135,44.52396326086958]}}]}