{"type":"FeatureCollection","features":[{"type":"Feature","properties":{"codesPostaux":["46320"],"population":79,"nom":"Sonac","code":"46306"},"geometry":{"type":"Point","coordinates":[1.8603152898550734,44.6964824637681]}}]}