{"type":"FeatureCollection","features":[{"type":"Feature","properties":{"codesPostaux":["46150"],"population":317,"nom":"Th\u00e9dirac","code":"46316"},"geometry":{"type":"Point","coordinates":[1.3271451908396947,44.599229160305356]}}]}