{"type":"FeatureCollection","features":[{"type":"Feature","properties":{"codesPostaux":["47350"],"population":121,"nom":"Agm\u00e9","code":"47002"},"geometry":{"type":"Point","coordinates":[0.33883298701298703,44.48889662337662]}}]}