{"type":"FeatureCollection","features":[{"type":"Feature","properties":{"codesPostaux":["47700"],"population":268,"nom":"Beauziac","code":"47026"},"geometry":{"type":"Point","coordinates":[0.04045697674418606,44.32059453488371]}}]}