{"type":"FeatureCollection","features":[{"type":"Feature","properties":{"codesPostaux":["47200"],"population":1594,"nom":"Beaupuy","code":"47024"},"geometry":{"type":"Point","coordinates":[0.14651234567901245,44.53568444444443]}}]}