{"type":"FeatureCollection","features":[{"type":"Feature","properties":{"codesPostaux":["47300"],"population":3117,"nom":"Bias","code":"47027"},"geometry":{"type":"Point","coordinates":[0.6704317647058824,44.40883023529411]}}]}