{"type":"FeatureCollection","features":[{"type":"Feature","properties":{"codesPostaux":["47700"],"population":4645,"nom":"Casteljaloux","code":"47052"},"geometry":{"type":"Point","coordinates":[0.08575937853107343,44.31360067796611]}}]}