{"type":"FeatureCollection","features":[{"type":"Feature","properties":{"codesPostaux":["47340"],"population":348,"nom":"Castella","code":"47053"},"geometry":{"type":"Point","coordinates":[0.6771097600000001,44.31081143999998]}}]}