{"type":"FeatureCollection","features":[{"type":"Feature","properties":{"codesPostaux":["47320"],"population":2549,"nom":"Clairac","code":"47065"},"geometry":{"type":"Point","coordinates":[0.37369361809045243,44.370502010050245]}}]}