{"type":"FeatureCollection","features":[{"type":"Feature","properties":{"codesPostaux":["47430"],"population":650,"nom":"Caumont-sur-Garonne","code":"47061"},"geometry":{"type":"Point","coordinates":[0.17530555555555558,44.4244997979798]}}]}