{"type":"FeatureCollection","features":[{"type":"Feature","properties":{"codesPostaux":["47130"],"population":812,"nom":"Clermont-Dessous","code":"47066"},"geometry":{"type":"Point","coordinates":[0.45224523809523803,44.25275867724868]}}]}