{"type":"FeatureCollection","features":[{"type":"Feature","properties":{"codesPostaux":["47500"],"population":850,"nom":"Condezaygues","code":"47070"},"geometry":{"type":"Point","coordinates":[0.9073155645161292,44.489813709677414]}}]}