{"type":"FeatureCollection","features":[{"type":"Feature","properties":{"codesPostaux":["47120"],"population":160,"nom":"Esclottes","code":"47089"},"geometry":{"type":"Point","coordinates":[0.1458707272727272,44.714406363636364]}}]}