{"type":"FeatureCollection","features":[{"type":"Feature","properties":{"codesPostaux":["47110"],"population":697,"nom":"Dolmayrac","code":"47081"},"geometry":{"type":"Point","coordinates":[0.5807089743589744,44.35967884615382]}}]}