{"type":"FeatureCollection","features":[{"type":"Feature","properties":{"codesPostaux":["47400"],"population":716,"nom":"Fauguerolles","code":"47094"},"geometry":{"type":"Point","coordinates":[0.24039500000000005,44.444452941176465]}}]}