{"type":"FeatureCollection","features":[{"type":"Feature","properties":{"codesPostaux":["47400"],"population":837,"nom":"Fauillet","code":"47095"},"geometry":{"type":"Point","coordinates":[0.2894621782178218,44.427378118811895]}}]}