{"type":"FeatureCollection","features":[{"type":"Feature","properties":{"codesPostaux":["47220"],"population":365,"nom":"Fals","code":"47092"},"geometry":{"type":"Point","coordinates":[0.68912022556391,44.10499864661654]}}]}