{"type":"FeatureCollection","features":[{"type":"Feature","properties":{"codesPostaux":["47230"],"population":952,"nom":"Feugarolles","code":"47097"},"geometry":{"type":"Point","coordinates":[0.36282726775956287,44.21266923497268]}}]}