{"type":"FeatureCollection","features":[{"type":"Feature","properties":{"codesPostaux":["47310"],"population":1951,"nom":"Estillac","code":"47091"},"geometry":{"type":"Point","coordinates":[0.5751613725490197,44.16970852941177]}}]}