{"type":"FeatureCollection","features":[{"type":"Feature","properties":{"codesPostaux":["47190"],"population":346,"nom":"Galapian","code":"47107"},"geometry":{"type":"Point","coordinates":[0.41272040816326533,44.29788928571433]}}]}