{"type":"FeatureCollection","features":[{"type":"Feature","properties":{"codesPostaux":["47340"],"population":1591,"nom":"Laroque-Timbaut","code":"47138"},"geometry":{"type":"Point","coordinates":[0.7530249532710281,44.27720929906543]}}]}