{"type":"FeatureCollection","features":[{"type":"Feature","properties":{"codesPostaux":["47300"],"population":1332,"nom":"L\u00e9dat","code":"47146"},"geometry":{"type":"Point","coordinates":[0.6681609815950919,44.44960987730061]}}]}