{"type":"FeatureCollection","features":[{"type":"Feature","properties":{"codesPostaux":["47200"],"population":828,"nom":"Marcellus","code":"47156"},"geometry":{"type":"Point","coordinates":[0.07499123076923077,44.47967692307689]}}]}