{"type":"FeatureCollection","features":[{"type":"Feature","properties":{"codesPostaux":["47290"],"population":443,"nom":"Lougratte","code":"47152"},"geometry":{"type":"Point","coordinates":[0.6267932369942196,44.59368352601155]}}]}