{"type":"FeatureCollection","features":[{"type":"Feature","properties":{"codesPostaux":["47200"],"population":567,"nom":"Mauvezin-sur-Gupie","code":"47163"},"geometry":{"type":"Point","coordinates":[0.17457335294117646,44.56332170588234]}}]}