{"type":"FeatureCollection","features":[{"type":"Feature","properties":{"codesPostaux":["47290"],"population":616,"nom":"Monbahus","code":"47170"},"geometry":{"type":"Point","coordinates":[0.5360886486486487,44.53732178378378]}}]}