{"type":"FeatureCollection","features":[{"type":"Feature","properties":{"codesPostaux":["47150"],"population":393,"nom":"Mons\u00e9gur","code":"47178"},"geometry":{"type":"Point","coordinates":[0.8772599242424246,44.48526659090908]}}]}