{"type":"FeatureCollection","features":[{"type":"Feature","properties":{"codesPostaux":["47600"],"population":612,"nom":"Montagnac-sur-Auvignon","code":"47180"},"geometry":{"type":"Point","coordinates":[0.4563392814371255,44.16710562874251]}}]}