{"type":"FeatureCollection","features":[{"type":"Feature","properties":{"codesPostaux":["47800"],"population":327,"nom":"Moustier","code":"47194"},"geometry":{"type":"Point","coordinates":[0.3020811382113822,44.642069756097555]}}]}