{"type":"FeatureCollection","features":[{"type":"Feature","properties":{"codesPostaux":["47600"],"population":229,"nom":"Nomdieu","code":"47197"},"geometry":{"type":"Point","coordinates":[0.4650957480314958,44.08388842519687]}}]}