{"type":"FeatureCollection","features":[{"type":"Feature","properties":{"codesPostaux":["47190"],"population":287,"nom":"Nicole","code":"47196"},"geometry":{"type":"Point","coordinates":[0.33698940298507474,44.33266417910447]}}]}