{"type":"FeatureCollection","features":[{"type":"Feature","properties":{"codesPostaux":["47520"],"population":9484,"nom":"Le Passage","code":"47201"},"geometry":{"type":"Point","coordinates":[0.5911307857142856,44.18492949999998]}}]}