{"type":"FeatureCollection","features":[{"type":"Feature","properties":{"codesPostaux":["47350"],"population":288,"nom":"Peyri\u00e8re","code":"47204"},"geometry":{"type":"Point","coordinates":[0.30498105769230766,44.57579182692307]}}]}