{"type":"FeatureCollection","features":[{"type":"Feature","properties":{"codesPostaux":["47480"],"population":4239,"nom":"Pont-du-Casse","code":"47209"},"geometry":{"type":"Point","coordinates":[0.6750847311827959,44.2360661827957]}}]}