{"type":"FeatureCollection","features":[{"type":"Feature","properties":{"codesPostaux":["47160"],"population":708,"nom":"Puch-d'Agenais","code":"47214"},"geometry":{"type":"Point","coordinates":[0.25682291390728473,44.32939609271525]}}]}