{"type":"FeatureCollection","features":[{"type":"Feature","properties":{"codesPostaux":["47250"],"population":158,"nom":"Romestaing","code":"47224"},"geometry":{"type":"Point","coordinates":[0.022671578947368404,44.415404385964905]}}]}