{"type":"FeatureCollection","features":[{"type":"Feature","properties":{"codesPostaux":["47170"],"population":586,"nom":"R\u00e9aup-Lisse","code":"47221"},"geometry":{"type":"Point","coordinates":[0.21896743772241994,44.08816790035591]}}]}