{"type":"FeatureCollection","features":[{"type":"Feature","properties":{"codesPostaux":["47700"],"population":164,"nom":"Ruffiac","code":"47227"},"geometry":{"type":"Point","coordinates":[0.03643348314606741,44.367305786516866]}}]}