{"type":"FeatureCollection","features":[{"type":"Feature","properties":{"codesPostaux":["47310"],"population":1659,"nom":"Sainte-Colombe-en-Bruilhois","code":"47238"},"geometry":{"type":"Point","coordinates":[0.5116974074074074,44.187048074074106]}}]}