{"type":"FeatureCollection","features":[{"type":"Feature","properties":{"codesPostaux":["47300"],"population":488,"nom":"Sainte-Colombe-de-Villeneuve","code":"47237"},"geometry":{"type":"Point","coordinates":[0.6586611695906434,44.36058935672514]}}]}