{"type":"FeatureCollection","features":[{"type":"Feature","properties":{"codesPostaux":["47120"],"population":88,"nom":"Saint-G\u00e9raud","code":"47245"},"geometry":{"type":"Point","coordinates":[0.1551176288659794,44.6243719587629]}}]}