{"type":"FeatureCollection","features":[{"type":"Feature","properties":{"codesPostaux":["47130"],"population":512,"nom":"Saint-Laurent","code":"47249"},"geometry":{"type":"Point","coordinates":[0.39775790322580656,44.234848709677415]}}]}