{"type":"FeatureCollection","features":[{"type":"Feature","properties":{"codesPostaux":["47210"],"population":306,"nom":"Saint-\u00c9tienne-de-Viller\u00e9al","code":"47240"},"geometry":{"type":"Point","coordinates":[0.7658772826086956,44.612209239130436]}}]}