{"type":"FeatureCollection","features":[{"type":"Feature","properties":{"codesPostaux":["47110"],"population":6132,"nom":"Sainte-Livrade-sur-Lot","code":"47252"},"geometry":{"type":"Point","coordinates":[0.5971737128712872,44.40019658415844]}}]}