{"type":"FeatureCollection","features":[{"type":"Feature","properties":{"codesPostaux":["47800"],"population":1183,"nom":"Saint-Pardoux-Isaac","code":"47264"},"geometry":{"type":"Point","coordinates":[0.37251481818181803,44.61131081818181]}}]}