{"type":"FeatureCollection","features":[{"type":"Feature","properties":{"codesPostaux":["47420"],"population":80,"nom":"Saum\u00e9jan","code":"47286"},"geometry":{"type":"Point","coordinates":[-0.033996209150326806,44.222494967320266]}}]}