{"type":"FeatureCollection","features":[{"type":"Feature","properties":{"codesPostaux":["47410"],"population":168,"nom":"S\u00e9galas","code":"47296"},"geometry":{"type":"Point","coordinates":[0.5327056390977443,44.58957458646614]}}]}