{"type":"FeatureCollection","features":[{"type":"Feature","properties":{"codesPostaux":["47360"],"population":141,"nom":"Sembas","code":"47297"},"geometry":{"type":"Point","coordinates":[0.6433199019607844,44.321082941176485]}}]}