{"type":"FeatureCollection","features":[{"type":"Feature","properties":{"codesPostaux":["47110"],"population":1001,"nom":"Le Temple-sur-Lot","code":"47306"},"geometry":{"type":"Point","coordinates":[0.5250552659574466,44.372443031914905]}}]}