{"type":"FeatureCollection","features":[{"type":"Feature","properties":{"codesPostaux":["47270"],"population":389,"nom":"Tayrac","code":"47305"},"geometry":{"type":"Point","coordinates":[0.8365125874125875,44.205346713286715]}}]}