{"type":"FeatureCollection","features":[{"type":"Feature","properties":{"codesPostaux":["47400"],"population":622,"nom":"Var\u00e8s","code":"47316"},"geometry":{"type":"Point","coordinates":[0.36085746913580247,44.43435259259261]}}]}