{"type":"FeatureCollection","features":[{"type":"Feature","properties":{"codesPostaux":["47380"],"population":144,"nom":"Tourtr\u00e8s","code":"47313"},"geometry":{"type":"Point","coordinates":[0.4204349438202248,44.50956292134831]}}]}