{"type":"FeatureCollection","features":[{"type":"Feature","properties":{"codesPostaux":["47120"],"population":313,"nom":"Villeneuve-de-Duras","code":"47321"},"geometry":{"type":"Point","coordinates":[0.2386092248062016,44.74098620155041]}}]}