{"type":"FeatureCollection","features":[{"type":"Feature","properties":{"codesPostaux":["48130"],"population":2390,"nom":"Peyre en Aubrac","code":"48009"},"geometry":{"type":"Point","coordinates":[3.266560611353714,44.69654688500728]}}]}