{"type":"FeatureCollection","features":[{"type":"Feature","properties":{"codesPostaux":["48200"],"population":333,"nom":"Les Monts-Verts","code":"48012"},"geometry":{"type":"Point","coordinates":[3.215664843205574,44.84854404181183]}}]}