{"type":"FeatureCollection","features":[{"type":"Feature","properties":{"codesPostaux":["48600"],"population":411,"nom":"Auroux","code":"48010"},"geometry":{"type":"Point","coordinates":[3.726602730496457,44.75588262411346]}}]}