{"type":"FeatureCollection","features":[{"type":"Feature","properties":{"codesPostaux":["48310"],"population":94,"nom":"Brion","code":"48031"},"geometry":{"type":"Point","coordinates":[3.0698684999999992,44.7494508125]}}]}