{"type":"FeatureCollection","features":[{"type":"Feature","properties":{"codesPostaux":["48000"],"population":370,"nom":"Brenoux","code":"48030"},"geometry":{"type":"Point","coordinates":[3.5332819199999994,44.48730696000001]}}]}