{"type":"FeatureCollection","features":[{"type":"Feature","properties":{"codesPostaux":["48600"],"population":288,"nom":"Chambon-le-Ch\u00e2teau","code":"48038"},"geometry":{"type":"Point","coordinates":[3.6534626751592376,44.85861859872612]}}]}