{"type":"FeatureCollection","features":[{"type":"Feature","properties":{"codesPostaux":["48310"],"population":94,"nom":"Chauchailles","code":"48044"},"geometry":{"type":"Point","coordinates":[3.074837083333333,44.795502976190505]}}]}