{"type":"FeatureCollection","features":[{"type":"Feature","properties":{"codesPostaux":["48310"],"population":165,"nom":"La Fage-Montivernoux","code":"48058"},"geometry":{"type":"Point","coordinates":[3.148622000000001,44.74169135294119]}}]}