{"type":"FeatureCollection","features":[{"type":"Feature","properties":{"codesPostaux":["48310"],"population":371,"nom":"Fournels","code":"48064"},"geometry":{"type":"Point","coordinates":[3.1262633976833967,44.808436756756755]}}]}