{"type":"FeatureCollection","features":[{"type":"Feature","properties":{"codesPostaux":["48140"],"population":64,"nom":"Julianges","code":"48077"},"geometry":{"type":"Point","coordinates":[3.3182683471074377,44.933814628099185]}}]}