{"type":"FeatureCollection","features":[{"type":"Feature","properties":{"codesPostaux":["48300"],"population":2944,"nom":"Langogne","code":"48080"},"geometry":{"type":"Point","coordinates":[3.8331704999999987,44.72377422222224]}}]}