{"type":"FeatureCollection","features":[{"type":"Feature","properties":{"codesPostaux":["48210"],"population":155,"nom":"La Mal\u00e8ne","code":"48088"},"geometry":{"type":"Point","coordinates":[3.310597000000002,44.31239641666668]}}]}