{"type":"FeatureCollection","features":[{"type":"Feature","properties":{"codesPostaux":["48100","48270"],"population":287,"nom":"Prinsu\u00e9jols-Malbouzon","code":"48087"},"geometry":{"type":"Point","coordinates":[3.167470719257541,44.68259767981441]}}]}