{"type":"FeatureCollection","features":[{"type":"Feature","properties":{"codesPostaux":["48300"],"population":343,"nom":"Naussac-Fontanes","code":"48105"},"geometry":{"type":"Point","coordinates":[3.7979776744186053,44.76226864341089]}}]}