{"type":"FeatureCollection","features":[{"type":"Feature","properties":{"codesPostaux":["48100"],"population":204,"nom":"Palhers","code":"48107"},"geometry":{"type":"Point","coordinates":[3.3077338679245267,44.51936103773585]}}]}