{"type":"FeatureCollection","features":[{"type":"Feature","properties":{"codesPostaux":["48310"],"population":97,"nom":"Noalhac","code":"48106"},"geometry":{"type":"Point","coordinates":[3.1136140716612353,44.79870179153093]}}]}