{"type":"FeatureCollection","features":[{"type":"Feature","properties":{"codesPostaux":["48110"],"population":174,"nom":"Le Pompidou","code":"48115"},"geometry":{"type":"Point","coordinates":[3.662883392070485,44.20573158590308]}}]}