{"type":"FeatureCollection","features":[{"type":"Feature","properties":{"codesPostaux":["48300"],"population":190,"nom":"Saint-Flour-de-Mercoire","code":"48150"},"geometry":{"type":"Point","coordinates":[3.8220079054054037,44.685708243243255]}}]}