{"type":"FeatureCollection","features":[{"type":"Feature","properties":{"codesPostaux":["48170"],"population":160,"nom":"Saint-Jean-la-Fouillouse","code":"48160"},"geometry":{"type":"Point","coordinates":[3.699266172839505,44.70582728395061]}}]}