{"type":"FeatureCollection","features":[{"type":"Feature","properties":{"codesPostaux":["48140"],"population":140,"nom":"Saint-Privat-du-Fau","code":"48179"},"geometry":{"type":"Point","coordinates":[3.3487325133689816,44.91619775401069]}}]}