{"type":"FeatureCollection","features":[{"type":"Feature","properties":{"codesPostaux":["48150"],"population":78,"nom":"Saint-Pierre-des-Tripiers","code":"48176"},"geometry":{"type":"Point","coordinates":[3.2709484951456305,44.222224563106764]}}]}