{"type":"FeatureCollection","features":[{"type":"Feature","properties":{"codesPostaux":["48220"],"population":447,"nom":"Vialas","code":"48194"},"geometry":{"type":"Point","coordinates":[3.8878998536585363,44.34161268292686]}}]}