{"type":"FeatureCollection","features":[{"type":"Feature","properties":{"codesPostaux":["49650"],"population":2980,"nom":"Allonnes","code":"49002"},"geometry":{"type":"Point","coordinates":[0.0133428025477707,47.29518904458599]}}]}