{"type":"FeatureCollection","features":[{"type":"Feature","properties":{"codesPostaux":["49440"],"population":968,"nom":"Angrie","code":"49008"},"geometry":{"type":"Point","coordinates":[-0.9725712676056338,47.570775598591524]}}]}