{"type":"FeatureCollection","features":[{"type":"Feature","properties":{"codesPostaux":["49420"],"population":302,"nom":"Armaill\u00e9","code":"49010"},"geometry":{"type":"Point","coordinates":[-1.140354252873563,47.71015040229886]}}]}