{"type":"FeatureCollection","features":[{"type":"Feature","properties":{"codesPostaux":["49390"],"population":588,"nom":"La Breille-les-Pins","code":"49045"},"geometry":{"type":"Point","coordinates":[0.08273207547169814,47.35148254716981]}}]}