{"type":"FeatureCollection","features":[{"type":"Feature","properties":{"codesPostaux":["49250","49320"],"population":10714,"nom":"Brissac Loire Aubance","code":"49050"},"geometry":{"type":"Point","coordinates":[-0.409809663865546,47.34791981512604]}}]}