{"type":"FeatureCollection","features":[{"type":"Feature","properties":{"codesPostaux":["49330"],"population":5412,"nom":"Les Hauts d'Anjou","code":"49065"},"geometry":{"type":"Point","coordinates":[-0.5428934482758622,47.70356932950188]}}]}