{"type":"FeatureCollection","features":[{"type":"Feature","properties":{"codesPostaux":["49220"],"population":368,"nom":"Chenill\u00e9-Champteuss\u00e9","code":"49067"},"geometry":{"type":"Point","coordinates":[-0.6591919847328245,47.67930816793893]}}]}