{"type":"FeatureCollection","features":[{"type":"Feature","properties":{"codesPostaux":["49440"],"population":815,"nom":"Challain-la-Potherie","code":"49061"},"geometry":{"type":"Point","coordinates":[-1.0904139930555552,47.623468749999944]}}]}