{"type":"FeatureCollection","features":[{"type":"Feature","properties":{"codesPostaux":["49560"],"population":348,"nom":"Cl\u00e9r\u00e9-sur-Layon","code":"49102"},"geometry":{"type":"Point","coordinates":[-0.4365211976047906,47.082830898203596]}}]}