{"type":"FeatureCollection","features":[{"type":"Feature","properties":{"codesPostaux":["49140"],"population":1718,"nom":"Corz\u00e9","code":"49110"},"geometry":{"type":"Point","coordinates":[-0.3737011180124224,47.541143105590066]}}]}