{"type":"FeatureCollection","features":[{"type":"Feature","properties":{"codesPostaux":["49000"],"population":3798,"nom":"\u00c9couflant","code":"49129"},"geometry":{"type":"Point","coordinates":[-0.5151288666666665,47.5248348]}}]}