{"type":"FeatureCollection","features":[{"type":"Feature","properties":{"codesPostaux":["49190"],"population":1398,"nom":"Den\u00e9e","code":"49120"},"geometry":{"type":"Point","coordinates":[-0.6046807947019868,47.369068543046346]}}]}