{"type":"FeatureCollection","features":[{"type":"Feature","properties":{"codesPostaux":["49430"],"population":543,"nom":"Huill\u00e9","code":"49159"},"geometry":{"type":"Point","coordinates":[-0.3117165034965035,47.66100412587414]}}]}