{"type":"FeatureCollection","features":[{"type":"Feature","properties":{"codesPostaux":["49330"],"population":788,"nom":"Juvardeil","code":"49170"},"geometry":{"type":"Point","coordinates":[-0.5159522012578617,47.66056490566037]}}]}