{"type":"FeatureCollection","features":[{"type":"Feature","properties":{"codesPostaux":["49370","49440"],"population":4692,"nom":"Val d'Erdre-Auxence","code":"49183"},"geometry":{"type":"Point","coordinates":[-0.9184071929824557,47.50542159356724]}}]}