{"type":"FeatureCollection","features":[{"type":"Feature","properties":{"codesPostaux":["49460"],"population":7213,"nom":"Montreuil-Juign\u00e9","code":"49214"},"geometry":{"type":"Point","coordinates":[-0.6191150000000002,47.54010570512822]}}]}