{"type":"FeatureCollection","features":[{"type":"Feature","properties":{"codesPostaux":["49640"],"population":3586,"nom":"Morannes sur Sarthe-Daumeray","code":"49220"},"geometry":{"type":"Point","coordinates":[-0.3816157974683544,47.713684886075995]}}]}