{"type":"FeatureCollection","features":[{"type":"Feature","properties":{"codesPostaux":["49680"],"population":988,"nom":"Neuill\u00e9","code":"49224"},"geometry":{"type":"Point","coordinates":[-0.023566893203883492,47.33433097087378]}}]}