{"type":"FeatureCollection","features":[{"type":"Feature","properties":{"codesPostaux":["49360"],"population":1029,"nom":"La Plaine","code":"49240"},"geometry":{"type":"Point","coordinates":[-0.6295253389830509,47.06383716101695]}}]}