{"type":"FeatureCollection","features":[{"type":"Feature","properties":{"codesPostaux":["49280"],"population":2584,"nom":"Saint-Christophe-du-Bois","code":"49269"},"geometry":{"type":"Point","coordinates":[-0.9657252064220182,47.033683188073354]}}]}