{"type":"FeatureCollection","features":[{"type":"Feature","properties":{"codesPostaux":["49400"],"population":681,"nom":"Rou-Marson","code":"49262"},"geometry":{"type":"Point","coordinates":[-0.1554564406779661,47.24331127118645]}}]}