{"type":"FeatureCollection","features":[{"type":"Feature","properties":{"codesPostaux":["49130"],"population":3521,"nom":"Sainte-Gemmes-sur-Loire","code":"49278"},"geometry":{"type":"Point","coordinates":[-0.5748215294117648,47.42795635294118]}}]}