{"type":"FeatureCollection","features":[{"type":"Feature","properties":{"codesPostaux":["49170"],"population":3529,"nom":"Saint-Georges-sur-Loire","code":"49283"},"geometry":{"type":"Point","coordinates":[-0.7541337209302323,47.40652540697673]}}]}