{"type":"FeatureCollection","features":[{"type":"Feature","properties":{"codesPostaux":["49130"],"population":236,"nom":"Saint-Jean-de-la-Croix","code":"49288"},"geometry":{"type":"Point","coordinates":[-0.5847415094339622,47.40938622641508]}}]}