{"type":"FeatureCollection","features":[{"type":"Feature","properties":{"codesPostaux":["49170"],"population":1672,"nom":"Saint-Martin-du-Fouilloux","code":"49306"},"geometry":{"type":"Point","coordinates":[-0.7060041732283462,47.43741338582677]}}]}