{"type":"FeatureCollection","features":[{"type":"Feature","properties":{"codesPostaux":["49360"],"population":914,"nom":"Somloire","code":"49336"},"geometry":{"type":"Point","coordinates":[-0.5962997460317461,47.03555679365079]}}]}