{"type":"FeatureCollection","features":[{"type":"Feature","properties":{"codesPostaux":["49400"],"population":797,"nom":"Souzay-Champigny","code":"49341"},"geometry":{"type":"Point","coordinates":[-0.02370246753246754,47.216449480519486]}}]}