{"type":"FeatureCollection","features":[{"type":"Feature","properties":{"codesPostaux":["49340"],"population":2823,"nom":"Tr\u00e9mentines","code":"49355"},"geometry":{"type":"Point","coordinates":[-0.8079137864077672,47.119843398058244]}}]}