{"type":"FeatureCollection","features":[{"type":"Feature","properties":{"codesPostaux":["49730"],"population":1891,"nom":"Varennes-sur-Loire","code":"49361"},"geometry":{"type":"Point","coordinates":[0.049964538461538456,47.252218230769216]}}]}