{"type":"FeatureCollection","features":[{"type":"Feature","properties":{"codesPostaux":["49390"],"population":1256,"nom":"Vernoil-le-Fourrier","code":"49369"},"geometry":{"type":"Point","coordinates":[0.09323762962962961,47.406732296296305]}}]}