{"type":"FeatureCollection","features":[{"type":"Feature","properties":{"codesPostaux":["49400"],"population":1244,"nom":"Varrains","code":"49362"},"geometry":{"type":"Point","coordinates":[-0.06819238095238092,47.22947583333333]}}]}