{"type":"FeatureCollection","features":[{"type":"Feature","properties":{"codesPostaux":["49680"],"population":2506,"nom":"Vivy","code":"49378"},"geometry":{"type":"Point","coordinates":[-0.06447695364238411,47.32446973509933]}}]}