{"type":"FeatureCollection","features":[{"type":"Feature","properties":{"codesPostaux":["50230"],"population":2799,"nom":"Agon-Coutainville","code":"50003"},"geometry":{"type":"Point","coordinates":[-1.5728435333333337,49.03246993333333]}}]}