{"type":"FeatureCollection","features":[{"type":"Feature","properties":{"codesPostaux":["50450"],"population":96,"nom":"La Baleine","code":"50028"},"geometry":{"type":"Point","coordinates":[-1.305287818181818,48.926434545454555]}}]}