{"type":"FeatureCollection","features":[{"type":"Feature","properties":{"codesPostaux":["50300"],"population":7890,"nom":"Avranches","code":"50025"},"geometry":{"type":"Point","coordinates":[-1.3551733070866134,48.69027440944881]}}]}