{"type":"FeatureCollection","features":[{"type":"Feature","properties":{"codesPostaux":["50500"],"population":666,"nom":"Auvers","code":"50023"},"geometry":{"type":"Point","coordinates":[-1.3292843378995427,49.30113438356164]}}]}