{"type":"FeatureCollection","features":[{"type":"Feature","properties":{"codesPostaux":["50430"],"population":392,"nom":"Bretteville-sur-Ay","code":"50078"},"geometry":{"type":"Point","coordinates":[-1.6168729487179492,49.26073397435896]}}]}