{"type":"FeatureCollection","features":[{"type":"Feature","properties":{"codesPostaux":["50290"],"population":795,"nom":"Br\u00e9ville-sur-Mer","code":"50081"},"geometry":{"type":"Point","coordinates":[-1.5520539999999996,48.868075333333316]}}]}