{"type":"FeatureCollection","features":[{"type":"Feature","properties":{"codesPostaux":["50150"],"population":167,"nom":"Brouains","code":"50088"},"geometry":{"type":"Point","coordinates":[-0.9632932743362832,48.72201477876104]}}]}