{"type":"FeatureCollection","features":[{"type":"Feature","properties":{"codesPostaux":["50480","50500"],"population":7887,"nom":"Carentan les Marais","code":"50099"},"geometry":{"type":"Point","coordinates":[-1.2296886797066007,49.322324572127165]}}]}