{"type":"FeatureCollection","features":[{"type":"Feature","properties":{"codesPostaux":["50100","50110","50120","50130","50460","50470"],"population":80978,"nom":"Cherbourg-en-Cotentin","code":"50129"},"geometry":{"type":"Point","coordinates":[-1.6414856678700371,49.64253355595669]}}]}