{"type":"FeatureCollection","features":[{"type":"Feature","properties":{"codesPostaux":["50330"],"population":204,"nom":"Clitourps","code":"50135"},"geometry":{"type":"Point","coordinates":[-1.3719604301075266,49.654134838709645]}}]}