{"type":"FeatureCollection","features":[{"type":"Feature","properties":{"codesPostaux":["50800"],"population":384,"nom":"Ch\u00e9renc\u00e9-le-H\u00e9ron","code":"50130"},"geometry":{"type":"Point","coordinates":[-1.2025294557823132,48.79933482993201]}}]}