{"type":"FeatureCollection","features":[{"type":"Feature","properties":{"codesPostaux":["50530"],"population":807,"nom":"Dragey-Ronthon","code":"50167"},"geometry":{"type":"Point","coordinates":[-1.487218359375,48.72000554687503]}}]}