{"type":"FeatureCollection","features":[{"type":"Feature","properties":{"codesPostaux":["50110"],"population":1511,"nom":"Digosville","code":"50162"},"geometry":{"type":"Point","coordinates":[-1.5299295804195798,49.63410244755245]}}]}