{"type":"FeatureCollection","features":[{"type":"Feature","properties":{"codesPostaux":["50310"],"population":367,"nom":"\u00c9mondeville","code":"50172"},"geometry":{"type":"Point","coordinates":[-1.337310843373494,49.463378192771096]}}]}