{"type":"FeatureCollection","features":[{"type":"Feature","properties":{"codesPostaux":["50360"],"population":376,"nom":"\u00c9tienville","code":"50177"},"geometry":{"type":"Point","coordinates":[-1.4350009821428562,49.38944125000002]}}]}