{"type":"FeatureCollection","features":[{"type":"Feature","properties":{"codesPostaux":["50310"],"population":171,"nom":"Fontenay-sur-Mer","code":"50190"},"geometry":{"type":"Point","coordinates":[-1.3056361068702291,49.495979465648865]}}]}