{"type":"FeatureCollection","features":[{"type":"Feature","properties":{"codesPostaux":["50760"],"population":483,"nom":"Gatteville-le-Phare","code":"50196"},"geometry":{"type":"Point","coordinates":[-1.2836190555555556,49.68087483333332]}}]}