{"type":"FeatureCollection","features":[{"type":"Feature","properties":{"codesPostaux":["50620"],"population":806,"nom":"Graignes-Mesnil-Angot","code":"50216"},"geometry":{"type":"Point","coordinates":[-1.2024822151898726,49.229784430379716]}}]}