{"type":"FeatureCollection","features":[{"type":"Feature","properties":{"codesPostaux":["50390"],"population":139,"nom":"Hautteville-Bocage","code":"50233"},"geometry":{"type":"Point","coordinates":[-1.4686748453608247,49.42618072164948]}}]}