{"type":"FeatureCollection","features":[{"type":"Feature","properties":{"codesPostaux":["50250","50580"],"population":4077,"nom":"La Haye","code":"50236"},"geometry":{"type":"Point","coordinates":[-1.5920244387755098,49.2840798214286]}}]}