{"type":"FeatureCollection","features":[{"type":"Feature","properties":{"codesPostaux":["50480"],"population":67,"nom":"Hiesville","code":"50246"},"geometry":{"type":"Point","coordinates":[-1.255928181818182,49.371822272727265]}}]}