{"type":"FeatureCollection","features":[{"type":"Feature","properties":{"codesPostaux":["50320"],"population":184,"nom":"Hocquigny","code":"50247"},"geometry":{"type":"Point","coordinates":[-1.4023870238095233,48.80730285714284]}}]}