{"type":"FeatureCollection","features":[{"type":"Feature","properties":{"codesPostaux":["50510"],"population":860,"nom":"Hudimesnil","code":"50252"},"geometry":{"type":"Point","coordinates":[-1.4654299999999998,48.866397732558106]}}]}