{"type":"FeatureCollection","features":[{"type":"Feature","properties":{"codesPostaux":["50220"],"population":663,"nom":"Juilley","code":"50259"},"geometry":{"type":"Point","coordinates":[-1.3485195312500002,48.59020281250001]}}]}