{"type":"FeatureCollection","features":[{"type":"Feature","properties":{"codesPostaux":["50520"],"population":1742,"nom":"Juvigny les Vall\u00e9es","code":"50260"},"geometry":{"type":"Point","coordinates":[-1.024441150000001,48.68009669999999]}}]}