{"type":"FeatureCollection","features":[{"type":"Feature","properties":{"codesPostaux":["50800"],"population":508,"nom":"La Lande-d'Airou","code":"50262"},"geometry":{"type":"Point","coordinates":[-1.2924715217391314,48.81980408695654]}}]}