{"type":"FeatureCollection","features":[{"type":"Feature","properties":{"codesPostaux":["50300"],"population":1290,"nom":"Marcey-les-Gr\u00e8ves","code":"50288"},"geometry":{"type":"Point","coordinates":[-1.3874635172413794,48.701563517241375]}}]}