{"type":"FeatureCollection","features":[{"type":"Feature","properties":{"codesPostaux":["50410"],"population":133,"nom":"Maupertuis","code":"50295"},"geometry":{"type":"Point","coordinates":[-1.193518767123288,48.96217465753425]}}]}