{"type":"FeatureCollection","features":[{"type":"Feature","properties":{"codesPostaux":["50520"],"population":175,"nom":"Le Mesnil-Adel\u00e9e","code":"50300"},"geometry":{"type":"Point","coordinates":[-1.064960795454545,48.702067386363645]}}]}