{"type":"FeatureCollection","features":[{"type":"Feature","properties":{"codesPostaux":["50570"],"population":180,"nom":"Le Mesnil-Eury","code":"50310"},"geometry":{"type":"Point","coordinates":[-1.2381149107142853,49.162343571428565]}}]}