{"type":"FeatureCollection","features":[{"type":"Feature","properties":{"codesPostaux":["50590"],"population":1332,"nom":"Montmartin-sur-Mer","code":"50349"},"geometry":{"type":"Point","coordinates":[-1.5259422448979585,48.99141836734695]}}]}