{"type":"FeatureCollection","features":[{"type":"Feature","properties":{"codesPostaux":["50170"],"population":41,"nom":"Le Mont-Saint-Michel","code":"50353"},"geometry":{"type":"Point","coordinates":[-1.521224285714286,48.624904285714294]}}]}