{"type":"FeatureCollection","features":[{"type":"Feature","properties":{"codesPostaux":["50420","50860"],"population":1510,"nom":"Moyon Villages","code":"50363"},"geometry":{"type":"Point","coordinates":[-1.1246080241935485,48.99600399193547]}}]}