{"type":"FeatureCollection","features":[{"type":"Feature","properties":{"codesPostaux":["50320"],"population":228,"nom":"La Mouche","code":"50361"},"geometry":{"type":"Point","coordinates":[-1.3517717525773192,48.78437608247421]}}]}