{"type":"FeatureCollection","features":[{"type":"Feature","properties":{"codesPostaux":["50250"],"population":196,"nom":"Neufmesnil","code":"50372"},"geometry":{"type":"Point","coordinates":[-1.5346754545454544,49.31237354545458]}}]}