{"type":"FeatureCollection","features":[{"type":"Feature","properties":{"codesPostaux":["50410"],"population":2628,"nom":"Percy-en-Normandie","code":"50393"},"geometry":{"type":"Point","coordinates":[-1.1978866763848406,48.91337102040818]}}]}