{"type":"FeatureCollection","features":[{"type":"Feature","properties":{"codesPostaux":["50310"],"population":151,"nom":"Ozeville","code":"50390"},"geometry":{"type":"Point","coordinates":[-1.3407249450549457,49.501244725274724]}}]}