{"type":"FeatureCollection","features":[{"type":"Feature","properties":{"codesPostaux":["50340"],"population":750,"nom":"Pierreville","code":"50401"},"geometry":{"type":"Point","coordinates":[-1.7739121476510062,49.467573892617466]}}]}