{"type":"FeatureCollection","features":[{"type":"Feature","properties":{"codesPostaux":["50390"],"population":390,"nom":"Rauville-la-Place","code":"50426"},"geometry":{"type":"Point","coordinates":[-1.5007443537414964,49.391156054421785]}}]}