{"type":"FeatureCollection","features":[{"type":"Feature","properties":{"codesPostaux":["50140"],"population":1346,"nom":"Romagny Fontenay","code":"50436"},"geometry":{"type":"Point","coordinates":[-0.9897593380614641,48.633242907801424]}}]}