{"type":"FeatureCollection","features":[{"type":"Feature","properties":{"codesPostaux":["50300"],"population":143,"nom":"Saint-Brice","code":"50451"},"geometry":{"type":"Point","coordinates":[-1.2991680147058826,48.70137897058822]}}]}