{"type":"FeatureCollection","features":[{"type":"Feature","properties":{"codesPostaux":["50760"],"population":318,"nom":"Sainte-Genevi\u00e8ve","code":"50469"},"geometry":{"type":"Point","coordinates":[-1.3085296052631585,49.66157157894736]}}]}