{"type":"FeatureCollection","features":[{"type":"Feature","properties":{"codesPostaux":["50680"],"population":392,"nom":"Saint-Georges-d'Elle","code":"50473"},"geometry":{"type":"Point","coordinates":[-0.9776618181818184,49.15568414141415]}}]}