{"type":"FeatureCollection","features":[{"type":"Feature","properties":{"codesPostaux":["50480"],"population":119,"nom":"Saint-Germain-de-Varreville","code":"50479"},"geometry":{"type":"Point","coordinates":[-1.2519072881355935,49.435055084745755]}}]}