{"type":"FeatureCollection","features":[{"type":"Feature","properties":{"codesPostaux":["50300"],"population":716,"nom":"Saint-Loup","code":"50505"},"geometry":{"type":"Point","coordinates":[-1.304570923076923,48.66327200000001]}}]}