{"type":"FeatureCollection","features":[{"type":"Feature","properties":{"codesPostaux":["50670"],"population":314,"nom":"Saint-Michel-de-Montjoie","code":"50525"},"geometry":{"type":"Point","coordinates":[-1.0264417821782181,48.76560554455447]}}]}