{"type":"FeatureCollection","features":[{"type":"Feature","properties":{"codesPostaux":["50510"],"population":321,"nom":"Saint-Sauveur-la-Pommeraye","code":"50549"},"geometry":{"type":"Point","coordinates":[-1.4383830952380958,48.84159214285715]}}]}