{"type":"FeatureCollection","features":[{"type":"Feature","properties":{"codesPostaux":["50670"],"population":502,"nom":"Saint-Pois","code":"50542"},"geometry":{"type":"Point","coordinates":[-1.057835688622754,48.75217461077844]}}]}