{"type":"FeatureCollection","features":[{"type":"Feature","properties":{"codesPostaux":["50390"],"population":2195,"nom":"Saint-Sauveur-le-Vicomte","code":"50551"},"geometry":{"type":"Point","coordinates":[-1.5466777124183013,49.380430457516354]}}]}