{"type":"FeatureCollection","features":[{"type":"Feature","properties":{"codesPostaux":["50300"],"population":1945,"nom":"Le Val-Saint-P\u00e8re","code":"50616"},"geometry":{"type":"Point","coordinates":[-1.3705047916666666,48.66089239583335]}}]}