{"type":"FeatureCollection","features":[{"type":"Feature","properties":{"codesPostaux":["50370"],"population":165,"nom":"Vernix","code":"50628"},"geometry":{"type":"Point","coordinates":[-1.2284307216494845,48.715432474226816]}}]}