{"type":"FeatureCollection","features":[{"type":"Feature","properties":{"codesPostaux":["50680"],"population":612,"nom":"Villiers-Fossard","code":"50641"},"geometry":{"type":"Point","coordinates":[-1.0636530526315788,49.16465389473686]}}]}