{"type":"FeatureCollection","features":[{"type":"Feature","properties":{"codesPostaux":["51170"],"population":47,"nom":"Aubilly","code":"51020"},"geometry":{"type":"Point","coordinates":[3.858061363636364,49.214523636363644]}}]}