{"type":"FeatureCollection","features":[{"type":"Feature","properties":{"codesPostaux":["51190"],"population":1806,"nom":"Avize","code":"51029"},"geometry":{"type":"Point","coordinates":[4.005327727272728,48.97476886363638]}}]}