{"type":"FeatureCollection","features":[{"type":"Feature","properties":{"codesPostaux":["51700"],"population":181,"nom":"Baslieux-sous-Ch\u00e2tillon","code":"51038"},"geometry":{"type":"Point","coordinates":[3.7916157333333347,49.12054400000002]}}]}