{"type":"FeatureCollection","features":[{"type":"Feature","properties":{"codesPostaux":["51300"],"population":258,"nom":"Bassuet","code":"51040"},"geometry":{"type":"Point","coordinates":[4.669216615384614,48.80203476923078]}}]}