{"type":"FeatureCollection","features":[{"type":"Feature","properties":{"codesPostaux":["51110"],"population":2001,"nom":"Bazancourt","code":"51043"},"geometry":{"type":"Point","coordinates":[4.167656666666668,49.36241639999999]}}]}