{"type":"FeatureCollection","features":[{"type":"Feature","properties":{"codesPostaux":["51420"],"population":511,"nom":"Berru","code":"51052"},"geometry":{"type":"Point","coordinates":[4.151197881355931,49.26809788135592]}}]}