{"type":"FeatureCollection","features":[{"type":"Feature","properties":{"codesPostaux":["51800"],"population":106,"nom":"Binarville","code":"51062"},"geometry":{"type":"Point","coordinates":[4.912156100386102,49.24694969111971]}}]}