{"type":"FeatureCollection","features":[{"type":"Feature","properties":{"codesPostaux":["51400"],"population":530,"nom":"Bouy","code":"51078"},"geometry":{"type":"Point","coordinates":[4.366038396226414,49.08936811320755]}}]}