{"type":"FeatureCollection","features":[{"type":"Feature","properties":{"codesPostaux":["51240"],"population":215,"nom":"Breuvery-sur-Coole","code":"51087"},"geometry":{"type":"Point","coordinates":[4.307758333333335,48.85764722222224]}}]}