{"type":"FeatureCollection","features":[{"type":"Feature","properties":{"codesPostaux":["51300"],"population":208,"nom":"Brusson","code":"51094"},"geometry":{"type":"Point","coordinates":[4.708665520833334,48.74222125000001]}}]}