{"type":"FeatureCollection","features":[{"type":"Feature","properties":{"codesPostaux":["51170"],"population":143,"nom":"Chambrecy","code":"51111"},"geometry":{"type":"Point","coordinates":[3.825835196078431,49.18385911764706]}}]}