{"type":"FeatureCollection","features":[{"type":"Feature","properties":{"codesPostaux":["51270"],"population":139,"nom":"Champaubert","code":"51113"},"geometry":{"type":"Point","coordinates":[3.7721254639175257,48.88925515463917]}}]}