{"type":"FeatureCollection","features":[{"type":"Feature","properties":{"codesPostaux":["51800"],"population":57,"nom":"La Chapelle-Felcourt","code":"51126"},"geometry":{"type":"Point","coordinates":[4.754257222222224,49.04119861111113]}}]}