{"type":"FeatureCollection","features":[{"type":"Feature","properties":{"codesPostaux":["51250"],"population":623,"nom":"Cheminon","code":"51144"},"geometry":{"type":"Point","coordinates":[4.911806688963208,48.74155759197324]}}]}