{"type":"FeatureCollection","features":[{"type":"Feature","properties":{"codesPostaux":["51260"],"population":670,"nom":"Conflans-sur-Seine","code":"51162"},"geometry":{"type":"Point","coordinates":[3.6791641666666686,48.54212368055553]}}]}