{"type":"FeatureCollection","features":[{"type":"Feature","properties":{"codesPostaux":["51230"],"population":177,"nom":"Connantray-Vaurefroy","code":"51164"},"geometry":{"type":"Point","coordinates":[4.070364285714286,48.73694440476189]}}]}