{"type":"FeatureCollection","features":[{"type":"Feature","properties":{"codesPostaux":["51330"],"population":65,"nom":"Contault","code":"51166"},"geometry":{"type":"Point","coordinates":[4.784373278688524,48.91335737704917]}}]}