{"type":"FeatureCollection","features":[{"type":"Feature","properties":{"codesPostaux":["51230"],"population":159,"nom":"Corroy","code":"51176"},"geometry":{"type":"Point","coordinates":[3.9576902531645577,48.70266784810126]}}]}