{"type":"FeatureCollection","features":[{"type":"Feature","properties":{"codesPostaux":["51210"],"population":105,"nom":"Corf\u00e9lix","code":"51170"},"geometry":{"type":"Point","coordinates":[3.7018547826086947,48.834446811594205]}}]}