{"type":"FeatureCollection","features":[{"type":"Feature","properties":{"codesPostaux":["51240"],"population":189,"nom":"Coup\u00e9ville","code":"51179"},"geometry":{"type":"Point","coordinates":[4.62403349514563,48.90660951456312]}}]}