{"type":"FeatureCollection","features":[{"type":"Feature","properties":{"codesPostaux":["51270"],"population":53,"nom":"Courjeonnet","code":"51186"},"geometry":{"type":"Point","coordinates":[3.8270506666666666,48.82750288888888]}}]}