{"type":"FeatureCollection","features":[{"type":"Feature","properties":{"codesPostaux":["51310"],"population":295,"nom":"Courgivaux","code":"51185"},"geometry":{"type":"Point","coordinates":[3.492751333333333,48.71373904761906]}}]}