{"type":"FeatureCollection","features":[{"type":"Feature","properties":{"codesPostaux":["51170"],"population":293,"nom":"Courlandon","code":"51187"},"geometry":{"type":"Point","coordinates":[3.7344058620689644,49.31392810344826]}}]}