{"type":"FeatureCollection","features":[{"type":"Feature","properties":{"codesPostaux":["51300"],"population":136,"nom":"Drouilly","code":"51220"},"geometry":{"type":"Point","coordinates":[4.516973846153847,48.770850192307684]}}]}