{"type":"FeatureCollection","features":[{"type":"Feature","properties":{"codesPostaux":["51310"],"population":86,"nom":"Escardes","code":"51233"},"geometry":{"type":"Point","coordinates":[3.5329326785714286,48.693355535714275]}}]}