{"type":"FeatureCollection","features":[{"type":"Feature","properties":{"codesPostaux":["51260"],"population":596,"nom":"Esclavolles-Lurey","code":"51234"},"geometry":{"type":"Point","coordinates":[3.6508342477876115,48.54976106194689]}}]}