{"type":"FeatureCollection","features":[{"type":"Feature","properties":{"codesPostaux":["51230"],"population":2258,"nom":"F\u00e8re-Champenoise","code":"51248"},"geometry":{"type":"Point","coordinates":[4.031720370370372,48.77398377777776]}}]}