{"type":"FeatureCollection","features":[{"type":"Feature","properties":{"codesPostaux":["51700"],"population":405,"nom":"Festigny","code":"51249"},"geometry":{"type":"Point","coordinates":[3.7634556716417915,49.041699776119394]}}]}