{"type":"FeatureCollection","features":[{"type":"Feature","properties":{"codesPostaux":["51210"],"population":385,"nom":"Fromenti\u00e8res","code":"51263"},"geometry":{"type":"Point","coordinates":[3.7061884269662944,48.89056393258426]}}]}