{"type":"FeatureCollection","features":[{"type":"Feature","properties":{"codesPostaux":["51130"],"population":160,"nom":"Germinon","code":"51268"},"geometry":{"type":"Point","coordinates":[4.185278571428571,48.88671392857141]}}]}