{"type":"FeatureCollection","features":[{"type":"Feature","properties":{"codesPostaux":["51300"],"population":1846,"nom":"Frignicourt","code":"51262"},"geometry":{"type":"Point","coordinates":[4.588906030534351,48.70068167938929]}}]}