{"type":"FeatureCollection","features":[{"type":"Feature","properties":{"codesPostaux":["51260"],"population":191,"nom":"Granges-sur-Aube","code":"51279"},"geometry":{"type":"Point","coordinates":[3.8614790625000004,48.58089395833333]}}]}