{"type":"FeatureCollection","features":[{"type":"Feature","properties":{"codesPostaux":["51340"],"population":302,"nom":"Heiltz-l'\u00c9v\u00eaque","code":"51290"},"geometry":{"type":"Point","coordinates":[4.734942513089005,48.779712513089]}}]}