{"type":"FeatureCollection","features":[{"type":"Feature","properties":{"codesPostaux":["51110"],"population":399,"nom":"Heutr\u00e9giville","code":"51293"},"geometry":{"type":"Point","coordinates":[4.267094117647061,49.320917058823525]}}]}