{"type":"FeatureCollection","features":[{"type":"Feature","properties":{"codesPostaux":["51700"],"population":113,"nom":"Jonquery","code":"51309"},"geometry":{"type":"Point","coordinates":[3.78629962962963,49.14552]}}]}