{"type":"FeatureCollection","features":[{"type":"Feature","properties":{"codesPostaux":["51290"],"population":107,"nom":"Isle-sur-Marne","code":"51300"},"geometry":{"type":"Point","coordinates":[4.685831842105264,48.64000434210527]}}]}