{"type":"FeatureCollection","features":[{"type":"Feature","properties":{"codesPostaux":["51340"],"population":205,"nom":"Jussecourt-Minecourt","code":"51311"},"geometry":{"type":"Point","coordinates":[4.781042093023256,48.79497054263566]}}]}