{"type":"FeatureCollection","features":[{"type":"Feature","properties":{"codesPostaux":["51500"],"population":707,"nom":"Mailly-Champagne","code":"51338"},"geometry":{"type":"Point","coordinates":[4.113291057692306,49.14923750000001]}}]}