{"type":"FeatureCollection","features":[{"type":"Feature","properties":{"codesPostaux":["51500"],"population":620,"nom":"Ludes","code":"51333"},"geometry":{"type":"Point","coordinates":[4.085885169491524,49.15519847457625]}}]}