{"type":"FeatureCollection","features":[{"type":"Feature","properties":{"codesPostaux":["51300"],"population":522,"nom":"Maisons-en-Champagne","code":"51340"},"geometry":{"type":"Point","coordinates":[4.476058928571429,48.738974404761905]}}]}