{"type":"FeatureCollection","features":[{"type":"Feature","properties":{"codesPostaux":["51530"],"population":268,"nom":"Mancy","code":"51342"},"geometry":{"type":"Point","coordinates":[3.9369469135802455,48.983523333333345]}}]}