{"type":"FeatureCollection","features":[{"type":"Feature","properties":{"codesPostaux":["51270"],"population":258,"nom":"Mareuil-en-Brie","code":"51345"},"geometry":{"type":"Point","coordinates":[3.7511123958333346,48.96154479166665]}}]}