{"type":"FeatureCollection","features":[{"type":"Feature","properties":{"codesPostaux":["51290"],"population":95,"nom":"Moncetz-l'Abbaye","code":"51373"},"geometry":{"type":"Point","coordinates":[4.661382647058822,48.64498602941176]}}]}