{"type":"FeatureCollection","features":[{"type":"Feature","properties":{"codesPostaux":["51500"],"population":259,"nom":"Montbr\u00e9","code":"51375"},"geometry":{"type":"Point","coordinates":[4.047543846153845,49.19193102564104]}}]}