{"type":"FeatureCollection","features":[{"type":"Feature","properties":{"codesPostaux":["51530"],"population":355,"nom":"Monthelon","code":"51378"},"geometry":{"type":"Point","coordinates":[3.935701363636365,48.99653999999998]}}]}