{"type":"FeatureCollection","features":[{"type":"Feature","properties":{"codesPostaux":["51530"],"population":309,"nom":"Moslins","code":"51387"},"geometry":{"type":"Point","coordinates":[3.918277642276423,48.95741959349591]}}]}