{"type":"FeatureCollection","features":[{"type":"Feature","properties":{"codesPostaux":["51160"],"population":204,"nom":"Mutigny","code":"51392"},"geometry":{"type":"Point","coordinates":[4.021378804347826,49.07440804347825]}}]}