{"type":"FeatureCollection","features":[{"type":"Feature","properties":{"codesPostaux":["51300"],"population":152,"nom":"Norrois","code":"51406"},"geometry":{"type":"Point","coordinates":[4.619517499999999,48.67034047619049]}}]}