{"type":"FeatureCollection","features":[{"type":"Feature","properties":{"codesPostaux":["51480"],"population":612,"nom":"\u0152uilly","code":"51410"},"geometry":{"type":"Point","coordinates":[3.797498554216867,49.065500120481914]}}]}