{"type":"FeatureCollection","features":[{"type":"Feature","properties":{"codesPostaux":["51120"],"population":73,"nom":"Oyes","code":"51421"},"geometry":{"type":"Point","coordinates":[3.7574255696202523,48.81271531645571]}}]}