{"type":"FeatureCollection","features":[{"type":"Feature","properties":{"codesPostaux":["51240"],"population":914,"nom":"Pogny","code":"51436"},"geometry":{"type":"Point","coordinates":[4.4885994594594605,48.85534324324328]}}]}