{"type":"FeatureCollection","features":[{"type":"Feature","properties":{"codesPostaux":["51460"],"population":76,"nom":"Poix","code":"51438"},"geometry":{"type":"Point","coordinates":[4.630932857142858,48.95884020408164]}}]}