{"type":"FeatureCollection","features":[{"type":"Feature","properties":{"codesPostaux":["51330"],"population":34,"nom":"Raps\u00e9court","code":"51452"},"geometry":{"type":"Point","coordinates":[4.784662638888889,49.021382500000016]}}]}