{"type":"FeatureCollection","features":[{"type":"Feature","properties":{"codesPostaux":["51330"],"population":60,"nom":"Remicourt","code":"51456"},"geometry":{"type":"Point","coordinates":[4.85729385321101,48.949210642201834]}}]}