{"type":"FeatureCollection","features":[{"type":"Feature","properties":{"codesPostaux":["51600"],"population":337,"nom":"Saint-Hilaire-le-Grand","code":"51486"},"geometry":{"type":"Point","coordinates":[4.464412920353983,49.16864663716812]}}]}