{"type":"FeatureCollection","features":[{"type":"Feature","properties":{"codesPostaux":["51120"],"population":79,"nom":"Saint-Loup","code":"51495"},"geometry":{"type":"Point","coordinates":[3.8228381395348836,48.73457581395349]}}]}