{"type":"FeatureCollection","features":[{"type":"Feature","properties":{"codesPostaux":["51470"],"population":5595,"nom":"Saint-Memmie","code":"51506"},"geometry":{"type":"Point","coordinates":[4.418915833333334,48.953133958333325]}}]}