{"type":"FeatureCollection","features":[{"type":"Feature","properties":{"codesPostaux":["51600"],"population":333,"nom":"Saint-Remy-sur-Bussy","code":"51515"},"geometry":{"type":"Point","coordinates":[4.588957962962963,49.06003833333333]}}]}