{"type":"FeatureCollection","features":[{"type":"Feature","properties":{"codesPostaux":["51120"],"population":105,"nom":"Saint-Remy-sous-Broyes","code":"51514"},"geometry":{"type":"Point","coordinates":[3.771786603773586,48.70316396226414]}}]}