{"type":"FeatureCollection","features":[{"type":"Feature","properties":{"codesPostaux":["51260"],"population":291,"nom":"Saron-sur-Aube","code":"51524"},"geometry":{"type":"Point","coordinates":[3.7352852000000007,48.57358660000002]}}]}