{"type":"FeatureCollection","features":[{"type":"Feature","properties":{"codesPostaux":["51170"],"population":177,"nom":"Serzy-et-Prin","code":"51534"},"geometry":{"type":"Point","coordinates":[3.7634852419354843,49.24588201612902]}}]}