{"type":"FeatureCollection","features":[{"type":"Feature","properties":{"codesPostaux":["51800"],"population":116,"nom":"Servon-Melzicourt","code":"51533"},"geometry":{"type":"Point","coordinates":[4.846331148148148,49.20457600000004]}}]}