{"type":"FeatureCollection","features":[{"type":"Feature","properties":{"codesPostaux":["51800"],"population":80,"nom":"Somme-Bionne","code":"51543"},"geometry":{"type":"Point","coordinates":[4.720695094339624,49.09094471698113]}}]}