{"type":"FeatureCollection","features":[{"type":"Feature","properties":{"codesPostaux":["51600"],"population":3998,"nom":"Suippes","code":"51559"},"geometry":{"type":"Point","coordinates":[4.519852347826087,49.12625565217393]}}]}