{"type":"FeatureCollection","features":[{"type":"Feature","properties":{"codesPostaux":["51510"],"population":281,"nom":"Thibie","code":"51566"},"geometry":{"type":"Point","coordinates":[4.214396610169491,48.91761338983049]}}]}