{"type":"FeatureCollection","features":[{"type":"Feature","properties":{"codesPostaux":["51370"],"population":377,"nom":"Thillois","code":"51569"},"geometry":{"type":"Point","coordinates":[3.9470386666666664,49.260067999999976]}}]}