{"type":"FeatureCollection","features":[{"type":"Feature","properties":{"codesPostaux":["51130"],"population":74,"nom":"Tr\u00e9con","code":"51578"},"geometry":{"type":"Point","coordinates":[4.082631960784314,48.86433686274509]}}]}