{"type":"FeatureCollection","features":[{"type":"Feature","properties":{"codesPostaux":["51400"],"population":260,"nom":"Vadenay","code":"51587"},"geometry":{"type":"Point","coordinates":[4.410285339805825,49.07840796116504]}}]}