{"type":"FeatureCollection","features":[{"type":"Feature","properties":{"codesPostaux":["51210"],"population":365,"nom":"Vauchamps","code":"51596"},"geometry":{"type":"Point","coordinates":[3.628904777777779,48.878885222222216]}}]}