{"type":"FeatureCollection","features":[{"type":"Feature","properties":{"codesPostaux":["51220"],"population":302,"nom":"Villers-Franqueux","code":"51633"},"geometry":{"type":"Point","coordinates":[3.9442989655172407,49.328131379310335]}}]}