{"type":"FeatureCollection","features":[{"type":"Feature","properties":{"codesPostaux":["51420"],"population":4833,"nom":"Witry-l\u00e8s-Reims","code":"51662"},"geometry":{"type":"Point","coordinates":[4.11591756302521,49.29091470588233]}}]}