{"type":"FeatureCollection","features":[{"type":"Feature","properties":{"codesPostaux":["52360"],"population":115,"nom":"Andilly-en-Bassigny","code":"52009"},"geometry":{"type":"Point","coordinates":[5.518311634615383,47.92605846153846]}}]}