{"type":"FeatureCollection","features":[{"type":"Feature","properties":{"codesPostaux":["52310"],"population":67,"nom":"Ann\u00e9ville-la-Prairie","code":"52011"},"geometry":{"type":"Point","coordinates":[5.088780933333332,48.19779013333335]}}]}