{"type":"FeatureCollection","features":[{"type":"Feature","properties":{"codesPostaux":["52160"],"population":189,"nom":"Auberive","code":"52023"},"geometry":{"type":"Point","coordinates":[5.116450554156174,47.77926730478587]}}]}