{"type":"FeatureCollection","features":[{"type":"Feature","properties":{"codesPostaux":["52190"],"population":83,"nom":"Aujeurres","code":"52027"},"geometry":{"type":"Point","coordinates":[5.174245434782607,47.742083152173926]}}]}