{"type":"FeatureCollection","features":[{"type":"Feature","properties":{"codesPostaux":["52100"],"population":1722,"nom":"Bettancourt-la-Ferr\u00e9e","code":"52045"},"geometry":{"type":"Point","coordinates":[4.9712005084745785,48.65472279661017]}}]}