{"type":"FeatureCollection","features":[{"type":"Feature","properties":{"codesPostaux":["52110"],"population":103,"nom":"Beurville","code":"52047"},"geometry":{"type":"Point","coordinates":[4.86136539473684,48.314351052631594]}}]}