{"type":"FeatureCollection","features":[{"type":"Feature","properties":{"codesPostaux":["52270"],"population":621,"nom":"Roches-Bettaincourt","code":"52044"},"geometry":{"type":"Point","coordinates":[5.27011072463768,48.30086207729467]}}]}