{"type":"FeatureCollection","features":[{"type":"Feature","properties":{"codesPostaux":["52340"],"population":1373,"nom":"Biesles","code":"52050"},"geometry":{"type":"Point","coordinates":[5.295755895953755,48.10015589595379]}}]}