{"type":"FeatureCollection","features":[{"type":"Feature","properties":{"codesPostaux":["52110"],"population":107,"nom":"Blumeray","code":"52057"},"geometry":{"type":"Point","coordinates":[4.861434696969696,48.35567893939395]}}]}