{"type":"FeatureCollection","features":[{"type":"Feature","properties":{"codesPostaux":["52200"],"population":136,"nom":"Brennes","code":"52070"},"geometry":{"type":"Point","coordinates":[5.28481481927711,47.79698024096384]}}]}