{"type":"FeatureCollection","features":[{"type":"Feature","properties":{"codesPostaux":["52240"],"population":690,"nom":"Breuvannes-en-Bassigny","code":"52074"},"geometry":{"type":"Point","coordinates":[5.622538488576449,48.07833936731106]}}]}