{"type":"FeatureCollection","features":[{"type":"Feature","properties":{"codesPostaux":["52700"],"population":192,"nom":"Briaucourt","code":"52075"},"geometry":{"type":"Point","coordinates":[5.19643786407767,48.20925029126215]}}]}