{"type":"FeatureCollection","features":[{"type":"Feature","properties":{"codesPostaux":["52000"],"population":356,"nom":"Brethenay","code":"52072"},"geometry":{"type":"Point","coordinates":[5.1385675675675655,48.15612391891891]}}]}