{"type":"FeatureCollection","features":[{"type":"Feature","properties":{"codesPostaux":["52130"],"population":733,"nom":"Brousseval","code":"52079"},"geometry":{"type":"Point","coordinates":[4.9835223809523805,48.493486190476204]}}]}