{"type":"FeatureCollection","features":[{"type":"Feature","properties":{"codesPostaux":["52700"],"population":47,"nom":"Chambroncourt","code":"52097"},"geometry":{"type":"Point","coordinates":[5.402699619047621,48.35027285714284]}}]}