{"type":"FeatureCollection","features":[{"type":"Feature","properties":{"codesPostaux":["52700"],"population":196,"nom":"Chalvraines","code":"52095"},"geometry":{"type":"Point","coordinates":[5.505088571428573,48.23422714285713]}}]}