{"type":"FeatureCollection","features":[{"type":"Feature","properties":{"codesPostaux":["52410"],"population":835,"nom":"Chamouilley","code":"52099"},"geometry":{"type":"Point","coordinates":[5.0504783333333325,48.60918654761904]}}]}