{"type":"FeatureCollection","features":[{"type":"Feature","properties":{"codesPostaux":["52600"],"population":2435,"nom":"Chalindrey","code":"52093"},"geometry":{"type":"Point","coordinates":[5.44088096330275,47.79642600917433]}}]}