{"type":"FeatureCollection","features":[{"type":"Feature","properties":{"codesPostaux":["52360"],"population":57,"nom":"Chatenay-Vaudin","code":"52116"},"geometry":{"type":"Point","coordinates":[5.448563013698627,47.85252506849316]}}]}