{"type":"FeatureCollection","features":[{"type":"Feature","properties":{"codesPostaux":["52000"],"population":1040,"nom":"Chamarandes-Choignes","code":"52125"},"geometry":{"type":"Point","coordinates":[5.184764728682171,48.100027364341074]}}]}