{"type":"FeatureCollection","features":[{"type":"Feature","properties":{"codesPostaux":["52150"],"population":116,"nom":"Chaumont-la-Ville","code":"52122"},"geometry":{"type":"Point","coordinates":[5.647551458333333,48.143842916666685]}}]}