{"type":"FeatureCollection","features":[{"type":"Feature","properties":{"codesPostaux":["52240"],"population":204,"nom":"Clefmont","code":"52132"},"geometry":{"type":"Point","coordinates":[5.505883141762455,48.106919386973246]}}]}