{"type":"FeatureCollection","features":[{"type":"Feature","properties":{"codesPostaux":["52700"],"population":90,"nom":"Clinchamp","code":"52133"},"geometry":{"type":"Point","coordinates":[5.440219130434783,48.19358339130432]}}]}