{"type":"FeatureCollection","features":[{"type":"Feature","properties":{"codesPostaux":["52000"],"population":312,"nom":"Condes","code":"52141"},"geometry":{"type":"Point","coordinates":[5.1431530882352945,48.14188014705883]}}]}