{"type":"FeatureCollection","features":[{"type":"Feature","properties":{"codesPostaux":["52130"],"population":88,"nom":"Domblain","code":"52169"},"geometry":{"type":"Point","coordinates":[5.004780909090908,48.46724393939394]}}]}