{"type":"FeatureCollection","features":[{"type":"Feature","properties":{"codesPostaux":["52140"],"population":209,"nom":"Dammartin-sur-Meuse","code":"52162"},"geometry":{"type":"Point","coordinates":[5.587829230769229,47.982077482517475]}}]}