{"type":"FeatureCollection","features":[{"type":"Feature","properties":{"codesPostaux":["52270"],"population":88,"nom":"Domremy-Land\u00e9ville","code":"52173"},"geometry":{"type":"Point","coordinates":[5.2547830701754386,48.360704035087714]}}]}