{"type":"FeatureCollection","features":[{"type":"Feature","properties":{"codesPostaux":["52110"],"population":276,"nom":"Dommartin-le-Saint-P\u00e8re","code":"52172"},"geometry":{"type":"Point","coordinates":[4.9147289230769236,48.406180461538426]}}]}