{"type":"FeatureCollection","features":[{"type":"Feature","properties":{"codesPostaux":["52230"],"population":97,"nom":"\u00c9chenay","code":"52181"},"geometry":{"type":"Point","coordinates":[5.309118240740741,48.46250462962965]}}]}