{"type":"FeatureCollection","features":[{"type":"Feature","properties":{"codesPostaux":["52600"],"population":69,"nom":"Grandchamp","code":"52228"},"geometry":{"type":"Point","coordinates":[5.443721044776118,47.72056104477615]}}]}