{"type":"FeatureCollection","features":[{"type":"Feature","properties":{"codesPostaux":["52290"],"population":817,"nom":"Humb\u00e9court","code":"52244"},"geometry":{"type":"Point","coordinates":[4.906054259259259,48.574558055555585]}}]}