{"type":"FeatureCollection","features":[{"type":"Feature","properties":{"codesPostaux":["52140"],"population":568,"nom":"Is-en-Bassigny","code":"52248"},"geometry":{"type":"Point","coordinates":[5.446743866666665,48.03459626666666]}}]}