{"type":"FeatureCollection","features":[{"type":"Feature","properties":{"codesPostaux":["52400"],"population":70,"nom":"Laneuvelle","code":"52264"},"geometry":{"type":"Point","coordinates":[5.668454239130438,47.93165782608697]}}]}