{"type":"FeatureCollection","features":[{"type":"Feature","properties":{"codesPostaux":["52700"],"population":316,"nom":"Liffol-le-Petit","code":"52289"},"geometry":{"type":"Point","coordinates":[5.537573069306929,48.292533861386126]}}]}