{"type":"FeatureCollection","features":[{"type":"Feature","properties":{"codesPostaux":["52500"],"population":103,"nom":"Maizi\u00e8res-sur-Amance","code":"52303"},"geometry":{"type":"Point","coordinates":[5.612004331210193,47.833837197452205]}}]}