{"type":"FeatureCollection","features":[{"type":"Feature","properties":{"codesPostaux":["52700"],"population":151,"nom":"Mareilles","code":"52313"},"geometry":{"type":"Point","coordinates":[5.253670575539569,48.1760154676259]}}]}