{"type":"FeatureCollection","features":[{"type":"Feature","properties":{"codesPostaux":["52320"],"population":43,"nom":"Mirbel","code":"52326"},"geometry":{"type":"Point","coordinates":[5.038275748031499,48.28228881889763]}}]}