{"type":"FeatureCollection","features":[{"type":"Feature","properties":{"codesPostaux":["52240"],"population":114,"nom":"Merrey","code":"52320"},"geometry":{"type":"Point","coordinates":[5.59443487394958,48.05309537815125]}}]}