{"type":"FeatureCollection","features":[{"type":"Feature","properties":{"codesPostaux":["52400"],"population":82,"nom":"Neuvelle-l\u00e8s-Voisey","code":"52350"},"geometry":{"type":"Point","coordinates":[5.790490571428573,47.86265014285715]}}]}