{"type":"FeatureCollection","features":[{"type":"Feature","properties":{"codesPostaux":["52360"],"population":96,"nom":"Orbigny-au-Val","code":"52363"},"geometry":{"type":"Point","coordinates":[5.426277954545456,47.88222227272726]}}]}