{"type":"FeatureCollection","features":[{"type":"Feature","properties":{"codesPostaux":["52500"],"population":46,"nom":"Pisseloup","code":"52390"},"geometry":{"type":"Point","coordinates":[5.741704069767442,47.830987209302336]}}]}