{"type":"FeatureCollection","features":[{"type":"Feature","properties":{"codesPostaux":["52230"],"population":37,"nom":"Sailly","code":"52443"},"geometry":{"type":"Point","coordinates":[5.264455851063829,48.43523159574467]}}]}