{"type":"FeatureCollection","features":[{"type":"Feature","properties":{"codesPostaux":["52200"],"population":104,"nom":"Saint-Martin-l\u00e8s-Langres","code":"52452"},"geometry":{"type":"Point","coordinates":[5.2688366666666635,47.89332356321839]}}]}