{"type":"FeatureCollection","features":[{"type":"Feature","properties":{"codesPostaux":["52210"],"population":154,"nom":"Saint-Loup-sur-Aujon","code":"52450"},"geometry":{"type":"Point","coordinates":[5.080623043478259,47.87871490683229]}}]}