{"type":"FeatureCollection","features":[{"type":"Feature","properties":{"codesPostaux":["52700"],"population":101,"nom":"Semilly","code":"52468"},"geometry":{"type":"Point","coordinates":[5.465567078651685,48.24908359550561]}}]}