{"type":"FeatureCollection","features":[{"type":"Feature","properties":{"codesPostaux":["52400"],"population":67,"nom":"Soyers","code":"52483"},"geometry":{"type":"Point","coordinates":[5.6902386238532126,47.86427110091743]}}]}