{"type":"FeatureCollection","features":[{"type":"Feature","properties":{"codesPostaux":["52500"],"population":34,"nom":"Tornay","code":"52493"},"geometry":{"type":"Point","coordinates":[5.596320096153848,47.693696442307704]}}]}