{"type":"FeatureCollection","features":[{"type":"Feature","properties":{"codesPostaux":["52500"],"population":28,"nom":"Valleroy","code":"52503"},"geometry":{"type":"Point","coordinates":[5.660179859154927,47.697214225352106]}}]}