{"type":"FeatureCollection","features":[{"type":"Feature","properties":{"codesPostaux":["52700"],"population":125,"nom":"Vesaignes-sous-Lafauche","code":"52517"},"geometry":{"type":"Point","coordinates":[5.441925784313726,48.28724862745097]}}]}