{"type":"FeatureCollection","features":[{"type":"Feature","properties":{"codesPostaux":["52000"],"population":306,"nom":"Verbiesles","code":"52514"},"geometry":{"type":"Point","coordinates":[5.191893612903225,48.07598000000001]}}]}