{"type":"FeatureCollection","features":[{"type":"Feature","properties":{"codesPostaux":["52800"],"population":108,"nom":"Vesaignes-sur-Marne","code":"52518"},"geometry":{"type":"Point","coordinates":[5.261687452830187,47.99984349056603]}}]}