{"type":"FeatureCollection","features":[{"type":"Feature","properties":{"codesPostaux":["52600"],"population":80,"nom":"Violot","code":"52539"},"geometry":{"type":"Point","coordinates":[5.444625542168672,47.75891879518074]}}]}