{"type":"FeatureCollection","features":[{"type":"Feature","properties":{"codesPostaux":["52200"],"population":89,"nom":"Voisines","code":"52545"},"geometry":{"type":"Point","coordinates":[5.181703583815027,47.85564352601156]}}]}