{"type":"FeatureCollection","features":[{"type":"Feature","properties":{"codesPostaux":["53210"],"population":2717,"nom":"Argentr\u00e9","code":"53007"},"geometry":{"type":"Point","coordinates":[-0.6234039200000006,48.09033663999998]}}]}