{"type":"FeatureCollection","features":[{"type":"Feature","properties":{"codesPostaux":["53800"],"population":127,"nom":"La Boissi\u00e8re","code":"53033"},"geometry":{"type":"Point","coordinates":[-0.9780105769230766,47.77504326923076]}}]}