{"type":"FeatureCollection","features":[{"type":"Feature","properties":{"codesPostaux":["53170"],"population":338,"nom":"Le Bignon-du-Maine","code":"53030"},"geometry":{"type":"Point","coordinates":[-0.6269240397350997,47.95154476821191]}}]}