{"type":"FeatureCollection","features":[{"type":"Feature","properties":{"codesPostaux":["53170"],"population":307,"nom":"Le Buret","code":"53046"},"geometry":{"type":"Point","coordinates":[-0.49275627272727274,47.921483909090924]}}]}