{"type":"FeatureCollection","features":[{"type":"Feature","properties":{"codesPostaux":["53120"],"population":823,"nom":"Brec\u00e9","code":"53042"},"geometry":{"type":"Point","coordinates":[-0.7698252395209578,48.38947125748501]}}]}