{"type":"FeatureCollection","features":[{"type":"Feature","properties":{"codesPostaux":["53370"],"population":313,"nom":"Champfr\u00e9mont","code":"53052"},"geometry":{"type":"Point","coordinates":[-0.10537815126050423,48.43416176470588]}}]}