{"type":"FeatureCollection","features":[{"type":"Feature","properties":{"codesPostaux":["53100"],"population":902,"nom":"Contest","code":"53074"},"geometry":{"type":"Point","coordinates":[-0.6986839748953972,48.26064368200834]}}]}