{"type":"FeatureCollection","features":[{"type":"Feature","properties":{"codesPostaux":["53700"],"population":202,"nom":"Crennes-sur-Fraub\u00e9e","code":"53085"},"geometry":{"type":"Point","coordinates":[-0.2687509638554214,48.37922873493977]}}]}