{"type":"FeatureCollection","features":[{"type":"Feature","properties":{"codesPostaux":["53230"],"population":653,"nom":"Courbeveille","code":"53082"},"geometry":{"type":"Point","coordinates":[-0.8865536224489796,47.984043826530616]}}]}