{"type":"FeatureCollection","features":[{"type":"Feature","properties":{"codesPostaux":["53540"],"population":916,"nom":"Cuill\u00e9","code":"53088"},"geometry":{"type":"Point","coordinates":[-1.1129555555555555,47.97097739837396]}}]}