{"type":"FeatureCollection","features":[{"type":"Feature","properties":{"codesPostaux":["53370"],"population":549,"nom":"Gesvres","code":"53106"},"geometry":{"type":"Point","coordinates":[-0.16079945945945961,48.38027691891895]}}]}