{"type":"FeatureCollection","features":[{"type":"Feature","properties":{"codesPostaux":["53540"],"population":159,"nom":"Gastines","code":"53102"},"geometry":{"type":"Point","coordinates":[-1.113407443609023,47.943470075187996]}}]}