{"type":"FeatureCollection","features":[{"type":"Feature","properties":{"codesPostaux":["53140"],"population":773,"nom":"Ligni\u00e8res-Org\u00e8res","code":"53133"},"geometry":{"type":"Point","coordinates":[-0.21773967948717962,48.52652788461538]}}]}