{"type":"FeatureCollection","features":[{"type":"Feature","properties":{"codesPostaux":["53440"],"population":804,"nom":"Marcill\u00e9-la-Ville","code":"53144"},"geometry":{"type":"Point","coordinates":[-0.47257256227758004,48.31982348754449]}}]}