{"type":"FeatureCollection","features":[{"type":"Feature","properties":{"codesPostaux":["53210"],"population":1109,"nom":"Louvign\u00e9","code":"53141"},"geometry":{"type":"Point","coordinates":[-0.6338542702702704,48.05313843243244]}}]}