{"type":"FeatureCollection","features":[{"type":"Feature","properties":{"codesPostaux":["53150"],"population":365,"nom":"Montourtier","code":"53159"},"geometry":{"type":"Point","coordinates":[-0.5454546853146851,48.20923223776226]}}]}