{"type":"FeatureCollection","features":[{"type":"Feature","properties":{"codesPostaux":["53300"],"population":529,"nom":"Le Pas","code":"53176"},"geometry":{"type":"Point","coordinates":[-0.699718571428571,48.422460448979585]}}]}