{"type":"FeatureCollection","features":[{"type":"Feature","properties":{"codesPostaux":["53100"],"population":797,"nom":"Parign\u00e9-sur-Braye","code":"53174"},"geometry":{"type":"Point","coordinates":[-0.6504161864406779,48.31840915254237]}}]}