{"type":"FeatureCollection","features":[{"type":"Feature","properties":{"codesPostaux":["53170"],"population":521,"nom":"Ruill\u00e9-Froid-Fonds","code":"53193"},"geometry":{"type":"Point","coordinates":[-0.6257500540540544,47.9013475135135]}}]}