{"type":"FeatureCollection","features":[{"type":"Feature","properties":{"codesPostaux":["53240"],"population":1616,"nom":"Saint-Jean-sur-Mayenne","code":"53229"},"geometry":{"type":"Point","coordinates":[-0.7545217351598172,48.142061050228335]}}]}