{"type":"FeatureCollection","features":[{"type":"Feature","properties":{"codesPostaux":["53240"],"population":366,"nom":"Saint-Germain-d'Anxure","code":"53222"},"geometry":{"type":"Point","coordinates":[-0.7329520168067225,48.22209306722687]}}]}