{"type":"FeatureCollection","features":[{"type":"Feature","properties":{"codesPostaux":["53150"],"population":199,"nom":"Saint-Ou\u00ebn-des-Vallons","code":"53244"},"geometry":{"type":"Point","coordinates":[-0.5566048226950356,48.172996595744664]}}]}