{"type":"FeatureCollection","features":[{"type":"Feature","properties":{"codesPostaux":["53350"],"population":246,"nom":"Saint-Michel-de-la-Ro\u00eb","code":"53242"},"geometry":{"type":"Point","coordinates":[-1.1329337962962962,47.87264129629631]}}]}