{"type":"FeatureCollection","features":[{"type":"Feature","properties":{"codesPostaux":["53390"],"population":336,"nom":"Senonnes","code":"53259"},"geometry":{"type":"Point","coordinates":[-1.2029246031746028,47.808535793650776]}}]}