{"type":"FeatureCollection","features":[{"type":"Feature","properties":{"codesPostaux":["53400"],"population":408,"nom":"Saint-Quentin-les-Anges","code":"53251"},"geometry":{"type":"Point","coordinates":[-0.8877168246445495,47.78808819905215]}}]}