{"type":"FeatureCollection","features":[{"type":"Feature","properties":{"codesPostaux":["53160"],"population":202,"nom":"Saint-Thomas-de-Courceriers","code":"53256"},"geometry":{"type":"Point","coordinates":[-0.2654065367965368,48.261350389610364]}}]}