{"type":"FeatureCollection","features":[{"type":"Feature","properties":{"codesPostaux":["53210"],"population":1104,"nom":"Soulg\u00e9-sur-Ouette","code":"53262"},"geometry":{"type":"Point","coordinates":[-0.5581344374999995,48.062413499999984]}}]}