{"type":"FeatureCollection","features":[{"type":"Feature","properties":{"codesPostaux":["54170"],"population":463,"nom":"Allain","code":"54008"},"geometry":{"type":"Point","coordinates":[5.920232417582418,48.55194384615383]}}]}