{"type":"FeatureCollection","features":[{"type":"Feature","properties":{"codesPostaux":["54370"],"population":247,"nom":"Arracourt","code":"54023"},"geometry":{"type":"Point","coordinates":[6.529610469798659,48.72564228187919]}}]}