{"type":"FeatureCollection","features":[{"type":"Feature","properties":{"codesPostaux":["54760"],"population":217,"nom":"Armaucourt","code":"54021"},"geometry":{"type":"Point","coordinates":[6.299062321428573,48.8118767857143]}}]}