{"type":"FeatureCollection","features":[{"type":"Feature","properties":{"codesPostaux":["54110"],"population":446,"nom":"Anthelupt","code":"54020"},"geometry":{"type":"Point","coordinates":[6.416408859649122,48.604837894736846]}}]}