{"type":"FeatureCollection","features":[{"type":"Feature","properties":{"codesPostaux":["54360"],"population":430,"nom":"Barbonville","code":"54045"},"geometry":{"type":"Point","coordinates":[6.3552033823529435,48.55132404411762]}}]}