{"type":"FeatureCollection","features":[{"type":"Feature","properties":{"codesPostaux":["54980"],"population":1221,"nom":"Batilly","code":"54051"},"geometry":{"type":"Point","coordinates":[5.97027839506173,49.17620345679013]}}]}