{"type":"FeatureCollection","features":[{"type":"Feature","properties":{"codesPostaux":["54620"],"population":148,"nom":"Bazailles","code":"54056"},"geometry":{"type":"Point","coordinates":[5.765886611570249,49.411165867768595]}}]}