{"type":"FeatureCollection","features":[{"type":"Feature","properties":{"codesPostaux":["54290"],"population":1622,"nom":"Bayon","code":"54054"},"geometry":{"type":"Point","coordinates":[6.323007925925928,48.48000822222221]}}]}