{"type":"FeatureCollection","features":[{"type":"Feature","properties":{"codesPostaux":["54940"],"population":1413,"nom":"Belleville","code":"54060"},"geometry":{"type":"Point","coordinates":[6.086055135135138,48.813484054054015]}}]}