{"type":"FeatureCollection","features":[{"type":"Feature","properties":{"codesPostaux":["54120"],"population":1080,"nom":"Bertrichamps","code":"54065"},"geometry":{"type":"Point","coordinates":[6.804409823529414,48.43220364705883]}}]}