{"type":"FeatureCollection","features":[{"type":"Feature","properties":{"codesPostaux":["54200"],"population":257,"nom":"Bouvron","code":"54088"},"geometry":{"type":"Point","coordinates":[5.886713255813954,48.73927662790698]}}]}