{"type":"FeatureCollection","features":[{"type":"Feature","properties":{"codesPostaux":["54770"],"population":1429,"nom":"Bouxi\u00e8res-aux-Ch\u00eanes","code":"54089"},"geometry":{"type":"Point","coordinates":[6.276919084507042,48.77110007042254]}}]}