{"type":"FeatureCollection","features":[{"type":"Feature","properties":{"codesPostaux":["54300"],"population":188,"nom":"Bonviller","code":"54083"},"geometry":{"type":"Point","coordinates":[6.4914986440677955,48.62889169491526]}}]}