{"type":"FeatureCollection","features":[{"type":"Feature","properties":{"codesPostaux":["54290"],"population":97,"nom":"Borville","code":"54085"},"geometry":{"type":"Point","coordinates":[6.395848901098902,48.447030109890115]}}]}