{"type":"FeatureCollection","features":[{"type":"Feature","properties":{"codesPostaux":["54136"],"population":4120,"nom":"Bouxi\u00e8res-aux-Dames","code":"54090"},"geometry":{"type":"Point","coordinates":[6.162833333333334,48.758527222222206]}}]}