{"type":"FeatureCollection","features":[{"type":"Feature","properties":{"codesPostaux":["54110"],"population":270,"nom":"Buissoncourt","code":"54104"},"geometry":{"type":"Point","coordinates":[6.335651574074073,48.67798194444445]}}]}