{"type":"FeatureCollection","features":[{"type":"Feature","properties":{"codesPostaux":["54280"],"population":746,"nom":"Brin-sur-Seille","code":"54100"},"geometry":{"type":"Point","coordinates":[6.366788191489364,48.77612840425533]}}]}