{"type":"FeatureCollection","features":[{"type":"Feature","properties":{"codesPostaux":["54230"],"population":2937,"nom":"Chaligny","code":"54111"},"geometry":{"type":"Point","coordinates":[6.092071503759398,48.63250308270677]}}]}