{"type":"FeatureCollection","features":[{"type":"Feature","properties":{"codesPostaux":["54330"],"population":114,"nom":"Chaouilley","code":"54117"},"geometry":{"type":"Point","coordinates":[6.064294743589746,48.44319487179488]}}]}