{"type":"FeatureCollection","features":[{"type":"Feature","properties":{"codesPostaux":["54300"],"population":2145,"nom":"Chanteheux","code":"54116"},"geometry":{"type":"Point","coordinates":[6.536619320388352,48.59481320388349]}}]}