{"type":"FeatureCollection","features":[{"type":"Feature","properties":{"codesPostaux":["54480"],"population":1702,"nom":"Cirey-sur-Vezouze","code":"54129"},"geometry":{"type":"Point","coordinates":[6.942112901554404,48.58728160621762]}}]}