{"type":"FeatureCollection","features":[{"type":"Feature","properties":{"codesPostaux":["54110"],"population":302,"nom":"Courbesseaux","code":"54139"},"geometry":{"type":"Point","coordinates":[6.4013225925925905,48.691921481481494]}}]}