{"type":"FeatureCollection","features":[{"type":"Feature","properties":{"codesPostaux":["54610"],"population":508,"nom":"Cl\u00e9mery","code":"54131"},"geometry":{"type":"Point","coordinates":[6.177417345132744,48.881686371681425]}}]}