{"type":"FeatureCollection","features":[{"type":"Feature","properties":{"codesPostaux":["54380"],"population":4572,"nom":"Dieulouard","code":"54157"},"geometry":{"type":"Point","coordinates":[6.051063103448276,48.83758471264368]}}]}