{"type":"FeatureCollection","features":[{"type":"Feature","properties":{"codesPostaux":["54385"],"population":413,"nom":"Dom\u00e8vre-en-Haye","code":"54160"},"geometry":{"type":"Point","coordinates":[5.936933571428575,48.81539133928569]}}]}