{"type":"FeatureCollection","features":[{"type":"Feature","properties":{"codesPostaux":["54370"],"population":195,"nom":"Drouville","code":"54173"},"geometry":{"type":"Point","coordinates":[6.409434000000002,48.66967093333335]}}]}