{"type":"FeatureCollection","features":[{"type":"Feature","properties":{"codesPostaux":["54150"],"population":294,"nom":"Fl\u00e9ville-Lixi\u00e8res","code":"54198"},"geometry":{"type":"Point","coordinates":[5.808182122905028,49.242008435754165]}}]}