{"type":"FeatureCollection","features":[{"type":"Feature","properties":{"codesPostaux":["54830"],"population":57,"nom":"Franconville","code":"54209"},"geometry":{"type":"Point","coordinates":[6.451170454545454,48.50066431818181]}}]}