{"type":"FeatureCollection","features":[{"type":"Feature","properties":{"codesPostaux":["54930"],"population":92,"nom":"Forcelles-sous-Gugney","code":"54204"},"geometry":{"type":"Point","coordinates":[6.083269500000003,48.392806600000014]}}]}