{"type":"FeatureCollection","features":[{"type":"Feature","properties":{"codesPostaux":["54570"],"population":2668,"nom":"Foug","code":"54205"},"geometry":{"type":"Point","coordinates":[5.783834866666665,48.67816726666668]}}]}