{"type":"FeatureCollection","features":[{"type":"Feature","properties":{"codesPostaux":["54800"],"population":182,"nom":"Gondrecourt-Aix","code":"54231"},"geometry":{"type":"Point","coordinates":[5.761823354430379,49.242261645569606]}}]}