{"type":"FeatureCollection","features":[{"type":"Feature","properties":{"codesPostaux":["54470"],"population":54,"nom":"Grosrouvres","code":"54240"},"geometry":{"type":"Point","coordinates":[5.845126818181819,48.8257887878788]}}]}