{"type":"FeatureCollection","features":[{"type":"Feature","properties":{"codesPostaux":["54450"],"population":213,"nom":"Herb\u00e9viller","code":"54259"},"geometry":{"type":"Point","coordinates":[6.749362958579886,48.55637301775146]}}]}