{"type":"FeatureCollection","features":[{"type":"Feature","properties":{"codesPostaux":["54800"],"population":383,"nom":"Jeandelize","code":"54277"},"geometry":{"type":"Point","coordinates":[5.79713012345679,49.17074222222221]}}]}