{"type":"FeatureCollection","features":[{"type":"Feature","properties":{"codesPostaux":["54800"],"population":1565,"nom":"Labry","code":"54286"},"geometry":{"type":"Point","coordinates":[5.870998571428573,49.1824674489796]}}]}