{"type":"FeatureCollection","features":[{"type":"Feature","properties":{"codesPostaux":["54360"],"population":102,"nom":"Land\u00e9court","code":"54293"},"geometry":{"type":"Point","coordinates":[6.4224632098765415,48.50168320987654]}}]}