{"type":"FeatureCollection","features":[{"type":"Feature","properties":{"codesPostaux":["54115"],"population":292,"nom":"Lal\u0153uf","code":"54291"},"geometry":{"type":"Point","coordinates":[6.008710173913046,48.465338086956535]}}]}