{"type":"FeatureCollection","features":[{"type":"Feature","properties":{"codesPostaux":["54700"],"population":329,"nom":"Loisy","code":"54320"},"geometry":{"type":"Point","coordinates":[6.10256075471698,48.871677264150954]}}]}