{"type":"FeatureCollection","features":[{"type":"Feature","properties":{"codesPostaux":["54200"],"population":585,"nom":"Lucey","code":"54327"},"geometry":{"type":"Point","coordinates":[5.833004999999998,48.72594345238093]}}]}