{"type":"FeatureCollection","features":[{"type":"Feature","properties":{"codesPostaux":["54670"],"population":957,"nom":"Malleloy","code":"54338"},"geometry":{"type":"Point","coordinates":[6.167428644067798,48.7934754237288]}}]}