{"type":"FeatureCollection","features":[{"type":"Feature","properties":{"codesPostaux":["54290"],"population":228,"nom":"Mangonville","code":"54344"},"geometry":{"type":"Point","coordinates":[6.285922222222223,48.45167809523808]}}]}