{"type":"FeatureCollection","features":[{"type":"Feature","properties":{"codesPostaux":["54300"],"population":179,"nom":"Manonviller","code":"54349"},"geometry":{"type":"Point","coordinates":[6.660013896103895,48.58511253246752]}}]}