{"type":"FeatureCollection","features":[{"type":"Feature","properties":{"codesPostaux":["54800"],"population":968,"nom":"Mars-la-Tour","code":"54353"},"geometry":{"type":"Point","coordinates":[5.885652302158274,49.097142805755375]}}]}