{"type":"FeatureCollection","features":[{"type":"Feature","properties":{"codesPostaux":["54670"],"population":643,"nom":"Millery","code":"54369"},"geometry":{"type":"Point","coordinates":[6.140475200000002,48.81946249999999]}}]}