{"type":"FeatureCollection","features":[{"type":"Feature","properties":{"codesPostaux":["54540"],"population":88,"nom":"Neuviller-l\u00e8s-Badonviller","code":"54398"},"geometry":{"type":"Point","coordinates":[6.8806766990291255,48.520996504854345]}}]}