{"type":"FeatureCollection","features":[{"type":"Feature","properties":{"codesPostaux":["54330"],"population":112,"nom":"Ogn\u00e9ville","code":"54407"},"geometry":{"type":"Point","coordinates":[6.058327761194029,48.471235671641786]}}]}