{"type":"FeatureCollection","features":[{"type":"Feature","properties":{"codesPostaux":["54150"],"population":412,"nom":"Norroy-le-Sec","code":"54402"},"geometry":{"type":"Point","coordinates":[5.807774153846157,49.2770366153846]}}]}