{"type":"FeatureCollection","features":[{"type":"Feature","properties":{"codesPostaux":["54740"],"population":246,"nom":"Ormes-et-Ville","code":"54411"},"geometry":{"type":"Point","coordinates":[6.202274754098356,48.487927377049196]}}]}