{"type":"FeatureCollection","features":[{"type":"Feature","properties":{"codesPostaux":["54450"],"population":72,"nom":"R\u00e9clonville","code":"54447"},"geometry":{"type":"Point","coordinates":[6.730994938271603,48.53763950617284]}}]}