{"type":"FeatureCollection","features":[{"type":"Feature","properties":{"codesPostaux":["54450"],"population":64,"nom":"Reillon","code":"54452"},"geometry":{"type":"Point","coordinates":[6.7421170238095245,48.598073928571445]}}]}