{"type":"FeatureCollection","features":[{"type":"Feature","properties":{"codesPostaux":["54630"],"population":2396,"nom":"Richardm\u00e9nil","code":"54459"},"geometry":{"type":"Point","coordinates":[6.177725362318841,48.596153043478274]}}]}