{"type":"FeatureCollection","features":[{"type":"Feature","properties":{"codesPostaux":["54450"],"population":67,"nom":"Saint-Martin","code":"54480"},"geometry":{"type":"Point","coordinates":[6.745284695652176,48.56918669565218]}}]}