{"type":"FeatureCollection","features":[{"type":"Feature","properties":{"codesPostaux":["54330"],"population":79,"nom":"Saxon-Sion","code":"54497"},"geometry":{"type":"Point","coordinates":[6.085575769230768,48.418174519230774]}}]}