{"type":"FeatureCollection","features":[{"type":"Feature","properties":{"codesPostaux":["54550"],"population":687,"nom":"Sexey-aux-Forges","code":"54505"},"geometry":{"type":"Point","coordinates":[6.030772376237623,48.62876732673265]}}]}