{"type":"FeatureCollection","features":[{"type":"Feature","properties":{"codesPostaux":["54830"],"population":95,"nom":"Seranville","code":"54501"},"geometry":{"type":"Point","coordinates":[6.515541875000001,48.45935895833332]}}]}