{"type":"FeatureCollection","features":[{"type":"Feature","properties":{"codesPostaux":["54930"],"population":11,"nom":"They-sous-Vaudemont","code":"54516"},"geometry":{"type":"Point","coordinates":[6.054317317073171,48.40278804878049]}}]}