{"type":"FeatureCollection","features":[{"type":"Feature","properties":{"codesPostaux":["54300"],"population":392,"nom":"Thi\u00e9baum\u00e9nil","code":"54520"},"geometry":{"type":"Point","coordinates":[6.627120618556702,48.578293402061824]}}]}