{"type":"FeatureCollection","features":[{"type":"Feature","properties":{"codesPostaux":["54830"],"population":141,"nom":"Vallois","code":"54543"},"geometry":{"type":"Point","coordinates":[6.547209927536229,48.462342391304325]}}]}