{"type":"FeatureCollection","features":[{"type":"Feature","properties":{"codesPostaux":["54480"],"population":623,"nom":"Val-et-Ch\u00e2tillon","code":"54540"},"geometry":{"type":"Point","coordinates":[7.006895429864251,48.553871312217176]}}]}