{"type":"FeatureCollection","features":[{"type":"Feature","properties":{"codesPostaux":["54330"],"population":73,"nom":"Vaud\u00e9mont","code":"54552"},"geometry":{"type":"Point","coordinates":[6.057055980392158,48.42197617647058]}}]}