{"type":"FeatureCollection","features":[{"type":"Feature","properties":{"codesPostaux":["54890"],"population":324,"nom":"Villecey-sur-Mad","code":"54570"},"geometry":{"type":"Point","coordinates":[5.94534445945946,48.99340148648648]}}]}