{"type":"FeatureCollection","features":[{"type":"Feature","properties":{"codesPostaux":["54190"],"population":9415,"nom":"Villerupt","code":"54580"},"geometry":{"type":"Point","coordinates":[5.927459230769229,49.46709240384616]}}]}