{"type":"FeatureCollection","features":[{"type":"Feature","properties":{"codesPostaux":["54200"],"population":1109,"nom":"Villey-Saint-\u00c9tienne","code":"54584"},"geometry":{"type":"Point","coordinates":[5.965634870129871,48.73114253246754]}}]}