{"type":"FeatureCollection","features":[{"type":"Feature","properties":{"codesPostaux":["55320"],"population":596,"nom":"Ancemont","code":"55009"},"geometry":{"type":"Point","coordinates":[5.3806444520547965,49.067839726027394]}}]}