{"type":"FeatureCollection","features":[{"type":"Feature","properties":{"codesPostaux":["55700"],"population":91,"nom":"Beauclair","code":"55036"},"geometry":{"type":"Point","coordinates":[5.122626842105263,49.45565248120302]}}]}