{"type":"FeatureCollection","features":[{"type":"Feature","properties":{"codesPostaux":["55130"],"population":71,"nom":"Baudign\u00e9court","code":"55030"},"geometry":{"type":"Point","coordinates":[5.459375436893201,48.56572310679611]}}]}