{"type":"FeatureCollection","features":[{"type":"Feature","properties":{"codesPostaux":["55100"],"nom":"Beaumont-en-Verdunois","code":"55039"},"geometry":{"type":"Point","coordinates":[5.413572631578948,49.264025000000004]}}]}