{"type":"FeatureCollection","features":[{"type":"Feature","properties":{"codesPostaux":["55300"],"population":60,"nom":"Bisl\u00e9e","code":"55054"},"geometry":{"type":"Point","coordinates":[5.511880510204081,48.871581734693876]}}]}