{"type":"FeatureCollection","features":[{"type":"Feature","properties":{"codesPostaux":["55400"],"population":19,"nom":"Blanz\u00e9e","code":"55055"},"geometry":{"type":"Point","coordinates":[5.531152499999999,49.15986515625]}}]}