{"type":"FeatureCollection","features":[{"type":"Feature","properties":{"codesPostaux":["55300"],"population":132,"nom":"Bouquemont","code":"55064"},"geometry":{"type":"Point","coordinates":[5.435610102040816,48.98440785714286]}}]}