{"type":"FeatureCollection","features":[{"type":"Feature","properties":{"codesPostaux":["55120"],"population":107,"nom":"Brabant-en-Argonne","code":"55068"},"geometry":{"type":"Point","coordinates":[5.143732923076923,49.121466999999996]}}]}