{"type":"FeatureCollection","features":[{"type":"Feature","properties":{"codesPostaux":["55150"],"population":192,"nom":"Br\u00e9h\u00e9ville","code":"55076"},"geometry":{"type":"Point","coordinates":[5.331169783783786,49.384056162162175]}}]}