{"type":"FeatureCollection","features":[{"type":"Feature","properties":{"codesPostaux":["55190"],"population":55,"nom":"Broussey-en-Blois","code":"55084"},"geometry":{"type":"Point","coordinates":[5.55634355371901,48.63389024793389]}}]}