{"type":"FeatureCollection","features":[{"type":"Feature","properties":{"codesPostaux":["55270"],"population":116,"nom":"Cheppy","code":"55113"},"geometry":{"type":"Point","coordinates":[5.074033095238095,49.21986202380952]}}]}