{"type":"FeatureCollection","features":[{"type":"Feature","properties":{"codesPostaux":["55270"],"population":54,"nom":"Cierges-sous-Montfaucon","code":"55115"},"geometry":{"type":"Point","coordinates":[5.090486372549019,49.2975231372549]}}]}