{"type":"FeatureCollection","features":[{"type":"Feature","properties":{"codesPostaux":["55000"],"population":158,"nom":"Culey","code":"55138"},"geometry":{"type":"Point","coordinates":[5.266353913043479,48.76391152173911]}}]}