{"type":"FeatureCollection","features":[{"type":"Feature","properties":{"codesPostaux":["55170"],"population":1707,"nom":"Cousances-les-Forges","code":"55132"},"geometry":{"type":"Point","coordinates":[5.0896512096774185,48.61384629032259]}}]}