{"type":"FeatureCollection","features":[{"type":"Feature","properties":{"codesPostaux":["55400"],"population":137,"nom":"Damloup","code":"55143"},"geometry":{"type":"Point","coordinates":[5.498324761904765,49.20094295238095]}}]}