{"type":"FeatureCollection","features":[{"type":"Feature","properties":{"codesPostaux":["55150"],"population":132,"nom":"Dombras","code":"55156"},"geometry":{"type":"Point","coordinates":[5.449995681818182,49.38256681818179]}}]}