{"type":"FeatureCollection","features":[{"type":"Feature","properties":{"codesPostaux":["55100"],"population":1287,"nom":"Dugny-sur-Meuse","code":"55166"},"geometry":{"type":"Point","coordinates":[5.369434502369669,49.101587867298576]}}]}