{"type":"FeatureCollection","features":[{"type":"Feature","properties":{"codesPostaux":["55150"],"population":132,"nom":"\u00c9curey-en-Verdunois","code":"55170"},"geometry":{"type":"Point","coordinates":[5.338398735632184,49.358032298850596]}}]}