{"type":"FeatureCollection","features":[{"type":"Feature","properties":{"codesPostaux":["55500"],"population":169,"nom":"Erneville-aux-Bois","code":"55179"},"geometry":{"type":"Point","coordinates":[5.4151879081632694,48.74001346938777]}}]}