{"type":"FeatureCollection","features":[{"type":"Feature","properties":{"codesPostaux":["55250"],"population":100,"nom":"\u00c8vres","code":"55185"},"geometry":{"type":"Point","coordinates":[5.1262477358490575,48.980792075471705]}}]}