{"type":"FeatureCollection","features":[{"type":"Feature","properties":{"codesPostaux":["55120"],"population":104,"nom":"Froidos","code":"55199"},"geometry":{"type":"Point","coordinates":[5.119570550458715,49.062818073394496]}}]}