{"type":"FeatureCollection","features":[{"type":"Feature","properties":{"codesPostaux":["55160"],"population":726,"nom":"Fresnes-en-Wo\u00ebvre","code":"55198"},"geometry":{"type":"Point","coordinates":[5.635113457943924,49.10293607476633]}}]}