{"type":"FeatureCollection","features":[{"type":"Feature","properties":{"codesPostaux":["55140"],"population":120,"nom":"Goussaincourt","code":"55217"},"geometry":{"type":"Point","coordinates":[5.672444197530864,48.481061851851855]}}]}