{"type":"FeatureCollection","features":[{"type":"Feature","properties":{"codesPostaux":["55150"],"population":33,"nom":"Gremilly","code":"55218"},"geometry":{"type":"Point","coordinates":[5.511045531914893,49.27819354609929]}}]}