{"type":"FeatureCollection","features":[{"type":"Feature","properties":{"codesPostaux":["55000"],"population":254,"nom":"Guerpont","code":"55221"},"geometry":{"type":"Point","coordinates":[5.255299906542057,48.72155504672898]}}]}