{"type":"FeatureCollection","features":[{"type":"Feature","properties":{"codesPostaux":["55400"],"population":38,"nom":"Gussainville","code":"55222"},"geometry":{"type":"Point","coordinates":[5.663908230769231,49.165488461538416]}}]}