{"type":"FeatureCollection","features":[{"type":"Feature","properties":{"codesPostaux":["55300"],"population":281,"nom":"Han-sur-Meuse","code":"55229"},"geometry":{"type":"Point","coordinates":[5.539669624060149,48.85701150375939]}}]}