{"type":"FeatureCollection","features":[{"type":"Feature","properties":{"codesPostaux":["55120"],"population":795,"nom":"Les Islettes","code":"55253"},"geometry":{"type":"Point","coordinates":[5.009870854700854,49.11269256410257]}}]}