{"type":"FeatureCollection","features":[{"type":"Feature","properties":{"codesPostaux":["55300"],"population":176,"nom":"K\u0153ur-la-Grande","code":"55263"},"geometry":{"type":"Point","coordinates":[5.467092156862745,48.86506264705881]}}]}