{"type":"FeatureCollection","features":[{"type":"Feature","properties":{"codesPostaux":["55800"],"population":396,"nom":"Laheycourt","code":"55271"},"geometry":{"type":"Point","coordinates":[5.037136254826258,48.90840374517372]}}]}