{"type":"FeatureCollection","features":[{"type":"Feature","properties":{"codesPostaux":["55300"],"population":283,"nom":"Lamorville","code":"55274"},"geometry":{"type":"Point","coordinates":[5.593673712574848,48.96217712574851]}}]}