{"type":"FeatureCollection","features":[{"type":"Feature","properties":{"codesPostaux":["55250"],"population":39,"nom":"Lisle-en-Barrois","code":"55295"},"geometry":{"type":"Point","coordinates":[5.057071531728667,48.9237352297593]}}]}