{"type":"FeatureCollection","features":[{"type":"Feature","properties":{"codesPostaux":["55260"],"population":53,"nom":"Ligni\u00e8res-sur-Aire","code":"55290"},"geometry":{"type":"Point","coordinates":[5.3884549999999996,48.81248357142857]}}]}