{"type":"FeatureCollection","features":[{"type":"Feature","properties":{"codesPostaux":["55300"],"population":82,"nom":"Loupmont","code":"55303"},"geometry":{"type":"Point","coordinates":[5.679727288135593,48.86843593220338]}}]}