{"type":"FeatureCollection","features":[{"type":"Feature","properties":{"codesPostaux":["55100"],"nom":"Louvemont-C\u00f4te-du-Poivre","code":"55307"},"geometry":{"type":"Point","coordinates":[5.402861666666669,49.23824322222222]}}]}