{"type":"FeatureCollection","features":[{"type":"Feature","properties":{"codesPostaux":["55150"],"population":391,"nom":"Mangiennes","code":"55316"},"geometry":{"type":"Point","coordinates":[5.533948595505619,49.346096629213505]}}]}