{"type":"FeatureCollection","features":[{"type":"Feature","properties":{"codesPostaux":["55700"],"population":63,"nom":"Martincourt-sur-Meuse","code":"55323"},"geometry":{"type":"Point","coordinates":[5.177071759259259,49.532532685185195]}}]}