{"type":"FeatureCollection","features":[{"type":"Feature","properties":{"codesPostaux":["55150"],"population":166,"nom":"Merles-sur-Loison","code":"55336"},"geometry":{"type":"Point","coordinates":[5.475756810344829,49.367048534482755]}}]}