{"type":"FeatureCollection","features":[{"type":"Feature","properties":{"codesPostaux":["55500"],"population":193,"nom":"Chanteraine","code":"55358"},"geometry":{"type":"Point","coordinates":[5.398851418918918,48.671618175675654]}}]}