{"type":"FeatureCollection","features":[{"type":"Feature","properties":{"codesPostaux":["55140"],"population":71,"nom":"Montigny-l\u00e8s-Vaucouleurs","code":"55350"},"geometry":{"type":"Point","coordinates":[5.609532037037037,48.58324657407407]}}]}