{"type":"FeatureCollection","features":[{"type":"Feature","properties":{"codesPostaux":["55000"],"population":970,"nom":"Val-d'Ornain","code":"55366"},"geometry":{"type":"Point","coordinates":[5.089913999999999,48.8144041851852]}}]}