{"type":"FeatureCollection","features":[{"type":"Feature","properties":{"codesPostaux":["55000"],"population":796,"nom":"Naives-Rosi\u00e8res","code":"55369"},"geometry":{"type":"Point","coordinates":[5.226278548387098,48.80127040322581]}}]}