{"type":"FeatureCollection","features":[{"type":"Feature","properties":{"codesPostaux":["55800"],"population":260,"nom":"Nettancourt","code":"55378"},"geometry":{"type":"Point","coordinates":[4.934804444444443,48.87221311111111]}}]}