{"type":"FeatureCollection","features":[{"type":"Feature","properties":{"codesPostaux":["55300"],"population":410,"nom":"Les Paroches","code":"55401"},"geometry":{"type":"Point","coordinates":[5.485805068493152,48.909896986301376]}}]}