{"type":"FeatureCollection","features":[{"type":"Feature","properties":{"codesPostaux":["55300"],"population":200,"nom":"Rambucourt","code":"55412"},"geometry":{"type":"Point","coordinates":[5.75781427184466,48.838698155339806]}}]}