{"type":"FeatureCollection","features":[{"type":"Feature","properties":{"codesPostaux":["55150"],"population":123,"nom":"R\u00e9ville-aux-Bois","code":"55428"},"geometry":{"type":"Point","coordinates":[5.3453172916666665,49.34053895833335]}}]}