{"type":"FeatureCollection","features":[{"type":"Feature","properties":{"codesPostaux":["55000"],"population":403,"nom":"Resson","code":"55426"},"geometry":{"type":"Point","coordinates":[5.23002652173913,48.77144356521741]}}]}