{"type":"FeatureCollection","features":[{"type":"Feature","properties":{"codesPostaux":["55800"],"population":2981,"nom":"Revigny-sur-Ornain","code":"55427"},"geometry":{"type":"Point","coordinates":[4.974446625766871,48.82737975460124]}}]}