{"type":"FeatureCollection","features":[{"type":"Feature","properties":{"codesPostaux":["55290"],"population":108,"nom":"Ribeaucourt","code":"55430"},"geometry":{"type":"Point","coordinates":[5.359702857142857,48.54537193277313]}}]}