{"type":"FeatureCollection","features":[{"type":"Feature","properties":{"codesPostaux":["55160"],"population":95,"nom":"Ronvaux","code":"55439"},"geometry":{"type":"Point","coordinates":[5.56008,49.12897705882352]}}]}