{"type":"FeatureCollection","features":[{"type":"Feature","properties":{"codesPostaux":["55320"],"population":294,"nom":"Rupt-en-Wo\u00ebvre","code":"55449"},"geometry":{"type":"Point","coordinates":[5.499487563025212,49.059470672268915]}}]}