{"type":"FeatureCollection","features":[{"type":"Feature","properties":{"codesPostaux":["55260"],"population":283,"nom":"Raival","code":"55442"},"geometry":{"type":"Point","coordinates":[5.245826217948716,48.88927602564104]}}]}