{"type":"FeatureCollection","features":[{"type":"Feature","properties":{"codesPostaux":["55300"],"population":740,"nom":"Sampigny","code":"55467"},"geometry":{"type":"Point","coordinates":[5.493420551181099,48.8192331496063]}}]}