{"type":"FeatureCollection","features":[{"type":"Feature","properties":{"codesPostaux":["55140"],"population":76,"nom":"Sepvigny","code":"55485"},"geometry":{"type":"Point","coordinates":[5.687749220779221,48.56193285714283]}}]}