{"type":"FeatureCollection","features":[{"type":"Feature","properties":{"codesPostaux":["55000"],"population":177,"nom":"Silmont","code":"55488"},"geometry":{"type":"Point","coordinates":[5.24677931372549,48.73602421568627]}}]}