{"type":"FeatureCollection","features":[{"type":"Feature","properties":{"codesPostaux":["55220"],"population":75,"nom":"Vadelaincourt","code":"55525"},"geometry":{"type":"Point","coordinates":[5.262152592592592,49.07142728395062]}}]}