{"type":"FeatureCollection","features":[{"type":"Feature","properties":{"codesPostaux":["55300"],"population":55,"nom":"Varn\u00e9ville","code":"55528"},"geometry":{"type":"Point","coordinates":[5.6598230526315785,48.8749825263158]}}]}