{"type":"FeatureCollection","features":[{"type":"Feature","properties":{"codesPostaux":["55300"],"population":88,"nom":"Valbois","code":"55530"},"geometry":{"type":"Point","coordinates":[5.616039014084505,48.93156260563382]}}]}