{"type":"FeatureCollection","features":[{"type":"Feature","properties":{"codesPostaux":["55250"],"population":159,"nom":"Villotte-devant-Louppy","code":"55569"},"geometry":{"type":"Point","coordinates":[5.067872727272729,48.894041948051964]}}]}