{"type":"FeatureCollection","features":[{"type":"Feature","properties":{"codesPostaux":["55260"],"population":193,"nom":"Villotte-sur-Aire","code":"55570"},"geometry":{"type":"Point","coordinates":[5.348630749999998,48.85523493750003]}}]}