{"type":"FeatureCollection","features":[{"type":"Feature","properties":{"codesPostaux":["56640"],"population":2108,"nom":"Arzon","code":"56005"},"geometry":{"type":"Point","coordinates":[-2.897161124620061,47.5497878115502]}}]}