{"type":"FeatureCollection","features":[{"type":"Feature","properties":{"codesPostaux":["56310"],"population":760,"nom":"Bieuzy","code":"56016"},"geometry":{"type":"Point","coordinates":[-3.0460953937007877,47.994928346456675]}}]}