{"type":"FeatureCollection","features":[{"type":"Feature","properties":{"codesPostaux":["56540"],"population":742,"nom":"Le Croisty","code":"56048"},"geometry":{"type":"Point","coordinates":[-3.372528461538462,48.06333580128205]}}]}