{"type":"FeatureCollection","features":[{"type":"Feature","properties":{"codesPostaux":["56120"],"population":872,"nom":"La Croix-Hell\u00e9an","code":"56050"},"geometry":{"type":"Point","coordinates":[-2.506898604651163,47.96405197674418]}}]}