{"type":"FeatureCollection","features":[{"type":"Feature","properties":{"codesPostaux":["56320"],"population":2822,"nom":"Le Faou\u00ebt","code":"56057"},"geometry":{"type":"Point","coordinates":[-3.5078253541076494,48.052434674220976]}}]}