{"type":"FeatureCollection","features":[{"type":"Feature","properties":{"codesPostaux":["56110"],"population":4079,"nom":"Gourin","code":"56066"},"geometry":{"type":"Point","coordinates":[-3.6001444650205743,48.12551627572018]}}]}