{"type":"FeatureCollection","features":[{"type":"Feature","properties":{"codesPostaux":["56590"],"population":2233,"nom":"Groix","code":"56069"},"geometry":{"type":"Point","coordinates":[-3.4676260869565194,47.63896670807458]}}]}