{"type":"FeatureCollection","features":[{"type":"Feature","properties":{"codesPostaux":["56190"],"population":908,"nom":"Le Guerno","code":"56077"},"geometry":{"type":"Point","coordinates":[-2.3966131333333345,47.59196966666668]}}]}