{"type":"FeatureCollection","features":[{"type":"Feature","properties":{"codesPostaux":["56600"],"population":21874,"nom":"Lanester","code":"56098"},"geometry":{"type":"Point","coordinates":[-3.320116121495323,47.77107200934582]}}]}