{"type":"FeatureCollection","features":[{"type":"Feature","properties":{"codesPostaux":["56650"],"population":6365,"nom":"Inzinzac-Lochrist","code":"56090"},"geometry":{"type":"Point","coordinates":[-3.2622197395833346,47.86110255208333]}}]}