{"type":"FeatureCollection","features":[{"type":"Feature","properties":{"codesPostaux":["56500"],"population":4116,"nom":"Locmin\u00e9","code":"56117"},"geometry":{"type":"Point","coordinates":[-2.8394107857142856,47.87918699999999]}}]}