{"type":"FeatureCollection","features":[{"type":"Feature","properties":{"codesPostaux":["56390"],"population":1550,"nom":"Locmaria-Grand-Champ","code":"56115"},"geometry":{"type":"Point","coordinates":[-2.791769033816425,47.76498091787438]}}]}