{"type":"FeatureCollection","features":[{"type":"Feature","properties":{"codesPostaux":["56800"],"population":1656,"nom":"Loyat","code":"56122"},"geometry":{"type":"Point","coordinates":[-2.393188963210702,47.995612307692255]}}]}