{"type":"FeatureCollection","features":[{"type":"Feature","properties":{"codesPostaux":["56430"],"population":3291,"nom":"Mauron","code":"56127"},"geometry":{"type":"Point","coordinates":[-2.311896340909092,48.083065386363614]}}]}