{"type":"FeatureCollection","features":[{"type":"Feature","properties":{"codesPostaux":["56140"],"population":2476,"nom":"Malestroit","code":"56124"},"geometry":{"type":"Point","coordinates":[-2.38734679245283,47.80849471698112]}}]}