{"type":"FeatureCollection","features":[{"type":"Feature","properties":{"codesPostaux":["56300"],"population":1782,"nom":"Malgu\u00e9nac","code":"56125"},"geometry":{"type":"Point","coordinates":[-3.062557248157244,48.06814432432436]}}]}