{"type":"FeatureCollection","features":[{"type":"Feature","properties":{"codesPostaux":["56890"],"population":2258,"nom":"Meucon","code":"56132"},"geometry":{"type":"Point","coordinates":[-2.7771935526315774,47.722326710526325]}}]}