{"type":"FeatureCollection","features":[{"type":"Feature","properties":{"codesPostaux":["56140"],"population":1728,"nom":"Pleucadeuc","code":"56159"},"geometry":{"type":"Point","coordinates":[-2.392691851851852,47.773976190476205]}}]}