{"type":"FeatureCollection","features":[{"type":"Feature","properties":{"codesPostaux":["56920"],"population":3677,"nom":"Noyal-Pontivy","code":"56151"},"geometry":{"type":"Point","coordinates":[-2.8909948675496664,48.06023846026492]}}]}