{"type":"FeatureCollection","features":[{"type":"Feature","properties":{"codesPostaux":["56420"],"population":1755,"nom":"Plaudren","code":"56157"},"geometry":{"type":"Point","coordinates":[-2.687511717948718,47.78418605128208]}}]}