{"type":"FeatureCollection","features":[{"type":"Feature","properties":{"codesPostaux":["56340"],"population":2133,"nom":"Plouharnel","code":"56168"},"geometry":{"type":"Point","coordinates":[-3.12055971014493,47.59607309178744]}}]}