{"type":"FeatureCollection","features":[{"type":"Feature","properties":{"codesPostaux":["56400"],"population":2473,"nom":"Plougoumelen","code":"56167"},"geometry":{"type":"Point","coordinates":[-2.8984332338308456,47.66146925373135]}}]}