{"type":"FeatureCollection","features":[{"type":"Feature","properties":{"codesPostaux":["56930"],"population":3594,"nom":"Plum\u00e9liau","code":"56173"},"geometry":{"type":"Point","coordinates":[-2.9688927218934937,47.96029654832358]}}]}