{"type":"FeatureCollection","features":[{"type":"Feature","properties":{"codesPostaux":["56220"],"population":1440,"nom":"Pluherlin","code":"56171"},"geometry":{"type":"Point","coordinates":[-2.3725354128440364,47.708877431192676]}}]}