{"type":"FeatureCollection","features":[{"type":"Feature","properties":{"codesPostaux":["56400"],"population":3859,"nom":"Plumergat","code":"56175"},"geometry":{"type":"Point","coordinates":[-2.9218842605633797,47.73235454225351]}}]}