{"type":"FeatureCollection","features":[{"type":"Feature","properties":{"codesPostaux":["56130"],"population":658,"nom":"La Roche-Bernard","code":"56195"},"geometry":{"type":"Point","coordinates":[-2.3006319444444445,47.51841194444445]}}]}