{"type":"FeatureCollection","features":[{"type":"Feature","properties":{"codesPostaux":["56140"],"population":749,"nom":"Saint-Congard","code":"56211"},"geometry":{"type":"Point","coordinates":[-2.3295325581395345,47.77257240310081]}}]}