{"type":"FeatureCollection","features":[{"type":"Feature","properties":{"codesPostaux":["56470"],"population":1594,"nom":"Saint-Philibert","code":"56233"},"geometry":{"type":"Point","coordinates":[-2.9967792063492036,47.57811301587305]}}]}