{"type":"FeatureCollection","features":[{"type":"Feature","properties":{"codesPostaux":["56490"],"population":689,"nom":"La Trinit\u00e9-Porho\u00ebt","code":"56257"},"geometry":{"type":"Point","coordinates":[-2.531584391534391,48.099769999999985]}}]}