{"type":"FeatureCollection","features":[{"type":"Feature","properties":{"codesPostaux":["57515"],"population":2606,"nom":"Alsting","code":"57013"},"geometry":{"type":"Point","coordinates":[7.0010797014925386,49.18030492537314]}}]}