{"type":"FeatureCollection","features":[{"type":"Feature","properties":{"codesPostaux":["57865"],"population":2199,"nom":"Amanvillers","code":"57017"},"geometry":{"type":"Point","coordinates":[6.047712386363639,49.16238193181818]}}]}