{"type":"FeatureCollection","features":[{"type":"Feature","properties":{"codesPostaux":["57380"],"population":131,"nom":"Arraincourt","code":"57027"},"geometry":{"type":"Point","coordinates":[6.531366099999998,48.976545300000005]}}]}