{"type":"FeatureCollection","features":[{"type":"Feature","properties":{"codesPostaux":["57580"],"population":217,"nom":"Arriance","code":"57029"},"geometry":{"type":"Point","coordinates":[6.500424791666668,49.01609291666665]}}]}