{"type":"FeatureCollection","features":[{"type":"Feature","properties":{"codesPostaux":["57440"],"population":1247,"nom":"Angevillers","code":"57022"},"geometry":{"type":"Point","coordinates":[6.042543592233009,49.3904813592233]}}]}