{"type":"FeatureCollection","features":[{"type":"Feature","properties":{"codesPostaux":["57670"],"population":544,"nom":"B\u00e9nestroff","code":"57060"},"geometry":{"type":"Point","coordinates":[6.756305803571429,48.908050178571436]}}]}