{"type":"FeatureCollection","features":[{"type":"Feature","properties":{"codesPostaux":["57660"],"population":226,"nom":"B\u00e9rig-Vintrange","code":"57063"},"geometry":{"type":"Point","coordinates":[6.694003333333333,48.97073949494951]}}]}