{"type":"FeatureCollection","features":[{"type":"Feature","properties":{"codesPostaux":["57630"],"population":92,"nom":"Bezange-la-Petite","code":"57077"},"geometry":{"type":"Point","coordinates":[6.612509178082193,48.73226383561644]}}]}