{"type":"FeatureCollection","features":[{"type":"Feature","properties":{"codesPostaux":["57220"],"population":227,"nom":"Bettange","code":"57070"},"geometry":{"type":"Point","coordinates":[6.488647545454545,49.23892754545457]}}]}