{"type":"FeatureCollection","features":[{"type":"Feature","properties":{"codesPostaux":["57220"],"population":250,"nom":"Bisten-en-Lorraine","code":"57087"},"geometry":{"type":"Point","coordinates":[6.602906704545455,49.16335977272727]}}]}