{"type":"FeatureCollection","features":[{"type":"Feature","properties":{"codesPostaux":["57260"],"population":121,"nom":"Bidestroff","code":"57081"},"geometry":{"type":"Point","coordinates":[6.789221041666668,48.84370843750002]}}]}