{"type":"FeatureCollection","features":[{"type":"Feature","properties":{"codesPostaux":["57170"],"population":332,"nom":"Bioncourt","code":"57084"},"geometry":{"type":"Point","coordinates":[6.366871206896555,48.79835663793103]}}]}