{"type":"FeatureCollection","features":[{"type":"Feature","properties":{"codesPostaux":["57200"],"population":631,"nom":"Blies-\u00c9bersing","code":"57092"},"geometry":{"type":"Point","coordinates":[7.141167761194032,49.11580328358209]}}]}