{"type":"FeatureCollection","features":[{"type":"Feature","properties":{"codesPostaux":["57200"],"population":598,"nom":"Blies-Guersviller","code":"57093"},"geometry":{"type":"Point","coordinates":[7.095886842105264,49.14566842105264]}}]}