{"type":"FeatureCollection","features":[{"type":"Feature","properties":{"codesPostaux":["57310"],"population":2998,"nom":"Bousse","code":"57102"},"geometry":{"type":"Point","coordinates":[6.2056513725490206,49.274915196078446]}}]}