{"type":"FeatureCollection","features":[{"type":"Feature","properties":{"codesPostaux":["57570"],"population":1166,"nom":"Boust","code":"57104"},"geometry":{"type":"Point","coordinates":[6.19372794871795,49.43438487179488]}}]}