{"type":"FeatureCollection","features":[{"type":"Feature","properties":{"codesPostaux":["57920"],"population":593,"nom":"Buding","code":"57117"},"geometry":{"type":"Point","coordinates":[6.32410925233645,49.32773915887852]}}]}