{"type":"FeatureCollection","features":[{"type":"Feature","properties":{"codesPostaux":["57580"],"population":125,"nom":"Chanville","code":"57127"},"geometry":{"type":"Point","coordinates":[6.439094736842107,49.04171407894737]}}]}