{"type":"FeatureCollection","features":[{"type":"Feature","properties":{"codesPostaux":["57640"],"population":678,"nom":"Charly-Oradour","code":"57129"},"geometry":{"type":"Point","coordinates":[6.246099418604652,49.175877441860465]}}]}