{"type":"FeatureCollection","features":[{"type":"Feature","properties":{"codesPostaux":["57450"],"population":691,"nom":"Cappel","code":"57122"},"geometry":{"type":"Point","coordinates":[6.845628449612405,49.07717]}}]}