{"type":"FeatureCollection","features":[{"type":"Feature","properties":{"codesPostaux":["57420"],"population":731,"nom":"Cheminot","code":"57137"},"geometry":{"type":"Point","coordinates":[6.13443561111111,48.95897966666666]}}]}