{"type":"FeatureCollection","features":[{"type":"Feature","properties":{"codesPostaux":["57320"],"population":268,"nom":"Ch\u00e2teau-Rouge","code":"57131"},"geometry":{"type":"Point","coordinates":[6.598255507246378,49.283021159420294]}}]}