{"type":"FeatureCollection","features":[{"type":"Feature","properties":{"codesPostaux":["57320"],"population":208,"nom":"Colmen","code":"57149"},"geometry":{"type":"Point","coordinates":[6.540315999999999,49.35600466666668]}}]}