{"type":"FeatureCollection","features":[{"type":"Feature","properties":{"codesPostaux":["57590"],"population":85,"nom":"Chicourt","code":"57141"},"geometry":{"type":"Point","coordinates":[6.505018142857143,48.918108857142876]}}]}