{"type":"FeatureCollection","features":[{"type":"Feature","properties":{"codesPostaux":["57680"],"population":2248,"nom":"Corny-sur-Moselle","code":"57153"},"geometry":{"type":"Point","coordinates":[6.075448533333334,49.03288853333334]}}]}