{"type":"FeatureCollection","features":[{"type":"Feature","properties":{"codesPostaux":["57660"],"population":392,"nom":"Diffembach-l\u00e8s-Hellimer","code":"57178"},"geometry":{"type":"Point","coordinates":[6.858308169934637,49.00675660130719]}}]}