{"type":"FeatureCollection","features":[{"type":"Feature","properties":{"codesPostaux":["57830"],"population":230,"nom":"Diane-Capelle","code":"57175"},"geometry":{"type":"Point","coordinates":[6.931280655737704,48.72993901639344]}}]}