{"type":"FeatureCollection","features":[{"type":"Feature","properties":{"codesPostaux":["57590"],"population":1083,"nom":"Delme","code":"57171"},"geometry":{"type":"Point","coordinates":[6.38420891089109,48.88344039603962]}}]}