{"type":"FeatureCollection","features":[{"type":"Feature","properties":{"codesPostaux":["57450"],"population":5554,"nom":"Far\u00e9bersviller","code":"57207"},"geometry":{"type":"Point","coordinates":[6.860834871794872,49.11756064102564]}}]}