{"type":"FeatureCollection","features":[{"type":"Feature","properties":{"codesPostaux":["57420"],"population":1016,"nom":"Fleury","code":"57218"},"geometry":{"type":"Point","coordinates":[6.200893690476191,49.03753428571428]}}]}