{"type":"FeatureCollection","features":[{"type":"Feature","properties":{"codesPostaux":["57320"],"population":1113,"nom":"Freistroff","code":"57235"},"geometry":{"type":"Point","coordinates":[6.486614602272726,49.28865238636363]}}]}