{"type":"FeatureCollection","features":[{"type":"Feature","properties":{"codesPostaux":["57170"],"population":181,"nom":"Fresnes-en-Saulnois","code":"57238"},"geometry":{"type":"Point","coordinates":[6.436950673076917,48.83514701923077]}}]}