{"type":"FeatureCollection","features":[{"type":"Feature","properties":{"codesPostaux":["57530"],"population":256,"nom":"Glatigny","code":"57249"},"geometry":{"type":"Point","coordinates":[6.348903977272726,49.14045375]}}]}