{"type":"FeatureCollection","features":[{"type":"Feature","properties":{"codesPostaux":["57220"],"population":523,"nom":"Gomelange","code":"57252"},"geometry":{"type":"Point","coordinates":[6.463690701754385,49.23698824561402]}}]}