{"type":"FeatureCollection","features":[{"type":"Feature","properties":{"codesPostaux":["57420"],"population":326,"nom":"Goin","code":"57251"},"geometry":{"type":"Point","coordinates":[6.221183406593404,48.99024472527473]}}]}