{"type":"FeatureCollection","features":[{"type":"Feature","properties":{"codesPostaux":["57660"],"population":578,"nom":"Grostenquin","code":"57262"},"geometry":{"type":"Point","coordinates":[6.741210170212767,48.98271859574468]}}]}