{"type":"FeatureCollection","features":[{"type":"Feature","properties":{"codesPostaux":["57410"],"population":1309,"nom":"Gros-R\u00e9derching","code":"57261"},"geometry":{"type":"Point","coordinates":[7.22206986394558,49.06471768707485]}}]}