{"type":"FeatureCollection","features":[{"type":"Feature","properties":{"codesPostaux":["57510"],"population":684,"nom":"Grundviller","code":"57263"},"geometry":{"type":"Point","coordinates":[6.981294295774647,49.04702112676054]}}]}