{"type":"FeatureCollection","features":[{"type":"Feature","properties":{"codesPostaux":["57870"],"population":397,"nom":"Harreberg","code":"57298"},"geometry":{"type":"Point","coordinates":[7.170778017241379,48.66284508620691]}}]}