{"type":"FeatureCollection","features":[{"type":"Feature","properties":{"codesPostaux":["57630"],"population":113,"nom":"Haraucourt-sur-Seille","code":"57295"},"geometry":{"type":"Point","coordinates":[6.60676717171717,48.80772737373737]}}]}