{"type":"FeatureCollection","features":[{"type":"Feature","properties":{"codesPostaux":["57230"],"population":304,"nom":"Haspelschiedt","code":"57301"},"geometry":{"type":"Point","coordinates":[7.4897242788461575,49.08384870192306]}}]}