{"type":"FeatureCollection","features":[{"type":"Feature","properties":{"codesPostaux":["57830"],"population":516,"nom":"H\u00e9ming","code":"57314"},"geometry":{"type":"Point","coordinates":[6.966095000000003,48.69599074999999]}}]}