{"type":"FeatureCollection","features":[{"type":"Feature","properties":{"codesPostaux":["57670"],"population":224,"nom":"Honskirch","code":"57335"},"geometry":{"type":"Point","coordinates":[6.966779870129875,48.939750454545454]}}]}