{"type":"FeatureCollection","features":[{"type":"Feature","properties":{"codesPostaux":["57470"],"population":6867,"nom":"Hombourg-Haut","code":"57332"},"geometry":{"type":"Point","coordinates":[6.777593764705882,49.127604470588224]}}]}