{"type":"FeatureCollection","features":[{"type":"Feature","properties":{"codesPostaux":["57720"],"population":559,"nom":"Hottviller","code":"57338"},"geometry":{"type":"Point","coordinates":[7.353068402777773,49.075035069444425]}}]}