{"type":"FeatureCollection","features":[{"type":"Feature","properties":{"codesPostaux":["57480"],"population":723,"nom":"Hunting","code":"57341"},"geometry":{"type":"Point","coordinates":[6.3247325,49.412672500000006]}}]}