{"type":"FeatureCollection","features":[{"type":"Feature","properties":{"codesPostaux":["57990"],"population":1347,"nom":"Hundling","code":"57340"},"geometry":{"type":"Point","coordinates":[6.983328800000001,49.10025493333334]}}]}