{"type":"FeatureCollection","features":[{"type":"Feature","properties":{"codesPostaux":["57920"],"population":163,"nom":"Kemplich","code":"57359"},"geometry":{"type":"Point","coordinates":[6.396938137254904,49.32232705882354]}}]}