{"type":"FeatureCollection","features":[{"type":"Feature","properties":{"codesPostaux":["57430"],"population":408,"nom":"Kappelkinger","code":"57357"},"geometry":{"type":"Point","coordinates":[6.910003274336284,48.97557398230089]}}]}