{"type":"FeatureCollection","features":[{"type":"Feature","properties":{"codesPostaux":["57245"],"population":1085,"nom":"Jury","code":"57351"},"geometry":{"type":"Point","coordinates":[6.255117906976744,49.07217302325582]}}]}