{"type":"FeatureCollection","features":[{"type":"Feature","properties":{"codesPostaux":["57590"],"population":118,"nom":"Juville","code":"57354"},"geometry":{"type":"Point","coordinates":[6.360634871794875,48.92939499999999]}}]}