{"type":"FeatureCollection","features":[{"type":"Feature","properties":{"codesPostaux":["57240"],"population":3217,"nom":"Knutange","code":"57368"},"geometry":{"type":"Point","coordinates":[6.031252371134022,49.33909896907215]}}]}