{"type":"FeatureCollection","features":[{"type":"Feature","properties":{"codesPostaux":["57385"],"population":341,"nom":"Laudrefang","code":"57386"},"geometry":{"type":"Point","coordinates":[6.6412451063829785,49.083139574468085]}}]}