{"type":"FeatureCollection","features":[{"type":"Feature","properties":{"codesPostaux":["57810"],"population":177,"nom":"Languimberg","code":"57383"},"geometry":{"type":"Point","coordinates":[6.877953811881189,48.72424400990099]}}]}