{"type":"FeatureCollection","features":[{"type":"Feature","properties":{"codesPostaux":["57580"],"population":313,"nom":"Lemud","code":"57392"},"geometry":{"type":"Point","coordinates":[6.363827419354837,49.0330422580645]}}]}