{"type":"FeatureCollection","features":[{"type":"Feature","properties":{"codesPostaux":["57340"],"population":89,"nom":"Lidrezing","code":"57401"},"geometry":{"type":"Point","coordinates":[6.714885092592592,48.88412129629629]}}]}