{"type":"FeatureCollection","features":[{"type":"Feature","properties":{"codesPostaux":["57670"],"population":69,"nom":"Lostroff","code":"57417"},"geometry":{"type":"Point","coordinates":[6.866603207547173,48.86655150943396]}}]}