{"type":"FeatureCollection","features":[{"type":"Feature","properties":{"codesPostaux":["57670"],"population":134,"nom":"Lhor","code":"57410"},"geometry":{"type":"Point","coordinates":[6.8788297,48.88539069999998]}}]}