{"type":"FeatureCollection","features":[{"type":"Feature","properties":{"codesPostaux":["57590"],"population":208,"nom":"Lucy","code":"57424"},"geometry":{"type":"Point","coordinates":[6.4754925287356295,48.9401108045977]}}]}