{"type":"FeatureCollection","features":[{"type":"Feature","properties":{"codesPostaux":["57480"],"population":624,"nom":"Malling","code":"57437"},"geometry":{"type":"Point","coordinates":[6.310391946902652,49.41286203539821]}}]}