{"type":"FeatureCollection","features":[{"type":"Feature","properties":{"codesPostaux":["57535"],"population":5814,"nom":"Marange-Silvange","code":"57443"},"geometry":{"type":"Point","coordinates":[6.110734594594592,49.217124527027046]}}]}