{"type":"FeatureCollection","features":[{"type":"Feature","properties":{"codesPostaux":["57590"],"population":145,"nom":"Manhou\u00e9","code":"57440"},"geometry":{"type":"Point","coordinates":[6.335933809523809,48.82587928571429]}}]}