{"type":"FeatureCollection","features":[{"type":"Feature","properties":{"codesPostaux":["57690"],"population":317,"nom":"Marange-Zondrange","code":"57444"},"geometry":{"type":"Point","coordinates":[6.530913625000001,49.11536600000001]}}]}