{"type":"FeatureCollection","features":[{"type":"Feature","properties":{"codesPostaux":["57245"],"population":1174,"nom":"M\u00e9cleuves","code":"57454"},"geometry":{"type":"Point","coordinates":[6.28186447368421,49.052119035087735]}}]}