{"type":"FeatureCollection","features":[{"type":"Feature","properties":{"codesPostaux":["57550"],"population":1560,"nom":"Merten","code":"57460"},"geometry":{"type":"Point","coordinates":[6.667098900000002,49.24725619999997]}}]}