{"type":"FeatureCollection","features":[{"type":"Feature","properties":{"codesPostaux":["57480"],"population":435,"nom":"Montenach","code":"57479"},"geometry":{"type":"Point","coordinates":[6.387779385964916,49.40979517543862]}}]}