{"type":"FeatureCollection","features":[{"type":"Feature","properties":{"codesPostaux":["57420"],"population":147,"nom":"Moncheux","code":"57472"},"geometry":{"type":"Point","coordinates":[6.339930795454544,48.94763659090909]}}]}