{"type":"FeatureCollection","features":[{"type":"Feature","properties":{"codesPostaux":["57860"],"population":2449,"nom":"Montois-la-Montagne","code":"57481"},"geometry":{"type":"Point","coordinates":[6.026671052631578,49.2253243859649]}}]}