{"type":"FeatureCollection","features":[{"type":"Feature","properties":{"codesPostaux":["57160"],"population":5076,"nom":"Moulins-l\u00e8s-Metz","code":"57487"},"geometry":{"type":"Point","coordinates":[6.111484712643676,49.0974943678161]}}]}