{"type":"FeatureCollection","features":[{"type":"Feature","properties":{"codesPostaux":["57930"],"population":266,"nom":"Niederstinzel","code":"57506"},"geometry":{"type":"Point","coordinates":[7.021823617021274,48.870599787234056]}}]}