{"type":"FeatureCollection","features":[{"type":"Feature","properties":{"codesPostaux":["57830"],"population":42,"nom":"Neufmoulins","code":"57500"},"geometry":{"type":"Point","coordinates":[6.971197096774197,48.67810951612903]}}]}