{"type":"FeatureCollection","features":[{"type":"Feature","properties":{"codesPostaux":["57670"],"population":39,"nom":"Neufvillage","code":"57501"},"geometry":{"type":"Point","coordinates":[6.779129047619048,48.934545714285704]}}]}