{"type":"FeatureCollection","features":[{"type":"Feature","properties":{"codesPostaux":["57220"],"population":417,"nom":"Ottonville","code":"57530"},"geometry":{"type":"Point","coordinates":[6.516956567164179,49.218838059701525]}}]}