{"type":"FeatureCollection","features":[{"type":"Feature","properties":{"codesPostaux":["57530"],"population":917,"nom":"Pange","code":"57533"},"geometry":{"type":"Point","coordinates":[6.35659419847328,49.08316549618319]}}]}