{"type":"FeatureCollection","features":[{"type":"Feature","properties":{"codesPostaux":["57170"],"population":289,"nom":"Pettoncourt","code":"57538"},"geometry":{"type":"Point","coordinates":[6.4110324242424195,48.787775530303044]}}]}