{"type":"FeatureCollection","features":[{"type":"Feature","properties":{"codesPostaux":["57870"],"population":626,"nom":"Plaine-de-Walsch","code":"57544"},"geometry":{"type":"Point","coordinates":[7.1519144594594595,48.68913067567566]}}]}