{"type":"FeatureCollection","features":[{"type":"Feature","properties":{"codesPostaux":["57590"],"population":110,"nom":"Pr\u00e9vocourt","code":"57555"},"geometry":{"type":"Point","coordinates":[6.432894823529411,48.923692823529414]}}]}