{"type":"FeatureCollection","features":[{"type":"Feature","properties":{"codesPostaux":["57890"],"population":2528,"nom":"Porcelette","code":"57550"},"geometry":{"type":"Point","coordinates":[6.6643667415730325,49.16568303370789]}}]}