{"type":"FeatureCollection","features":[{"type":"Feature","properties":{"codesPostaux":["57320"],"population":148,"nom":"R\u00e9melfang","code":"57567"},"geometry":{"type":"Point","coordinates":[6.511721500000001,49.26759566666667]}}]}