{"type":"FeatureCollection","features":[{"type":"Feature","properties":{"codesPostaux":["57230"],"population":367,"nom":"Reyersviller","code":"57577"},"geometry":{"type":"Point","coordinates":[7.3934945528455245,49.03870983739834]}}]}