{"type":"FeatureCollection","features":[{"type":"Feature","properties":{"codesPostaux":["57720"],"population":580,"nom":"Rimling","code":"57584"},"geometry":{"type":"Point","coordinates":[7.263905519480523,49.09283974025973]}}]}