{"type":"FeatureCollection","features":[{"type":"Feature","properties":{"codesPostaux":["57930"],"population":368,"nom":"Romelfing","code":"57592"},"geometry":{"type":"Point","coordinates":[7.001616406249998,48.83371000000001]}}]}