{"type":"FeatureCollection","features":[{"type":"Feature","properties":{"codesPostaux":["57480"],"population":593,"nom":"Rustroff","code":"57604"},"geometry":{"type":"Point","coordinates":[6.373701020408162,49.44217081632653]}}]}