{"type":"FeatureCollection","features":[{"type":"Feature","properties":{"codesPostaux":["57640"],"population":503,"nom":"Sanry-l\u00e8s-Vigy","code":"57626"},"geometry":{"type":"Point","coordinates":[6.279038674698796,49.186426867469855]}}]}