{"type":"FeatureCollection","features":[{"type":"Feature","properties":{"codesPostaux":["57640"],"population":442,"nom":"Servigny-l\u00e8s-Sainte-Barbe","code":"57649"},"geometry":{"type":"Point","coordinates":[6.274753103448275,49.145957241379314]}}]}