{"type":"FeatureCollection","features":[{"type":"Feature","properties":{"codesPostaux":["57170"],"population":28,"nom":"Sotzeling","code":"57657"},"geometry":{"type":"Point","coordinates":[6.6372990769230755,48.869277999999994]}}]}