{"type":"FeatureCollection","features":[{"type":"Feature","properties":{"codesPostaux":["57420"],"population":33,"nom":"Silly-en-Saulnois","code":"57653"},"geometry":{"type":"Point","coordinates":[6.279134523809525,48.992436428571445]}}]}