{"type":"FeatureCollection","features":[{"type":"Feature","properties":{"codesPostaux":["57580"],"population":352,"nom":"Sorbey","code":"57656"},"geometry":{"type":"Point","coordinates":[6.318809058823527,49.03835741176472]}}]}