{"type":"FeatureCollection","features":[{"type":"Feature","properties":{"codesPostaux":["57385"],"population":1453,"nom":"Teting-sur-Nied","code":"57668"},"geometry":{"type":"Point","coordinates":[6.669662352941176,49.053053137254906]}}]}