{"type":"FeatureCollection","features":[{"type":"Feature","properties":{"codesPostaux":["57340"],"population":103,"nom":"Suisse","code":"57662"},"geometry":{"type":"Point","coordinates":[6.57904164556962,48.96463037974684]}}]}