{"type":"FeatureCollection","features":[{"type":"Feature","properties":{"codesPostaux":["57070"],"population":906,"nom":"Vantoux","code":"57693"},"geometry":{"type":"Point","coordinates":[6.234894246575342,49.13234931506848]}}]}