{"type":"FeatureCollection","features":[{"type":"Feature","properties":{"codesPostaux":["57560"],"population":308,"nom":"Vasperviller","code":"57697"},"geometry":{"type":"Point","coordinates":[7.072301208791212,48.63510087912089]}}]}