{"type":"FeatureCollection","features":[{"type":"Feature","properties":{"codesPostaux":["57170"],"population":133,"nom":"Vaxy","code":"57702"},"geometry":{"type":"Point","coordinates":[6.5277608421052635,48.85831715789474]}}]}