{"type":"FeatureCollection","features":[{"type":"Feature","properties":{"codesPostaux":["57690"],"population":420,"nom":"Haute-Vigneulles","code":"57714"},"geometry":{"type":"Point","coordinates":[6.558057802197802,49.093865934065946]}}]}