{"type":"FeatureCollection","features":[{"type":"Feature","properties":{"codesPostaux":["57630"],"population":1333,"nom":"Vic-sur-Seille","code":"57712"},"geometry":{"type":"Point","coordinates":[6.527235395683456,48.772970935251784]}}]}