{"type":"FeatureCollection","features":[{"type":"Feature","properties":{"codesPostaux":["57550"],"population":491,"nom":"Villing","code":"57720"},"geometry":{"type":"Point","coordinates":[6.629926315789477,49.28132868421051]}}]}