{"type":"FeatureCollection","features":[{"type":"Feature","properties":{"codesPostaux":["57640"],"population":546,"nom":"Vry","code":"57736"},"geometry":{"type":"Point","coordinates":[6.362304181818182,49.19123224242425]}}]}