{"type":"FeatureCollection","features":[{"type":"Feature","properties":{"codesPostaux":["57430"],"population":1505,"nom":"Willerwald","code":"57746"},"geometry":{"type":"Point","coordinates":[7.038780841121496,49.018524672897215]}}]}