{"type":"FeatureCollection","features":[{"type":"Feature","properties":{"codesPostaux":["57630"],"population":116,"nom":"Xanrey","code":"57754"},"geometry":{"type":"Point","coordinates":[6.583870266666665,48.74992306666667]}}]}