{"type":"FeatureCollection","features":[{"type":"Feature","properties":{"codesPostaux":["57590"],"population":86,"nom":"Xocourt","code":"57755"},"geometry":{"type":"Point","coordinates":[6.3787883505154666,48.910755773195895]}}]}