{"type":"FeatureCollection","features":[{"type":"Feature","properties":{"codesPostaux":["57340"],"population":64,"nom":"Zarbeling","code":"57759"},"geometry":{"type":"Point","coordinates":[6.6892582417582425,48.88991164835167]}}]}