{"type":"FeatureCollection","features":[{"type":"Feature","properties":{"codesPostaux":["57970"],"population":1011,"nom":"Stuckange","code":"57767"},"geometry":{"type":"Point","coordinates":[6.2303596774193535,49.32514215053764]}}]}