{"type":"FeatureCollection","features":[{"type":"Feature","properties":{"codesPostaux":["57330"],"population":1042,"nom":"Zoufftgen","code":"57764"},"geometry":{"type":"Point","coordinates":[6.136035263157896,49.466653552631584]}}]}