{"type":"FeatureCollection","features":[{"type":"Feature","properties":{"codesPostaux":["58800"],"population":177,"nom":"Anthien","code":"58008"},"geometry":{"type":"Point","coordinates":[3.7157030232558164,47.29848343023259]}}]}