{"type":"FeatureCollection","features":[{"type":"Feature","properties":{"codesPostaux":["58200"],"population":864,"nom":"Alligny-Cosne","code":"58002"},"geometry":{"type":"Point","coordinates":[3.075517294117647,47.44699311764709]}}]}