{"type":"FeatureCollection","features":[{"type":"Feature","properties":{"codesPostaux":["58110"],"population":407,"nom":"Alluy","code":"58004"},"geometry":{"type":"Point","coordinates":[3.6443294871794865,47.03314635897437]}}]}