{"type":"FeatureCollection","features":[{"type":"Feature","properties":{"codesPostaux":["58230"],"population":645,"nom":"Alligny-en-Morvan","code":"58003"},"geometry":{"type":"Point","coordinates":[4.167463113772456,47.20218640718567]}}]}