{"type":"FeatureCollection","features":[{"type":"Feature","properties":{"codesPostaux":["58500"],"population":303,"nom":"Armes","code":"58011"},"geometry":{"type":"Point","coordinates":[3.5581320930232576,47.4587361627907]}}]}