{"type":"FeatureCollection","features":[{"type":"Feature","properties":{"codesPostaux":["58430"],"population":802,"nom":"Arleuf","code":"58010"},"geometry":{"type":"Point","coordinates":[4.0129304166666655,47.04436187499995]}}]}