{"type":"FeatureCollection","features":[{"type":"Feature","properties":{"codesPostaux":["58420"],"population":164,"nom":"Beaulieu","code":"58026"},"geometry":{"type":"Point","coordinates":[3.5333310071942448,47.25909892086333]}}]}