{"type":"FeatureCollection","features":[{"type":"Feature","properties":{"codesPostaux":["58110"],"population":314,"nom":"Biches","code":"58030"},"geometry":{"type":"Point","coordinates":[3.6669284782608687,46.994849347826104]}}]}