{"type":"FeatureCollection","features":[{"type":"Feature","properties":{"codesPostaux":["58400"],"population":311,"nom":"Champvoux","code":"58056"},"geometry":{"type":"Point","coordinates":[3.0788508108108106,47.14804324324325]}}]}