{"type":"FeatureCollection","features":[{"type":"Feature","properties":{"codesPostaux":["58400"],"population":1460,"nom":"Chaulgnes","code":"58067"},"geometry":{"type":"Point","coordinates":[3.1075007236842103,47.12095598684208]}}]}