{"type":"FeatureCollection","features":[{"type":"Feature","properties":{"codesPostaux":["58120"],"population":2086,"nom":"Ch\u00e2teau-Chinon (Ville)","code":"58062"},"geometry":{"type":"Point","coordinates":[3.9269632812499995,47.064292734375]}}]}