{"type":"FeatureCollection","features":[{"type":"Feature","properties":{"codesPostaux":["58160"],"population":592,"nom":"Chevenon","code":"58072"},"geometry":{"type":"Point","coordinates":[3.2256841584158393,46.906603217821775]}}]}