{"type":"FeatureCollection","features":[{"type":"Feature","properties":{"codesPostaux":["58220"],"population":215,"nom":"Couloutre","code":"58089"},"geometry":{"type":"Point","coordinates":[3.221089915966387,47.39242705882353]}}]}