{"type":"FeatureCollection","features":[{"type":"Feature","properties":{"codesPostaux":["58300"],"population":512,"nom":"Devay","code":"58096"},"geometry":{"type":"Point","coordinates":[3.5443307936507944,46.80644984126982]}}]}