{"type":"FeatureCollection","features":[{"type":"Feature","properties":{"codesPostaux":["58300"],"population":5689,"nom":"Decize","code":"58095"},"geometry":{"type":"Point","coordinates":[3.4693036363636343,46.809560606060636]}}]}