{"type":"FeatureCollection","features":[{"type":"Feature","properties":{"codesPostaux":["58230"],"population":348,"nom":"Dun-les-Places","code":"58106"},"geometry":{"type":"Point","coordinates":[4.020580787878788,47.28918996969698]}}]}