{"type":"FeatureCollection","features":[{"type":"Feature","properties":{"codesPostaux":["58270"],"population":80,"nom":"Frasnay-Reugny","code":"58119"},"geometry":{"type":"Point","coordinates":[3.5293251773049636,46.992374964539]}}]}