{"type":"FeatureCollection","features":[{"type":"Feature","properties":{"codesPostaux":["58160"],"population":3559,"nom":"Imphy","code":"58134"},"geometry":{"type":"Point","coordinates":[3.2884039855072458,46.938431594202896]}}]}