{"type":"FeatureCollection","features":[{"type":"Feature","properties":{"codesPostaux":["58240"],"population":632,"nom":"Luthenay-Uxeloup","code":"58148"},"geometry":{"type":"Point","coordinates":[3.2612381818181837,46.853363675889334]}}]}