{"type":"FeatureCollection","features":[{"type":"Feature","properties":{"codesPostaux":["58800"],"population":206,"nom":"Marigny-sur-Yonne","code":"58159"},"geometry":{"type":"Point","coordinates":[3.644191650485437,47.28801339805826]}}]}