{"type":"FeatureCollection","features":[{"type":"Feature","properties":{"codesPostaux":["58410"],"population":122,"nom":"Menestreau","code":"58162"},"geometry":{"type":"Point","coordinates":[3.2615071317829463,47.409883023255794]}}]}