{"type":"FeatureCollection","features":[{"type":"Feature","properties":{"codesPostaux":["58400"],"population":692,"nom":"Mesves-sur-Loire","code":"58164"},"geometry":{"type":"Point","coordinates":[3.0116509210526323,47.22637197368419]}}]}