{"type":"FeatureCollection","features":[{"type":"Feature","properties":{"codesPostaux":["58250"],"population":139,"nom":"Montambert","code":"58172"},"geometry":{"type":"Point","coordinates":[3.6842193469387743,46.77306110204081]}}]}