{"type":"FeatureCollection","features":[{"type":"Feature","properties":{"codesPostaux":["58700"],"population":122,"nom":"Montenoison","code":"58174"},"geometry":{"type":"Point","coordinates":[3.421830842105265,47.21744894736845]}}]}