{"type":"FeatureCollection","features":[{"type":"Feature","properties":{"codesPostaux":["58350"],"population":104,"nom":"Nannay","code":"58188"},"geometry":{"type":"Point","coordinates":[3.1662277848101263,47.26029797468356]}}]}