{"type":"FeatureCollection","features":[{"type":"Feature","properties":{"codesPostaux":["58700"],"population":90,"nom":"Murlin","code":"58186"},"geometry":{"type":"Point","coordinates":[3.171332410714285,47.199862946428574]}}]}