{"type":"FeatureCollection","features":[{"type":"Feature","properties":{"codesPostaux":["58500"],"population":335,"nom":"Oisy","code":"58198"},"geometry":{"type":"Point","coordinates":[3.449319433962265,47.46700176100628]}}]}