{"type":"FeatureCollection","features":[{"type":"Feature","properties":{"codesPostaux":["58000"],"population":34841,"nom":"Nevers","code":"58194"},"geometry":{"type":"Point","coordinates":[3.1601224113475173,46.98818468085107]}}]}