{"type":"FeatureCollection","features":[{"type":"Feature","properties":{"codesPostaux":["58700"],"population":365,"nom":"Nolay","code":"58196"},"geometry":{"type":"Point","coordinates":[3.3213811203319503,47.123456514522836]}}]}