{"type":"FeatureCollection","features":[{"type":"Feature","properties":{"codesPostaux":["58210"],"population":141,"nom":"Oudan","code":"58201"},"geometry":{"type":"Point","coordinates":[3.3306221296296297,47.342469444444454]}}]}