{"type":"FeatureCollection","features":[{"type":"Feature","properties":{"codesPostaux":["58400"],"population":708,"nom":"Raveau","code":"58220"},"geometry":{"type":"Point","coordinates":[3.109108630136988,47.184403972602716]}}]}