{"type":"FeatureCollection","features":[{"type":"Feature","properties":{"codesPostaux":["58330"],"population":173,"nom":"Saint-Benin-des-Bois","code":"58233"},"geometry":{"type":"Point","coordinates":[3.407759567567567,47.125838432432424]}}]}