{"type":"FeatureCollection","features":[{"type":"Feature","properties":{"codesPostaux":["58270"],"population":1306,"nom":"Saint-Benin-d'Azy","code":"58232"},"geometry":{"type":"Point","coordinates":[3.4020271314741017,46.99357980079683]}}]}