{"type":"FeatureCollection","features":[{"type":"Feature","properties":{"codesPostaux":["58120"],"population":211,"nom":"Saint-Hilaire-en-Morvan","code":"58244"},"geometry":{"type":"Point","coordinates":[3.8834547292418753,47.06902653429601]}}]}