{"type":"FeatureCollection","features":[{"type":"Feature","properties":{"codesPostaux":["58130"],"population":602,"nom":"Saint-Martin-d'Heuille","code":"58254"},"geometry":{"type":"Point","coordinates":[3.2239940707964605,47.04602973451328]}}]}