{"type":"FeatureCollection","features":[{"type":"Feature","properties":{"codesPostaux":["58270"],"population":436,"nom":"Saint-Sulpice","code":"58269"},"geometry":{"type":"Point","coordinates":[3.357083285714285,47.065381785714294]}}]}