{"type":"FeatureCollection","features":[{"type":"Feature","properties":{"codesPostaux":["58000"],"population":1586,"nom":"Sermoise-sur-Loire","code":"58278"},"geometry":{"type":"Point","coordinates":[3.188660952380953,46.93704444444444]}}]}