{"type":"FeatureCollection","features":[{"type":"Feature","properties":{"codesPostaux":["58360"],"population":249,"nom":"S\u00e9melay","code":"58276"},"geometry":{"type":"Point","coordinates":[3.867531152647973,46.85721766355141]}}]}