{"type":"FeatureCollection","features":[{"type":"Feature","properties":{"codesPostaux":["58190"],"population":45,"nom":"Talon","code":"58284"},"geometry":{"type":"Point","coordinates":[3.5480653333333336,47.33685483333333]}}]}