{"type":"FeatureCollection","features":[{"type":"Feature","properties":{"codesPostaux":["58110"],"population":189,"nom":"Tintury","code":"58292"},"geometry":{"type":"Point","coordinates":[3.57160032051282,47.003455]}}]}