{"type":"FeatureCollection","features":[{"type":"Feature","properties":{"codesPostaux":["58240"],"population":188,"nom":"Tresnay","code":"58296"},"geometry":{"type":"Point","coordinates":[3.20081564814815,46.70274037037037]}}]}