{"type":"FeatureCollection","features":[{"type":"Feature","properties":{"codesPostaux":["58640"],"population":9440,"nom":"Varennes-Vauzelles","code":"58303"},"geometry":{"type":"Point","coordinates":[3.1398131279620833,47.03983123222747]}}]}