{"type":"FeatureCollection","features":[{"type":"Feature","properties":{"codesPostaux":["58130"],"population":1839,"nom":"Urzy","code":"58300"},"geometry":{"type":"Point","coordinates":[3.2000020111731833,47.056927932960896]}}]}