{"type":"FeatureCollection","features":[{"type":"Feature","properties":{"codesPostaux":["58270"],"population":292,"nom":"Ville-Langy","code":"58311"},"geometry":{"type":"Point","coordinates":[3.5068218781725897,46.935693401015236]}}]}