{"type":"FeatureCollection","features":[{"type":"Feature","properties":{"codesPostaux":["58420"],"population":99,"nom":"Vitry-Lach\u00e9","code":"58313"},"geometry":{"type":"Point","coordinates":[3.561112242424241,47.193875939393926]}}]}