{"type":"FeatureCollection","features":[{"type":"Feature","properties":{"codesPostaux":["59251"],"population":3387,"nom":"Allennes-les-Marais","code":"59005"},"geometry":{"type":"Point","coordinates":[2.950552413793104,50.539981379310355]}}]}