{"type":"FeatureCollection","features":[{"type":"Feature","properties":{"codesPostaux":["59491","59493","59650"],"population":62616,"nom":"Villeneuve-d'Ascq","code":"59009"},"geometry":{"type":"Point","coordinates":[3.1577714396887155,50.635710583657584]}}]}