{"type":"FeatureCollection","features":[{"type":"Feature","properties":{"codesPostaux":["59380"],"population":2398,"nom":"Armbouts-Cappel","code":"59016"},"geometry":{"type":"Point","coordinates":[2.35016044117647,50.9855192647059]}}]}