{"type":"FeatureCollection","features":[{"type":"Feature","properties":{"codesPostaux":["59165"],"population":4399,"nom":"Auberchicourt","code":"59024"},"geometry":{"type":"Point","coordinates":[3.2291013043478265,50.3355129347826]}}]}