{"type":"FeatureCollection","features":[{"type":"Feature","properties":{"codesPostaux":["59249"],"population":1536,"nom":"Aubers","code":"59025"},"geometry":{"type":"Point","coordinates":[2.826138484848484,50.59565863636363]}}]}