{"type":"FeatureCollection","features":[{"type":"Feature","properties":{"codesPostaux":["59830"],"population":1605,"nom":"Bachy","code":"59042"},"geometry":{"type":"Point","coordinates":[3.2685667415730353,50.541683370786494]}}]}