{"type":"FeatureCollection","features":[{"type":"Feature","properties":{"codesPostaux":["59540"],"population":775,"nom":"B\u00e9thencourt","code":"59075"},"geometry":{"type":"Point","coordinates":[3.421970641025641,50.14417615384616]}}]}