{"type":"FeatureCollection","features":[{"type":"Feature","properties":{"codesPostaux":["59235"],"population":2220,"nom":"Bers\u00e9e","code":"59071"},"geometry":{"type":"Point","coordinates":[3.149812032520325,50.47259048780487]}}]}