{"type":"FeatureCollection","features":[{"type":"Feature","properties":{"codesPostaux":["59380"],"population":1754,"nom":"Bierne","code":"59082"},"geometry":{"type":"Point","coordinates":[2.4093702597402595,50.96719272727271]}}]}