{"type":"FeatureCollection","features":[{"type":"Feature","properties":{"codesPostaux":["59189"],"population":726,"nom":"Bo\u00ebseghem","code":"59087"},"geometry":{"type":"Point","coordinates":[2.43869507936508,50.67196698412701]}}]}