{"type":"FeatureCollection","features":[{"type":"Feature","properties":{"codesPostaux":["59190"],"population":595,"nom":"Borre","code":"59091"},"geometry":{"type":"Point","coordinates":[2.577833888888889,50.73670055555554]}}]}