{"type":"FeatureCollection","features":[{"type":"Feature","properties":{"codesPostaux":["59400"],"population":356,"nom":"Boursies","code":"59097"},"geometry":{"type":"Point","coordinates":[3.0428217777777786,50.14184177777778]}}]}