{"type":"FeatureCollection","features":[{"type":"Feature","properties":{"codesPostaux":["59144"],"population":408,"nom":"Bry","code":"59116"},"geometry":{"type":"Point","coordinates":[3.6882953571428554,50.31576238095237]}}]}