{"type":"FeatureCollection","features":[{"type":"Feature","properties":{"codesPostaux":["59213"],"population":161,"nom":"Capelle","code":"59127"},"geometry":{"type":"Point","coordinates":[3.5550130681818173,50.24049681818181]}}]}