{"type":"FeatureCollection","features":[{"type":"Feature","properties":{"codesPostaux":["59180"],"population":7948,"nom":"Cappelle-la-Grande","code":"59131"},"geometry":{"type":"Point","coordinates":[2.3686139999999996,50.991869272727286]}}]}