{"type":"FeatureCollection","features":[{"type":"Feature","properties":{"codesPostaux":["59244"],"population":1256,"nom":"Cartignies","code":"59134"},"geometry":{"type":"Point","coordinates":[3.8489464596273293,50.07140211180122]}}]}