{"type":"FeatureCollection","features":[{"type":"Feature","properties":{"codesPostaux":["59217"],"population":674,"nom":"Catteni\u00e8res","code":"59138"},"geometry":{"type":"Point","coordinates":[3.3337543999999997,50.13323900000001]}}]}