{"type":"FeatureCollection","features":[{"type":"Feature","properties":{"codesPostaux":["59225"],"population":1130,"nom":"Clary","code":"59149"},"geometry":{"type":"Point","coordinates":[3.39454976744186,50.069354069767435]}}]}