{"type":"FeatureCollection","features":[{"type":"Feature","properties":{"codesPostaux":["59740"],"population":62,"nom":"Choisies","code":"59147"},"geometry":{"type":"Point","coordinates":[4.0456231034482775,50.21069560344828]}}]}