{"type":"FeatureCollection","features":[{"type":"Feature","properties":{"codesPostaux":["59279"],"population":738,"nom":"Craywick","code":"59159"},"geometry":{"type":"Point","coordinates":[2.217186086956522,50.973461594202895]}}]}