{"type":"FeatureCollection","features":[{"type":"Feature","properties":{"codesPostaux":["59310"],"population":2867,"nom":"Coutiches","code":"59158"},"geometry":{"type":"Point","coordinates":[3.2002001785714294,50.44650708333333]}}]}