{"type":"FeatureCollection","features":[{"type":"Feature","properties":{"codesPostaux":["59440"],"population":577,"nom":"Dourlers","code":"59181"},"geometry":{"type":"Point","coordinates":[3.9419763963963974,50.17692585585587]}}]}