{"type":"FeatureCollection","features":[{"type":"Feature","properties":{"codesPostaux":["59140","59240","59279","59430","59640"],"population":89882,"nom":"Dunkerque","code":"59183"},"geometry":{"type":"Point","coordinates":[2.339790238095238,51.03236380952378]}}]}