{"type":"FeatureCollection","features":[{"type":"Feature","properties":{"codesPostaux":["59320"],"population":561,"nom":"Englos","code":"59195"},"geometry":{"type":"Point","coordinates":[2.9599220967741946,50.62712451612903]}}]}