{"type":"FeatureCollection","features":[{"type":"Feature","properties":{"codesPostaux":["59127"],"population":633,"nom":"\u00c9lincourt","code":"59191"},"geometry":{"type":"Point","coordinates":[3.367279090909091,50.04212613636364]}}]}