{"type":"FeatureCollection","features":[{"type":"Feature","properties":{"codesPostaux":["59161"],"population":3333,"nom":"Escaud\u0153uvres","code":"59206"},"geometry":{"type":"Point","coordinates":[3.276973636363636,50.19263844155843]}}]}