{"type":"FeatureCollection","features":[{"type":"Feature","properties":{"codesPostaux":["59278"],"population":4144,"nom":"Escautpont","code":"59207"},"geometry":{"type":"Point","coordinates":[3.5624058181818183,50.41756763636362]}}]}