{"type":"FeatureCollection","features":[{"type":"Feature","properties":{"codesPostaux":["59151"],"population":1058,"nom":"Estr\u00e9es","code":"59214"},"geometry":{"type":"Point","coordinates":[3.073361764705882,50.300590588235266]}}]}