{"type":"FeatureCollection","features":[{"type":"Feature","properties":{"codesPostaux":["59148"],"population":5521,"nom":"Flines-lez-Raches","code":"59239"},"geometry":{"type":"Point","coordinates":[3.1829627272727277,50.42263153846152]}}]}