{"type":"FeatureCollection","features":[{"type":"Feature","properties":{"codesPostaux":["59680"],"population":5367,"nom":"Ferri\u00e8re-la-Grande","code":"59230"},"geometry":{"type":"Point","coordinates":[3.9938804132231405,50.24768057851239]}}]}