{"type":"FeatureCollection","features":[{"type":"Feature","properties":{"codesPostaux":["59610"],"population":12581,"nom":"Fourmies","code":"59249"},"geometry":{"type":"Point","coordinates":[4.065416304347827,50.010041086956505]}}]}