{"type":"FeatureCollection","features":[{"type":"Feature","properties":{"codesPostaux":["59273"],"population":3353,"nom":"Fretin","code":"59256"},"geometry":{"type":"Point","coordinates":[3.1277128735632185,50.56846873563219]}}]}