{"type":"FeatureCollection","features":[{"type":"Feature","properties":{"codesPostaux":["59122","59254"],"population":4151,"nom":"Ghyvelde","code":"59260"},"geometry":{"type":"Point","coordinates":[2.5138734057971015,51.0299506521739]}}]}