{"type":"FeatureCollection","features":[{"type":"Feature","properties":{"codesPostaux":["59600"],"population":781,"nom":"Gognies-Chauss\u00e9e","code":"59264"},"geometry":{"type":"Point","coordinates":[3.9404285981308407,50.31967420560748]}}]}