{"type":"FeatureCollection","features":[{"type":"Feature","properties":{"codesPostaux":["59244"],"population":513,"nom":"Grand-Fayt","code":"59270"},"geometry":{"type":"Point","coordinates":[3.802928828124998,50.11328210937499]}}]}