{"type":"FeatureCollection","features":[{"type":"Feature","properties":{"codesPostaux":["59360"],"population":495,"nom":"La Groise","code":"59274"},"geometry":{"type":"Point","coordinates":[3.685564615384616,50.075841846153814]}}]}