{"type":"FeatureCollection","features":[{"type":"Feature","properties":{"codesPostaux":["59330"],"population":14271,"nom":"Hautmont","code":"59291"},"geometry":{"type":"Point","coordinates":[3.9160229310344823,50.24525887931031]}}]}