{"type":"FeatureCollection","features":[{"type":"Feature","properties":{"codesPostaux":["59510"],"population":18721,"nom":"Hem","code":"59299"},"geometry":{"type":"Point","coordinates":[3.190890945945948,50.65397499999998]}}]}