{"type":"FeatureCollection","features":[{"type":"Feature","properties":{"codesPostaux":["59134"],"population":2319,"nom":"Herlies","code":"59303"},"geometry":{"type":"Point","coordinates":[2.8507869736842104,50.585333684210525]}}]}