{"type":"FeatureCollection","features":[{"type":"Feature","properties":{"codesPostaux":["59570"],"population":901,"nom":"Houdain-lez-Bavay","code":"59315"},"geometry":{"type":"Point","coordinates":[3.7872001418439725,50.33318326241135]}}]}