{"type":"FeatureCollection","features":[{"type":"Feature","properties":{"codesPostaux":["59460"],"population":9897,"nom":"Jeumont","code":"59324"},"geometry":{"type":"Point","coordinates":[4.099436826923076,50.289736153846135]}}]}