{"type":"FeatureCollection","features":[{"type":"Feature","properties":{"codesPostaux":["59552"],"population":5073,"nom":"Lambres-lez-Douai","code":"59329"},"geometry":{"type":"Point","coordinates":[3.059584333333332,50.35386306666663]}}]}