{"type":"FeatureCollection","features":[{"type":"Feature","properties":{"codesPostaux":["59530"],"population":876,"nom":"Jolimetz","code":"59325"},"geometry":{"type":"Point","coordinates":[3.6775042857142854,50.23097678571429]}}]}