{"type":"FeatureCollection","features":[{"type":"Feature","properties":{"codesPostaux":["59480"],"population":1409,"nom":"Illies","code":"59320"},"geometry":{"type":"Point","coordinates":[2.829300000000001,50.56048636363637]}}]}