{"type":"FeatureCollection","features":[{"type":"Feature","properties":{"codesPostaux":["59810"],"population":6969,"nom":"Lesquin","code":"59343"},"geometry":{"type":"Point","coordinates":[3.116453444444446,50.58957988888888]}}]}