{"type":"FeatureCollection","features":[{"type":"Feature","properties":{"codesPostaux":["59126"],"population":8192,"nom":"Linselles","code":"59352"},"geometry":{"type":"Point","coordinates":[3.0708686567164176,50.734942014925366]}}]}