{"type":"FeatureCollection","features":[{"type":"Feature","properties":{"codesPostaux":["59120"],"population":20650,"nom":"Loos","code":"59360"},"geometry":{"type":"Point","coordinates":[3.0202158823529404,50.60990529411765]}}]}