{"type":"FeatureCollection","features":[{"type":"Feature","properties":{"codesPostaux":["59134"],"population":637,"nom":"Le Maisnil","code":"59371"},"geometry":{"type":"Point","coordinates":[2.87994105263158,50.61572710526315]}}]}