{"type":"FeatureCollection","features":[{"type":"Feature","properties":{"codesPostaux":["59440"],"population":482,"nom":"Marbaix","code":"59374"},"geometry":{"type":"Point","coordinates":[3.8409596598639473,50.129897074829955]}}]}