{"type":"FeatureCollection","features":[{"type":"Feature","properties":{"codesPostaux":["59172"],"population":848,"nom":"Mastaing","code":"59391"},"geometry":{"type":"Point","coordinates":[3.2976701639344252,50.30647795081968]}}]}