{"type":"FeatureCollection","features":[{"type":"Feature","properties":{"codesPostaux":["59710"],"population":2730,"nom":"M\u00e9rignies","code":"59398"},"geometry":{"type":"Point","coordinates":[3.1141368000000003,50.50933047999998]}}]}