{"type":"FeatureCollection","features":[{"type":"Feature","properties":{"codesPostaux":["59370"],"population":21513,"nom":"Mons-en-Bar\u0153ul","code":"59410"},"geometry":{"type":"Point","coordinates":[3.107255806451613,50.642935161290325]}}]}