{"type":"FeatureCollection","features":[{"type":"Feature","properties":{"codesPostaux":["59218"],"population":297,"nom":"Neuville-en-Avesnois","code":"59425"},"geometry":{"type":"Point","coordinates":[3.5856931858407095,50.199322212389376]}}]}