{"type":"FeatureCollection","features":[{"type":"Feature","properties":{"codesPostaux":["59940"],"population":1229,"nom":"Neuf-Berquin","code":"59423"},"geometry":{"type":"Point","coordinates":[2.662803529411765,50.66701911764708]}}]}