{"type":"FeatureCollection","features":[{"type":"Feature","properties":{"codesPostaux":["59850"],"population":7407,"nom":"Nieppe","code":"59431"},"geometry":{"type":"Point","coordinates":[2.821467924528302,50.69843867924529]}}]}