{"type":"FeatureCollection","features":[{"type":"Feature","properties":{"codesPostaux":["59400"],"population":496,"nom":"Niergnies","code":"59432"},"geometry":{"type":"Point","coordinates":[3.255578904109589,50.140963287671234]}}]}