{"type":"FeatureCollection","features":[{"type":"Feature","properties":{"codesPostaux":["59570"],"population":713,"nom":"Obies","code":"59441"},"geometry":{"type":"Point","coordinates":[3.782724320987654,50.26959061728395]}}]}