{"type":"FeatureCollection","features":[{"type":"Feature","properties":{"codesPostaux":["59122"],"population":507,"nom":"Oost-Cappel","code":"59448"},"geometry":{"type":"Point","coordinates":[2.5883036065573783,50.92877540983605]}}]}