{"type":"FeatureCollection","features":[{"type":"Feature","properties":{"codesPostaux":["59680"],"population":262,"nom":"Obrechies","code":"59442"},"geometry":{"type":"Point","coordinates":[4.033973520000002,50.22046143999998]}}]}