{"type":"FeatureCollection","features":[{"type":"Feature","properties":{"codesPostaux":["59273"],"population":895,"nom":"P\u00e9ronne-en-M\u00e9lantois","code":"59458"},"geometry":{"type":"Point","coordinates":[3.171369714285715,50.56413342857143]}}]}