{"type":"FeatureCollection","features":[{"type":"Feature","properties":{"codesPostaux":["59840"],"population":8275,"nom":"P\u00e9renchies","code":"59457"},"geometry":{"type":"Point","coordinates":[2.9707417391304354,50.66828021739131]}}]}