{"type":"FeatureCollection","features":[{"type":"Feature","properties":{"codesPostaux":["59670"],"population":549,"nom":"Oxela\u00ebre","code":"59454"},"geometry":{"type":"Point","coordinates":[2.4699599999999995,50.78510714285715]}}]}