{"type":"FeatureCollection","features":[{"type":"Feature","properties":{"codesPostaux":["59269"],"population":942,"nom":"Qu\u00e9r\u00e9naing","code":"59480"},"geometry":{"type":"Point","coordinates":[3.5090511111111113,50.28530111111111]}}]}