{"type":"FeatureCollection","features":[{"type":"Feature","properties":{"codesPostaux":["59173"],"population":2085,"nom":"Renescure","code":"59497"},"geometry":{"type":"Point","coordinates":[2.3787966129032254,50.73124556451615]}}]}