{"type":"FeatureCollection","features":[{"type":"Feature","properties":{"codesPostaux":["59159"],"population":378,"nom":"Rib\u00e9court-la-Tour","code":"59500"},"geometry":{"type":"Point","coordinates":[3.1313260504201685,50.10375789915966]}}]}