{"type":"FeatureCollection","features":[{"type":"Feature","properties":{"codesPostaux":["59990"],"population":775,"nom":"Rombies-et-Marchipont","code":"59505"},"geometry":{"type":"Point","coordinates":[3.649684400000001,50.37097319999998]}}]}