{"type":"FeatureCollection","features":[{"type":"Feature","properties":{"codesPostaux":["59285"],"population":963,"nom":"Rubrouck","code":"59516"},"geometry":{"type":"Point","coordinates":[2.3605415909090905,50.834884772727264]}}]}