{"type":"FeatureCollection","features":[{"type":"Feature","properties":{"codesPostaux":["59350"],"population":11533,"nom":"Saint-Andr\u00e9-lez-Lille","code":"59527"},"geometry":{"type":"Point","coordinates":[3.0462776842105264,50.65964189473685]}}]}