{"type":"FeatureCollection","features":[{"type":"Feature","properties":{"codesPostaux":["59630"],"population":1015,"nom":"Saint-Pierre-Brouck","code":"59539"},"geometry":{"type":"Point","coordinates":[2.1956026785714284,50.89306553571428]}}]}