{"type":"FeatureCollection","features":[{"type":"Feature","properties":{"codesPostaux":["59496"],"population":2974,"nom":"Salom\u00e9","code":"59550"},"geometry":{"type":"Point","coordinates":[2.8354618749999987,50.5398290625]}}]}