{"type":"FeatureCollection","features":[{"type":"Feature","properties":{"codesPostaux":["59216"],"population":1503,"nom":"Sars-Poteries","code":"59555"},"geometry":{"type":"Point","coordinates":[4.043520633802817,50.158338239436596]}}]}