{"type":"FeatureCollection","features":[{"type":"Feature","properties":{"codesPostaux":["59269"],"population":677,"nom":"Sepmeries","code":"59565"},"geometry":{"type":"Point","coordinates":[3.5639057627118644,50.27797220338984]}}]}