{"type":"FeatureCollection","features":[{"type":"Feature","properties":{"codesPostaux":["59554"],"population":543,"nom":"Tilloy-lez-Cambrai","code":"59597"},"geometry":{"type":"Point","coordinates":[3.217616470588235,50.20035161764707]}}]}