{"type":"FeatureCollection","features":[{"type":"Feature","properties":{"codesPostaux":["59175"],"population":1692,"nom":"Vendeville","code":"59609"},"geometry":{"type":"Point","coordinates":[3.080560425531915,50.57273531914895]}}]}