{"type":"FeatureCollection","features":[{"type":"Feature","properties":{"codesPostaux":["59125"],"population":6312,"nom":"Trith-Saint-L\u00e9ger","code":"59603"},"geometry":{"type":"Point","coordinates":[3.4863497647058814,50.329252117647066]}}]}