{"type":"FeatureCollection","features":[{"type":"Feature","properties":{"codesPostaux":["59144"],"population":1057,"nom":"Wargnies-le-Grand","code":"59639"},"geometry":{"type":"Point","coordinates":[3.6577063106796093,50.30811203883495]}}]}