{"type":"FeatureCollection","features":[{"type":"Feature","properties":{"codesPostaux":["59400"],"population":345,"nom":"Wambaix","code":"59635"},"geometry":{"type":"Point","coordinates":[3.3078562500000004,50.128547159090914]}}]}