{"type":"FeatureCollection","features":[{"type":"Feature","properties":{"codesPostaux":["59150"],"population":41522,"nom":"Wattrelos","code":"59650"},"geometry":{"type":"Point","coordinates":[3.2166866824644558,50.70732293838857]}}]}