{"type":"FeatureCollection","features":[{"type":"Feature","properties":{"codesPostaux":["59134"],"population":424,"nom":"Wicres","code":"59658"},"geometry":{"type":"Point","coordinates":[2.869080204081634,50.5675487755102]}}]}