{"type":"FeatureCollection","features":[{"type":"Feature","properties":{"codesPostaux":["59470"],"population":5469,"nom":"Wormhout","code":"59663"},"geometry":{"type":"Point","coordinates":[2.4841248507462685,50.88238253731342]}}]}