{"type":"FeatureCollection","features":[{"type":"Feature","properties":{"codesPostaux":["59380"],"population":320,"nom":"Wylder","code":"59665"},"geometry":{"type":"Point","coordinates":[2.4854445454545453,50.912297636363625]}}]}