{"type":"FeatureCollection","features":[{"type":"Feature","properties":{"codesPostaux":["60480"],"population":507,"nom":"Abbeville-Saint-Lucien","code":"60003"},"geometry":{"type":"Point","coordinates":[2.165956883116884,49.51901688311687]}}]}