{"type":"FeatureCollection","features":[{"type":"Feature","properties":{"codesPostaux":["60570"],"population":3074,"nom":"Andeville","code":"60012"},"geometry":{"type":"Point","coordinates":[2.1681422058823525,49.25687735294117]}}]}