{"type":"FeatureCollection","features":[{"type":"Feature","properties":{"codesPostaux":["60120"],"population":1229,"nom":"Ansauvillers","code":"60017"},"geometry":{"type":"Point","coordinates":[2.383301,49.57061766666666]}}]}