{"type":"FeatureCollection","features":[{"type":"Feature","properties":{"codesPostaux":["60940"],"population":1529,"nom":"Angicourt","code":"60013"},"geometry":{"type":"Point","coordinates":[2.5055764197530865,49.31616271604941]}}]}