{"type":"FeatureCollection","features":[{"type":"Feature","properties":{"codesPostaux":["60300"],"population":690,"nom":"Apremont","code":"60022"},"geometry":{"type":"Point","coordinates":[2.5158591304347824,49.23223913043479]}}]}