{"type":"FeatureCollection","features":[{"type":"Feature","properties":{"codesPostaux":["60350"],"population":1865,"nom":"Attichy","code":"60025"},"geometry":{"type":"Point","coordinates":[3.0472919318181813,49.42187068181817]}}]}