{"type":"FeatureCollection","features":[{"type":"Feature","properties":{"codesPostaux":["60190"],"population":357,"nom":"Avrigny","code":"60036"},"geometry":{"type":"Point","coordinates":[2.5784451063829783,49.384975957446805]}}]}