{"type":"FeatureCollection","features":[{"type":"Feature","properties":{"codesPostaux":["60380"],"population":127,"nom":"Bazancourt","code":"60049"},"geometry":{"type":"Point","coordinates":[1.7381742105263156,49.551024736842095]}}]}