{"type":"FeatureCollection","features":[{"type":"Feature","properties":{"codesPostaux":["60000"],"population":55252,"nom":"Beauvais","code":"60057"},"geometry":{"type":"Point","coordinates":[2.0847115499999997,49.44052130000003]}}]}