{"type":"FeatureCollection","features":[{"type":"Feature","properties":{"codesPostaux":["60400"],"population":211,"nom":"B\u00e9h\u00e9ricourt","code":"60059"},"geometry":{"type":"Point","coordinates":[3.0656165263157877,49.59557599999999]}}]}