{"type":"FeatureCollection","features":[{"type":"Feature","properties":{"codesPostaux":["60370"],"population":1655,"nom":"Berthecourt","code":"60065"},"geometry":{"type":"Point","coordinates":[2.221334608695653,49.34726034782607]}}]}