{"type":"FeatureCollection","features":[{"type":"Feature","properties":{"codesPostaux":["60650"],"population":618,"nom":"Blacourt","code":"60073"},"geometry":{"type":"Point","coordinates":[1.866619347826087,49.457545869565216]}}]}