{"type":"FeatureCollection","features":[{"type":"Feature","properties":{"codesPostaux":["60490"],"population":467,"nom":"Boulogne-la-Grasse","code":"60093"},"geometry":{"type":"Point","coordinates":[2.699321869158878,49.61093495327105]}}]}