{"type":"FeatureCollection","features":[{"type":"Feature","properties":{"codesPostaux":["60590"],"population":246,"nom":"Boutencourt","code":"60097"},"geometry":{"type":"Point","coordinates":[1.871751882352941,49.32269235294116]}}]}