{"type":"FeatureCollection","features":[{"type":"Feature","properties":{"codesPostaux":["60220"],"population":97,"nom":"Boutavent","code":"60096"},"geometry":{"type":"Point","coordinates":[1.749886734693877,49.63808224489797]}}]}