{"type":"FeatureCollection","features":[{"type":"Feature","properties":{"codesPostaux":["60120"],"population":4536,"nom":"Breteuil","code":"60104"},"geometry":{"type":"Point","coordinates":[2.2846379816513758,49.63304174311924]}}]}