{"type":"FeatureCollection","features":[{"type":"Feature","properties":{"codesPostaux":["60170"],"population":1998,"nom":"Cambronne-l\u00e8s-Rib\u00e9court","code":"60119"},"geometry":{"type":"Point","coordinates":[2.897555801526716,49.50589977099238]}}]}