{"type":"FeatureCollection","features":[{"type":"Feature","properties":{"codesPostaux":["60300"],"population":912,"nom":"Chamant","code":"60138"},"geometry":{"type":"Point","coordinates":[2.6275664473684217,49.225327500000006]}}]}