{"type":"FeatureCollection","features":[{"type":"Feature","properties":{"codesPostaux":["60730"],"population":1509,"nom":"Cauvigny","code":"60135"},"geometry":{"type":"Point","coordinates":[2.2334736363636356,49.30056070707072]}}]}