{"type":"FeatureCollection","features":[{"type":"Feature","properties":{"codesPostaux":["60130"],"population":536,"nom":"Catillon-Fumechon","code":"60133"},"geometry":{"type":"Point","coordinates":[2.3803563218390793,49.52885103448275]}}]}