{"type":"FeatureCollection","features":[{"type":"Feature","properties":{"codesPostaux":["60710"],"population":1887,"nom":"Chevri\u00e8res","code":"60149"},"geometry":{"type":"Point","coordinates":[2.677237887323943,49.34454535211268]}}]}