{"type":"FeatureCollection","features":[{"type":"Feature","properties":{"codesPostaux":["60120"],"population":395,"nom":"Chepoix","code":"60146"},"geometry":{"type":"Point","coordinates":[2.3846086170212777,49.607071702127655]}}]}