{"type":"FeatureCollection","features":[{"type":"Feature","properties":{"codesPostaux":["60940"],"population":1530,"nom":"Cinqueux","code":"60154"},"geometry":{"type":"Point","coordinates":[2.528945324675324,49.31736610389612]}}]}