{"type":"FeatureCollection","features":[{"type":"Feature","properties":{"codesPostaux":["60490"],"population":663,"nom":"Conchy-les-Pots","code":"60160"},"geometry":{"type":"Point","coordinates":[2.7332036764705876,49.60457676470589]}}]}