{"type":"FeatureCollection","features":[{"type":"Feature","properties":{"codesPostaux":["60240"],"population":844,"nom":"Courcelles-l\u00e8s-Gisors","code":"60169"},"geometry":{"type":"Point","coordinates":[1.7322528735632177,49.26210712643678]}}]}