{"type":"FeatureCollection","features":[{"type":"Feature","properties":{"codesPostaux":["60120"],"population":432,"nom":"Cormeilles","code":"60163"},"geometry":{"type":"Point","coordinates":[2.2004897500000005,49.64363387499999]}}]}