{"type":"FeatureCollection","features":[{"type":"Feature","properties":{"codesPostaux":["60350"],"population":2138,"nom":"Cuise-la-Motte","code":"60188"},"geometry":{"type":"Point","coordinates":[3.0053150495049508,49.38731702970298]}}]}