{"type":"FeatureCollection","features":[{"type":"Feature","properties":{"codesPostaux":["60790"],"population":926,"nom":"La Drenne","code":"60196"},"geometry":{"type":"Point","coordinates":[2.0971331775700937,49.30522242990653]}}]}