{"type":"FeatureCollection","features":[{"type":"Feature","properties":{"codesPostaux":["60490"],"population":616,"nom":"Cuvilly","code":"60191"},"geometry":{"type":"Point","coordinates":[2.701702823529412,49.5483965882353]}}]}