{"type":"FeatureCollection","features":[{"type":"Feature","properties":{"codesPostaux":["60590"],"population":133,"nom":"\u00c9nencourt-L\u00e9age","code":"60208"},"geometry":{"type":"Point","coordinates":[1.8459961538461538,49.30444051282051]}}]}