{"type":"FeatureCollection","features":[{"type":"Feature","properties":{"codesPostaux":["60130"],"population":172,"nom":"Erquinvillers","code":"60216"},"geometry":{"type":"Point","coordinates":[2.487543636363636,49.458317454545465]}}]}