{"type":"FeatureCollection","features":[{"type":"Feature","properties":{"codesPostaux":["60240"],"population":525,"nom":"Fleury","code":"60239"},"geometry":{"type":"Point","coordinates":[1.9670390625000007,49.247895937500004]}}]}