{"type":"FeatureCollection","features":[{"type":"Feature","properties":{"codesPostaux":["60360"],"population":268,"nom":"Fontaine-Bonneleau","code":"60240"},"geometry":{"type":"Point","coordinates":[2.147741103448275,49.65927096551725]}}]}