{"type":"FeatureCollection","features":[{"type":"Feature","properties":{"codesPostaux":["60000"],"population":412,"nom":"Fouquenies","code":"60250"},"geometry":{"type":"Point","coordinates":[2.034778131868131,49.46769340659339]}}]}