{"type":"FeatureCollection","features":[{"type":"Feature","properties":{"codesPostaux":["60240"],"population":463,"nom":"Fresne-L\u00e9guillon","code":"60257"},"geometry":{"type":"Point","coordinates":[1.9900531775700936,49.24839439252335]}}]}