{"type":"FeatureCollection","features":[{"type":"Feature","properties":{"codesPostaux":["60240"],"population":771,"nom":"Fresneaux-Montchevreuil","code":"60256"},"geometry":{"type":"Point","coordinates":[2.005805679999999,49.28661263999998]}}]}