{"type":"FeatureCollection","features":[{"type":"Feature","properties":{"codesPostaux":["60120"],"population":359,"nom":"Gannes","code":"60268"},"geometry":{"type":"Point","coordinates":[2.4213926923076925,49.57620807692307]}}]}