{"type":"FeatureCollection","features":[{"type":"Feature","properties":{"codesPostaux":["60800"],"population":517,"nom":"Fresnoy-le-Luat","code":"60261"},"geometry":{"type":"Point","coordinates":[2.765154555555555,49.21026433333335]}}]}