{"type":"FeatureCollection","features":[{"type":"Feature","properties":{"codesPostaux":["60400"],"population":321,"nom":"Grandr\u00fb","code":"60287"},"geometry":{"type":"Point","coordinates":[3.0802398913043483,49.608640000000015]}}]}