{"type":"FeatureCollection","features":[{"type":"Feature","properties":{"codesPostaux":["60240"],"population":365,"nom":"Hadancourt-le-Haut-Clocher","code":"60293"},"geometry":{"type":"Point","coordinates":[1.8477374038461543,49.191735192307696]}}]}