{"type":"FeatureCollection","features":[{"type":"Feature","properties":{"codesPostaux":["60350"],"population":270,"nom":"Hautefontaine","code":"60305"},"geometry":{"type":"Point","coordinates":[3.057973437499999,49.36425453125001]}}]}