{"type":"FeatureCollection","features":[{"type":"Feature","properties":{"codesPostaux":["60119"],"population":801,"nom":"H\u00e9nonville","code":"60309"},"geometry":{"type":"Point","coordinates":[2.0531785365853668,49.211835365853666]}}]}