{"type":"FeatureCollection","features":[{"type":"Feature","properties":{"codesPostaux":["60710"],"population":614,"nom":"Houdancourt","code":"60318"},"geometry":{"type":"Point","coordinates":[2.6463637681159424,49.33730144927536]}}]}