{"type":"FeatureCollection","features":[{"type":"Feature","properties":{"codesPostaux":["60390"],"population":603,"nom":"La Houssoye","code":"60319"},"geometry":{"type":"Point","coordinates":[1.9497519736842117,49.35503013157895]}}]}