{"type":"FeatureCollection","features":[{"type":"Feature","properties":{"codesPostaux":["60650"],"population":1577,"nom":"Lachapelle-aux-Pots","code":"60333"},"geometry":{"type":"Point","coordinates":[1.917921846153847,49.447384564102556]}}]}