{"type":"FeatureCollection","features":[{"type":"Feature","properties":{"codesPostaux":["60380"],"population":150,"nom":"Lachapelle-sous-Gerberoy","code":"60335"},"geometry":{"type":"Point","coordinates":[1.8736598924731191,49.53882569892474]}}]}