{"type":"FeatureCollection","features":[{"type":"Feature","properties":{"codesPostaux":["60590"],"population":447,"nom":"Labosse","code":"60331"},"geometry":{"type":"Point","coordinates":[1.905140615384615,49.352611076923075]}}]}