{"type":"FeatureCollection","features":[{"type":"Feature","properties":{"codesPostaux":["60260"],"population":9136,"nom":"Lamorlaye","code":"60346"},"geometry":{"type":"Point","coordinates":[2.4236118749999993,49.15679260416666]}}]}