{"type":"FeatureCollection","features":[{"type":"Feature","properties":{"codesPostaux":["60800"],"population":922,"nom":"L\u00e9vignen","code":"60358"},"geometry":{"type":"Point","coordinates":[2.9132544444444437,49.19913923076921]}}]}