{"type":"FeatureCollection","features":[{"type":"Feature","properties":{"codesPostaux":["60640"],"population":210,"nom":"Libermont","code":"60362"},"geometry":{"type":"Point","coordinates":[2.9794627000000014,49.68942489999999]}}]}