{"type":"FeatureCollection","features":[{"type":"Feature","properties":{"codesPostaux":["60140"],"population":7204,"nom":"Liancourt","code":"60360"},"geometry":{"type":"Point","coordinates":[2.464029074074075,49.331084999999995]}}]}