{"type":"FeatureCollection","features":[{"type":"Feature","properties":{"codesPostaux":["60600"],"population":389,"nom":"Maimbeville","code":"60375"},"geometry":{"type":"Point","coordinates":[2.5206635211267603,49.413415352112686]}}]}