{"type":"FeatureCollection","features":[{"type":"Feature","properties":{"codesPostaux":["60490"],"population":409,"nom":"Marest-sur-Matz","code":"60378"},"geometry":{"type":"Point","coordinates":[2.823181025641027,49.50313602564105]}}]}