{"type":"FeatureCollection","features":[{"type":"Feature","properties":{"codesPostaux":["60420"],"population":2711,"nom":"Maignelay-Montigny","code":"60374"},"geometry":{"type":"Point","coordinates":[2.521648396226415,49.54958377358492]}}]}