{"type":"FeatureCollection","features":[{"type":"Feature","properties":{"codesPostaux":["60420"],"population":110,"nom":"M\u00e9n\u00e9villers","code":"60394"},"geometry":{"type":"Point","coordinates":[2.6050418571428566,49.5194732857143]}}]}