{"type":"FeatureCollection","features":[{"type":"Feature","properties":{"codesPostaux":["60660"],"population":240,"nom":"Maysel","code":"60391"},"geometry":{"type":"Point","coordinates":[2.3680244444444445,49.25447194444445]}}]}