{"type":"FeatureCollection","features":[{"type":"Feature","properties":{"codesPostaux":["60880"],"population":2091,"nom":"Le Meux","code":"60402"},"geometry":{"type":"Point","coordinates":[2.7458512087912097,49.371176923076916]}}]}