{"type":"FeatureCollection","features":[{"type":"Feature","properties":{"codesPostaux":["60810"],"population":162,"nom":"Mont\u00e9pilloy","code":"60415"},"geometry":{"type":"Point","coordinates":[2.7079286885245906,49.2123532786885]}}]}