{"type":"FeatureCollection","features":[{"type":"Feature","properties":{"codesPostaux":["60190"],"population":242,"nom":"Montmartin","code":"60424"},"geometry":{"type":"Point","coordinates":[2.6952121739130437,49.46697753623189]}}]}