{"type":"FeatureCollection","features":[{"type":"Feature","properties":{"codesPostaux":["60127"],"population":1023,"nom":"Morienval","code":"60430"},"geometry":{"type":"Point","coordinates":[2.9320274736842125,49.301241368421046]}}]}