{"type":"FeatureCollection","features":[{"type":"Feature","properties":{"codesPostaux":["60350"],"population":226,"nom":"Moulin-sous-Touvent","code":"60438"},"geometry":{"type":"Point","coordinates":[3.060613728813561,49.46295610169492]}}]}