{"type":"FeatureCollection","features":[{"type":"Feature","properties":{"codesPostaux":["60490"],"population":212,"nom":"Mortemer","code":"60434"},"geometry":{"type":"Point","coordinates":[2.673894520547945,49.57066356164384]}}]}