{"type":"FeatureCollection","features":[{"type":"Feature","properties":{"codesPostaux":["60250"],"population":80,"nom":"Mouchy-le-Ch\u00e2tel","code":"60437"},"geometry":{"type":"Point","coordinates":[2.248004705882353,49.32664705882353]}}]}