{"type":"FeatureCollection","features":[{"type":"Feature","properties":{"codesPostaux":["60480"],"population":182,"nom":"Noir\u00e9mont","code":"60465"},"geometry":{"type":"Point","coordinates":[2.214865625,49.548817375]}}]}