{"type":"FeatureCollection","features":[{"type":"Feature","properties":{"codesPostaux":["60840"],"population":1009,"nom":"Nointel","code":"60464"},"geometry":{"type":"Point","coordinates":[2.487534202898551,49.38710028985507]}}]}