{"type":"FeatureCollection","features":[{"type":"Feature","properties":{"codesPostaux":["60480"],"population":777,"nom":"Noyers-Saint-Martin","code":"60470"},"geometry":{"type":"Point","coordinates":[2.267015777777779,49.55192888888887]}}]}