{"type":"FeatureCollection","features":[{"type":"Feature","properties":{"codesPostaux":["60650"],"population":1365,"nom":"Ons-en-Bray","code":"60477"},"geometry":{"type":"Point","coordinates":[1.921616277372262,49.4220588321168]}}]}