{"type":"FeatureCollection","features":[{"type":"Feature","properties":{"codesPostaux":["60120"],"population":163,"nom":"Plainville","code":"60496"},"geometry":{"type":"Point","coordinates":[2.4517692156862756,49.61458215686274]}}]}