{"type":"FeatureCollection","features":[{"type":"Feature","properties":{"codesPostaux":["60430"],"population":1106,"nom":"Ponchon","code":"60504"},"geometry":{"type":"Point","coordinates":[2.1871094736842096,49.350533458646616]}}]}