{"type":"FeatureCollection","features":[{"type":"Feature","properties":{"codesPostaux":["60330"],"population":3267,"nom":"Le Plessis-Belleville","code":"60500"},"geometry":{"type":"Point","coordinates":[2.75835914893617,49.10032255319148]}}]}