{"type":"FeatureCollection","features":[{"type":"Feature","properties":{"codesPostaux":["60290"],"population":2587,"nom":"Rantigny","code":"60524"},"geometry":{"type":"Point","coordinates":[2.434591803278689,49.33642901639346]}}]}