{"type":"FeatureCollection","features":[{"type":"Feature","properties":{"codesPostaux":["60130"],"population":1139,"nom":"Ravenel","code":"60526"},"geometry":{"type":"Point","coordinates":[2.5062724590163934,49.514239999999994]}}]}