{"type":"FeatureCollection","features":[{"type":"Feature","properties":{"codesPostaux":["60490"],"population":254,"nom":"Ricquebourg","code":"60538"},"geometry":{"type":"Point","coordinates":[2.75359380952381,49.56079047619048]}}]}