{"type":"FeatureCollection","features":[{"type":"Feature","properties":{"codesPostaux":["60126"],"population":568,"nom":"Rivecourt","code":"60540"},"geometry":{"type":"Point","coordinates":[2.7365370731707315,49.34814219512194]}}]}