{"type":"FeatureCollection","features":[{"type":"Feature","properties":{"codesPostaux":["60420"],"population":277,"nom":"Sains-Morainvillers","code":"60564"},"geometry":{"type":"Point","coordinates":[2.4614629411764706,49.58132929411766]}}]}