{"type":"FeatureCollection","features":[{"type":"Feature","properties":{"codesPostaux":["60380"],"population":94,"nom":"Saint-Deniscourt","code":"60571"},"geometry":{"type":"Point","coordinates":[1.8648436206896557,49.609612068965525]}}]}