{"type":"FeatureCollection","features":[{"type":"Feature","properties":{"codesPostaux":["60730"],"population":2889,"nom":"Sainte-Genevi\u00e8ve","code":"60575"},"geometry":{"type":"Point","coordinates":[2.1996694666666663,49.291462133333326]}}]}