{"type":"FeatureCollection","features":[{"type":"Feature","properties":{"codesPostaux":["60370"],"population":641,"nom":"Saint-F\u00e9lix","code":"60574"},"geometry":{"type":"Point","coordinates":[2.2839027205882347,49.35697022058821]}}]}