{"type":"FeatureCollection","features":[{"type":"Feature","properties":{"codesPostaux":["60350"],"population":330,"nom":"Saint-\u00c9tienne-Roilaye","code":"60572"},"geometry":{"type":"Point","coordinates":[3.0126399999999998,49.3637945652174]}}]}