{"type":"FeatureCollection","features":[{"type":"Feature","properties":{"codesPostaux":["60410"],"population":993,"nom":"Saintines","code":"60578"},"geometry":{"type":"Point","coordinates":[2.768820266666667,49.304726133333325]}}]}