{"type":"FeatureCollection","features":[{"type":"Feature","properties":{"codesPostaux":["60860"],"population":1294,"nom":"Saint-Omer-en-Chauss\u00e9e","code":"60590"},"geometry":{"type":"Point","coordinates":[1.9994775,49.531904166666656]}}]}