{"type":"FeatureCollection","features":[{"type":"Feature","properties":{"codesPostaux":["60410"],"population":626,"nom":"Saint-Vaast-de-Longmont","code":"60600"},"geometry":{"type":"Point","coordinates":[2.7477283673469395,49.2976518367347]}}]}