{"type":"FeatureCollection","features":[{"type":"Feature","properties":{"codesPostaux":["60210"],"population":336,"nom":"Sarnois","code":"60605"},"geometry":{"type":"Point","coordinates":[1.923648222222222,49.68034155555556]}}]}