{"type":"FeatureCollection","features":[{"type":"Feature","properties":{"codesPostaux":["60510"],"population":984,"nom":"Therdonne","code":"60628"},"geometry":{"type":"Point","coordinates":[2.1457756842105264,49.4247914736842]}}]}