{"type":"FeatureCollection","features":[{"type":"Feature","properties":{"codesPostaux":["60210"],"population":436,"nom":"Sommereux","code":"60622"},"geometry":{"type":"Point","coordinates":[2.0143631168831173,49.67507701298701]}}]}