{"type":"FeatureCollection","features":[{"type":"Feature","properties":{"codesPostaux":["60160"],"population":1066,"nom":"Thiverny","code":"60635"},"geometry":{"type":"Point","coordinates":[2.4297165116279076,49.24678279069769]}}]}