{"type":"FeatureCollection","features":[{"type":"Feature","properties":{"codesPostaux":["60310"],"population":758,"nom":"Thiescourt","code":"60632"},"geometry":{"type":"Point","coordinates":[2.8680633582089547,49.56073052238807]}}]}