{"type":"FeatureCollection","features":[{"type":"Feature","properties":{"codesPostaux":["60350"],"population":2107,"nom":"Trosly-Breuil","code":"60647"},"geometry":{"type":"Point","coordinates":[2.9661590361445795,49.40209939759037]}}]}