{"type":"FeatureCollection","features":[{"type":"Feature","properties":{"codesPostaux":["60240"],"population":180,"nom":"Vaudancourt","code":"60659"},"geometry":{"type":"Point","coordinates":[1.7636975581395342,49.230811279069776]}}]}