{"type":"FeatureCollection","features":[{"type":"Feature","properties":{"codesPostaux":["60130"],"population":273,"nom":"Valescourt","code":"60653"},"geometry":{"type":"Point","coordinates":[2.4298808490566035,49.487206320754716]}}]}