{"type":"FeatureCollection","features":[{"type":"Feature","properties":{"codesPostaux":["60400"],"population":381,"nom":"Varesnes","code":"60655"},"geometry":{"type":"Point","coordinates":[3.0723461832061076,49.5616675572519]}}]}