{"type":"FeatureCollection","features":[{"type":"Feature","properties":{"codesPostaux":["60117"],"population":684,"nom":"Vauciennes","code":"60658"},"geometry":{"type":"Point","coordinates":[3.016918400000002,49.22500746666672]}}]}