{"type":"FeatureCollection","features":[{"type":"Feature","properties":{"codesPostaux":["60117"],"population":953,"nom":"Vaumoise","code":"60661"},"geometry":{"type":"Point","coordinates":[2.9810883333333327,49.24114512820514]}}]}