{"type":"FeatureCollection","features":[{"type":"Feature","properties":{"codesPostaux":["60590"],"population":350,"nom":"Le Vaumain","code":"60660"},"geometry":{"type":"Point","coordinates":[1.8646381538461545,49.336333076923076]}}]}