{"type":"FeatureCollection","features":[{"type":"Feature","properties":{"codesPostaux":["60112"],"population":731,"nom":"Verderel-l\u00e8s-Sauqueuse","code":"60668"},"geometry":{"type":"Point","coordinates":[2.0818831818181813,49.50727242424241]}}]}