{"type":"FeatureCollection","features":[{"type":"Feature","properties":{"codesPostaux":["60350"],"population":626,"nom":"Vieux-Moulin","code":"60674"},"geometry":{"type":"Point","coordinates":[2.9289465384615383,49.39718230769232]}}]}