{"type":"FeatureCollection","features":[{"type":"Feature","properties":{"codesPostaux":["60340"],"population":2338,"nom":"Villers-sous-Saint-Leu","code":"60686"},"geometry":{"type":"Point","coordinates":[2.387592424242424,49.2165962121212]}}]}