{"type":"FeatureCollection","features":[{"type":"Feature","properties":{"codesPostaux":["60860"],"population":159,"nom":"Villers-sur-Bonni\u00e8res","code":"60688"},"geometry":{"type":"Point","coordinates":[1.963405217391304,49.53416521739131]}}]}