{"type":"FeatureCollection","features":[{"type":"Feature","properties":{"codesPostaux":["60420"],"population":300,"nom":"Wacquemoulin","code":"60698"},"geometry":{"type":"Point","coordinates":[2.6180287272727267,49.50850554545456]}}]}