{"type":"FeatureCollection","features":[{"type":"Feature","properties":{"codesPostaux":["61100"],"population":424,"nom":"Aubusson","code":"61011"},"geometry":{"type":"Point","coordinates":[-0.5561505952380953,48.77957107142856]}}]}