{"type":"FeatureCollection","features":[{"type":"Feature","properties":{"codesPostaux":["61170"],"population":118,"nom":"Bur\u00e9","code":"61066"},"geometry":{"type":"Point","coordinates":[0.4049028828828828,48.50737234234234]}}]}