{"type":"FeatureCollection","features":[{"type":"Feature","properties":{"codesPostaux":["61390"],"population":105,"nom":"Brullemail","code":"61064"},"geometry":{"type":"Point","coordinates":[0.32699022900763347,48.656513893129784]}}]}