{"type":"FeatureCollection","features":[{"type":"Feature","properties":{"codesPostaux":["61330"],"population":1242,"nom":"Ceauc\u00e9","code":"61075"},"geometry":{"type":"Point","coordinates":[-0.6332864814814811,48.49376921296298]}}]}