{"type":"FeatureCollection","features":[{"type":"Feature","properties":{"codesPostaux":["61120"],"population":193,"nom":"Camembert","code":"61071"},"geometry":{"type":"Point","coordinates":[0.17000173333333338,48.891797333333336]}}]}