{"type":"FeatureCollection","features":[{"type":"Feature","properties":{"codesPostaux":["61500"],"population":482,"nom":"La Chapelle-pr\u00e8s-S\u00e9es","code":"61098"},"geometry":{"type":"Point","coordinates":[0.14790018691588783,48.565186822429915]}}]}