{"type":"FeatureCollection","features":[{"type":"Feature","properties":{"codesPostaux":["61230"],"population":181,"nom":"Cisai-Saint-Aubin","code":"61108"},"geometry":{"type":"Point","coordinates":[0.3535431756756757,48.77291601351352]}}]}