{"type":"FeatureCollection","features":[{"type":"Feature","properties":{"codesPostaux":["61360"],"population":294,"nom":"Coulimer","code":"61121"},"geometry":{"type":"Point","coordinates":[0.4585222043010751,48.477792849462375]}}]}