{"type":"FeatureCollection","features":[{"type":"Feature","properties":{"codesPostaux":["61170"],"population":502,"nom":"Coulonges-sur-Sarthe","code":"61126"},"geometry":{"type":"Point","coordinates":[0.39250995780590714,48.52431734177214]}}]}