{"type":"FeatureCollection","features":[{"type":"Feature","properties":{"codesPostaux":["61600"],"population":139,"nom":"Faverolles","code":"61158"},"geometry":{"type":"Point","coordinates":[-0.29396930817610084,48.667774025157215]}}]}