{"type":"FeatureCollection","features":[{"type":"Feature","properties":{"codesPostaux":["61210"],"population":453,"nom":"Giel-Courteilles","code":"61189"},"geometry":{"type":"Point","coordinates":[-0.20955029411764703,48.76258176470588]}}]}