{"type":"FeatureCollection","features":[{"type":"Feature","properties":{"codesPostaux":["61320"],"population":184,"nom":"La Lande-de-Goult","code":"61216"},"geometry":{"type":"Point","coordinates":[-0.06055273255813953,48.58945453488375]}}]}