{"type":"FeatureCollection","features":[{"type":"Feature","properties":{"codesPostaux":["61220"],"population":136,"nom":"Lignou","code":"61227"},"geometry":{"type":"Point","coordinates":[-0.3390527192982454,48.6760855263158]}}]}