{"type":"FeatureCollection","features":[{"type":"Feature","properties":{"codesPostaux":["61240"],"population":28,"nom":"Lign\u00e8res","code":"61225"},"geometry":{"type":"Point","coordinates":[0.30730023529411776,48.738804]}}]}