{"type":"FeatureCollection","features":[{"type":"Feature","properties":{"codesPostaux":["61600"],"population":249,"nom":"Lonlay-le-Tesson","code":"61233"},"geometry":{"type":"Point","coordinates":[-0.34000268518518517,48.65059740740739]}}]}