{"type":"FeatureCollection","features":[{"type":"Feature","properties":{"codesPostaux":["61160"],"population":76,"nom":"Louvi\u00e8res-en-Auge","code":"61238"},"geometry":{"type":"Point","coordinates":[0.02746949152542372,48.87133101694914]}}]}