{"type":"FeatureCollection","features":[{"type":"Feature","properties":{"codesPostaux":["61170"],"population":758,"nom":"Le M\u00eale-sur-Sarthe","code":"61258"},"geometry":{"type":"Point","coordinates":[0.3537722727272728,48.51069431818182]}}]}