{"type":"FeatureCollection","features":[{"type":"Feature","properties":{"codesPostaux":["61230"],"population":122,"nom":"M\u00e9nil-Hubert-en-Exmes","code":"61268"},"geometry":{"type":"Point","coordinates":[0.22778076923076923,48.803850128205134]}}]}