{"type":"FeatureCollection","features":[{"type":"Feature","properties":{"codesPostaux":["61430"],"population":457,"nom":"M\u00e9nil-Hubert-sur-Orne","code":"61269"},"geometry":{"type":"Point","coordinates":[-0.41334226277372255,48.84590299270074]}}]}