{"type":"FeatureCollection","features":[{"type":"Feature","properties":{"codesPostaux":["61210"],"population":135,"nom":"Montreuil-au-Houlme","code":"61290"},"geometry":{"type":"Point","coordinates":[-0.2600840860215055,48.68025096774195]}}]}