{"type":"FeatureCollection","features":[{"type":"Feature","properties":{"codesPostaux":["61160"],"population":83,"nom":"Montreuil-la-Cambe","code":"61291"},"geometry":{"type":"Point","coordinates":[0.033850714285714296,48.88434848214284]}}]}