{"type":"FeatureCollection","features":[{"type":"Feature","properties":{"codesPostaux":["61120"],"population":239,"nom":"Neuville-sur-Touques","code":"61307"},"geometry":{"type":"Point","coordinates":[0.2803004918032788,48.86710877049182]}}]}