{"type":"FeatureCollection","features":[{"type":"Feature","properties":{"codesPostaux":["61130"],"population":274,"nom":"Origny-le-Roux","code":"61319"},"geometry":{"type":"Point","coordinates":[0.4206800000000001,48.33323242774565]}}]}