{"type":"FeatureCollection","features":[{"type":"Feature","properties":{"codesPostaux":["61400"],"population":743,"nom":"Le Pin-la-Garenne","code":"61329"},"geometry":{"type":"Point","coordinates":[0.5494306711409399,48.44420422818792]}}]}