{"type":"FeatureCollection","features":[{"type":"Feature","properties":{"codesPostaux":["61220"],"population":303,"nom":"Pointel","code":"61332"},"geometry":{"type":"Point","coordinates":[-0.3451773076923077,48.700247032967006]}}]}