{"type":"FeatureCollection","features":[{"type":"Feature","properties":{"codesPostaux":["61320"],"population":154,"nom":"Rouperroux","code":"61357"},"geometry":{"type":"Point","coordinates":[-0.08103537037037035,48.54627435185185]}}]}