{"type":"FeatureCollection","features":[{"type":"Feature","properties":{"codesPostaux":["61250"],"population":120,"nom":"Saint-C\u00e9neri-le-G\u00e9rei","code":"61372"},"geometry":{"type":"Point","coordinates":[-0.040813370786516846,48.38815168539324]}}]}