{"type":"FeatureCollection","features":[{"type":"Feature","properties":{"codesPostaux":["61230"],"population":355,"nom":"Saint-Evroult-de-Montfort","code":"61385"},"geometry":{"type":"Point","coordinates":[0.31622888888888884,48.81108700000002]}}]}