{"type":"FeatureCollection","features":[{"type":"Feature","properties":{"codesPostaux":["61370"],"population":1102,"nom":"Sainte-Gauburge-Sainte-Colombe","code":"61389"},"geometry":{"type":"Point","coordinates":[0.44155209090909103,48.71415636363636]}}]}