{"type":"FeatureCollection","features":[{"type":"Feature","properties":{"codesPostaux":["61160"],"population":70,"nom":"Saint-Gervais-des-Sablons","code":"61399"},"geometry":{"type":"Point","coordinates":[0.07395133333333336,48.90301093333335]}}]}