{"type":"FeatureCollection","features":[{"type":"Feature","properties":{"codesPostaux":["61560"],"population":89,"nom":"Saint-Germain-de-Martigny","code":"61396"},"geometry":{"type":"Point","coordinates":[0.4686597435897439,48.5873955128205]}}]}