{"type":"FeatureCollection","features":[{"type":"Feature","properties":{"codesPostaux":["61500"],"population":137,"nom":"Saint-Hilaire-la-G\u00e9rard","code":"61403"},"geometry":{"type":"Point","coordinates":[0.05475240000000002,48.59159376000001]}}]}