{"type":"FeatureCollection","features":[{"type":"Feature","properties":{"codesPostaux":["61270"],"population":326,"nom":"Saint-Hilaire-sur-Risle","code":"61406"},"geometry":{"type":"Point","coordinates":[0.5127248837209301,48.72733261627907]}}]}