{"type":"FeatureCollection","features":[{"type":"Feature","properties":{"codesPostaux":["61320"],"population":79,"nom":"Sainte-Marie-la-Robert","code":"61420"},"geometry":{"type":"Point","coordinates":[-0.1405339080459769,48.63091279693483]}}]}