{"type":"FeatureCollection","features":[{"type":"Feature","properties":{"codesPostaux":["61550"],"population":263,"nom":"Saint-Nicolas-de-Sommaire","code":"61435"},"geometry":{"type":"Point","coordinates":[0.58678,48.81068941798942]}}]}