{"type":"FeatureCollection","features":[{"type":"Feature","properties":{"codesPostaux":["61100"],"population":637,"nom":"Saint-Paul","code":"61443"},"geometry":{"type":"Point","coordinates":[-0.6260461111111112,48.74136138888889]}}]}