{"type":"FeatureCollection","features":[{"type":"Feature","properties":{"codesPostaux":["61360"],"population":74,"nom":"Saint-Quentin-de-Blavou","code":"61450"},"geometry":{"type":"Point","coordinates":[0.42200227941176477,48.480581838235295]}}]}