{"type":"FeatureCollection","features":[{"type":"Feature","properties":{"codesPostaux":["61120"],"population":219,"nom":"Ticheville","code":"61485"},"geometry":{"type":"Point","coordinates":[0.26373771428571413,48.907018499999985]}}]}