{"type":"FeatureCollection","features":[{"type":"Feature","properties":{"codesPostaux":["61250"],"population":1543,"nom":"Valframbert","code":"61497"},"geometry":{"type":"Point","coordinates":[0.11630722222222227,48.461899861111114]}}]}