{"type":"FeatureCollection","features":[{"type":"Feature","properties":{"codesPostaux":["61230"],"population":91,"nom":"La Trinit\u00e9-des-Laitiers","code":"61493"},"geometry":{"type":"Point","coordinates":[0.3780365680473373,48.80191479289941]}}]}