{"type":"FeatureCollection","features":[{"type":"Feature","properties":{"codesPostaux":["61300"],"population":216,"nom":"Vitrai-sous-Laigle","code":"61510"},"geometry":{"type":"Point","coordinates":[0.7023384415584415,48.718210389610384]}}]}