{"type":"FeatureCollection","features":[{"type":"Feature","properties":{"codesPostaux":["62690"],"population":249,"nom":"Agni\u00e8res","code":"62012"},"geometry":{"type":"Point","coordinates":[2.606113880597015,50.351817313432825]}}]}