{"type":"FeatureCollection","features":[{"type":"Feature","properties":{"codesPostaux":["62217"],"population":1946,"nom":"Agny","code":"62013"},"geometry":{"type":"Point","coordinates":[2.761775833333333,50.25133416666667]}}]}