{"type":"FeatureCollection","features":[{"type":"Feature","properties":{"codesPostaux":["62850"],"population":940,"nom":"Alquines","code":"62024"},"geometry":{"type":"Point","coordinates":[1.9966991935483869,50.736182822580666]}}]}