{"type":"FeatureCollection","features":[{"type":"Feature","properties":{"codesPostaux":["62260"],"population":506,"nom":"Amettes","code":"62029"},"geometry":{"type":"Point","coordinates":[2.3940363934426236,50.526802131147534]}}]}