{"type":"FeatureCollection","features":[{"type":"Feature","properties":{"codesPostaux":["62760"],"population":313,"nom":"Amplier","code":"62030"},"geometry":{"type":"Point","coordinates":[2.39705,50.137009550561814]}}]}