{"type":"FeatureCollection","features":[{"type":"Feature","properties":{"codesPostaux":["62690"],"population":1399,"nom":"Aubigny-en-Artois","code":"62045"},"geometry":{"type":"Point","coordinates":[2.5866196249999986,50.350700749999994]}}]}