{"type":"FeatureCollection","features":[{"type":"Feature","properties":{"codesPostaux":["62650"],"population":43,"nom":"Avesnes","code":"62062"},"geometry":{"type":"Point","coordinates":[1.964865238095238,50.55137214285713]}}]}