{"type":"FeatureCollection","features":[{"type":"Feature","properties":{"codesPostaux":["62550"],"population":412,"nom":"Bailleul-l\u00e8s-Pernes","code":"62071"},"geometry":{"type":"Point","coordinates":[2.3817242028985497,50.5065368115942]}}]}