{"type":"FeatureCollection","features":[{"type":"Feature","properties":{"codesPostaux":["62850"],"population":203,"nom":"Bainghen","code":"62076"},"geometry":{"type":"Point","coordinates":[1.9046690909090904,50.75245193181819]}}]}