{"type":"FeatureCollection","features":[{"type":"Feature","properties":{"codesPostaux":["62123"],"population":260,"nom":"Bailleulval","code":"62074"},"geometry":{"type":"Point","coordinates":[2.6277602816901404,50.22141450704223]}}]}