{"type":"FeatureCollection","features":[{"type":"Feature","properties":{"codesPostaux":["62580"],"population":1292,"nom":"Bailleul-Sir-Berthoult","code":"62073"},"geometry":{"type":"Point","coordinates":[2.8423823157894748,50.337377263157904]}}]}