{"type":"FeatureCollection","features":[{"type":"Feature","properties":{"codesPostaux":["62960"],"population":241,"nom":"Beaumetz-l\u00e8s-Aire","code":"62095"},"geometry":{"type":"Point","coordinates":[2.221426363636364,50.54446545454545]}}]}