{"type":"FeatureCollection","features":[{"type":"Feature","properties":{"codesPostaux":["62124"],"population":619,"nom":"Beaumetz-l\u00e8s-Cambrai","code":"62096"},"geometry":{"type":"Point","coordinates":[2.98713017699115,50.124978141592926]}}]}