{"type":"FeatureCollection","features":[{"type":"Feature","properties":{"codesPostaux":["62124"],"population":378,"nom":"Beugny","code":"62122"},"geometry":{"type":"Point","coordinates":[2.9362484210526314,50.11965596491228]}}]}