{"type":"FeatureCollection","features":[{"type":"Feature","properties":{"codesPostaux":["62250"],"population":413,"nom":"Beuvrequen","code":"62125"},"geometry":{"type":"Point","coordinates":[1.673622755102041,50.79991469387754]}}]}