{"type":"FeatureCollection","features":[{"type":"Feature","properties":{"codesPostaux":["62770"],"population":744,"nom":"Blangy-sur-Ternoise","code":"62138"},"geometry":{"type":"Point","coordinates":[2.1727786138613854,50.42333900990097]}}]}