{"type":"FeatureCollection","features":[{"type":"Feature","properties":{"codesPostaux":["62175"],"population":404,"nom":"Boiry-Sainte-Rictrude","code":"62147"},"geometry":{"type":"Point","coordinates":[2.74708223880597,50.20168895522387]}}]}