{"type":"FeatureCollection","features":[{"type":"Feature","properties":{"codesPostaux":["62270"],"population":651,"nom":"Bonni\u00e8res","code":"62154"},"geometry":{"type":"Point","coordinates":[2.270825032258065,50.235847354838725]}}]}