{"type":"FeatureCollection","features":[{"type":"Feature","properties":{"codesPostaux":["62860"],"population":1220,"nom":"Bourlon","code":"62164"},"geometry":{"type":"Point","coordinates":[3.119475312499999,50.17754489583334]}}]}