{"type":"FeatureCollection","features":[{"type":"Feature","properties":{"codesPostaux":["62550"],"population":598,"nom":"Bours","code":"62166"},"geometry":{"type":"Point","coordinates":[2.40851171641791,50.44765253731344]}}]}