{"type":"FeatureCollection","features":[{"type":"Feature","properties":{"codesPostaux":["62610"],"population":1314,"nom":"Br\u00eames","code":"62174"},"geometry":{"type":"Point","coordinates":[1.9563083898305087,50.845279915254224]}}]}