{"type":"FeatureCollection","features":[{"type":"Feature","properties":{"codesPostaux":["62690"],"population":632,"nom":"Camblain-l'Abb\u00e9","code":"62199"},"geometry":{"type":"Point","coordinates":[2.635162031250001,50.37649843749998]}}]}