{"type":"FeatureCollection","features":[{"type":"Feature","properties":{"codesPostaux":["62350"],"population":1611,"nom":"Calonne-sur-la-Lys","code":"62195"},"geometry":{"type":"Point","coordinates":[2.6050301063829795,50.61479829787233]}}]}