{"type":"FeatureCollection","features":[{"type":"Feature","properties":{"codesPostaux":["62170"],"population":647,"nom":"La Calotterie","code":"62196"},"geometry":{"type":"Point","coordinates":[1.7235347619047618,50.478723333333356]}}]}