{"type":"FeatureCollection","features":[{"type":"Feature","properties":{"codesPostaux":["62176"],"population":2636,"nom":"Camiers","code":"62201"},"geometry":{"type":"Point","coordinates":[1.621112314049586,50.55950099173552]}}]}