{"type":"FeatureCollection","features":[{"type":"Feature","properties":{"codesPostaux":["62150"],"population":340,"nom":"Caucourt","code":"62218"},"geometry":{"type":"Point","coordinates":[2.5728442666666678,50.396920399999985]}}]}