{"type":"FeatureCollection","features":[{"type":"Feature","properties":{"codesPostaux":["62220"],"population":16873,"nom":"Carvin","code":"62215"},"geometry":{"type":"Point","coordinates":[2.949427984496124,50.49205255813954]}}]}