{"type":"FeatureCollection","features":[{"type":"Feature","properties":{"codesPostaux":["62500"],"population":633,"nom":"Clairmarais","code":"62225"},"geometry":{"type":"Point","coordinates":[2.3444507971014485,50.76710471014491]}}]}