{"type":"FeatureCollection","features":[{"type":"Feature","properties":{"codesPostaux":["62180"],"population":133,"nom":"Colline-Beaumont","code":"62231"},"geometry":{"type":"Point","coordinates":[1.6761132911392398,50.340549367088585]}}]}