{"type":"FeatureCollection","features":[{"type":"Feature","properties":{"codesPostaux":["62126"],"population":486,"nom":"Conteville-l\u00e8s-Boulogne","code":"62237"},"geometry":{"type":"Point","coordinates":[1.731860789473685,50.74348236842106]}}]}