{"type":"FeatureCollection","features":[{"type":"Feature","properties":{"codesPostaux":["62136"],"population":2734,"nom":"La Couture","code":"62252"},"geometry":{"type":"Point","coordinates":[2.7002573376623364,50.579214740259765]}}]}