{"type":"FeatureCollection","features":[{"type":"Feature","properties":{"codesPostaux":["62560"],"population":374,"nom":"Dennebr\u0153ucq","code":"62267"},"geometry":{"type":"Point","coordinates":[2.1560312195121956,50.5811482113821]}}]}