{"type":"FeatureCollection","features":[{"type":"Feature","properties":{"codesPostaux":["62780"],"population":5128,"nom":"Cucq","code":"62261"},"geometry":{"type":"Point","coordinates":[1.62623568,50.491869279999996]}}]}