{"type":"FeatureCollection","features":[{"type":"Feature","properties":{"codesPostaux":["62830"],"population":519,"nom":"Doudeauville","code":"62273"},"geometry":{"type":"Point","coordinates":[1.8314523595505623,50.62233876404496]}}]}