{"type":"FeatureCollection","features":[{"type":"Feature","properties":{"codesPostaux":["62145"],"population":950,"nom":"Estr\u00e9e-Blanche","code":"62313"},"geometry":{"type":"Point","coordinates":[2.3227433333333343,50.590921666666674]}}]}