{"type":"FeatureCollection","features":[{"type":"Feature","properties":{"codesPostaux":["62156"],"population":250,"nom":"\u00c9terpigny","code":"62319"},"geometry":{"type":"Point","coordinates":[2.9803675000000003,50.256607794117656]}}]}