{"type":"FeatureCollection","features":[{"type":"Feature","properties":{"codesPostaux":["62400"],"population":1598,"nom":"Essars","code":"62310"},"geometry":{"type":"Point","coordinates":[2.6604997872340426,50.549860425531925]}}]}