{"type":"FeatureCollection","features":[{"type":"Feature","properties":{"codesPostaux":["62141"],"population":4583,"nom":"\u00c9vin-Malmaison","code":"62321"},"geometry":{"type":"Point","coordinates":[3.0335678125000007,50.43543015624999]}}]}