{"type":"FeatureCollection","features":[{"type":"Feature","properties":{"codesPostaux":["62960"],"population":574,"nom":"Febvin-Palfart","code":"62327"},"geometry":{"type":"Point","coordinates":[2.306001276595744,50.53791414893618]}}]}