{"type":"FeatureCollection","features":[{"type":"Feature","properties":{"codesPostaux":["62270"],"population":215,"nom":"Flers","code":"62337"},"geometry":{"type":"Point","coordinates":[2.2512837142857145,50.31858757142857]}}]}