{"type":"FeatureCollection","features":[{"type":"Feature","properties":{"codesPostaux":["62132"],"population":895,"nom":"Fiennes","code":"62334"},"geometry":{"type":"Point","coordinates":[1.8265540909090912,50.82169378787881]}}]}