{"type":"FeatureCollection","features":[{"type":"Feature","properties":{"codesPostaux":["62128"],"population":281,"nom":"Fontaine-l\u00e8s-Croisilles","code":"62343"},"geometry":{"type":"Point","coordinates":[2.9082698,50.21586720000002]}}]}