{"type":"FeatureCollection","features":[{"type":"Feature","properties":{"codesPostaux":["62810"],"population":142,"nom":"Fosseux","code":"62347"},"geometry":{"type":"Point","coordinates":[2.564150266666666,50.256862666666684]}}]}