{"type":"FeatureCollection","features":[{"type":"Feature","properties":{"codesPostaux":["62630"],"population":803,"nom":"Frencq","code":"62354"},"geometry":{"type":"Point","coordinates":[1.6926964189189189,50.56476871621623]}}]}