{"type":"FeatureCollection","features":[{"type":"Feature","properties":{"codesPostaux":["62232"],"population":1069,"nom":"Fouqui\u00e8res-l\u00e8s-B\u00e9thune","code":"62350"},"geometry":{"type":"Point","coordinates":[2.6143684615384615,50.51310974358974]}}]}