{"type":"FeatureCollection","features":[{"type":"Feature","properties":{"codesPostaux":["62130"],"population":19,"nom":"Guinecourt","code":"62396"},"geometry":{"type":"Point","coordinates":[2.22950275,50.349464999999995]}}]}