{"type":"FeatureCollection","features":[{"type":"Feature","properties":{"codesPostaux":["62118"],"population":495,"nom":"Hamblain-les-Pr\u00e9s","code":"62405"},"geometry":{"type":"Point","coordinates":[2.955555230769231,50.28935353846155]}}]}