{"type":"FeatureCollection","features":[{"type":"Feature","properties":{"codesPostaux":["62124"],"population":185,"nom":"Haplincourt","code":"62410"},"geometry":{"type":"Point","coordinates":[2.940689242424242,50.092565757575734]}}]}