{"type":"FeatureCollection","features":[{"type":"Feature","properties":{"codesPostaux":["62690"],"population":533,"nom":"Hermaville","code":"62438"},"geometry":{"type":"Point","coordinates":[2.589302428571429,50.32601457142859]}}]}