{"type":"FeatureCollection","features":[{"type":"Feature","properties":{"codesPostaux":["62990"],"population":179,"nom":"Hesmond","code":"62449"},"geometry":{"type":"Point","coordinates":[1.9454119867549657,50.465412251655636]}}]}