{"type":"FeatureCollection","features":[{"type":"Feature","properties":{"codesPostaux":["62310"],"population":115,"nom":"H\u00e9zecques","code":"62453"},"geometry":{"type":"Point","coordinates":[2.1857933333333324,50.53315569444443]}}]}