{"type":"FeatureCollection","features":[{"type":"Feature","properties":{"codesPostaux":["62130"],"population":125,"nom":"Huclier","code":"62462"},"geometry":{"type":"Point","coordinates":[2.356039545454546,50.43788113636362]}}]}