{"type":"FeatureCollection","features":[{"type":"Feature","properties":{"codesPostaux":["62158"],"population":224,"nom":"Humbercamps","code":"62465"},"geometry":{"type":"Point","coordinates":[2.5783892,50.188092399999995]}}]}