{"type":"FeatureCollection","features":[{"type":"Feature","properties":{"codesPostaux":["62410"],"population":3167,"nom":"Hulluch","code":"62464"},"geometry":{"type":"Point","coordinates":[2.8134127999999987,50.48745493333333]}}]}