{"type":"FeatureCollection","features":[{"type":"Feature","properties":{"codesPostaux":["62630"],"population":250,"nom":"Hubersent","code":"62460"},"geometry":{"type":"Point","coordinates":[1.7449455882352947,50.58147980392156]}}]}