{"type":"FeatureCollection","features":[{"type":"Feature","properties":{"codesPostaux":["62140"],"population":934,"nom":"Huby-Saint-Leu","code":"62461"},"geometry":{"type":"Point","coordinates":[2.0185629230769244,50.39500876923075]}}]}