{"type":"FeatureCollection","features":[{"type":"Feature","properties":{"codesPostaux":["62490"],"population":930,"nom":"Izel-l\u00e8s-\u00c9querchin","code":"62476"},"geometry":{"type":"Point","coordinates":[2.943948723404256,50.36367829787234]}}]}