{"type":"FeatureCollection","features":[{"type":"Feature","properties":{"codesPostaux":["62159"],"population":353,"nom":"Lagnicourt-Marcel","code":"62484"},"geometry":{"type":"Point","coordinates":[2.9590061320754706,50.1552716981132]}}]}