{"type":"FeatureCollection","features":[{"type":"Feature","properties":{"codesPostaux":["62113"],"population":2549,"nom":"Labourse","code":"62480"},"geometry":{"type":"Point","coordinates":[2.6827005714285703,50.491372285714284]}}]}