{"type":"FeatureCollection","features":[{"type":"Feature","properties":{"codesPostaux":["62960"],"population":369,"nom":"Laires","code":"62485"},"geometry":{"type":"Point","coordinates":[2.2571672727272722,50.5418130681818]}}]}