{"type":"FeatureCollection","features":[{"type":"Feature","properties":{"codesPostaux":["62124"],"population":61,"nom":"L\u00e9chelle","code":"62494"},"geometry":{"type":"Point","coordinates":[2.9774762295081967,50.054971803278676]}}]}