{"type":"FeatureCollection","features":[{"type":"Feature","properties":{"codesPostaux":["62810"],"population":146,"nom":"Lignereuil","code":"62511"},"geometry":{"type":"Point","coordinates":[2.471646829268292,50.29071268292684]}}]}