{"type":"FeatureCollection","features":[{"type":"Feature","properties":{"codesPostaux":["62120"],"population":214,"nom":"Linghem","code":"62517"},"geometry":{"type":"Point","coordinates":[2.3737796428571425,50.59281714285715]}}]}