{"type":"FeatureCollection","features":[{"type":"Feature","properties":{"codesPostaux":["62750"],"population":6581,"nom":"Loos-en-Gohelle","code":"62528"},"geometry":{"type":"Point","coordinates":[2.78218705128205,50.452618461538464]}}]}