{"type":"FeatureCollection","features":[{"type":"Feature","properties":{"codesPostaux":["62630"],"population":259,"nom":"Longvilliers","code":"62527"},"geometry":{"type":"Point","coordinates":[1.741138706896551,50.53346905172412]}}]}