{"type":"FeatureCollection","features":[{"type":"Feature","properties":{"codesPostaux":["62170"],"population":170,"nom":"La Madelaine-sous-Montreuil","code":"62535"},"geometry":{"type":"Point","coordinates":[1.7472125333333335,50.46779946666668]}}]}