{"type":"FeatureCollection","features":[{"type":"Feature","properties":{"codesPostaux":["62127"],"population":619,"nom":"Magnicourt-en-Comte","code":"62536"},"geometry":{"type":"Point","coordinates":[2.481385434782609,50.405025978260845]}}]}