{"type":"FeatureCollection","features":[{"type":"Feature","properties":{"codesPostaux":["62240"],"population":553,"nom":"Lottinghen","code":"62530"},"geometry":{"type":"Point","coordinates":[1.9351556687898084,50.6791092356688]}}]}