{"type":"FeatureCollection","features":[{"type":"Feature","properties":{"codesPostaux":["62120"],"population":1975,"nom":"Mametz","code":"62543"},"geometry":{"type":"Point","coordinates":[2.306472585034014,50.63307714285715]}}]}