{"type":"FeatureCollection","features":[{"type":"Feature","properties":{"codesPostaux":["62250"],"population":350,"nom":"Maninghen-Henne","code":"62546"},"geometry":{"type":"Point","coordinates":[1.6719966249999996,50.76963362500001]}}]}