{"type":"FeatureCollection","features":[{"type":"Feature","properties":{"codesPostaux":["62161"],"population":2467,"nom":"Mar\u0153uil","code":"62557"},"geometry":{"type":"Point","coordinates":[2.7095409523809533,50.33199028571428]}}]}