{"type":"FeatureCollection","features":[{"type":"Feature","properties":{"codesPostaux":["62217"],"population":620,"nom":"Mercatel","code":"62568"},"geometry":{"type":"Point","coordinates":[2.7837859649122803,50.23346543859652]}}]}