{"type":"FeatureCollection","features":[{"type":"Feature","properties":{"codesPostaux":["62890"],"population":630,"nom":"Mentque-Nortb\u00e9court","code":"62567"},"geometry":{"type":"Point","coordinates":[2.0914233333333336,50.77176788617887]}}]}