{"type":"FeatureCollection","features":[{"type":"Feature","properties":{"codesPostaux":["62760"],"population":624,"nom":"Mondicourt","code":"62583"},"geometry":{"type":"Point","coordinates":[2.467735131578947,50.17221710526316]}}]}