{"type":"FeatureCollection","features":[{"type":"Feature","properties":{"codesPostaux":["62840"],"population":1304,"nom":"Neuve-Chapelle","code":"62606"},"geometry":{"type":"Point","coordinates":[2.780741875,50.587388125]}}]}