{"type":"FeatureCollection","features":[{"type":"Feature","properties":{"codesPostaux":["62580"],"population":383,"nom":"Oppy","code":"62639"},"geometry":{"type":"Point","coordinates":[2.887040196078433,50.349209607843136]}}]}