{"type":"FeatureCollection","features":[{"type":"Feature","properties":{"codesPostaux":["62810"],"population":276,"nom":"Noyelle-Vion","code":"62630"},"geometry":{"type":"Point","coordinates":[2.5489101282051294,50.292199358974365]}}]}