{"type":"FeatureCollection","features":[{"type":"Feature","properties":{"codesPostaux":["62370"],"population":1147,"nom":"Offekerque","code":"62634"},"geometry":{"type":"Point","coordinates":[2.018100326086956,50.936079782608715]}}]}