{"type":"FeatureCollection","features":[{"type":"Feature","properties":{"codesPostaux":["62880"],"population":3157,"nom":"Pont-\u00e0-Vendin","code":"62666"},"geometry":{"type":"Point","coordinates":[2.8866784313725495,50.47583176470587]}}]}