{"type":"FeatureCollection","features":[{"type":"Feature","properties":{"codesPostaux":["62118"],"population":454,"nom":"Plouvain","code":"62660"},"geometry":{"type":"Point","coordinates":[2.9182700000000006,50.3037875]}}]}