{"type":"FeatureCollection","features":[{"type":"Feature","properties":{"codesPostaux":["62240"],"population":617,"nom":"Quesques","code":"62678"},"geometry":{"type":"Point","coordinates":[1.9413478531073454,50.70236384180788]}}]}