{"type":"FeatureCollection","features":[{"type":"Feature","properties":{"codesPostaux":["62650"],"population":588,"nom":"Preures","code":"62670"},"geometry":{"type":"Point","coordinates":[1.8851790322580648,50.570310107526886]}}]}