{"type":"FeatureCollection","features":[{"type":"Feature","properties":{"codesPostaux":["62390"],"population":248,"nom":"Qu\u0153ux-Haut-Ma\u00eenil","code":"62683"},"geometry":{"type":"Point","coordinates":[2.1051279381443293,50.30115835051546]}}]}