{"type":"FeatureCollection","features":[{"type":"Feature","properties":{"codesPostaux":["62650"],"population":59,"nom":"Quilen","code":"62682"},"geometry":{"type":"Point","coordinates":[1.9336814754098364,50.52938475409836]}}]}