{"type":"FeatureCollection","features":[{"type":"Feature","properties":{"codesPostaux":["62170"],"population":283,"nom":"Recques-sur-Course","code":"62698"},"geometry":{"type":"Point","coordinates":[1.7810467105263164,50.5219452631579]}}]}