{"type":"FeatureCollection","features":[{"type":"Feature","properties":{"codesPostaux":["62140"],"population":214,"nom":"Regnauville","code":"62700"},"geometry":{"type":"Point","coordinates":[1.9997894339622644,50.31717566037736]}}]}