{"type":"FeatureCollection","features":[{"type":"Feature","properties":{"codesPostaux":["62720"],"population":2071,"nom":"Rety","code":"62705"},"geometry":{"type":"Point","coordinates":[1.7888996428571442,50.791438010204054]}}]}