{"type":"FeatureCollection","features":[{"type":"Feature","properties":{"codesPostaux":["62770"],"population":318,"nom":"Rollancourt","code":"62719"},"geometry":{"type":"Point","coordinates":[2.1272354950495043,50.41454886138611]}}]}