{"type":"FeatureCollection","features":[{"type":"Feature","properties":{"codesPostaux":["62610"],"population":565,"nom":"Rodelinghem","code":"62716"},"geometry":{"type":"Point","coordinates":[1.9306453225806446,50.832787258064506]}}]}