{"type":"FeatureCollection","features":[{"type":"Feature","properties":{"codesPostaux":["62390"],"population":88,"nom":"Rougefay","code":"62722"},"geometry":{"type":"Point","coordinates":[2.169387307692308,50.27570557692309]}}]}