{"type":"FeatureCollection","features":[{"type":"Feature","properties":{"codesPostaux":["62120"],"population":1910,"nom":"Roquetoire","code":"62721"},"geometry":{"type":"Point","coordinates":[2.3465371304347835,50.66994573913043]}}]}