{"type":"FeatureCollection","features":[{"type":"Feature","properties":{"codesPostaux":["62223"],"population":6637,"nom":"Saint-Laurent-Blangy","code":"62753"},"geometry":{"type":"Point","coordinates":[2.8079075781249996,50.306786953124984]}}]}