{"type":"FeatureCollection","features":[{"type":"Feature","properties":{"codesPostaux":["62830"],"population":3983,"nom":"Samer","code":"62773"},"geometry":{"type":"Point","coordinates":[1.746308603603604,50.63445774774775]}}]}