{"type":"FeatureCollection","features":[{"type":"Feature","properties":{"codesPostaux":["62450"],"population":171,"nom":"Le Sars","code":"62777"},"geometry":{"type":"Point","coordinates":[2.7775206779661015,50.07027135593219]}}]}