{"type":"FeatureCollection","features":[{"type":"Feature","properties":{"codesPostaux":["62270"],"population":54,"nom":"S\u00e9ricourt","code":"62791"},"geometry":{"type":"Point","coordinates":[2.3116797142857144,50.295525999999995]}}]}