{"type":"FeatureCollection","features":[{"type":"Feature","properties":{"codesPostaux":["62810"],"population":173,"nom":"Le Souich","code":"62802"},"geometry":{"type":"Point","coordinates":[2.363354285714286,50.22159634920633]}}]}