{"type":"FeatureCollection","features":[{"type":"Feature","properties":{"codesPostaux":["62580"],"population":1217,"nom":"Th\u00e9lus","code":"62810"},"geometry":{"type":"Point","coordinates":[2.799582299999999,50.350353799999986]}}]}