{"type":"FeatureCollection","features":[{"type":"Feature","properties":{"codesPostaux":["62690"],"population":226,"nom":"Tilloy-l\u00e8s-Hermaville","code":"62816"},"geometry":{"type":"Point","coordinates":[2.552721,50.329366500000006]}}]}