{"type":"FeatureCollection","features":[{"type":"Feature","properties":{"codesPostaux":["62129"],"population":1120,"nom":"Th\u00e9rouanne","code":"62811"},"geometry":{"type":"Point","coordinates":[2.249988545454545,50.631556909090904]}}]}