{"type":"FeatureCollection","features":[{"type":"Feature","properties":{"codesPostaux":["62450"],"population":406,"nom":"Le Transloy","code":"62829"},"geometry":{"type":"Point","coordinates":[2.8860562068965514,50.05031]}}]}