{"type":"FeatureCollection","features":[{"type":"Feature","properties":{"codesPostaux":["62630"],"population":494,"nom":"Tubersent","code":"62832"},"geometry":{"type":"Point","coordinates":[1.6982014516129034,50.52059016129031]}}]}