{"type":"FeatureCollection","features":[{"type":"Feature","properties":{"codesPostaux":["62240"],"population":392,"nom":"Vieil-Moutier","code":"62853"},"geometry":{"type":"Point","coordinates":[1.9097248437500005,50.668075937500014]}}]}