{"type":"FeatureCollection","features":[{"type":"Feature","properties":{"codesPostaux":["62127"],"population":122,"nom":"Villers-Sir-Simon","code":"62860"},"geometry":{"type":"Point","coordinates":[2.491265882352941,50.31614941176472]}}]}