{"type":"FeatureCollection","features":[{"type":"Feature","properties":{"codesPostaux":["62120"],"population":1306,"nom":"Wardrecques","code":"62875"},"geometry":{"type":"Point","coordinates":[2.341237169811321,50.70405716981132]}}]}