{"type":"FeatureCollection","features":[{"type":"Feature","properties":{"codesPostaux":["62650"],"population":239,"nom":"Wicquinghem","code":"62886"},"geometry":{"type":"Point","coordinates":[1.9542653124999996,50.57360406249999]}}]}