{"type":"FeatureCollection","features":[{"type":"Feature","properties":{"codesPostaux":["62890"],"population":627,"nom":"Zouafques","code":"62904"},"geometry":{"type":"Point","coordinates":[2.05630231884058,50.821436231884064]}}]}