{"type":"FeatureCollection","features":[{"type":"Feature","properties":{"codesPostaux":["62124"],"population":437,"nom":"Ytres","code":"62909"},"geometry":{"type":"Point","coordinates":[2.9946327058823528,50.065814941176484]}}]}