{"type":"FeatureCollection","features":[{"type":"Feature","properties":{"codesPostaux":["62570"],"population":3337,"nom":"Wizernes","code":"62902"},"geometry":{"type":"Point","coordinates":[2.2269666666666668,50.71576361904763]}}]}