{"type":"FeatureCollection","features":[{"type":"Feature","properties":{"codesPostaux":["62500"],"population":848,"nom":"Zudausques","code":"62905"},"geometry":{"type":"Point","coordinates":[2.159439411764706,50.752461058823535]}}]}