{"type":"FeatureCollection","features":[{"type":"Feature","properties":{"codesPostaux":["62650"],"population":591,"nom":"Zoteux","code":"62903"},"geometry":{"type":"Point","coordinates":[1.887902394366198,50.61626366197185]}}]}