{"type":"FeatureCollection","features":[{"type":"Feature","properties":{"codesPostaux":["63700"],"population":231,"nom":"Ars-les-Favets","code":"63011"},"geometry":{"type":"Point","coordinates":[2.747975114503818,46.199776641221376]}}]}