{"type":"FeatureCollection","features":[{"type":"Feature","properties":{"codesPostaux":["63340"],"population":1048,"nom":"Le Breuil-sur-Couze","code":"63052"},"geometry":{"type":"Point","coordinates":[3.266388700000001,45.46852649999999]}}]}