{"type":"FeatureCollection","features":[{"type":"Feature","properties":{"codesPostaux":["63670"],"population":4975,"nom":"Le Cendre","code":"63069"},"geometry":{"type":"Point","coordinates":[3.1962303529411757,45.717423176470575]}}]}