{"type":"FeatureCollection","features":[{"type":"Feature","properties":{"codesPostaux":["63580"],"population":151,"nom":"Cham\u00e9ane","code":"63078"},"geometry":{"type":"Point","coordinates":[3.4366218518518505,45.52216274074074]}}]}