{"type":"FeatureCollection","features":[{"type":"Feature","properties":{"codesPostaux":["63590"],"population":380,"nom":"La Chapelle-Agnon","code":"63086"},"geometry":{"type":"Point","coordinates":[3.632631720930232,45.62991897674417]}}]}