{"type":"FeatureCollection","features":[{"type":"Feature","properties":{"codesPostaux":["63580"],"population":66,"nom":"La Chapelle-sur-Usson","code":"63088"},"geometry":{"type":"Point","coordinates":[3.389826956521741,45.464601652173926]}}]}