{"type":"FeatureCollection","features":[{"type":"Feature","properties":{"codesPostaux":["63290"],"population":207,"nom":"Charnat","code":"63095"},"geometry":{"type":"Point","coordinates":[3.4354612121212127,45.94393868686869]}}]}