{"type":"FeatureCollection","features":[{"type":"Feature","properties":{"codesPostaux":["63320"],"population":74,"nom":"Courgoul","code":"63122"},"geometry":{"type":"Point","coordinates":[3.0411166049382703,45.51004728395063]}}]}