{"type":"FeatureCollection","features":[{"type":"Feature","properties":{"codesPostaux":["63220"],"population":627,"nom":"Dore-l'\u00c9glise","code":"63139"},"geometry":{"type":"Point","coordinates":[3.753838258426965,45.37539887640448]}}]}