{"type":"FeatureCollection","features":[{"type":"Feature","properties":{"codesPostaux":["63111"],"population":1452,"nom":"Dallet","code":"63133"},"geometry":{"type":"Point","coordinates":[3.242825789473683,45.77160868421054]}}]}