{"type":"FeatureCollection","features":[{"type":"Feature","properties":{"codesPostaux":["63720"],"population":2440,"nom":"Ennezat","code":"63148"},"geometry":{"type":"Point","coordinates":[3.2171365555555567,45.896438]}}]}