{"type":"FeatureCollection","features":[{"type":"Feature","properties":{"codesPostaux":["63300"],"population":1345,"nom":"Escoutoux","code":"63151"},"geometry":{"type":"Point","coordinates":[3.5589417672413792,45.813693060344825]}}]}