{"type":"FeatureCollection","features":[{"type":"Feature","properties":{"codesPostaux":["63390"],"population":357,"nom":"Goutti\u00e8res","code":"63171"},"geometry":{"type":"Point","coordinates":[2.7781030627306276,46.05876612546124]}}]}