{"type":"FeatureCollection","features":[{"type":"Feature","properties":{"codesPostaux":["63350"],"population":1080,"nom":"Joze","code":"63180"},"geometry":{"type":"Point","coordinates":[3.3119204716981128,45.8694733018868]}}]}