{"type":"FeatureCollection","features":[{"type":"Feature","properties":{"codesPostaux":["63290"],"population":298,"nom":"Lachaux","code":"63184"},"geometry":{"type":"Point","coordinates":[3.5915782258064533,45.99563818548385]}}]}