{"type":"FeatureCollection","features":[{"type":"Feature","properties":{"codesPostaux":["63320"],"population":485,"nom":"Ludesse","code":"63199"},"geometry":{"type":"Point","coordinates":[3.099445428571429,45.613658285714294]}}]}