{"type":"FeatureCollection","features":[{"type":"Feature","properties":{"codesPostaux":["63340"],"population":182,"nom":"Mareugheol","code":"63209"},"geometry":{"type":"Point","coordinates":[3.163915806451613,45.48297827956991]}}]}