{"type":"FeatureCollection","features":[{"type":"Feature","properties":{"codesPostaux":["63560"],"population":575,"nom":"Menat","code":"63223"},"geometry":{"type":"Point","coordinates":[2.896134366812226,46.107163886462885]}}]}