{"type":"FeatureCollection","features":[{"type":"Feature","properties":{"codesPostaux":["63700"],"population":1022,"nom":"Montaigut","code":"63233"},"geometry":{"type":"Point","coordinates":[2.7998999152542376,46.17972703389832]}}]}