{"type":"FeatureCollection","features":[{"type":"Feature","properties":{"codesPostaux":["63880"],"population":725,"nom":"Olliergues","code":"63258"},"geometry":{"type":"Point","coordinates":[3.6312420710059183,45.68982834319529]}}]}