{"type":"FeatureCollection","features":[{"type":"Feature","properties":{"codesPostaux":["63830"],"population":2082,"nom":"Nohanent","code":"63254"},"geometry":{"type":"Point","coordinates":[3.056501724137932,45.81186172413793]}}]}