{"type":"FeatureCollection","features":[{"type":"Feature","properties":{"codesPostaux":["63880"],"population":153,"nom":"Olmet","code":"63260"},"geometry":{"type":"Point","coordinates":[3.662065999999997,45.71629419047621]}}]}