{"type":"FeatureCollection","features":[{"type":"Feature","properties":{"codesPostaux":["63290"],"population":1567,"nom":"Pasli\u00e8res","code":"63271"},"geometry":{"type":"Point","coordinates":[3.501756363636362,45.922202972027954]}}]}