{"type":"FeatureCollection","features":[{"type":"Feature","properties":{"codesPostaux":["63500"],"population":490,"nom":"Parentignat","code":"63270"},"geometry":{"type":"Point","coordinates":[3.287584625,45.531229624999995]}}]}