{"type":"FeatureCollection","features":[{"type":"Feature","properties":{"codesPostaux":["63380"],"population":714,"nom":"Pontaumur","code":"63283"},"geometry":{"type":"Point","coordinates":[2.6746648584905666,45.86171561320755]}}]}