{"type":"FeatureCollection","features":[{"type":"Feature","properties":{"codesPostaux":["63420"],"population":47,"nom":"Roche-Charles-la-Mayrand","code":"63303"},"geometry":{"type":"Point","coordinates":[3.023651832460732,45.451355497382195]}}]}