{"type":"FeatureCollection","features":[{"type":"Feature","properties":{"codesPostaux":["63630"],"population":215,"nom":"Saint-Bonnet-le-Chastel","code":"63324"},"geometry":{"type":"Point","coordinates":[3.6390666051660494,45.458259188191896]}}]}