{"type":"FeatureCollection","features":[{"type":"Feature","properties":{"codesPostaux":["63320"],"population":398,"nom":"Saint-Di\u00e9ry","code":"63335"},"geometry":{"type":"Point","coordinates":[3.0023732452830183,45.541267622641485]}}]}