{"type":"FeatureCollection","features":[{"type":"Feature","properties":{"codesPostaux":["63700"],"population":3652,"nom":"Saint-\u00c9loy-les-Mines","code":"63338"},"geometry":{"type":"Point","coordinates":[2.8448877889447233,46.16656819095477]}}]}