{"type":"FeatureCollection","features":[{"type":"Feature","properties":{"codesPostaux":["63440"],"population":131,"nom":"Saint-Gal-sur-Sioule","code":"63344"},"geometry":{"type":"Point","coordinates":[2.995291607142858,46.10655464285712]}}]}