{"type":"FeatureCollection","features":[{"type":"Feature","properties":{"codesPostaux":["63520"],"population":270,"nom":"Saint-Flour","code":"63343"},"geometry":{"type":"Point","coordinates":[3.509377741935482,45.708493741935506]}}]}