{"type":"FeatureCollection","features":[{"type":"Feature","properties":{"codesPostaux":["63380"],"population":101,"nom":"Saint-Hilaire-les-Monges","code":"63359"},"geometry":{"type":"Point","coordinates":[2.6640665771812064,45.80812523489933]}}]}