{"type":"FeatureCollection","features":[{"type":"Feature","properties":{"codesPostaux":["63340"],"population":99,"nom":"Saint-H\u00e9rent","code":"63357"},"geometry":{"type":"Point","coordinates":[3.137303084112152,45.462275560747656]}}]}