{"type":"FeatureCollection","features":[{"type":"Feature","properties":{"codesPostaux":["63270"],"population":818,"nom":"Saint-Maurice","code":"63378"},"geometry":{"type":"Point","coordinates":[3.2404960747663547,45.66946242990656]}}]}