{"type":"FeatureCollection","features":[{"type":"Feature","properties":{"codesPostaux":["63480"],"population":127,"nom":"Saint-Pierre-la-Bourlhonne","code":"63384"},"geometry":{"type":"Point","coordinates":[3.741185396825398,45.67785833333333]}}]}