{"type":"FeatureCollection","features":[{"type":"Feature","properties":{"codesPostaux":["63950"],"population":1124,"nom":"Saint-Sauves-d'Auvergne","code":"63397"},"geometry":{"type":"Point","coordinates":[2.701119029649595,45.61465592991918]}}]}