{"type":"FeatureCollection","features":[{"type":"Feature","properties":{"codesPostaux":["63220"],"population":105,"nom":"Saint-Sauveur-la-Sagne","code":"63398"},"geometry":{"type":"Point","coordinates":[3.666148786127167,45.39296919075144]}}]}