{"type":"FeatureCollection","features":[{"type":"Feature","properties":{"codesPostaux":["63560"],"population":528,"nom":"Servant","code":"63419"},"geometry":{"type":"Point","coordinates":[2.9312219545454545,46.13952450000002]}}]}