{"type":"FeatureCollection","features":[{"type":"Feature","properties":{"codesPostaux":["63730"],"population":685,"nom":"La Sauvetat","code":"63413"},"geometry":{"type":"Point","coordinates":[3.1679659420289847,45.644031594202886]}}]}