{"type":"FeatureCollection","features":[{"type":"Feature","properties":{"codesPostaux":["63690"],"population":167,"nom":"Singles","code":"63421"},"geometry":{"type":"Point","coordinates":[2.553912445652173,45.56143945652173]}}]}