{"type":"FeatureCollection","features":[{"type":"Feature","properties":{"codesPostaux":["63340"],"population":43,"nom":"Ternant-les-Eaux","code":"63429"},"geometry":{"type":"Point","coordinates":[3.126206347826085,45.47971565217393]}}]}