{"type":"FeatureCollection","features":[{"type":"Feature","properties":{"codesPostaux":["63600"],"population":170,"nom":"Thioli\u00e8res","code":"63431"},"geometry":{"type":"Point","coordinates":[3.696039722222222,45.580595000000024]}}]}