{"type":"FeatureCollection","features":[{"type":"Feature","properties":{"codesPostaux":["63600"],"population":209,"nom":"Valcivi\u00e8res","code":"63441"},"geometry":{"type":"Point","coordinates":[3.817531079136691,45.59592388489208]}}]}