{"type":"FeatureCollection","features":[{"type":"Feature","properties":{"codesPostaux":["63340"],"population":163,"nom":"Villeneuve","code":"63458"},"geometry":{"type":"Point","coordinates":[3.1860510000000004,45.47564816666668]}}]}