{"type":"FeatureCollection","features":[{"type":"Feature","properties":{"codesPostaux":["63310"],"population":534,"nom":"Villeneuve-les-Cerfs","code":"63459"},"geometry":{"type":"Point","coordinates":[3.3308430769230792,46.02083340659342]}}]}