{"type":"FeatureCollection","features":[{"type":"Feature","properties":{"codesPostaux":["63350"],"population":343,"nom":"Vinzelles","code":"63461"},"geometry":{"type":"Point","coordinates":[3.422942037037037,45.927682962962955]}}]}