{"type":"FeatureCollection","features":[{"type":"Feature","properties":{"codesPostaux":["63530"],"population":4425,"nom":"Volvic","code":"63470"},"geometry":{"type":"Point","coordinates":[3.0220227108433724,45.86510584337352]}}]}