{"type":"FeatureCollection","features":[{"type":"Feature","properties":{"codesPostaux":["64400"],"population":929,"nom":"Agnos","code":"64007"},"geometry":{"type":"Point","coordinates":[-0.626986559139785,43.1533764516129]}}]}