{"type":"FeatureCollection","features":[{"type":"Feature","properties":{"codesPostaux":["64430"],"population":321,"nom":"Aldudes","code":"64016"},"geometry":{"type":"Point","coordinates":[-1.4225880620155043,43.09827147286824]}}]}