{"type":"FeatureCollection","features":[{"type":"Feature","properties":{"codesPostaux":["64120"],"population":435,"nom":"Amendeuix-Oneix","code":"64018"},"geometry":{"type":"Point","coordinates":[-1.046080967741935,43.344597161290324]}}]}