{"type":"FeatureCollection","features":[{"type":"Feature","properties":{"codesPostaux":["64220"],"population":161,"nom":"Ainhice-Mongelos","code":"64013"},"geometry":{"type":"Point","coordinates":[-1.1624953987730062,43.20851601226992]}}]}