{"type":"FeatureCollection","features":[{"type":"Feature","properties":{"codesPostaux":["64350"],"population":154,"nom":"Anoye","code":"64028"},"geometry":{"type":"Point","coordinates":[-0.1321645535714286,43.39758883928569]}}]}