{"type":"FeatureCollection","features":[{"type":"Feature","properties":{"codesPostaux":["64190"],"population":211,"nom":"Araujuzon","code":"64032"},"geometry":{"type":"Point","coordinates":[-0.8312599999999999,43.34823779141104]}}]}