{"type":"FeatureCollection","features":[{"type":"Feature","properties":{"codesPostaux":["64220"],"population":230,"nom":"Arn\u00e9guy","code":"64047"},"geometry":{"type":"Point","coordinates":[-1.2763213452914797,43.08224654708522]}}]}