{"type":"FeatureCollection","features":[{"type":"Feature","properties":{"codesPostaux":["64130"],"population":96,"nom":"Arrast-Larrebieu","code":"64050"},"geometry":{"type":"Point","coordinates":[-0.853762086330935,43.28243294964026]}}]}