{"type":"FeatureCollection","features":[{"type":"Feature","properties":{"codesPostaux":["64510"],"population":1799,"nom":"Assat","code":"64067"},"geometry":{"type":"Point","coordinates":[-0.2844062184873947,43.25870848739497]}}]}