{"type":"FeatureCollection","features":[{"type":"Feature","properties":{"codesPostaux":["64130"],"population":673,"nom":"Barcus","code":"64093"},"geometry":{"type":"Point","coordinates":[-0.779476443768997,43.183950212765986]}}]}