{"type":"FeatureCollection","features":[{"type":"Feature","properties":{"codesPostaux":["64530"],"population":597,"nom":"Barzun","code":"64097"},"geometry":{"type":"Point","coordinates":[-0.1399328409090909,43.2156111363636]}}]}