{"type":"FeatureCollection","features":[{"type":"Feature","properties":{"codesPostaux":["64270"],"population":897,"nom":"Bellocq","code":"64108"},"geometry":{"type":"Point","coordinates":[-0.9174157615894043,43.51013920529804]}}]}