{"type":"FeatureCollection","features":[{"type":"Feature","properties":{"codesPostaux":["64220"],"population":75,"nom":"B\u00e9horl\u00e9guy","code":"64107"},"geometry":{"type":"Point","coordinates":[-1.1020084615384622,43.120835692307686]}}]}