{"type":"FeatureCollection","features":[{"type":"Feature","properties":{"codesPostaux":["64140"],"population":13479,"nom":"Bill\u00e8re","code":"64129"},"geometry":{"type":"Point","coordinates":[-0.39707315789473696,43.30406915789473]}}]}