{"type":"FeatureCollection","features":[{"type":"Feature","properties":{"codesPostaux":["64120"],"population":153,"nom":"Bunus","code":"64150"},"geometry":{"type":"Point","coordinates":[-1.06306225,43.20408491666669]}}]}