{"type":"FeatureCollection","features":[{"type":"Feature","properties":{"codesPostaux":["64250"],"population":6672,"nom":"Cambo-les-Bains","code":"64160"},"geometry":{"type":"Point","coordinates":[-1.3899286956521737,43.36736396739129]}}]}