{"type":"FeatureCollection","features":[{"type":"Feature","properties":{"codesPostaux":["64520"],"population":879,"nom":"Came","code":"64161"},"geometry":{"type":"Point","coordinates":[-1.0875724567474052,43.485046885813134]}}]}