{"type":"FeatureCollection","features":[{"type":"Feature","properties":{"codesPostaux":["64300"],"population":604,"nom":"Cast\u00e9tis","code":"64177"},"geometry":{"type":"Point","coordinates":[-0.7147933636363638,43.47678727272726]}}]}