{"type":"FeatureCollection","features":[{"type":"Feature","properties":{"codesPostaux":["64490"],"population":75,"nom":"Cette-Eygun","code":"64185"},"geometry":{"type":"Point","coordinates":[-0.5550564566929134,42.935351417322806]}}]}