{"type":"FeatureCollection","features":[{"type":"Feature","properties":{"codesPostaux":["64190"],"population":201,"nom":"Charre","code":"64186"},"geometry":{"type":"Point","coordinates":[-0.8569684210526315,43.30891909774436]}}]}