{"type":"FeatureCollection","features":[{"type":"Feature","properties":{"codesPostaux":["64330"],"population":188,"nom":"Castetpugon","code":"64180"},"geometry":{"type":"Point","coordinates":[-0.22846567567567577,43.56299817567565]}}]}