{"type":"FeatureCollection","features":[{"type":"Feature","properties":{"codesPostaux":["64130"],"population":523,"nom":"Esp\u00e8s-Undurein","code":"64214"},"geometry":{"type":"Point","coordinates":[-0.8887274719101118,43.273379438202255]}}]}