{"type":"FeatureCollection","features":[{"type":"Feature","properties":{"codesPostaux":["64390"],"population":108,"nom":"Espiute","code":"64215"},"geometry":{"type":"Point","coordinates":[-0.9126019277108435,43.35267638554217]}}]}