{"type":"FeatureCollection","features":[{"type":"Feature","properties":{"codesPostaux":["64110"],"population":3566,"nom":"Gelos","code":"64237"},"geometry":{"type":"Point","coordinates":[-0.36652034246575305,43.251970821917816]}}]}