{"type":"FeatureCollection","features":[{"type":"Feature","properties":{"codesPostaux":["64120"],"population":309,"nom":"Garris","code":"64235"},"geometry":{"type":"Point","coordinates":[-1.0577964130434783,43.34221239130435]}}]}