{"type":"FeatureCollection","features":[{"type":"Feature","properties":{"codesPostaux":["64210"],"population":1281,"nom":"Gu\u00e9thary","code":"64249"},"geometry":{"type":"Point","coordinates":[-1.612841956521739,43.423225869565215]}}]}