{"type":"FeatureCollection","features":[{"type":"Feature","properties":{"codesPostaux":["64520"],"population":949,"nom":"Guiche","code":"64250"},"geometry":{"type":"Point","coordinates":[-1.2089934415584431,43.50289857142856]}}]}