{"type":"FeatureCollection","features":[{"type":"Feature","properties":{"codesPostaux":["64470"],"population":85,"nom":"Haux","code":"64258"},"geometry":{"type":"Point","coordinates":[-0.8329582467532467,43.063301948051965]}}]}