{"type":"FeatureCollection","features":[{"type":"Feature","properties":{"codesPostaux":["64240"],"population":475,"nom":"Isturits","code":"64277"},"geometry":{"type":"Point","coordinates":[-1.2127176530612245,43.36760938775511]}}]}