{"type":"FeatureCollection","features":[{"type":"Feature","properties":{"codesPostaux":["64780"],"population":866,"nom":"Irissarry","code":"64273"},"geometry":{"type":"Point","coordinates":[-1.2408393607305943,43.26447232876711]}}]}