{"type":"FeatureCollection","features":[{"type":"Feature","properties":{"codesPostaux":["64460"],"population":171,"nom":"Labatut","code":"64293"},"geometry":{"type":"Point","coordinates":[-0.0207051376146789,43.41816376146788]}}]}