{"type":"FeatureCollection","features":[{"type":"Feature","properties":{"codesPostaux":["64170"],"population":588,"nom":"Labastide-Monr\u00e9jeau","code":"64290"},"geometry":{"type":"Point","coordinates":[-0.524948111111111,43.38895177777778]}}]}