{"type":"FeatureCollection","features":[{"type":"Feature","properties":{"codesPostaux":["64150"],"population":703,"nom":"Lahourcade","code":"64306"},"geometry":{"type":"Point","coordinates":[-0.6287002631578948,43.35487973684213]}}]}