{"type":"FeatureCollection","features":[{"type":"Feature","properties":{"codesPostaux":["64150"],"population":1201,"nom":"Lagor","code":"64301"},"geometry":{"type":"Point","coordinates":[-0.669406179245283,43.38016471698114]}}]}