{"type":"FeatureCollection","features":[{"type":"Feature","properties":{"codesPostaux":["64120"],"population":404,"nom":"Larceveau-Arros-Cibits","code":"64314"},"geometry":{"type":"Point","coordinates":[-1.086758971962617,43.22398813084113]}}]}