{"type":"FeatureCollection","features":[{"type":"Feature","properties":{"codesPostaux":["64570"],"population":486,"nom":"Lanne-en-Bar\u00e9tous","code":"64310"},"geometry":{"type":"Point","coordinates":[-0.7847718532818531,43.08039787644789]}}]}