{"type":"FeatureCollection","features":[{"type":"Feature","properties":{"codesPostaux":["64560"],"population":191,"nom":"Larrau","code":"64316"},"geometry":{"type":"Point","coordinates":[-0.996394839857651,43.010239501779374]}}]}