{"type":"FeatureCollection","features":[{"type":"Feature","properties":{"codesPostaux":["64290"],"population":199,"nom":"Lasseubetat","code":"64325"},"geometry":{"type":"Point","coordinates":[-0.4456205454545455,43.18610018181816]}}]}