{"type":"FeatureCollection","features":[{"type":"Feature","properties":{"codesPostaux":["64800"],"population":857,"nom":"Lestelle-B\u00e9tharram","code":"64339"},"geometry":{"type":"Point","coordinates":[-0.2171070833333332,43.12372590277776]}}]}