{"type":"FeatureCollection","features":[{"type":"Feature","properties":{"codesPostaux":["64350"],"population":59,"nom":"Lucarr\u00e9","code":"64357"},"geometry":{"type":"Point","coordinates":[-0.08409879120879121,43.404088021978026]}}]}