{"type":"FeatureCollection","features":[{"type":"Feature","properties":{"codesPostaux":["64240"],"population":548,"nom":"Macaye","code":"64364"},"geometry":{"type":"Point","coordinates":[-1.326298473282441,43.31928561068703]}}]}