{"type":"FeatureCollection","features":[{"type":"Feature","properties":{"codesPostaux":["64460"],"population":113,"nom":"Maure","code":"64372"},"geometry":{"type":"Point","coordinates":[-0.07646036585365855,43.377127926829274]}}]}