{"type":"FeatureCollection","features":[{"type":"Feature","properties":{"codesPostaux":["64110"],"population":1894,"nom":"Maz\u00e8res-Lezons","code":"64373"},"geometry":{"type":"Point","coordinates":[-0.3557622580645162,43.26940048387097]}}]}