{"type":"FeatureCollection","features":[{"type":"Feature","properties":{"codesPostaux":["64120"],"population":261,"nom":"M\u00e9harin","code":"64375"},"geometry":{"type":"Point","coordinates":[-1.1432685393258426,43.326999550561794]}}]}