{"type":"FeatureCollection","features":[{"type":"Feature","properties":{"codesPostaux":["64410"],"population":109,"nom":"Mialos","code":"64383"},"geometry":{"type":"Point","coordinates":[-0.41128790322580633,43.49983217741936]}}]}