{"type":"FeatureCollection","features":[{"type":"Feature","properties":{"codesPostaux":["64350"],"population":129,"nom":"Momy","code":"64388"},"geometry":{"type":"Point","coordinates":[-0.10621285714285719,43.39053885714285]}}]}