{"type":"FeatureCollection","features":[{"type":"Feature","properties":{"codesPostaux":["64190"],"population":295,"nom":"M\u00e9ritein","code":"64381"},"geometry":{"type":"Point","coordinates":[-0.7527620270270272,43.335951486486486]}}]}