{"type":"FeatureCollection","features":[{"type":"Feature","properties":{"codesPostaux":["64160"],"population":367,"nom":"Monassut-Audiracq","code":"64389"},"geometry":{"type":"Point","coordinates":[-0.19796351999999998,43.411382719999985]}}]}