{"type":"FeatureCollection","features":[{"type":"Feature","properties":{"codesPostaux":["64460"],"population":462,"nom":"Montaner","code":"64398"},"geometry":{"type":"Point","coordinates":[-0.021974112149532706,43.346698504672894]}}]}