{"type":"FeatureCollection","features":[{"type":"Feature","properties":{"codesPostaux":["64190"],"population":185,"nom":"Montfort","code":"64403"},"geometry":{"type":"Point","coordinates":[-0.8639860769230769,43.36811030769227]}}]}