{"type":"FeatureCollection","features":[{"type":"Feature","properties":{"codesPostaux":["64470"],"population":305,"nom":"Montory","code":"64404"},"geometry":{"type":"Point","coordinates":[-0.8165573939393944,43.09266951515152]}}]}