{"type":"FeatureCollection","features":[{"type":"Feature","properties":{"codesPostaux":["64420"],"population":1579,"nom":"Nousty","code":"64419"},"geometry":{"type":"Point","coordinates":[-0.21684518518518522,43.26439425925927]}}]}