{"type":"FeatureCollection","features":[{"type":"Feature","properties":{"codesPostaux":["64150"],"population":144,"nom":"Nogu\u00e8res","code":"64418"},"geometry":{"type":"Point","coordinates":[-0.6055160377358488,43.36973113207548]}}]}