{"type":"FeatureCollection","features":[{"type":"Feature","properties":{"codesPostaux":["64150"],"population":6770,"nom":"Mourenx","code":"64410"},"geometry":{"type":"Point","coordinates":[-0.6143349074074073,43.37621722222224]}}]}