{"type":"FeatureCollection","features":[{"type":"Feature","properties":{"codesPostaux":["64150"],"population":477,"nom":"Os-Marsillon","code":"64431"},"geometry":{"type":"Point","coordinates":[-0.6179317977528087,43.38560719101124]}}]}