{"type":"FeatureCollection","features":[{"type":"Feature","properties":{"codesPostaux":["64190"],"population":43,"nom":"Ossenx","code":"64434"},"geometry":{"type":"Point","coordinates":[-0.8071850000000003,43.37677944444444]}}]}