{"type":"FeatureCollection","features":[{"type":"Feature","properties":{"codesPostaux":["64230"],"population":1578,"nom":"Poey-de-Lescar","code":"64448"},"geometry":{"type":"Point","coordinates":[-0.4631172357723579,43.35218146341464]}}]}