{"type":"FeatureCollection","features":[{"type":"Feature","properties":{"codesPostaux":["64150"],"population":872,"nom":"Pardies","code":"64443"},"geometry":{"type":"Point","coordinates":[-0.5883082608695649,43.358408115942034]}}]}