{"type":"FeatureCollection","features":[{"type":"Feature","properties":{"codesPostaux":["64270"],"population":1203,"nom":"Puyo\u00f4","code":"64461"},"geometry":{"type":"Point","coordinates":[-0.907994129032258,43.537166]}}]}