{"type":"FeatureCollection","features":[{"type":"Feature","properties":{"codesPostaux":["64110"],"population":798,"nom":"Rontignon","code":"64467"},"geometry":{"type":"Point","coordinates":[-0.34221556701030936,43.24295587628864]}}]}