{"type":"FeatureCollection","features":[{"type":"Feature","properties":{"codesPostaux":["64160"],"population":617,"nom":"Saint-Armou","code":"64470"},"geometry":{"type":"Point","coordinates":[-0.302591673151751,43.40536848249027]}}]}