{"type":"FeatureCollection","features":[{"type":"Feature","properties":{"codesPostaux":["64430"],"population":1619,"nom":"Saint-\u00c9tienne-de-Ba\u00efgorry","code":"64477"},"geometry":{"type":"Point","coordinates":[-1.3538025000000005,43.17774577205881]}}]}