{"type":"FeatureCollection","features":[{"type":"Feature","properties":{"codesPostaux":["64270"],"population":153,"nom":"Saint-Dos","code":"64474"},"geometry":{"type":"Point","coordinates":[-1.023291346153846,43.47358557692309]}}]}