{"type":"FeatureCollection","features":[{"type":"Feature","properties":{"codesPostaux":["64520"],"population":687,"nom":"Sames","code":"64502"},"geometry":{"type":"Point","coordinates":[-1.1570630534351145,43.52077351145039]}}]}