{"type":"FeatureCollection","features":[{"type":"Feature","properties":{"codesPostaux":["64160"],"population":243,"nom":"Sedze-Maubecq","code":"64515"},"geometry":{"type":"Point","coordinates":[-0.12237845528455281,43.35612569105692]}}]}