{"type":"FeatureCollection","features":[{"type":"Feature","properties":{"codesPostaux":["64121"],"population":3973,"nom":"Serres-Castet","code":"64519"},"geometry":{"type":"Point","coordinates":[-0.3681032211538461,43.38251168269228]}}]}