{"type":"FeatureCollection","features":[{"type":"Feature","properties":{"codesPostaux":["64160"],"population":750,"nom":"Serres-Morla\u00e0s","code":"64520"},"geometry":{"type":"Point","coordinates":[-0.2649276923076923,43.32382461538461]}}]}