{"type":"FeatureCollection","features":[{"type":"Feature","properties":{"codesPostaux":["64350"],"population":370,"nom":"Simacourbe","code":"64524"},"geometry":{"type":"Point","coordinates":[-0.17188890547263674,43.44931731343284]}}]}