{"type":"FeatureCollection","features":[{"type":"Feature","properties":{"codesPostaux":["64160"],"population":76,"nom":"Urost","code":"64544"},"geometry":{"type":"Point","coordinates":[-0.14953999999999998,43.33941486486487]}}]}