{"type":"FeatureCollection","features":[{"type":"Feature","properties":{"codesPostaux":["64110"],"population":714,"nom":"Uzos","code":"64550"},"geometry":{"type":"Point","coordinates":[-0.35240092592592587,43.25991018518518]}}]}