{"type":"FeatureCollection","features":[{"type":"Feature","properties":{"codesPostaux":["64150"],"population":357,"nom":"Vielles\u00e9gure","code":"64556"},"geometry":{"type":"Point","coordinates":[-0.7020617768595039,43.35682871900827]}}]}