{"type":"FeatureCollection","features":[{"type":"Feature","properties":{"codesPostaux":["65260"],"population":279,"nom":"Adast","code":"65001"},"geometry":{"type":"Point","coordinates":[-0.07672513513513515,42.975719459459455]}}]}