{"type":"FeatureCollection","features":[{"type":"Feature","properties":{"codesPostaux":["65240"],"population":120,"nom":"Adervielle-Pouchergues","code":"65003"},"geometry":{"type":"Point","coordinates":[0.3925851685393258,42.80355550561796]}}]}