{"type":"FeatureCollection","features":[{"type":"Feature","properties":{"codesPostaux":["65370"],"population":36,"nom":"Antichan","code":"65014"},"geometry":{"type":"Point","coordinates":[0.5847041176470588,42.991729117647054]}}]}