{"type":"FeatureCollection","features":[{"type":"Feature","properties":{"codesPostaux":["65100"],"population":254,"nom":"Arcizac-ez-Angles","code":"65020"},"geometry":{"type":"Point","coordinates":[0.01456214285714286,43.097002857142854]}}]}