{"type":"FeatureCollection","features":[{"type":"Feature","properties":{"codesPostaux":["65100"],"population":267,"nom":"Aspin-en-Lavedan","code":"65040"},"geometry":{"type":"Point","coordinates":[-0.04570194444444445,43.074192499999995]}}]}