{"type":"FeatureCollection","features":[{"type":"Feature","properties":{"codesPostaux":["65360"],"population":148,"nom":"Barbazan-Dessus","code":"65063"},"geometry":{"type":"Point","coordinates":[0.14399854368932044,43.16076330097088]}}]}