{"type":"FeatureCollection","features":[{"type":"Feature","properties":{"codesPostaux":["65200"],"population":52,"nom":"Banios","code":"65060"},"geometry":{"type":"Point","coordinates":[0.2291080555555556,43.04143027777778]}}]}