{"type":"FeatureCollection","features":[{"type":"Feature","properties":{"codesPostaux":["65380"],"population":131,"nom":"Barry","code":"65067"},"geometry":{"type":"Point","coordinates":[0.019743673469387758,43.13721897959184]}}]}