{"type":"FeatureCollection","features":[{"type":"Feature","properties":{"codesPostaux":["65140"],"population":56,"nom":"Barbachen","code":"65061"},"geometry":{"type":"Point","coordinates":[0.12648413333333336,43.429362933333344]}}]}