{"type":"FeatureCollection","features":[{"type":"Feature","properties":{"codesPostaux":["65230"],"population":44,"nom":"Betb\u00e8ze","code":"65088"},"geometry":{"type":"Point","coordinates":[0.5716460824742268,43.28985680412371]}}]}