{"type":"FeatureCollection","features":[{"type":"Feature","properties":{"codesPostaux":["65120"],"population":112,"nom":"Betpouey","code":"65089"},"geometry":{"type":"Point","coordinates":[0.06423451923076924,42.861098076923085]}}]}