{"type":"FeatureCollection","features":[{"type":"Feature","properties":{"codesPostaux":["65130"],"population":60,"nom":"Bettes","code":"65091"},"geometry":{"type":"Point","coordinates":[0.22092636363636364,43.08213525252527]}}]}