{"type":"FeatureCollection","features":[{"type":"Feature","properties":{"codesPostaux":["65170"],"population":157,"nom":"Bourisp","code":"65106"},"geometry":{"type":"Point","coordinates":[0.3387823529411764,42.831343921568624]}}]}