{"type":"FeatureCollection","features":[{"type":"Feature","properties":{"codesPostaux":["65460"],"population":781,"nom":"Bours","code":"65108"},"geometry":{"type":"Point","coordinates":[0.09273379999999999,43.280586199999995]}}]}