{"type":"FeatureCollection","features":[{"type":"Feature","properties":{"codesPostaux":["65500"],"population":427,"nom":"Camal\u00e8s","code":"65121"},"geometry":{"type":"Point","coordinates":[0.08210783582089552,43.35983455223882]}}]}