{"type":"FeatureCollection","features":[{"type":"Feature","properties":{"codesPostaux":["65230"],"population":40,"nom":"Caubous","code":"65136"},"geometry":{"type":"Point","coordinates":[0.4644101204819277,43.24199216867469]}}]}