{"type":"FeatureCollection","features":[{"type":"Feature","properties":{"codesPostaux":["65240"],"population":58,"nom":"Cazaux-Fr\u00e9chet-An\u00e9ran-Camors","code":"65141"},"geometry":{"type":"Point","coordinates":[0.4340932432432433,42.83829391891891]}}]}