{"type":"FeatureCollection","features":[{"type":"Feature","properties":{"codesPostaux":["65170"],"population":29,"nom":"Ens","code":"65157"},"geometry":{"type":"Point","coordinates":[0.3352231372549019,42.79339039215685]}}]}