{"type":"FeatureCollection","features":[{"type":"Feature","properties":{"codesPostaux":["65250"],"population":400,"nom":"Escala","code":"65159"},"geometry":{"type":"Point","coordinates":[0.4100626829268294,43.08302634146342]}}]}