{"type":"FeatureCollection","features":[{"type":"Feature","properties":{"codesPostaux":["65100"],"population":99,"nom":"Escoub\u00e8s-Pouts","code":"65164"},"geometry":{"type":"Point","coordinates":[0.027799775280898872,43.10531056179775]}}]}