{"type":"FeatureCollection","features":[{"type":"Feature","properties":{"codesPostaux":["65130"],"population":64,"nom":"Esp\u00e8che","code":"65166"},"geometry":{"type":"Point","coordinates":[0.2998581999999999,43.0619266]}}]}