{"type":"FeatureCollection","features":[{"type":"Feature","properties":{"codesPostaux":["65130"],"population":32,"nom":"Fr\u00e9chendets","code":"65179"},"geometry":{"type":"Point","coordinates":[0.2365279487179488,43.06224076923076]}}]}