{"type":"FeatureCollection","features":[{"type":"Feature","properties":{"codesPostaux":["65140"],"population":108,"nom":"Gensac","code":"65196"},"geometry":{"type":"Point","coordinates":[0.08807505747126436,43.43349000000001]}}]}