{"type":"FeatureCollection","features":[{"type":"Feature","properties":{"codesPostaux":["65120"],"population":377,"nom":"Gavarnie-G\u00e8dre","code":"65192"},"geometry":{"type":"Point","coordinates":[-0.006891282608695645,42.75766078260872]}}]}