{"type":"FeatureCollection","features":[{"type":"Feature","properties":{"codesPostaux":["65200"],"population":1194,"nom":"Gerde","code":"65198"},"geometry":{"type":"Point","coordinates":[0.17990065217391302,43.05693717391302]}}]}