{"type":"FeatureCollection","features":[{"type":"Feature","properties":{"codesPostaux":["65100"],"population":143,"nom":"Gazost","code":"65191"},"geometry":{"type":"Point","coordinates":[0.02081791666666668,42.99915916666668]}}]}