{"type":"FeatureCollection","features":[{"type":"Feature","properties":{"codesPostaux":["65190"],"population":232,"nom":"Goudon","code":"65206"},"geometry":{"type":"Point","coordinates":[0.23663850340136044,43.24432496598639]}}]}