{"type":"FeatureCollection","features":[{"type":"Feature","properties":{"codesPostaux":["65190"],"population":162,"nom":"Hitte","code":"65222"},"geometry":{"type":"Point","coordinates":[0.1596663736263736,43.15590318681319]}}]}