{"type":"FeatureCollection","features":[{"type":"Feature","properties":{"codesPostaux":["65290"],"population":4076,"nom":"Juillan","code":"65235"},"geometry":{"type":"Point","coordinates":[0.02849028571428571,43.20007385714284]}}]}