{"type":"FeatureCollection","features":[{"type":"Feature","properties":{"codesPostaux":["65370"],"population":244,"nom":"Izaourt","code":"65230"},"geometry":{"type":"Point","coordinates":[0.6027604651162789,43.01747651162791]}}]}