{"type":"FeatureCollection","features":[{"type":"Feature","properties":{"codesPostaux":["65220"],"population":113,"nom":"Lalanne-Trie","code":"65250"},"geometry":{"type":"Point","coordinates":[0.3316781818181818,43.31300818181816]}}]}