{"type":"FeatureCollection","features":[{"type":"Feature","properties":{"codesPostaux":["65140"],"population":144,"nom":"Lam\u00e9ac","code":"65254"},"geometry":{"type":"Point","coordinates":[0.23012901785714288,43.33096285714287]}}]}