{"type":"FeatureCollection","features":[{"type":"Feature","properties":{"codesPostaux":["65220"],"population":85,"nom":"Lapeyre","code":"65260"},"geometry":{"type":"Point","coordinates":[0.32453522388059697,43.32547029850744]}}]}