{"type":"FeatureCollection","features":[{"type":"Feature","properties":{"codesPostaux":["65100"],"population":14644,"nom":"Lourdes","code":"65286"},"geometry":{"type":"Point","coordinates":[-0.08328666666666659,43.10961846666669]}}]}