{"type":"FeatureCollection","features":[{"type":"Feature","properties":{"codesPostaux":["65240"],"population":62,"nom":"Loudervielle","code":"65283"},"geometry":{"type":"Point","coordinates":[0.43007944444444435,42.80631688888889]}}]}