{"type":"FeatureCollection","features":[{"type":"Feature","properties":{"codesPostaux":["65350"],"population":190,"nom":"Louit","code":"65285"},"geometry":{"type":"Point","coordinates":[0.16519904761904763,43.3005681904762]}}]}