{"type":"FeatureCollection","features":[{"type":"Feature","properties":{"codesPostaux":["65220"],"population":115,"nom":"Lustar","code":"65293"},"geometry":{"type":"Point","coordinates":[0.33651561224489795,43.26810367346939]}}]}