{"type":"FeatureCollection","features":[{"type":"Feature","properties":{"codesPostaux":["65700"],"population":437,"nom":"Madiran","code":"65296"},"geometry":{"type":"Point","coordinates":[-0.05771320652173913,43.55090375000001]}}]}