{"type":"FeatureCollection","features":[{"type":"Feature","properties":{"codesPostaux":["65190"],"population":200,"nom":"Luc","code":"65290"},"geometry":{"type":"Point","coordinates":[0.1838935064935065,43.14760350649351]}}]}