{"type":"FeatureCollection","features":[{"type":"Feature","properties":{"codesPostaux":["65370"],"population":122,"nom":"Maul\u00e9on-Barousse","code":"65305"},"geometry":{"type":"Point","coordinates":[0.5774500000000002,42.94776799999999]}}]}