{"type":"FeatureCollection","features":[{"type":"Feature","properties":{"codesPostaux":["65350"],"population":234,"nom":"Marseillan","code":"65301"},"geometry":{"type":"Point","coordinates":[0.2143288073394495,43.30302247706424]}}]}