{"type":"FeatureCollection","features":[{"type":"Feature","properties":{"codesPostaux":["65200"],"population":247,"nom":"M\u00e9rilheu","code":"65310"},"geometry":{"type":"Point","coordinates":[0.17822701030927834,43.10205525773197]}}]}