{"type":"FeatureCollection","features":[{"type":"Feature","properties":{"codesPostaux":["65150"],"population":160,"nom":"Nestier","code":"65327"},"geometry":{"type":"Point","coordinates":[0.4783246969696972,43.059861666666656]}}]}