{"type":"FeatureCollection","features":[{"type":"Feature","properties":{"codesPostaux":["65150"],"population":241,"nom":"Nistos","code":"65329"},"geometry":{"type":"Point","coordinates":[0.4763645762711865,43.00040940677963]}}]}