{"type":"FeatureCollection","features":[{"type":"Feature","properties":{"codesPostaux":["65200"],"population":805,"nom":"Montgaillard","code":"65320"},"geometry":{"type":"Point","coordinates":[0.11876027972027968,43.12301615384617]}}]}