{"type":"FeatureCollection","features":[{"type":"Feature","properties":{"codesPostaux":["65200"],"population":510,"nom":"Ordizan","code":"65335"},"geometry":{"type":"Point","coordinates":[0.14512701754385962,43.10756464912279]}}]}