{"type":"FeatureCollection","features":[{"type":"Feature","properties":{"codesPostaux":["65380"],"population":2314,"nom":"Ossun","code":"65344"},"geometry":{"type":"Point","coordinates":[-0.05002043165467624,43.18653791366905]}}]}