{"type":"FeatureCollection","features":[{"type":"Feature","properties":{"codesPostaux":["65190"],"population":159,"nom":"Peyraube","code":"65357"},"geometry":{"type":"Point","coordinates":[0.2546902298850574,43.2024916091954]}}]}