{"type":"FeatureCollection","features":[{"type":"Feature","properties":{"codesPostaux":["65100"],"population":890,"nom":"Poueyferr\u00e9","code":"65366"},"geometry":{"type":"Point","coordinates":[-0.08473628205128206,43.11995551282053]}}]}