{"type":"FeatureCollection","features":[{"type":"Feature","properties":{"codesPostaux":["65220"],"population":179,"nom":"Sadournin","code":"65383"},"geometry":{"type":"Point","coordinates":[0.4105921951219513,43.319700060975606]}}]}