{"type":"FeatureCollection","features":[{"type":"Feature","properties":{"codesPostaux":["65120"],"population":128,"nom":"Saligos","code":"65399"},"geometry":{"type":"Point","coordinates":[-0.010049347826086958,42.89606304347826]}}]}