{"type":"FeatureCollection","features":[{"type":"Feature","properties":{"codesPostaux":["65370"],"population":214,"nom":"Sal\u00e9chan","code":"65398"},"geometry":{"type":"Point","coordinates":[0.6286344736842104,42.95390763157894]}}]}