{"type":"FeatureCollection","features":[{"type":"Feature","properties":{"codesPostaux":["65270"],"population":1211,"nom":"Saint-P\u00e9-de-Bigorre","code":"65395"},"geometry":{"type":"Point","coordinates":[-0.15947783783783778,43.088356864864856]}}]}