{"type":"FeatureCollection","features":[{"type":"Feature","properties":{"codesPostaux":["65700"],"population":211,"nom":"Sombrun","code":"65429"},"geometry":{"type":"Point","coordinates":[0.00018318518518518483,43.47989059259261]}}]}