{"type":"FeatureCollection","features":[{"type":"Feature","properties":{"codesPostaux":["65200"],"population":104,"nom":"Uzer","code":"65459"},"geometry":{"type":"Point","coordinates":[0.1953470212765956,43.080075744680855]}}]}