{"type":"FeatureCollection","features":[{"type":"Feature","properties":{"codesPostaux":["65360"],"population":514,"nom":"Vielle-Adour","code":"65464"},"geometry":{"type":"Point","coordinates":[0.13163770642201839,43.14401642201834]}}]}