{"type":"FeatureCollection","features":[{"type":"Feature","properties":{"codesPostaux":["65120"],"population":78,"nom":"Viella","code":"65463"},"geometry":{"type":"Point","coordinates":[0.022116046511627904,42.87256790697674]}}]}