{"type":"FeatureCollection","features":[{"type":"Feature","properties":{"codesPostaux":["65260"],"population":402,"nom":"Villelongue","code":"65473"},"geometry":{"type":"Point","coordinates":[-0.025926915887850458,42.94589271028037]}}]}