{"type":"FeatureCollection","features":[{"type":"Feature","properties":{"codesPostaux":["66320"],"population":105,"nom":"Arboussols","code":"66007"},"geometry":{"type":"Point","coordinates":[2.50684972972973,42.66147824324324]}}]}