{"type":"FeatureCollection","features":[{"type":"Feature","properties":{"codesPostaux":["66700"],"population":9914,"nom":"Argel\u00e8s-sur-Mer","code":"66008"},"geometry":{"type":"Point","coordinates":[3.0304702666666663,42.52303220000002]}}]}