{"type":"FeatureCollection","features":[{"type":"Feature","properties":{"codesPostaux":["66360"],"population":46,"nom":"Ayguat\u00e9bia-Talau","code":"66010"},"geometry":{"type":"Point","coordinates":[2.1929800877192993,42.55694618421051]}}]}