{"type":"FeatureCollection","features":[{"type":"Feature","properties":{"codesPostaux":["66110"],"population":79,"nom":"La Bastide","code":"66018"},"geometry":{"type":"Point","coordinates":[2.5771707633587773,42.53650793893132]}}]}