{"type":"FeatureCollection","features":[{"type":"Feature","properties":{"codesPostaux":["66670"],"population":3987,"nom":"Bages","code":"66011"},"geometry":{"type":"Point","coordinates":[2.8869558928571424,42.603984642857135]}}]}