{"type":"FeatureCollection","features":[{"type":"Feature","properties":{"codesPostaux":["66330"],"population":9577,"nom":"Cabestany","code":"66028"},"geometry":{"type":"Point","coordinates":[2.9429313580246896,42.676368888888895]}}]}