{"type":"FeatureCollection","features":[{"type":"Feature","properties":{"codesPostaux":["66500"],"population":114,"nom":"Camp\u00f4me","code":"66034"},"geometry":{"type":"Point","coordinates":[2.3888921428571415,42.64857650793651]}}]}