{"type":"FeatureCollection","features":[{"type":"Feature","properties":{"codesPostaux":["66720"],"population":148,"nom":"Caramany","code":"66039"},"geometry":{"type":"Point","coordinates":[2.5628217999999983,42.73387670000002]}}]}