{"type":"FeatureCollection","features":[{"type":"Feature","properties":{"codesPostaux":["66680"],"population":4914,"nom":"Canoh\u00e8s","code":"66038"},"geometry":{"type":"Point","coordinates":[2.835643243243244,42.650918378378364]}}]}