{"type":"FeatureCollection","features":[{"type":"Feature","properties":{"codesPostaux":["66400"],"population":7663,"nom":"C\u00e9ret","code":"66049"},"geometry":{"type":"Point","coordinates":[2.745402889908259,42.48338720183486]}}]}