{"type":"FeatureCollection","features":[{"type":"Feature","properties":{"codesPostaux":["66290"],"population":1378,"nom":"Cerb\u00e8re","code":"66048"},"geometry":{"type":"Point","coordinates":[3.1598214919354843,42.44669008064518]}}]}