{"type":"FeatureCollection","features":[{"type":"Feature","properties":{"codesPostaux":["66360"],"population":16,"nom":"Caudi\u00e8s-de-Conflent","code":"66047"},"geometry":{"type":"Point","coordinates":[2.144206610169492,42.559606779661]}}]}