{"type":"FeatureCollection","features":[{"type":"Feature","properties":{"codesPostaux":["66500"],"population":367,"nom":"Codalet","code":"66052"},"geometry":{"type":"Point","coordinates":[2.4130898684210527,42.60222473684212]}}]}