{"type":"FeatureCollection","features":[{"type":"Feature","properties":{"codesPostaux":["66500"],"population":54,"nom":"Conat","code":"66054"},"geometry":{"type":"Point","coordinates":[2.3401520000000007,42.61836785714285]}}]}