{"type":"FeatureCollection","features":[{"type":"Feature","properties":{"codesPostaux":["66360"],"population":121,"nom":"Escaro","code":"66068"},"geometry":{"type":"Point","coordinates":[2.312079250000001,42.540010374999994]}}]}