{"type":"FeatureCollection","features":[{"type":"Feature","properties":{"codesPostaux":["66150"],"population":246,"nom":"Corsavy","code":"66060"},"geometry":{"type":"Point","coordinates":[2.559599912280701,42.480304824561415]}}]}