{"type":"FeatureCollection","features":[{"type":"Feature","properties":{"codesPostaux":["66130"],"population":5405,"nom":"Ille-sur-T\u00eat","code":"66088"},"geometry":{"type":"Point","coordinates":[2.6276469312169315,42.67148148148149]}}]}