{"type":"FeatureCollection","features":[{"type":"Feature","properties":{"codesPostaux":["66740"],"population":2148,"nom":"Laroque-des-Alb\u00e8res","code":"66093"},"geometry":{"type":"Point","coordinates":[2.9342507070707073,42.524283434343445]}}]}