{"type":"FeatureCollection","features":[{"type":"Feature","properties":{"codesPostaux":["66360"],"population":46,"nom":"Jujols","code":"66090"},"geometry":{"type":"Point","coordinates":[2.284518181818182,42.585271363636366]}}]}