{"type":"FeatureCollection","features":[{"type":"Feature","properties":{"codesPostaux":["66230"],"population":47,"nom":"Laman\u00e8re","code":"66091"},"geometry":{"type":"Point","coordinates":[2.51725358108108,42.361892972972974]}}]}