{"type":"FeatureCollection","features":[{"type":"Feature","properties":{"codesPostaux":["66320"],"population":549,"nom":"Marquixanes","code":"66103"},"geometry":{"type":"Point","coordinates":[2.48291371681416,42.637180973451315]}}]}