{"type":"FeatureCollection","features":[{"type":"Feature","properties":{"codesPostaux":["66210"],"population":275,"nom":"Matemale","code":"66105"},"geometry":{"type":"Point","coordinates":[2.122633421052632,42.58947828947369]}}]}