{"type":"FeatureCollection","features":[{"type":"Feature","properties":{"codesPostaux":["66460"],"population":840,"nom":"Maury","code":"66107"},"geometry":{"type":"Point","coordinates":[2.6317179279279275,42.809976666666664]}}]}