{"type":"FeatureCollection","features":[{"type":"Feature","properties":{"codesPostaux":["66740"],"population":1207,"nom":"Montesquieu-des-Alb\u00e8res","code":"66115"},"geometry":{"type":"Point","coordinates":[2.871482585034013,42.518505170068025]}}]}