{"type":"FeatureCollection","features":[{"type":"Feature","properties":{"codesPostaux":["66300"],"population":205,"nom":"Montauriol","code":"66112"},"geometry":{"type":"Point","coordinates":[2.724415952380953,42.57929055555557]}}]}