{"type":"FeatureCollection","features":[{"type":"Feature","properties":{"codesPostaux":["66600"],"population":1382,"nom":"Peyrestortes","code":"66138"},"geometry":{"type":"Point","coordinates":[2.851159615384616,42.74711288461538]}}]}