{"type":"FeatureCollection","features":[{"type":"Feature","properties":{"codesPostaux":["66690"],"population":3153,"nom":"Palau-del-Vidre","code":"66133"},"geometry":{"type":"Point","coordinates":[2.9581568493150683,42.56696178082193]}}]}