{"type":"FeatureCollection","features":[{"type":"Feature","properties":{"codesPostaux":["66730"],"population":55,"nom":"P\u00e9zilla-de-Conflent","code":"66139"},"geometry":{"type":"Point","coordinates":[2.492658799999999,42.734856000000015]}}]}