{"type":"FeatureCollection","features":[{"type":"Feature","properties":{"codesPostaux":["66210"],"population":73,"nom":"Puyvalador","code":"66154"},"geometry":{"type":"Point","coordinates":[2.1143752314814823,42.65098972222221]}}]}