{"type":"FeatureCollection","features":[{"type":"Feature","properties":{"codesPostaux":["66360"],"population":26,"nom":"Railleu","code":"66157"},"geometry":{"type":"Point","coordinates":[2.1631199999999997,42.59040551020408]}}]}