{"type":"FeatureCollection","features":[{"type":"Feature","properties":{"codesPostaux":["66280"],"population":4887,"nom":"Saleilles","code":"66189"},"geometry":{"type":"Point","coordinates":[2.948868333333333,42.658717833333334]}}]}