{"type":"FeatureCollection","features":[{"type":"Feature","properties":{"codesPostaux":["66220"],"population":1872,"nom":"Saint-Paul-de-Fenouillet","code":"66187"},"geometry":{"type":"Point","coordinates":[2.4987459770114953,42.81729620689655]}}]}