{"type":"FeatureCollection","features":[{"type":"Feature","properties":{"codesPostaux":["66250"],"population":9851,"nom":"Saint-Laurent-de-la-Salanque","code":"66180"},"geometry":{"type":"Point","coordinates":[3.0100225,42.782977727272716]}}]}