{"type":"FeatureCollection","features":[{"type":"Feature","properties":{"codesPostaux":["66360"],"population":46,"nom":"Souanyas","code":"66197"},"geometry":{"type":"Point","coordinates":[2.279315357142857,42.548835119047624]}}]}