{"type":"FeatureCollection","features":[{"type":"Feature","properties":{"codesPostaux":["66270"],"population":7300,"nom":"Le Soler","code":"66195"},"geometry":{"type":"Point","coordinates":[2.7989752688172045,42.67876290322579]}}]}