{"type":"FeatureCollection","features":[{"type":"Feature","properties":{"codesPostaux":["66110"],"population":50,"nom":"Taulis","code":"66203"},"geometry":{"type":"Point","coordinates":[2.6173206249999987,42.51461732142856]}}]}