{"type":"FeatureCollection","features":[{"type":"Feature","properties":{"codesPostaux":["66300"],"population":163,"nom":"Tord\u00e8res","code":"66211"},"geometry":{"type":"Point","coordinates":[2.76109542635659,42.564508449612404]}}]}