{"type":"FeatureCollection","features":[{"type":"Feature","properties":{"codesPostaux":["66300"],"population":1177,"nom":"Villemolaque","code":"66226"},"geometry":{"type":"Point","coordinates":[2.8510499236641222,42.59393618320612]}}]}