{"type":"FeatureCollection","features":[{"type":"Feature","properties":{"codesPostaux":["66610"],"population":1292,"nom":"Villeneuve-la-Rivi\u00e8re","code":"66228"},"geometry":{"type":"Point","coordinates":[2.7972891304347827,42.70388978260869]}}]}