{"type":"FeatureCollection","features":[{"type":"Feature","properties":{"codesPostaux":["66500"],"population":220,"nom":"Villefranche-de-Conflent","code":"66223"},"geometry":{"type":"Point","coordinates":[2.365746202531645,42.59301759493672]}}]}