{"type":"FeatureCollection","features":[{"type":"Feature","properties":{"codesPostaux":["67220"],"population":470,"nom":"Alb\u00e9","code":"67003"},"geometry":{"type":"Point","coordinates":[7.345295866666664,48.36144733333333]}}]}