{"type":"FeatureCollection","features":[{"type":"Feature","properties":{"codesPostaux":["67250"],"population":688,"nom":"Aschbach","code":"67012"},"geometry":{"type":"Point","coordinates":[7.981404186046512,48.940634883720925]}}]}