{"type":"FeatureCollection","features":[{"type":"Feature","properties":{"codesPostaux":["67500"],"population":963,"nom":"Batzendorf","code":"67023"},"geometry":{"type":"Point","coordinates":[7.7132233333333335,48.78668026666667]}}]}