{"type":"FeatureCollection","features":[{"type":"Feature","properties":{"codesPostaux":["67130"],"population":172,"nom":"Belmont","code":"67027"},"geometry":{"type":"Point","coordinates":[7.253661142857141,48.41241371428573]}}]}