{"type":"FeatureCollection","features":[{"type":"Feature","properties":{"codesPostaux":["67170"],"population":615,"nom":"Bernolsheim","code":"67033"},"geometry":{"type":"Point","coordinates":[7.6860962790697664,48.75192720930233]}}]}