{"type":"FeatureCollection","features":[{"type":"Feature","properties":{"codesPostaux":["67210"],"population":1467,"nom":"Bernardswiller","code":"67031"},"geometry":{"type":"Point","coordinates":[7.454006619718309,48.446420704225375]}}]}