{"type":"FeatureCollection","features":[{"type":"Feature","properties":{"codesPostaux":["67340"],"population":279,"nom":"Bischholtz","code":"67044"},"geometry":{"type":"Point","coordinates":[7.536711111111111,48.89257622222222]}}]}