{"type":"FeatureCollection","features":[{"type":"Feature","properties":{"codesPostaux":["67150"],"population":476,"nom":"Bolsenheim","code":"67054"},"geometry":{"type":"Point","coordinates":[7.605849833333332,48.42509983333332]}}]}