{"type":"FeatureCollection","features":[{"type":"Feature","properties":{"codesPostaux":["67330"],"population":158,"nom":"Bosselshausen","code":"67057"},"geometry":{"type":"Point","coordinates":[7.509725555555556,48.806011111111125]}}]}