{"type":"FeatureCollection","features":[{"type":"Feature","properties":{"codesPostaux":["67360"],"population":352,"nom":"Dieffenbach-l\u00e8s-W\u0153rth","code":"67093"},"geometry":{"type":"Point","coordinates":[7.793247196261681,48.93103981308412]}}]}