{"type":"FeatureCollection","features":[{"type":"Feature","properties":{"codesPostaux":["67360"],"population":1082,"nom":"Durrenbach","code":"67110"},"geometry":{"type":"Point","coordinates":[7.7683288764044915,48.89772752808991]}}]}