{"type":"FeatureCollection","features":[{"type":"Feature","properties":{"codesPostaux":["67700"],"population":417,"nom":"Eckartswiller","code":"67117"},"geometry":{"type":"Point","coordinates":[7.324416909871247,48.78625442060088]}}]}