{"type":"FeatureCollection","features":[{"type":"Feature","properties":{"codesPostaux":["67480"],"population":729,"nom":"Forstfeld","code":"67140"},"geometry":{"type":"Point","coordinates":[8.047743749999999,48.86261765624999]}}]}