{"type":"FeatureCollection","features":[{"type":"Feature","properties":{"codesPostaux":["67118"],"population":7133,"nom":"Geispolsheim","code":"67152"},"geometry":{"type":"Point","coordinates":[7.6619921789883225,48.51209466926071]}}]}