{"type":"FeatureCollection","features":[{"type":"Feature","properties":{"codesPostaux":["67170"],"population":2335,"nom":"Geudertheim","code":"67156"},"geometry":{"type":"Point","coordinates":[7.76095658227848,48.71355379746835]}}]}