{"type":"FeatureCollection","features":[{"type":"Feature","properties":{"codesPostaux":["67130"],"population":437,"nom":"Grandfontaine","code":"67165"},"geometry":{"type":"Point","coordinates":[7.122867802816899,48.49544098591551]}}]}