{"type":"FeatureCollection","features":[{"type":"Feature","properties":{"codesPostaux":["67700"],"population":670,"nom":"Haegen","code":"67179"},"geometry":{"type":"Point","coordinates":[7.29609202586207,48.69869353448274]}}]}