{"type":"FeatureCollection","features":[{"type":"Feature","properties":{"codesPostaux":["67360"],"population":404,"nom":"Hegeney","code":"67186"},"geometry":{"type":"Point","coordinates":[7.737212886597939,48.88549206185567]}}]}