{"type":"FeatureCollection","features":[{"type":"Feature","properties":{"codesPostaux":["67330"],"population":671,"nom":"Hattmatt","code":"67185"},"geometry":{"type":"Point","coordinates":[7.429075181818183,48.78879000000002]}}]}