{"type":"FeatureCollection","features":[{"type":"Feature","properties":{"codesPostaux":["67150"],"population":1396,"nom":"Hindisheim","code":"67197"},"geometry":{"type":"Point","coordinates":[7.626409056603771,48.46968547169813]}}]}