{"type":"FeatureCollection","features":[{"type":"Feature","properties":{"codesPostaux":["67260"],"population":1584,"nom":"Keskastel","code":"67234"},"geometry":{"type":"Point","coordinates":[7.052738599033816,48.982655217391326]}}]}