{"type":"FeatureCollection","features":[{"type":"Feature","properties":{"codesPostaux":["67250"],"population":904,"nom":"Kutzenhausen","code":"67254"},"geometry":{"type":"Point","coordinates":[7.848633235294118,48.940766372549]}}]}