{"type":"FeatureCollection","features":[{"type":"Feature","properties":{"codesPostaux":["67450"],"population":2905,"nom":"Lampertheim","code":"67256"},"geometry":{"type":"Point","coordinates":[7.692190624999998,48.65629348214285]}}]}