{"type":"FeatureCollection","features":[{"type":"Feature","properties":{"codesPostaux":["67240"],"population":1037,"nom":"Kurtzenhouse","code":"67252"},"geometry":{"type":"Point","coordinates":[7.803417499999999,48.73862849999999]}}]}