{"type":"FeatureCollection","features":[{"type":"Feature","properties":{"codesPostaux":["67510"],"population":1614,"nom":"Lembach","code":"67263"},"geometry":{"type":"Point","coordinates":[7.7687460623229505,49.005113371104805]}}]}