{"type":"FeatureCollection","features":[{"type":"Feature","properties":{"codesPostaux":["67480"],"population":854,"nom":"Leutenheim","code":"67264"},"geometry":{"type":"Point","coordinates":[7.999622731481484,48.85285935185189]}}]}