{"type":"FeatureCollection","features":[{"type":"Feature","properties":{"codesPostaux":["67700"],"population":238,"nom":"Maennolsheim","code":"67279"},"geometry":{"type":"Point","coordinates":[7.472206666666666,48.698263999999995]}}]}