{"type":"FeatureCollection","features":[{"type":"Feature","properties":{"codesPostaux":["67580"],"population":648,"nom":"Mietesheim","code":"67292"},"geometry":{"type":"Point","coordinates":[7.652625739130433,48.87730034782613]}}]}