{"type":"FeatureCollection","features":[{"type":"Feature","properties":{"codesPostaux":["67190"],"population":954,"nom":"Mollkirch","code":"67299"},"geometry":{"type":"Point","coordinates":[7.369378923076923,48.50613907692308]}}]}