{"type":"FeatureCollection","features":[{"type":"Feature","properties":{"codesPostaux":["67580"],"population":3382,"nom":"Mertzwiller","code":"67291"},"geometry":{"type":"Point","coordinates":[7.6886339644970425,48.87538739644968]}}]}