{"type":"FeatureCollection","features":[{"type":"Feature","properties":{"codesPostaux":["67480"],"population":359,"nom":"Neuhaeusel","code":"67319"},"geometry":{"type":"Point","coordinates":[8.091384594594597,48.82156594594595]}}]}