{"type":"FeatureCollection","features":[{"type":"Feature","properties":{"codesPostaux":["67207"],"population":1394,"nom":"Niederhausbergen","code":"67326"},"geometry":{"type":"Point","coordinates":[7.704874107142857,48.6236392857143]}}]}