{"type":"FeatureCollection","features":[{"type":"Feature","properties":{"codesPostaux":["67280"],"population":1403,"nom":"Niederhaslach","code":"67325"},"geometry":{"type":"Point","coordinates":[7.345314461538463,48.534647846153845]}}]}