{"type":"FeatureCollection","features":[{"type":"Feature","properties":{"codesPostaux":["67660"],"population":4119,"nom":"Betschdorf","code":"67339"},"geometry":{"type":"Point","coordinates":[7.937773146853146,48.88411349650349]}}]}