{"type":"FeatureCollection","features":[{"type":"Feature","properties":{"codesPostaux":["67330"],"population":246,"nom":"Niedersoultzbach","code":"67333"},"geometry":{"type":"Point","coordinates":[7.471960444444445,48.849930888888885]}}]}