{"type":"FeatureCollection","features":[{"type":"Feature","properties":{"codesPostaux":["67210"],"population":10932,"nom":"Obernai","code":"67348"},"geometry":{"type":"Point","coordinates":[7.466673734439835,48.45438796680498]}}]}