{"type":"FeatureCollection","features":[{"type":"Feature","properties":{"codesPostaux":["67205"],"population":4855,"nom":"Oberhausbergen","code":"67343"},"geometry":{"type":"Point","coordinates":[7.6854559090909085,48.60715954545454]}}]}