{"type":"FeatureCollection","features":[{"type":"Feature","properties":{"codesPostaux":["67520"],"population":454,"nom":"Odratzheim","code":"67354"},"geometry":{"type":"Point","coordinates":[7.491290277777775,48.59935055555557]}}]}