{"type":"FeatureCollection","features":[{"type":"Feature","properties":{"codesPostaux":["67340"],"population":816,"nom":"Offwiller","code":"67358"},"geometry":{"type":"Point","coordinates":[7.538704662162159,48.91809351351351]}}]}