{"type":"FeatureCollection","features":[{"type":"Feature","properties":{"codesPostaux":["67203"],"population":2244,"nom":"Oberschaeffolsheim","code":"67350"},"geometry":{"type":"Point","coordinates":[7.64737100917431,48.58714596330279]}}]}