{"type":"FeatureCollection","features":[{"type":"Feature","properties":{"codesPostaux":["67540"],"population":11925,"nom":"Ostwald","code":"67365"},"geometry":{"type":"Point","coordinates":[7.7084518823529375,48.54489211764705]}}]}