{"type":"FeatureCollection","features":[{"type":"Feature","properties":{"codesPostaux":["67390"],"population":348,"nom":"Richtolsheim","code":"67398"},"geometry":{"type":"Point","coordinates":[7.609723555555555,48.22294533333333]}}]}