{"type":"FeatureCollection","features":[{"type":"Feature","properties":{"codesPostaux":["67480"],"population":951,"nom":"Roppenheim","code":"67409"},"geometry":{"type":"Point","coordinates":[8.066113170731708,48.8377031707317]}}]}