{"type":"FeatureCollection","features":[{"type":"Feature","properties":{"codesPostaux":["67270"],"population":266,"nom":"Rohr","code":"67406"},"geometry":{"type":"Point","coordinates":[7.5373308536585375,48.69471914634146]}}]}