{"type":"FeatureCollection","features":[{"type":"Feature","properties":{"codesPostaux":["67260"],"population":317,"nom":"Rimsdorf","code":"67401"},"geometry":{"type":"Point","coordinates":[7.116914657534248,48.9291490410959]}}]}