{"type":"FeatureCollection","features":[{"type":"Feature","properties":{"codesPostaux":["67170"],"population":324,"nom":"Rottelsheim","code":"67417"},"geometry":{"type":"Point","coordinates":[7.710532926829269,48.75765926829267]}}]}