{"type":"FeatureCollection","features":[{"type":"Feature","properties":{"codesPostaux":["67230"],"population":1140,"nom":"Sand","code":"67433"},"geometry":{"type":"Point","coordinates":[7.625846938775511,48.375315204081616]}}]}