{"type":"FeatureCollection","features":[{"type":"Feature","properties":{"codesPostaux":["67340"],"population":448,"nom":"Schillersdorf","code":"67446"},"geometry":{"type":"Point","coordinates":[7.524527325581397,48.86568569767444]}}]}