{"type":"FeatureCollection","features":[{"type":"Feature","properties":{"codesPostaux":["67630"],"population":808,"nom":"Scheibenhard","code":"67443"},"geometry":{"type":"Point","coordinates":[8.145145300000001,48.973246599999996]}}]}