{"type":"FeatureCollection","features":[{"type":"Feature","properties":{"codesPostaux":["67470"],"population":3311,"nom":"Seltz","code":"67463"},"geometry":{"type":"Point","coordinates":[8.089579045226133,48.89932763819094]}}]}