{"type":"FeatureCollection","features":[{"type":"Feature","properties":{"codesPostaux":["67250"],"population":3035,"nom":"Soultz-sous-For\u00eats","code":"67474"},"geometry":{"type":"Point","coordinates":[7.868917384615383,48.95014065384615]}}]}