{"type":"FeatureCollection","features":[{"type":"Feature","properties":{"codesPostaux":["67340"],"population":256,"nom":"Sparsbach","code":"67475"},"geometry":{"type":"Point","coordinates":[7.403789568965518,48.876856120689645]}}]}