{"type":"FeatureCollection","features":[{"type":"Feature","properties":{"codesPostaux":["67280"],"population":1487,"nom":"Urmatt","code":"67500"},"geometry":{"type":"Point","coordinates":[7.294469855072462,48.5390374637681]}}]}