{"type":"FeatureCollection","features":[{"type":"Feature","properties":{"codesPostaux":["67170"],"population":367,"nom":"Wahlenheim","code":"67510"},"geometry":{"type":"Point","coordinates":[7.6875028571428565,48.765292857142875]}}]}