{"type":"FeatureCollection","features":[{"type":"Feature","properties":{"codesPostaux":["67520"],"population":707,"nom":"Wangen","code":"67517"},"geometry":{"type":"Point","coordinates":[7.465660153846153,48.61865723076924]}}]}