{"type":"FeatureCollection","features":[{"type":"Feature","properties":{"codesPostaux":["67320"],"population":609,"nom":"Weyer","code":"67528"},"geometry":{"type":"Point","coordinates":[7.157912,48.853475515151516]}}]}