{"type":"FeatureCollection","features":[{"type":"Feature","properties":{"codesPostaux":["67310"],"population":1671,"nom":"Westhoffen","code":"67525"},"geometry":{"type":"Point","coordinates":[7.421553517241381,48.60396931034483]}}]}