{"type":"FeatureCollection","features":[{"type":"Feature","properties":{"codesPostaux":["67290"],"population":1588,"nom":"Wingen-sur-Moder","code":"67538"},"geometry":{"type":"Point","coordinates":[7.37349860103627,48.92288590673576]}}]}