{"type":"FeatureCollection","features":[{"type":"Feature","properties":{"codesPostaux":["67270"],"population":716,"nom":"Wilwisheim","code":"67534"},"geometry":{"type":"Point","coordinates":[7.502117832167829,48.75250055944058]}}]}