{"type":"FeatureCollection","features":[{"type":"Feature","properties":{"codesPostaux":["67510"],"population":456,"nom":"Wingen","code":"67537"},"geometry":{"type":"Point","coordinates":[7.8122747244094475,49.03536724409448]}}]}