{"type":"FeatureCollection","features":[{"type":"Feature","properties":{"codesPostaux":["67310"],"population":249,"nom":"Zehnacker","code":"67555"},"geometry":{"type":"Point","coordinates":[7.452448461538461,48.67159487179487]}}]}