{"type":"FeatureCollection","features":[{"type":"Feature","properties":{"codesPostaux":["67110"],"population":783,"nom":"Zinswiller","code":"67558"},"geometry":{"type":"Point","coordinates":[7.58969840490798,48.91455631901844]}}]}