{"type":"FeatureCollection","features":[{"type":"Feature","properties":{"codesPostaux":["67290"],"population":237,"nom":"Zittersheim","code":"67559"},"geometry":{"type":"Point","coordinates":[7.3427283999999995,48.90134640000001]}}]}