{"type":"FeatureCollection","features":[{"type":"Feature","properties":{"codesPostaux":["68210"],"population":818,"nom":"Ballersdorf","code":"68017"},"geometry":{"type":"Point","coordinates":[7.154568648648647,47.61911567567569]}}]}