{"type":"FeatureCollection","features":[{"type":"Feature","properties":{"codesPostaux":["68520"],"population":1828,"nom":"Burnhaupt-le-Bas","code":"68059"},"geometry":{"type":"Point","coordinates":[7.151099552238805,47.71467970149256]}}]}