{"type":"FeatureCollection","features":[{"type":"Feature","properties":{"codesPostaux":["68480"],"population":352,"nom":"Courtavon","code":"68067"},"geometry":{"type":"Point","coordinates":[7.197295684210531,47.468645789473676]}}]}