{"type":"FeatureCollection","features":[{"type":"Feature","properties":{"codesPostaux":["68210"],"population":256,"nom":"Elbach","code":"68079"},"geometry":{"type":"Point","coordinates":[7.071129833333335,47.64223866666668]}}]}