{"type":"FeatureCollection","features":[{"type":"Feature","properties":{"codesPostaux":["68480"],"population":872,"nom":"Durmenach","code":"68075"},"geometry":{"type":"Point","coordinates":[7.340356078431373,47.527494313725484]}}]}