{"type":"FeatureCollection","features":[{"type":"Feature","properties":{"codesPostaux":["68470"],"population":1682,"nom":"Fellering","code":"68089"},"geometry":{"type":"Point","coordinates":[6.967873980263162,47.91886289473686]}}]}