{"type":"FeatureCollection","features":[{"type":"Feature","properties":{"codesPostaux":["68210"],"population":384,"nom":"Eteimbes","code":"68085"},"geometry":{"type":"Point","coordinates":[7.044046393442624,47.70342377049181]}}]}