{"type":"FeatureCollection","features":[{"type":"Feature","properties":{"codesPostaux":["68640"],"population":454,"nom":"Feldbach","code":"68087"},"geometry":{"type":"Point","coordinates":[7.254795365853657,47.534001219512206]}}]}