{"type":"FeatureCollection","features":[{"type":"Feature","properties":{"codesPostaux":["68130"],"population":276,"nom":"Emlingen","code":"68080"},"geometry":{"type":"Point","coordinates":[7.291679607843137,47.626393725490196]}}]}