{"type":"FeatureCollection","features":[{"type":"Feature","properties":{"codesPostaux":["68720"],"population":542,"nom":"Saint-Bernard","code":"68081"},"geometry":{"type":"Point","coordinates":[7.204144936708863,47.66617151898735]}}]}