{"type":"FeatureCollection","features":[{"type":"Feature","properties":{"codesPostaux":["68480"],"population":731,"nom":"Ferrette","code":"68090"},"geometry":{"type":"Point","coordinates":[7.314210379746834,47.49301924050633]}}]}