{"type":"FeatureCollection","features":[{"type":"Feature","properties":{"codesPostaux":["68320"],"population":1154,"nom":"Fortschwihr","code":"68095"},"geometry":{"type":"Point","coordinates":[7.4501493750000005,48.08614125]}}]}