{"type":"FeatureCollection","features":[{"type":"Feature","properties":{"codesPostaux":["68740"],"population":2323,"nom":"Fessenheim","code":"68091"},"geometry":{"type":"Point","coordinates":[7.5277919354838705,47.90905193548387]}}]}