{"type":"FeatureCollection","features":[{"type":"Feature","properties":{"codesPostaux":["68440"],"population":4881,"nom":"Habsheim","code":"68118"},"geometry":{"type":"Point","coordinates":[7.410289999999999,47.726783815789474]}}]}