{"type":"FeatureCollection","features":[{"type":"Feature","properties":{"codesPostaux":["68116"],"population":1349,"nom":"Guewenheim","code":"68115"},"geometry":{"type":"Point","coordinates":[7.091245689655174,47.75059353448276]}}]}