{"type":"FeatureCollection","features":[{"type":"Feature","properties":{"codesPostaux":["68220"],"population":638,"nom":"Hagenthal-le-Haut","code":"68121"},"geometry":{"type":"Point","coordinates":[7.453336216216218,47.51824351351351]}}]}