{"type":"FeatureCollection","features":[{"type":"Feature","properties":{"codesPostaux":["68240"],"population":4634,"nom":"Kaysersberg Vignoble","code":"68162"},"geometry":{"type":"Point","coordinates":[7.271765188679245,48.14736207547167]}}]}