{"type":"FeatureCollection","features":[{"type":"Feature","properties":{"codesPostaux":["68480"],"population":509,"nom":"K\u0153stlach","code":"68169"},"geometry":{"type":"Point","coordinates":[7.270365365853658,47.51624378048782]}}]}