{"type":"FeatureCollection","features":[{"type":"Feature","properties":{"codesPostaux":["68480"],"population":236,"nom":"Kiffis","code":"68165"},"geometry":{"type":"Point","coordinates":[7.353885842696627,47.439932808988786]}}]}