{"type":"FeatureCollection","features":[{"type":"Feature","properties":{"codesPostaux":["68320"],"population":1781,"nom":"Kunheim","code":"68172"},"geometry":{"type":"Point","coordinates":[7.543819215686274,48.075594313725496]}}]}