{"type":"FeatureCollection","features":[{"type":"Feature","properties":{"codesPostaux":["68280"],"population":836,"nom":"Logelheim","code":"68189"},"geometry":{"type":"Point","coordinates":[7.416065744680854,48.02142]}}]}