{"type":"FeatureCollection","features":[{"type":"Feature","properties":{"codesPostaux":["68780"],"population":903,"nom":"Le Haut Soultzbach","code":"68219"},"geometry":{"type":"Point","coordinates":[7.059083831775703,47.73308766355139]}}]}