{"type":"FeatureCollection","features":[{"type":"Feature","properties":{"codesPostaux":["68640"],"population":1050,"nom":"Muespach-le-Haut","code":"68222"},"geometry":{"type":"Point","coordinates":[7.408444880952381,47.54098702380952]}}]}