{"type":"FeatureCollection","features":[{"type":"Feature","properties":{"codesPostaux":["68220"],"population":514,"nom":"Neuwiller","code":"68232"},"geometry":{"type":"Point","coordinates":[7.512074406779662,47.52547186440679]}}]}