{"type":"FeatureCollection","features":[{"type":"Feature","properties":{"codesPostaux":["68230"],"population":539,"nom":"Niedermorschwihr","code":"68237"},"geometry":{"type":"Point","coordinates":[7.25627701492537,48.10036686567165]}}]}