{"type":"FeatureCollection","features":[{"type":"Feature","properties":{"codesPostaux":["68420"],"population":360,"nom":"Obermorschwihr","code":"68244"},"geometry":{"type":"Point","coordinates":[7.293015625000001,48.02336265625]}}]}