{"type":"FeatureCollection","features":[{"type":"Feature","properties":{"codesPostaux":["68480"],"population":729,"nom":"Oltingue","code":"68248"},"geometry":{"type":"Point","coordinates":[7.398941162790701,47.4906176744186]}}]}