{"type":"FeatureCollection","features":[{"type":"Feature","properties":{"codesPostaux":["68600"],"population":1020,"nom":"Obersaasheim","code":"68246"},"geometry":{"type":"Point","coordinates":[7.567381139240507,47.983610253164564]}}]}