{"type":"FeatureCollection","features":[{"type":"Feature","properties":{"codesPostaux":["68890"],"population":1818,"nom":"R\u00e9guisheim","code":"68266"},"geometry":{"type":"Point","coordinates":[7.348248584070801,47.89041699115043]}}]}