{"type":"FeatureCollection","features":[{"type":"Feature","properties":{"codesPostaux":["68210"],"population":232,"nom":"Romagny","code":"68282"},"geometry":{"type":"Point","coordinates":[7.069649655172414,47.60897367816093]}}]}