{"type":"FeatureCollection","features":[{"type":"Feature","properties":{"codesPostaux":["68590"],"population":335,"nom":"Rodern","code":"68280"},"geometry":{"type":"Point","coordinates":[7.311212335766422,48.23755131386861]}}]}