{"type":"FeatureCollection","features":[{"type":"Feature","properties":{"codesPostaux":["68590"],"population":1029,"nom":"Saint-Hippolyte","code":"68296"},"geometry":{"type":"Point","coordinates":[7.352579116279069,48.23624809302324]}}]}