{"type":"FeatureCollection","features":[{"type":"Feature","properties":{"codesPostaux":["68440"],"population":1145,"nom":"Schlierbach","code":"68301"},"geometry":{"type":"Point","coordinates":[7.409205223880598,47.67834238805971]}}]}