{"type":"FeatureCollection","features":[{"type":"Feature","properties":{"codesPostaux":["68470"],"population":228,"nom":"Storckensohn","code":"68328"},"geometry":{"type":"Point","coordinates":[6.940341034482761,47.86403885057471]}}]}