{"type":"FeatureCollection","features":[{"type":"Feature","properties":{"codesPostaux":["68700"],"population":1363,"nom":"Steinbach","code":"68322"},"geometry":{"type":"Point","coordinates":[7.136807441860468,47.824600581395366]}}]}