{"type":"FeatureCollection","features":[{"type":"Feature","properties":{"codesPostaux":["68580"],"population":374,"nom":"Ueberstrass","code":"68340"},"geometry":{"type":"Point","coordinates":[7.1468826829268295,47.54565658536587]}}]}