{"type":"FeatureCollection","features":[{"type":"Feature","properties":{"codesPostaux":["68510"],"population":869,"nom":"Uffheim","code":"68341"},"geometry":{"type":"Point","coordinates":[7.4419174285714265,47.64658571428572]}}]}