{"type":"FeatureCollection","features":[{"type":"Feature","properties":{"codesPostaux":["68190"],"population":2080,"nom":"Ungersheim","code":"68343"},"geometry":{"type":"Point","coordinates":[7.306954814814818,47.87329777777779]}}]}