{"type":"FeatureCollection","features":[{"type":"Feature","properties":{"codesPostaux":["68510"],"population":565,"nom":"Waltenheim","code":"68357"},"geometry":{"type":"Point","coordinates":[7.424197826086958,47.65522565217392]}}]}