{"type":"FeatureCollection","features":[{"type":"Feature","properties":{"codesPostaux":["68230"],"population":1270,"nom":"Wihr-au-Val","code":"68368"},"geometry":{"type":"Point","coordinates":[7.199104336283185,48.055748761061956]}}]}