{"type":"FeatureCollection","features":[{"type":"Feature","properties":{"codesPostaux":["68130"],"population":830,"nom":"Wittersdorf","code":"68377"},"geometry":{"type":"Point","coordinates":[7.273237638888888,47.616254861111116]}}]}