{"type":"FeatureCollection","features":[{"type":"Feature","properties":{"codesPostaux":["69250"],"population":2804,"nom":"Albigny-sur-Sa\u00f4ne","code":"69003"},"geometry":{"type":"Point","coordinates":[4.8283033333333325,45.86661888888889]}}]}