{"type":"FeatureCollection","features":[{"type":"Feature","properties":{"codesPostaux":["69380"],"population":746,"nom":"Alix","code":"69004"},"geometry":{"type":"Point","coordinates":[4.6539415686274515,45.91507098039216]}}]}