{"type":"FeatureCollection","features":[{"type":"Feature","properties":{"codesPostaux":["69610"],"population":1115,"nom":"Aveize","code":"69014"},"geometry":{"type":"Point","coordinates":[4.473522357142858,45.678045]}}]}