{"type":"FeatureCollection","features":[{"type":"Feature","properties":{"codesPostaux":["69300"],"population":42581,"nom":"Caluire-et-Cuire","code":"69034"},"geometry":{"type":"Point","coordinates":[4.8525255000000005,45.797654625000014]}}]}