{"type":"FeatureCollection","features":[{"type":"Feature","properties":{"codesPostaux":["69270"],"population":2598,"nom":"Couzon-au-Mont-d'Or","code":"69068"},"geometry":{"type":"Point","coordinates":[4.820484,45.84801155555555]}}]}