{"type":"FeatureCollection","features":[{"type":"Feature","properties":{"codesPostaux":["69490"],"population":455,"nom":"Dareiz\u00e9","code":"69073"},"geometry":{"type":"Point","coordinates":[4.489424857142856,45.90660857142856]}}]}