{"type":"FeatureCollection","features":[{"type":"Feature","properties":{"codesPostaux":["69430"],"population":852,"nom":"Lantigni\u00e9","code":"69109"},"geometry":{"type":"Point","coordinates":[4.6131812765957445,46.15149659574469]}}]}