{"type":"FeatureCollection","features":[{"type":"Feature","properties":{"codesPostaux":["69380"],"population":2611,"nom":"Lozanne","code":"69121"},"geometry":{"type":"Point","coordinates":[4.681642428571428,45.856962999999986]}}]}