{"type":"FeatureCollection","features":[{"type":"Feature","properties":{"codesPostaux":["69770"],"population":1322,"nom":"Montrottier","code":"69139"},"geometry":{"type":"Point","coordinates":[4.459084914285718,45.79640428571428]}}]}