{"type":"FeatureCollection","features":[{"type":"Feature","properties":{"codesPostaux":["69530"],"population":2308,"nom":"Orli\u00e9nas","code":"69148"},"geometry":{"type":"Point","coordinates":[4.728518543689319,45.659445145631075]}}]}