{"type":"FeatureCollection","features":[{"type":"Feature","properties":{"codesPostaux":["69440"],"population":304,"nom":"Riverie","code":"69166"},"geometry":{"type":"Point","coordinates":[4.5892604,45.59861839999999]}}]}