{"type":"FeatureCollection","features":[{"type":"Feature","properties":{"codesPostaux":["69460"],"population":823,"nom":"Salles-Arbuissonnas-en-Beaujolais","code":"69172"},"geometry":{"type":"Point","coordinates":[4.632011818181819,46.04655818181819]}}]}