{"type":"FeatureCollection","features":[{"type":"Feature","properties":{"codesPostaux":["69560"],"population":1868,"nom":"Sainte-Colombe","code":"69189"},"geometry":{"type":"Point","coordinates":[4.8571680555555545,45.52441805555556]}}]}