{"type":"FeatureCollection","features":[{"type":"Feature","properties":{"codesPostaux":["69870"],"population":301,"nom":"Saint-Bonnet-le-Troncy","code":"69183"},"geometry":{"type":"Point","coordinates":[4.412682394366199,46.07287816901406]}}]}