{"type":"FeatureCollection","features":[{"type":"Feature","properties":{"codesPostaux":["69460"],"population":727,"nom":"Saint-\u00c9tienne-la-Varenne","code":"69198"},"geometry":{"type":"Point","coordinates":[4.6185811538461525,46.08215153846155]}}]}