{"type":"FeatureCollection","features":[{"type":"Feature","properties":{"codesPostaux":["69870"],"population":136,"nom":"Saint-Cyr-le-Chatoux","code":"69192"},"geometry":{"type":"Point","coordinates":[4.535007849462366,46.0318682795699]}}]}