{"type":"FeatureCollection","features":[{"type":"Feature","properties":{"codesPostaux":["69190"],"population":17584,"nom":"Saint-Fons","code":"69199"},"geometry":{"type":"Point","coordinates":[4.855940425531914,45.70131127659573]}}]}