{"type":"FeatureCollection","features":[{"type":"Feature","properties":{"codesPostaux":["69560"],"population":1270,"nom":"Saint-Cyr-sur-le-Rh\u00f4ne","code":"69193"},"geometry":{"type":"Point","coordinates":[4.831535666666667,45.51926766666666]}}]}