{"type":"FeatureCollection","features":[{"type":"Feature","properties":{"codesPostaux":["69230"],"population":20696,"nom":"Saint-Genis-Laval","code":"69204"},"geometry":{"type":"Point","coordinates":[4.791344806201548,45.68925496124031]}}]}