{"type":"FeatureCollection","features":[{"type":"Feature","properties":{"codesPostaux":["69790"],"population":600,"nom":"Saint-Igny-de-Vers","code":"69209"},"geometry":{"type":"Point","coordinates":[4.437592617801045,46.231227329842916]}}]}