{"type":"FeatureCollection","features":[{"type":"Feature","properties":{"codesPostaux":["69650"],"population":2929,"nom":"Saint-Germain-au-Mont-d'Or","code":"69207"},"geometry":{"type":"Point","coordinates":[4.79805867647059,45.88465058823529]}}]}