{"type":"FeatureCollection","features":[{"type":"Feature","properties":{"codesPostaux":["69380"],"population":408,"nom":"Saint-Jean-des-Vignes","code":"69212"},"geometry":{"type":"Point","coordinates":[4.684097118644069,45.87549474576272]}}]}