{"type":"FeatureCollection","features":[{"type":"Feature","properties":{"codesPostaux":["69870"],"population":754,"nom":"Saint-Just-d'Avray","code":"69217"},"geometry":{"type":"Point","coordinates":[4.460532919708029,46.001048905109506]}}]}