{"type":"FeatureCollection","features":[{"type":"Feature","properties":{"codesPostaux":["69440"],"population":4047,"nom":"Chabani\u00e8re","code":"69228"},"geometry":{"type":"Point","coordinates":[4.623239446494464,45.587118265682676]}}]}