{"type":"FeatureCollection","features":[{"type":"Feature","properties":{"codesPostaux":["69590"],"population":3566,"nom":"Saint-Symphorien-sur-Coise","code":"69238"},"geometry":{"type":"Point","coordinates":[4.449989578947367,45.63112168421055]}}]}