{"type":"FeatureCollection","features":[{"type":"Feature","properties":{"codesPostaux":["69620"],"population":1113,"nom":"Saint-V\u00e9rand","code":"69239"},"geometry":{"type":"Point","coordinates":[4.522809354838709,45.92030916129033]}}]}