{"type":"FeatureCollection","features":[{"type":"Feature","properties":{"codesPostaux":["69890"],"population":3922,"nom":"La Tour-de-Salvagny","code":"69250"},"geometry":{"type":"Point","coordinates":[4.717345727272726,45.80483763636366]}}]}