{"type":"FeatureCollection","features":[{"type":"Feature","properties":{"codesPostaux":["69360"],"population":4128,"nom":"Communay","code":"69272"},"geometry":{"type":"Point","coordinates":[4.835234769230768,45.59464184615385]}}]}