{"type":"FeatureCollection","features":[{"type":"Feature","properties":{"codesPostaux":["69970"],"population":3869,"nom":"Chaponnay","code":"69270"},"geometry":{"type":"Point","coordinates":[4.95058635135135,45.62508256756758]}}]}