{"type":"FeatureCollection","features":[{"type":"Feature","properties":{"codesPostaux":["69250"],"population":2934,"nom":"Montanay","code":"69284"},"geometry":{"type":"Point","coordinates":[4.868817605633805,45.87577859154929]}}]}