{"type":"FeatureCollection","features":[{"type":"Feature","properties":{"codesPostaux":["69360"],"population":5382,"nom":"Ternay","code":"69297"},"geometry":{"type":"Point","coordinates":[4.811353157894734,45.60791631578949]}}]}