{"type":"FeatureCollection","features":[{"type":"Feature","properties":{"codesPostaux":["70100"],"population":482,"nom":"Ancier","code":"70018"},"geometry":{"type":"Point","coordinates":[5.636248985507246,47.44500971014493]}}]}