{"type":"FeatureCollection","features":[{"type":"Feature","properties":{"codesPostaux":["70120"],"population":253,"nom":"Arbecey","code":"70025"},"geometry":{"type":"Point","coordinates":[5.929014680851062,47.74362432624115]}}]}