{"type":"FeatureCollection","features":[{"type":"Feature","properties":{"codesPostaux":["70000"],"population":429,"nom":"Auxon","code":"70044"},"geometry":{"type":"Point","coordinates":[6.157226028368796,47.6968756028369]}}]}