{"type":"FeatureCollection","features":[{"type":"Feature","properties":{"codesPostaux":["70100"],"population":246,"nom":"Auvet-et-la-Chapelotte","code":"70043"},"geometry":{"type":"Point","coordinates":[5.5309582905982895,47.50456914529915]}}]}