{"type":"FeatureCollection","features":[{"type":"Feature","properties":{"codesPostaux":["70800"],"population":134,"nom":"Bassigney","code":"70052"},"geometry":{"type":"Point","coordinates":[6.1839972881355925,47.826803813559316]}}]}