{"type":"FeatureCollection","features":[{"type":"Feature","properties":{"codesPostaux":["70230"],"population":77,"nom":"Besnans","code":"70065"},"geometry":{"type":"Point","coordinates":[6.252182622950818,47.4497955737705]}}]}