{"type":"FeatureCollection","features":[{"type":"Feature","properties":{"codesPostaux":["70110"],"population":236,"nom":"Borey","code":"70077"},"geometry":{"type":"Point","coordinates":[6.357124651162792,47.58753333333331]}}]}