{"type":"FeatureCollection","features":[{"type":"Feature","properties":{"codesPostaux":["70400"],"population":617,"nom":"Brevilliers","code":"70096"},"geometry":{"type":"Point","coordinates":[6.7915759740259745,47.5804948051948]}}]}