{"type":"FeatureCollection","features":[{"type":"Feature","properties":{"codesPostaux":["70190"],"population":380,"nom":"Bussi\u00e8res","code":"70107"},"geometry":{"type":"Point","coordinates":[5.982015270270271,47.33751783783783]}}]}