{"type":"FeatureCollection","features":[{"type":"Feature","properties":{"codesPostaux":["70100"],"population":108,"nom":"Broye-les-Loups-et-Verfontaine","code":"70100"},"geometry":{"type":"Point","coordinates":[5.433712228915662,47.452732710843385]}}]}