{"type":"FeatureCollection","features":[{"type":"Feature","properties":{"codesPostaux":["70500"],"population":33,"nom":"Chauvirey-le-Vieil","code":"70144"},"geometry":{"type":"Point","coordinates":[5.762187216494845,47.784714123711325]}}]}