{"type":"FeatureCollection","features":[{"type":"Feature","properties":{"codesPostaux":["70170"],"population":138,"nom":"Chaux-l\u00e8s-Port","code":"70146"},"geometry":{"type":"Point","coordinates":[6.047439677419354,47.71796161290321]}}]}