{"type":"FeatureCollection","features":[{"type":"Feature","properties":{"codesPostaux":["70190"],"population":353,"nom":"Cirey","code":"70154"},"geometry":{"type":"Point","coordinates":[6.132938819444446,47.41324590277773]}}]}