{"type":"FeatureCollection","features":[{"type":"Feature","properties":{"codesPostaux":["70160"],"population":126,"nom":"Contr\u00e9glise","code":"70170"},"geometry":{"type":"Point","coordinates":[6.0267178823529415,47.838127529411764]}}]}