{"type":"FeatureCollection","features":[{"type":"Feature","properties":{"codesPostaux":["70400"],"population":207,"nom":"\u00c9chavanne","code":"70205"},"geometry":{"type":"Point","coordinates":[6.728200747663551,47.656421588785065]}}]}