{"type":"FeatureCollection","features":[{"type":"Feature","properties":{"codesPostaux":["70110"],"population":712,"nom":"Esprels","code":"70219"},"geometry":{"type":"Point","coordinates":[6.370329999999998,47.5377865289256]}}]}