{"type":"FeatureCollection","features":[{"type":"Feature","properties":{"codesPostaux":["70310"],"population":99,"nom":"Esmouli\u00e8res","code":"70217"},"geometry":{"type":"Point","coordinates":[6.616180690690695,47.85323840840841]}}]}