{"type":"FeatureCollection","features":[{"type":"Feature","properties":{"codesPostaux":["70270"],"population":152,"nom":"\u00c9cromagny","code":"70210"},"geometry":{"type":"Point","coordinates":[6.570999011627903,47.79411372093021]}}]}