{"type":"FeatureCollection","features":[{"type":"Feature","properties":{"codesPostaux":["70300"],"population":252,"nom":"\u00c9huns","code":"70213"},"geometry":{"type":"Point","coordinates":[6.299016446280992,47.76617471074382]}}]}