{"type":"FeatureCollection","features":[{"type":"Feature","properties":{"codesPostaux":["70800"],"population":133,"nom":"Fleurey-l\u00e8s-Saint-Loup","code":"70238"},"geometry":{"type":"Point","coordinates":[6.29201658536585,47.922855203252034]}}]}