{"type":"FeatureCollection","features":[{"type":"Feature","properties":{"codesPostaux":["70800"],"population":117,"nom":"Francalmont","code":"70249"},"geometry":{"type":"Point","coordinates":[6.275084174757281,47.82924932038837]}}]}