{"type":"FeatureCollection","features":[{"type":"Feature","properties":{"codesPostaux":["70270"],"population":744,"nom":"Fresse","code":"70256"},"geometry":{"type":"Point","coordinates":[6.666920872483223,47.763752416107366]}}]}