{"type":"FeatureCollection","features":[{"type":"Feature","properties":{"codesPostaux":["70100"],"population":5555,"nom":"Gray","code":"70279"},"geometry":{"type":"Point","coordinates":[5.610037708333329,47.43391975000002]}}]}