{"type":"FeatureCollection","features":[{"type":"Feature","properties":{"codesPostaux":["70110"],"population":422,"nom":"Gouhenans","code":"70271"},"geometry":{"type":"Point","coordinates":[6.486751180555556,47.61312951388888]}}]}