{"type":"FeatureCollection","features":[{"type":"Feature","properties":{"codesPostaux":["70200"],"population":405,"nom":"Lomont","code":"70306"},"geometry":{"type":"Point","coordinates":[6.594585251396647,47.621927541899424]}}]}