{"type":"FeatureCollection","features":[{"type":"Feature","properties":{"codesPostaux":["70200"],"population":390,"nom":"Lyoffans","code":"70313"},"geometry":{"type":"Point","coordinates":[6.590018532110089,47.64436522935781]}}]}