{"type":"FeatureCollection","features":[{"type":"Feature","properties":{"codesPostaux":["70300"],"population":168,"nom":"Magnivray","code":"70314"},"geometry":{"type":"Point","coordinates":[6.466552688172043,47.78234473118279]}}]}