{"type":"FeatureCollection","features":[{"type":"Feature","properties":{"codesPostaux":["70200"],"population":1345,"nom":"Magny-Vernois","code":"70321"},"geometry":{"type":"Point","coordinates":[6.474595357142857,47.66901892857145]}}]}