{"type":"FeatureCollection","features":[{"type":"Feature","properties":{"codesPostaux":["70160"],"population":291,"nom":"Mersuay","code":"70343"},"geometry":{"type":"Point","coordinates":[6.141628842592593,47.78582578703703]}}]}