{"type":"FeatureCollection","features":[{"type":"Feature","properties":{"codesPostaux":["70110"],"population":225,"nom":"Moimay","code":"70349"},"geometry":{"type":"Point","coordinates":[6.399285326086956,47.559455108695644]}}]}