{"type":"FeatureCollection","features":[{"type":"Feature","properties":{"codesPostaux":["70000"],"population":254,"nom":"Montcey","code":"70358"},"geometry":{"type":"Point","coordinates":[6.238256470588236,47.65495811764705]}}]}