{"type":"FeatureCollection","features":[{"type":"Feature","properties":{"codesPostaux":["70120"],"population":62,"nom":"Mont-Saint-L\u00e9ger","code":"70369"},"geometry":{"type":"Point","coordinates":[5.795909142857142,47.63653000000001]}}]}