{"type":"FeatureCollection","features":[{"type":"Feature","properties":{"codesPostaux":["70120"],"population":265,"nom":"La Roche-Morey","code":"70373"},"geometry":{"type":"Point","coordinates":[5.7536546632124335,47.69304155440414]}}]}