{"type":"FeatureCollection","features":[{"type":"Feature","properties":{"codesPostaux":["70000"],"population":2025,"nom":"Noidans-l\u00e8s-Vesoul","code":"70388"},"geometry":{"type":"Point","coordinates":[6.1207162790697645,47.613956046511625]}}]}