{"type":"FeatureCollection","features":[{"type":"Feature","properties":{"codesPostaux":["70200"],"population":335,"nom":"La Neuvelle-l\u00e8s-Lure","code":"70385"},"geometry":{"type":"Point","coordinates":[6.551200714285712,47.71436488095239]}}]}