{"type":"FeatureCollection","features":[{"type":"Feature","properties":{"codesPostaux":["70110"],"population":62,"nom":"Oppenans","code":"70395"},"geometry":{"type":"Point","coordinates":[6.383686315789473,47.58708947368421]}}]}