{"type":"FeatureCollection","features":[{"type":"Feature","properties":{"codesPostaux":["70500"],"population":224,"nom":"Ormoy","code":"70399"},"geometry":{"type":"Point","coordinates":[5.987408877551021,47.881967091836735]}}]}