{"type":"FeatureCollection","features":[{"type":"Feature","properties":{"codesPostaux":["70200"],"population":213,"nom":"Palante","code":"70403"},"geometry":{"type":"Point","coordinates":[6.5814151898734154,47.664879746835446]}}]}