{"type":"FeatureCollection","features":[{"type":"Feature","properties":{"codesPostaux":["70500"],"population":119,"nom":"Ouge","code":"70400"},"geometry":{"type":"Point","coordinates":[5.703305933333334,47.799828866666694]}}]}