{"type":"FeatureCollection","features":[{"type":"Feature","properties":{"codesPostaux":["70500"],"population":24,"nom":"Ranzevelle","code":"70437"},"geometry":{"type":"Point","coordinates":[5.982493541666667,47.9073225]}}]}