{"type":"FeatureCollection","features":[{"type":"Feature","properties":{"codesPostaux":["70000"],"population":341,"nom":"Raze","code":"70439"},"geometry":{"type":"Point","coordinates":[5.997944756097564,47.58217975609757]}}]}