{"type":"FeatureCollection","features":[{"type":"Feature","properties":{"codesPostaux":["70280"],"population":954,"nom":"Raddon-et-Chapendu","code":"70435"},"geometry":{"type":"Point","coordinates":[6.4572142857142865,47.85258809523808]}}]}