{"type":"FeatureCollection","features":[{"type":"Feature","properties":{"codesPostaux":["70190"],"population":247,"nom":"Recologne-l\u00e8s-Rioz","code":"70441"},"geometry":{"type":"Point","coordinates":[5.989230387096774,47.46898309677422]}}]}