{"type":"FeatureCollection","features":[{"type":"Feature","properties":{"codesPostaux":["70200"],"population":104,"nom":"Rignovelle","code":"70445"},"geometry":{"type":"Point","coordinates":[6.476347321428574,47.76597375000001]}}]}