{"type":"FeatureCollection","features":[{"type":"Feature","properties":{"codesPostaux":["70120"],"population":39,"nom":"La Rochelle","code":"70450"},"geometry":{"type":"Point","coordinates":[5.73005771428571,47.74940971428569]}}]}