{"type":"FeatureCollection","features":[{"type":"Feature","properties":{"codesPostaux":["70110"],"population":78,"nom":"Saint-Ferjeux","code":"70462"},"geometry":{"type":"Point","coordinates":[6.5046212307692315,47.54540784615385]}}]}