{"type":"FeatureCollection","features":[{"type":"Feature","properties":{"codesPostaux":["70300"],"population":171,"nom":"Sainte-Marie-en-Chaux","code":"70470"},"geometry":{"type":"Point","coordinates":[6.300383617021278,47.795918936170224]}}]}