{"type":"FeatureCollection","features":[{"type":"Feature","properties":{"codesPostaux":["70300"],"population":243,"nom":"Saint-Valbert","code":"70475"},"geometry":{"type":"Point","coordinates":[6.395830821917809,47.85854342465755]}}]}