{"type":"FeatureCollection","features":[{"type":"Feature","properties":{"codesPostaux":["70190"],"population":423,"nom":"Sorans-l\u00e8s-Breurey","code":"70493"},"geometry":{"type":"Point","coordinates":[6.0592252892562,47.38834396694216]}}]}