{"type":"FeatureCollection","features":[{"type":"Feature","properties":{"codesPostaux":["70120"],"population":109,"nom":"Theuley","code":"70499"},"geometry":{"type":"Point","coordinates":[5.815539696969698,47.621294141414154]}}]}