{"type":"FeatureCollection","features":[{"type":"Feature","properties":{"codesPostaux":["70240"],"population":114,"nom":"Servigney","code":"70490"},"geometry":{"type":"Point","coordinates":[6.295652499999999,47.72781749999999]}}]}