{"type":"FeatureCollection","features":[{"type":"Feature","properties":{"codesPostaux":["70230"],"population":92,"nom":"Thi\u00e9nans","code":"70501"},"geometry":{"type":"Point","coordinates":[6.278255578947367,47.47242589473684]}}]}