{"type":"FeatureCollection","features":[{"type":"Feature","properties":{"codesPostaux":["70120"],"population":85,"nom":"Tincey-et-Pontrebeau","code":"70502"},"geometry":{"type":"Point","coordinates":[5.7881800917431185,47.60376513761468]}}]}