{"type":"FeatureCollection","features":[{"type":"Feature","properties":{"codesPostaux":["70130"],"population":93,"nom":"Vanne","code":"70520"},"geometry":{"type":"Point","coordinates":[5.851802500000001,47.59978309523809]}}]}