{"type":"FeatureCollection","features":[{"type":"Feature","properties":{"codesPostaux":["70240"],"population":140,"nom":"Varogne","code":"70522"},"geometry":{"type":"Point","coordinates":[6.2112731896551745,47.7179479310345]}}]}