{"type":"FeatureCollection","features":[{"type":"Feature","properties":{"codesPostaux":["70240"],"population":135,"nom":"La Villeneuve-Bellenoye-et-la-Maize","code":"70558"},"geometry":{"type":"Point","coordinates":[6.240040694444441,47.70923541666666]}}]}