{"type":"FeatureCollection","features":[{"type":"Feature","properties":{"codesPostaux":["70700"],"population":136,"nom":"Villefrancon","code":"70557"},"geometry":{"type":"Point","coordinates":[5.744233539823008,47.41537168141594]}}]}