{"type":"FeatureCollection","features":[{"type":"Feature","properties":{"codesPostaux":["70500"],"population":277,"nom":"Vitrey-sur-Mance","code":"70572"},"geometry":{"type":"Point","coordinates":[5.7568948255813925,47.81192837209306]}}]}