{"type":"FeatureCollection","features":[{"type":"Feature","properties":{"codesPostaux":["70310"],"population":142,"nom":"La Voivre","code":"70573"},"geometry":{"type":"Point","coordinates":[6.557867434782608,47.82161539130435]}}]}