{"type":"FeatureCollection","features":[{"type":"Feature","properties":{"codesPostaux":["71400"],"population":13863,"nom":"Autun","code":"71014"},"geometry":{"type":"Point","coordinates":[4.305068216704287,46.9482748081264]}}]}