{"type":"FeatureCollection","features":[{"type":"Feature","properties":{"codesPostaux":["71640"],"population":130,"nom":"Barizey","code":"71019"},"geometry":{"type":"Point","coordinates":[4.670277027027027,46.792240810810824]}}]}