{"type":"FeatureCollection","features":[{"type":"Feature","properties":{"codesPostaux":["71270"],"population":273,"nom":"Bellevesvre","code":"71029"},"geometry":{"type":"Point","coordinates":[5.3633718435754165,46.847127262569835]}}]}