{"type":"FeatureCollection","features":[{"type":"Feature","properties":{"codesPostaux":["71270"],"population":116,"nom":"Beauvernois","code":"71028"},"geometry":{"type":"Point","coordinates":[5.442019044117648,46.84600022058822]}}]}