{"type":"FeatureCollection","features":[{"type":"Feature","properties":{"codesPostaux":["71250"],"population":210,"nom":"Bergesserin","code":"71030"},"geometry":{"type":"Point","coordinates":[4.562622554744526,46.39802094890511]}}]}