{"type":"FeatureCollection","features":[{"type":"Feature","properties":{"codesPostaux":["71620"],"population":795,"nom":"Bey","code":"71033"},"geometry":{"type":"Point","coordinates":[4.9722504,46.8208986]}}]}