{"type":"FeatureCollection","features":[{"type":"Feature","properties":{"codesPostaux":["71250"],"population":260,"nom":"Buffi\u00e8res","code":"71065"},"geometry":{"type":"Point","coordinates":[4.537552388059702,46.4266591044776]}}]}