{"type":"FeatureCollection","features":[{"type":"Feature","properties":{"codesPostaux":["71100"],"population":45166,"nom":"Chalon-sur-Sa\u00f4ne","code":"71076"},"geometry":{"type":"Point","coordinates":[4.844095242718446,46.78945592233012]}}]}