{"type":"FeatureCollection","features":[{"type":"Feature","properties":{"codesPostaux":["71570"],"population":586,"nom":"Ch\u00e2nes","code":"71084"},"geometry":{"type":"Point","coordinates":[4.758491060606062,46.244434696969684]}}]}