{"type":"FeatureCollection","features":[{"type":"Feature","properties":{"codesPostaux":["71530"],"population":2395,"nom":"Champforgeuil","code":"71081"},"geometry":{"type":"Point","coordinates":[4.82929,46.816430112359555]}}]}