{"type":"FeatureCollection","features":[{"type":"Feature","properties":{"codesPostaux":["71500"],"population":559,"nom":"La Chapelle-Naude","code":"71092"},"geometry":{"type":"Point","coordinates":[5.197810686567162,46.58920083582089]}}]}