{"type":"FeatureCollection","features":[{"type":"Feature","properties":{"codesPostaux":["71700"],"population":199,"nom":"Chardonnay","code":"71100"},"geometry":{"type":"Point","coordinates":[4.850280948275858,46.508794396551735]}}]}