{"type":"FeatureCollection","features":[{"type":"Feature","properties":{"codesPostaux":["71270"],"population":444,"nom":"Charette-Varennes","code":"71101"},"geometry":{"type":"Point","coordinates":[5.195788842592594,46.898475555555535]}}]}