{"type":"FeatureCollection","features":[{"type":"Feature","properties":{"codesPostaux":["71380"],"population":1057,"nom":"Ch\u00e2tenoy-en-Bresse","code":"71117"},"geometry":{"type":"Point","coordinates":[4.915673150684931,46.79359726027398]}}]}