{"type":"FeatureCollection","features":[{"type":"Feature","properties":{"codesPostaux":["71250"],"population":30,"nom":"Ch\u00e9rizet","code":"71125"},"geometry":{"type":"Point","coordinates":[4.568690000000002,46.515538082191746]}}]}