{"type":"FeatureCollection","features":[{"type":"Feature","properties":{"codesPostaux":["71220"],"population":77,"nom":"Chevagny-sur-Guye","code":"71127"},"geometry":{"type":"Point","coordinates":[4.499737171717172,46.540210202020205]}}]}