{"type":"FeatureCollection","features":[{"type":"Feature","properties":{"codesPostaux":["71340"],"population":404,"nom":"Chenay-le-Ch\u00e2tel","code":"71123"},"geometry":{"type":"Point","coordinates":[3.939043205574912,46.229331463414645]}}]}