{"type":"FeatureCollection","features":[{"type":"Feature","properties":{"codesPostaux":["71460"],"population":245,"nom":"Chissey-l\u00e8s-M\u00e2con","code":"71130"},"geometry":{"type":"Point","coordinates":[4.745731709844558,46.52006259067361]}}]}