{"type":"FeatureCollection","features":[{"type":"Feature","properties":{"codesPostaux":["71420"],"population":2332,"nom":"Ciry-le-Noble","code":"71132"},"geometry":{"type":"Point","coordinates":[4.293245993690854,46.596884511041026]}}]}