{"type":"FeatureCollection","features":[{"type":"Feature","properties":{"codesPostaux":["71310"],"population":175,"nom":"Dampierre-en-Bresse","code":"71168"},"geometry":{"type":"Point","coordinates":[5.195713055555557,46.82764216666665]}}]}