{"type":"FeatureCollection","features":[{"type":"Feature","properties":{"codesPostaux":["71480"],"population":794,"nom":"Dommartin-l\u00e8s-Cuiseaux","code":"71177"},"geometry":{"type":"Point","coordinates":[5.288604072398187,46.501611266968325]}}]}