{"type":"FeatureCollection","features":[{"type":"Feature","properties":{"codesPostaux":["71240"],"population":452,"nom":"\u00c9trigny","code":"71193"},"geometry":{"type":"Point","coordinates":[4.785523510638297,46.5853614893617]}}]}