{"type":"FeatureCollection","features":[{"type":"Feature","properties":{"codesPostaux":["71360"],"population":2295,"nom":"\u00c9pinac","code":"71190"},"geometry":{"type":"Point","coordinates":[4.513845880281688,46.987999929577505]}}]}