{"type":"FeatureCollection","features":[{"type":"Feature","properties":{"codesPostaux":["71420"],"population":1380,"nom":"G\u00e9nelard","code":"71212"},"geometry":{"type":"Point","coordinates":[4.245939393939394,46.58233409090907]}}]}