{"type":"FeatureCollection","features":[{"type":"Feature","properties":{"codesPostaux":["71800"],"population":610,"nom":"Gibles","code":"71218"},"geometry":{"type":"Point","coordinates":[4.387548563218392,46.31284540229887]}}]}