{"type":"FeatureCollection","features":[{"type":"Feature","properties":{"codesPostaux":["71640"],"population":3661,"nom":"Givry","code":"71221"},"geometry":{"type":"Point","coordinates":[4.761554675925925,46.769460509259275]}}]}