{"type":"FeatureCollection","features":[{"type":"Feature","properties":{"codesPostaux":["71700"],"population":34,"nom":"Grevilly","code":"71226"},"geometry":{"type":"Point","coordinates":[4.8186701369863,46.51488520547945]}}]}