{"type":"FeatureCollection","features":[{"type":"Feature","properties":{"codesPostaux":["71570"],"population":509,"nom":"Leynes","code":"71258"},"geometry":{"type":"Point","coordinates":[4.730019764705881,46.26384705882354]}}]}