{"type":"FeatureCollection","features":[{"type":"Feature","properties":{"codesPostaux":["71270"],"population":136,"nom":"Lays-sur-le-Doubs","code":"71254"},"geometry":{"type":"Point","coordinates":[5.240051322314053,46.921714462809916]}}]}