{"type":"FeatureCollection","features":[{"type":"Feature","properties":{"codesPostaux":["71220"],"population":701,"nom":"Le Rousset-Marizy","code":"71279"},"geometry":{"type":"Point","coordinates":[4.431200449999997,46.57095814999999]}}]}