{"type":"FeatureCollection","features":[{"type":"Feature","properties":{"codesPostaux":["71240"],"population":389,"nom":"Mancey","code":"71274"},"geometry":{"type":"Point","coordinates":[4.845556643356643,46.569495034965044]}}]}