{"type":"FeatureCollection","features":[{"type":"Feature","properties":{"codesPostaux":["71240"],"population":521,"nom":"Marnay","code":"71283"},"geometry":{"type":"Point","coordinates":[4.915246590909091,46.70113556818182]}}]}