{"type":"FeatureCollection","features":[{"type":"Feature","properties":{"codesPostaux":["71700"],"population":120,"nom":"Martailly-l\u00e8s-Brancion","code":"71284"},"geometry":{"type":"Point","coordinates":[4.791003536585367,46.53440060975609]}}]}