{"type":"FeatureCollection","features":[{"type":"Feature","properties":{"codesPostaux":["71340"],"population":975,"nom":"Melay","code":"71291"},"geometry":{"type":"Point","coordinates":[4.007207572463767,46.20644221014492]}}]}