{"type":"FeatureCollection","features":[{"type":"Feature","properties":{"codesPostaux":["71710"],"population":2195,"nom":"Montcenis","code":"71309"},"geometry":{"type":"Point","coordinates":[4.392942983870968,46.78635346774197]}}]}