{"type":"FeatureCollection","features":[{"type":"Feature","properties":{"codesPostaux":["71270"],"population":174,"nom":"Mont-l\u00e8s-Seurre","code":"71315"},"geometry":{"type":"Point","coordinates":[5.1300303278688535,46.95215663934426]}}]}