{"type":"FeatureCollection","features":[{"type":"Feature","properties":{"codesPostaux":["71120"],"population":428,"nom":"Ozolles","code":"71339"},"geometry":{"type":"Point","coordinates":[4.350189946524066,46.39075695187166]}}]}