{"type":"FeatureCollection","features":[{"type":"Feature","properties":{"codesPostaux":["71420"],"population":401,"nom":"Oudry","code":"71334"},"geometry":{"type":"Point","coordinates":[4.1640904545454545,46.57621295454546]}}]}