{"type":"FeatureCollection","features":[{"type":"Feature","properties":{"codesPostaux":["71400"],"population":52,"nom":"La Petite-Verri\u00e8re","code":"71349"},"geometry":{"type":"Point","coordinates":[4.162909781420766,47.044352896174864]}}]}