{"type":"FeatureCollection","features":[{"type":"Feature","properties":{"codesPostaux":["71260"],"population":659,"nom":"P\u00e9ronne","code":"71345"},"geometry":{"type":"Point","coordinates":[4.802602727272726,46.43979181818181]}}]}