{"type":"FeatureCollection","features":[{"type":"Feature","properties":{"codesPostaux":["71700"],"population":593,"nom":"Plottes","code":"71353"},"geometry":{"type":"Point","coordinates":[4.884029813664597,46.53359546583851]}}]}