{"type":"FeatureCollection","features":[{"type":"Feature","properties":{"codesPostaux":["71800"],"population":69,"nom":"Prizy","code":"71361"},"geometry":{"type":"Point","coordinates":[4.218065263157892,46.352082368421044]}}]}