{"type":"FeatureCollection","features":[{"type":"Feature","properties":{"codesPostaux":["71150"],"population":450,"nom":"Remigny","code":"71369"},"geometry":{"type":"Point","coordinates":[4.723747321428571,46.91095517857143]}}]}