{"type":"FeatureCollection","features":[{"type":"Feature","properties":{"codesPostaux":["71160"],"population":690,"nom":"Rigny-sur-Arroux","code":"71370"},"geometry":{"type":"Point","coordinates":[4.022443958333334,46.54403291666669]}}]}