{"type":"FeatureCollection","features":[{"type":"Feature","properties":{"codesPostaux":["71580"],"population":763,"nom":"Saillenard","code":"71380"},"geometry":{"type":"Point","coordinates":[5.372117748691098,46.69866575916232]}}]}