{"type":"FeatureCollection","features":[{"type":"Feature","properties":{"codesPostaux":["71440"],"population":110,"nom":"Saint-Andr\u00e9-en-Bresse","code":"71386"},"geometry":{"type":"Point","coordinates":[5.086061348314607,46.64920101123595]}}]}