{"type":"FeatureCollection","features":[{"type":"Feature","properties":{"codesPostaux":["71510"],"population":564,"nom":"Saint-B\u00e9rain-sur-Dheune","code":"71391"},"geometry":{"type":"Point","coordinates":[4.611958095238099,46.81918557823129]}}]}