{"type":"FeatureCollection","features":[{"type":"Feature","properties":{"codesPostaux":["71240"],"population":755,"nom":"Saint-Cyr","code":"71402"},"geometry":{"type":"Point","coordinates":[4.893043928571427,46.68506910714285]}}]}