{"type":"FeatureCollection","features":[{"type":"Feature","properties":{"codesPostaux":["71350"],"population":441,"nom":"Saint-Gervais-en-Valli\u00e8re","code":"71423"},"geometry":{"type":"Point","coordinates":[4.959909276018098,46.953197104072366]}}]}