{"type":"FeatureCollection","features":[{"type":"Feature","properties":{"codesPostaux":["71210"],"population":1053,"nom":"Saint-Laurent-d'Andenay","code":"71436"},"geometry":{"type":"Point","coordinates":[4.515364,46.73144193103448]}}]}