{"type":"FeatureCollection","features":[{"type":"Feature","properties":{"codesPostaux":["71240"],"population":1125,"nom":"Saint-Loup-de-Varennes","code":"71444"},"geometry":{"type":"Point","coordinates":[4.8523088749999985,46.72325987500003]}}]}