{"type":"FeatureCollection","features":[{"type":"Feature","properties":{"codesPostaux":["71118"],"population":1336,"nom":"Saint-Martin-Belle-Roche","code":"71448"},"geometry":{"type":"Point","coordinates":[4.853275999999998,46.37934974999999]}}]}