{"type":"FeatureCollection","features":[{"type":"Feature","properties":{"codesPostaux":["71380"],"population":5962,"nom":"Saint-Marcel","code":"71445"},"geometry":{"type":"Point","coordinates":[4.895771573033705,46.77412966292137]}}]}