{"type":"FeatureCollection","features":[{"type":"Feature","properties":{"codesPostaux":["71490"],"population":123,"nom":"Saint-Martin-de-Commune","code":"71450"},"geometry":{"type":"Point","coordinates":[4.517110568720378,46.90346663507107]}}]}