{"type":"FeatureCollection","features":[{"type":"Feature","properties":{"codesPostaux":["71620"],"population":1919,"nom":"Saint-Martin-en-Bresse","code":"71456"},"geometry":{"type":"Point","coordinates":[5.0606810725552025,46.79998337539434]}}]}