{"type":"FeatureCollection","features":[{"type":"Feature","properties":{"codesPostaux":["71740"],"population":584,"nom":"Saint-Maurice-l\u00e8s-Ch\u00e2teauneuf","code":"71463"},"geometry":{"type":"Point","coordinates":[4.251988159999999,46.223339840000015]}}]}