{"type":"FeatureCollection","features":[{"type":"Feature","properties":{"codesPostaux":["71520"],"population":327,"nom":"Saint-Point","code":"71470"},"geometry":{"type":"Point","coordinates":[4.61727327272727,46.33700872727274]}}]}