{"type":"FeatureCollection","features":[{"type":"Feature","properties":{"codesPostaux":["71570"],"population":1119,"nom":"Saint-Symphorien-d'Ancelles","code":"71481"},"geometry":{"type":"Point","coordinates":[4.769558588235294,46.19818023529412]}}]}