{"type":"FeatureCollection","features":[{"type":"Feature","properties":{"codesPostaux":["71460"],"population":78,"nom":"Savianges","code":"71505"},"geometry":{"type":"Point","coordinates":[4.603190421052634,46.689641473684205]}}]}