{"type":"FeatureCollection","features":[{"type":"Feature","properties":{"codesPostaux":["71310"],"population":592,"nom":"Serley","code":"71516"},"geometry":{"type":"Point","coordinates":[5.237560496183208,46.78837423664126]}}]}