{"type":"FeatureCollection","features":[{"type":"Feature","properties":{"codesPostaux":["71110"],"population":653,"nom":"Semur-en-Brionnais","code":"71510"},"geometry":{"type":"Point","coordinates":[4.093020725806451,46.27464322580645]}}]}