{"type":"FeatureCollection","features":[{"type":"Feature","properties":{"codesPostaux":["71330"],"population":1217,"nom":"Simard","code":"71523"},"geometry":{"type":"Point","coordinates":[5.182092828685259,46.71617111553785]}}]}