{"type":"FeatureCollection","features":[{"type":"Feature","properties":{"codesPostaux":["71100"],"population":1385,"nom":"Sevrey","code":"71520"},"geometry":{"type":"Point","coordinates":[4.8230642519685025,46.738734960629934]}}]}