{"type":"FeatureCollection","features":[{"type":"Feature","properties":{"codesPostaux":["71330"],"population":125,"nom":"Le Tartre","code":"71534"},"geometry":{"type":"Point","coordinates":[5.352400810810812,46.74543391891892]}}]}