{"type":"FeatureCollection","features":[{"type":"Feature","properties":{"codesPostaux":["71360"],"population":521,"nom":"Sully","code":"71530"},"geometry":{"type":"Point","coordinates":[4.451839515151519,46.98201481818188]}}]}