{"type":"FeatureCollection","features":[{"type":"Feature","properties":{"codesPostaux":["71320"],"population":1610,"nom":"Toulon-sur-Arroux","code":"71542"},"geometry":{"type":"Point","coordinates":[4.155134172413796,46.691032172413784]}}]}