{"type":"FeatureCollection","features":[{"type":"Feature","properties":{"codesPostaux":["71800"],"population":585,"nom":"Varennes-sous-Dun","code":"71559"},"geometry":{"type":"Point","coordinates":[4.3373799305555565,46.27699888888892]}}]}