{"type":"FeatureCollection","features":[{"type":"Feature","properties":{"codesPostaux":["71600"],"population":681,"nom":"Varenne-Saint-Germain","code":"71557"},"geometry":{"type":"Point","coordinates":[4.0293676666666665,46.43674833333332]}}]}