{"type":"FeatureCollection","features":[{"type":"Feature","properties":{"codesPostaux":["71680"],"population":720,"nom":"Vinzelles","code":"71583"},"geometry":{"type":"Point","coordinates":[4.780107916666667,46.267129375]}}]}