{"type":"FeatureCollection","features":[{"type":"Feature","properties":{"codesPostaux":["72600"],"population":97,"nom":"Bl\u00e8ves","code":"72037"},"geometry":{"type":"Point","coordinates":[0.33454400000000006,48.448375777777784]}}]}