{"type":"FeatureCollection","features":[{"type":"Feature","properties":{"codesPostaux":["72160"],"population":530,"nom":"Beill\u00e9","code":"72031"},"geometry":{"type":"Point","coordinates":[0.5116280904522617,48.08229025125625]}}]}