{"type":"FeatureCollection","features":[{"type":"Feature","properties":{"codesPostaux":["72320"],"population":74,"nom":"Champrond","code":"72057"},"geometry":{"type":"Point","coordinates":[0.7501366666666665,48.08664019047617]}}]}