{"type":"FeatureCollection","features":[{"type":"Feature","properties":{"codesPostaux":["72500"],"population":422,"nom":"Chenu","code":"72077"},"geometry":{"type":"Point","coordinates":[0.352905229357798,47.60206486238532]}}]}