{"type":"FeatureCollection","features":[{"type":"Feature","properties":{"codesPostaux":["72610"],"population":216,"nom":"Chenay","code":"72076"},"geometry":{"type":"Point","coordinates":[0.1613854666666667,48.44895266666666]}}]}