{"type":"FeatureCollection","features":[{"type":"Feature","properties":{"codesPostaux":["72550"],"population":1078,"nom":"Chaufour-Notre-Dame","code":"72073"},"geometry":{"type":"Point","coordinates":[0.06198135869565218,48.01649777173917]}}]}