{"type":"FeatureCollection","features":[{"type":"Feature","properties":{"codesPostaux":["72500"],"population":6338,"nom":"Montval-sur-Loir","code":"72071"},"geometry":{"type":"Point","coordinates":[0.4224976804123713,47.69212546391754]}}]}