{"type":"FeatureCollection","features":[{"type":"Feature","properties":{"codesPostaux":["72120"],"population":546,"nom":"Conflans-sur-Anille","code":"72087"},"geometry":{"type":"Point","coordinates":[0.7207465432098764,47.96758123456791]}}]}