{"type":"FeatureCollection","features":[{"type":"Feature","properties":{"codesPostaux":["72130"],"population":457,"nom":"Coulombiers","code":"72097"},"geometry":{"type":"Point","coordinates":[0.12486313725490192,48.29419320261437]}}]}