{"type":"FeatureCollection","features":[{"type":"Feature","properties":{"codesPostaux":["72140"],"population":584,"nom":"Criss\u00e9","code":"72109"},"geometry":{"type":"Point","coordinates":[-0.06764937037037036,48.17959677777781]}}]}