{"type":"FeatureCollection","features":[{"type":"Feature","properties":{"codesPostaux":["72220"],"population":4658,"nom":"\u00c9commoy","code":"72124"},"geometry":{"type":"Point","coordinates":[0.28243077294686003,47.82124169082128]}}]}