{"type":"FeatureCollection","features":[{"type":"Feature","properties":{"codesPostaux":["72160"],"population":1052,"nom":"Duneau","code":"72122"},"geometry":{"type":"Point","coordinates":[0.5288419622641507,48.066575207547146]}}]}