{"type":"FeatureCollection","features":[{"type":"Feature","properties":{"codesPostaux":["72400"],"population":9116,"nom":"La Fert\u00e9-Bernard","code":"72132"},"geometry":{"type":"Point","coordinates":[0.6345456313993171,48.18354331058017]}}]}