{"type":"FeatureCollection","features":[{"type":"Feature","properties":{"codesPostaux":["72600","72610"],"population":2251,"nom":"Villeneuve-en-Perseigne","code":"72137"},"geometry":{"type":"Point","coordinates":[0.23524712918660248,48.446026531100486]}}]}