{"type":"FeatureCollection","features":[{"type":"Feature","properties":{"codesPostaux":["72150"],"population":1935,"nom":"Le Grand-Luc\u00e9","code":"72143"},"geometry":{"type":"Point","coordinates":[0.47747274914089366,47.85660171821302]}}]}