{"type":"FeatureCollection","features":[{"type":"Feature","properties":{"codesPostaux":["72140"],"population":391,"nom":"Le Grez","code":"72145"},"geometry":{"type":"Point","coordinates":[-0.15501170731707317,48.18498207317073]}}]}