{"type":"FeatureCollection","features":[{"type":"Feature","properties":{"codesPostaux":["72300"],"population":737,"nom":"Louailles","code":"72167"},"geometry":{"type":"Point","coordinates":[-0.23879837209302335,47.78321581395347]}}]}