{"type":"FeatureCollection","features":[{"type":"Feature","properties":{"codesPostaux":["72450"],"population":1933,"nom":"Lombron","code":"72165"},"geometry":{"type":"Point","coordinates":[0.41151765060240975,48.08343349397591]}}]}