{"type":"FeatureCollection","features":[{"type":"Feature","properties":{"codesPostaux":["72390"],"population":1450,"nom":"Le Luart","code":"72172"},"geometry":{"type":"Point","coordinates":[0.5955108910891086,48.08212722772276]}}]}