{"type":"FeatureCollection","features":[{"type":"Feature","properties":{"codesPostaux":["72500"],"population":1276,"nom":"Luceau","code":"72173"},"geometry":{"type":"Point","coordinates":[0.393173774834437,47.71930814569538]}}]}