{"type":"FeatureCollection","features":[{"type":"Feature","properties":{"codesPostaux":["72600"],"population":142,"nom":"Marollette","code":"72188"},"geometry":{"type":"Point","coordinates":[0.36406171875,48.37710171875]}}]}