{"type":"FeatureCollection","features":[{"type":"Feature","properties":{"codesPostaux":["72230"],"population":3498,"nom":"Monc\u00e9-en-Belin","code":"72200"},"geometry":{"type":"Point","coordinates":[0.19637290598290594,47.89869547008545]}}]}