{"type":"FeatureCollection","features":[{"type":"Feature","properties":{"codesPostaux":["72260"],"population":223,"nom":"Monhoudou","code":"72202"},"geometry":{"type":"Point","coordinates":[0.32741699999999996,48.28688145454547]}}]}