{"type":"FeatureCollection","features":[{"type":"Feature","properties":{"codesPostaux":["72190"],"population":2362,"nom":"Neuville-sur-Sarthe","code":"72217"},"geometry":{"type":"Point","coordinates":[0.21507621761658033,48.07492865284977]}}]}