{"type":"FeatureCollection","features":[{"type":"Feature","properties":{"codesPostaux":["72610"],"population":695,"nom":"Oisseau-le-Petit","code":"72225"},"geometry":{"type":"Point","coordinates":[0.07164364406779658,48.34859313559324]}}]}