{"type":"FeatureCollection","features":[{"type":"Feature","properties":{"codesPostaux":["72330"],"population":1335,"nom":"Oiz\u00e9","code":"72226"},"geometry":{"type":"Point","coordinates":[0.11337291925465835,47.80000701863357]}}]}