{"type":"FeatureCollection","features":[{"type":"Feature","properties":{"codesPostaux":["72110"],"population":232,"nom":"Pr\u00e9velles","code":"72246"},"geometry":{"type":"Point","coordinates":[0.47441689655172437,48.1556772413793]}}]}