{"type":"FeatureCollection","features":[{"type":"Feature","properties":{"codesPostaux":["72150"],"population":804,"nom":"Pruill\u00e9-l'\u00c9guill\u00e9","code":"72248"},"geometry":{"type":"Point","coordinates":[0.42285840579710154,47.83546072463766]}}]}