{"type":"FeatureCollection","features":[{"type":"Feature","properties":{"codesPostaux":["72700"],"population":2295,"nom":"Rouillon","code":"72257"},"geometry":{"type":"Point","coordinates":[0.14679370370370373,47.99812740740739]}}]}