{"type":"FeatureCollection","features":[{"type":"Feature","properties":{"codesPostaux":["72210"],"population":2707,"nom":"Ro\u00e9z\u00e9-sur-Sarthe","code":"72253"},"geometry":{"type":"Point","coordinates":[0.07509268072289157,47.894811987951826]}}]}