{"type":"FeatureCollection","features":[{"type":"Feature","properties":{"codesPostaux":["72220"],"population":723,"nom":"Saint-Biez-en-Belin","code":"72268"},"geometry":{"type":"Point","coordinates":[0.24043234782608697,47.82019773913045]}}]}