{"type":"FeatureCollection","features":[{"type":"Feature","properties":{"codesPostaux":["72170"],"population":217,"nom":"Saint-Christophe-du-Jambet","code":"72273"},"geometry":{"type":"Point","coordinates":[0.06737533936651587,48.23380280542986]}}]}