{"type":"FeatureCollection","features":[{"type":"Feature","properties":{"codesPostaux":["72220"],"population":2115,"nom":"Saint-Gervais-en-Belin","code":"72287"},"geometry":{"type":"Point","coordinates":[0.204208947368421,47.86705210526316]}}]}