{"type":"FeatureCollection","features":[{"type":"Feature","properties":{"codesPostaux":["72130"],"population":503,"nom":"Saint-L\u00e9onard-des-Bois","code":"72294"},"geometry":{"type":"Point","coordinates":[-0.07602252688172043,48.35607817204298]}}]}