{"type":"FeatureCollection","features":[{"type":"Feature","properties":{"codesPostaux":["72120"],"population":185,"nom":"Sainte-Osmane","code":"72304"},"geometry":{"type":"Point","coordinates":[0.6078809876543206,47.87193055555555]}}]}