{"type":"FeatureCollection","features":[{"type":"Feature","properties":{"codesPostaux":["72220"],"population":1319,"nom":"Saint-Ouen-en-Belin","code":"72306"},"geometry":{"type":"Point","coordinates":[0.22117713114754098,47.837117786885216]}}]}