{"type":"FeatureCollection","features":[{"type":"Feature","properties":{"codesPostaux":["72360"],"population":292,"nom":"Sarc\u00e9","code":"72327"},"geometry":{"type":"Point","coordinates":[0.22903063380281702,47.72545169014086]}}]}