{"type":"FeatureCollection","features":[{"type":"Feature","properties":{"codesPostaux":["72650"],"population":2484,"nom":"Saint-Saturnin","code":"72320"},"geometry":{"type":"Point","coordinates":[0.1648758333333333,48.06242653846154]}}]}