{"type":"FeatureCollection","features":[{"type":"Feature","properties":{"codesPostaux":["72210"],"population":698,"nom":"Soulign\u00e9-Flac\u00e9","code":"72339"},"geometry":{"type":"Point","coordinates":[0.015743076923076933,47.964045344129545]}}]}