{"type":"FeatureCollection","features":[{"type":"Feature","properties":{"codesPostaux":["72170"],"population":620,"nom":"S\u00e9grie","code":"72332"},"geometry":{"type":"Point","coordinates":[0.019536133333333337,48.21408696666668]}}]}