{"type":"FeatureCollection","features":[{"type":"Feature","properties":{"codesPostaux":["72300"],"population":1273,"nom":"Solesmes","code":"72336"},"geometry":{"type":"Point","coordinates":[-0.2896731395348837,47.84036860465117]}}]}