{"type":"FeatureCollection","features":[{"type":"Feature","properties":{"codesPostaux":["72310"],"population":332,"nom":"Vanc\u00e9","code":"72368"},"geometry":{"type":"Point","coordinates":[0.653453010752688,47.83360279569894]}}]}