{"type":"FeatureCollection","features":[{"type":"Feature","properties":{"codesPostaux":["72300"],"population":1458,"nom":"Vion","code":"72378"},"geometry":{"type":"Point","coordinates":[-0.2678169841269841,47.81170206349208]}}]}