{"type":"FeatureCollection","features":[{"type":"Feature","properties":{"codesPostaux":["72400"],"population":543,"nom":"Villaines-la-Gonais","code":"72375"},"geometry":{"type":"Point","coordinates":[0.6119145762711861,48.132293728813565]}}]}