{"type":"FeatureCollection","features":[{"type":"Feature","properties":{"codesPostaux":["72150"],"population":673,"nom":"Villaines-sous-Luc\u00e9","code":"72376"},"geometry":{"type":"Point","coordinates":[0.4983755491329483,47.8766871676301]}}]}