{"type":"FeatureCollection","features":[{"type":"Feature","properties":{"codesPostaux":["72440"],"population":880,"nom":"Volnay","code":"72382"},"geometry":{"type":"Point","coordinates":[0.4674978680203046,47.94957192893401]}}]}