{"type":"FeatureCollection","features":[{"type":"Feature","properties":{"codesPostaux":["73100"],"population":29580,"nom":"Aix-les-Bains","code":"73008"},"geometry":{"type":"Point","coordinates":[5.915662265625002,45.696476406249985]}}]}