{"type":"FeatureCollection","features":[{"type":"Feature","properties":{"codesPostaux":["73340"],"population":174,"nom":"Aillon-le-Vieux","code":"73005"},"geometry":{"type":"Point","coordinates":[6.09145971830986,45.65074788732394]}}]}