{"type":"FeatureCollection","features":[{"type":"Feature","properties":{"codesPostaux":["73340"],"population":414,"nom":"Arith","code":"73020"},"geometry":{"type":"Point","coordinates":[6.066811812865497,45.7204667251462]}}]}