{"type":"FeatureCollection","features":[{"type":"Feature","properties":{"codesPostaux":["73470"],"population":355,"nom":"Ayn","code":"73027"},"geometry":{"type":"Point","coordinates":[5.750217228915664,45.569957469879505]}}]}