{"type":"FeatureCollection","features":[{"type":"Feature","properties":{"codesPostaux":["73170"],"population":266,"nom":"Billi\u00e8me","code":"73042"},"geometry":{"type":"Point","coordinates":[5.811293571428571,45.71661607142858]}}]}