{"type":"FeatureCollection","features":[{"type":"Feature","properties":{"codesPostaux":["73520"],"population":1193,"nom":"La Bridoire","code":"73058"},"geometry":{"type":"Point","coordinates":[5.740835855855857,45.53313315315316]}}]}