{"type":"FeatureCollection","features":[{"type":"Feature","properties":{"codesPostaux":["73700"],"population":7174,"nom":"Bourg-Saint-Maurice","code":"73054"},"geometry":{"type":"Point","coordinates":[6.7828241605839406,45.671302019464726]}}]}