{"type":"FeatureCollection","features":[{"type":"Feature","properties":{"codesPostaux":["73390"],"population":573,"nom":"Chamousset","code":"73068"},"geometry":{"type":"Point","coordinates":[6.209821956521738,45.561688260869566]}}]}