{"type":"FeatureCollection","features":[{"type":"Feature","properties":{"codesPostaux":["73700"],"population":540,"nom":"Les Chapelles","code":"73077"},"geometry":{"type":"Point","coordinates":[6.709950785714284,45.61151471428573]}}]}