{"type":"FeatureCollection","features":[{"type":"Feature","properties":{"codesPostaux":["73170"],"population":295,"nom":"Lucey","code":"73149"},"geometry":{"type":"Point","coordinates":[5.797028032786884,45.76085016393441]}}]}