{"type":"FeatureCollection","features":[{"type":"Feature","properties":{"codesPostaux":["73210"],"population":853,"nom":"Landry","code":"73142"},"geometry":{"type":"Point","coordinates":[6.757749861111113,45.56218430555555]}}]}