{"type":"FeatureCollection","features":[{"type":"Feature","properties":{"codesPostaux":["73340"],"population":745,"nom":"Lescheraines","code":"73146"},"geometry":{"type":"Point","coordinates":[6.107814011627909,45.71411866279068]}}]}