{"type":"FeatureCollection","features":[{"type":"Feature","properties":{"codesPostaux":["73470"],"population":170,"nom":"Marcieux","code":"73152"},"geometry":{"type":"Point","coordinates":[5.776477258883248,45.61676604060912]}}]}