{"type":"FeatureCollection","features":[{"type":"Feature","properties":{"codesPostaux":["73210"],"population":3814,"nom":"La Plagne Tarentaise","code":"73150"},"geometry":{"type":"Point","coordinates":[6.6982759952038435,45.558061294964084]}}]}