{"type":"FeatureCollection","features":[{"type":"Feature","properties":{"codesPostaux":["73220"],"population":122,"nom":"Montgilbert","code":"73168"},"geometry":{"type":"Point","coordinates":[6.273807252747252,45.53926164835163]}}]}