{"type":"FeatureCollection","features":[{"type":"Feature","properties":{"codesPostaux":["73310"],"population":420,"nom":"Motz","code":"73180"},"geometry":{"type":"Point","coordinates":[5.843861063829789,45.921461276595714]}}]}