{"type":"FeatureCollection","features":[{"type":"Feature","properties":{"codesPostaux":["73200"],"population":742,"nom":"Pallud","code":"73196"},"geometry":{"type":"Point","coordinates":[6.386011447368425,45.689194736842104]}}]}