{"type":"FeatureCollection","features":[{"type":"Feature","properties":{"codesPostaux":["73330"],"population":2043,"nom":"Le Pont-de-Beauvoisin","code":"73204"},"geometry":{"type":"Point","coordinates":[5.681587906976745,45.53714558139535]}}]}