{"type":"FeatureCollection","features":[{"type":"Feature","properties":{"codesPostaux":["73130"],"population":96,"nom":"Saint-Alban-des-Villards","code":"73221"},"geometry":{"type":"Point","coordinates":[6.243054709302328,45.314458953488376]}}]}