{"type":"FeatureCollection","features":[{"type":"Feature","properties":{"codesPostaux":["73520"],"population":1621,"nom":"Saint-B\u00e9ron","code":"73226"},"geometry":{"type":"Point","coordinates":[5.723207864077668,45.50388699029124]}}]}