{"type":"FeatureCollection","features":[{"type":"Feature","properties":{"codesPostaux":["73160"],"population":743,"nom":"Saint-Cassin","code":"73228"},"geometry":{"type":"Point","coordinates":[5.882309259259263,45.52526895061732]}}]}