{"type":"FeatureCollection","features":[{"type":"Feature","properties":{"codesPostaux":["73300"],"population":7968,"nom":"Saint-Jean-de-Maurienne","code":"73248"},"geometry":{"type":"Point","coordinates":[6.340580063291139,45.2674265822785]}}]}