{"type":"FeatureCollection","features":[{"type":"Feature","properties":{"codesPostaux":["73230"],"population":1628,"nom":"Saint-Jean-d'Arvey","code":"73243"},"geometry":{"type":"Point","coordinates":[5.98809894736842,45.60022984210526]}}]}