{"type":"FeatureCollection","features":[{"type":"Feature","properties":{"codesPostaux":["73140"],"population":2486,"nom":"Saint-Michel-de-Maurienne","code":"73261"},"geometry":{"type":"Point","coordinates":[6.488657901234573,45.22738969135801]}}]}