{"type":"FeatureCollection","features":[{"type":"Feature","properties":{"codesPostaux":["73530"],"population":340,"nom":"Saint-Sorlin-d'Arves","code":"73280"},"geometry":{"type":"Point","coordinates":[6.2068732916666685,45.200811166666654]}}]}