{"type":"FeatureCollection","features":[{"type":"Feature","properties":{"codesPostaux":["73230"],"population":457,"nom":"Thoiry","code":"73293"},"geometry":{"type":"Point","coordinates":[6.041874518072292,45.59498704819274]}}]}