{"type":"FeatureCollection","features":[{"type":"Feature","properties":{"codesPostaux":["73400"],"population":7019,"nom":"Ugine","code":"73303"},"geometry":{"type":"Point","coordinates":[6.428719260700391,45.77627778210116]}}]}