{"type":"FeatureCollection","features":[{"type":"Feature","properties":{"codesPostaux":["73300"],"population":257,"nom":"Villarembert","code":"73318"},"geometry":{"type":"Point","coordinates":[6.261376782608696,45.241538521739145]}}]}