{"type":"FeatureCollection","features":[{"type":"Feature","properties":{"codesPostaux":["73230"],"population":441,"nom":"Verel-Pragondran","code":"73310"},"geometry":{"type":"Point","coordinates":[5.950990853658538,45.61966670731707]}}]}