{"type":"FeatureCollection","features":[{"type":"Feature","properties":{"codesPostaux":["73640"],"population":380,"nom":"Villaroger","code":"73323"},"geometry":{"type":"Point","coordinates":[6.867813242009133,45.56134726027398]}}]}