{"type":"FeatureCollection","features":[{"type":"Feature","properties":{"codesPostaux":["74200"],"population":4226,"nom":"Allinges","code":"74005"},"geometry":{"type":"Point","coordinates":[6.460264912280701,46.33250619883042]}}]}