{"type":"FeatureCollection","features":[{"type":"Feature","properties":{"codesPostaux":["74350"],"population":806,"nom":"Andilly","code":"74009"},"geometry":{"type":"Point","coordinates":[6.07037945736434,46.07144193798448]}}]}