{"type":"FeatureCollection","features":[{"type":"Feature","properties":{"codesPostaux":["74100"],"population":6092,"nom":"Ambilly","code":"74008"},"geometry":{"type":"Point","coordinates":[6.222274035087718,46.195556842105276]}}]}