{"type":"FeatureCollection","features":[{"type":"Feature","properties":{"codesPostaux":["74380"],"population":1351,"nom":"Arthaz-Pont-Notre-Dame","code":"74021"},"geometry":{"type":"Point","coordinates":[6.267702470588236,46.16135117647059]}}]}