{"type":"FeatureCollection","features":[{"type":"Feature","properties":{"codesPostaux":["74200"],"population":1275,"nom":"Armoy","code":"74020"},"geometry":{"type":"Point","coordinates":[6.51003873563218,46.34953459770115]}}]}