{"type":"FeatureCollection","features":[{"type":"Feature","properties":{"codesPostaux":["74890"],"population":5235,"nom":"Bons-en-Chablais","code":"74043"},"geometry":{"type":"Point","coordinates":[6.367084761904766,46.27431479591836]}}]}