{"type":"FeatureCollection","features":[{"type":"Feature","properties":{"codesPostaux":["74890"],"population":940,"nom":"Brenthonne","code":"74048"},"geometry":{"type":"Point","coordinates":[6.39125797385621,46.27322039215685]}}]}