{"type":"FeatureCollection","features":[{"type":"Feature","properties":{"codesPostaux":["74410"],"population":134,"nom":"La Chapelle-Saint-Maurice","code":"74060"},"geometry":{"type":"Point","coordinates":[6.147462769230768,45.77435215384614]}}]}