{"type":"FeatureCollection","features":[{"type":"Feature","properties":{"codesPostaux":["74500"],"population":578,"nom":"Chevenoz","code":"74073"},"geometry":{"type":"Point","coordinates":[6.638468620689656,46.334420517241355]}}]}