{"type":"FeatureCollection","features":[{"type":"Feature","properties":{"codesPostaux":["74520"],"population":442,"nom":"Chevrier","code":"74074"},"geometry":{"type":"Point","coordinates":[5.9085726829268275,46.107675853658534]}}]}