{"type":"FeatureCollection","features":[{"type":"Feature","properties":{"codesPostaux":["74160"],"population":3884,"nom":"Collonges-sous-Sal\u00e8ve","code":"74082"},"geometry":{"type":"Point","coordinates":[6.154575921052633,46.13630355263156]}}]}