{"type":"FeatureCollection","features":[{"type":"Feature","properties":{"codesPostaux":["74150"],"population":754,"nom":"\u00c9tercy","code":"74117"},"geometry":{"type":"Point","coordinates":[6.006483943661971,45.89264507042253]}}]}