{"type":"FeatureCollection","features":[{"type":"Feature","properties":{"codesPostaux":["74130"],"population":540,"nom":"Faucigny","code":"74122"},"geometry":{"type":"Point","coordinates":[6.372126052631579,46.11449960526315]}}]}