{"type":"FeatureCollection","features":[{"type":"Feature","properties":{"codesPostaux":["74910"],"population":508,"nom":"Franclens","code":"74130"},"geometry":{"type":"Point","coordinates":[5.826173432835821,46.04410641791044]}}]}