{"type":"FeatureCollection","features":[{"type":"Feature","properties":{"codesPostaux":["74890"],"population":684,"nom":"Lully","code":"74156"},"geometry":{"type":"Point","coordinates":[6.403548970588233,46.29599764705881]}}]}