{"type":"FeatureCollection","features":[{"type":"Feature","properties":{"codesPostaux":["74150"],"population":678,"nom":"Marigny-Saint-Marcel","code":"74165"},"geometry":{"type":"Point","coordinates":[5.988453181818179,45.82938545454546]}}]}