{"type":"FeatureCollection","features":[{"type":"Feature","properties":{"codesPostaux":["74150"],"population":1816,"nom":"Marcellaz-Albanais","code":"74161"},"geometry":{"type":"Point","coordinates":[5.998825196078432,45.87003112745099]}}]}