{"type":"FeatureCollection","features":[{"type":"Feature","properties":{"codesPostaux":["74290"],"population":1905,"nom":"Menthon-Saint-Bernard","code":"74176"},"geometry":{"type":"Point","coordinates":[6.201882777777778,45.86616930555556]}}]}