{"type":"FeatureCollection","features":[{"type":"Feature","properties":{"codesPostaux":["74560"],"population":1060,"nom":"La Muraz","code":"74193"},"geometry":{"type":"Point","coordinates":[6.200424379562043,46.120577518248176]}}]}