{"type":"FeatureCollection","features":[{"type":"Feature","properties":{"codesPostaux":["74550"],"population":867,"nom":"Orcier","code":"74206"},"geometry":{"type":"Point","coordinates":[6.497614583333333,46.316141250000015]}}]}