{"type":"FeatureCollection","features":[{"type":"Feature","properties":{"codesPostaux":["74160"],"population":1677,"nom":"Neydens","code":"74201"},"geometry":{"type":"Point","coordinates":[6.104288705035973,46.11593115107911]}}]}