{"type":"FeatureCollection","features":[{"type":"Feature","properties":{"codesPostaux":["74800"],"population":11184,"nom":"La Roche-sur-Foron","code":"74224"},"geometry":{"type":"Point","coordinates":[6.30026947761194,46.044546753731375]}}]}