{"type":"FeatureCollection","features":[{"type":"Feature","properties":{"codesPostaux":["74700"],"population":15853,"nom":"Sallanches","code":"74256"},"geometry":{"type":"Point","coordinates":[6.61134274509804,45.936282113289785]}}]}