{"type":"FeatureCollection","features":[{"type":"Feature","properties":{"codesPostaux":["74340"],"population":2282,"nom":"Samo\u00ebns","code":"74258"},"geometry":{"type":"Point","coordinates":[6.745402928571429,46.08608511904765]}}]}