{"type":"FeatureCollection","features":[{"type":"Feature","properties":{"codesPostaux":["74420"],"population":436,"nom":"Saxel","code":"74261"},"geometry":{"type":"Point","coordinates":[6.400410675675675,46.245887297297294]}}]}