{"type":"FeatureCollection","features":[{"type":"Feature","properties":{"codesPostaux":["74930"],"population":1106,"nom":"Scientrier","code":"74262"},"geometry":{"type":"Point","coordinates":[6.31483746835443,46.118113670886075]}}]}