{"type":"FeatureCollection","features":[{"type":"Feature","properties":{"codesPostaux":["74430"],"population":463,"nom":"Seytroux","code":"74271"},"geometry":{"type":"Point","coordinates":[6.605296037735848,46.235981226415085]}}]}