{"type":"FeatureCollection","features":[{"type":"Feature","properties":{"codesPostaux":["74740"],"population":781,"nom":"Sixt-Fer-\u00e0-Cheval","code":"74273"},"geometry":{"type":"Point","coordinates":[6.811438337129839,46.056910182232336]}}]}