{"type":"FeatureCollection","features":[{"type":"Feature","properties":{"codesPostaux":["74910"],"population":375,"nom":"Usinens","code":"74285"},"geometry":{"type":"Point","coordinates":[5.851452399999996,46.012602399999984]}}]}