{"type":"FeatureCollection","features":[{"type":"Feature","properties":{"codesPostaux":["74200"],"population":34610,"nom":"Thonon-les-Bains","code":"74281"},"geometry":{"type":"Point","coordinates":[6.478565297297292,46.371129243243274]}}]}