{"type":"FeatureCollection","features":[{"type":"Feature","properties":{"codesPostaux":["74290"],"population":2355,"nom":"Veyrier-du-Lac","code":"74299"},"geometry":{"type":"Point","coordinates":[6.184256818181819,45.88218545454546]}}]}