{"type":"FeatureCollection","features":[{"type":"Feature","properties":{"codesPostaux":["76370"],"population":697,"nom":"Ancourt","code":"76008"},"geometry":{"type":"Point","coordinates":[1.1825785833333333,49.90760550000005]}}]}