{"type":"FeatureCollection","features":[{"type":"Feature","properties":{"codesPostaux":["76710"],"population":683,"nom":"Anceaumeville","code":"76007"},"geometry":{"type":"Point","coordinates":[1.0658094444444444,49.56827074074072]}}]}