{"type":"FeatureCollection","features":[{"type":"Feature","properties":{"codesPostaux":["76560"],"population":300,"nom":"Ancourteville-sur-H\u00e9ricourt","code":"76009"},"geometry":{"type":"Point","coordinates":[0.6628945833333334,49.69027166666664]}}]}