{"type":"FeatureCollection","features":[{"type":"Feature","properties":{"codesPostaux":["76280"],"population":1452,"nom":"Angerville-l'Orcher","code":"76014"},"geometry":{"type":"Point","coordinates":[0.29051655555555544,49.584739222222225]}}]}