{"type":"FeatureCollection","features":[{"type":"Feature","properties":{"codesPostaux":["76490"],"population":352,"nom":"Anquetierville","code":"76022"},"geometry":{"type":"Point","coordinates":[0.6332313461538459,49.537909807692316]}}]}