{"type":"FeatureCollection","features":[{"type":"Feature","properties":{"codesPostaux":["76880"],"population":2776,"nom":"Arques-la-Bataille","code":"76026"},"geometry":{"type":"Point","coordinates":[1.1409422085889567,49.88484601226994]}}]}