{"type":"FeatureCollection","features":[{"type":"Feature","properties":{"codesPostaux":["76730"],"population":731,"nom":"Auppegard","code":"76036"},"geometry":{"type":"Point","coordinates":[1.0254430909090908,49.83028036363636]}}]}