{"type":"FeatureCollection","features":[{"type":"Feature","properties":{"codesPostaux":["76390"],"population":2289,"nom":"Aumale","code":"76035"},"geometry":{"type":"Point","coordinates":[1.7525396753246758,49.771361753246765]}}]}