{"type":"FeatureCollection","features":[{"type":"Feature","properties":{"codesPostaux":["76190"],"population":683,"nom":"Autretot","code":"76041"},"geometry":{"type":"Point","coordinates":[0.7282570967741936,49.65500419354839]}}]}