{"type":"FeatureCollection","features":[{"type":"Feature","properties":{"codesPostaux":["76730"],"population":154,"nom":"Auzouville-sur-Sa\u00e2ne","code":"76047"},"geometry":{"type":"Point","coordinates":[0.9316961363636367,49.744354659090895]}}]}