{"type":"FeatureCollection","features":[{"type":"Feature","properties":{"codesPostaux":["76660"],"population":106,"nom":"Baillolet","code":"76053"},"geometry":{"type":"Point","coordinates":[1.4362774561403504,49.79224131578947]}}]}