{"type":"FeatureCollection","features":[{"type":"Feature","properties":{"codesPostaux":["76450"],"population":114,"nom":"Bertreville","code":"76084"},"geometry":{"type":"Point","coordinates":[0.5805902857142858,49.76536742857143]}}]}