{"type":"FeatureCollection","features":[{"type":"Feature","properties":{"codesPostaux":["76210"],"population":1112,"nom":"Beuzeville-la-Grenier","code":"76090"},"geometry":{"type":"Point","coordinates":[0.42277094594594583,49.59250581081082]}}]}