{"type":"FeatureCollection","features":[{"type":"Feature","properties":{"codesPostaux":["76730"],"population":105,"nom":"Biville-la-Rivi\u00e8re","code":"76097"},"geometry":{"type":"Point","coordinates":[0.9236378260869564,49.77682304347826]}}]}