{"type":"FeatureCollection","features":[{"type":"Feature","properties":{"codesPostaux":["76210"],"population":11551,"nom":"Bolbec","code":"76114"},"geometry":{"type":"Point","coordinates":[0.4836612413793101,49.5732447586207]}}]}