{"type":"FeatureCollection","features":[{"type":"Feature","properties":{"codesPostaux":["76110"],"population":270,"nom":"Bornambusc","code":"76118"},"geometry":{"type":"Point","coordinates":[0.35582727272727266,49.62480424242425]}}]}