{"type":"FeatureCollection","features":[{"type":"Feature","properties":{"codesPostaux":["76750"],"population":345,"nom":"Bosc-\u00c9deline","code":"76121"},"geometry":{"type":"Point","coordinates":[1.4366011428571424,49.57693657142856]}}]}