{"type":"FeatureCollection","features":[{"type":"Feature","properties":{"codesPostaux":["76850"],"population":1498,"nom":"Bosc-le-Hard","code":"76125"},"geometry":{"type":"Point","coordinates":[1.1822569565217391,49.623254057971025]}}]}