{"type":"FeatureCollection","features":[{"type":"Feature","properties":{"codesPostaux":["76850"],"population":344,"nom":"Bracquetuit","code":"76138"},"geometry":{"type":"Point","coordinates":[1.1683136065573771,49.664405737704904]}}]}