{"type":"FeatureCollection","features":[{"type":"Feature","properties":{"codesPostaux":["76270"],"population":279,"nom":"Bouelles","code":"76130"},"geometry":{"type":"Point","coordinates":[1.4917019827586206,49.72060275862069]}}]}