{"type":"FeatureCollection","features":[{"type":"Feature","properties":{"codesPostaux":["76530"],"population":778,"nom":"La Bouille","code":"76131"},"geometry":{"type":"Point","coordinates":[0.9338021818181818,49.3501370909091]}}]}