{"type":"FeatureCollection","features":[{"type":"Feature","properties":{"codesPostaux":["76110"],"population":1319,"nom":"Bretteville-du-Grand-Caux","code":"76143"},"geometry":{"type":"Point","coordinates":[0.384719375,49.66648125000002]}}]}