{"type":"FeatureCollection","features":[{"type":"Feature","properties":{"codesPostaux":["76270"],"population":881,"nom":"Bully","code":"76147"},"geometry":{"type":"Point","coordinates":[1.3692128104575172,49.72532392156863]}}]}