{"type":"FeatureCollection","features":[{"type":"Feature","properties":{"codesPostaux":["76490"],"population":4182,"nom":"Rives-en-Seine","code":"76164"},"geometry":{"type":"Point","coordinates":[0.7246255279503104,49.526332981366444]}}]}