{"type":"FeatureCollection","features":[{"type":"Feature","properties":{"codesPostaux":["76640"],"population":161,"nom":"Cl\u00e9ville","code":"76181"},"geometry":{"type":"Point","coordinates":[0.6136285542168671,49.62197024096386]}}]}