{"type":"FeatureCollection","features":[{"type":"Feature","properties":{"codesPostaux":["76390"],"population":527,"nom":"Conteville","code":"76186"},"geometry":{"type":"Point","coordinates":[1.631928737864077,49.697884077669904]}}]}