{"type":"FeatureCollection","features":[{"type":"Feature","properties":{"codesPostaux":["76760"],"population":780,"nom":"Criquetot-sur-Ouville","code":"76198"},"geometry":{"type":"Point","coordinates":[0.8475721794871794,49.672445769230755]}}]}