{"type":"FeatureCollection","features":[{"type":"Feature","properties":{"codesPostaux":["76850"],"population":357,"nom":"La Crique","code":"76193"},"geometry":{"type":"Point","coordinates":[1.2074730107526885,49.69589172043011]}}]}