{"type":"FeatureCollection","features":[{"type":"Feature","properties":{"codesPostaux":["76280"],"population":2425,"nom":"Criquetot-l'Esneval","code":"76196"},"geometry":{"type":"Point","coordinates":[0.2613631999999999,49.63809706666666]}}]}