{"type":"FeatureCollection","features":[{"type":"Feature","properties":{"codesPostaux":["76280"],"population":358,"nom":"Cuverville","code":"76206"},"geometry":{"type":"Point","coordinates":[0.264065,49.666242037037044]}}]}