{"type":"FeatureCollection","features":[{"type":"Feature","properties":{"codesPostaux":["76160"],"population":9515,"nom":"Darn\u00e9tal","code":"76212"},"geometry":{"type":"Point","coordinates":[1.1528718085106382,49.443906702127684]}}]}