{"type":"FeatureCollection","features":[{"type":"Feature","properties":{"codesPostaux":["76220"],"population":415,"nom":"Elbeuf-en-Bray","code":"76229"},"geometry":{"type":"Point","coordinates":[1.6535616666666668,49.492884487179495]}}]}