{"type":"FeatureCollection","features":[{"type":"Feature","properties":{"codesPostaux":["76480"],"population":4133,"nom":"Duclair","code":"76222"},"geometry":{"type":"Point","coordinates":[0.8672422448979589,49.48835666666668]}}]}