{"type":"FeatureCollection","features":[{"type":"Feature","properties":{"codesPostaux":["76640"],"population":328,"nom":"Envronville","code":"76236"},"geometry":{"type":"Point","coordinates":[0.6733964912280701,49.65947438596493]}}]}