{"type":"FeatureCollection","features":[{"type":"Feature","properties":{"codesPostaux":["76780"],"population":461,"nom":"Elbeuf-sur-Andelle","code":"76230"},"geometry":{"type":"Point","coordinates":[1.388124375,49.476234196428585]}}]}