{"type":"FeatureCollection","features":[{"type":"Feature","properties":{"codesPostaux":["76750"],"population":273,"nom":"Ernemont-sur-Buchy","code":"76243"},"geometry":{"type":"Point","coordinates":[1.3623750980392155,49.54082549019607]}}]}