{"type":"FeatureCollection","features":[{"type":"Feature","properties":{"codesPostaux":["76260"],"population":1106,"nom":"\u00c9talondes","code":"76252"},"geometry":{"type":"Point","coordinates":[1.3893613043478261,50.0329106521739]}}]}