{"type":"FeatureCollection","features":[{"type":"Feature","properties":{"codesPostaux":["76270"],"population":177,"nom":"Flamets-Fr\u00e9tils","code":"76265"},"geometry":{"type":"Point","coordinates":[1.5866816853932586,49.73156573033707]}}]}