{"type":"FeatureCollection","features":[{"type":"Feature","properties":{"codesPostaux":["76280"],"population":188,"nom":"Fongueusemare","code":"76268"},"geometry":{"type":"Point","coordinates":[0.30568166666666685,49.67614133333331]}}]}