{"type":"FeatureCollection","features":[{"type":"Feature","properties":{"codesPostaux":["76890"],"population":35,"nom":"La Fontelaye","code":"76274"},"geometry":{"type":"Point","coordinates":[0.9466857407407407,49.694141111111094]}}]}