{"type":"FeatureCollection","features":[{"type":"Feature","properties":{"codesPostaux":["76170"],"population":2070,"nom":"La Fr\u00e9naye","code":"76281"},"geometry":{"type":"Point","coordinates":[0.5673367226890755,49.523081512605046]}}]}