{"type":"FeatureCollection","features":[{"type":"Feature","properties":{"codesPostaux":["76740"],"population":392,"nom":"La Gaillarde","code":"76294"},"geometry":{"type":"Point","coordinates":[0.8735150724637684,49.83610753623187]}}]}