{"type":"FeatureCollection","features":[{"type":"Feature","properties":{"codesPostaux":["76270"],"population":168,"nom":"Graval","code":"76323"},"geometry":{"type":"Point","coordinates":[1.5510920000000004,49.72958854545453]}}]}