{"type":"FeatureCollection","features":[{"type":"Feature","properties":{"codesPostaux":["76370"],"population":800,"nom":"Gr\u00e8ges","code":"76324"},"geometry":{"type":"Point","coordinates":[1.1488503333333335,49.921878666666665]}}]}