{"type":"FeatureCollection","features":[{"type":"Feature","properties":{"codesPostaux":["76390"],"population":464,"nom":"Haudricourt","code":"76344"},"geometry":{"type":"Point","coordinates":[1.7003328901734103,49.738779768786124]}}]}