{"type":"FeatureCollection","features":[{"type":"Feature","properties":{"codesPostaux":["76640"],"population":693,"nom":"Hattenville","code":"76342"},"geometry":{"type":"Point","coordinates":[0.5326770000000002,49.65365911111109]}}]}