{"type":"FeatureCollection","features":[{"type":"Feature","properties":{"codesPostaux":["76390"],"population":380,"nom":"Illois","code":"76372"},"geometry":{"type":"Point","coordinates":[1.6473759550561797,49.74770483146068]}}]}