{"type":"FeatureCollection","features":[{"type":"Feature","properties":{"codesPostaux":["76390"],"population":137,"nom":"Landes-Vieilles-et-Neuves","code":"76381"},"geometry":{"type":"Point","coordinates":[1.6355050537634408,49.785568172043014]}}]}