{"type":"FeatureCollection","features":[{"type":"Feature","properties":{"codesPostaux":["76860"],"population":581,"nom":"Longueil","code":"76395"},"geometry":{"type":"Point","coordinates":[0.947326896551724,49.88513908045978]}}]}