{"type":"FeatureCollection","features":[{"type":"Feature","properties":{"codesPostaux":["76790"],"population":1179,"nom":"Les Loges","code":"76390"},"geometry":{"type":"Point","coordinates":[0.2870187116564418,49.70022337423314]}}]}