{"type":"FeatureCollection","features":[{"type":"Feature","properties":{"codesPostaux":["76290"],"population":801,"nom":"Mannevillette","code":"76409"},"geometry":{"type":"Point","coordinates":[0.17686092307692305,49.59616784615383]}}]}