{"type":"FeatureCollection","features":[{"type":"Feature","properties":{"codesPostaux":["76880"],"population":459,"nom":"Martigny","code":"76413"},"geometry":{"type":"Point","coordinates":[1.1491695999999998,49.86110399999999]}}]}