{"type":"FeatureCollection","features":[{"type":"Feature","properties":{"codesPostaux":["76680"],"population":309,"nom":"Mathonville","code":"76416"},"geometry":{"type":"Point","coordinates":[1.3782632758620685,49.62464465517242]}}]}