{"type":"FeatureCollection","features":[{"type":"Feature","properties":{"codesPostaux":["76490"],"population":995,"nom":"Maul\u00e9vrier-Sainte-Gertrude","code":"76418"},"geometry":{"type":"Point","coordinates":[0.7084019374999996,49.55319306250001]}}]}