{"type":"FeatureCollection","features":[{"type":"Feature","properties":{"codesPostaux":["76240"],"population":7698,"nom":"Le Mesnil-Esnard","code":"76429"},"geometry":{"type":"Point","coordinates":[1.1446250892857146,49.41085642857142]}}]}