{"type":"FeatureCollection","features":[{"type":"Feature","properties":{"codesPostaux":["76460"],"population":19,"nom":"Le Mesnil-Durdent","code":"76428"},"geometry":{"type":"Point","coordinates":[0.7711246666666668,49.818332666666656]}}]}