{"type":"FeatureCollection","features":[{"type":"Feature","properties":{"codesPostaux":["76170"],"population":816,"nom":"M\u00e9lamare","code":"76421"},"geometry":{"type":"Point","coordinates":[0.43570855421686744,49.54046939759036]}}]}