{"type":"FeatureCollection","features":[{"type":"Feature","properties":{"codesPostaux":["76340"],"population":648,"nom":"Monchaux-Soreng","code":"76441"},"geometry":{"type":"Point","coordinates":[1.5773853883495137,49.95394315533978]}}]}