{"type":"FeatureCollection","features":[{"type":"Feature","properties":{"codesPostaux":["76260"],"population":590,"nom":"Monchy-sur-Eu","code":"76442"},"geometry":{"type":"Point","coordinates":[1.4538953846153848,49.99059051282052]}}]}