{"type":"FeatureCollection","features":[{"type":"Feature","properties":{"codesPostaux":["76710"],"population":4833,"nom":"Montville","code":"76452"},"geometry":{"type":"Point","coordinates":[1.0789481818181819,49.54958286713286]}}]}