{"type":"FeatureCollection","features":[{"type":"Feature","properties":{"codesPostaux":["76220"],"population":272,"nom":"Montroty","code":"76450"},"geometry":{"type":"Point","coordinates":[1.660509360465116,49.43072738372093]}}]}