{"type":"FeatureCollection","features":[{"type":"Feature","properties":{"codesPostaux":["76590"],"population":134,"nom":"Muchedent","code":"76458"},"geometry":{"type":"Point","coordinates":[1.185713913043479,49.76579634782609]}}]}