{"type":"FeatureCollection","features":[{"type":"Feature","properties":{"codesPostaux":["76460"],"population":1196,"nom":"N\u00e9ville","code":"76467"},"geometry":{"type":"Point","coordinates":[0.7117534146341465,49.82492158536584]}}]}