{"type":"FeatureCollection","features":[{"type":"Feature","properties":{"codesPostaux":["76520"],"population":2263,"nom":"La Neuville-Chant-d'Oisel","code":"76464"},"geometry":{"type":"Point","coordinates":[1.249274033613445,49.38195831932775]}}]}