{"type":"FeatureCollection","features":[{"type":"Feature","properties":{"codesPostaux":["76940"],"population":741,"nom":"Notre-Dame-de-Bliquetuit","code":"76473"},"geometry":{"type":"Point","coordinates":[0.7550001694915255,49.49208050847459]}}]}