{"type":"FeatureCollection","features":[{"type":"Feature","properties":{"codesPostaux":["76170","76330"],"population":9556,"nom":"Port-J\u00e9r\u00f4me-sur-Seine","code":"76476"},"geometry":{"type":"Point","coordinates":[0.5959034224598928,49.51651983957218]}}]}