{"type":"FeatureCollection","features":[{"type":"Feature","properties":{"codesPostaux":["76450"],"population":503,"nom":"Ouainville","code":"76488"},"geometry":{"type":"Point","coordinates":[0.5866412068965517,49.7844151724138]}}]}