{"type":"FeatureCollection","features":[{"type":"Feature","properties":{"codesPostaux":["76760"],"population":642,"nom":"Ouville-l'Abbaye","code":"76491"},"geometry":{"type":"Point","coordinates":[0.8643305172413794,49.69104948275862]}}]}