{"type":"FeatureCollection","features":[{"type":"Feature","properties":{"codesPostaux":["76340"],"population":477,"nom":"Pierrecourt","code":"76500"},"geometry":{"type":"Point","coordinates":[1.6421513999999997,49.887831999999996]}}]}