{"type":"FeatureCollection","features":[{"type":"Feature","properties":{"codesPostaux":["76210"],"population":500,"nom":"Raffetot","code":"76518"},"geometry":{"type":"Point","coordinates":[0.5187801612903227,49.60016]}}]}