{"type":"FeatureCollection","features":[{"type":"Feature","properties":{"codesPostaux":["76430"],"population":1306,"nom":"La Remu\u00e9e","code":"76522"},"geometry":{"type":"Point","coordinates":[0.4129341860465117,49.52669069767441]}}]}