{"type":"FeatureCollection","features":[{"type":"Feature","properties":{"codesPostaux":["76113"],"population":1290,"nom":"Sahurs","code":"76550"},"geometry":{"type":"Point","coordinates":[0.9469238888888888,49.3652675]}}]}