{"type":"FeatureCollection","features":[{"type":"Feature","properties":{"codesPostaux":["76750"],"population":687,"nom":"Sainte-Croix-sur-Buchy","code":"76571"},"geometry":{"type":"Point","coordinates":[1.3432513533834587,49.56793714285715]}}]}