{"type":"FeatureCollection","features":[{"type":"Feature","properties":{"codesPostaux":["76860"],"population":140,"nom":"Saint-Denis-d'Aclon","code":"76572"},"geometry":{"type":"Point","coordinates":[0.949980652173913,49.865786956521745]}}]}