{"type":"FeatureCollection","features":[{"type":"Feature","properties":{"codesPostaux":["76116"],"population":513,"nom":"Saint-Denis-le-Thiboult","code":"76573"},"geometry":{"type":"Point","coordinates":[1.350491666666667,49.457339761904755]}}]}