{"type":"FeatureCollection","features":[{"type":"Feature","properties":{"codesPostaux":["76690"],"population":913,"nom":"Saint-Georges-sur-Fontaine","code":"76580"},"geometry":{"type":"Point","coordinates":[1.1732175294117648,49.54989011764705]}}]}