{"type":"FeatureCollection","features":[{"type":"Feature","properties":{"codesPostaux":["76400"],"population":689,"nom":"Sainte-H\u00e9l\u00e8ne-Bondeville","code":"76587"},"geometry":{"type":"Point","coordinates":[0.46282280000000015,49.771060533333326]}}]}