{"type":"FeatureCollection","features":[{"type":"Feature","properties":{"codesPostaux":["76750"],"population":402,"nom":"Saint-Germain-des-Essourts","code":"76581"},"geometry":{"type":"Point","coordinates":[1.3152558536585361,49.53703573170731]}}]}