{"type":"FeatureCollection","features":[{"type":"Feature","properties":{"codesPostaux":["76700"],"population":1412,"nom":"Saint-Laurent-de-Br\u00e8vedent","code":"76596"},"geometry":{"type":"Point","coordinates":[0.2674503797468355,49.53195987341772]}}]}