{"type":"FeatureCollection","features":[{"type":"Feature","properties":{"codesPostaux":["76440"],"population":104,"nom":"Saint-Michel-d'Halescourt","code":"76623"},"geometry":{"type":"Point","coordinates":[1.658472297297297,49.609478783783786]}}]}