{"type":"FeatureCollection","features":[{"type":"Feature","properties":{"codesPostaux":["76170"],"population":1427,"nom":"Saint-Nicolas-de-la-Taille","code":"76627"},"geometry":{"type":"Point","coordinates":[0.4710446666666666,49.51204914285715]}}]}