{"type":"FeatureCollection","features":[{"type":"Feature","properties":{"codesPostaux":["76680"],"population":2541,"nom":"Saint-Sa\u00ebns","code":"76648"},"geometry":{"type":"Point","coordinates":[1.2756131451612904,49.668903225806446]}}]}