{"type":"FeatureCollection","features":[{"type":"Feature","properties":{"codesPostaux":["76270"],"population":637,"nom":"Saint-Saire","code":"76649"},"geometry":{"type":"Point","coordinates":[1.4791525680933861,49.68568058365761]}}]}