{"type":"FeatureCollection","features":[{"type":"Feature","properties":{"codesPostaux":["76430"],"population":622,"nom":"Saint-Vincent-Cramesnil","code":"76658"},"geometry":{"type":"Point","coordinates":[0.3569952500000001,49.51022525000003]}}]}