{"type":"FeatureCollection","features":[{"type":"Feature","properties":{"codesPostaux":["76630"],"population":410,"nom":"Sauchay","code":"76665"},"geometry":{"type":"Point","coordinates":[1.2017751401869161,49.916948411214946]}}]}