{"type":"FeatureCollection","features":[{"type":"Feature","properties":{"codesPostaux":["76540"],"population":404,"nom":"Thiergeville","code":"76688"},"geometry":{"type":"Point","coordinates":[0.4869957258064515,49.73142532258064]}}]}