{"type":"FeatureCollection","features":[{"type":"Feature","properties":{"codesPostaux":["76560"],"population":386,"nom":"Le Torp-Mesnil","code":"76699"},"geometry":{"type":"Point","coordinates":[0.902728653846154,49.725295961538464]}}]}