{"type":"FeatureCollection","features":[{"type":"Feature","properties":{"codesPostaux":["76890"],"population":1508,"nom":"T\u00f4tes","code":"76700"},"geometry":{"type":"Point","coordinates":[1.0416768965517238,49.685036034482756]}}]}