{"type":"FeatureCollection","features":[{"type":"Feature","properties":{"codesPostaux":["76470"],"population":5116,"nom":"Le Tr\u00e9port","code":"76711"},"geometry":{"type":"Point","coordinates":[1.3791536111111113,50.05594763888891]}}]}