{"type":"FeatureCollection","features":[{"type":"Feature","properties":{"codesPostaux":["76890"],"population":424,"nom":"Vassonville","code":"76723"},"geometry":{"type":"Point","coordinates":[1.0811402531645566,49.69281594936709]}}]}