{"type":"FeatureCollection","features":[{"type":"Feature","properties":{"codesPostaux":["76150"],"population":948,"nom":"La Vaupali\u00e8re","code":"76728"},"geometry":{"type":"Point","coordinates":[0.9895967187500001,49.48120078125]}}]}