{"type":"FeatureCollection","features":[{"type":"Feature","properties":{"codesPostaux":["76119"],"population":1005,"nom":"Varengeville-sur-Mer","code":"76720"},"geometry":{"type":"Point","coordinates":[0.9968415853658537,49.90540951219513]}}]}