{"type":"FeatureCollection","features":[{"type":"Feature","properties":{"codesPostaux":["76110"],"population":361,"nom":"Virville","code":"76747"},"geometry":{"type":"Point","coordinates":[0.35533694444444425,49.59101805555556]}}]}