{"type":"FeatureCollection","features":[{"type":"Feature","properties":{"codesPostaux":["76520"],"population":1158,"nom":"Ymare","code":"76753"},"geometry":{"type":"Point","coordinates":[1.1661896629213482,49.3457017977528]}}]}