{"type":"FeatureCollection","features":[{"type":"Feature","properties":{"codesPostaux":["76540"],"population":576,"nom":"Ypreville-Biville","code":"76755"},"geometry":{"type":"Point","coordinates":[0.5311317441860465,49.69358046511627]}}]}