{"type":"FeatureCollection","features":[{"type":"Feature","properties":{"codesPostaux":["77760"],"population":388,"nom":"Amponville","code":"77003"},"geometry":{"type":"Point","coordinates":[2.5266721052631578,48.29470631578948]}}]}