{"type":"FeatureCollection","features":[{"type":"Feature","properties":{"codesPostaux":["77630"],"population":1040,"nom":"Arbonne-la-For\u00eat","code":"77006"},"geometry":{"type":"Point","coordinates":[2.5590610256410256,48.416526153846156]}}]}