{"type":"FeatureCollection","features":[{"type":"Feature","properties":{"codesPostaux":["77410"],"population":3245,"nom":"Annet-sur-Marne","code":"77005"},"geometry":{"type":"Point","coordinates":[2.704297821782179,48.91934039603961]}}]}