{"type":"FeatureCollection","features":[{"type":"Feature","properties":{"codesPostaux":["77130"],"population":167,"nom":"Barbey","code":"77021"},"geometry":{"type":"Point","coordinates":[3.048903773584906,48.364987358490566]}}]}