{"type":"FeatureCollection","features":[{"type":"Feature","properties":{"codesPostaux":["77630"],"population":1277,"nom":"Barbizon","code":"77022"},"geometry":{"type":"Point","coordinates":[2.5996104918032783,48.449657377049185]}}]}