{"type":"FeatureCollection","features":[{"type":"Feature","properties":{"codesPostaux":["77940"],"population":566,"nom":"Blennes","code":"77035"},"geometry":{"type":"Point","coordinates":[3.0082964444444444,48.2393737777778]}}]}