{"type":"FeatureCollection","features":[{"type":"Feature","properties":{"codesPostaux":["77310"],"population":3776,"nom":"Boissise-le-Roi","code":"77040"},"geometry":{"type":"Point","coordinates":[2.566374556962025,48.51694936708863]}}]}