{"type":"FeatureCollection","features":[{"type":"Feature","properties":{"codesPostaux":["77580"],"population":1463,"nom":"Bouleurs","code":"77047"},"geometry":{"type":"Point","coordinates":[2.905774222222222,48.87992411111111]}}]}