{"type":"FeatureCollection","features":[{"type":"Feature","properties":{"codesPostaux":["77400"],"population":464,"nom":"Carnetin","code":"77062"},"geometry":{"type":"Point","coordinates":[2.700605294117647,48.90404921568628]}}]}