{"type":"FeatureCollection","features":[{"type":"Feature","properties":{"codesPostaux":["77320"],"population":317,"nom":"Cerneux","code":"77066"},"geometry":{"type":"Point","coordinates":[3.3450645192307698,48.70673961538459]}}]}