{"type":"FeatureCollection","features":[{"type":"Feature","properties":{"codesPostaux":["77260"],"population":1376,"nom":"Chamigny","code":"77078"},"geometry":{"type":"Point","coordinates":[3.137138278145694,48.98617834437085]}}]}