{"type":"FeatureCollection","features":[{"type":"Feature","properties":{"codesPostaux":["77720"],"population":1474,"nom":"La Chapelle-Gauthier","code":"77086"},"geometry":{"type":"Point","coordinates":[2.8591855307262573,48.53337212290506]}}]}