{"type":"FeatureCollection","features":[{"type":"Feature","properties":{"codesPostaux":["77410"],"population":11599,"nom":"Claye-Souilly","code":"77118"},"geometry":{"type":"Point","coordinates":[2.6768618399999995,48.940565599999985]}}]}