{"type":"FeatureCollection","features":[{"type":"Feature","properties":{"codesPostaux":["77440"],"population":1801,"nom":"Congis-sur-Th\u00e9rouanne","code":"77126"},"geometry":{"type":"Point","coordinates":[2.9771847058823537,49.01728294117647]}}]}