{"type":"FeatureCollection","features":[{"type":"Feature","properties":{"codesPostaux":["77440"],"population":631,"nom":"Cocherel","code":"77120"},"geometry":{"type":"Point","coordinates":[3.0933944897959194,49.01867]}}]}