{"type":"FeatureCollection","features":[{"type":"Feature","properties":{"codesPostaux":["77580"],"population":4253,"nom":"Cr\u00e9cy-la-Chapelle","code":"77142"},"geometry":{"type":"Point","coordinates":[2.9199346969696975,48.85548583333332]}}]}