{"type":"FeatureCollection","features":[{"type":"Feature","properties":{"codesPostaux":["77520"],"population":2913,"nom":"Donnemarie-Dontilly","code":"77159"},"geometry":{"type":"Point","coordinates":[3.1187921641791054,48.48020708955222]}}]}