{"type":"FeatureCollection","features":[{"type":"Feature","properties":{"codesPostaux":["77126"],"population":319,"nom":"\u00c9gligny","code":"77167"},"geometry":{"type":"Point","coordinates":[3.1289755769230783,48.43687673076925]}}]}