{"type":"FeatureCollection","features":[{"type":"Feature","properties":{"codesPostaux":["77450"],"population":6189,"nom":"Esbly","code":"77171"},"geometry":{"type":"Point","coordinates":[2.8130566129032246,48.90163306451613]}}]}