{"type":"FeatureCollection","features":[{"type":"Feature","properties":{"codesPostaux":["77515"],"population":2513,"nom":"Faremoutiers","code":"77176"},"geometry":{"type":"Point","coordinates":[3.002312571428572,48.77916628571428]}}]}