{"type":"FeatureCollection","features":[{"type":"Feature","properties":{"codesPostaux":["77166"],"population":2588,"nom":"\u00c9vry-Gr\u00e9gy-sur-Yerre","code":"77175"},"geometry":{"type":"Point","coordinates":[2.6452089714285707,48.65567279999999]}}]}