{"type":"FeatureCollection","features":[{"type":"Feature","properties":{"codesPostaux":["77320"],"population":4770,"nom":"La Fert\u00e9-Gaucher","code":"77182"},"geometry":{"type":"Point","coordinates":[3.307693592233009,48.78955665048545]}}]}