{"type":"FeatureCollection","features":[{"type":"Feature","properties":{"codesPostaux":["77120"],"population":147,"nom":"Giremoutiers","code":"77206"},"geometry":{"type":"Point","coordinates":[3.030667878787879,48.8531709090909]}}]}