{"type":"FeatureCollection","features":[{"type":"Feature","properties":{"codesPostaux":["77910"],"population":1345,"nom":"Germigny-l'\u00c9v\u00eaque","code":"77203"},"geometry":{"type":"Point","coordinates":[2.956208906249999,48.98824750000001]}}]}