{"type":"FeatureCollection","features":[{"type":"Feature","properties":{"codesPostaux":["77515"],"population":324,"nom":"Hautefeuille","code":"77224"},"geometry":{"type":"Point","coordinates":[2.9659102083333337,48.768577708333346]}}]}