{"type":"FeatureCollection","features":[{"type":"Feature","properties":{"codesPostaux":["77390"],"population":3358,"nom":"Guignes","code":"77222"},"geometry":{"type":"Point","coordinates":[2.804694479166667,48.63679677083334]}}]}