{"type":"FeatureCollection","features":[{"type":"Feature","properties":{"codesPostaux":["77760"],"population":283,"nom":"Guercheville","code":"77220"},"geometry":{"type":"Point","coordinates":[2.5544075862068962,48.2583948275862]}}]}