{"type":"FeatureCollection","features":[{"type":"Feature","properties":{"codesPostaux":["77970"],"population":1533,"nom":"Jouy-le-Ch\u00e2tel","code":"77239"},"geometry":{"type":"Point","coordinates":[3.1511418333333348,48.67449974999999]}}]}