{"type":"FeatureCollection","features":[{"type":"Feature","properties":{"codesPostaux":["77450"],"population":919,"nom":"Isles-l\u00e8s-Villenoy","code":"77232"},"geometry":{"type":"Point","coordinates":[2.830274545454545,48.911995]}}]}