{"type":"FeatureCollection","features":[{"type":"Feature","properties":{"codesPostaux":["77148"],"population":463,"nom":"Laval-en-Brie","code":"77245"},"geometry":{"type":"Point","coordinates":[2.9723620869565206,48.45542426086956]}}]}