{"type":"FeatureCollection","features":[{"type":"Feature","properties":{"codesPostaux":["77700"],"population":7722,"nom":"Magny-le-Hongre","code":"77268"},"geometry":{"type":"Point","coordinates":[2.819585375,48.86788612500002]}}]}