{"type":"FeatureCollection","features":[{"type":"Feature","properties":{"codesPostaux":["77540"],"population":1543,"nom":"Lumigny-Nesles-Ormeaux","code":"77264"},"geometry":{"type":"Point","coordinates":[2.962529142857142,48.71573222857146]}}]}