{"type":"FeatureCollection","features":[{"type":"Feature","properties":{"codesPostaux":["77570"],"population":128,"nom":"Maisoncelles-en-G\u00e2tinais","code":"77271"},"geometry":{"type":"Point","coordinates":[2.617838222222222,48.1851548888889]}}]}