{"type":"FeatureCollection","features":[{"type":"Feature","properties":{"codesPostaux":["77520"],"population":244,"nom":"Meigneux","code":"77286"},"geometry":{"type":"Point","coordinates":[3.094771086956522,48.5133120652174]}}]}