{"type":"FeatureCollection","features":[{"type":"Feature","properties":{"codesPostaux":["77410"],"population":1113,"nom":"Messy","code":"77292"},"geometry":{"type":"Point","coordinates":[2.6894572941176476,48.966189176470586]}}]}