{"type":"FeatureCollection","features":[{"type":"Feature","properties":{"codesPostaux":["77130"],"population":17173,"nom":"Montereau-Fault-Yonne","code":"77305"},"geometry":{"type":"Point","coordinates":[2.963373047619049,48.38660657142858]}}]}