{"type":"FeatureCollection","features":[{"type":"Feature","properties":{"codesPostaux":["77710"],"population":702,"nom":"Nanteau-sur-Lunain","code":"77329"},"geometry":{"type":"Point","coordinates":[2.8213584615384626,48.25538956043956]}}]}