{"type":"FeatureCollection","features":[{"type":"Feature","properties":{"codesPostaux":["77100"],"population":5890,"nom":"Nanteuil-l\u00e8s-Meaux","code":"77330"},"geometry":{"type":"Point","coordinates":[2.901409354838709,48.93077806451614]}}]}