{"type":"FeatureCollection","features":[{"type":"Feature","properties":{"codesPostaux":["77114"],"population":355,"nom":"Noyen-sur-Seine","code":"77341"},"geometry":{"type":"Point","coordinates":[3.3408246060606053,48.45316787878787]}}]}