{"type":"FeatureCollection","features":[{"type":"Feature","properties":{"codesPostaux":["77167"],"population":827,"nom":"Poligny","code":"77370"},"geometry":{"type":"Point","coordinates":[2.7518780769230777,48.236783942307675]}}]}