{"type":"FeatureCollection","features":[{"type":"Feature","properties":{"codesPostaux":["77000"],"population":3238,"nom":"La Rochette","code":"77389"},"geometry":{"type":"Point","coordinates":[2.662657910447761,48.50441895522387]}}]}