{"type":"FeatureCollection","features":[{"type":"Feature","properties":{"codesPostaux":["77750"],"population":1926,"nom":"Saint-Cyr-sur-Morin","code":"77405"},"geometry":{"type":"Point","coordinates":[3.17094532934132,48.91191952095807]}}]}