{"type":"FeatureCollection","features":[{"type":"Feature","properties":{"codesPostaux":["77650"],"population":887,"nom":"Saint-Loup-de-Naud","code":"77418"},"geometry":{"type":"Point","coordinates":[3.221311224489794,48.536074897959175]}}]}