{"type":"FeatureCollection","features":[{"type":"Feature","properties":{"codesPostaux":["77370"],"population":231,"nom":"Saint-Just-en-Brie","code":"77416"},"geometry":{"type":"Point","coordinates":[3.1268804761904763,48.6028430952381]}}]}