{"type":"FeatureCollection","features":[{"type":"Feature","properties":{"codesPostaux":["77120"],"population":1361,"nom":"Saints","code":"77433"},"geometry":{"type":"Point","coordinates":[3.061257375886526,48.757589148936184]}}]}