{"type":"FeatureCollection","features":[{"type":"Feature","properties":{"codesPostaux":["77210"],"population":2325,"nom":"Samoreau","code":"77442"},"geometry":{"type":"Point","coordinates":[2.7784675806451613,48.42064177419355]}}]}