{"type":"FeatureCollection","features":[{"type":"Feature","properties":{"codesPostaux":["77240"],"population":1917,"nom":"Seine-Port","code":"77447"},"geometry":{"type":"Point","coordinates":[2.555744347826087,48.55464239130437]}}]}