{"type":"FeatureCollection","features":[{"type":"Feature","properties":{"codesPostaux":["77320"],"population":343,"nom":"Sancy-l\u00e8s-Provins","code":"77444"},"geometry":{"type":"Point","coordinates":[3.394086288659795,48.710366597938126]}}]}