{"type":"FeatureCollection","features":[{"type":"Feature","properties":{"codesPostaux":["77460"],"population":5494,"nom":"Souppes-sur-Loing","code":"77458"},"geometry":{"type":"Point","coordinates":[2.7441070940170937,48.18540085470085]}}]}