{"type":"FeatureCollection","features":[{"type":"Feature","properties":{"codesPostaux":["77111"],"population":2055,"nom":"Soignolles-en-Brie","code":"77455"},"geometry":{"type":"Point","coordinates":[2.707743333333332,48.64623486111114]}}]}