{"type":"FeatureCollection","features":[{"type":"Feature","properties":{"codesPostaux":["77115"],"population":1154,"nom":"Sivry-Courtry","code":"77453"},"geometry":{"type":"Point","coordinates":[2.762035270270269,48.533630202702675]}}]}