{"type":"FeatureCollection","features":[{"type":"Feature","properties":{"codesPostaux":["77130"],"population":221,"nom":"La Tombe","code":"77467"},"geometry":{"type":"Point","coordinates":[3.0907485365853655,48.38823170731708]}}]}