{"type":"FeatureCollection","features":[{"type":"Feature","properties":{"codesPostaux":["77360"],"population":13200,"nom":"Vaires-sur-Marne","code":"77479"},"geometry":{"type":"Point","coordinates":[2.630949672131146,48.86927622950817]}}]}