{"type":"FeatureCollection","features":[{"type":"Feature","properties":{"codesPostaux":["77240"],"population":7154,"nom":"Vert-Saint-Denis","code":"77495"},"geometry":{"type":"Point","coordinates":[2.627814408602151,48.56568892473117]}}]}