{"type":"FeatureCollection","features":[{"type":"Feature","properties":{"codesPostaux":["77470"],"population":404,"nom":"Villemareuil","code":"77505"},"geometry":{"type":"Point","coordinates":[2.9766820967741943,48.92431806451614]}}]}