{"type":"FeatureCollection","features":[{"type":"Feature","properties":{"codesPostaux":["78770"],"population":473,"nom":"Autouillet","code":"78036"},"geometry":{"type":"Point","coordinates":[1.79723,48.846256874999995]}}]}