{"type":"FeatureCollection","features":[{"type":"Feature","properties":{"codesPostaux":["78126"],"population":1154,"nom":"Aulnay-sur-Mauldre","code":"78033"},"geometry":{"type":"Point","coordinates":[1.8410442187499994,48.93021265625]}}]}