{"type":"FeatureCollection","features":[{"type":"Feature","properties":{"codesPostaux":["78200"],"population":271,"nom":"Boinvilliers","code":"78072"},"geometry":{"type":"Point","coordinates":[1.663792203389831,48.9197220338983]}}]}