{"type":"FeatureCollection","features":[{"type":"Feature","properties":{"codesPostaux":["78390"],"population":14008,"nom":"Bois-d'Arcy","code":"78073"},"geometry":{"type":"Point","coordinates":[2.026473793103448,48.80682482758619]}}]}