{"type":"FeatureCollection","features":[{"type":"Feature","properties":{"codesPostaux":["78200"],"population":621,"nom":"Boissy-Mauvoisin","code":"78082"},"geometry":{"type":"Point","coordinates":[1.5878282258064513,48.9684229032258]}}]}