{"type":"FeatureCollection","features":[{"type":"Feature","properties":{"codesPostaux":["78830"],"population":1942,"nom":"Bullion","code":"78120"},"geometry":{"type":"Point","coordinates":[1.9810979729729736,48.619250540540556]}}]}