{"type":"FeatureCollection","features":[{"type":"Feature","properties":{"codesPostaux":["78720"],"population":1633,"nom":"Cernay-la-Ville","code":"78128"},"geometry":{"type":"Point","coordinates":[1.9585371774193547,48.67004935483871]}}]}