{"type":"FeatureCollection","features":[{"type":"Feature","properties":{"codesPostaux":["78570"],"population":10013,"nom":"Chanteloup-les-Vignes","code":"78138"},"geometry":{"type":"Point","coordinates":[2.0310365151515164,48.97539742424243]}}]}