{"type":"FeatureCollection","features":[{"type":"Feature","properties":{"codesPostaux":["78460"],"population":5750,"nom":"Chevreuse","code":"78160"},"geometry":{"type":"Point","coordinates":[2.0393833962264156,48.70825169811322]}}]}