{"type":"FeatureCollection","features":[{"type":"Feature","properties":{"codesPostaux":["78410"],"population":585,"nom":"La Falaise","code":"78230"},"geometry":{"type":"Point","coordinates":[1.8264721794871788,48.94079833333335]}}]}