{"type":"FeatureCollection","features":[{"type":"Feature","properties":{"codesPostaux":["78930"],"population":2135,"nom":"Guerville","code":"78291"},"geometry":{"type":"Point","coordinates":[1.7410284761904768,48.95267485714285]}}]}