{"type":"FeatureCollection","features":[{"type":"Feature","properties":{"codesPostaux":["78440"],"population":4359,"nom":"Issou","code":"78314"},"geometry":{"type":"Point","coordinates":[1.7880537500000002,48.98897354166666]}}]}