{"type":"FeatureCollection","features":[{"type":"Feature","properties":{"codesPostaux":["78200"],"population":45052,"nom":"Mantes-la-Jolie","code":"78361"},"geometry":{"type":"Point","coordinates":[1.7018874509803918,48.99444294117646]}}]}