{"type":"FeatureCollection","features":[{"type":"Feature","properties":{"codesPostaux":["78320"],"population":6605,"nom":"Le Mesnil-Saint-Denis","code":"78397"},"geometry":{"type":"Point","coordinates":[1.963054620689654,48.74025620689654]}}]}