{"type":"FeatureCollection","features":[{"type":"Feature","properties":{"codesPostaux":["78970"],"population":3626,"nom":"M\u00e9zi\u00e8res-sur-Seine","code":"78402"},"geometry":{"type":"Point","coordinates":[1.7800148314606736,48.94949460674157]}}]}