{"type":"FeatureCollection","features":[{"type":"Feature","properties":{"codesPostaux":["78440"],"population":338,"nom":"Montalet-le-Bois","code":"78416"},"geometry":{"type":"Point","coordinates":[1.8285017142857147,49.04530657142857]}}]}