{"type":"FeatureCollection","features":[{"type":"Feature","properties":{"codesPostaux":["78124"],"population":529,"nom":"Montainville","code":"78415"},"geometry":{"type":"Point","coordinates":[1.8603497402597398,48.87923077922079]}}]}