{"type":"FeatureCollection","features":[{"type":"Feature","properties":{"codesPostaux":["78640"],"population":926,"nom":"Neauphle-le-Vieux","code":"78443"},"geometry":{"type":"Point","coordinates":[1.8614533599999994,48.81590016]}}]}