{"type":"FeatureCollection","features":[{"type":"Feature","properties":{"codesPostaux":["78230"],"population":16237,"nom":"Le Pecq","code":"78481"},"geometry":{"type":"Point","coordinates":[2.1022552238805967,48.8923847761194]}}]}