{"type":"FeatureCollection","features":[{"type":"Feature","properties":{"codesPostaux":["78980"],"population":454,"nom":"Saint-Illiers-le-Bois","code":"78559"},"geometry":{"type":"Point","coordinates":[1.5093594,48.961749999999995]}}]}