{"type":"FeatureCollection","features":[{"type":"Feature","properties":{"codesPostaux":["78730"],"population":911,"nom":"Sainte-Mesme","code":"78569"},"geometry":{"type":"Point","coordinates":[1.9465373417721528,48.53625696202533]}}]}