{"type":"FeatureCollection","features":[{"type":"Feature","properties":{"codesPostaux":["78125"],"population":752,"nom":"Vieille-\u00c9glise-en-Yvelines","code":"78655"},"geometry":{"type":"Point","coordinates":[1.875860579710145,48.66913724637683]}}]}