{"type":"FeatureCollection","features":[{"type":"Feature","properties":{"codesPostaux":["78670"],"population":5127,"nom":"Villennes-sur-Seine","code":"78672"},"geometry":{"type":"Point","coordinates":[1.9965468571428573,48.93827814285716]}}]}