{"type":"FeatureCollection","features":[{"type":"Feature","properties":{"codesPostaux":["79350"],"population":867,"nom":"Amailloux","code":"79008"},"geometry":{"type":"Point","coordinates":[-0.30585411003236246,46.74050792880258]}}]}