{"type":"FeatureCollection","features":[{"type":"Feature","properties":{"codesPostaux":["79150","79300"],"population":3287,"nom":"Argentonnay","code":"79013"},"geometry":{"type":"Point","coordinates":[-0.421600895522388,46.96903543710019]}}]}