{"type":"FeatureCollection","features":[{"type":"Feature","properties":{"codesPostaux":["79110"],"population":212,"nom":"Aubign\u00e9","code":"79018"},"geometry":{"type":"Point","coordinates":[-0.15118630136986302,46.04043568493151]}}]}