{"type":"FeatureCollection","features":[{"type":"Feature","properties":{"codesPostaux":["79370"],"population":989,"nom":"Beaussais-Vitr\u00e9","code":"79030"},"geometry":{"type":"Point","coordinates":[-0.17860678733031662,46.28389764705885]}}]}