{"type":"FeatureCollection","features":[{"type":"Feature","properties":{"codesPostaux":["79290"],"population":1062,"nom":"Bouill\u00e9-Loretz","code":"79043"},"geometry":{"type":"Point","coordinates":[-0.26441604081632647,47.08520069387754]}}]}