{"type":"FeatureCollection","features":[{"type":"Feature","properties":{"codesPostaux":["79300"],"population":18962,"nom":"Bressuire","code":"79049"},"geometry":{"type":"Point","coordinates":[-0.47843550224887543,46.85883337331333]}}]}