{"type":"FeatureCollection","features":[{"type":"Feature","properties":{"codesPostaux":["79310"],"population":238,"nom":"La Boissi\u00e8re-en-G\u00e2tine","code":"79040"},"geometry":{"type":"Point","coordinates":[-0.3789669565217392,46.54146930434783]}}]}