{"type":"FeatureCollection","features":[{"type":"Feature","properties":{"codesPostaux":["79290"],"population":785,"nom":"Brion-pr\u00e8s-Thouet","code":"79056"},"geometry":{"type":"Point","coordinates":[-0.1859686666666667,47.05097826666668]}}]}