{"type":"FeatureCollection","features":[{"type":"Feature","properties":{"codesPostaux":["79320"],"population":498,"nom":"Le Breuil-Bernard","code":"79051"},"geometry":{"type":"Point","coordinates":[-0.5559439735099339,46.71186483443708]}}]}