{"type":"FeatureCollection","features":[{"type":"Feature","properties":{"codesPostaux":["79230"],"population":713,"nom":"Br\u00fblain","code":"79058"},"geometry":{"type":"Point","coordinates":[-0.3177091874999999,46.20090012499999]}}]}