{"type":"FeatureCollection","features":[{"type":"Feature","properties":{"codesPostaux":["79190"],"population":176,"nom":"Caunay","code":"79060"},"geometry":{"type":"Point","coordinates":[0.0878577027027027,46.19991027027026]}}]}