{"type":"FeatureCollection","features":[{"type":"Feature","properties":{"codesPostaux":["79150","79290"],"population":2022,"nom":"Val en Vignes","code":"79063"},"geometry":{"type":"Point","coordinates":[-0.3544222289156628,47.039979789156625]}}]}