{"type":"FeatureCollection","features":[{"type":"Feature","properties":{"codesPostaux":["79360"],"population":992,"nom":"Plaine-d'Argenson","code":"79078"},"geometry":{"type":"Point","coordinates":[-0.4801168032786885,46.13429045081968]}}]}