{"type":"FeatureCollection","features":[{"type":"Feature","properties":{"codesPostaux":["79410"],"population":1732,"nom":"Cherveux","code":"79086"},"geometry":{"type":"Point","coordinates":[-0.352189214659686,46.42536539267016]}}]}