{"type":"FeatureCollection","features":[{"type":"Feature","properties":{"codesPostaux":["79120"],"population":606,"nom":"Chey","code":"79087"},"geometry":{"type":"Point","coordinates":[-0.04962193548387097,46.29376749999997]}}]}