{"type":"FeatureCollection","features":[{"type":"Feature","properties":{"codesPostaux":["79800"],"population":263,"nom":"La Couarde","code":"79098"},"geometry":{"type":"Point","coordinates":[-0.14465402597402596,46.311770974025976]}}]}