{"type":"FeatureCollection","features":[{"type":"Feature","properties":{"codesPostaux":["79170"],"population":105,"nom":"Juill\u00e9","code":"79142"},"geometry":{"type":"Point","coordinates":[-0.22361804123711346,46.114372164948456]}}]}