{"type":"FeatureCollection","features":[{"type":"Feature","properties":{"codesPostaux":["79110"],"population":383,"nom":"Loubill\u00e9","code":"79154"},"geometry":{"type":"Point","coordinates":[-0.060911034482758634,46.0452500689655]}}]}