{"type":"FeatureCollection","features":[{"type":"Feature","properties":{"codesPostaux":["79460"],"population":2680,"nom":"Magn\u00e9","code":"79162"},"geometry":{"type":"Point","coordinates":[-0.5566461818181816,46.310047545454566]}}]}