{"type":"FeatureCollection","features":[{"type":"Feature","properties":{"codesPostaux":["79800"],"population":1749,"nom":"La Mothe-Saint-H\u00e9ray","code":"79184"},"geometry":{"type":"Point","coordinates":[-0.12236942857142859,46.35372835714285]}}]}