{"type":"FeatureCollection","features":[{"type":"Feature","properties":{"codesPostaux":["79100"],"population":922,"nom":"Oiron","code":"79196"},"geometry":{"type":"Point","coordinates":[-0.0882000740740741,46.93310955555556]}}]}