{"type":"FeatureCollection","features":[{"type":"Feature","properties":{"codesPostaux":["79250"],"population":5632,"nom":"Nueil-les-Aubiers","code":"79195"},"geometry":{"type":"Point","coordinates":[-0.6044965498154983,46.92976051660516]}}]}