{"type":"FeatureCollection","features":[{"type":"Feature","properties":{"codesPostaux":["79160"],"population":65,"nom":"Puihardy","code":"79223"},"geometry":{"type":"Point","coordinates":[-0.5429991666666668,46.52501520833332]}}]}