{"type":"FeatureCollection","features":[{"type":"Feature","properties":{"codesPostaux":["79450"],"population":1752,"nom":"Saint-Aubin-le-Cloud","code":"79239"},"geometry":{"type":"Point","coordinates":[-0.3383763880597015,46.66024713432835]}}]}