{"type":"FeatureCollection","features":[{"type":"Feature","properties":{"codesPostaux":["79800"],"population":641,"nom":"Sainte-Eanne","code":"79246"},"geometry":{"type":"Point","coordinates":[-0.1348106849315068,46.38946068493151]}}]}