{"type":"FeatureCollection","features":[{"type":"Feature","properties":{"codesPostaux":["79210"],"population":1591,"nom":"Saint-Hilaire-la-Palud","code":"79257"},"geometry":{"type":"Point","coordinates":[-0.7112125161290321,46.266833548387105]}}]}