{"type":"FeatureCollection","features":[{"type":"Feature","properties":{"codesPostaux":["79200"],"population":413,"nom":"Saint-Germain-de-Longue-Chaume","code":"79255"},"geometry":{"type":"Point","coordinates":[-0.3445422307692308,46.7190953076923]}}]}