{"type":"FeatureCollection","features":[{"type":"Feature","properties":{"codesPostaux":["79600"],"population":368,"nom":"Saint-G\u00e9n\u00e9roux","code":"79252"},"geometry":{"type":"Point","coordinates":[-0.14881614285714284,46.88117871428573]}}]}