{"type":"FeatureCollection","features":[{"type":"Feature","properties":{"codesPostaux":["79160"],"population":372,"nom":"Saint-Maixent-de-Beugn\u00e9","code":"79269"},"geometry":{"type":"Point","coordinates":[-0.6177460732984295,46.5157792146597]}}]}