{"type":"FeatureCollection","features":[{"type":"Feature","properties":{"codesPostaux":["79420"],"population":350,"nom":"Saint-Lin","code":"79267"},"geometry":{"type":"Point","coordinates":[-0.23175615853658527,46.53204353658537]}}]}