{"type":"FeatureCollection","features":[{"type":"Feature","properties":{"codesPostaux":["79400"],"population":6545,"nom":"Saint-Maixent-l'\u00c9cole","code":"79270"},"geometry":{"type":"Point","coordinates":[-0.20571835051546394,46.41081360824744]}}]}