{"type":"FeatureCollection","features":[{"type":"Feature","properties":{"codesPostaux":["79500"],"population":877,"nom":"Saint-Martin-l\u00e8s-Melle","code":"79279"},"geometry":{"type":"Point","coordinates":[-0.16770373626373633,46.222491098901116]}}]}