{"type":"FeatureCollection","features":[{"type":"Feature","properties":{"codesPostaux":["79220"],"population":809,"nom":"Sainte-Ouenne","code":"79284"},"geometry":{"type":"Point","coordinates":[-0.444760704225352,46.44355535211266]}}]}