{"type":"FeatureCollection","features":[{"type":"Feature","properties":{"codesPostaux":["79270"],"population":1876,"nom":"Saint-Symphorien","code":"79298"},"geometry":{"type":"Point","coordinates":[-0.48428322033898324,46.26893288135596]}}]}