{"type":"FeatureCollection","features":[{"type":"Feature","properties":{"codesPostaux":["79240"],"population":384,"nom":"Scill\u00e9","code":"79309"},"geometry":{"type":"Point","coordinates":[-0.5564091826923077,46.60062706730771]}}]}