{"type":"FeatureCollection","features":[{"type":"Feature","properties":{"codesPostaux":["79270"],"population":756,"nom":"Sansais","code":"79304"},"geometry":{"type":"Point","coordinates":[-0.594646,46.290566800000015]}}]}