{"type":"FeatureCollection","features":[{"type":"Feature","properties":{"codesPostaux":["79800"],"population":884,"nom":"Souvign\u00e9","code":"79319"},"geometry":{"type":"Point","coordinates":[-0.16948515999999988,46.35890448000001]}}]}