{"type":"FeatureCollection","features":[{"type":"Feature","properties":{"codesPostaux":["79220"],"population":654,"nom":"Surin","code":"79320"},"geometry":{"type":"Point","coordinates":[-0.45757201257861646,46.47472522012575]}}]}