{"type":"FeatureCollection","features":[{"type":"Feature","properties":{"codesPostaux":["79110"],"population":318,"nom":"Tillou","code":"79330"},"geometry":{"type":"Point","coordinates":[-0.11891423728813563,46.14996771186442]}}]}