{"type":"FeatureCollection","features":[{"type":"Feature","properties":{"codesPostaux":["79100"],"population":131,"nom":"Tourtenay","code":"79331"},"geometry":{"type":"Point","coordinates":[-0.11088740259740265,47.04469961038962]}}]}