{"type":"FeatureCollection","features":[{"type":"Feature","properties":{"codesPostaux":["79240"],"population":570,"nom":"Vernoux-en-G\u00e2tine","code":"79342"},"geometry":{"type":"Point","coordinates":[-0.5195715,46.62424928571428]}}]}