{"type":"FeatureCollection","features":[{"type":"Feature","properties":{"codesPostaux":["79420"],"population":124,"nom":"Vautebis","code":"79341"},"geometry":{"type":"Point","coordinates":[-0.15131233128834357,46.53571521472395]}}]}