{"type":"FeatureCollection","features":[{"type":"Feature","properties":{"codesPostaux":["80150"],"population":198,"nom":"Agenvillers","code":"80006"},"geometry":{"type":"Point","coordinates":[1.9233874999999998,50.18168234375002]}}]}