{"type":"FeatureCollection","features":[{"type":"Feature","properties":{"codesPostaux":["80110"],"population":142,"nom":"Aubvillers","code":"80037"},"geometry":{"type":"Point","coordinates":[2.4769733333333317,49.7095943859649]}}]}