{"type":"FeatureCollection","features":[{"type":"Feature","properties":{"codesPostaux":["80640"],"population":134,"nom":"Aumont","code":"80041"},"geometry":{"type":"Point","coordinates":[1.9275153191489356,49.88021829787233]}}]}