{"type":"FeatureCollection","features":[{"type":"Feature","properties":{"codesPostaux":["80430"],"population":217,"nom":"Beaucamps-le-Jeune","code":"80061"},"geometry":{"type":"Point","coordinates":[1.7674863636363634,49.81676079545457]}}]}