{"type":"FeatureCollection","features":[{"type":"Feature","properties":{"codesPostaux":["80190"],"population":175,"nom":"Billancourt","code":"80105"},"geometry":{"type":"Point","coordinates":[2.9043315254237276,49.740343389830535]}}]}