{"type":"FeatureCollection","features":[{"type":"Feature","properties":{"codesPostaux":["80440"],"population":555,"nom":"Blangy-Tronville","code":"80107"},"geometry":{"type":"Point","coordinates":[2.4253464705882344,49.87195858823531]}}]}