{"type":"FeatureCollection","features":[{"type":"Feature","properties":{"codesPostaux":["80200"],"population":339,"nom":"Bouchavesnes-Bergen","code":"80115"},"geometry":{"type":"Point","coordinates":[2.922963064516128,49.992474435483864]}}]}