{"type":"FeatureCollection","features":[{"type":"Feature","properties":{"codesPostaux":["80200"],"population":155,"nom":"Bouvincourt-en-Vermandois","code":"80128"},"geometry":{"type":"Point","coordinates":[3.0472774999999994,49.891078249999985]}}]}