{"type":"FeatureCollection","features":[{"type":"Feature","properties":{"codesPostaux":["80440"],"population":3115,"nom":"Boves","code":"80131"},"geometry":{"type":"Point","coordinates":[2.3817239884393056,49.8384790751445]}}]}