{"type":"FeatureCollection","features":[{"type":"Feature","properties":{"codesPostaux":["80540"],"population":414,"nom":"Bovelles","code":"80130"},"geometry":{"type":"Point","coordinates":[2.1418585542168667,49.890670843373485]}}]}