{"type":"FeatureCollection","features":[{"type":"Feature","properties":{"codesPostaux":["80400"],"population":56,"nom":"Breuil","code":"80139"},"geometry":{"type":"Point","coordinates":[2.9487795833333337,49.73680291666665]}}]}