{"type":"FeatureCollection","features":[{"type":"Feature","properties":{"codesPostaux":["80230"],"population":189,"nom":"Brutelles","code":"80146"},"geometry":{"type":"Point","coordinates":[1.5162825974025973,50.135300779220785]}}]}