{"type":"FeatureCollection","features":[{"type":"Feature","properties":{"codesPostaux":["80670"],"population":651,"nom":"Canaples","code":"80166"},"geometry":{"type":"Point","coordinates":[2.2261508653846147,50.05858625000001]}}]}