{"type":"FeatureCollection","features":[{"type":"Feature","properties":{"codesPostaux":["80700"],"population":271,"nom":"Champien","code":"80185"},"geometry":{"type":"Point","coordinates":[2.863985617977528,49.69240921348314]}}]}