{"type":"FeatureCollection","features":[{"type":"Feature","properties":{"codesPostaux":["80310"],"population":102,"nom":"Cavillon","code":"80180"},"geometry":{"type":"Point","coordinates":[2.0767157575757573,49.917850303030285]}}]}