{"type":"FeatureCollection","features":[{"type":"Feature","properties":{"codesPostaux":["80700"],"population":73,"nom":"La Chavatte","code":"80189"},"geometry":{"type":"Point","coordinates":[2.7644804166666668,49.756165]}}]}