{"type":"FeatureCollection","features":[{"type":"Feature","properties":{"codesPostaux":["80540"],"population":379,"nom":"Clairy-Saulchoix","code":"80198"},"geometry":{"type":"Point","coordinates":[2.1669456363636366,49.853543818181805]}}]}