{"type":"FeatureCollection","features":[{"type":"Feature","properties":{"codesPostaux":["80360"],"population":802,"nom":"Combles","code":"80204"},"geometry":{"type":"Point","coordinates":[2.8737290740740757,50.00826453703703]}}]}