{"type":"FeatureCollection","features":[{"type":"Feature","properties":{"codesPostaux":["80560"],"population":82,"nom":"Colincamps","code":"80203"},"geometry":{"type":"Point","coordinates":[2.603668450704226,50.100727183098606]}}]}