{"type":"FeatureCollection","features":[{"type":"Feature","properties":{"codesPostaux":["80160"],"population":53,"nom":"Courcelles-sous-Thoix","code":"80219"},"geometry":{"type":"Point","coordinates":[2.076777532467532,49.72036506493508]}}]}