{"type":"FeatureCollection","features":[{"type":"Feature","properties":{"codesPostaux":["80290"],"population":434,"nom":"Croixrault","code":"80227"},"geometry":{"type":"Point","coordinates":[1.985889813084112,49.79274140186917]}}]}