{"type":"FeatureCollection","features":[{"type":"Feature","properties":{"codesPostaux":["80370"],"population":306,"nom":"Cramont","code":"80221"},"geometry":{"type":"Point","coordinates":[2.0511186567164184,50.15532701492538]}}]}