{"type":"FeatureCollection","features":[{"type":"Feature","properties":{"codesPostaux":["80500"],"population":99,"nom":"Courtemanche","code":"80220"},"geometry":{"type":"Point","coordinates":[2.5430977777777777,49.66378873015873]}}]}