{"type":"FeatureCollection","features":[{"type":"Feature","properties":{"codesPostaux":["80370"],"population":281,"nom":"Doml\u00e9ger-Longvillers","code":"80245"},"geometry":{"type":"Point","coordinates":[2.0866799009900987,50.158067128712894]}}]}