{"type":"FeatureCollection","features":[{"type":"Feature","properties":{"codesPostaux":["80620"],"population":1152,"nom":"Domart-en-Ponthieu","code":"80241"},"geometry":{"type":"Point","coordinates":[2.1287391139240506,50.080397151898744]}}]}