{"type":"FeatureCollection","features":[{"type":"Feature","properties":{"codesPostaux":["80400"],"population":233,"nom":"Douilly","code":"80252"},"geometry":{"type":"Point","coordinates":[3.062950576923076,49.79721413461538]}}]}