{"type":"FeatureCollection","features":[{"type":"Feature","properties":{"codesPostaux":["80132"],"population":886,"nom":"Drucat","code":"80260"},"geometry":{"type":"Point","coordinates":[1.8629409565217396,50.14543895652174]}}]}