{"type":"FeatureCollection","features":[{"type":"Feature","properties":{"codesPostaux":["80290"],"population":305,"nom":"\u00c9quennes-\u00c9ramecourt","code":"80276"},"geometry":{"type":"Point","coordinates":[1.9594087234042545,49.73040308510637]}}]}