{"type":"FeatureCollection","features":[{"type":"Feature","properties":{"codesPostaux":["80690"],"population":189,"nom":"Ergnies","code":"80281"},"geometry":{"type":"Point","coordinates":[2.0333120689655173,50.087735517241384]}}]}