{"type":"FeatureCollection","features":[{"type":"Feature","properties":{"codesPostaux":["80580"],"population":491,"nom":"\u00c9rondelle","code":"80282"},"geometry":{"type":"Point","coordinates":[1.8783531081081086,50.04532729729731]}}]}