{"type":"FeatureCollection","features":[{"type":"Feature","properties":{"codesPostaux":["80190"],"population":137,"nom":"\u00c9talon","code":"80292"},"geometry":{"type":"Point","coordinates":[2.8475021311475412,49.76178704918033]}}]}