{"type":"FeatureCollection","features":[{"type":"Feature","properties":{"codesPostaux":["80500"],"population":391,"nom":"\u00c9telfay","code":"80293"},"geometry":{"type":"Point","coordinates":[2.6078447457627116,49.66283118644066]}}]}