{"type":"FeatureCollection","features":[{"type":"Feature","properties":{"codesPostaux":["80360"],"population":283,"nom":"Fins","code":"80312"},"geometry":{"type":"Point","coordinates":[3.036619206349206,50.03852968253968]}}]}