{"type":"FeatureCollection","features":[{"type":"Feature","properties":{"codesPostaux":["80500"],"population":153,"nom":"Figni\u00e8res","code":"80311"},"geometry":{"type":"Point","coordinates":[2.5880204838709675,49.6831112903226]}}]}