{"type":"FeatureCollection","features":[{"type":"Feature","properties":{"codesPostaux":["80750"],"population":677,"nom":"Fienvillers","code":"80310"},"geometry":{"type":"Point","coordinates":[2.2380905468749983,50.118654375]}}]}