{"type":"FeatureCollection","features":[{"type":"Feature","properties":{"codesPostaux":["80560"],"population":178,"nom":"Forceville","code":"80329"},"geometry":{"type":"Point","coordinates":[2.557966962025317,50.06629531645569]}}]}