{"type":"FeatureCollection","features":[{"type":"Feature","properties":{"codesPostaux":["80150"],"population":161,"nom":"Fontaine-sur-Maye","code":"80327"},"geometry":{"type":"Point","coordinates":[1.9232457407407413,50.23562611111111]}}]}