{"type":"FeatureCollection","features":[{"type":"Feature","properties":{"codesPostaux":["80510"],"population":534,"nom":"Fontaine-sur-Somme","code":"80328"},"geometry":{"type":"Point","coordinates":[1.9358426612903228,50.030649596774175]}}]}