{"type":"FeatureCollection","features":[{"type":"Feature","properties":{"codesPostaux":["80140"],"population":69,"nom":"Foucaucourt-Hors-Nesle","code":"80336"},"geometry":{"type":"Point","coordinates":[1.7148065306122449,49.916906938775526]}}]}