{"type":"FeatureCollection","features":[{"type":"Feature","properties":{"codesPostaux":["80140"],"population":192,"nom":"Fresnes-Tilloloy","code":"80354"},"geometry":{"type":"Point","coordinates":[1.7646861764705883,49.98247294117647]}}]}