{"type":"FeatureCollection","features":[{"type":"Feature","properties":{"codesPostaux":["80700"],"population":340,"nom":"Gruny","code":"80393"},"geometry":{"type":"Point","coordinates":[2.8129878571428564,49.72566404761904]}}]}