{"type":"FeatureCollection","features":[{"type":"Feature","properties":{"codesPostaux":["80700"],"population":75,"nom":"Grivillers","code":"80391"},"geometry":{"type":"Point","coordinates":[2.70278181818182,49.65813681818182]}}]}