{"type":"FeatureCollection","features":[{"type":"Feature","properties":{"codesPostaux":["80310"],"population":721,"nom":"Hangest-sur-Somme","code":"80416"},"geometry":{"type":"Point","coordinates":[2.0412704477611943,49.9818794029851]}}]}