{"type":"FeatureCollection","features":[{"type":"Feature","properties":{"codesPostaux":["80500"],"population":416,"nom":"Hargicourt","code":"80419"},"geometry":{"type":"Point","coordinates":[2.5209163750000005,49.713472125000024]}}]}