{"type":"FeatureCollection","features":[{"type":"Feature","properties":{"codesPostaux":["80131"],"population":1650,"nom":"Harbonni\u00e8res","code":"80417"},"geometry":{"type":"Point","coordinates":[2.665699655172414,49.84222195402298]}}]}