{"type":"FeatureCollection","features":[{"type":"Feature","properties":{"codesPostaux":["80680"],"population":529,"nom":"H\u00e9b\u00e9court","code":"80424"},"geometry":{"type":"Point","coordinates":[2.2596217567567574,49.819804459459455]}}]}