{"type":"FeatureCollection","features":[{"type":"Feature","properties":{"codesPostaux":["80670"],"population":411,"nom":"Havernas","code":"80423"},"geometry":{"type":"Point","coordinates":[2.2306029333333326,50.035768933333344]}}]}