{"type":"FeatureCollection","features":[{"type":"Feature","properties":{"codesPostaux":["80560"],"population":117,"nom":"H\u00e9dauville","code":"80425"},"geometry":{"type":"Point","coordinates":[2.5729121621621616,50.049545270270286]}}]}