{"type":"FeatureCollection","features":[{"type":"Feature","properties":{"codesPostaux":["80122"],"population":547,"nom":"Heudicourt","code":"80438"},"geometry":{"type":"Point","coordinates":[3.092499764705883,50.03041894117645]}}]}