{"type":"FeatureCollection","features":[{"type":"Feature","properties":{"codesPostaux":["80640"],"population":1668,"nom":"Hornoy-le-Bourg","code":"80443"},"geometry":{"type":"Point","coordinates":[1.9052477253218871,49.84440901287554]}}]}