{"type":"FeatureCollection","features":[{"type":"Feature","properties":{"codesPostaux":["80800"],"population":698,"nom":"Lamotte-Warfus\u00e9e","code":"80463"},"geometry":{"type":"Point","coordinates":[2.5912624999999996,49.8805498]}}]}