{"type":"FeatureCollection","features":[{"type":"Feature","properties":{"codesPostaux":["80290"],"population":62,"nom":"Lamaronde","code":"80460"},"geometry":{"type":"Point","coordinates":[1.9040568965517242,49.802798965517226]}}]}