{"type":"FeatureCollection","features":[{"type":"Feature","properties":{"codesPostaux":["80240"],"population":227,"nom":"Li\u00e9ramont","code":"80475"},"geometry":{"type":"Point","coordinates":[3.0492661194029855,49.995085223880615]}}]}