{"type":"FeatureCollection","features":[{"type":"Feature","properties":{"codesPostaux":["80140"],"population":114,"nom":"Ligni\u00e8res-en-Vimeu","code":"80480"},"geometry":{"type":"Point","coordinates":[1.745024545454545,49.910455454545456]}}]}