{"type":"FeatureCollection","features":[{"type":"Feature","properties":{"codesPostaux":["80510"],"population":1664,"nom":"Longpr\u00e9-les-Corps-Saints","code":"80488"},"geometry":{"type":"Point","coordinates":[1.9795542553191483,50.011099787234045]}}]}