{"type":"FeatureCollection","features":[{"type":"Feature","properties":{"codesPostaux":["80600"],"population":569,"nom":"Lucheux","code":"80495"},"geometry":{"type":"Point","coordinates":[2.4262305019305015,50.204418996138976]}}]}