{"type":"FeatureCollection","features":[{"type":"Feature","properties":{"codesPostaux":["80290"],"population":6,"nom":"M\u00e9r\u00e9aucourt","code":"80528"},"geometry":{"type":"Point","coordinates":[1.9302051351351353,49.731398378378366]}}]}