{"type":"FeatureCollection","features":[{"type":"Feature","properties":{"codesPostaux":["80620"],"population":83,"nom":"Mesnil-Domqueur","code":"80537"},"geometry":{"type":"Point","coordinates":[2.0627685714285717,50.13201408163265]}}]}