{"type":"FeatureCollection","features":[{"type":"Feature","properties":{"codesPostaux":["80360"],"population":147,"nom":"Mesnil-en-Arrouaise","code":"80538"},"geometry":{"type":"Point","coordinates":[2.950304375,50.03435312500002]}}]}