{"type":"FeatureCollection","features":[{"type":"Feature","properties":{"codesPostaux":["80190"],"population":565,"nom":"Mesnil-Saint-Nicaise","code":"80542"},"geometry":{"type":"Point","coordinates":[2.9153050819672126,49.77888262295084]}}]}