{"type":"FeatureCollection","features":[{"type":"Feature","properties":{"codesPostaux":["80600"],"population":193,"nom":"M\u00e9zerolles","code":"80544"},"geometry":{"type":"Point","coordinates":[2.2273574050632914,50.18416898734176]}}]}