{"type":"FeatureCollection","features":[{"type":"Feature","properties":{"codesPostaux":["80200"],"population":1222,"nom":"Moislains","code":"80552"},"geometry":{"type":"Point","coordinates":[2.9700848407643305,49.995231910828004]}}]}