{"type":"FeatureCollection","features":[{"type":"Feature","properties":{"codesPostaux":["80540"],"population":836,"nom":"Molliens-Dreuil","code":"80554"},"geometry":{"type":"Point","coordinates":[2.0097409565217377,49.8831531304348]}}]}