{"type":"FeatureCollection","features":[{"type":"Feature","properties":{"codesPostaux":["80200"],"population":574,"nom":"Estr\u00e9es-Mons","code":"80557"},"geometry":{"type":"Point","coordinates":[3.009469541284404,49.88090568807341]}}]}