{"type":"FeatureCollection","features":[{"type":"Feature","properties":{"codesPostaux":["80140"],"population":93,"nom":"Moufli\u00e8res","code":"80575"},"geometry":{"type":"Point","coordinates":[1.7443261290322578,49.92668741935483]}}]}