{"type":"FeatureCollection","features":[{"type":"Feature","properties":{"codesPostaux":["80400"],"population":836,"nom":"Muille-Villette","code":"80579"},"geometry":{"type":"Point","coordinates":[3.0664222891566273,49.724834578313256]}}]}