{"type":"FeatureCollection","features":[{"type":"Feature","properties":{"codesPostaux":["80132"],"population":320,"nom":"Neuilly-l'H\u00f4pital","code":"80590"},"geometry":{"type":"Point","coordinates":[1.8772811267605636,50.16981169014087]}}]}