{"type":"FeatureCollection","features":[{"type":"Feature","properties":{"codesPostaux":["80860"],"population":1281,"nom":"Nouvion","code":"80598"},"geometry":{"type":"Point","coordinates":[1.784471238095238,50.2135256190476]}}]}