{"type":"FeatureCollection","features":[{"type":"Feature","properties":{"codesPostaux":["80860"],"population":753,"nom":"Noyelles-sur-Mer","code":"80600"},"geometry":{"type":"Point","coordinates":[1.7319401515151516,50.193466818181804]}}]}