{"type":"FeatureCollection","features":[{"type":"Feature","properties":{"codesPostaux":["80600"],"population":308,"nom":"Outrebois","code":"80614"},"geometry":{"type":"Point","coordinates":[2.25174992063492,50.171506269841245]}}]}