{"type":"FeatureCollection","features":[{"type":"Feature","properties":{"codesPostaux":["80160"],"population":477,"nom":"Prouzel","code":"80643"},"geometry":{"type":"Point","coordinates":[2.190837222222222,49.811015416666656]}}]}