{"type":"FeatureCollection","features":[{"type":"Feature","properties":{"codesPostaux":["80320"],"population":271,"nom":"Puzeaux","code":"80647"},"geometry":{"type":"Point","coordinates":[2.822594482758621,49.79992965517242]}}]}