{"type":"FeatureCollection","features":[{"type":"Feature","properties":{"codesPostaux":["80600"],"population":34,"nom":"Remaisnil","code":"80666"},"geometry":{"type":"Point","coordinates":[2.2396362,50.20462]}}]}