{"type":"FeatureCollection","features":[{"type":"Feature","properties":{"codesPostaux":["80310"],"population":194,"nom":"Riencourt","code":"80673"},"geometry":{"type":"Point","coordinates":[2.037839178082192,49.923268356164364]}}]}