{"type":"FeatureCollection","features":[{"type":"Feature","properties":{"codesPostaux":["80250"],"population":285,"nom":"Rouvrel","code":"80681"},"geometry":{"type":"Point","coordinates":[2.4199666265060245,49.7709809638554]}}]}