{"type":"FeatureCollection","features":[{"type":"Feature","properties":{"codesPostaux":["80680"],"population":557,"nom":"Rumigny","code":"80690"},"geometry":{"type":"Point","coordinates":[2.2833746969696964,49.80682833333333]}}]}