{"type":"FeatureCollection","features":[{"type":"Feature","properties":{"codesPostaux":["80800"],"population":314,"nom":"Sailly-Laurette","code":"80693"},"geometry":{"type":"Point","coordinates":[2.614248131868133,49.91994494505495]}}]}