{"type":"FeatureCollection","features":[{"type":"Feature","properties":{"codesPostaux":["80430"],"population":114,"nom":"Saint-Aubin-Rivi\u00e8re","code":"80699"},"geometry":{"type":"Point","coordinates":[1.7794922222222214,49.8679831746032]}}]}