{"type":"FeatureCollection","features":[{"type":"Feature","properties":{"codesPostaux":["80780"],"population":1866,"nom":"Saint-L\u00e9ger-l\u00e8s-Domart","code":"80706"},"geometry":{"type":"Point","coordinates":[2.1462869918699177,50.05784983739837]}}]}