{"type":"FeatureCollection","features":[{"type":"Feature","properties":{"codesPostaux":["80560"],"population":91,"nom":"Saint-L\u00e9ger-l\u00e8s-Authie","code":"80705"},"geometry":{"type":"Point","coordinates":[2.514112786885247,50.125657377049194]}}]}