{"type":"FeatureCollection","features":[{"type":"Feature","properties":{"codesPostaux":["80470"],"population":1450,"nom":"Saint-Sauveur","code":"80718"},"geometry":{"type":"Point","coordinates":[2.2169492207792207,49.9490912987013]}}]}