{"type":"FeatureCollection","features":[{"type":"Feature","properties":{"codesPostaux":["80610"],"population":1988,"nom":"Saint-Ouen","code":"80711"},"geometry":{"type":"Point","coordinates":[2.1210953488372097,50.037203255813964]}}]}