{"type":"FeatureCollection","features":[{"type":"Feature","properties":{"codesPostaux":["80160"],"population":1000,"nom":"Saint-Sauflieu","code":"80717"},"geometry":{"type":"Point","coordinates":[2.25252012345679,49.78884493827161]}}]}