{"type":"FeatureCollection","features":[{"type":"Feature","properties":{"codesPostaux":["80490"],"population":243,"nom":"Sorel-en-Vimeu","code":"80736"},"geometry":{"type":"Point","coordinates":[1.9152587931034484,50.01266051724136]}}]}