{"type":"FeatureCollection","features":[{"type":"Feature","properties":{"codesPostaux":["80200"],"population":173,"nom":"Tertry","code":"80750"},"geometry":{"type":"Point","coordinates":[3.071565522388059,49.860321492537345]}}]}