{"type":"FeatureCollection","features":[{"type":"Feature","properties":{"codesPostaux":["62760"],"population":61,"nom":"Thi\u00e8vres","code":"80756"},"geometry":{"type":"Point","coordinates":[2.462854266666667,50.12007973333334]}}]}