{"type":"FeatureCollection","features":[{"type":"Feature","properties":{"codesPostaux":["80300"],"population":129,"nom":"Thiepval","code":"80753"},"geometry":{"type":"Point","coordinates":[2.6850313636363627,50.05934818181817]}}]}