{"type":"FeatureCollection","features":[{"type":"Feature","properties":{"codesPostaux":["80250"],"population":172,"nom":"Thory","code":"80758"},"geometry":{"type":"Point","coordinates":[2.436321621621621,49.72235432432433]}}]}