{"type":"FeatureCollection","features":[{"type":"Feature","properties":{"codesPostaux":["80870"],"population":297,"nom":"T\u0153ufles","code":"80764"},"geometry":{"type":"Point","coordinates":[1.7093397530864196,50.061642222222225]}}]}