{"type":"FeatureCollection","features":[{"type":"Feature","properties":{"codesPostaux":["80230"],"population":400,"nom":"Vaudricourt","code":"80780"},"geometry":{"type":"Point","coordinates":[1.5498701754385966,50.11472684210528]}}]}