{"type":"FeatureCollection","features":[{"type":"Feature","properties":{"codesPostaux":["80480"],"population":730,"nom":"Vers-sur-Selle","code":"80791"},"geometry":{"type":"Point","coordinates":[2.228235161290324,49.843202419354846]}}]}