{"type":"FeatureCollection","features":[{"type":"Feature","properties":{"codesPostaux":["80150"],"population":461,"nom":"Vironchaux","code":"80808"},"geometry":{"type":"Point","coordinates":[1.823286296296296,50.29811722222224]}}]}