{"type":"FeatureCollection","features":[{"type":"Feature","properties":{"codesPostaux":["80240"],"population":645,"nom":"Villers-Faucon","code":"80802"},"geometry":{"type":"Point","coordinates":[3.1063675496688745,49.97930304635759]}}]}