{"type":"FeatureCollection","features":[{"type":"Feature","properties":{"codesPostaux":["80150"],"population":312,"nom":"Yvrench","code":"80832"},"geometry":{"type":"Point","coordinates":[2.0143872857142857,50.18448957142857]}}]}