{"type":"FeatureCollection","features":[{"type":"Feature","properties":{"codesPostaux":["81470"],"population":224,"nom":"Aguts","code":"81001"},"geometry":{"type":"Point","coordinates":[1.923172500000001,43.53193132812501]}}]}