{"type":"FeatureCollection","features":[{"type":"Feature","properties":{"codesPostaux":["81500"],"population":963,"nom":"Ambres","code":"81011"},"geometry":{"type":"Point","coordinates":[1.8363407843137256,43.72821333333332]}}]}