{"type":"FeatureCollection","features":[{"type":"Feature","properties":{"codesPostaux":["81430"],"population":455,"nom":"Ambialet","code":"81010"},"geometry":{"type":"Point","coordinates":[2.390206239316238,43.92713903133902]}}]}