{"type":"FeatureCollection","features":[{"type":"Feature","properties":{"codesPostaux":["81660"],"population":1225,"nom":"Bout-du-Pont-de-Larn","code":"81036"},"geometry":{"type":"Point","coordinates":[2.430092986111111,43.503849513888895]}}]}