{"type":"FeatureCollection","features":[{"type":"Feature","properties":{"codesPostaux":["81700"],"population":115,"nom":"Bertre","code":"81030"},"geometry":{"type":"Point","coordinates":[1.9454668181818184,43.60520386363637]}}]}