{"type":"FeatureCollection","features":[{"type":"Feature","properties":{"codesPostaux":["81100"],"population":1998,"nom":"Burlats","code":"81042"},"geometry":{"type":"Point","coordinates":[2.337608731343285,43.63487291044772]}}]}