{"type":"FeatureCollection","features":[{"type":"Feature","properties":{"codesPostaux":["81170"],"population":368,"nom":"Les Cabannes","code":"81045"},"geometry":{"type":"Point","coordinates":[1.9296584615384613,44.07657675213674]}}]}