{"type":"FeatureCollection","features":[{"type":"Feature","properties":{"codesPostaux":["81990"],"population":2052,"nom":"Cambon","code":"81052"},"geometry":{"type":"Point","coordinates":[2.2318652040816334,43.912101326530625]}}]}