{"type":"FeatureCollection","features":[{"type":"Feature","properties":{"codesPostaux":["81150"],"population":194,"nom":"Castanet","code":"81061"},"geometry":{"type":"Point","coordinates":[2.0373047933884303,43.97552603305783]}}]}