{"type":"FeatureCollection","features":[{"type":"Feature","properties":{"codesPostaux":["81400"],"population":9688,"nom":"Carmaux","code":"81060"},"geometry":{"type":"Point","coordinates":[2.1681005660377357,44.05635716981129]}}]}