{"type":"FeatureCollection","features":[{"type":"Feature","properties":{"codesPostaux":["81340"],"population":84,"nom":"Courris","code":"81071"},"geometry":{"type":"Point","coordinates":[2.399352671755725,43.9583264885496]}}]}