{"type":"FeatureCollection","features":[{"type":"Feature","properties":{"codesPostaux":["81350"],"population":171,"nom":"Crespinet","code":"81073"},"geometry":{"type":"Point","coordinates":[2.2902050617283933,43.954663827160466]}}]}