{"type":"FeatureCollection","features":[{"type":"Feature","properties":{"codesPostaux":["81600"],"population":221,"nom":"F\u00e9nols","code":"81090"},"geometry":{"type":"Point","coordinates":[2.054799054054054,43.84927405405405]}}]}