{"type":"FeatureCollection","features":[{"type":"Feature","properties":{"codesPostaux":["81500"],"population":914,"nom":"Fiac","code":"81092"},"geometry":{"type":"Point","coordinates":[1.91776594736842,43.69337489473685]}}]}