{"type":"FeatureCollection","features":[{"type":"Feature","properties":{"codesPostaux":["81500"],"population":1450,"nom":"Giroussens","code":"81104"},"geometry":{"type":"Point","coordinates":[1.7990795312500014,43.773298125]}}]}