{"type":"FeatureCollection","features":[{"type":"Feature","properties":{"codesPostaux":["81800"],"population":549,"nom":"Grazac","code":"81106"},"geometry":{"type":"Point","coordinates":[1.6489398058252425,43.84392655339808]}}]}