{"type":"FeatureCollection","features":[{"type":"Feature","properties":{"codesPostaux":["81300"],"population":11807,"nom":"Graulhet","code":"81105"},"geometry":{"type":"Point","coordinates":[1.996322116564417,43.75677524539877]}}]}