{"type":"FeatureCollection","features":[{"type":"Feature","properties":{"codesPostaux":["81170"],"population":78,"nom":"Labarthe-Bleys","code":"81111"},"geometry":{"type":"Point","coordinates":[1.8930304651162793,44.08616540697673]}}]}