{"type":"FeatureCollection","features":[{"type":"Feature","properties":{"codesPostaux":["81120"],"population":483,"nom":"Laboutarie","code":"81119"},"geometry":{"type":"Point","coordinates":[2.1122279032258064,43.78770983870967]}}]}