{"type":"FeatureCollection","features":[{"type":"Feature","properties":{"codesPostaux":["81210"],"population":1734,"nom":"Lacrouzette","code":"81128"},"geometry":{"type":"Point","coordinates":[2.362278969465648,43.6621251908397]}}]}