{"type":"FeatureCollection","features":[{"type":"Feature","properties":{"codesPostaux":["81500"],"population":10691,"nom":"Lavaur","code":"81140"},"geometry":{"type":"Point","coordinates":[1.81573380462725,43.68644110539842]}}]}