{"type":"FeatureCollection","features":[{"type":"Feature","properties":{"codesPostaux":["81500"],"population":344,"nom":"Massac-S\u00e9ran","code":"81159"},"geometry":{"type":"Point","coordinates":[1.8657237777777778,43.66497277777779]}}]}