{"type":"FeatureCollection","features":[{"type":"Feature","properties":{"codesPostaux":["81530"],"population":282,"nom":"Le Masnau-Massugui\u00e8s","code":"81158"},"geometry":{"type":"Point","coordinates":[2.5397150408719344,43.80756411444142]}}]}