{"type":"FeatureCollection","features":[{"type":"Feature","properties":{"codesPostaux":["81300"],"population":92,"nom":"Miss\u00e8cle","code":"81169"},"geometry":{"type":"Point","coordinates":[1.984348,43.722291999999996]}}]}