{"type":"FeatureCollection","features":[{"type":"Feature","properties":{"codesPostaux":["81440"],"population":615,"nom":"Montdragon","code":"81174"},"geometry":{"type":"Point","coordinates":[2.100176086956522,43.77626442028987]}}]}