{"type":"FeatureCollection","features":[{"type":"Feature","properties":{"codesPostaux":["81640"],"population":1422,"nom":"Monesti\u00e9s","code":"81170"},"geometry":{"type":"Point","coordinates":[2.0986127745664747,44.08190208092485]}}]}