{"type":"FeatureCollection","features":[{"type":"Feature","properties":{"codesPostaux":["81470"],"population":121,"nom":"Mouzens","code":"81189"},"geometry":{"type":"Point","coordinates":[1.8911466666666665,43.53125012820512]}}]}