{"type":"FeatureCollection","features":[{"type":"Feature","properties":{"codesPostaux":["81120"],"population":324,"nom":"Orban","code":"81198"},"geometry":{"type":"Point","coordinates":[2.0782147747747755,43.83775027027027]}}]}