{"type":"FeatureCollection","features":[{"type":"Feature","properties":{"codesPostaux":["81490"],"population":855,"nom":"Noailhac","code":"81196"},"geometry":{"type":"Point","coordinates":[2.3578289999999997,43.57620387500002]}}]}