{"type":"FeatureCollection","features":[{"type":"Feature","properties":{"codesPostaux":["81140"],"population":578,"nom":"Penne","code":"81206"},"geometry":{"type":"Point","coordinates":[1.7199170892018787,44.081386056338054]}}]}