{"type":"FeatureCollection","features":[{"type":"Feature","properties":{"codesPostaux":["81310"],"population":949,"nom":"Parisot","code":"81202"},"geometry":{"type":"Point","coordinates":[1.8303620284697504,43.81047291814947]}}]}