{"type":"FeatureCollection","features":[{"type":"Feature","properties":{"codesPostaux":["81660"],"population":2886,"nom":"Pont-de-Larn","code":"81209"},"geometry":{"type":"Point","coordinates":[2.412171836734692,43.531716693877534]}}]}