{"type":"FeatureCollection","features":[{"type":"Feature","properties":{"codesPostaux":["81700"],"population":3255,"nom":"Puylaurens","code":"81219"},"geometry":{"type":"Point","coordinates":[2.007255779220779,43.58161097402599]}}]}