{"type":"FeatureCollection","features":[{"type":"Feature","properties":{"codesPostaux":["81340"],"population":209,"nom":"Saint-Cirgue","code":"81247"},"geometry":{"type":"Point","coordinates":[2.368502418300653,43.97054261437909]}}]}