{"type":"FeatureCollection","features":[{"type":"Feature","properties":{"codesPostaux":["81340"],"population":214,"nom":"Saint-Julien-Gaul\u00e8ne","code":"81259"},"geometry":{"type":"Point","coordinates":[2.3407006302521016,43.99575352941176]}}]}