{"type":"FeatureCollection","features":[{"type":"Feature","properties":{"codesPostaux":["81170"],"population":405,"nom":"Saint-Martin-Lagu\u00e9pie","code":"81263"},"geometry":{"type":"Point","coordinates":[1.9622181132075462,44.13232494339621]}}]}