{"type":"FeatureCollection","features":[{"type":"Feature","properties":{"codesPostaux":["81490"],"population":541,"nom":"Saint-Salvy-de-la-Balme","code":"81269"},"geometry":{"type":"Point","coordinates":[2.381757240000001,43.60975259999998]}}]}