{"type":"FeatureCollection","features":[{"type":"Feature","properties":{"codesPostaux":["81700"],"population":149,"nom":"Saint-Sernin-l\u00e8s-Lavaur","code":"81270"},"geometry":{"type":"Point","coordinates":[1.9709694339622648,43.54381679245282]}}]}