{"type":"FeatureCollection","features":[{"type":"Feature","properties":{"codesPostaux":["81630"],"population":257,"nom":"La Sauzi\u00e8re-Saint-Jean","code":"81279"},"geometry":{"type":"Point","coordinates":[1.6473492352941181,43.953825]}}]}