{"type":"FeatureCollection","features":[{"type":"Feature","properties":{"codesPostaux":["81990"],"population":812,"nom":"Sali\u00e8s","code":"81274"},"geometry":{"type":"Point","coordinates":[2.1338263414634144,43.88443024390244]}}]}