{"type":"FeatureCollection","features":[{"type":"Feature","properties":{"codesPostaux":["81150"],"population":1082,"nom":"Terssac","code":"81297"},"geometry":{"type":"Point","coordinates":[2.0664596078431368,43.921361568627454]}}]}