{"type":"FeatureCollection","features":[{"type":"Feature","properties":{"codesPostaux":["81090"],"population":820,"nom":"Valdurenque","code":"81307"},"geometry":{"type":"Point","coordinates":[2.3128945454545455,43.57286445454545]}}]}