{"type":"FeatureCollection","features":[{"type":"Feature","properties":{"codesPostaux":["81110"],"population":965,"nom":"Verdalle","code":"81312"},"geometry":{"type":"Point","coordinates":[2.1820109657320867,43.493303177570084]}}]}