{"type":"FeatureCollection","features":[{"type":"Feature","properties":{"codesPostaux":["81130"],"population":478,"nom":"Villeneuve-sur-V\u00e8re","code":"81319"},"geometry":{"type":"Point","coordinates":[2.0311965333333335,44.00652026666669]}}]}