{"type":"FeatureCollection","features":[{"type":"Feature","properties":{"codesPostaux":["81140"],"population":228,"nom":"Le Verdier","code":"81313"},"geometry":{"type":"Point","coordinates":[1.838783982300886,43.99270194690264]}}]}