{"type":"FeatureCollection","features":[{"type":"Feature","properties":{"codesPostaux":["81220"],"population":355,"nom":"Viterbe","code":"81323"},"geometry":{"type":"Point","coordinates":[1.910042386363637,43.677082954545455]}}]}