{"type":"FeatureCollection","features":[{"type":"Feature","properties":{"codesPostaux":["81290"],"population":1931,"nom":"Viviers-l\u00e8s-Montagnes","code":"81325"},"geometry":{"type":"Point","coordinates":[2.172351395348838,43.54587720930231]}}]}