{"type":"FeatureCollection","features":[{"type":"Feature","properties":{"codesPostaux":["82200"],"population":702,"nom":"Boudou","code":"82019"},"geometry":{"type":"Point","coordinates":[1.0149851960784317,44.104355392156855]}}]}