{"type":"FeatureCollection","features":[{"type":"Feature","properties":{"codesPostaux":["82170"],"population":728,"nom":"Canals","code":"82028"},"geometry":{"type":"Point","coordinates":[1.2965371428571426,43.859166904761906]}}]}