{"type":"FeatureCollection","features":[{"type":"Feature","properties":{"codesPostaux":["82190"],"population":391,"nom":"Bourg-de-Visa","code":"82022"},"geometry":{"type":"Point","coordinates":[0.9516451933701657,44.24946309392263]}}]}