{"type":"FeatureCollection","features":[{"type":"Feature","properties":{"codesPostaux":["82160"],"population":1502,"nom":"Caylus","code":"82038"},"geometry":{"type":"Point","coordinates":[1.762418554216866,44.2384143373494]}}]}