{"type":"FeatureCollection","features":[{"type":"Feature","properties":{"codesPostaux":["82390"],"population":851,"nom":"Durfort-Lacapelette","code":"82051"},"geometry":{"type":"Point","coordinates":[1.1422942152466367,44.17956089686098]}}]}