{"type":"FeatureCollection","features":[{"type":"Feature","properties":{"codesPostaux":["82400"],"population":404,"nom":"Espalais","code":"82054"},"geometry":{"type":"Point","coordinates":[0.9166475257731959,44.0772055670103]}}]}