{"type":"FeatureCollection","features":[{"type":"Feature","properties":{"codesPostaux":["82700"],"population":1056,"nom":"Escatalens","code":"82052"},"geometry":{"type":"Point","coordinates":[1.197861363636363,43.98480886363634]}}]}