{"type":"FeatureCollection","features":[{"type":"Feature","properties":{"codesPostaux":["82170"],"population":573,"nom":"Fabas","code":"82057"},"geometry":{"type":"Point","coordinates":[1.340746621621622,43.86162243243243]}}]}