{"type":"FeatureCollection","features":[{"type":"Feature","properties":{"codesPostaux":["82500"],"population":40,"nom":"Goas","code":"82071"},"geometry":{"type":"Point","coordinates":[0.9626288461538465,43.81635051282051]}}]}