{"type":"FeatureCollection","features":[{"type":"Feature","properties":{"codesPostaux":["82290"],"population":3128,"nom":"La Ville-Dieu-du-Temple","code":"82096"},"geometry":{"type":"Point","coordinates":[1.2198861538461545,44.045270164835145]}}]}