{"type":"FeatureCollection","features":[{"type":"Feature","properties":{"codesPostaux":["82300"],"population":1342,"nom":"Monteils","code":"82126"},"geometry":{"type":"Point","coordinates":[1.5634455357142851,44.17478705357143]}}]}