{"type":"FeatureCollection","features":[{"type":"Feature","properties":{"codesPostaux":["82200"],"population":773,"nom":"Montesquieu","code":"82127"},"geometry":{"type":"Point","coordinates":[1.066628087431694,44.17704306010928]}}]}