{"type":"FeatureCollection","features":[{"type":"Feature","properties":{"codesPostaux":["82800"],"population":1116,"nom":"Montricoux","code":"82132"},"geometry":{"type":"Point","coordinates":[1.6210211585365852,44.106696097561]}}]}