{"type":"FeatureCollection","features":[{"type":"Feature","properties":{"codesPostaux":["82800"],"population":367,"nom":"Puygaillard-de-Quercy","code":"82145"},"geometry":{"type":"Point","coordinates":[1.6271988535031843,44.029956114649664]}}]}