{"type":"FeatureCollection","features":[{"type":"Feature","properties":{"codesPostaux":["82400"],"population":606,"nom":"Pommevic","code":"82141"},"geometry":{"type":"Point","coordinates":[0.9382237681159417,44.09416043478262]}}]}