{"type":"FeatureCollection","features":[{"type":"Feature","properties":{"codesPostaux":["82130"],"population":410,"nom":"Piquecos","code":"82140"},"geometry":{"type":"Point","coordinates":[1.3176022680412367,44.10487979381442]}}]}