{"type":"FeatureCollection","features":[{"type":"Feature","properties":{"codesPostaux":["82370"],"population":1765,"nom":"Saint-Nauphary","code":"82167"},"geometry":{"type":"Point","coordinates":[1.451424242424243,43.960431878787865]}}]}