{"type":"FeatureCollection","features":[{"type":"Feature","properties":{"codesPostaux":["82340"],"population":507,"nom":"Saint-Loup","code":"82165"},"geometry":{"type":"Point","coordinates":[0.8546931884057971,44.079250362318845]}}]}