{"type":"FeatureCollection","features":[{"type":"Feature","properties":{"codesPostaux":["82400"],"population":237,"nom":"Saint-Vincent-Lespinasse","code":"82175"},"geometry":{"type":"Point","coordinates":[0.9648628682170541,44.11854906976746]}}]}