{"type":"FeatureCollection","features":[{"type":"Feature","properties":{"codesPostaux":["82370"],"population":596,"nom":"Varennes","code":"82188"},"geometry":{"type":"Point","coordinates":[1.491216194690266,43.91177318584071]}}]}