{"type":"FeatureCollection","features":[{"type":"Feature","properties":{"codesPostaux":["82370"],"population":1266,"nom":"Villebrumier","code":"82194"},"geometry":{"type":"Point","coordinates":[1.4522407894736842,43.92027486842105]}}]}