{"type":"FeatureCollection","features":[{"type":"Feature","properties":{"codesPostaux":["83630"],"population":209,"nom":"Baudinard-sur-Verdon","code":"83014"},"geometry":{"type":"Point","coordinates":[6.132686860465117,43.71900453488372]}}]}