{"type":"FeatureCollection","features":[{"type":"Feature","properties":{"codesPostaux":["83440"],"population":5505,"nom":"Fayence","code":"83055"},"geometry":{"type":"Point","coordinates":[6.676394301886797,43.60854467924528]}}]}