{"type":"FeatureCollection","features":[{"type":"Feature","properties":{"codesPostaux":["83590"],"population":4273,"nom":"Gonfaron","code":"83067"},"geometry":{"type":"Point","coordinates":[6.313165494505496,43.31979252747253]}}]}