{"type":"FeatureCollection","features":[{"type":"Feature","properties":{"codesPostaux":["83130"],"population":25298,"nom":"La Garde","code":"83062"},"geometry":{"type":"Point","coordinates":[6.00558439716312,43.119691276595745]}}]}