{"type":"FeatureCollection","features":[{"type":"Feature","properties":{"codesPostaux":["83980"],"population":5148,"nom":"Le Lavandou","code":"83070"},"geometry":{"type":"Point","coordinates":[6.400899102990033,43.15559697674421]}}]}