{"type":"FeatureCollection","features":[{"type":"Feature","properties":{"codesPostaux":["83440"],"population":6118,"nom":"Montauroux","code":"83081"},"geometry":{"type":"Point","coordinates":[6.7909083426966275,43.5866068539326]}}]}