{"type":"FeatureCollection","features":[{"type":"Feature","properties":{"codesPostaux":["83136"],"population":2573,"nom":"N\u00e9oules","code":"83088"},"geometry":{"type":"Point","coordinates":[6.025779034482754,43.29440075862069]}}]}