{"type":"FeatureCollection","features":[{"type":"Feature","properties":{"codesPostaux":["83670"],"population":786,"nom":"Pontev\u00e8s","code":"83095"},"geometry":{"type":"Point","coordinates":[6.062712735849057,43.55134792452831]}}]}