{"type":"FeatureCollection","features":[{"type":"Feature","properties":{"codesPostaux":["83136"],"population":2526,"nom":"La Roquebrussanne","code":"83108"},"geometry":{"type":"Point","coordinates":[5.992304873096447,43.33755781725887]}}]}