{"type":"FeatureCollection","features":[{"type":"Feature","properties":{"codesPostaux":["83530","83700"],"population":34005,"nom":"Saint-Rapha\u00ebl","code":"83118"},"geometry":{"type":"Point","coordinates":[6.8646086046511625,43.43971020084568]}}]}