{"type":"FeatureCollection","features":[{"type":"Feature","properties":{"codesPostaux":["83560"],"population":244,"nom":"Saint-Martin-de-Palli\u00e8res","code":"83114"},"geometry":{"type":"Point","coordinates":[5.882220362318838,43.578146884058]}}]}