{"type":"FeatureCollection","features":[{"type":"Feature","properties":{"codesPostaux":["83630"],"population":252,"nom":"Les Salles-sur-Verdon","code":"83122"},"geometry":{"type":"Point","coordinates":[6.210625294117645,43.76457470588237]}}]}