{"type":"FeatureCollection","features":[{"type":"Feature","properties":{"codesPostaux":["83210"],"population":2422,"nom":"Solli\u00e8s-Ville","code":"83132"},"geometry":{"type":"Point","coordinates":[6.028786304347825,43.17628010869567]}}]}