{"type":"FeatureCollection","features":[{"type":"Feature","properties":{"codesPostaux":["83160"],"population":21463,"nom":"La Valette-du-Var","code":"83144"},"geometry":{"type":"Point","coordinates":[5.987647226890757,43.14941697478991]}}]}