{"type":"FeatureCollection","features":[{"type":"Feature","properties":{"codesPostaux":["83170"],"population":978,"nom":"Vins-sur-Caramy","code":"83151"},"geometry":{"type":"Point","coordinates":[6.148783257575756,43.43099863636364]}}]}