{"type":"FeatureCollection","features":[{"type":"Feature","properties":{"codesPostaux":["83430"],"population":5780,"nom":"Saint-Mandrier-sur-Mer","code":"83153"},"geometry":{"type":"Point","coordinates":[5.925527957746479,43.07826739436617]}}]}