{"type":"FeatureCollection","features":[{"type":"Feature","properties":{"codesPostaux":["84210"],"population":2683,"nom":"Althen-des-Paluds","code":"84001"},"geometry":{"type":"Point","coordinates":[4.954991515151516,44.01351621212122]}}]}