{"type":"FeatureCollection","features":[{"type":"Feature","properties":{"codesPostaux":["84500"],"population":13776,"nom":"Boll\u00e8ne","code":"84019"},"geometry":{"type":"Point","coordinates":[4.749678965517241,44.2902843965517]}}]}