{"type":"FeatureCollection","features":[{"type":"Feature","properties":{"codesPostaux":["84110"],"population":271,"nom":"Buisson","code":"84022"},"geometry":{"type":"Point","coordinates":[4.993888507462686,44.27331925373133]}}]}