{"type":"FeatureCollection","features":[{"type":"Feature","properties":{"codesPostaux":["84300"],"population":25636,"nom":"Cavaillon","code":"84035"},"geometry":{"type":"Point","coordinates":[5.051377934782609,43.838994565217384]}}]}