{"type":"FeatureCollection","features":[{"type":"Feature","properties":{"codesPostaux":["84470"],"population":3303,"nom":"Ch\u00e2teauneuf-de-Gadagne","code":"84036"},"geometry":{"type":"Point","coordinates":[4.941852410714285,43.9313704464286]}}]}