{"type":"FeatureCollection","features":[{"type":"Feature","properties":{"codesPostaux":["84110"],"population":412,"nom":"Crestet","code":"84040"},"geometry":{"type":"Point","coordinates":[5.090367272727273,44.21102371900825]}}]}