{"type":"FeatureCollection","features":[{"type":"Feature","properties":{"codesPostaux":["84220"],"population":1142,"nom":"Goult","code":"84051"},"geometry":{"type":"Point","coordinates":[5.245860706521738,43.871645380434764]}}]}