{"type":"FeatureCollection","features":[{"type":"Feature","properties":{"codesPostaux":["84190"],"population":125,"nom":"Lafare","code":"84059"},"geometry":{"type":"Point","coordinates":[5.0526156896551715,44.15451086206895]}}]}