{"type":"FeatureCollection","features":[{"type":"Feature","properties":{"codesPostaux":["84220"],"population":248,"nom":"Lioux","code":"84066"},"geometry":{"type":"Point","coordinates":[5.297921219512196,43.96946260162601]}}]}