{"type":"FeatureCollection","features":[{"type":"Feature","properties":{"codesPostaux":["84870"],"population":2528,"nom":"Loriol-du-Comtat","code":"84067"},"geometry":{"type":"Point","coordinates":[5.00419403508772,44.07560701754385]}}]}