{"type":"FeatureCollection","features":[{"type":"Feature","properties":{"codesPostaux":["84160"],"population":793,"nom":"Puyvert","code":"84095"},"geometry":{"type":"Point","coordinates":[5.34133652173913,43.750611739130434]}}]}