{"type":"FeatureCollection","features":[{"type":"Feature","properties":{"codesPostaux":["84210"],"population":433,"nom":"La Roque-sur-Pernes","code":"84101"},"geometry":{"type":"Point","coordinates":[5.099222000000001,43.974041357142845]}}]}