{"type":"FeatureCollection","features":[{"type":"Feature","properties":{"codesPostaux":["84400"],"population":1016,"nom":"Saignon","code":"84105"},"geometry":{"type":"Point","coordinates":[5.440677062937064,43.85930489510486]}}]}