{"type":"FeatureCollection","features":[{"type":"Feature","properties":{"codesPostaux":["84330"],"population":514,"nom":"Saint-Pierre-de-Vassols","code":"84115"},"geometry":{"type":"Point","coordinates":[5.1466696296296295,44.09348518518519]}}]}