{"type":"FeatureCollection","features":[{"type":"Feature","properties":{"codesPostaux":["84390"],"population":1359,"nom":"Sault","code":"84123"},"geometry":{"type":"Point","coordinates":[5.386049242424246,44.06925897727269]}}]}