{"type":"FeatureCollection","features":[{"type":"Feature","properties":{"codesPostaux":["84600"],"population":9519,"nom":"Valr\u00e9as","code":"84138"},"geometry":{"type":"Point","coordinates":[5.003522565217389,44.3757635652174]}}]}