{"type":"FeatureCollection","features":[{"type":"Feature","properties":{"codesPostaux":["84100"],"population":1480,"nom":"Uchaux","code":"84135"},"geometry":{"type":"Point","coordinates":[4.800263369565218,44.211079673913034]}}]}