{"type":"FeatureCollection","features":[{"type":"Feature","properties":{"codesPostaux":["84110"],"population":6089,"nom":"Vaison-la-Romaine","code":"84137"},"geometry":{"type":"Point","coordinates":[5.0596307109004774,44.24643289099526]}}]}