{"type":"FeatureCollection","features":[{"type":"Feature","properties":{"codesPostaux":["85630"],"population":1792,"nom":"Barb\u00e2tre","code":"85011"},"geometry":{"type":"Point","coordinates":[-2.1621816842105273,46.92609947368422]}}]}