{"type":"FeatureCollection","features":[{"type":"Feature","properties":{"codesPostaux":["85600"],"population":3168,"nom":"Bouff\u00e9r\u00e9","code":"85027"},"geometry":{"type":"Point","coordinates":[-1.3512293582887696,46.95928657754009]}}]}