{"type":"FeatureCollection","features":[{"type":"Feature","properties":{"codesPostaux":["85610"],"population":1757,"nom":"La Bernardi\u00e8re","code":"85021"},"geometry":{"type":"Point","coordinates":[-1.269483253588517,47.04095272727272]}}]}