{"type":"FeatureCollection","features":[{"type":"Feature","properties":{"codesPostaux":["85480"],"population":3265,"nom":"Bournezeau","code":"85034"},"geometry":{"type":"Point","coordinates":[-1.1493905803571425,46.64053214285708]}}]}