{"type":"FeatureCollection","features":[{"type":"Feature","properties":{"codesPostaux":["85310"],"population":3578,"nom":"La Chaize-le-Vicomte","code":"85046"},"geometry":{"type":"Point","coordinates":[-1.2946450969529086,46.66485961218835]}}]}