{"type":"FeatureCollection","features":[{"type":"Feature","properties":{"codesPostaux":["85170"],"population":4144,"nom":"Dompierre-sur-Yon","code":"85081"},"geometry":{"type":"Point","coordinates":[-1.3707377260981901,46.75775198966411]}}]}