{"type":"FeatureCollection","features":[{"type":"Feature","properties":{"codesPostaux":["85140"],"population":8460,"nom":"Essarts en Bocage","code":"85084"},"geometry":{"type":"Point","coordinates":[-1.2157076410998557,46.77917062228658]}}]}