{"type":"FeatureCollection","features":[{"type":"Feature","properties":{"codesPostaux":["85240"],"population":216,"nom":"Faymoreau","code":"85087"},"geometry":{"type":"Point","coordinates":[-0.631139340101523,46.54003604060914]}}]}