{"type":"FeatureCollection","features":[{"type":"Feature","properties":{"codesPostaux":["85440"],"population":2145,"nom":"Grosbreuil","code":"85103"},"geometry":{"type":"Point","coordinates":[-1.6068298326359838,46.54715623430963]}}]}