{"type":"FeatureCollection","features":[{"type":"Feature","properties":{"codesPostaux":["85170"],"population":3340,"nom":"Les Lucs-sur-Boulogne","code":"85129"},"geometry":{"type":"Point","coordinates":[-1.486650175953079,46.8592133431085]}}]}