{"type":"FeatureCollection","features":[{"type":"Feature","properties":{"codesPostaux":["85600"],"population":5118,"nom":"Montaigu","code":"85146"},"geometry":{"type":"Point","coordinates":[-1.3130261538461538,46.97655051282053]}}]}