{"type":"FeatureCollection","features":[{"type":"Feature","properties":{"codesPostaux":["85450"],"population":369,"nom":"Moreilles","code":"85149"},"geometry":{"type":"Point","coordinates":[-1.0964097297297293,46.421910000000004]}}]}