{"type":"FeatureCollection","features":[{"type":"Feature","properties":{"codesPostaux":["85200"],"population":1070,"nom":"Mervent","code":"85143"},"geometry":{"type":"Point","coordinates":[-0.7494824853801166,46.53249157894738]}}]}