{"type":"FeatureCollection","features":[{"type":"Feature","properties":{"codesPostaux":["85370"],"population":2313,"nom":"Nalliers","code":"85159"},"geometry":{"type":"Point","coordinates":[-1.0327537168141592,46.468866460177]}}]}