{"type":"FeatureCollection","features":[{"type":"Feature","properties":{"codesPostaux":["85640"],"population":2821,"nom":"Mouchamps","code":"85153"},"geometry":{"type":"Point","coordinates":[-1.053488791469194,46.781109644549794]}}]}