{"type":"FeatureCollection","features":[{"type":"Feature","properties":{"codesPostaux":["85390"],"population":1816,"nom":"Mouilleron-Saint-Germain","code":"85154"},"geometry":{"type":"Point","coordinates":[-0.8430867279411766,46.66541147058823]}}]}