{"type":"FeatureCollection","features":[{"type":"Feature","properties":{"codesPostaux":["85690"],"population":1997,"nom":"Notre-Dame-de-Monts","code":"85164"},"geometry":{"type":"Point","coordinates":[-2.095634452554745,46.840877153284666]}}]}