{"type":"FeatureCollection","features":[{"type":"Feature","properties":{"codesPostaux":["85250"],"population":1764,"nom":"Saint-Andr\u00e9-Goule-d'Oie","code":"85196"},"geometry":{"type":"Point","coordinates":[-1.205914808743169,46.852280109289666]}}]}