{"type":"FeatureCollection","features":[{"type":"Feature","properties":{"codesPostaux":["85110"],"population":1533,"nom":"Sainte-C\u00e9cile","code":"85202"},"geometry":{"type":"Point","coordinates":[-1.127207436708862,46.73685623417718]}}]}