{"type":"FeatureCollection","features":[{"type":"Feature","properties":{"codesPostaux":["85540"],"population":428,"nom":"Saint-Benoist-sur-Mer","code":"85201"},"geometry":{"type":"Point","coordinates":[-1.3439407947019868,46.421392450331105]}}]}