{"type":"FeatureCollection","features":[{"type":"Feature","properties":{"codesPostaux":["85670"],"population":2079,"nom":"Saint-\u00c9tienne-du-Bois","code":"85210"},"geometry":{"type":"Point","coordinates":[-1.5962910271903334,46.832740574018096]}}]}