{"type":"FeatureCollection","features":[{"type":"Feature","properties":{"codesPostaux":["85270"],"population":11169,"nom":"Saint-Hilaire-de-Riez","code":"85226"},"geometry":{"type":"Point","coordinates":[-1.9651447311827968,46.73990365591396]}}]}