{"type":"FeatureCollection","features":[{"type":"Feature","properties":{"codesPostaux":["85800"],"population":7469,"nom":"Saint-Gilles-Croix-de-Vie","code":"85222"},"geometry":{"type":"Point","coordinates":[-1.9212624137931031,46.69220146551724]}}]}