{"type":"FeatureCollection","features":[{"type":"Feature","properties":{"codesPostaux":["85600"],"population":4412,"nom":"Saint-Hilaire-de-Loulay","code":"85224"},"geometry":{"type":"Point","coordinates":[-1.333351755952381,47.00986395833329]}}]}