{"type":"FeatureCollection","features":[{"type":"Feature","properties":{"codesPostaux":["85480"],"population":1012,"nom":"Saint-Hilaire-le-Vouhis","code":"85232"},"geometry":{"type":"Point","coordinates":[-1.1562912201591504,46.68088787798406]}}]}