{"type":"FeatureCollection","features":[{"type":"Feature","properties":{"codesPostaux":["85160"],"population":8349,"nom":"Saint-Jean-de-Monts","code":"85234"},"geometry":{"type":"Point","coordinates":[-2.031491545454545,46.80060960606058]}}]}