{"type":"FeatureCollection","features":[{"type":"Feature","properties":{"codesPostaux":["85220"],"population":997,"nom":"Saint-Maixent-sur-Vie","code":"85239"},"geometry":{"type":"Point","coordinates":[-1.8266368907563035,46.73491596638657]}}]}