{"type":"FeatureCollection","features":[{"type":"Feature","properties":{"codesPostaux":["85410"],"population":368,"nom":"Saint-Laurent-de-la-Salle","code":"85237"},"geometry":{"type":"Point","coordinates":[-0.924211625441696,46.58034477031803]}}]}