{"type":"FeatureCollection","features":[{"type":"Feature","properties":{"codesPostaux":["85440"],"population":814,"nom":"Saint-Hilaire-la-For\u00eat","code":"85231"},"geometry":{"type":"Point","coordinates":[-1.5261811000000005,46.45626760000002]}}]}