{"type":"FeatureCollection","features":[{"type":"Feature","properties":{"codesPostaux":["85470"],"population":2607,"nom":"Brem-sur-Mer","code":"85243"},"geometry":{"type":"Point","coordinates":[-1.8070821022727281,46.61168187499998]}}]}