{"type":"FeatureCollection","features":[{"type":"Feature","properties":{"codesPostaux":["85580"],"population":2313,"nom":"Saint-Michel-en-l'Herm","code":"85255"},"geometry":{"type":"Point","coordinates":[-1.251261674641148,46.345568229665076]}}]}