{"type":"FeatureCollection","features":[{"type":"Feature","properties":{"codesPostaux":["85220"],"population":1398,"nom":"Saint-R\u00e9v\u00e9rend","code":"85268"},"geometry":{"type":"Point","coordinates":[-1.8270995930232548,46.705287906976714]}}]}