{"type":"FeatureCollection","features":[{"type":"Feature","properties":{"codesPostaux":["85200"],"population":995,"nom":"S\u00e9rign\u00e9","code":"85281"},"geometry":{"type":"Point","coordinates":[-0.847123486842105,46.50754611842104]}}]}