{"type":"FeatureCollection","features":[{"type":"Feature","properties":{"codesPostaux":["85580"],"population":1089,"nom":"Triaize","code":"85297"},"geometry":{"type":"Point","coordinates":[-1.2008267543859648,46.36095078947367]}}]}