{"type":"FeatureCollection","features":[{"type":"Feature","properties":{"codesPostaux":["85240"],"population":726,"nom":"Xanton-Chassenon","code":"85306"},"geometry":{"type":"Point","coordinates":[-0.6964975690607735,46.457014751381216]}}]}