{"type":"FeatureCollection","features":[{"type":"Feature","properties":{"codesPostaux":["85460"],"population":703,"nom":"La Faute-sur-Mer","code":"85307"},"geometry":{"type":"Point","coordinates":[-1.3084436363636365,46.31733262626263]}}]}