{"type":"FeatureCollection","features":[{"type":"Feature","properties":{"codesPostaux":["86310"],"population":578,"nom":"Antigny","code":"86006"},"geometry":{"type":"Point","coordinates":[0.8470800581395347,46.53232686046512]}}]}