{"type":"FeatureCollection","features":[{"type":"Feature","properties":{"codesPostaux":["86530"],"population":1710,"nom":"Availles-en-Ch\u00e2tellerault","code":"86014"},"geometry":{"type":"Point","coordinates":[0.5739429292929291,46.751214747474734]}}]}