{"type":"FeatureCollection","features":[{"type":"Feature","properties":{"codesPostaux":["86460"],"population":1293,"nom":"Availles-Limouzine","code":"86015"},"geometry":{"type":"Point","coordinates":[0.6312370028011206,46.14036722689075]}}]}