{"type":"FeatureCollection","features":[{"type":"Feature","properties":{"codesPostaux":["86510"],"population":735,"nom":"Brux","code":"86039"},"geometry":{"type":"Point","coordinates":[0.1910503703703704,46.251838666666664]}}]}