{"type":"FeatureCollection","features":[{"type":"Feature","properties":{"codesPostaux":["86700"],"population":519,"nom":"Ceaux-en-Couh\u00e9","code":"86043"},"geometry":{"type":"Point","coordinates":[0.23791098039215688,46.31534392156863]}}]}