{"type":"FeatureCollection","features":[{"type":"Feature","properties":{"codesPostaux":["86600"],"population":1334,"nom":"Celle-L\u00e9vescault","code":"86045"},"geometry":{"type":"Point","coordinates":[0.1748194029850747,46.40598661691544]}}]}