{"type":"FeatureCollection","features":[{"type":"Feature","properties":{"codesPostaux":["86380"],"population":993,"nom":"Chabournay","code":"86048"},"geometry":{"type":"Point","coordinates":[0.2696806666666667,46.72349166666667]}}]}