{"type":"FeatureCollection","features":[{"type":"Feature","properties":{"codesPostaux":["86210"],"population":662,"nom":"La Chapelle-Mouli\u00e8re","code":"86058"},"geometry":{"type":"Point","coordinates":[0.5400177419354835,46.64683314516129]}}]}