{"type":"FeatureCollection","features":[{"type":"Feature","properties":{"codesPostaux":["86600"],"population":1123,"nom":"Coulombiers","code":"86083"},"geometry":{"type":"Point","coordinates":[0.18194761538461535,46.49052946153848]}}]}