{"type":"FeatureCollection","features":[{"type":"Feature","properties":{"codesPostaux":["86110"],"population":402,"nom":"Cuhon","code":"86089"},"geometry":{"type":"Point","coordinates":[0.09736697916666663,46.76409989583334]}}]}