{"type":"FeatureCollection","features":[{"type":"Feature","properties":{"codesPostaux":["86410"],"population":545,"nom":"Dienn\u00e9","code":"86094"},"geometry":{"type":"Point","coordinates":[0.5418783846153847,46.444005307692294]}}]}