{"type":"FeatureCollection","features":[{"type":"Feature","properties":{"codesPostaux":["86120"],"population":212,"nom":"Cur\u00e7ay-sur-Dive","code":"86090"},"geometry":{"type":"Point","coordinates":[-0.05606529411764704,47.013015294117665]}}]}