{"type":"FeatureCollection","features":[{"type":"Feature","properties":{"codesPostaux":["86340"],"population":412,"nom":"Gizay","code":"86105"},"geometry":{"type":"Point","coordinates":[0.4276497278911567,46.43731081632654]}}]}