{"type":"FeatureCollection","features":[{"type":"Feature","properties":{"codesPostaux":["86300"],"population":62,"nom":"Lauthiers","code":"86122"},"geometry":{"type":"Point","coordinates":[0.725492448979592,46.606018163265304]}}]}