{"type":"FeatureCollection","features":[{"type":"Feature","properties":{"codesPostaux":["86220"],"population":437,"nom":"Leugny","code":"86130"},"geometry":{"type":"Point","coordinates":[0.6953501234567899,46.90047938271607]}}]}