{"type":"FeatureCollection","features":[{"type":"Feature","properties":{"codesPostaux":["86170"],"population":316,"nom":"Maisonneuve","code":"86144"},"geometry":{"type":"Point","coordinates":[0.04710616666666667,46.718043333333306]}}]}