{"type":"FeatureCollection","features":[{"type":"Feature","properties":{"codesPostaux":["86170"],"population":303,"nom":"Massognes","code":"86150"},"geometry":{"type":"Point","coordinates":[0.06175869047619046,46.74928797619048]}}]}