{"type":"FeatureCollection","features":[{"type":"Feature","properties":{"codesPostaux":["86420"],"population":732,"nom":"Monts-sur-Guesnes","code":"86167"},"geometry":{"type":"Point","coordinates":[0.19016452054794522,46.91082493150685]}}]}