{"type":"FeatureCollection","features":[{"type":"Feature","properties":{"codesPostaux":["86500"],"population":6197,"nom":"Montmorillon","code":"86165"},"geometry":{"type":"Point","coordinates":[0.8860601485148516,46.43375227722773]}}]}