{"type":"FeatureCollection","features":[{"type":"Feature","properties":{"codesPostaux":["86500"],"population":390,"nom":"Moulismes","code":"86170"},"geometry":{"type":"Point","coordinates":[0.8027340993788818,46.31475167701866]}}]}