{"type":"FeatureCollection","features":[{"type":"Feature","properties":{"codesPostaux":["86420"],"population":225,"nom":"Prin\u00e7ay","code":"86201"},"geometry":{"type":"Point","coordinates":[0.2595313888888887,46.92526592592593]}}]}