{"type":"FeatureCollection","features":[{"type":"Feature","properties":{"codesPostaux":["86260"],"population":611,"nom":"La Puye","code":"86202"},"geometry":{"type":"Point","coordinates":[0.7480255769230764,46.64192471153845]}}]}