{"type":"FeatureCollection","features":[{"type":"Feature","properties":{"codesPostaux":["86230"],"population":327,"nom":"Saint-Christophe","code":"86217"},"geometry":{"type":"Point","coordinates":[0.3722289411764705,46.91988764705882]}}]}