{"type":"FeatureCollection","features":[{"type":"Feature","properties":{"codesPostaux":["86250"],"population":416,"nom":"Saint-Romain","code":"86242"},"geometry":{"type":"Point","coordinates":[0.3881746601941749,46.226967669902905]}}]}