{"type":"FeatureCollection","features":[{"type":"Feature","properties":{"codesPostaux":["86350"],"population":551,"nom":"Saint-Secondin","code":"86248"},"geometry":{"type":"Point","coordinates":[0.4894129801324502,46.3257394039735]}}]}