{"type":"FeatureCollection","features":[{"type":"Feature","properties":{"codesPostaux":["86110"],"population":817,"nom":"Thurageau","code":"86271"},"geometry":{"type":"Point","coordinates":[0.2739689908256882,46.779701834862394]}}]}