{"type":"FeatureCollection","features":[{"type":"Feature","properties":{"codesPostaux":["86110"],"population":355,"nom":"Varennes","code":"86277"},"geometry":{"type":"Point","coordinates":[0.1990041052631579,46.76558884210526]}}]}