{"type":"FeatureCollection","features":[{"type":"Feature","properties":{"codesPostaux":["86420"],"population":400,"nom":"Verrue","code":"86286"},"geometry":{"type":"Point","coordinates":[0.1784214649681528,46.86854369426753]}}]}