{"type":"FeatureCollection","features":[{"type":"Feature","properties":{"codesPostaux":["86150"],"population":698,"nom":"Le Vigeant","code":"86289"},"geometry":{"type":"Point","coordinates":[0.6370965517241384,46.21921163793105]}}]}