{"type":"FeatureCollection","features":[{"type":"Feature","properties":{"codesPostaux":["86310"],"population":106,"nom":"Villemort","code":"86291"},"geometry":{"type":"Point","coordinates":[0.9267055263157893,46.549934736842104]}}]}