{"type":"FeatureCollection","features":[{"type":"Feature","properties":{"codesPostaux":["87160"],"population":1004,"nom":"Arnac-la-Poste","code":"87003"},"geometry":{"type":"Point","coordinates":[1.383582705061081,46.26247830715532]}}]}