{"type":"FeatureCollection","features":[{"type":"Feature","properties":{"codesPostaux":["87370"],"population":605,"nom":"Bersac-sur-Rivalier","code":"87013"},"geometry":{"type":"Point","coordinates":[1.4154678308026032,46.07845984815619]}}]}