{"type":"FeatureCollection","features":[{"type":"Feature","properties":{"codesPostaux":["87300"],"population":422,"nom":"Berneuil","code":"87012"},"geometry":{"type":"Point","coordinates":[1.1086365000000005,46.06280913888884]}}]}