{"type":"FeatureCollection","features":[{"type":"Feature","properties":{"codesPostaux":["87460"],"population":859,"nom":"Bujaleuf","code":"87024"},"geometry":{"type":"Point","coordinates":[1.6264803037974673,45.79990906329112]}}]}