{"type":"FeatureCollection","features":[{"type":"Feature","properties":{"codesPostaux":["87230"],"population":670,"nom":"Champsac","code":"87036"},"geometry":{"type":"Point","coordinates":[0.9580726835443035,45.7047060506329]}}]}