{"type":"FeatureCollection","features":[{"type":"Feature","properties":{"codesPostaux":["87440"],"population":251,"nom":"La Chapelle-Montbrandeix","code":"87037"},"geometry":{"type":"Point","coordinates":[0.8460966233766235,45.64234753246753]}}]}