{"type":"FeatureCollection","features":[{"type":"Feature","properties":{"codesPostaux":["87600"],"population":333,"nom":"Ch\u00e9ronnac","code":"87044"},"geometry":{"type":"Point","coordinates":[0.7501158232931726,45.75577028112448]}}]}