{"type":"FeatureCollection","features":[{"type":"Feature","properties":{"codesPostaux":["87160"],"population":263,"nom":"Cromac","code":"87053"},"geometry":{"type":"Point","coordinates":[1.3125776767676767,46.36437707070708]}}]}