{"type":"FeatureCollection","features":[{"type":"Feature","properties":{"codesPostaux":["87320"],"population":387,"nom":"Darnac","code":"87055"},"geometry":{"type":"Point","coordinates":[0.9632268292682927,46.23469268292686]}}]}