{"type":"FeatureCollection","features":[{"type":"Feature","properties":{"codesPostaux":["87230"],"population":1040,"nom":"Flavignac","code":"87066"},"geometry":{"type":"Point","coordinates":[1.0699052923976606,45.71006514619885]}}]}