{"type":"FeatureCollection","features":[{"type":"Feature","properties":{"codesPostaux":["87190"],"population":378,"nom":"Droux","code":"87061"},"geometry":{"type":"Point","coordinates":[1.148489920318725,46.16446900398404]}}]}