{"type":"FeatureCollection","features":[{"type":"Feature","properties":{"codesPostaux":["87220"],"population":6139,"nom":"Feytiat","code":"87065"},"geometry":{"type":"Point","coordinates":[1.330829419889503,45.8095586187845]}}]}