{"type":"FeatureCollection","features":[{"type":"Feature","properties":{"codesPostaux":["87310"],"population":393,"nom":"Gorre","code":"87073"},"geometry":{"type":"Point","coordinates":[0.9917723624595463,45.73426951456311]}}]}