{"type":"FeatureCollection","features":[{"type":"Feature","properties":{"codesPostaux":["87520"],"population":711,"nom":"Javerdat","code":"87078"},"geometry":{"type":"Point","coordinates":[0.9610077339901479,45.956900665024634]}}]}