{"type":"FeatureCollection","features":[{"type":"Feature","properties":{"codesPostaux":["87400"],"population":842,"nom":"La Geneytouse","code":"87070"},"geometry":{"type":"Point","coordinates":[1.4530202040816338,45.78717146938775]}}]}