{"type":"FeatureCollection","features":[{"type":"Feature","properties":{"codesPostaux":["87890"],"population":192,"nom":"Jouac","code":"87080"},"geometry":{"type":"Point","coordinates":[1.2569319999999997,46.348237920000024]}}]}