{"type":"FeatureCollection","features":[{"type":"Feature","properties":{"codesPostaux":["87380"],"population":1120,"nom":"Magnac-Bourg","code":"87088"},"geometry":{"type":"Point","coordinates":[1.433984925373134,45.60345562189056]}}]}