{"type":"FeatureCollection","features":[{"type":"Feature","properties":{"codesPostaux":["87400"],"population":391,"nom":"Moissannes","code":"87099"},"geometry":{"type":"Point","coordinates":[1.554225056179775,45.87662235955056]}}]}