{"type":"FeatureCollection","features":[{"type":"Feature","properties":{"codesPostaux":["87800"],"population":513,"nom":"Meilhac","code":"87094"},"geometry":{"type":"Point","coordinates":[1.1567640598290598,45.714161923076894]}}]}