{"type":"FeatureCollection","features":[{"type":"Feature","properties":{"codesPostaux":["87330"],"population":255,"nom":"Montrol-S\u00e9nard","code":"87100"},"geometry":{"type":"Point","coordinates":[0.9538383415841588,46.023760594059404]}}]}