{"type":"FeatureCollection","features":[{"type":"Feature","properties":{"codesPostaux":["87210"],"population":370,"nom":"Oradour-Saint-Genest","code":"87109"},"geometry":{"type":"Point","coordinates":[1.0224934375000003,46.24700725694446]}}]}