{"type":"FeatureCollection","features":[{"type":"Feature","properties":{"codesPostaux":["87330"],"population":114,"nom":"Mortemart","code":"87101"},"geometry":{"type":"Point","coordinates":[0.957189897435897,46.04889538461535]}}]}