{"type":"FeatureCollection","features":[{"type":"Feature","properties":{"codesPostaux":["87130"],"population":911,"nom":"Neuvic-Entier","code":"87105"},"geometry":{"type":"Point","coordinates":[1.6453650613496928,45.73403999999999]}}]}