{"type":"FeatureCollection","features":[{"type":"Feature","properties":{"codesPostaux":["87350"],"population":10560,"nom":"Panazol","code":"87114"},"geometry":{"type":"Point","coordinates":[1.3282429098360664,45.83564040983608]}}]}