{"type":"FeatureCollection","features":[{"type":"Feature","properties":{"codesPostaux":["87520"],"population":2424,"nom":"Oradour-sur-Glane","code":"87110"},"geometry":{"type":"Point","coordinates":[1.0182956766917302,45.94341757518797]}}]}