{"type":"FeatureCollection","features":[{"type":"Feature","properties":{"codesPostaux":["87400"],"population":820,"nom":"Roy\u00e8res","code":"87129"},"geometry":{"type":"Point","coordinates":[1.4337193661971825,45.85139137323944]}}]}