{"type":"FeatureCollection","features":[{"type":"Feature","properties":{"codesPostaux":["87310"],"population":725,"nom":"Saint-Cyr","code":"87141"},"geometry":{"type":"Point","coordinates":[0.9832649003984061,45.79747458167331]}}]}