{"type":"FeatureCollection","features":[{"type":"Feature","properties":{"codesPostaux":["87400"],"population":529,"nom":"Saint-Denis-des-Murs","code":"87142"},"geometry":{"type":"Point","coordinates":[1.5344720512820527,45.77937512820512]}}]}