{"type":"FeatureCollection","features":[{"type":"Feature","properties":{"codesPostaux":["87190"],"population":392,"nom":"Saint-Hilaire-la-Treille","code":"87149"},"geometry":{"type":"Point","coordinates":[1.3161145533141205,46.242716945244965]}}]}