{"type":"FeatureCollection","features":[{"type":"Feature","properties":{"codesPostaux":["87400"],"population":567,"nom":"Saint-Martin-Terressus","code":"87167"},"geometry":{"type":"Point","coordinates":[1.459781030927835,45.91074288659788]}}]}