{"type":"FeatureCollection","features":[{"type":"Feature","properties":{"codesPostaux":["87260"],"population":1246,"nom":"Saint-Paul","code":"87174"},"geometry":{"type":"Point","coordinates":[1.4436261988304089,45.753763070175445]}}]}