{"type":"FeatureCollection","features":[{"type":"Feature","properties":{"codesPostaux":["87370"],"population":857,"nom":"Saint-Sulpice-Lauri\u00e8re","code":"87181"},"geometry":{"type":"Point","coordinates":[1.477060432692308,46.05629072115381]}}]}