{"type":"FeatureCollection","features":[{"type":"Feature","properties":{"codesPostaux":["87440"],"population":178,"nom":"Les Salles-Lavauguyon","code":"87189"},"geometry":{"type":"Point","coordinates":[0.6985798101265819,45.74365867088607]}}]}