{"type":"FeatureCollection","features":[{"type":"Feature","properties":{"codesPostaux":["87140"],"population":403,"nom":"Vaulry","code":"87198"},"geometry":{"type":"Point","coordinates":[1.090055761589404,46.0308994701987]}}]}