{"type":"FeatureCollection","features":[{"type":"Feature","properties":{"codesPostaux":["87430"],"population":4637,"nom":"Verneuil-sur-Vienne","code":"87201"},"geometry":{"type":"Point","coordinates":[1.1281690181818187,45.85012789090908]}}]}