{"type":"FeatureCollection","features":[{"type":"Feature","properties":{"codesPostaux":["87260"],"population":1363,"nom":"Vicq-sur-Breuilh","code":"87203"},"geometry":{"type":"Point","coordinates":[1.392587467248908,45.64683545851527]}}]}