{"type":"FeatureCollection","features":[{"type":"Feature","properties":{"codesPostaux":["87110"],"population":2068,"nom":"Le Vigen","code":"87205"},"geometry":{"type":"Point","coordinates":[1.2828540601503755,45.741027644110176]}}]}