{"type":"FeatureCollection","features":[{"type":"Feature","properties":{"codesPostaux":["88630"],"population":78,"nom":"Avranville","code":"88025"},"geometry":{"type":"Point","coordinates":[5.533493090909091,48.421436363636374]}}]}