{"type":"FeatureCollection","features":[{"type":"Feature","properties":{"codesPostaux":["88500"],"population":88,"nom":"Avillers","code":"88023"},"geometry":{"type":"Point","coordinates":[6.204137954545453,48.31455590909092]}}]}