{"type":"FeatureCollection","features":[{"type":"Feature","properties":{"codesPostaux":["88320"],"population":102,"nom":"Blevaincourt","code":"88062"},"geometry":{"type":"Point","coordinates":[5.689643315508022,48.121355133689875]}}]}