{"type":"FeatureCollection","features":[{"type":"Feature","properties":{"codesPostaux":["88250"],"population":4262,"nom":"La Bresse","code":"88075"},"geometry":{"type":"Point","coordinates":[6.930559195979907,48.015299849246226]}}]}