{"type":"FeatureCollection","features":[{"type":"Feature","properties":{"codesPostaux":["88130"],"population":4653,"nom":"Charmes","code":"88090"},"geometry":{"type":"Point","coordinates":[6.317111666666666,48.38391027210885]}}]}