{"type":"FeatureCollection","features":[{"type":"Feature","properties":{"codesPostaux":["88500"],"population":44,"nom":"Chef-Haut","code":"88100"},"geometry":{"type":"Point","coordinates":[6.009112380952382,48.35419984126985]}}]}