{"type":"FeatureCollection","features":[{"type":"Feature","properties":{"codesPostaux":["88410"],"population":218,"nom":"Claudon","code":"88105"},"geometry":{"type":"Point","coordinates":[6.042734937759338,48.036227344398355]}}]}