{"type":"FeatureCollection","features":[{"type":"Feature","properties":{"codesPostaux":["88700"],"population":64,"nom":"Deinvillers","code":"88127"},"geometry":{"type":"Point","coordinates":[6.565422432432431,48.41356747747748]}}]}