{"type":"FeatureCollection","features":[{"type":"Feature","properties":{"codesPostaux":["88270"],"population":94,"nom":"Derbamont","code":"88129"},"geometry":{"type":"Point","coordinates":[6.269650686274509,48.26667901960785]}}]}