{"type":"FeatureCollection","features":[{"type":"Feature","properties":{"codesPostaux":["88260"],"population":85,"nom":"Dombasle-devant-Darney","code":"88138"},"geometry":{"type":"Point","coordinates":[6.079976292134834,48.12934752808988]}}]}