{"type":"FeatureCollection","features":[{"type":"Feature","properties":{"codesPostaux":["88000"],"population":1482,"nom":"Deyvillers","code":"88132"},"geometry":{"type":"Point","coordinates":[6.5240379120879135,48.19779505494507]}}]}