{"type":"FeatureCollection","features":[{"type":"Feature","properties":{"codesPostaux":["88600"],"population":227,"nom":"Domfaing","code":"88145"},"geometry":{"type":"Point","coordinates":[6.75315234375,48.23780453125]}}]}