{"type":"FeatureCollection","features":[{"type":"Feature","properties":{"codesPostaux":["88130"],"population":757,"nom":"Essegney","code":"88163"},"geometry":{"type":"Point","coordinates":[6.344538595041321,48.38006099173553]}}]}