{"type":"FeatureCollection","features":[{"type":"Feature","properties":{"codesPostaux":["88410"],"population":52,"nom":"Fign\u00e9velle","code":"88171"},"geometry":{"type":"Point","coordinates":[5.905515384615384,47.984274615384635]}}]}