{"type":"FeatureCollection","features":[{"type":"Feature","properties":{"codesPostaux":["88600"],"population":232,"nom":"Fim\u00e9nil","code":"88172"},"geometry":{"type":"Point","coordinates":[6.709416666666665,48.17875999999999]}}]}