{"type":"FeatureCollection","features":[{"type":"Feature","properties":{"codesPostaux":["88120"],"population":371,"nom":"Gerbamont","code":"88197"},"geometry":{"type":"Point","coordinates":[6.764900408163265,48.005565714285716]}}]}