{"type":"FeatureCollection","features":[{"type":"Feature","properties":{"codesPostaux":["88210"],"population":73,"nom":"Grandrupt","code":"88215"},"geometry":{"type":"Point","coordinates":[7.059478695652173,48.371403043478274]}}]}