{"type":"FeatureCollection","features":[{"type":"Feature","properties":{"codesPostaux":["88240"],"population":255,"nom":"Gruey-l\u00e8s-Surance","code":"88221"},"geometry":{"type":"Point","coordinates":[6.174376842105265,48.032023092105284]}}]}