{"type":"FeatureCollection","features":[{"type":"Feature","properties":{"codesPostaux":["88700"],"population":1127,"nom":"Jeanm\u00e9nil","code":"88251"},"geometry":{"type":"Point","coordinates":[6.703821212121212,48.327829826839796]}}]}