{"type":"FeatureCollection","features":[{"type":"Feature","properties":{"codesPostaux":["88300"],"population":301,"nom":"Landaville","code":"88259"},"geometry":{"type":"Point","coordinates":[5.748750784313727,48.282989411764696]}}]}