{"type":"FeatureCollection","features":[{"type":"Feature","properties":{"codesPostaux":["88630"],"population":88,"nom":"Jubainville","code":"88255"},"geometry":{"type":"Point","coordinates":[5.749308354430378,48.45519860759495]}}]}