{"type":"FeatureCollection","features":[{"type":"Feature","properties":{"codesPostaux":["88410"],"population":74,"nom":"Lironcourt","code":"88272"},"geometry":{"type":"Point","coordinates":[5.8825370652173925,47.97067369565216]}}]}