{"type":"FeatureCollection","features":[{"type":"Feature","properties":{"codesPostaux":["88270"],"population":61,"nom":"Madecourt","code":"88279"},"geometry":{"type":"Point","coordinates":[6.11303649122807,48.23964210526315]}}]}