{"type":"FeatureCollection","features":[{"type":"Feature","properties":{"codesPostaux":["88500"],"population":220,"nom":"Mazirot","code":"88295"},"geometry":{"type":"Point","coordinates":[6.158296153846153,48.322977019230784]}}]}