{"type":"FeatureCollection","features":[{"type":"Feature","properties":{"codesPostaux":["88330"],"population":429,"nom":"Moriville","code":"88313"},"geometry":{"type":"Point","coordinates":[6.424327828947366,48.34378756578949]}}]}