{"type":"FeatureCollection","features":[{"type":"Feature","properties":{"codesPostaux":["88170"],"population":201,"nom":"Morelmaison","code":"88312"},"geometry":{"type":"Point","coordinates":[5.915915249999999,48.319133125000015]}}]}