{"type":"FeatureCollection","features":[{"type":"Feature","properties":{"codesPostaux":["88140"],"population":50,"nom":"Morville","code":"88316"},"geometry":{"type":"Point","coordinates":[5.793676417910449,48.234658955223885]}}]}