{"type":"FeatureCollection","features":[{"type":"Feature","properties":{"codesPostaux":["88600"],"population":495,"nom":"La Neuveville-devant-L\u00e9panges","code":"88322"},"geometry":{"type":"Point","coordinates":[6.666286115107914,48.1552202877698]}}]}