{"type":"FeatureCollection","features":[{"type":"Feature","properties":{"codesPostaux":["88500"],"population":278,"nom":"O\u00eblleville","code":"88334"},"geometry":{"type":"Point","coordinates":[6.024512972972973,48.33430234234235]}}]}