{"type":"FeatureCollection","features":[{"type":"Feature","properties":{"codesPostaux":["88490"],"population":84,"nom":"La Petite-Fosse","code":"88345"},"geometry":{"type":"Point","coordinates":[7.049605980392156,48.31785784313724]}}]}