{"type":"FeatureCollection","features":[{"type":"Feature","properties":{"codesPostaux":["88330"],"population":176,"nom":"Pallegney","code":"88342"},"geometry":{"type":"Point","coordinates":[6.446997500000002,48.29409677083331]}}]}