{"type":"FeatureCollection","features":[{"type":"Feature","properties":{"codesPostaux":["88330"],"population":1273,"nom":"Portieux","code":"88355"},"geometry":{"type":"Point","coordinates":[6.365443142857141,48.35004895238097]}}]}