{"type":"FeatureCollection","features":[{"type":"Feature","properties":{"codesPostaux":["88600"],"population":256,"nom":"Les Pouli\u00e8res","code":"88356"},"geometry":{"type":"Point","coordinates":[6.788645571428568,48.200284571428575]}}]}