{"type":"FeatureCollection","features":[{"type":"Feature","properties":{"codesPostaux":["88130"],"population":21,"nom":"Rapey","code":"88374"},"geometry":{"type":"Point","coordinates":[6.251685555555555,48.317750158730156]}}]}