{"type":"FeatureCollection","features":[{"type":"Feature","properties":{"codesPostaux":["88640"],"population":197,"nom":"Rehaupal","code":"88380"},"geometry":{"type":"Point","coordinates":[6.743016111111111,48.11855227777776]}}]}