{"type":"FeatureCollection","features":[{"type":"Feature","properties":{"codesPostaux":["88120"],"population":2194,"nom":"Saint-Am\u00e9","code":"88409"},"geometry":{"type":"Point","coordinates":[6.656378369565213,48.02429282608695]}}]}