{"type":"FeatureCollection","features":[{"type":"Feature","properties":{"codesPostaux":["88560"],"population":1426,"nom":"Saint-Maurice-sur-Moselle","code":"88426"},"geometry":{"type":"Point","coordinates":[6.854129153439151,47.84107534391534]}}]}