{"type":"FeatureCollection","features":[{"type":"Feature","properties":{"codesPostaux":["88100"],"population":2386,"nom":"Sainte-Marguerite","code":"88424"},"geometry":{"type":"Point","coordinates":[6.974028620689655,48.266595689655155]}}]}