{"type":"FeatureCollection","features":[{"type":"Feature","properties":{"codesPostaux":["88270"],"population":111,"nom":"Saint-Vallier","code":"88437"},"geometry":{"type":"Point","coordinates":[6.319322413793104,48.27809482758622]}}]}