{"type":"FeatureCollection","features":[{"type":"Feature","properties":{"codesPostaux":["88500"],"population":75,"nom":"Saint-Prancher","code":"88433"},"geometry":{"type":"Point","coordinates":[5.948136666666667,48.346134597701145]}}]}