{"type":"FeatureCollection","features":[{"type":"Feature","properties":{"codesPostaux":["88130"],"population":196,"nom":"Savigny","code":"88449"},"geometry":{"type":"Point","coordinates":[6.219335035460991,48.355694609929074]}}]}