{"type":"FeatureCollection","features":[{"type":"Feature","properties":{"codesPostaux":["88800"],"population":137,"nom":"They-sous-Montfort","code":"88466"},"geometry":{"type":"Point","coordinates":[5.966230833333339,48.2309793939394]}}]}