{"type":"FeatureCollection","features":[{"type":"Feature","properties":{"codesPostaux":["88320"],"population":127,"nom":"Tollaincourt","code":"88475"},"geometry":{"type":"Point","coordinates":[5.726304054878049,48.09661603658537]}}]}