{"type":"FeatureCollection","features":[{"type":"Feature","properties":{"codesPostaux":["88270"],"population":149,"nom":"Velotte-et-Tatign\u00e9court","code":"88499"},"geometry":{"type":"Point","coordinates":[6.168916778523492,48.25636322147652]}}]}