{"type":"FeatureCollection","features":[{"type":"Feature","properties":{"codesPostaux":["88140"],"population":168,"nom":"Vaudoncourt","code":"88496"},"geometry":{"type":"Point","coordinates":[5.805460294117645,48.219772352941156]}}]}