{"type":"FeatureCollection","features":[{"type":"Feature","properties":{"codesPostaux":["88500"],"population":227,"nom":"Villers","code":"88507"},"geometry":{"type":"Point","coordinates":[6.1751340625,48.30637937499999]}}]}