{"type":"FeatureCollection","features":[{"type":"Feature","properties":{"codesPostaux":["88170"],"population":156,"nom":"Vicherey","code":"88504"},"geometry":{"type":"Point","coordinates":[5.9340923404255355,48.383022553191495]}}]}