{"type":"FeatureCollection","features":[{"type":"Feature","properties":{"codesPostaux":["88600"],"population":130,"nom":"Vervezelle","code":"88502"},"geometry":{"type":"Point","coordinates":[6.74188042857143,48.22238485714287]}}]}