{"type":"FeatureCollection","features":[{"type":"Feature","properties":{"codesPostaux":["88350"],"population":81,"nom":"Villouxel","code":"88511"},"geometry":{"type":"Point","coordinates":[5.582932340425533,48.34585659574468]}}]}