{"type":"FeatureCollection","features":[{"type":"Feature","properties":{"codesPostaux":["88470"],"population":712,"nom":"La Voivre","code":"88519"},"geometry":{"type":"Point","coordinates":[6.902951221374048,48.34374816793892]}}]}