{"type":"FeatureCollection","features":[{"type":"Feature","properties":{"codesPostaux":["88460"],"population":148,"nom":"Xamontarupt","code":"88528"},"geometry":{"type":"Point","coordinates":[6.64427042424242,48.12387593939394]}}]}