{"type":"FeatureCollection","features":[{"type":"Feature","properties":{"codesPostaux":["89160"],"population":183,"nom":"Ancy-le-Libre","code":"89006"},"geometry":{"type":"Point","coordinates":[4.1453852000000015,47.80662128000002]}}]}