{"type":"FeatureCollection","features":[{"type":"Feature","properties":{"codesPostaux":["89320"],"population":641,"nom":"Arces-Dilo","code":"89014"},"geometry":{"type":"Point","coordinates":[3.584173161764706,48.100952867647045]}}]}