{"type":"FeatureCollection","features":[{"type":"Feature","properties":{"codesPostaux":["89440"],"population":142,"nom":"Athie","code":"89022"},"geometry":{"type":"Point","coordinates":[3.997908301886792,47.54417905660376]}}]}