{"type":"FeatureCollection","features":[{"type":"Feature","properties":{"codesPostaux":["89660"],"population":310,"nom":"Brosses","code":"89057"},"geometry":{"type":"Point","coordinates":[3.6879997101449256,47.529186956521734]}}]}