{"type":"FeatureCollection","features":[{"type":"Feature","properties":{"codesPostaux":["89630"],"population":134,"nom":"Bussi\u00e8res","code":"89058"},"geometry":{"type":"Point","coordinates":[4.048733664921469,47.42681387434555]}}]}