{"type":"FeatureCollection","features":[{"type":"Feature","properties":{"codesPostaux":["89290"],"population":1549,"nom":"Champs-sur-Yonne","code":"89077"},"geometry":{"type":"Point","coordinates":[3.6018447826086954,47.74939913043479]}}]}