{"type":"FeatureCollection","features":[{"type":"Feature","properties":{"codesPostaux":["89400"],"population":1166,"nom":"Charmoy","code":"89085"},"geometry":{"type":"Point","coordinates":[3.4972401724137936,47.94420379310344]}}]}