{"type":"FeatureCollection","features":[{"type":"Feature","properties":{"codesPostaux":["89800"],"population":92,"nom":"La Chapelle-Vaupelteigne","code":"89081"},"geometry":{"type":"Point","coordinates":[3.770367045454547,47.8436130681818]}}]}