{"type":"FeatureCollection","features":[{"type":"Feature","properties":{"codesPostaux":["89120","89350"],"population":5147,"nom":"Charny Or\u00e9e de Puisaye","code":"89086"},"geometry":{"type":"Point","coordinates":[3.129314279835391,47.88189393004113]}}]}