{"type":"FeatureCollection","features":[{"type":"Feature","properties":{"codesPostaux":["89580"],"population":309,"nom":"Charentenay","code":"89084"},"geometry":{"type":"Point","coordinates":[3.5543995049504944,47.64535772277229]}}]}