{"type":"FeatureCollection","features":[{"type":"Feature","properties":{"codesPostaux":["89400"],"population":454,"nom":"Chichery","code":"89105"},"geometry":{"type":"Point","coordinates":[3.512335512820513,47.90547269230769]}}]}