{"type":"FeatureCollection","features":[{"type":"Feature","properties":{"codesPostaux":["89190"],"population":281,"nom":"Les Cl\u00e9rimois","code":"89111"},"geometry":{"type":"Point","coordinates":[3.4623022727272716,48.229169318181796]}}]}