{"type":"FeatureCollection","features":[{"type":"Feature","properties":{"codesPostaux":["89240"],"population":1147,"nom":"Diges","code":"89139"},"geometry":{"type":"Point","coordinates":[3.3933262820512833,47.72148769230771]}}]}