{"type":"FeatureCollection","features":[{"type":"Feature","properties":{"codesPostaux":["89200"],"population":106,"nom":"Domecy-sur-le-Vault","code":"89146"},"geometry":{"type":"Point","coordinates":[3.811500493827161,47.49111222222223]}}]}