{"type":"FeatureCollection","features":[{"type":"Feature","properties":{"codesPostaux":["89210"],"population":393,"nom":"Esnon","code":"89156"},"geometry":{"type":"Point","coordinates":[3.5661354166666643,48.01405975]}}]}