{"type":"FeatureCollection","features":[{"type":"Feature","properties":{"codesPostaux":["89360"],"population":1023,"nom":"Flogny-la-Chapelle","code":"89169"},"geometry":{"type":"Point","coordinates":[3.8793953005464514,47.96184879781421]}}]}