{"type":"FeatureCollection","features":[{"type":"Feature","properties":{"codesPostaux":["89160"],"population":132,"nom":"Fulvy","code":"89184"},"geometry":{"type":"Point","coordinates":[4.165985090909091,47.741340545454534]}}]}