{"type":"FeatureCollection","features":[{"type":"Feature","properties":{"codesPostaux":["89310"],"population":69,"nom":"Fresnes","code":"89183"},"geometry":{"type":"Point","coordinates":[3.9936872839506172,47.761376913580264]}}]}