{"type":"FeatureCollection","features":[{"type":"Feature","properties":{"codesPostaux":["89290"],"population":290,"nom":"Irancy","code":"89202"},"geometry":{"type":"Point","coordinates":[3.6858199999999997,47.713171160714275]}}]}