{"type":"FeatureCollection","features":[{"type":"Feature","properties":{"codesPostaux":["89250"],"population":411,"nom":"Hauterive","code":"89200"},"geometry":{"type":"Point","coordinates":[3.610076766917294,47.92814075187973]}}]}