{"type":"FeatureCollection","features":[{"type":"Feature","properties":{"codesPostaux":["89300"],"population":9690,"nom":"Joigny","code":"89206"},"geometry":{"type":"Point","coordinates":[3.412267562189056,48.018856467661706]}}]}