{"type":"FeatureCollection","features":[{"type":"Feature","properties":{"codesPostaux":["89160"],"population":148,"nom":"Jully","code":"89210"},"geometry":{"type":"Point","coordinates":[4.300782525252527,47.77039707070708]}}]}