{"type":"FeatureCollection","features":[{"type":"Feature","properties":{"codesPostaux":["89290"],"population":411,"nom":"Jussy","code":"89212"},"geometry":{"type":"Point","coordinates":[3.571562272727273,47.71602329545456]}}]}