{"type":"FeatureCollection","features":[{"type":"Feature","properties":{"codesPostaux":["89240"],"population":1383,"nom":"Lindry","code":"89228"},"geometry":{"type":"Point","coordinates":[3.4280702912621352,47.80243077669905]}}]}