{"type":"FeatureCollection","features":[{"type":"Feature","properties":{"codesPostaux":["89100"],"population":1540,"nom":"Malay-le-Grand","code":"89239"},"geometry":{"type":"Point","coordinates":[3.350284395604396,48.16681428571426]}}]}