{"type":"FeatureCollection","features":[{"type":"Feature","properties":{"codesPostaux":["89480"],"population":151,"nom":"Lucy-sur-Yonne","code":"89234"},"geometry":{"type":"Point","coordinates":[3.5682148484848484,47.518475]}}]}