{"type":"FeatureCollection","features":[{"type":"Feature","properties":{"codesPostaux":["89500"],"population":811,"nom":"Marsangy","code":"89245"},"geometry":{"type":"Point","coordinates":[3.2440013592233012,48.11203407766991]}}]}