{"type":"FeatureCollection","features":[{"type":"Feature","properties":{"codesPostaux":["89660"],"population":214,"nom":"Merry-sur-Yonne","code":"89253"},"geometry":{"type":"Point","coordinates":[3.6400912422360236,47.55990813664595]}}]}