{"type":"FeatureCollection","features":[{"type":"Feature","properties":{"codesPostaux":["89130"],"population":590,"nom":"M\u00e9zilles","code":"89254"},"geometry":{"type":"Point","coordinates":[3.189155471698114,47.697152754717]}}]}