{"type":"FeatureCollection","features":[{"type":"Feature","properties":{"codesPostaux":["89700"],"population":184,"nom":"Molosmes","code":"89262"},"geometry":{"type":"Point","coordinates":[4.0264693396226425,47.903822264150925]}}]}