{"type":"FeatureCollection","features":[{"type":"Feature","properties":{"codesPostaux":["89310"],"population":105,"nom":"Moulins-en-Tonnerrois","code":"89271"},"geometry":{"type":"Point","coordinates":[4.044562666666668,47.730080857142866]}}]}