{"type":"FeatureCollection","features":[{"type":"Feature","properties":{"codesPostaux":["89100"],"population":4719,"nom":"Paron","code":"89287"},"geometry":{"type":"Point","coordinates":[3.237087051282052,48.185481538461545]}}]}