{"type":"FeatureCollection","features":[{"type":"Feature","properties":{"codesPostaux":["89390"],"population":408,"nom":"Nuits","code":"89280"},"geometry":{"type":"Point","coordinates":[4.197249059829058,47.72331264957263]}}]}