{"type":"FeatureCollection","features":[{"type":"Feature","properties":{"codesPostaux":["89000"],"population":1289,"nom":"Perrigny","code":"89295"},"geometry":{"type":"Point","coordinates":[3.5248031666666657,47.823035333333316]}}]}