{"type":"FeatureCollection","features":[{"type":"Feature","properties":{"codesPostaux":["89460"],"population":200,"nom":"Pr\u00e9gilbert","code":"89314"},"geometry":{"type":"Point","coordinates":[3.677130919540229,47.63859252873565]}}]}