{"type":"FeatureCollection","features":[{"type":"Feature","properties":{"codesPostaux":["89440"],"population":274,"nom":"Pr\u00e9cy-le-Sec","code":"89312"},"geometry":{"type":"Point","coordinates":[3.818844337349395,47.586984277108435]}}]}