{"type":"FeatureCollection","features":[{"type":"Feature","properties":{"codesPostaux":["89200"],"population":203,"nom":"Provency","code":"89316"},"geometry":{"type":"Point","coordinates":[3.947453265306122,47.54468102040818]}}]}