{"type":"FeatureCollection","features":[{"type":"Feature","properties":{"codesPostaux":["89170"],"population":105,"nom":"Ronch\u00e8res","code":"89325"},"geometry":{"type":"Point","coordinates":[3.1200257692307694,47.65489134615386]}}]}