{"type":"FeatureCollection","features":[{"type":"Feature","properties":{"codesPostaux":["89520"],"population":918,"nom":"Saint-Sauveur-en-Puisaye","code":"89368"},"geometry":{"type":"Point","coordinates":[3.2126327192982442,47.63990201754389]}}]}