{"type":"FeatureCollection","features":[{"type":"Feature","properties":{"codesPostaux":["89150"],"population":1703,"nom":"Saint-Val\u00e9rien","code":"89370"},"geometry":{"type":"Point","coordinates":[3.0988827737226274,48.17352927007302]}}]}