{"type":"FeatureCollection","features":[{"type":"Feature","properties":{"codesPostaux":["89100"],"population":662,"nom":"Saligny","code":"89373"},"geometry":{"type":"Point","coordinates":[3.3510482474226806,48.21410762886599]}}]}