{"type":"FeatureCollection","features":[{"type":"Feature","properties":{"codesPostaux":["89150"],"population":404,"nom":"Savigny-sur-Clairis","code":"89380"},"geometry":{"type":"Point","coordinates":[3.081748428571428,48.078384142857125]}}]}