{"type":"FeatureCollection","features":[{"type":"Feature","properties":{"codesPostaux":["89420"],"population":88,"nom":"Talcy","code":"89406"},"geometry":{"type":"Point","coordinates":[4.076033658536584,47.57826463414635]}}]}