{"type":"FeatureCollection","features":[{"type":"Feature","properties":{"codesPostaux":["89450"],"population":64,"nom":"Tharoiseau","code":"89409"},"geometry":{"type":"Point","coordinates":[3.8188844927536243,47.46273521739131]}}]}