{"type":"FeatureCollection","features":[{"type":"Feature","properties":{"codesPostaux":["89430"],"population":40,"nom":"Thorey","code":"89413"},"geometry":{"type":"Point","coordinates":[4.11462021978022,47.89642054945055]}}]}