{"type":"FeatureCollection","features":[{"type":"Feature","properties":{"codesPostaux":["89320"],"population":354,"nom":"Vaumort","code":"89434"},"geometry":{"type":"Point","coordinates":[3.441985625,48.142041]}}]}