{"type":"FeatureCollection","features":[{"type":"Feature","properties":{"codesPostaux":["89700"],"population":181,"nom":"V\u00e9zinnes","code":"89447"},"geometry":{"type":"Point","coordinates":[3.935460178571429,47.895486964285716]}}]}