{"type":"FeatureCollection","features":[{"type":"Feature","properties":{"codesPostaux":["89150"],"population":228,"nom":"Vernoy","code":"89442"},"geometry":{"type":"Point","coordinates":[3.128366249999999,48.09428464285714]}}]}