{"type":"FeatureCollection","features":[{"type":"Feature","properties":{"codesPostaux":["89140"],"population":323,"nom":"Villeperrot","code":"89465"},"geometry":{"type":"Point","coordinates":[3.2103773913043487,48.257703188405806]}}]}