{"type":"FeatureCollection","features":[{"type":"Feature","properties":{"codesPostaux":["89160"],"population":150,"nom":"Villiers-les-Hauts","code":"89470"},"geometry":{"type":"Point","coordinates":[4.1582131034482765,47.72347137931033]}}]}