{"type":"FeatureCollection","features":[{"type":"Feature","properties":{"codesPostaux":["89160"],"population":135,"nom":"Vireaux","code":"89481"},"geometry":{"type":"Point","coordinates":[4.040139910714286,47.78791133928572]}}]}