{"type":"FeatureCollection","features":[{"type":"Feature","properties":{"codesPostaux":["90150"],"population":321,"nom":"Angeot","code":"90002"},"geometry":{"type":"Point","coordinates":[7.008109090909092,47.69462727272727]}}]}