{"type":"FeatureCollection","features":[{"type":"Feature","properties":{"codesPostaux":["90160"],"population":1104,"nom":"Bessoncourt","code":"90012"},"geometry":{"type":"Point","coordinates":[6.941035471698115,47.64644716981133]}}]}