{"type":"FeatureCollection","features":[{"type":"Feature","properties":{"codesPostaux":["90140"],"population":299,"nom":"Charmois","code":"90021"},"geometry":{"type":"Point","coordinates":[6.945103839285712,47.57821830357143]}}]}