{"type":"FeatureCollection","features":[{"type":"Feature","properties":{"codesPostaux":["90340"],"population":1593,"nom":"Ch\u00e8vremont","code":"90026"},"geometry":{"type":"Point","coordinates":[6.933923490566038,47.62660150943394]}}]}