{"type":"FeatureCollection","features":[{"type":"Feature","properties":{"codesPostaux":["90800"],"population":307,"nom":"Buc","code":"90020"},"geometry":{"type":"Point","coordinates":[6.7890710638297875,47.61881234042552]}}]}