{"type":"FeatureCollection","features":[{"type":"Feature","properties":{"codesPostaux":["90400"],"population":651,"nom":"Dorans","code":"90035"},"geometry":{"type":"Point","coordinates":[6.8412062500000035,47.58708357142855]}}]}