{"type":"FeatureCollection","features":[{"type":"Feature","properties":{"codesPostaux":["90160"],"population":771,"nom":"Denney","code":"90034"},"geometry":{"type":"Point","coordinates":[6.901242881355931,47.654468983050826]}}]}