{"type":"FeatureCollection","features":[{"type":"Feature","properties":{"codesPostaux":["90100"],"population":5818,"nom":"Delle","code":"90033"},"geometry":{"type":"Point","coordinates":[7.003377832167837,47.51389566433567]}}]}