{"type":"FeatureCollection","features":[{"type":"Feature","properties":{"codesPostaux":["90150"],"population":419,"nom":"Menoncourt","code":"90067"},"geometry":{"type":"Point","coordinates":[6.951870000000001,47.68163461538462]}}]}