{"type":"FeatureCollection","features":[{"type":"Feature","properties":{"codesPostaux":["90120"],"population":1400,"nom":"M\u00e9zir\u00e9","code":"90069"},"geometry":{"type":"Point","coordinates":[6.922084358974361,47.5324526923077]}}]}