{"type":"FeatureCollection","features":[{"type":"Feature","properties":{"codesPostaux":["90360"],"population":192,"nom":"Petitefontaine","code":"90078"},"geometry":{"type":"Point","coordinates":[7.007682711864406,47.723769152542374]}}]}