{"type":"FeatureCollection","features":[{"type":"Feature","properties":{"codesPostaux":["90340"],"population":281,"nom":"Novillard","code":"90074"},"geometry":{"type":"Point","coordinates":[6.963695901639348,47.603393360655744]}}]}