{"type":"FeatureCollection","features":[{"type":"Feature","properties":{"codesPostaux":["90170"],"population":280,"nom":"Petitmagny","code":"90079"},"geometry":{"type":"Point","coordinates":[6.898662592592593,47.72176296296297]}}]}