{"type":"FeatureCollection","features":[{"type":"Feature","properties":{"codesPostaux":["90200"],"population":1025,"nom":"Rougegoutte","code":"90088"},"geometry":{"type":"Point","coordinates":[6.862125176470586,47.73469999999999]}}]}