{"type":"FeatureCollection","features":[{"type":"Feature","properties":{"codesPostaux":["90100"],"population":287,"nom":"Thiancourt","code":"90096"},"geometry":{"type":"Point","coordinates":[6.984828500000001,47.52398758333332]}}]}