{"type":"FeatureCollection","features":[{"type":"Feature","properties":{"codesPostaux":["90400"],"population":1193,"nom":"Tr\u00e9venans","code":"90097"},"geometry":{"type":"Point","coordinates":[6.868456219512197,47.567728902439036]}}]}