{"type":"FeatureCollection","features":[{"type":"Feature","properties":{"codesPostaux":["90110"],"population":626,"nom":"Saint-Germain-le-Ch\u00e2telet","code":"90091"},"geometry":{"type":"Point","coordinates":[6.960732911392407,47.70100215189872]}}]}