{"type":"FeatureCollection","features":[{"type":"Feature","properties":{"codesPostaux":["90200"],"population":752,"nom":"Vescemont","code":"90102"},"geometry":{"type":"Point","coordinates":[6.859853749999998,47.752615208333346]}}]}