{"type":"FeatureCollection","features":[{"type":"Feature","properties":{"codesPostaux":["91470"],"population":1642,"nom":"Angervilliers","code":"91017"},"geometry":{"type":"Point","coordinates":[2.0628713953488376,48.591064069767434]}}]}