{"type":"FeatureCollection","features":[{"type":"Feature","properties":{"codesPostaux":["91570"],"population":4483,"nom":"Bi\u00e8vres","code":"91064"},"geometry":{"type":"Point","coordinates":[2.210119111111111,48.76111577777778]}}]}