{"type":"FeatureCollection","features":[{"type":"Feature","properties":{"codesPostaux":["91850"],"population":2131,"nom":"Bouray-sur-Juine","code":"91095"},"geometry":{"type":"Point","coordinates":[2.296588313253012,48.51400421686748]}}]}