{"type":"FeatureCollection","features":[{"type":"Feature","properties":{"codesPostaux":["91650"],"population":8454,"nom":"Breuillet","code":"91105"},"geometry":{"type":"Point","coordinates":[2.167963944954129,48.57444844036697]}}]}