{"type":"FeatureCollection","features":[{"type":"Feature","properties":{"codesPostaux":["91440"],"population":9725,"nom":"Bures-sur-Yvette","code":"91122"},"geometry":{"type":"Point","coordinates":[2.15627372413793,48.69129737931034]}}]}