{"type":"FeatureCollection","features":[{"type":"Feature","properties":{"codesPostaux":["91490"],"population":346,"nom":"Courances","code":"91180"},"geometry":{"type":"Point","coordinates":[2.486032470588235,48.43971776470588]}}]}