{"type":"FeatureCollection","features":[{"type":"Feature","properties":{"codesPostaux":["91410"],"population":10342,"nom":"Dourdan","code":"91200"},"geometry":{"type":"Point","coordinates":[1.9870707851239684,48.5345912809918]}}]}