{"type":"FeatureCollection","features":[{"type":"Feature","properties":{"codesPostaux":["91660"],"population":231,"nom":"Estouches","code":"91222"},"geometry":{"type":"Point","coordinates":[2.135980810810811,48.310292162162156]}}]}