{"type":"FeatureCollection","features":[{"type":"Feature","properties":{"codesPostaux":["91410"],"population":1154,"nom":"Les Granges-le-Roi","code":"91284"},"geometry":{"type":"Point","coordinates":[2.0079811764705884,48.49880225490195]}}]}