{"type":"FeatureCollection","features":[{"type":"Feature","properties":{"codesPostaux":["91590"],"population":953,"nom":"Guigneville-sur-Essonne","code":"91293"},"geometry":{"type":"Point","coordinates":[2.3599437864077677,48.46308504854369]}}]}