{"type":"FeatureCollection","features":[{"type":"Feature","properties":{"codesPostaux":["91760"],"population":6659,"nom":"Itteville","code":"91315"},"geometry":{"type":"Point","coordinates":[2.347493113772455,48.51536784431136]}}]}