{"type":"FeatureCollection","features":[{"type":"Feature","properties":{"codesPostaux":["91510"],"population":1964,"nom":"Janville-sur-Juine","code":"91318"},"geometry":{"type":"Point","coordinates":[2.250934809160306,48.50218175572519]}}]}