{"type":"FeatureCollection","features":[{"type":"Feature","properties":{"codesPostaux":["91630"],"population":1433,"nom":"Leudeville","code":"91332"},"geometry":{"type":"Point","coordinates":[2.3295864835164846,48.57299285714288]}}]}