{"type":"FeatureCollection","features":[{"type":"Feature","properties":{"codesPostaux":["91310"],"population":6594,"nom":"Longpont-sur-Orge","code":"91347"},"geometry":{"type":"Point","coordinates":[2.2885994949494943,48.63531383838385]}}]}