{"type":"FeatureCollection","features":[{"type":"Feature","properties":{"codesPostaux":["91590"],"population":706,"nom":"Mondeville","code":"91412"},"geometry":{"type":"Point","coordinates":[2.4172742553191484,48.490251489361704]}}]}