{"type":"FeatureCollection","features":[{"type":"Feature","properties":{"codesPostaux":["91620"],"population":4778,"nom":"Nozay","code":"91458"},"geometry":{"type":"Point","coordinates":[2.242252413793103,48.660883448275854]}}]}