{"type":"FeatureCollection","features":[{"type":"Feature","properties":{"codesPostaux":["91290"],"population":4107,"nom":"La Norville","code":"91457"},"geometry":{"type":"Point","coordinates":[2.266790909090909,48.57963948051948]}}]}