{"type":"FeatureCollection","features":[{"type":"Feature","properties":{"codesPostaux":["91410"],"population":311,"nom":"Plessis-Saint-Benoist","code":"91495"},"geometry":{"type":"Point","coordinates":[2.0076608928571433,48.442600535714284]}}]}