{"type":"FeatureCollection","features":[{"type":"Feature","properties":{"codesPostaux":["91940"],"population":289,"nom":"Saint-Jean-de-Beauregard","code":"91560"},"geometry":{"type":"Point","coordinates":[2.175161304347826,48.66550507246378]}}]}