{"type":"FeatureCollection","features":[{"type":"Feature","properties":{"codesPostaux":["91250"],"population":5343,"nom":"Saintry-sur-Seine","code":"91577"},"geometry":{"type":"Point","coordinates":[2.4956812499999996,48.5930725]}}]}