{"type":"FeatureCollection","features":[{"type":"Feature","properties":{"codesPostaux":["91530"],"population":1648,"nom":"Sermaise","code":"91593"},"geometry":{"type":"Point","coordinates":[2.0917382417582417,48.53053582417583]}}]}