{"type":"FeatureCollection","features":[{"type":"Feature","properties":{"codesPostaux":["91580"],"population":403,"nom":"Souzy-la-Briche","code":"91602"},"geometry":{"type":"Point","coordinates":[2.1473304285714283,48.528756]}}]}