{"type":"FeatureCollection","features":[{"type":"Feature","properties":{"codesPostaux":["91740"],"population":232,"nom":"Congerville-Thionville","code":"91613"},"geometry":{"type":"Point","coordinates":[1.9904683157894734,48.37794873684211]}}]}