{"type":"FeatureCollection","features":[{"type":"Feature","properties":{"codesPostaux":["91580"],"population":721,"nom":"Villeconin","code":"91662"},"geometry":{"type":"Point","coordinates":[2.126099279279279,48.49822432432433]}}]}