{"type":"FeatureCollection","features":[{"type":"Feature","properties":{"codesPostaux":["91140"],"population":10344,"nom":"Villebon-sur-Yvette","code":"91661"},"geometry":{"type":"Point","coordinates":[2.2369696093750004,48.69790546874999]}}]}