{"type":"FeatureCollection","features":[{"type":"Feature","properties":{"codesPostaux":["91320"],"population":7143,"nom":"Wissous","code":"91689"},"geometry":{"type":"Point","coordinates":[2.3293809876543214,48.73321333333333]}}]}