{"type":"FeatureCollection","features":[{"type":"Feature","properties":{"codesPostaux":["92260"],"population":22378,"nom":"Fontenay-aux-Roses","code":"92032"},"geometry":{"type":"Point","coordinates":[2.2826922448979587,48.789906734693886]}}]}