{"type":"FeatureCollection","features":[{"type":"Feature","properties":{"codesPostaux":["92240"],"population":30304,"nom":"Malakoff","code":"92046"},"geometry":{"type":"Point","coordinates":[2.2903355999999997,48.813463999999996]}}]}