{"type":"FeatureCollection","features":[{"type":"Feature","properties":{"codesPostaux":["92120"],"population":49656,"nom":"Montrouge","code":"92049"},"geometry":{"type":"Point","coordinates":[2.318010909090909,48.81344454545455]}}]}