{"type":"FeatureCollection","features":[{"type":"Feature","properties":{"codesPostaux":["92310"],"population":23404,"nom":"S\u00e8vres","code":"92072"},"geometry":{"type":"Point","coordinates":[2.2098715116279077,48.8216746511628]}}]}