{"type":"FeatureCollection","features":[{"type":"Feature","properties":{"codesPostaux":["92410"],"population":11266,"nom":"Ville-d'Avray","code":"92077"},"geometry":{"type":"Point","coordinates":[2.1772541818181823,48.82247345454546]}}]}