{"type":"FeatureCollection","features":[{"type":"Feature","properties":{"codesPostaux":["92150"],"population":48066,"nom":"Suresnes","code":"92073"},"geometry":{"type":"Point","coordinates":[2.2160460465116274,48.870278139534875]}}]}