{"type":"FeatureCollection","features":[{"type":"Feature","properties":{"codesPostaux":["93190"],"population":43099,"nom":"Livry-Gargan","code":"93046"},"geometry":{"type":"Point","coordinates":[2.5349509009009004,48.9203337837838]}}]}