{"type":"FeatureCollection","features":[{"type":"Feature","properties":{"codesPostaux":["93310"],"population":17908,"nom":"Le Pr\u00e9-Saint-Gervais","code":"93061"},"geometry":{"type":"Point","coordinates":[2.4074359999999997,48.88463720000001]}}]}