{"type":"FeatureCollection","features":[{"type":"Feature","properties":{"codesPostaux":["94360"],"population":16423,"nom":"Bry-sur-Marne","code":"94015"},"geometry":{"type":"Point","coordinates":[2.5222085185185192,48.8368512962963]}}]}