{"type":"FeatureCollection","features":[{"type":"Feature","properties":{"codesPostaux":["94490"],"population":10016,"nom":"Ormesson-sur-Marne","code":"94055"},"geometry":{"type":"Point","coordinates":[2.538874545454545,48.78572218181818]}}]}