{"type":"FeatureCollection","features":[{"type":"Feature","properties":{"codesPostaux":["94170"],"population":33480,"nom":"Le Perreux-sur-Marne","code":"94058"},"geometry":{"type":"Point","coordinates":[2.506140238095238,48.84388404761904]}}]}