{"type":"FeatureCollection","features":[{"type":"Feature","properties":{"codesPostaux":["94130"],"population":31367,"nom":"Nogent-sur-Marne","code":"94052"},"geometry":{"type":"Point","coordinates":[2.4769032000000006,48.836542400000006]}}]}