{"type":"FeatureCollection","features":[{"type":"Feature","properties":{"codesPostaux":["94310"],"population":22377,"nom":"Orly","code":"94054"},"geometry":{"type":"Point","coordinates":[2.4002320000000004,48.742616857142856]}}]}