{"type":"FeatureCollection","features":[{"type":"Feature","properties":{"codesPostaux":["94100","94210"],"population":74133,"nom":"Saint-Maur-des-Foss\u00e9s","code":"94068"},"geometry":{"type":"Point","coordinates":[2.490535471698113,48.80157264150943]}}]}