{"type":"FeatureCollection","features":[{"type":"Feature","properties":{"codesPostaux":["94300"],"population":49695,"nom":"Vincennes","code":"94080"},"geometry":{"type":"Point","coordinates":[2.4411590697674423,48.84797953488372]}}]}