{"type":"FeatureCollection","features":[{"type":"Feature","properties":{"codesPostaux":["95100"],"population":106817,"nom":"Argenteuil","code":"95018"},"geometry":{"type":"Point","coordinates":[2.2433797979797983,48.954656464646455]}}]}