{"type":"FeatureCollection","features":[{"type":"Feature","properties":{"codesPostaux":["95420","95710"],"population":414,"nom":"Ambleville","code":"95011"},"geometry":{"type":"Point","coordinates":[1.6962276470588231,49.15195176470586]}}]}