{"type":"FeatureCollection","features":[{"type":"Feature","properties":{"codesPostaux":["95420"],"population":291,"nom":"Arthies","code":"95024"},"geometry":{"type":"Point","coordinates":[1.798987580645161,49.0901714516129]}}]}