{"type":"FeatureCollection","features":[{"type":"Feature","properties":{"codesPostaux":["95270"],"population":2577,"nom":"Asni\u00e8res-sur-Oise","code":"95026"},"geometry":{"type":"Point","coordinates":[2.3810860937499996,49.143261640625035]}}]}