{"type":"FeatureCollection","features":[{"type":"Feature","properties":{"codesPostaux":["95770"],"population":317,"nom":"Buhy","code":"95119"},"geometry":{"type":"Point","coordinates":[1.7062658695652186,49.19013239130433]}}]}