{"type":"FeatureCollection","features":[{"type":"Feature","properties":{"codesPostaux":["95660"],"population":4717,"nom":"Champagne-sur-Oise","code":"95134"},"geometry":{"type":"Point","coordinates":[2.2248012500000005,49.141954431818185]}}]}