{"type":"FeatureCollection","features":[{"type":"Feature","properties":{"codesPostaux":["95440"],"population":7263,"nom":"\u00c9couen","code":"95205"},"geometry":{"type":"Point","coordinates":[2.38073104477612,49.02253925373134]}}]}