{"type":"FeatureCollection","features":[{"type":"Feature","properties":{"codesPostaux":["95380"],"population":113,"nom":"\u00c9piais-l\u00e8s-Louvres","code":"95212"},"geometry":{"type":"Point","coordinates":[2.5498799999999995,49.03266831325301]}}]}