{"type":"FeatureCollection","features":[{"type":"Feature","properties":{"codesPostaux":["95300"],"population":2377,"nom":"Ennery","code":"95211"},"geometry":{"type":"Point","coordinates":[2.1083259770114937,49.073210574712654]}}]}