{"type":"FeatureCollection","features":[{"type":"Feature","properties":{"codesPostaux":["95120"],"population":28021,"nom":"Ermont","code":"95219"},"geometry":{"type":"Point","coordinates":[2.2588133898305087,48.98723271186442]}}]}