{"type":"FeatureCollection","features":[{"type":"Feature","properties":{"codesPostaux":["95130"],"population":33375,"nom":"Franconville","code":"95252"},"geometry":{"type":"Point","coordinates":[2.223231126760563,48.98359014084506]}}]}