{"type":"FeatureCollection","features":[{"type":"Feature","properties":{"codesPostaux":["95450"],"population":171,"nom":"Guiry-en-Vexin","code":"95295"},"geometry":{"type":"Point","coordinates":[1.8526771212121214,49.115666363636365]}}]}