{"type":"FeatureCollection","features":[{"type":"Feature","properties":{"codesPostaux":["95420"],"population":201,"nom":"Maud\u00e9tour-en-Vexin","code":"95379"},"geometry":{"type":"Point","coordinates":[1.7758089285714285,49.11218607142856]}}]}