{"type":"FeatureCollection","features":[{"type":"Feature","properties":{"codesPostaux":["95560"],"population":3414,"nom":"Montsoult","code":"95430"},"geometry":{"type":"Point","coordinates":[2.300526288659793,49.07253041237116]}}]}