{"type":"FeatureCollection","features":[{"type":"Feature","properties":{"codesPostaux":["95520"],"population":16441,"nom":"Osny","code":"95476"},"geometry":{"type":"Point","coordinates":[2.0648887179487176,49.06657884615384]}}]}