{"type":"FeatureCollection","features":[{"type":"Feature","properties":{"codesPostaux":["95270"],"population":2688,"nom":"Saint-Martin-du-Tertre","code":"95566"},"geometry":{"type":"Point","coordinates":[2.335620677966103,49.09757347457624]}}]}