{"type":"FeatureCollection","features":[{"type":"Feature","properties":{"codesPostaux":["95510"],"population":492,"nom":"Villers-en-Arthies","code":"95676"},"geometry":{"type":"Point","coordinates":[1.7301749999999998,49.08014703125001]}}]}