{"type":"FeatureCollection","features":[{"type":"Feature","properties":{"codesPostaux":["95720"],"population":179,"nom":"Villiers-le-Sec","code":"95682"},"geometry":{"type":"Point","coordinates":[2.386183888888889,49.07325222222224]}}]}