{"type":"FeatureCollection","features":[{"type":"Feature","properties":{"codesPostaux":["97130"],"population":19201,"nom":"Capesterre-Belle-Eau","code":"97107"},"geometry":{"type":"Point","coordinates":[-61.60291911838789,16.051347078085637]}}]}