{"type":"FeatureCollection","features":[{"type":"Feature","properties":{"codesPostaux":["97160"],"population":22456,"nom":"Le Moule","code":"97117"},"geometry":{"type":"Point","coordinates":[-61.36673639215681,16.325903980392177]}}]}