{"type":"FeatureCollection","features":[{"type":"Feature","properties":{"codesPostaux":["97190"],"population":26900,"nom":"Le Gosier","code":"97113"},"geometry":{"type":"Point","coordinates":[-61.48265397196262,16.2179559813084]}}]}