{"type":"FeatureCollection","features":[{"type":"Feature","properties":{"codesPostaux":["97116"],"population":6594,"nom":"Pointe-Noire","code":"97121"},"geometry":{"type":"Point","coordinates":[-61.77029318749995,16.229693875]}}]}