{"type":"FeatureCollection","features":[{"type":"Feature","properties":{"codesPostaux":["97119"],"population":7425,"nom":"Vieux-Habitants","code":"97134"},"geometry":{"type":"Point","coordinates":[-61.72753088328072,16.082780536277593]}}]}