{"type":"FeatureCollection","features":[{"type":"Feature","properties":{"codesPostaux":["97136"],"population":1093,"nom":"Terre-de-Bas","code":"97130"},"geometry":{"type":"Point","coordinates":[-61.626879627907016,15.849999023255807]}}]}