{"type":"FeatureCollection","features":[{"type":"Feature","properties":{"codesPostaux":["97250"],"population":1632,"nom":"Le Pr\u00eacheur","code":"97219"},"geometry":{"type":"Point","coordinates":[-61.20243258215968,14.824840563380278]}}]}