{"type":"FeatureCollection","features":[{"type":"Feature","properties":{"codesPostaux":["97218"],"population":583,"nom":"Grand'Rivi\u00e8re","code":"97211"},"geometry":{"type":"Point","coordinates":[-61.17950797468355,14.85069170886076]}}]}