{"type":"FeatureCollection","features":[{"type":"Feature","properties":{"codesPostaux":["97212"],"population":16885,"nom":"Saint-Joseph","code":"97224"},"geometry":{"type":"Point","coordinates":[-61.04522368550363,14.67833412776412]}}]}