{"type":"FeatureCollection","features":[{"type":"Feature","properties":{"codesPostaux":["97231"],"population":23296,"nom":"Le Robert","code":"97222"},"geometry":{"type":"Point","coordinates":[-60.920236798603085,14.677971839348082]}}]}