{"type":"FeatureCollection","features":[{"type":"Feature","properties":{"codesPostaux":["97320"],"population":41515,"nom":"Saint-Laurent-du-Maroni","code":"97311"},"geometry":{"type":"Point","coordinates":[-53.97829708136623,4.973395120799782]}}]}