{"type":"FeatureCollection","features":[{"type":"Feature","properties":{"codesPostaux":["97438"],"population":32605,"nom":"Sainte-Marie","code":"97418"},"geometry":{"type":"Point","coordinates":[55.53050882926826,-20.952830439024382]}}]}