{"type":"FeatureCollection","features":[{"type":"Feature","properties":{"codesPostaux":["97421","97450"],"population":52656,"nom":"Saint-Louis","code":"97414"},"geometry":{"type":"Point","coordinates":[55.42063501639345,-21.22476881967216]}}]}