{"type":"FeatureCollection","features":[{"type":"Feature","properties":{"codesPostaux":["97411","97422","97423","97434","97435","97460"],"population":104332,"nom":"Saint-Paul","code":"97415"},"geometry":{"type":"Point","coordinates":[55.35039216666668,-21.063536000000013]}}]}