{"type":"FeatureCollection","features":[{"type":"Feature","properties":{"codesPostaux":["97418","97430"],"population":76090,"nom":"Le Tampon","code":"97422"},"geometry":{"type":"Point","coordinates":[55.5582456418385,-21.218746719492867]}}]}