{"type":"FeatureCollection","features":[{"type":"Feature","properties":{"codesPostaux":["97630"],"nom":"Acoua","code":"97601"},"geometry":{"type":"Point","coordinates":[45.051285749999984,-12.722195000000005]}}]}