{"type":"FeatureCollection","features":[{"type":"Feature","properties":{"codesPostaux":["97620"],"nom":"Bou\u00e9ni","code":"97604"},"geometry":{"type":"Point","coordinates":[45.09492129464284,-12.923012455357139]}}]}